Workbook

Sheet Índice
B2: Información General | C2: Liga
B3: Resumen Ejecutivo | C3: Dashboard_Ex
B5: Funcionalidades | C5: Liga
B6: Funcionalidades Onboarding | C6: BD_Onboarding
B7: Funcionalidades Operaciones | C7: BD_Operaciones
B8: Funcionalidades Post Venta | C8: BD_PostVenta
B10: Service Blueprint | C10: Liga
B11: Onboarding TDC Apolo | C11: Onboarding TDC
B12: Operaciones | C12: Operaciones
B13: Post Venta | C13: Post Venta
B15: Inventario de Datos | C15: Liga
B16: Onboarding (Apolo) | C16: Inventario de Datos Apolo
B17: Operaciones (TDC)
B18: Post-Venta (TDC)

Sheet Dashboard_Ex
B2: FUNCIONALIDADES MVP TDC VISA
B3: Proceso | C3: Funcionalidades Totales | D3: Funcionalidades Habilitadas | E3: Grado de Avance
B4: Onboarding | C4: =Dashboard_Control!D17 -> 73 | D4: 31 | E4: =D4/C4 -> 0.42465753
B5: Operaciones | C5: =Dashboard_Control!D23 -> 66 | D5: 0 | E5: 0
B6: Post Venta | C6: =Dashboard_Control!D29 -> #REF! | D6: 0 | E6: 0
B7: Total | C7: =SUM(C4:C6) -> #REF! | D7: =SUM(D4:D6) -> 31 | E7: =SUM(E4:E6) -> 0.42465753
B10: APIs MVP TDC VISA
B11: Proceso | C11: Funcionalidades | D11: API's Estimadas | E11: Diseño BIAN | G11: Diseño Técnico Level Up | I11: Desarrollo Level Up | K11: Pruebas | M11: Liberación
B12: Onboarding | C12: =Dashboard_Control!D17 -> 73 | D12: =Dashboard_Control!G17 -> 294 | E12: 100 | F12: =E12/D12 -> 0.34013605 | G12: 21 | H12: =G12/D12 -> 0.071428571 | I12: 21 | J12: =I12/D12 -> 0.071428571 | K12: 0 | L12: =K12/D12 -> 0 | M12: 0 | N12: =M12/D12 -> 0
B13: Operaciones | C13: =Dashboard_Control!D23 -> 66 | D13: =Dashboard_Control!G23 -> 3080 | E13: =Dashboard_Control!H23 -> 65 | F13: =E13/D13 -> 0.021103896 | G13: 0 | H13: =G13/D13 -> 0 | I13: 0 | J13: =I13/D13 -> 0 | K13: 0 | L13: =K13/D13 -> 0 | M13: 0 | N13: =M13/D13 -> 0
B14: Post Venta | C14: =Dashboard_Control!D29 -> #REF! | D14: =Dashboard_Control!G29 -> 0 | E14: 0 | F14: =E14/D14 -> #DIV/0! | G14: 0 | H14: =G14/D14 -> #DIV/0! | I14: 0 | J14: =I14/D14 -> #DIV/0! | K14: 0 | L14: =K14/D14 -> #DIV/0! | M14: 0 | N14: =M14/D14 -> #DIV/0!
B15: Otros | C15: - | D15: - | E15: 149 | F15: -% | G15: - | H15: -% | I15: - | J15: -% | K15: - | L15: -% | M15: - | N15: -%
B16: Total | C16: =SUM(C12:C15) -> #REF! | D16: =SUM(D12:D15) -> 3374 | E16: =SUM(E12:E15) -> 314 | F16: =E16/D16 -> 0.093064612 | G16: =SUM(G12:G15) -> 21 | H16: =G16/D16 -> 0.0062240664 | I16: =SUM(I12:I15) -> 21 | J16: =I16/D16 -> 0.0062240664 | K16: =SUM(K12:K15) -> 0 | L16: =K16/D16 -> 0 | M16: =SUM(M12:M15) -> 0 | N16: =M16/D16 -> 0
C18: OB | D18: OPS | E18: P.Venta | F18: Reportes | G18: Carpeta CNBV
B19: FX | C19: 76 | D19: =C13 -> 66 | E19: =C14 -> #REF! | F19: 54 | G19: 24
B20: API's | C20: 273 | D20: =D13 -> 3080 | E20: =D14 -> 0
B21: Service BP (As Is)
B22: Service BP (To Be)
A23: Apificación | B23: Diseño BIAN
B24: Diseño Técnico
B25: Desarrollo
B26: Pruebas
B27: Liberación | C27: 5 DE 273
B28: Datos Aprovisionados | C28: 23 DE 605 | D28: 800 | E28: 350 | F28: 1
B29: Insumos Carpeta de Autorización | C29: 8 | D29: 19
B33: DATOS MVP TDC VISA
B34: Proceso | C34: Datos Totales Generados | D34: Datos Totales Aprovisionados | E34: Grado de Avance
B35: Onboarding | C35: 235 | D35: 5 | E35: =D35/C35 -> 0.021276596
B36: Operaciones | C36: =Dashboard_Control!D53 -> 0 | D36: 0 | E36: 0
B37: Post Venta | C37: =Dashboard_Control!D59 -> 0 | D37: 0 | E37: 0
B38: Total | C38: =SUM(C35:C37) -> 235 | D38: =SUM(D35:D37) -> 5 | E38: =SUM(E35:E37) -> 0.021276596

Sheet BD_Onboarding
D1: Apificación | N1: Canal | V1: Avance de Funcionalidad | AF1: Solo APIS | AK1: TOTAL | AQ1: diseñadas | AS1: Dominio | AT1: Sistema | AW1: totales | AY1: Dominio | AZ1: Sistema
A2: ID | B2: Tipo | C2: DESCRIPCION | D2: Base | E2: Recepción | F2: Negocio | G2: Dominio | H2: Sistema | I2: APIs proceso actual | J2: SPL proceso actual | K2: APIs Estimadas To Be | L2: Estatus de Api | M2: Responsable | N2: Apolo | O2: Sucursal | P2: MAD | Q2: App | R2: CAT | S2: BPI | T2: BO | U2: ATM | V2: Contemplado MVP | W2: Estatus | X2: Comentario | Y2: Fecha Inicio | Z2: Fecha Estimada | AB2: Funcionalidades Totales Habilitadas (SOLO APIS) | AC2: Funcionalidades Totales Habilitadas (diseñadas + SDK+ SAAS) | AD2: Conteo Fx | AF2: totales actuales | AG2: totales esperado | AH2: Completadas actual | AI2: Completas esperado | AK2: totales actuales | AL2: totales esperado | AM2: Completadas actual | AN2: Completas esperado | AP2: Apis diseñadas total | AQ2: Recepción | AR2: Negocio | AS2: Transformación | AT2: Sistema | AV2: Apis diseñadas total | AW2: Recepción | AX2: Negocio | AY2: Transformación | AZ2: Sistema
A3: IC-001 | B3: Onboarding | C3: Capturar la identificación | E3: /experience/sales/partyLifecycleManagement/v1/documentation/capture | F3: N/A | G3: /sales/partyLifecycleManagement/v1/documentation/capture | H3: /system/sales/partyLifecycleManagement/v1/documentation/capture | J3: 3 | K3: =J3*$J$147 -> 10.5 | L3: Backlog | M3: Rafael Elizalde | N3: x | V3: Sí | W3: Por definir | AB3: =IF(AG3=0,0,IF(AF3=AG3,1,0))*AD3 -> 0 | AC3: =IF(AK3=AL3,1,0)*AD3 -> 1 | AD3: =IF(ISNUMBER(MATCH(A3,$A$2:A2,0)),0,1) -> 1 | AF3: =SUMIFS(AH$3:AH$251,$A$3:$A$251,$A3) -> 1 | AG3: =SUMIFS(AI$3:AI$251,$A$3:$A$251,$A3) -> 2 | AH3: =IF(SUM(AW3:AZ3)=0,0,IF(SUM(AQ3:AT3)=SUM(AW3:AZ3),1,0)) -> 1 | AI3: 1 | AK3: =SUMIFS(AM$3:AM$251,$A$3:$A$251,$A3) -> 2 | AL3: =SUMIFS(AN$3:AN$251,$A$3:$A$251,$A3) -> 2 | AM3: =IF(SUM(AQ3:AT3)=SUM(AW3:AZ3),1,0) -> 1 | AN3: 1 | AP3: =SUM(AQ3:AT3) -> 3 | AQ3: =IF(OR(E3="",E3="TBD",E3="N/A",E3="SDK",E3="SAAS"),0,1) -> 1 | AR3: =IF(OR(F3="",F3="TBD",F3="N/A",F3="SDK",F3="SAAS"),0,1) -> 0 | AS3: =IF(OR(G3="",G3="TBD",G3="N/A",G3="SDK",G3="SAAS"),0,1) -> 1 | AT3: =IF(OR(H3="",H3="TBD",H3="N/A",H3="SDK",H3="SAAS"),0,1) -> 1 | AV3: =SUM(AW3:AZ3) -> 3 | AW3: =IF(OR(E3="",E3="N/A",E3="SDK",E3="SAAS"),0,1) -> 1 | AX3: =IF(OR(F3="",F3="N/A",F3="SDK",F3="SAAS"),0,1) -> 0 | AY3: =IF(OR(G3="",G3="N/A",G3="SDK",G3="SAAS"),0,1) -> 1 | AZ3: =IF(OR(H3="",H3="N/A",H3="SDK",H3="SAAS"),0,1) -> 1
A4: IC-001 | B4: Onboarding | C4: Capturar la identificación | D4: SDK | E4: SDK | F4: SDK | G4: SDK | H4: SDK | L4: Backlog | M4: Rafael Elizalde | N4: x | V4: Sí | W4: Por definir | AB4: =IF(AG4=0,0,IF(AF4=AG4,1,0))*AD4 -> 0 | AC4: =IF(AK4=AL4,1,0)*AD4 -> 0 | AD4: =IF(ISNUMBER(MATCH(A4,$A$2:A3,0)),0,1) -> 0 | AF4: =SUMIFS(AH$3:AH$251,$A$3:$A$251,$A4) -> 1 | AG4: =SUMIFS(AI$3:AI$77,$A$3:$A$77,$A4) -> 2 | AH4: =IF(SUM(AW4:AZ4)=0,0,IF(SUM(AQ4:AT4)=SUM(AW4:AZ4),1,0)) -> 0 | AI4: 1 | AK4: =SUMIFS(AM$3:AM$251,$A$3:$A$251,$A4) -> 2 | AL4: =SUMIFS(AN$3:AN$251,$A$3:$A$251,$A4) -> 2 | AM4: =IF(SUM(AQ4:AT4)=SUM(AW4:AZ4),1,0) -> 1 | AN4: 1 | AP4: =SUM(AQ4:AT4) -> 0 | AQ4: =IF(OR(E4="",E4="TBD",E4="N/A",E4="SDK",E4="SAAS"),0,1) -> 0 | AR4: =IF(OR(F4="",F4="TBD",F4="N/A",F4="SDK",F4="SAAS"),0,1) -> 0 | AS4: =IF(OR(G4="",G4="TBD",G4="N/A",G4="SDK",G4="SAAS"),0,1) -> 0 | AT4: =IF(OR(H4="",H4="TBD",H4="N/A",H4="SDK",H4="SAAS"),0,1) -> 0 | AV4: =SUM(AW4:AZ4) -> 0 | AW4: =IF(OR(E4="",E4="N/A",E4="SDK",E4="SAAS"),0,1) -> 0 | AX4: =IF(OR(F4="",F4="N/A",F4="SDK",F4="SAAS"),0,1) -> 0 | AY4: =IF(OR(G4="",G4="N/A",G4="SDK",G4="SAAS"),0,1) -> 0 | AZ4: =IF(OR(H4="",H4="N/A",H4="SDK",H4="SAAS"),0,1) -> 0
A5: IC-002 | B5: Onboarding | C5: Capacidad de Auto-clasificación de la identificación y retroalimentación en tiempo real (INE, Identificación de Extranjeros, Pasaporte) | D5: SDK | E5: SDK | F5: SDK | G5: SDK | H5: SDK | K5: =J5*$J$147 -> 0 | L5: Backlog | M5: Rafael Elizalde | N5: x | V5: Sí | W5: Por definir | AB5: =IF(AG5=0,0,IF(AF5=AG5,1,0))*AD5 -> 0 | AC5: =IF(AK5=AL5,1,0)*AD5 -> 1 | AD5: =IF(ISNUMBER(MATCH(A5,$A$2:A3,0)),0,1) -> 1 | AF5: =SUMIFS(AH$3:AH$251,$A$3:$A$251,$A5) -> 0 | AG5: =SUMIFS(AI$3:AI$77,$A$3:$A$77,$A5) -> 1 | AH5: =IF(SUM(AW5:AZ5)=0,0,IF(SUM(AQ5:AT5)=SUM(AW5:AZ5),1,0)) -> 0 | AI5: 1 | AK5: =SUMIFS(AM$3:AM$251,$A$3:$A$251,$A5) -> 1 | AL5: =SUMIFS(AN$3:AN$251,$A$3:$A$251,$A5) -> 1 | AM5: =IF(SUM(AQ5:AT5)=SUM(AW5:AZ5),1,0) -> 1 | AN5: 1 | AP5: =SUM(AQ5:AT5) -> 0 | AQ5: =IF(OR(E5="",E5="TBD",E5="N/A",E5="SDK",E5="SAAS"),0,1) -> 0 | AR5: =IF(OR(F5="",F5="TBD",F5="N/A",F5="SDK",F5="SAAS"),0,1) -> 0 | AS5: =IF(OR(G5="",G5="TBD",G5="N/A",G5="SDK",G5="SAAS"),0,1) -> 0 | AT5: =IF(OR(H5="",H5="TBD",H5="N/A",H5="SDK",H5="SAAS"),0,1) -> 0 | AV5: =SUM(AW5:AZ5) -> 0 | AW5: =IF(OR(E5="",E5="N/A",E5="SDK",E5="SAAS"),0,1) -> 0 | AX5: =IF(OR(F5="",F5="N/A",F5="SDK",F5="SAAS"),0,1) -> 0 | AY5: =IF(OR(G5="",G5="N/A",G5="SDK",G5="SAAS"),0,1) -> 0 | AZ5: =IF(OR(H5="",H5="N/A",H5="SDK",H5="SAAS"),0,1) -> 0
A6: IC-003 | B6: Onboarding | C6: Validar y contrastar el rostro del documento utilizado como documento de identificación en el proceso | E6: /experience/crossChannel/sessionDialogue/v1/customerContactSelfieProcedure/initiate | F6: N/A | G6: /crossChannel/sessionDialogue/v1/customerContactSelfieProcedure/initiate | H6: /system/crossChannel/sessionDialogue/v1/customerContactSessionProcedure/initiate | K6: =J6*$J$147 -> 0 | L6: Backlog | M6: Rafael Elizalde | N6: x | V6: Sí | W6: Por definir | AB6: =IF(AG6=0,0,IF(AF6=AG6,1,0))*AD6 -> 1 | AC6: =IF(AK6=AL6,1,0)*AD6 -> 1 | AD6: =IF(ISNUMBER(MATCH(A6,$A$2:A5,0)),0,1) -> 1 | AF6: =SUMIFS(AH$3:AH$251,$A$3:$A$251,$A6) -> 1 | AG6: =SUMIFS(AI$3:AI$77,$A$3:$A$77,$A6) -> 1 | AH6: =IF(SUM(AW6:AZ6)=0,0,IF(SUM(AQ6:AT6)=SUM(AW6:AZ6),1,0)) -> 1 | AI6: 1 | AK6: =SUMIFS(AM$3:AM$251,$A$3:$A$251,$A6) -> 1 | AL6: =SUMIFS(AN$3:AN$251,$A$3:$A$251,$A6) -> 1 | AM6: =IF(SUM(AQ6:AT6)=SUM(AW6:AZ6),1,0) -> 1 | AN6: 1 | AP6: =SUM(AQ6:AT6) -> 3 | AQ6: =IF(OR(E6="",E6="TBD",E6="N/A",E6="SDK",E6="SAAS"),0,1) -> 1 | AR6: =IF(OR(F6="",F6="TBD",F6="N/A",F6="SDK",F6="SAAS"),0,1) -> 0 | AS6: =IF(OR(G6="",G6="TBD",G6="N/A",G6="SDK",G6="SAAS"),0,1) -> 1 | AT6: =IF(OR(H6="",H6="TBD",H6="N/A",H6="SDK",H6="SAAS"),0,1) -> 1 | AV6: =SUM(AW6:AZ6) -> 3 | AW6: =IF(OR(E6="",E6="N/A",E6="SDK",E6="SAAS"),0,1) -> 1 | AX6: =IF(OR(F6="",F6="N/A",F6="SDK",F6="SAAS"),0,1) -> 0 | AY6: =IF(OR(G6="",G6="N/A",G6="SDK",G6="SAAS"),0,1) -> 1 | AZ6: =IF(OR(H6="",H6="N/A",H6="SDK",H6="SAAS"),0,1) -> 1
A7: IC-003 | B7: Onboarding | C7: Validar y contrastar el rostro del documento utilizado como documento de identificación en el proceso | D7: SDK | E7: SDK | F7: SDK | G7: SDK | H7: SDK
A8: IC-004 | B8: Onboarding | C8: Captura automática el rostro del solicitante / cliente de forma segura e inteligente | D8: SDK | E8: SDK | F8: SDK | G8: SDK | H8: SDK | K8: =J8*$J$147 -> 0 | L8: Backlog | M8: Rafael Elizalde | N8: x | V8: Sí | W8: Por definir | AB8: =IF(AG8=0,0,IF(AF8=AG8,1,0))*AD8 -> 0 | AC8: =IF(AK8=AL8,1,0)*AD8 -> 1 | AD8: =IF(ISNUMBER(MATCH(A8,$A$2:A6,0)),0,1) -> 1 | AF8: =SUMIFS(AH$3:AH$251,$A$3:$A$251,$A8) -> 0 | AG8: =SUMIFS(AI$3:AI$77,$A$3:$A$77,$A8) -> 1 | AH8: =IF(SUM(AW8:AZ8)=0,0,IF(SUM(AQ8:AT8)=SUM(AW8:AZ8),1,0)) -> 0 | AI8: 1 | AK8: =SUMIFS(AM$3:AM$251,$A$3:$A$251,$A8) -> 1 | AL8: =SUMIFS(AN$3:AN$251,$A$3:$A$251,$A8) -> 1 | AM8: =IF(SUM(AQ8:AT8)=SUM(AW8:AZ8),1,0) -> 1 | AN8: 1 | AP8: =SUM(AQ8:AT8) -> 0 | AQ8: =IF(OR(E8="",E8="TBD",E8="N/A",E8="SDK",E8="SAAS"),0,1) -> 0 | AR8: =IF(OR(F8="",F8="TBD",F8="N/A",F8="SDK",F8="SAAS"),0,1) -> 0 | AS8: =IF(OR(G8="",G8="TBD",G8="N/A",G8="SDK",G8="SAAS"),0,1) -> 0 | AT8: =IF(OR(H8="",H8="TBD",H8="N/A",H8="SDK",H8="SAAS"),0,1) -> 0 | AV8: =SUM(AW8:AZ8) -> 0 | AW8: =IF(OR(E8="",E8="N/A",E8="SDK",E8="SAAS"),0,1) -> 0 | AX8: =IF(OR(F8="",F8="N/A",F8="SDK",F8="SAAS"),0,1) -> 0 | AY8: =IF(OR(G8="",G8="N/A",G8="SDK",G8="SAAS"),0,1) -> 0 | AZ8: =IF(OR(H8="",H8="N/A",H8="SDK",H8="SAAS"),0,1) -> 0
A9: IC-005 | B9: Onboarding | C9: Probar la captura de dirección (OCR comprobante domicilio) | D9: SDK | E9: SDK | F9: SDK | G9: SDK | H9: SDK | K9: =J9*$J$147 -> 0 | L9: Backlog | M9: Rafael Elizalde | N9: x | V9: Sí | W9: Por definir | AB9: =IF(AG9=0,0,IF(AF9=AG9,1,0))*AD9 -> 0 | AC9: =IF(AK9=AL9,1,0)*AD9 -> 1 | AD9: =IF(ISNUMBER(MATCH(A9,$A$2:A8,0)),0,1) -> 1 | AF9: =SUMIFS(AH$3:AH$251,$A$3:$A$251,$A9) -> 0 | AG9: =SUMIFS(AI$3:AI$77,$A$3:$A$77,$A9) -> 1 | AH9: =IF(SUM(AW9:AZ9)=0,0,IF(SUM(AQ9:AT9)=SUM(AW9:AZ9),1,0)) -> 0 | AI9: 1 | AK9: =SUMIFS(AM$3:AM$251,$A$3:$A$251,$A9) -> 1 | AL9: =SUMIFS(AN$3:AN$251,$A$3:$A$251,$A9) -> 1 | AM9: =IF(SUM(AQ9:AT9)=SUM(AW9:AZ9),1,0) -> 1 | AN9: 1 | AP9: =SUM(AQ9:AT9) -> 0 | AQ9: =IF(OR(E9="",E9="TBD",E9="N/A",E9="SDK",E9="SAAS"),0,1) -> 0 | AR9: =IF(OR(F9="",F9="TBD",F9="N/A",F9="SDK",F9="SAAS"),0,1) -> 0 | AS9: =IF(OR(G9="",G9="TBD",G9="N/A",G9="SDK",G9="SAAS"),0,1) -> 0 | AT9: =IF(OR(H9="",H9="TBD",H9="N/A",H9="SDK",H9="SAAS"),0,1) -> 0 | AV9: =SUM(AW9:AZ9) -> 0 | AW9: =IF(OR(E9="",E9="N/A",E9="SDK",E9="SAAS"),0,1) -> 0 | AX9: =IF(OR(F9="",F9="N/A",F9="SDK",F9="SAAS"),0,1) -> 0 | AY9: =IF(OR(G9="",G9="N/A",G9="SDK",G9="SAAS"),0,1) -> 0 | AZ9: =IF(OR(H9="",H9="N/A",H9="SDK",H9="SAAS"),0,1) -> 0
A10: IC-006 | B10: Onboarding | C10: Validar el Celular a través de un OTP enviado por SMS | E10: /experience/salesAndService/v1/onBoardingPhoneParty/evaluate | F10: /channels/v1/onBoardingPhoneParty/evaluate | G10: /crossChannel/sessionDialogue/v1/customerContactSessionProcedure/capture /operationalServices/issuedDeviceAdministration/v1/tokenAssignment/initiate | H10: /system/crossChannel/sessionDialogue/v1/customerContactSessionProcedure/capture /system/operationalServices/issuedDeviceAdministration/v1/tokenAssignment/initiate | J10: 4 | K10: =J10*$J$147 -> 14 | L10: Backlog | M10: Rafael Elizalde | N10: x | V10: Sí | W10: Por definir | AB10: =IF(AG10=0,0,IF(AF10=AG10,1,0))*AD10 -> 1 | AC10: =IF(AK10=AL10,1,0)*AD10 -> 1 | AD10: =IF(ISNUMBER(MATCH(A10,$A$2:A9,0)),0,1) -> 1 | AF10: =SUMIFS(AH$3:AH$251,$A$3:$A$251,$A10) -> 2 | AG10: =SUMIFS(AI$3:AI$77,$A$3:$A$77,$A10) -> 2 | AH10: =IF(SUM(AW10:AZ10)=0,0,IF(SUM(AQ10:AT10)=SUM(AW10:AZ10),1,0)) -> 1 | AI10: 1 | AK10: =SUMIFS(AM$3:AM$251,$A$3:$A$251,$A10) -> 2 | AL10: =SUMIFS(AN$3:AN$251,$A$3:$A$251,$A10) -> 2 | AM10: =IF(SUM(AQ10:AT10)=SUM(AW10:AZ10),1,0) -> 1 | AN10: 1 | AP10: =SUM(AQ10:AT10) -> 4 | AQ10: =IF(OR(E10="",E10="TBD",E10="N/A",E10="SDK",E10="SAAS"),0,1) -> 1 | AR10: =IF(OR(F10="",F10="TBD",F10="N/A",F10="SDK",F10="SAAS"),0,1) -> 1 | AS10: =IF(OR(G10="",G10="TBD",G10="N/A",G10="SDK",G10="SAAS"),0,1) -> 1 | AT10: =IF(OR(H10="",H10="TBD",H10="N/A",H10="SDK",H10="SAAS"),0,1) -> 1 | AV10: =SUM(AW10:AZ10) -> 4 | AW10: =IF(OR(E10="",E10="N/A",E10="SDK",E10="SAAS"),0,1) -> 1 | AX10: =IF(OR(F10="",F10="N/A",F10="SDK",F10="SAAS"),0,1) -> 1 | AY10: =IF(OR(G10="",G10="N/A",G10="SDK",G10="SAAS"),0,1) -> 1 | AZ10: =IF(OR(H10="",H10="N/A",H10="SDK",H10="SAAS"),0,1) -> 1
A11: IC-006 | B11: Onboarding | C11: Validar el Celular a través de un OTP enviado por SMS | E11: /experience/operationalservices/issueddeviceadministration/v1/tokenAssignment/evaluate | F11: /customers/v1/ocrDocument/retrieve | G11: /operationalServices/issuedDeviceAdministration/v1/tokenAssignment/evaluate | H11: /system/operationalServices/issuedDeviceAdministration | K11: =J11*$J$147 -> 0 | L11: Backlog | M11: Rafael Elizalde | N11: x | V11: Sí | W11: Por definir | AB11: =IF(AG11=0,0,IF(AF11=AG11,1,0))*AD11 -> 0 | AC11: =IF(AK11=AL11,1,0)*AD11 -> 0 | AD11: =IF(ISNUMBER(MATCH(A11,$A$2:A10,0)),0,1) -> 0 | AF11: =SUMIFS(AH$3:AH$251,$A$3:$A$251,$A11) -> 2 | AG11: =SUMIFS(AI$3:AI$77,$A$3:$A$77,$A11) -> 2 | AH11: =IF(SUM(AW11:AZ11)=0,0,IF(SUM(AQ11:AT11)=SUM(AW11:AZ11),1,0)) -> 1 | AI11: 1 | AK11: =SUMIFS(AM$3:AM$251,$A$3:$A$251,$A11) -> 2 | AL11: =SUMIFS(AN$3:AN$251,$A$3:$A$251,$A11) -> 2 | AM11: =IF(SUM(AQ11:AT11)=SUM(AW11:AZ11),1,0) -> 1 | AN11: 1 | AP11: =SUM(AQ11:AT11) -> 4 | AQ11: =IF(OR(E11="",E11="TBD",E11="N/A",E11="SDK",E11="SAAS"),0,1) -> 1 | AR11: =IF(OR(F11="",F11="TBD",F11="N/A",F11="SDK",F11="SAAS"),0,1) -> 1 | AS11: =IF(OR(G11="",G11="TBD",G11="N/A",G11="SDK",G11="SAAS"),0,1) -> 1 | AT11: =IF(OR(H11="",H11="TBD",H11="N/A",H11="SDK",H11="SAAS"),0,1) -> 1 | AV11: =SUM(AW11:AZ11) -> 4 | AW11: =IF(OR(E11="",E11="N/A",E11="SDK",E11="SAAS"),0,1) -> 1 | AX11: =IF(OR(F11="",F11="N/A",F11="SDK",F11="SAAS"),0,1) -> 1 | AY11: =IF(OR(G11="",G11="N/A",G11="SDK",G11="SAAS"),0,1) -> 1 | AZ11: =IF(OR(H11="",H11="N/A",H11="SDK",H11="SAAS"),0,1) -> 1
A12: IC-007 | B12: Onboarding | C12: Validar el Email a través de un OTP enviado por correo electrónico | E12: /experience/channels/v1/onBoardingEmailParty/evaluate | F12: TBD | G12: TBD | H12: TBD | J12: 2 | K12: =J12*$J$147 -> 7 | L12: Backlog | M12: Rafael Elizalde | N12: x | V12: Sí | W12: Por definir | AB12: =IF(AG12=0,0,IF(AF12=AG12,1,0))*AD12 -> 0 | AC12: =IF(AK12=AL12,1,0)*AD12 -> 0 | AD12: =IF(ISNUMBER(MATCH(A12,$A$2:A11,0)),0,1) -> 1 | AF12: =SUMIFS(AH$3:AH$251,$A$3:$A$251,$A12) -> 0 | AG12: =SUMIFS(AI$3:AI$77,$A$3:$A$77,$A12) -> 1 | AH12: =IF(SUM(AW12:AZ12)=0,0,IF(SUM(AQ12:AT12)=SUM(AW12:AZ12),1,0)) -> 0 | AI12: 1 | AK12: =SUMIFS(AM$3:AM$251,$A$3:$A$251,$A12) -> 0 | AL12: =SUMIFS(AN$3:AN$251,$A$3:$A$251,$A12) -> 1 | AM12: =IF(SUM(AQ12:AT12)=SUM(AW12:AZ12),1,0) -> 0 | AN12: 1 | AP12: =SUM(AQ12:AT12) -> 1 | AQ12: =IF(OR(E12="",E12="TBD",E12="N/A",E12="SDK",E12="SAAS"),0,1) -> 1 | AR12: =IF(OR(F12="",F12="TBD",F12="N/A",F12="SDK",F12="SAAS"),0,1) -> 0 | AS12: =IF(OR(G12="",G12="TBD",G12="N/A",G12="SDK",G12="SAAS"),0,1) -> 0 | AT12: =IF(OR(H12="",H12="TBD",H12="N/A",H12="SDK",H12="SAAS"),0,1) -> 0 | AV12: =SUM(AW12:AZ12) -> 4 | AW12: =IF(OR(E12="",E12="N/A",E12="SDK",E12="SAAS"),0,1) -> 1 | AX12: =IF(OR(F12="",F12="N/A",F12="SDK",F12="SAAS"),0,1) -> 1 | AY12: =IF(OR(G12="",G12="N/A",G12="SDK",G12="SAAS"),0,1) -> 1 | AZ12: =IF(OR(H12="",H12="N/A",H12="SDK",H12="SAAS"),0,1) -> 1
A13: IC-008 | B13: Onboarding | C13: Extraer la información dentro del documento de identificación (OCR) | E13: /experience/customers/v1/ocrDocument/retrieve | F13: /customers/v1/ocrDocument/retrieve | G13: /sales/partyLifecycleManagement/v1/documentation/execute | H13: /system/sales/partyLifecycleManagement/v1/documentation/execute | J13: 1 | K13: =J13*$J$147 -> 3.5 | L13: Backlog | M13: Rafael Elizalde | N13: x | V13: Sí | W13: Por definir | AB13: =IF(AG13=0,0,IF(AF13=AG13,1,0))*AD13 -> 0 | AC13: =IF(AK13=AL13,1,0)*AD13 -> 1 | AD13: =IF(ISNUMBER(MATCH(A13,$A$2:A12,0)),0,1) -> 1 | AF13: =SUMIFS(AH$3:AH$251,$A$3:$A$251,$A13) -> 1 | AG13: =SUMIFS(AI$3:AI$77,$A$3:$A$77,$A13) -> 2 | AH13: =IF(SUM(AW13:AZ13)=0,0,IF(SUM(AQ13:AT13)=SUM(AW13:AZ13),1,0)) -> 1 | AI13: 1 | AK13: =SUMIFS(AM$3:AM$251,$A$3:$A$251,$A13) -> 2 | AL13: =SUMIFS(AN$3:AN$251,$A$3:$A$251,$A13) -> 2 | AM13: =IF(SUM(AQ13:AT13)=SUM(AW13:AZ13),1,0) -> 1 | AN13: 1 | AP13: =SUM(AQ13:AT13) -> 4 | AQ13: =IF(OR(E13="",E13="TBD",E13="N/A",E13="SDK",E13="SAAS"),0,1) -> 1 | AR13: =IF(OR(F13="",F13="TBD",F13="N/A",F13="SDK",F13="SAAS"),0,1) -> 1 | AS13: =IF(OR(G13="",G13="TBD",G13="N/A",G13="SDK",G13="SAAS"),0,1) -> 1 | AT13: =IF(OR(H13="",H13="TBD",H13="N/A",H13="SDK",H13="SAAS"),0,1) -> 1 | AV13: =SUM(AW13:AZ13) -> 4 | AW13: =IF(OR(E13="",E13="N/A",E13="SDK",E13="SAAS"),0,1) -> 1 | AX13: =IF(OR(F13="",F13="N/A",F13="SDK",F13="SAAS"),0,1) -> 1 | AY13: =IF(OR(G13="",G13="N/A",G13="SDK",G13="SAAS"),0,1) -> 1 | AZ13: =IF(OR(H13="",H13="N/A",H13="SDK",H13="SAAS"),0,1) -> 1
A14: IC-008 | B14: Onboarding | C14: Extraer la información dentro del documento de identificación (OCR) | D14: SDK | E14: SDK | F14: N/A | G14: N/A | H14: N/A | K14: =J14*$J$147 -> 0 | L14: Backlog | M14: Rafael Elizalde | N14: x | V14: Sí | W14: Por definir | AB14: =IF(AG14=0,0,IF(AF14=AG14,1,0))*AD14 -> 0 | AC14: =IF(AK14=AL14,1,0)*AD14 -> 0 | AD14: =IF(ISNUMBER(MATCH(A14,$A$2:A13,0)),0,1) -> 0 | AF14: =SUMIFS(AH$3:AH$251,$A$3:$A$251,$A14) -> 1 | AG14: =SUMIFS(AI$3:AI$77,$A$3:$A$77,$A14) -> 2 | AH14: =IF(SUM(AW14:AZ14)=0,0,IF(SUM(AQ14:AT14)=SUM(AW14:AZ14),1,0)) -> 0 | AI14: 1 | AK14: =SUMIFS(AM$3:AM$251,$A$3:$A$251,$A14) -> 2 | AL14: =SUMIFS(AN$3:AN$251,$A$3:$A$251,$A14) -> 2 | AM14: =IF(SUM(AQ14:AT14)=SUM(AW14:AZ14),1,0) -> 1 | AN14: 1 | AP14: =SUM(AQ14:AT14) -> 0 | AQ14: =IF(OR(E14="",E14="TBD",E14="N/A",E14="SDK",E14="SAAS"),0,1) -> 0 | AR14: =IF(OR(F14="",F14="TBD",F14="N/A",F14="SDK",F14="SAAS"),0,1) -> 0 | AS14: =IF(OR(G14="",G14="TBD",G14="N/A",G14="SDK",G14="SAAS"),0,1) -> 0 | AT14: =IF(OR(H14="",H14="TBD",H14="N/A",H14="SDK",H14="SAAS"),0,1) -> 0 | AV14: =SUM(AW14:AZ14) -> 0 | AW14: =IF(OR(E14="",E14="N/A",E14="SDK",E14="SAAS"),0,1) -> 0 | AX14: =IF(OR(F14="",F14="N/A",F14="SDK",F14="SAAS"),0,1) -> 0 | AY14: =IF(OR(G14="",G14="N/A",G14="SDK",G14="SAAS"),0,1) -> 0 | AZ14: =IF(OR(H14="",H14="N/A",H14="SDK",H14="SAAS"),0,1) -> 0
A15: IC-009 | B15: Onboarding | C15: Validar al prospecto / cliente contra la lista nominal del INE | E15: TBD | F15: TBD | G15: /sales/partyLifecycleManagement/v1/ine/evaluate | H15: /system/sales/partyLifecycleManagement/v1/ine/evaluate | K15: =J15*$J$147 -> 0 | L15: Backlog | M15: Rafael Elizalde | N15: x | V15: Sí | W15: Por definir | AB15: =IF(AG15=0,0,IF(AF15=AG15,1,0))*AD15 -> 0 | AC15: =IF(AK15=AL15,1,0)*AD15 -> 0 | AD15: =IF(ISNUMBER(MATCH(A15,$A$2:A13,0)),0,1) -> 1 | AF15: =SUMIFS(AH$3:AH$251,$A$3:$A$251,$A15) -> 0 | AG15: =SUMIFS(AI$3:AI$77,$A$3:$A$77,$A15) -> 2 | AH15: =IF(SUM(AW15:AZ15)=0,0,IF(SUM(AQ15:AT15)=SUM(AW15:AZ15),1,0)) -> 0 | AI15: 1 | AK15: =SUMIFS(AM$3:AM$251,$A$3:$A$251,$A15) -> 0 | AL15: =SUMIFS(AN$3:AN$251,$A$3:$A$251,$A15) -> 2 | AM15: =IF(SUM(AQ15:AT15)=SUM(AW15:AZ15),1,0) -> 0 | AN15: 1 | AP15: =SUM(AQ15:AT15) -> 2 | AQ15: =IF(OR(E15="",E15="TBD",E15="N/A",E15="SDK",E15="SAAS"),0,1) -> 0 | AR15: =IF(OR(F15="",F15="TBD",F15="N/A",F15="SDK",F15="SAAS"),0,1) -> 0 | AS15: =IF(OR(G15="",G15="TBD",G15="N/A",G15="SDK",G15="SAAS"),0,1) -> 1 | AT15: =IF(OR(H15="",H15="TBD",H15="N/A",H15="SDK",H15="SAAS"),0,1) -> 1 | AV15: =SUM(AW15:AZ15) -> 4 | AW15: =IF(OR(E15="",E15="N/A",E15="SDK",E15="SAAS"),0,1) -> 1 | AX15: =IF(OR(F15="",F15="N/A",F15="SDK",F15="SAAS"),0,1) -> 1 | AY15: =IF(OR(G15="",G15="N/A",G15="SDK",G15="SAAS"),0,1) -> 1 | AZ15: =IF(OR(H15="",H15="N/A",H15="SDK",H15="SAAS"),0,1) -> 1
A16: IC-009 | B16: Onboarding | C16: Validar al prospecto / cliente contra la lista nominal del INE | E16: TBD | F16: TBD | G16: /sales/partyLifecycleManagement/v1/ine/retrieve | H16: /system/sales/partyLifecycleManagement/v1/ine/retrieve | K16: =J16*$J$147 -> 0 | L16: Backlog | M16: Rafael Elizalde | N16: x | V16: Sí | W16: Por definir | AB16: =IF(AG16=0,0,IF(AF16=AG16,1,0))*AD16 -> 0 | AC16: =IF(AK16=AL16,1,0)*AD16 -> 0 | AD16: =IF(ISNUMBER(MATCH(A16,$A$2:A14,0)),0,1) -> 1 | AF16: =SUMIFS(AH$3:AH$251,$A$3:$A$251,$A16) -> 0 | AG16: =SUMIFS(AI$3:AI$77,$A$3:$A$77,$A16) -> 2 | AH16: =IF(SUM(AW16:AZ16)=0,0,IF(SUM(AQ16:AT16)=SUM(AW16:AZ16),1,0)) -> 0 | AI16: 1 | AK16: =SUMIFS(AM$3:AM$251,$A$3:$A$251,$A16) -> 0 | AL16: =SUMIFS(AN$3:AN$251,$A$3:$A$251,$A16) -> 2 | AM16: =IF(SUM(AQ16:AT16)=SUM(AW16:AZ16),1,0) -> 0 | AN16: 1 | AP16: =SUM(AQ16:AT16) -> 2 | AQ16: =IF(OR(E16="",E16="TBD",E16="N/A",E16="SDK",E16="SAAS"),0,1) -> 0 | AR16: =IF(OR(F16="",F16="TBD",F16="N/A",F16="SDK",F16="SAAS"),0,1) -> 0 | AS16: =IF(OR(G16="",G16="TBD",G16="N/A",G16="SDK",G16="SAAS"),0,1) -> 1 | AT16: =IF(OR(H16="",H16="TBD",H16="N/A",H16="SDK",H16="SAAS"),0,1) -> 1 | AV16: =SUM(AW16:AZ16) -> 4 | AW16: =IF(OR(E16="",E16="N/A",E16="SDK",E16="SAAS"),0,1) -> 1 | AX16: =IF(OR(F16="",F16="N/A",F16="SDK",F16="SAAS"),0,1) -> 1 | AY16: =IF(OR(G16="",G16="N/A",G16="SDK",G16="SAAS"),0,1) -> 1 | AZ16: =IF(OR(H16="",H16="N/A",H16="SDK",H16="SAAS"),0,1) -> 1
A17: IC-010 | B17: Onboarding | C17: Validar la coincidencia facial contra el INE | E17: /experience/CrossChannel/SessionDialogue/v1/customerContactSelfieProcedure/initiate | K17: =J17*$J$147 -> 0 | L17: Backlog | M17: Rafael Elizalde | N17: x | V17: Sí | W17: Por definir | AB17: =IF(AG17=0,0,IF(AF17=AG17,1,0))*AD17 -> 1 | AC17: =IF(AK17=AL17,1,0)*AD17 -> 1 | AD17: =IF(ISNUMBER(MATCH(A17,$A$2:A15,0)),0,1) -> 1 | AF17: =SUMIFS(AH$3:AH$251,$A$3:$A$251,$A17) -> 1 | AG17: =SUMIFS(AI$3:AI$77,$A$3:$A$77,$A17) -> 1 | AH17: =IF(SUM(AW17:AZ17)=0,0,IF(SUM(AQ17:AT17)=SUM(AW17:AZ17),1,0)) -> 1 | AI17: 1 | AK17: =SUMIFS(AM$3:AM$251,$A$3:$A$251,$A17) -> 1 | AL17: =SUMIFS(AN$3:AN$251,$A$3:$A$251,$A17) -> 1 | AM17: =IF(SUM(AQ17:AT17)=SUM(AW17:AZ17),1,0) -> 1 | AN17: 1 | AP17: =SUM(AQ17:AT17) -> 1 | AQ17: =IF(OR(E17="",E17="TBD",E17="N/A",E17="SDK",E17="SAAS"),0,1) -> 1 | AR17: =IF(OR(F17="",F17="TBD",F17="N/A",F17="SDK",F17="SAAS"),0,1) -> 0 | AS17: =IF(OR(G17="",G17="TBD",G17="N/A",G17="SDK",G17="SAAS"),0,1) -> 0 | AT17: =IF(OR(H17="",H17="TBD",H17="N/A",H17="SDK",H17="SAAS"),0,1) -> 0 | AV17: =SUM(AW17:AZ17) -> 1 | AW17: =IF(OR(E17="",E17="N/A",E17="SDK",E17="SAAS"),0,1) -> 1 | AX17: =IF(OR(F17="",F17="N/A",F17="SDK",F17="SAAS"),0,1) -> 0 | AY17: =IF(OR(G17="",G17="N/A",G17="SDK",G17="SAAS"),0,1) -> 0 | AZ17: =IF(OR(H17="",H17="N/A",H17="SDK",H17="SAAS"),0,1) -> 0
A18: IC-011 | B18: Onboarding | C18: Calcular el RFC del cliente / prospecto | E18: N/A | F18: N/A | G18: /sales/partyLifecycleManagement/v1/rfc/evaluate | H18: /system/sales/partyLifecycleManagement/v1/rfc/evaluate | J18: 1 | K18: =J18*$J$147 -> 3.5 | L18: Backlog | M18: Rafael Elizalde | N18: x | V18: Sí | W18: Por definir | AB18: =IF(AG18=0,0,IF(AF18=AG18,1,0))*AD18 -> 1 | AC18: =IF(AK18=AL18,1,0)*AD18 -> 1 | AD18: =IF(ISNUMBER(MATCH(A18,$A$2:A17,0)),0,1) -> 1 | AF18: =SUMIFS(AH$3:AH$251,$A$3:$A$251,$A18) -> 1 | AG18: =SUMIFS(AI$3:AI$77,$A$3:$A$77,$A18) -> 1 | AH18: =IF(SUM(AW18:AZ18)=0,0,IF(SUM(AQ18:AT18)=SUM(AW18:AZ18),1,0)) -> 1 | AI18: 1 | AK18: =SUMIFS(AM$3:AM$251,$A$3:$A$251,$A18) -> 1 | AL18: =SUMIFS(AN$3:AN$251,$A$3:$A$251,$A18) -> 1 | AM18: =IF(SUM(AQ18:AT18)=SUM(AW18:AZ18),1,0) -> 1 | AN18: 1 | AP18: =SUM(AQ18:AT18) -> 2 | AQ18: =IF(OR(E18="",E18="TBD",E18="N/A",E18="SDK",E18="SAAS"),0,1) -> 0 | AR18: =IF(OR(F18="",F18="TBD",F18="N/A",F18="SDK",F18="SAAS"),0,1) -> 0 | AS18: =IF(OR(G18="",G18="TBD",G18="N/A",G18="SDK",G18="SAAS"),0,1) -> 1 | AT18: =IF(OR(H18="",H18="TBD",H18="N/A",H18="SDK",H18="SAAS"),0,1) -> 1 | AV18: =SUM(AW18:AZ18) -> 2 | AW18: =IF(OR(E18="",E18="N/A",E18="SDK",E18="SAAS"),0,1) -> 0 | AX18: =IF(OR(F18="",F18="N/A",F18="SDK",F18="SAAS"),0,1) -> 0 | AY18: =IF(OR(G18="",G18="N/A",G18="SDK",G18="SAAS"),0,1) -> 1 | AZ18: =IF(OR(H18="",H18="N/A",H18="SDK",H18="SAAS"),0,1) -> 1
A19: IC-012 | B19: Onboarding | C19: Validar el CURP ante RENAPO | E19: N/A | F19: N/A | G19: /sales/partyLifecycleManagement/v1/renapo/{curp}/retrieve | H19: /system/sales/partyLifecycleManagement/v1/renapo/{curp}/retrieve | J19: 1 | K19: =J19*$J$147 -> 3.5 | L19: Backlog | M19: Rafael Elizalde | N19: x | V19: Sí | W19: Por definir | AB19: =IF(AG19=0,0,IF(AF19=AG19,1,0))*AD19 -> 1 | AC19: =IF(AK19=AL19,1,0)*AD19 -> 1 | AD19: =IF(ISNUMBER(MATCH(A19,$A$2:A18,0)),0,1) -> 1 | AF19: =SUMIFS(AH$3:AH$251,$A$3:$A$251,$A19) -> 1 | AG19: =SUMIFS(AI$3:AI$77,$A$3:$A$77,$A19) -> 1 | AH19: =IF(SUM(AW19:AZ19)=0,0,IF(SUM(AQ19:AT19)=SUM(AW19:AZ19),1,0)) -> 1 | AI19: 1 | AK19: =SUMIFS(AM$3:AM$251,$A$3:$A$251,$A19) -> 1 | AL19: =SUMIFS(AN$3:AN$251,$A$3:$A$251,$A19) -> 1 | AM19: =IF(SUM(AQ19:AT19)=SUM(AW19:AZ19),1,0) -> 1 | AN19: 1 | AP19: =SUM(AQ19:AT19) -> 2 | AQ19: =IF(OR(E19="",E19="TBD",E19="N/A",E19="SDK",E19="SAAS"),0,1) -> 0 | AR19: =IF(OR(F19="",F19="TBD",F19="N/A",F19="SDK",F19="SAAS"),0,1) -> 0 | AS19: =IF(OR(G19="",G19="TBD",G19="N/A",G19="SDK",G19="SAAS"),0,1) -> 1 | AT19: =IF(OR(H19="",H19="TBD",H19="N/A",H19="SDK",H19="SAAS"),0,1) -> 1 | AV19: =SUM(AW19:AZ19) -> 2 | AW19: =IF(OR(E19="",E19="N/A",E19="SDK",E19="SAAS"),0,1) -> 0 | AX19: =IF(OR(F19="",F19="N/A",F19="SDK",F19="SAAS"),0,1) -> 0 | AY19: =IF(OR(G19="",G19="N/A",G19="SDK",G19="SAAS"),0,1) -> 1 | AZ19: =IF(OR(H19="",H19="N/A",H19="SDK",H19="SAAS"),0,1) -> 1
A20: IC-013 | B20: Onboarding | C20: Extraer la información dentro del comprobante de domicilio (OCR) | E20: /experience/customers/v1/ocrDocument/retrieve | F20: /customers/v1/ocrDocument/retrieve | G20: /sales/partyLifecycleManagement/v1/documentation/execute | H20: /system/sales/partyLifecycleManagement/v1/documentation/execute | K20: =J20*$J$147 -> 0 | L20: Backlog | M20: Rafael Elizalde | N20: x | V20: Sí | W20: Por definir | AB20: =IF(AG20=0,0,IF(AF20=AG20,1,0))*AD20 -> 1 | AC20: =IF(AK20=AL20,1,0)*AD20 -> 1 | AD20: =IF(ISNUMBER(MATCH(A20,$A$2:A19,0)),0,1) -> 1 | AF20: =SUMIFS(AH$3:AH$251,$A$3:$A$251,$A20) -> 1 | AG20: =SUMIFS(AI$3:AI$77,$A$3:$A$77,$A20) -> 1 | AH20: =IF(SUM(AW20:AZ20)=0,0,IF(SUM(AQ20:AT20)=SUM(AW20:AZ20),1,0)) -> 1 | AI20: 1 | AK20: =SUMIFS(AM$3:AM$251,$A$3:$A$251,$A20) -> 1 | AL20: =SUMIFS(AN$3:AN$251,$A$3:$A$251,$A20) -> 1 | AM20: =IF(SUM(AQ20:AT20)=SUM(AW20:AZ20),1,0) -> 1 | AN20: 1 | AP20: =SUM(AQ20:AT20) -> 4 | AQ20: =IF(OR(E20="",E20="TBD",E20="N/A",E20="SDK",E20="SAAS"),0,1) -> 1 | AR20: =IF(OR(F20="",F20="TBD",F20="N/A",F20="SDK",F20="SAAS"),0,1) -> 1 | AS20: =IF(OR(G20="",G20="TBD",G20="N/A",G20="SDK",G20="SAAS"),0,1) -> 1 | AT20: =IF(OR(H20="",H20="TBD",H20="N/A",H20="SDK",H20="SAAS"),0,1) -> 1 | AV20: =SUM(AW20:AZ20) -> 4 | AW20: =IF(OR(E20="",E20="N/A",E20="SDK",E20="SAAS"),0,1) -> 1 | AX20: =IF(OR(F20="",F20="N/A",F20="SDK",F20="SAAS"),0,1) -> 1 | AY20: =IF(OR(G20="",G20="N/A",G20="SDK",G20="SAAS"),0,1) -> 1 | AZ20: =IF(OR(H20="",H20="N/A",H20="SDK",H20="SAAS"),0,1) -> 1
A21: IC-016 | B21: Onboarding | C21: Validar la coincidencia facial contra la identificación (1:1) | D21: SDK | E21: SDK | F21: SDK | G21: SDK | H21: SDK | K21: =J21*$J$147 -> 0 | L21: Backlog | M21: Rafael Elizalde | N21: x | V21: Sí | W21: Por definir | AB21: =IF(AG21=0,0,IF(AF21=AG21,1,0))*AD21 -> 0 | AC21: =IF(AK21=AL21,1,0)*AD21 -> 1 | AD21: =IF(ISNUMBER(MATCH(A21,$A$2:A20,0)),0,1) -> 1 | AF21: =SUMIFS(AH$3:AH$251,$A$3:$A$251,$A21) -> 0 | AG21: =SUMIFS(AI$3:AI$77,$A$3:$A$77,$A21) -> 1 | AH21: =IF(SUM(AW21:AZ21)=0,0,IF(SUM(AQ21:AT21)=SUM(AW21:AZ21),1,0)) -> 0 | AI21: 1 | AK21: =SUMIFS(AM$3:AM$251,$A$3:$A$251,$A21) -> 1 | AL21: =SUMIFS(AN$3:AN$251,$A$3:$A$251,$A21) -> 1 | AM21: =IF(SUM(AQ21:AT21)=SUM(AW21:AZ21),1,0) -> 1 | AN21: 1 | AP21: =SUM(AQ21:AT21) -> 0 | AQ21: =IF(OR(E21="",E21="TBD",E21="N/A",E21="SDK",E21="SAAS"),0,1) -> 0 | AR21: =IF(OR(F21="",F21="TBD",F21="N/A",F21="SDK",F21="SAAS"),0,1) -> 0 | AS21: =IF(OR(G21="",G21="TBD",G21="N/A",G21="SDK",G21="SAAS"),0,1) -> 0 | AT21: =IF(OR(H21="",H21="TBD",H21="N/A",H21="SDK",H21="SAAS"),0,1) -> 0 | AV21: =SUM(AW21:AZ21) -> 0 | AW21: =IF(OR(E21="",E21="N/A",E21="SDK",E21="SAAS"),0,1) -> 0 | AX21: =IF(OR(F21="",F21="N/A",F21="SDK",F21="SAAS"),0,1) -> 0 | AY21: =IF(OR(G21="",G21="N/A",G21="SDK",G21="SAAS"),0,1) -> 0 | AZ21: =IF(OR(H21="",H21="N/A",H21="SDK",H21="SAAS"),0,1) -> 0
A22: IC-017 | B22: Onboarding | C22: Reconocimiento facial 1:N para evitar duplicidades | D22: SDK | E22: SDK | F22: SDK | G22: SDK | H22: SDK | K22: =J22*$J$147 -> 0 | L22: Backlog | M22: Rafael Elizalde | N22: x | V22: Sí | W22: Por definir | AB22: =IF(AG22=0,0,IF(AF22=AG22,1,0))*AD22 -> 0 | AC22: =IF(AK22=AL22,1,0)*AD22 -> 1 | AD22: =IF(ISNUMBER(MATCH(A22,$A$2:A21,0)),0,1) -> 1 | AF22: =SUMIFS(AH$3:AH$251,$A$3:$A$251,$A22) -> 0 | AG22: =SUMIFS(AI$3:AI$77,$A$3:$A$77,$A22) -> 1 | AH22: =IF(SUM(AW22:AZ22)=0,0,IF(SUM(AQ22:AT22)=SUM(AW22:AZ22),1,0)) -> 0 | AI22: 1 | AK22: =SUMIFS(AM$3:AM$251,$A$3:$A$251,$A22) -> 1 | AL22: =SUMIFS(AN$3:AN$251,$A$3:$A$251,$A22) -> 1 | AM22: =IF(SUM(AQ22:AT22)=SUM(AW22:AZ22),1,0) -> 1 | AN22: 1 | AP22: =SUM(AQ22:AT22) -> 0 | AQ22: =IF(OR(E22="",E22="TBD",E22="N/A",E22="SDK",E22="SAAS"),0,1) -> 0 | AR22: =IF(OR(F22="",F22="TBD",F22="N/A",F22="SDK",F22="SAAS"),0,1) -> 0 | AS22: =IF(OR(G22="",G22="TBD",G22="N/A",G22="SDK",G22="SAAS"),0,1) -> 0 | AT22: =IF(OR(H22="",H22="TBD",H22="N/A",H22="SDK",H22="SAAS"),0,1) -> 0 | AV22: =SUM(AW22:AZ22) -> 0 | AW22: =IF(OR(E22="",E22="N/A",E22="SDK",E22="SAAS"),0,1) -> 0 | AX22: =IF(OR(F22="",F22="N/A",F22="SDK",F22="SAAS"),0,1) -> 0 | AY22: =IF(OR(G22="",G22="N/A",G22="SDK",G22="SAAS"),0,1) -> 0 | AZ22: =IF(OR(H22="",H22="N/A",H22="SDK",H22="SAAS"),0,1) -> 0
A23: IC-018 | B23: Onboarding | C23: Validación de Personas Políticamentes Expuestas (PPEs), Listas negras internacionales y locales, así como otras listas de bloqueo | E23: /experience/Customers/v1/onboardingPartySuitability/evaluate | F23: /customers/v1/onboardingPartySuitability/evaluate | G23: /sales/partyLifecycleManagement/v1/qualification/retrieve | H23: /system/sales/partyLifecycleManagement/v1/qualification/retrieve | J23: 6 | K23: =J23*$J$147 -> 21 | L23: Backlog | M23: Rafael Elizalde | N23: x | V23: Sí | W23: Por definir | AB23: =IF(AG23=0,0,IF(AF23=AG23,1,0))*AD23 -> 1 | AC23: =IF(AK23=AL23,1,0)*AD23 -> 1 | AD23: =IF(ISNUMBER(MATCH(A23,$A$2:A22,0)),0,1) -> 1 | AF23: =SUMIFS(AH$3:AH$251,$A$3:$A$251,$A23) -> 1 | AG23: =SUMIFS(AI$3:AI$77,$A$3:$A$77,$A23) -> 1 | AH23: =IF(SUM(AW23:AZ23)=0,0,IF(SUM(AQ23:AT23)=SUM(AW23:AZ23),1,0)) -> 1 | AI23: 1 | AK23: =SUMIFS(AM$3:AM$251,$A$3:$A$251,$A23) -> 1 | AL23: =SUMIFS(AN$3:AN$251,$A$3:$A$251,$A23) -> 1 | AM23: =IF(SUM(AQ23:AT23)=SUM(AW23:AZ23),1,0) -> 1 | AN23: 1 | AP23: =SUM(AQ23:AT23) -> 4 | AQ23: =IF(OR(E23="",E23="TBD",E23="N/A",E23="SDK",E23="SAAS"),0,1) -> 1 | AR23: =IF(OR(F23="",F23="TBD",F23="N/A",F23="SDK",F23="SAAS"),0,1) -> 1 | AS23: =IF(OR(G23="",G23="TBD",G23="N/A",G23="SDK",G23="SAAS"),0,1) -> 1 | AT23: =IF(OR(H23="",H23="TBD",H23="N/A",H23="SDK",H23="SAAS"),0,1) -> 1 | AV23: =SUM(AW23:AZ23) -> 4 | AW23: =IF(OR(E23="",E23="N/A",E23="SDK",E23="SAAS"),0,1) -> 1 | AX23: =IF(OR(F23="",F23="N/A",F23="SDK",F23="SAAS"),0,1) -> 1 | AY23: =IF(OR(G23="",G23="N/A",G23="SDK",G23="SAAS"),0,1) -> 1 | AZ23: =IF(OR(H23="",H23="N/A",H23="SDK",H23="SAAS"),0,1) -> 1
A24: IC-019 | B24: Onboarding | C24: Obtener la Dirección IP del dispositivo en donde se está ejecutando el proceso | E24: /experience/channels/v1/onBoardingParty/initiate | F24: /salesAndService/v1/onBoardingParty/initiate | G24: /crossChannel/sessionDialogue/v1/customerContactSessionProcedure/initiate | K24: =J24*$J$147 -> 0 | L24: Backlog | M24: Rafael Elizalde | N24: x | V24: Sí | W24: Por definir | AB24: =IF(AG24=0,0,IF(AF24=AG24,1,0))*AD24 -> 1 | AC24: =IF(AK24=AL24,1,0)*AD24 -> 1 | AD24: =IF(ISNUMBER(MATCH(A24,$A$2:A23,0)),0,1) -> 1 | AF24: =SUMIFS(AH$3:AH$251,$A$3:$A$251,$A24) -> 1 | AG24: =SUMIFS(AI$3:AI$77,$A$3:$A$77,$A24) -> 1 | AH24: =IF(SUM(AW24:AZ24)=0,0,IF(SUM(AQ24:AT24)=SUM(AW24:AZ24),1,0)) -> 1 | AI24: 1 | AK24: =SUMIFS(AM$3:AM$251,$A$3:$A$251,$A24) -> 1 | AL24: =SUMIFS(AN$3:AN$251,$A$3:$A$251,$A24) -> 1 | AM24: =IF(SUM(AQ24:AT24)=SUM(AW24:AZ24),1,0) -> 1 | AN24: 1 | AP24: =SUM(AQ24:AT24) -> 3 | AQ24: =IF(OR(E24="",E24="TBD",E24="N/A",E24="SDK",E24="SAAS"),0,1) -> 1 | AR24: =IF(OR(F24="",F24="TBD",F24="N/A",F24="SDK",F24="SAAS"),0,1) -> 1 | AS24: =IF(OR(G24="",G24="TBD",G24="N/A",G24="SDK",G24="SAAS"),0,1) -> 1 | AT24: =IF(OR(H24="",H24="TBD",H24="N/A",H24="SDK",H24="SAAS"),0,1) -> 0 | AV24: =SUM(AW24:AZ24) -> 3 | AW24: =IF(OR(E24="",E24="N/A",E24="SDK",E24="SAAS"),0,1) -> 1 | AX24: =IF(OR(F24="",F24="N/A",F24="SDK",F24="SAAS"),0,1) -> 1 | AY24: =IF(OR(G24="",G24="N/A",G24="SDK",G24="SAAS"),0,1) -> 1 | AZ24: =IF(OR(H24="",H24="N/A",H24="SDK",H24="SAAS"),0,1) -> 0
A25: IC-020 | B25: Onboarding | C25: Obtener la Geolocalización (longitud y altitud) | E25: /experience/channels/v1/onBoardingParty/initiate | F25: /salesAndService/v1/onBoardingParty/initiate | G25: /crossChannel/sessionDialogue/v1/customerContactSessionProcedure/initiate | K25: =J25*$J$147 -> 0 | L25: Backlog | M25: Rafael Elizalde | N25: x | V25: Sí | W25: Por definir | AB25: =IF(AG25=0,0,IF(AF25=AG25,1,0))*AD25 -> 1 | AC25: =IF(AK25=AL25,1,0)*AD25 -> 1 | AD25: =IF(ISNUMBER(MATCH(A25,$A$2:A24,0)),0,1) -> 1 | AF25: =SUMIFS(AH$3:AH$251,$A$3:$A$251,$A25) -> 1 | AG25: =SUMIFS(AI$3:AI$77,$A$3:$A$77,$A25) -> 1 | AH25: =IF(SUM(AW25:AZ25)=0,0,IF(SUM(AQ25:AT25)=SUM(AW25:AZ25),1,0)) -> 1 | AI25: 1 | AK25: =SUMIFS(AM$3:AM$251,$A$3:$A$251,$A25) -> 1 | AL25: =SUMIFS(AN$3:AN$251,$A$3:$A$251,$A25) -> 1 | AM25: =IF(SUM(AQ25:AT25)=SUM(AW25:AZ25),1,0) -> 1 | AN25: 1 | AP25: =SUM(AQ25:AT25) -> 3 | AQ25: =IF(OR(E25="",E25="TBD",E25="N/A",E25="SDK",E25="SAAS"),0,1) -> 1 | AR25: =IF(OR(F25="",F25="TBD",F25="N/A",F25="SDK",F25="SAAS"),0,1) -> 1 | AS25: =IF(OR(G25="",G25="TBD",G25="N/A",G25="SDK",G25="SAAS"),0,1) -> 1 | AT25: =IF(OR(H25="",H25="TBD",H25="N/A",H25="SDK",H25="SAAS"),0,1) -> 0 | AV25: =SUM(AW25:AZ25) -> 3 | AW25: =IF(OR(E25="",E25="N/A",E25="SDK",E25="SAAS"),0,1) -> 1 | AX25: =IF(OR(F25="",F25="N/A",F25="SDK",F25="SAAS"),0,1) -> 1 | AY25: =IF(OR(G25="",G25="N/A",G25="SDK",G25="SAAS"),0,1) -> 1 | AZ25: =IF(OR(H25="",H25="N/A",H25="SDK",H25="SAAS"),0,1) -> 0
A26: IC-021 | B26: Onboarding | C26: Generar el Hash ID del dispositivo | E26: /experience/channels/v1/onBoardingParty/initiate | F26: /salesAndService/v1/onBoardingParty/initiate | G26: /crossChannel/sessionDialogue/v1/customerContactSessionProcedure/initiate | K26: =J26*$J$147 -> 0 | L26: Backlog | M26: Rafael Elizalde | N26: x | V26: Sí | W26: Por definir | AB26: =IF(AG26=0,0,IF(AF26=AG26,1,0))*AD26 -> 1 | AC26: =IF(AK26=AL26,1,0)*AD26 -> 1 | AD26: =IF(ISNUMBER(MATCH(A26,$A$2:A25,0)),0,1) -> 1 | AF26: =SUMIFS(AH$3:AH$251,$A$3:$A$251,$A26) -> 1 | AG26: =SUMIFS(AI$3:AI$77,$A$3:$A$77,$A26) -> 1 | AH26: =IF(SUM(AW26:AZ26)=0,0,IF(SUM(AQ26:AT26)=SUM(AW26:AZ26),1,0)) -> 1 | AI26: 1 | AK26: =SUMIFS(AM$3:AM$251,$A$3:$A$251,$A26) -> 1 | AL26: =SUMIFS(AN$3:AN$251,$A$3:$A$251,$A26) -> 1 | AM26: =IF(SUM(AQ26:AT26)=SUM(AW26:AZ26),1,0) -> 1 | AN26: 1 | AP26: =SUM(AQ26:AT26) -> 3 | AQ26: =IF(OR(E26="",E26="TBD",E26="N/A",E26="SDK",E26="SAAS"),0,1) -> 1 | AR26: =IF(OR(F26="",F26="TBD",F26="N/A",F26="SDK",F26="SAAS"),0,1) -> 1 | AS26: =IF(OR(G26="",G26="TBD",G26="N/A",G26="SDK",G26="SAAS"),0,1) -> 1 | AT26: =IF(OR(H26="",H26="TBD",H26="N/A",H26="SDK",H26="SAAS"),0,1) -> 0 | AV26: =SUM(AW26:AZ26) -> 3 | AW26: =IF(OR(E26="",E26="N/A",E26="SDK",E26="SAAS"),0,1) -> 1 | AX26: =IF(OR(F26="",F26="N/A",F26="SDK",F26="SAAS"),0,1) -> 1 | AY26: =IF(OR(G26="",G26="N/A",G26="SDK",G26="SAAS"),0,1) -> 1 | AZ26: =IF(OR(H26="",H26="N/A",H26="SDK",H26="SAAS"),0,1) -> 0
A27: IC-022 | B27: Onboarding | C27: Validar comprobante de ingresos (estados de cuenta bancarios) | E27: TBD | F27: TBD | G27: TBD | H27: TBD | K27: =J27*$J$147 -> 0 | L27: Backlog | M27: Rafael Elizalde | N27: x | V27: Post MVP | W27: Por definir | AB27: =IF(AG27=0,0,IF(AF27=AG27,1,0))*AD27 -> 0 | AC27: =IF(AK27=AL27,1,0)*AD27 -> 0 | AD27: =IF(ISNUMBER(MATCH(A27,$A$2:A26,0)),0,1) -> 1 | AF27: =SUMIFS(AH$3:AH$251,$A$3:$A$251,$A27) -> 0 | AG27: =SUMIFS(AI$3:AI$77,$A$3:$A$77,$A27) -> 1 | AH27: =IF(SUM(AW27:AZ27)=0,0,IF(SUM(AQ27:AT27)=SUM(AW27:AZ27),1,0)) -> 0 | AI27: 1 | AK27: =SUMIFS(AM$3:AM$251,$A$3:$A$251,$A27) -> 0 | AL27: =SUMIFS(AN$3:AN$251,$A$3:$A$251,$A27) -> 1 | AM27: =IF(SUM(AQ27:AT27)=SUM(AW27:AZ27),1,0) -> 0 | AN27: 1 | AP27: =SUM(AQ27:AT27) -> 0 | AQ27: =IF(OR(E27="",E27="TBD",E27="N/A",E27="SDK",E27="SAAS"),0,1) -> 0 | AR27: =IF(OR(F27="",F27="TBD",F27="N/A",F27="SDK",F27="SAAS"),0,1) -> 0 | AS27: =IF(OR(G27="",G27="TBD",G27="N/A",G27="SDK",G27="SAAS"),0,1) -> 0 | AT27: =IF(OR(H27="",H27="TBD",H27="N/A",H27="SDK",H27="SAAS"),0,1) -> 0 | AV27: =SUM(AW27:AZ27) -> 4 | AW27: =IF(OR(E27="",E27="N/A",E27="SDK",E27="SAAS"),0,1) -> 1 | AX27: =IF(OR(F27="",F27="N/A",F27="SDK",F27="SAAS"),0,1) -> 1 | AY27: =IF(OR(G27="",G27="N/A",G27="SDK",G27="SAAS"),0,1) -> 1 | AZ27: =IF(OR(H27="",H27="N/A",H27="SDK",H27="SAAS"),0,1) -> 1
A28: IC-024 | B28: Onboarding | C28: Generar la videograbación como parte de la prueba de vida (Video Selfie) | E28: /experience/crossChannel/sessionDialogue/v1/customerContactVideoSelfieProcedure/initiate | J28: 1 | K28: =J28*$J$147 -> 3.5 | L28: Backlog | M28: Rafael Elizalde | N28: x | V28: Sí | W28: Por definir | AB28: =IF(AG28=0,0,IF(AF28=AG28,1,0))*AD28 -> 1 | AC28: =IF(AK28=AL28,1,0)*AD28 -> 1 | AD28: =IF(ISNUMBER(MATCH(A28,$A$2:A27,0)),0,1) -> 1 | AF28: =SUMIFS(AH$3:AH$251,$A$3:$A$251,$A28) -> 2 | AG28: =SUMIFS(AI$3:AI$77,$A$3:$A$77,$A28) -> 2 | AH28: =IF(SUM(AW28:AZ28)=0,0,IF(SUM(AQ28:AT28)=SUM(AW28:AZ28),1,0)) -> 1 | AI28: 1 | AK28: =SUMIFS(AM$3:AM$251,$A$3:$A$251,$A28) -> 2 | AL28: =SUMIFS(AN$3:AN$251,$A$3:$A$251,$A28) -> 2 | AM28: =IF(SUM(AQ28:AT28)=SUM(AW28:AZ28),1,0) -> 1 | AN28: 1 | AP28: =SUM(AQ28:AT28) -> 1 | AQ28: =IF(OR(E28="",E28="TBD",E28="N/A",E28="SDK",E28="SAAS"),0,1) -> 1 | AR28: =IF(OR(F28="",F28="TBD",F28="N/A",F28="SDK",F28="SAAS"),0,1) -> 0 | AS28: =IF(OR(G28="",G28="TBD",G28="N/A",G28="SDK",G28="SAAS"),0,1) -> 0 | AT28: =IF(OR(H28="",H28="TBD",H28="N/A",H28="SDK",H28="SAAS"),0,1) -> 0 | AV28: =SUM(AW28:AZ28) -> 1 | AW28: =IF(OR(E28="",E28="N/A",E28="SDK",E28="SAAS"),0,1) -> 1 | AX28: =IF(OR(F28="",F28="N/A",F28="SDK",F28="SAAS"),0,1) -> 0 | AY28: =IF(OR(G28="",G28="N/A",G28="SDK",G28="SAAS"),0,1) -> 0 | AZ28: =IF(OR(H28="",H28="N/A",H28="SDK",H28="SAAS"),0,1) -> 0
A29: IC-024 | B29: Onboarding | C29: Generar la videograbación como parte de la prueba de vida (Video Selfie) | E29: /experience/crossChannel/sessionDialogue/v1/customerContactVideoSelfieProcedure/retrieve | J29: 1 | K29: =J29*$J$147 -> 3.5 | L29: Backlog | M29: Rafael Elizalde | N29: x | V29: Sí | W29: Por definir | AB29: =IF(AG29=0,0,IF(AF29=AG29,1,0))*AD29 -> 0 | AC29: =IF(AK29=AL29,1,0)*AD29 -> 0 | AD29: =IF(ISNUMBER(MATCH(A29,$A$2:A28,0)),0,1) -> 0 | AF29: =SUMIFS(AH$3:AH$251,$A$3:$A$251,$A29) -> 2 | AG29: =SUMIFS(AI$3:AI$77,$A$3:$A$77,$A29) -> 2 | AH29: =IF(SUM(AW29:AZ29)=0,0,IF(SUM(AQ29:AT29)=SUM(AW29:AZ29),1,0)) -> 1 | AI29: 1 | AK29: =SUMIFS(AM$3:AM$251,$A$3:$A$251,$A29) -> 2 | AL29: =SUMIFS(AN$3:AN$251,$A$3:$A$251,$A29) -> 2 | AM29: =IF(SUM(AQ29:AT29)=SUM(AW29:AZ29),1,0) -> 1 | AN29: 1 | AP29: =SUM(AQ29:AT29) -> 1 | AQ29: =IF(OR(E29="",E29="TBD",E29="N/A",E29="SDK",E29="SAAS"),0,1) -> 1 | AR29: =IF(OR(F29="",F29="TBD",F29="N/A",F29="SDK",F29="SAAS"),0,1) -> 0 | AS29: =IF(OR(G29="",G29="TBD",G29="N/A",G29="SDK",G29="SAAS"),0,1) -> 0 | AT29: =IF(OR(H29="",H29="TBD",H29="N/A",H29="SDK",H29="SAAS"),0,1) -> 0 | AV29: =SUM(AW29:AZ29) -> 1 | AW29: =IF(OR(E29="",E29="N/A",E29="SDK",E29="SAAS"),0,1) -> 1 | AX29: =IF(OR(F29="",F29="N/A",F29="SDK",F29="SAAS"),0,1) -> 0 | AY29: =IF(OR(G29="",G29="N/A",G29="SDK",G29="SAAS"),0,1) -> 0 | AZ29: =IF(OR(H29="",H29="N/A",H29="SDK",H29="SAAS"),0,1) -> 0
A30: IC-025 | B30: Onboarding | C30: Firmar del contrato (Non Repudiation) | E30: TBD | F30: TBD | G30: TBD | H30: TBD | K30: =J30*$J$147 -> 0 | L30: Backlog | M30: Rafael Elizalde | N30: x | V30: Sí | W30: Por definir | AB30: =IF(AG30=0,0,IF(AF30=AG30,1,0))*AD30 -> 0 | AC30: =IF(AK30=AL30,1,0)*AD30 -> 0 | AD30: =IF(ISNUMBER(MATCH(A30,$A$2:A28,0)),0,1) -> 1 | AF30: =SUMIFS(AH$3:AH$251,$A$3:$A$251,$A30) -> 0 | AG30: =SUMIFS(AI$3:AI$77,$A$3:$A$77,$A30) -> 1 | AH30: =IF(SUM(AW30:AZ30)=0,0,IF(SUM(AQ30:AT30)=SUM(AW30:AZ30),1,0)) -> 0 | AI30: 1 | AK30: =SUMIFS(AM$3:AM$251,$A$3:$A$251,$A30) -> 0 | AL30: =SUMIFS(AN$3:AN$251,$A$3:$A$251,$A30) -> 1 | AM30: =IF(SUM(AQ30:AT30)=SUM(AW30:AZ30),1,0) -> 0 | AN30: 1 | AP30: =SUM(AQ30:AT30) -> 0 | AQ30: =IF(OR(E30="",E30="TBD",E30="N/A",E30="SDK",E30="SAAS"),0,1) -> 0 | AR30: =IF(OR(F30="",F30="TBD",F30="N/A",F30="SDK",F30="SAAS"),0,1) -> 0 | AS30: =IF(OR(G30="",G30="TBD",G30="N/A",G30="SDK",G30="SAAS"),0,1) -> 0 | AT30: =IF(OR(H30="",H30="TBD",H30="N/A",H30="SDK",H30="SAAS"),0,1) -> 0 | AV30: =SUM(AW30:AZ30) -> 4 | AW30: =IF(OR(E30="",E30="N/A",E30="SDK",E30="SAAS"),0,1) -> 1 | AX30: =IF(OR(F30="",F30="N/A",F30="SDK",F30="SAAS"),0,1) -> 1 | AY30: =IF(OR(G30="",G30="N/A",G30="SDK",G30="SAAS"),0,1) -> 1 | AZ30: =IF(OR(H30="",H30="N/A",H30="SDK",H30="SAAS"),0,1) -> 1
A31: IC-027 | B31: Onboarding | C31: Firmar con NOM 151 | E31: TBD | F31: TBD | G31: TBD | H31: TBD | K31: =J31*$J$147 -> 0 | L31: Backlog | M31: Rafael Elizalde | N31: x | V31: Sí | W31: Por definir | AB31: =IF(AG31=0,0,IF(AF31=AG31,1,0))*AD31 -> 0 | AC31: =IF(AK31=AL31,1,0)*AD31 -> 0 | AD31: =IF(ISNUMBER(MATCH(A31,$A$2:A30,0)),0,1) -> 1 | AF31: =SUMIFS(AH$3:AH$251,$A$3:$A$251,$A31) -> 0 | AG31: =SUMIFS(AI$3:AI$77,$A$3:$A$77,$A31) -> 1 | AH31: =IF(SUM(AW31:AZ31)=0,0,IF(SUM(AQ31:AT31)=SUM(AW31:AZ31),1,0)) -> 0 | AI31: 1 | AK31: =SUMIFS(AM$3:AM$251,$A$3:$A$251,$A31) -> 0 | AL31: =SUMIFS(AN$3:AN$251,$A$3:$A$251,$A31) -> 1 | AM31: =IF(SUM(AQ31:AT31)=SUM(AW31:AZ31),1,0) -> 0 | AN31: 1 | AP31: =SUM(AQ31:AT31) -> 0 | AQ31: =IF(OR(E31="",E31="TBD",E31="N/A",E31="SDK",E31="SAAS"),0,1) -> 0 | AR31: =IF(OR(F31="",F31="TBD",F31="N/A",F31="SDK",F31="SAAS"),0,1) -> 0 | AS31: =IF(OR(G31="",G31="TBD",G31="N/A",G31="SDK",G31="SAAS"),0,1) -> 0 | AT31: =IF(OR(H31="",H31="TBD",H31="N/A",H31="SDK",H31="SAAS"),0,1) -> 0 | AV31: =SUM(AW31:AZ31) -> 4 | AW31: =IF(OR(E31="",E31="N/A",E31="SDK",E31="SAAS"),0,1) -> 1 | AX31: =IF(OR(F31="",F31="N/A",F31="SDK",F31="SAAS"),0,1) -> 1 | AY31: =IF(OR(G31="",G31="N/A",G31="SDK",G31="SAAS"),0,1) -> 1 | AZ31: =IF(OR(H31="",H31="N/A",H31="SDK",H31="SAAS"),0,1) -> 1
A32: IC-028 | B32: Onboarding | C32: Firmar los eventos con un certificado | E32: TBD | F32: TBD | G32: TBD | H32: TBD | K32: =J32*$J$147 -> 0 | L32: Backlog | M32: Rafael Elizalde | N32: x | V32: Sí | W32: Por definir | AB32: =IF(AG32=0,0,IF(AF32=AG32,1,0))*AD32 -> 0 | AC32: =IF(AK32=AL32,1,0)*AD32 -> 0 | AD32: =IF(ISNUMBER(MATCH(A32,$A$2:A31,0)),0,1) -> 1 | AF32: =SUMIFS(AH$3:AH$251,$A$3:$A$251,$A32) -> 0 | AG32: =SUMIFS(AI$3:AI$77,$A$3:$A$77,$A32) -> 1 | AH32: =IF(SUM(AW32:AZ32)=0,0,IF(SUM(AQ32:AT32)=SUM(AW32:AZ32),1,0)) -> 0 | AI32: 1 | AK32: =SUMIFS(AM$3:AM$251,$A$3:$A$251,$A32) -> 0 | AL32: =SUMIFS(AN$3:AN$251,$A$3:$A$251,$A32) -> 1 | AM32: =IF(SUM(AQ32:AT32)=SUM(AW32:AZ32),1,0) -> 0 | AN32: 1 | AP32: =SUM(AQ32:AT32) -> 0 | AQ32: =IF(OR(E32="",E32="TBD",E32="N/A",E32="SDK",E32="SAAS"),0,1) -> 0 | AR32: =IF(OR(F32="",F32="TBD",F32="N/A",F32="SDK",F32="SAAS"),0,1) -> 0 | AS32: =IF(OR(G32="",G32="TBD",G32="N/A",G32="SDK",G32="SAAS"),0,1) -> 0 | AT32: =IF(OR(H32="",H32="TBD",H32="N/A",H32="SDK",H32="SAAS"),0,1) -> 0 | AV32: =SUM(AW32:AZ32) -> 4 | AW32: =IF(OR(E32="",E32="N/A",E32="SDK",E32="SAAS"),0,1) -> 1 | AX32: =IF(OR(F32="",F32="N/A",F32="SDK",F32="SAAS"),0,1) -> 1 | AY32: =IF(OR(G32="",G32="N/A",G32="SDK",G32="SAAS"),0,1) -> 1 | AZ32: =IF(OR(H32="",H32="N/A",H32="SDK",H32="SAAS"),0,1) -> 1
A33: MD - 001 | B33: Onboarding | C33: Generación y versionamiento de Plantillas HTML asociadas a la experiencia digital | D33: SAAS | E33: SAAS | F33: SAAS | G33: SAAS | H33: SAAS | K33: =J33*$J$147 -> 0 | L33: Backlog | M33: Rafael Elizalde | N33: x | V33: Sí | W33: Por definir | AB33: =IF(AG33=0,0,IF(AF33=AG33,1,0))*AD33 -> 0 | AC33: =IF(AK33=AL33,1,0)*AD33 -> 1 | AD33: =IF(ISNUMBER(MATCH(A33,$A$2:A32,0)),0,1) -> 1 | AF33: =SUMIFS(AH$3:AH$251,$A$3:$A$251,$A33) -> 0 | AG33: =SUMIFS(AI$3:AI$77,$A$3:$A$77,$A33) -> 1 | AH33: =IF(SUM(AW33:AZ33)=0,0,IF(SUM(AQ33:AT33)=SUM(AW33:AZ33),1,0)) -> 0 | AI33: 1 | AK33: =SUMIFS(AM$3:AM$251,$A$3:$A$251,$A33) -> 1 | AL33: =SUMIFS(AN$3:AN$251,$A$3:$A$251,$A33) -> 1 | AM33: =IF(SUM(AQ33:AT33)=SUM(AW33:AZ33),1,0) -> 1 | AN33: 1 | AP33: =SUM(AQ33:AT33) -> 0 | AQ33: =IF(OR(E33="",E33="TBD",E33="N/A",E33="SDK",E33="SAAS"),0,1) -> 0 | AR33: =IF(OR(F33="",F33="TBD",F33="N/A",F33="SDK",F33="SAAS"),0,1) -> 0 | AS33: =IF(OR(G33="",G33="TBD",G33="N/A",G33="SDK",G33="SAAS"),0,1) -> 0 | AT33: =IF(OR(H33="",H33="TBD",H33="N/A",H33="SDK",H33="SAAS"),0,1) -> 0 | AV33: =SUM(AW33:AZ33) -> 0 | AW33: =IF(OR(E33="",E33="N/A",E33="SDK",E33="SAAS"),0,1) -> 0 | AX33: =IF(OR(F33="",F33="N/A",F33="SDK",F33="SAAS"),0,1) -> 0 | AY33: =IF(OR(G33="",G33="N/A",G33="SDK",G33="SAAS"),0,1) -> 0 | AZ33: =IF(OR(H33="",H33="N/A",H33="SDK",H33="SAAS"),0,1) -> 0
A34: MD - 002 | B34: Onboarding | C34: Contar con catálogo de plantillas HTML que permitan la reutilización de código | D34: SAAS | E34: SAAS | F34: SAAS | G34: SAAS | H34: SAAS | K34: =J34*$J$147 -> 0 | L34: Backlog | M34: Rafael Elizalde | N34: x | V34: Sí | W34: Por definir | AB34: =IF(AG34=0,0,IF(AF34=AG34,1,0))*AD34 -> 0 | AC34: =IF(AK34=AL34,1,0)*AD34 -> 1 | AD34: =IF(ISNUMBER(MATCH(A34,$A$2:A33,0)),0,1) -> 1 | AF34: =SUMIFS(AH$3:AH$251,$A$3:$A$251,$A34) -> 0 | AG34: =SUMIFS(AI$3:AI$77,$A$3:$A$77,$A34) -> 1 | AH34: =IF(SUM(AW34:AZ34)=0,0,IF(SUM(AQ34:AT34)=SUM(AW34:AZ34),1,0)) -> 0 | AI34: 1 | AK34: =SUMIFS(AM$3:AM$251,$A$3:$A$251,$A34) -> 1 | AL34: =SUMIFS(AN$3:AN$251,$A$3:$A$251,$A34) -> 1 | AM34: =IF(SUM(AQ34:AT34)=SUM(AW34:AZ34),1,0) -> 1 | AN34: 1 | AP34: =SUM(AQ34:AT34) -> 0 | AQ34: =IF(OR(E34="",E34="TBD",E34="N/A",E34="SDK",E34="SAAS"),0,1) -> 0 | AR34: =IF(OR(F34="",F34="TBD",F34="N/A",F34="SDK",F34="SAAS"),0,1) -> 0 | AS34: =IF(OR(G34="",G34="TBD",G34="N/A",G34="SDK",G34="SAAS"),0,1) -> 0 | AT34: =IF(OR(H34="",H34="TBD",H34="N/A",H34="SDK",H34="SAAS"),0,1) -> 0 | AV34: =SUM(AW34:AZ34) -> 0 | AW34: =IF(OR(E34="",E34="N/A",E34="SDK",E34="SAAS"),0,1) -> 0 | AX34: =IF(OR(F34="",F34="N/A",F34="SDK",F34="SAAS"),0,1) -> 0 | AY34: =IF(OR(G34="",G34="N/A",G34="SDK",G34="SAAS"),0,1) -> 0 | AZ34: =IF(OR(H34="",H34="N/A",H34="SDK",H34="SAAS"),0,1) -> 0
A35: MD - 003 | B35: Onboarding | C35: Gestión de sitios para organizar los canales digitales de la compañía | D35: SAAS | E35: SAAS | F35: SAAS | G35: SAAS | H35: SAAS | K35: =J35*$J$147 -> 0 | L35: Backlog | M35: Rafael Elizalde | N35: x | V35: Sí | W35: Por definir | AB35: =IF(AG35=0,0,IF(AF35=AG35,1,0))*AD35 -> 0 | AC35: =IF(AK35=AL35,1,0)*AD35 -> 1 | AD35: =IF(ISNUMBER(MATCH(A35,$A$2:A34,0)),0,1) -> 1 | AF35: =SUMIFS(AH$3:AH$251,$A$3:$A$251,$A35) -> 0 | AG35: =SUMIFS(AI$3:AI$77,$A$3:$A$77,$A35) -> 1 | AH35: =IF(SUM(AW35:AZ35)=0,0,IF(SUM(AQ35:AT35)=SUM(AW35:AZ35),1,0)) -> 0 | AI35: 1 | AK35: =SUMIFS(AM$3:AM$251,$A$3:$A$251,$A35) -> 1 | AL35: =SUMIFS(AN$3:AN$251,$A$3:$A$251,$A35) -> 1 | AM35: =IF(SUM(AQ35:AT35)=SUM(AW35:AZ35),1,0) -> 1 | AN35: 1 | AP35: =SUM(AQ35:AT35) -> 0 | AQ35: =IF(OR(E35="",E35="TBD",E35="N/A",E35="SDK",E35="SAAS"),0,1) -> 0 | AR35: =IF(OR(F35="",F35="TBD",F35="N/A",F35="SDK",F35="SAAS"),0,1) -> 0 | AS35: =IF(OR(G35="",G35="TBD",G35="N/A",G35="SDK",G35="SAAS"),0,1) -> 0 | AT35: =IF(OR(H35="",H35="TBD",H35="N/A",H35="SDK",H35="SAAS"),0,1) -> 0 | AV35: =SUM(AW35:AZ35) -> 0 | AW35: =IF(OR(E35="",E35="N/A",E35="SDK",E35="SAAS"),0,1) -> 0 | AX35: =IF(OR(F35="",F35="N/A",F35="SDK",F35="SAAS"),0,1) -> 0 | AY35: =IF(OR(G35="",G35="N/A",G35="SDK",G35="SAAS"),0,1) -> 0 | AZ35: =IF(OR(H35="",H35="N/A",H35="SDK",H35="SAAS"),0,1) -> 0
A36: MD - 004 | B36: Onboarding | C36: Páginas dinámicas para definir la estructura de cada sitio y agregar contenido | D36: SAAS | E36: SAAS | F36: SAAS | G36: SAAS | H36: SAAS | K36: =J36*$J$147 -> 0 | L36: Backlog | M36: Rafael Elizalde | N36: x | V36: Sí | W36: Por definir | AB36: =IF(AG36=0,0,IF(AF36=AG36,1,0))*AD36 -> 0 | AC36: =IF(AK36=AL36,1,0)*AD36 -> 1 | AD36: =IF(ISNUMBER(MATCH(A36,$A$2:A35,0)),0,1) -> 1 | AF36: =SUMIFS(AH$3:AH$251,$A$3:$A$251,$A36) -> 0 | AG36: =SUMIFS(AI$3:AI$77,$A$3:$A$77,$A36) -> 1 | AH36: =IF(SUM(AW36:AZ36)=0,0,IF(SUM(AQ36:AT36)=SUM(AW36:AZ36),1,0)) -> 0 | AI36: 1 | AK36: =SUMIFS(AM$3:AM$251,$A$3:$A$251,$A36) -> 1 | AL36: =SUMIFS(AN$3:AN$251,$A$3:$A$251,$A36) -> 1 | AM36: =IF(SUM(AQ36:AT36)=SUM(AW36:AZ36),1,0) -> 1 | AN36: 1 | AP36: =SUM(AQ36:AT36) -> 0 | AQ36: =IF(OR(E36="",E36="TBD",E36="N/A",E36="SDK",E36="SAAS"),0,1) -> 0 | AR36: =IF(OR(F36="",F36="TBD",F36="N/A",F36="SDK",F36="SAAS"),0,1) -> 0 | AS36: =IF(OR(G36="",G36="TBD",G36="N/A",G36="SDK",G36="SAAS"),0,1) -> 0 | AT36: =IF(OR(H36="",H36="TBD",H36="N/A",H36="SDK",H36="SAAS"),0,1) -> 0 | AV36: =SUM(AW36:AZ36) -> 0 | AW36: =IF(OR(E36="",E36="N/A",E36="SDK",E36="SAAS"),0,1) -> 0 | AX36: =IF(OR(F36="",F36="N/A",F36="SDK",F36="SAAS"),0,1) -> 0 | AY36: =IF(OR(G36="",G36="N/A",G36="SDK",G36="SAAS"),0,1) -> 0 | AZ36: =IF(OR(H36="",H36="N/A",H36="SDK",H36="SAAS"),0,1) -> 0
A37: MD - 005 | B37: Onboarding | C37: Capacidad de crear componentes reutilizables usando tecnologías de Javascript, HTML y CSS | D37: SAAS | E37: SAAS | F37: SAAS | G37: SAAS | H37: SAAS | K37: =J37*$J$147 -> 0 | L37: Backlog | M37: Rafael Elizalde | N37: x | V37: Sí | W37: Por definir | AB37: =IF(AG37=0,0,IF(AF37=AG37,1,0))*AD37 -> 0 | AC37: =IF(AK37=AL37,1,0)*AD37 -> 1 | AD37: =IF(ISNUMBER(MATCH(A37,$A$2:A36,0)),0,1) -> 1 | AF37: =SUMIFS(AH$3:AH$251,$A$3:$A$251,$A37) -> 0 | AG37: =SUMIFS(AI$3:AI$77,$A$3:$A$77,$A37) -> 1 | AH37: =IF(SUM(AW37:AZ37)=0,0,IF(SUM(AQ37:AT37)=SUM(AW37:AZ37),1,0)) -> 0 | AI37: 1 | AK37: =SUMIFS(AM$3:AM$251,$A$3:$A$251,$A37) -> 1 | AL37: =SUMIFS(AN$3:AN$251,$A$3:$A$251,$A37) -> 1 | AM37: =IF(SUM(AQ37:AT37)=SUM(AW37:AZ37),1,0) -> 1 | AN37: 1 | AP37: =SUM(AQ37:AT37) -> 0 | AQ37: =IF(OR(E37="",E37="TBD",E37="N/A",E37="SDK",E37="SAAS"),0,1) -> 0 | AR37: =IF(OR(F37="",F37="TBD",F37="N/A",F37="SDK",F37="SAAS"),0,1) -> 0 | AS37: =IF(OR(G37="",G37="TBD",G37="N/A",G37="SDK",G37="SAAS"),0,1) -> 0 | AT37: =IF(OR(H37="",H37="TBD",H37="N/A",H37="SDK",H37="SAAS"),0,1) -> 0 | AV37: =SUM(AW37:AZ37) -> 0 | AW37: =IF(OR(E37="",E37="N/A",E37="SDK",E37="SAAS"),0,1) -> 0 | AX37: =IF(OR(F37="",F37="N/A",F37="SDK",F37="SAAS"),0,1) -> 0 | AY37: =IF(OR(G37="",G37="N/A",G37="SDK",G37="SAAS"),0,1) -> 0 | AZ37: =IF(OR(H37="",H37="N/A",H37="SDK",H37="SAAS"),0,1) -> 0
A38: MD - 006 | B38: Onboarding | C38: Capacidad para crear micro frontends para múltiples sitios y aplicaciones | D38: SAAS | E38: SAAS | F38: SAAS | G38: SAAS | H38: SAAS | K38: =J38*$J$147 -> 0 | L38: Backlog | M38: Rafael Elizalde | N38: x | V38: Sí | W38: Por definir | AB38: =IF(AG38=0,0,IF(AF38=AG38,1,0))*AD38 -> 0 | AC38: =IF(AK38=AL38,1,0)*AD38 -> 1 | AD38: =IF(ISNUMBER(MATCH(A38,$A$2:A37,0)),0,1) -> 1 | AF38: =SUMIFS(AH$3:AH$251,$A$3:$A$251,$A38) -> 0 | AG38: =SUMIFS(AI$3:AI$77,$A$3:$A$77,$A38) -> 1 | AH38: =IF(SUM(AW38:AZ38)=0,0,IF(SUM(AQ38:AT38)=SUM(AW38:AZ38),1,0)) -> 0 | AI38: 1 | AK38: =SUMIFS(AM$3:AM$251,$A$3:$A$251,$A38) -> 1 | AL38: =SUMIFS(AN$3:AN$251,$A$3:$A$251,$A38) -> 1 | AM38: =IF(SUM(AQ38:AT38)=SUM(AW38:AZ38),1,0) -> 1 | AN38: 1 | AP38: =SUM(AQ38:AT38) -> 0 | AQ38: =IF(OR(E38="",E38="TBD",E38="N/A",E38="SDK",E38="SAAS"),0,1) -> 0 | AR38: =IF(OR(F38="",F38="TBD",F38="N/A",F38="SDK",F38="SAAS"),0,1) -> 0 | AS38: =IF(OR(G38="",G38="TBD",G38="N/A",G38="SDK",G38="SAAS"),0,1) -> 0 | AT38: =IF(OR(H38="",H38="TBD",H38="N/A",H38="SDK",H38="SAAS"),0,1) -> 0 | AV38: =SUM(AW38:AZ38) -> 0 | AW38: =IF(OR(E38="",E38="N/A",E38="SDK",E38="SAAS"),0,1) -> 0 | AX38: =IF(OR(F38="",F38="N/A",F38="SDK",F38="SAAS"),0,1) -> 0 | AY38: =IF(OR(G38="",G38="N/A",G38="SDK",G38="SAAS"),0,1) -> 0 | AZ38: =IF(OR(H38="",H38="N/A",H38="SDK",H38="SAAS"),0,1) -> 0
A39: MD - 007 | B39: Onboarding | C39: Capacidad para extender funcionalidades a diferentes sitios y aplicaciones incluso con una entidad separada | D39: SAAS | E39: SAAS | F39: SAAS | G39: SAAS | H39: SAAS | K39: =J39*$J$147 -> 0 | L39: Backlog | M39: Rafael Elizalde | N39: x | V39: Sí | W39: Por definir | AB39: =IF(AG39=0,0,IF(AF39=AG39,1,0))*AD39 -> 0 | AC39: =IF(AK39=AL39,1,0)*AD39 -> 1 | AD39: =IF(ISNUMBER(MATCH(A39,$A$2:A38,0)),0,1) -> 1 | AF39: =SUMIFS(AH$3:AH$251,$A$3:$A$251,$A39) -> 0 | AG39: =SUMIFS(AI$3:AI$77,$A$3:$A$77,$A39) -> 1 | AH39: =IF(SUM(AW39:AZ39)=0,0,IF(SUM(AQ39:AT39)=SUM(AW39:AZ39),1,0)) -> 0 | AI39: 1 | AK39: =SUMIFS(AM$3:AM$251,$A$3:$A$251,$A39) -> 1 | AL39: =SUMIFS(AN$3:AN$251,$A$3:$A$251,$A39) -> 1 | AM39: =IF(SUM(AQ39:AT39)=SUM(AW39:AZ39),1,0) -> 1 | AN39: 1 | AP39: =SUM(AQ39:AT39) -> 0 | AQ39: =IF(OR(E39="",E39="TBD",E39="N/A",E39="SDK",E39="SAAS"),0,1) -> 0 | AR39: =IF(OR(F39="",F39="TBD",F39="N/A",F39="SDK",F39="SAAS"),0,1) -> 0 | AS39: =IF(OR(G39="",G39="TBD",G39="N/A",G39="SDK",G39="SAAS"),0,1) -> 0 | AT39: =IF(OR(H39="",H39="TBD",H39="N/A",H39="SDK",H39="SAAS"),0,1) -> 0 | AV39: =SUM(AW39:AZ39) -> 0 | AW39: =IF(OR(E39="",E39="N/A",E39="SDK",E39="SAAS"),0,1) -> 0 | AX39: =IF(OR(F39="",F39="N/A",F39="SDK",F39="SAAS"),0,1) -> 0 | AY39: =IF(OR(G39="",G39="N/A",G39="SDK",G39="SAAS"),0,1) -> 0 | AZ39: =IF(OR(H39="",H39="N/A",H39="SDK",H39="SAAS"),0,1) -> 0
A40: MD - 008 | B40: Onboarding | C40: Segmentación de componentes de acuerdo a su estado, autor, tags o por nombre de la funcionalidad | D40: SAAS | E40: SAAS | F40: SAAS | G40: SAAS | H40: SAAS | K40: =J40*$J$147 -> 0 | L40: Backlog | M40: Rafael Elizalde | N40: x | V40: Sí | W40: Por definir | AB40: =IF(AG40=0,0,IF(AF40=AG40,1,0))*AD40 -> 0 | AC40: =IF(AK40=AL40,1,0)*AD40 -> 1 | AD40: =IF(ISNUMBER(MATCH(A40,$A$2:A39,0)),0,1) -> 1 | AF40: =SUMIFS(AH$3:AH$251,$A$3:$A$251,$A40) -> 0 | AG40: =SUMIFS(AI$3:AI$77,$A$3:$A$77,$A40) -> 1 | AH40: =IF(SUM(AW40:AZ40)=0,0,IF(SUM(AQ40:AT40)=SUM(AW40:AZ40),1,0)) -> 0 | AI40: 1 | AK40: =SUMIFS(AM$3:AM$251,$A$3:$A$251,$A40) -> 1 | AL40: =SUMIFS(AN$3:AN$251,$A$3:$A$251,$A40) -> 1 | AM40: =IF(SUM(AQ40:AT40)=SUM(AW40:AZ40),1,0) -> 1 | AN40: 1 | AP40: =SUM(AQ40:AT40) -> 0 | AQ40: =IF(OR(E40="",E40="TBD",E40="N/A",E40="SDK",E40="SAAS"),0,1) -> 0 | AR40: =IF(OR(F40="",F40="TBD",F40="N/A",F40="SDK",F40="SAAS"),0,1) -> 0 | AS40: =IF(OR(G40="",G40="TBD",G40="N/A",G40="SDK",G40="SAAS"),0,1) -> 0 | AT40: =IF(OR(H40="",H40="TBD",H40="N/A",H40="SDK",H40="SAAS"),0,1) -> 0 | AV40: =SUM(AW40:AZ40) -> 0 | AW40: =IF(OR(E40="",E40="N/A",E40="SDK",E40="SAAS"),0,1) -> 0 | AX40: =IF(OR(F40="",F40="N/A",F40="SDK",F40="SAAS"),0,1) -> 0 | AY40: =IF(OR(G40="",G40="N/A",G40="SDK",G40="SAAS"),0,1) -> 0 | AZ40: =IF(OR(H40="",H40="N/A",H40="SDK",H40="SAAS"),0,1) -> 0
A41: MD - 009 | B41: Onboarding | C41: Capacidad de generar plantillas para organizar estructuras globales del sitio y el sistema de diseño | D41: SAAS | E41: SAAS | F41: SAAS | G41: SAAS | H41: SAAS | K41: =J41*$J$147 -> 0 | L41: Backlog | M41: Rafael Elizalde | N41: x | V41: Sí | W41: Por definir | AB41: =IF(AG41=0,0,IF(AF41=AG41,1,0))*AD41 -> 0 | AC41: =IF(AK41=AL41,1,0)*AD41 -> 1 | AD41: =IF(ISNUMBER(MATCH(A41,$A$2:A40,0)),0,1) -> 1 | AF41: =SUMIFS(AH$3:AH$251,$A$3:$A$251,$A41) -> 0 | AG41: =SUMIFS(AI$3:AI$77,$A$3:$A$77,$A41) -> 1 | AH41: =IF(SUM(AW41:AZ41)=0,0,IF(SUM(AQ41:AT41)=SUM(AW41:AZ41),1,0)) -> 0 | AI41: 1 | AK41: =SUMIFS(AM$3:AM$251,$A$3:$A$251,$A41) -> 1 | AL41: =SUMIFS(AN$3:AN$251,$A$3:$A$251,$A41) -> 1 | AM41: =IF(SUM(AQ41:AT41)=SUM(AW41:AZ41),1,0) -> 1 | AN41: 1 | AP41: =SUM(AQ41:AT41) -> 0 | AQ41: =IF(OR(E41="",E41="TBD",E41="N/A",E41="SDK",E41="SAAS"),0,1) -> 0 | AR41: =IF(OR(F41="",F41="TBD",F41="N/A",F41="SDK",F41="SAAS"),0,1) -> 0 | AS41: =IF(OR(G41="",G41="TBD",G41="N/A",G41="SDK",G41="SAAS"),0,1) -> 0 | AT41: =IF(OR(H41="",H41="TBD",H41="N/A",H41="SDK",H41="SAAS"),0,1) -> 0 | AV41: =SUM(AW41:AZ41) -> 0 | AW41: =IF(OR(E41="",E41="N/A",E41="SDK",E41="SAAS"),0,1) -> 0 | AX41: =IF(OR(F41="",F41="N/A",F41="SDK",F41="SAAS"),0,1) -> 0 | AY41: =IF(OR(G41="",G41="N/A",G41="SDK",G41="SAAS"),0,1) -> 0 | AZ41: =IF(OR(H41="",H41="N/A",H41="SDK",H41="SAAS"),0,1) -> 0
A42: MD - 010 | B42: Onboarding | C42: Flexibilidad para modificar las plantillas base y su estructura según se requiera | D42: SAAS | E42: SAAS | F42: SAAS | G42: SAAS | H42: SAAS | K42: =J42*$J$147 -> 0 | L42: Backlog | M42: Rafael Elizalde | N42: x | V42: Sí | W42: Por definir | AB42: =IF(AG42=0,0,IF(AF42=AG42,1,0))*AD42 -> 0 | AC42: =IF(AK42=AL42,1,0)*AD42 -> 1 | AD42: =IF(ISNUMBER(MATCH(A42,$A$2:A41,0)),0,1) -> 1 | AF42: =SUMIFS(AH$3:AH$251,$A$3:$A$251,$A42) -> 0 | AG42: =SUMIFS(AI$3:AI$77,$A$3:$A$77,$A42) -> 1 | AH42: =IF(SUM(AW42:AZ42)=0,0,IF(SUM(AQ42:AT42)=SUM(AW42:AZ42),1,0)) -> 0 | AI42: 1 | AK42: =SUMIFS(AM$3:AM$251,$A$3:$A$251,$A42) -> 1 | AL42: =SUMIFS(AN$3:AN$251,$A$3:$A$251,$A42) -> 1 | AM42: =IF(SUM(AQ42:AT42)=SUM(AW42:AZ42),1,0) -> 1 | AN42: 1 | AP42: =SUM(AQ42:AT42) -> 0 | AQ42: =IF(OR(E42="",E42="TBD",E42="N/A",E42="SDK",E42="SAAS"),0,1) -> 0 | AR42: =IF(OR(F42="",F42="TBD",F42="N/A",F42="SDK",F42="SAAS"),0,1) -> 0 | AS42: =IF(OR(G42="",G42="TBD",G42="N/A",G42="SDK",G42="SAAS"),0,1) -> 0 | AT42: =IF(OR(H42="",H42="TBD",H42="N/A",H42="SDK",H42="SAAS"),0,1) -> 0 | AV42: =SUM(AW42:AZ42) -> 0 | AW42: =IF(OR(E42="",E42="N/A",E42="SDK",E42="SAAS"),0,1) -> 0 | AX42: =IF(OR(F42="",F42="N/A",F42="SDK",F42="SAAS"),0,1) -> 0 | AY42: =IF(OR(G42="",G42="N/A",G42="SDK",G42="SAAS"),0,1) -> 0 | AZ42: =IF(OR(H42="",H42="N/A",H42="SDK",H42="SAAS"),0,1) -> 0
A43: MD - 011 | B43: Onboarding | C43: Creación de Snippets de código HTML, JS y CSS para extender la funcionalidad de algún sitio | D43: SAAS | E43: SAAS | F43: SAAS | G43: SAAS | H43: SAAS | K43: =J43*$J$147 -> 0 | L43: Backlog | M43: Rafael Elizalde | N43: x | V43: Sí | W43: Por definir | AB43: =IF(AG43=0,0,IF(AF43=AG43,1,0))*AD43 -> 0 | AC43: =IF(AK43=AL43,1,0)*AD43 -> 1 | AD43: =IF(ISNUMBER(MATCH(A43,$A$2:A42,0)),0,1) -> 1 | AF43: =SUMIFS(AH$3:AH$251,$A$3:$A$251,$A43) -> 0 | AG43: =SUMIFS(AI$3:AI$77,$A$3:$A$77,$A43) -> 1 | AH43: =IF(SUM(AW43:AZ43)=0,0,IF(SUM(AQ43:AT43)=SUM(AW43:AZ43),1,0)) -> 0 | AI43: 1 | AK43: =SUMIFS(AM$3:AM$251,$A$3:$A$251,$A43) -> 1 | AL43: =SUMIFS(AN$3:AN$251,$A$3:$A$251,$A43) -> 1 | AM43: =IF(SUM(AQ43:AT43)=SUM(AW43:AZ43),1,0) -> 1 | AN43: 1 | AP43: =SUM(AQ43:AT43) -> 0 | AQ43: =IF(OR(E43="",E43="TBD",E43="N/A",E43="SDK",E43="SAAS"),0,1) -> 0 | AR43: =IF(OR(F43="",F43="TBD",F43="N/A",F43="SDK",F43="SAAS"),0,1) -> 0 | AS43: =IF(OR(G43="",G43="TBD",G43="N/A",G43="SDK",G43="SAAS"),0,1) -> 0 | AT43: =IF(OR(H43="",H43="TBD",H43="N/A",H43="SDK",H43="SAAS"),0,1) -> 0 | AV43: =SUM(AW43:AZ43) -> 0 | AW43: =IF(OR(E43="",E43="N/A",E43="SDK",E43="SAAS"),0,1) -> 0 | AX43: =IF(OR(F43="",F43="N/A",F43="SDK",F43="SAAS"),0,1) -> 0 | AY43: =IF(OR(G43="",G43="N/A",G43="SDK",G43="SAAS"),0,1) -> 0 | AZ43: =IF(OR(H43="",H43="N/A",H43="SDK",H43="SAAS"),0,1) -> 0
A44: MD - 012 | B44: Onboarding | C44: Proceso de aprobación y publicación de plantillas, así como control de versionados | D44: SAAS | E44: SAAS | F44: SAAS | G44: SAAS | H44: SAAS | K44: =J44*$J$147 -> 0 | L44: Backlog | M44: Rafael Elizalde | N44: x | V44: Sí | W44: Por definir | AB44: =IF(AG44=0,0,IF(AF44=AG44,1,0))*AD44 -> 0 | AC44: =IF(AK44=AL44,1,0)*AD44 -> 1 | AD44: =IF(ISNUMBER(MATCH(A44,$A$2:A43,0)),0,1) -> 1 | AF44: =SUMIFS(AH$3:AH$251,$A$3:$A$251,$A44) -> 0 | AG44: =SUMIFS(AI$3:AI$77,$A$3:$A$77,$A44) -> 1 | AH44: =IF(SUM(AW44:AZ44)=0,0,IF(SUM(AQ44:AT44)=SUM(AW44:AZ44),1,0)) -> 0 | AI44: 1 | AK44: =SUMIFS(AM$3:AM$251,$A$3:$A$251,$A44) -> 1 | AL44: =SUMIFS(AN$3:AN$251,$A$3:$A$251,$A44) -> 1 | AM44: =IF(SUM(AQ44:AT44)=SUM(AW44:AZ44),1,0) -> 1 | AN44: 1 | AP44: =SUM(AQ44:AT44) -> 0 | AQ44: =IF(OR(E44="",E44="TBD",E44="N/A",E44="SDK",E44="SAAS"),0,1) -> 0 | AR44: =IF(OR(F44="",F44="TBD",F44="N/A",F44="SDK",F44="SAAS"),0,1) -> 0 | AS44: =IF(OR(G44="",G44="TBD",G44="N/A",G44="SDK",G44="SAAS"),0,1) -> 0 | AT44: =IF(OR(H44="",H44="TBD",H44="N/A",H44="SDK",H44="SAAS"),0,1) -> 0 | AV44: =SUM(AW44:AZ44) -> 0 | AW44: =IF(OR(E44="",E44="N/A",E44="SDK",E44="SAAS"),0,1) -> 0 | AX44: =IF(OR(F44="",F44="N/A",F44="SDK",F44="SAAS"),0,1) -> 0 | AY44: =IF(OR(G44="",G44="N/A",G44="SDK",G44="SAAS"),0,1) -> 0 | AZ44: =IF(OR(H44="",H44="N/A",H44="SDK",H44="SAAS"),0,1) -> 0
... A51: OB - 002 | B51: Onboarding | C51: Creación de expediente digital cliente BanCoppel | D51: TBD | E51: TBD | F51: TBD | G51: TBD | H51: TBD | K51: =J51*$J$147 -> 0 | L51: Backlog | M51: Rafael Elizalde | N51: x | V51: Sí | W51: Por definir | AB51: =IF(AG51=0,0,IF(AF51=AG51,1,0))*AD51 -> 0 | AC51: =IF(AK51=AL51,1,0)*AD51 -> 0 | AD51: =IF(ISNUMBER(MATCH(A51,$A$2:A50,0)),0,1) -> 1 | AF51: =SUMIFS(AH$3:AH$251,$A$3:$A$251,$A51) -> 0 | AG51: =SUMIFS(AI$3:AI$77,$A$3:$A$77,$A51) -> 1 | AH51: =IF(SUM(AW51:AZ51)=0,0,IF(SUM(AQ51:AT51)=SUM(AW51:AZ51),1,0)) -> 0 | AI51: 1 | AK51: =SUMIFS(AM$3:AM$251,$A$3:$A$251,$A51) -> 0 | AL51: =SUMIFS(AN$3:AN$251,$A$3:$A$251,$A51) -> 1 | AM51: =IF(SUM(AQ51:AT51)=SUM(AW51:AZ51),1,0) -> 0 | AN51: 1 | AP51: =SUM(AQ51:AT51) -> 0 | AQ51: =IF(OR(E51="",E51="TBD",E51="N/A",E51="SDK",E51="SAAS"),0,1) -> 0 | AR51: =IF(OR(F51="",F51="TBD",F51="N/A",F51="SDK",F51="SAAS"),0,1) -> 0 | AS51: =IF(OR(G51="",G51="TBD",G51="N/A",G51="SDK",G51="SAAS"),0,1) -> 0 | AT51: =IF(OR(H51="",H51="TBD",H51="N/A",H51="SDK",H51="SAAS"),0,1) -> 0 | AV51: =SUM(AW51:AZ51) -> 4 | AW51: =IF(OR(E51="",E51="N/A",E51="SDK",E51="SAAS"),0,1) -> 1 | AX51: =IF(OR(F51="",F51="N/A",F51="SDK",F51="SAAS"),0,1) -> 1 | AY51: =IF(OR(G51="",G51="N/A",G51="SDK",G51="SAAS"),0,1) -> 1 | AZ51: =IF(OR(H51="",H51="N/A",H51="SDK",H51="SAAS"),0,1) -> 1
A52: OB - 003 | B52: Onboarding | C52: Carga de documentos en expediente | E52: TBD | F52: TBD | G52: TBD | H52: TBD | K52: =J52*$J$147 -> 0 | L52: Backlog | M52: Rafael Elizalde | N52: x | V52: Sí | W52: Por definir | AB52: =IF(AG52=0,0,IF(AF52=AG52,1,0))*AD52 -> 0 | AC52: =IF(AK52=AL52,1,0)*AD52 -> 0 | AD52: =IF(ISNUMBER(MATCH(A52,$A$2:A51,0)),0,1) -> 1 | AF52: =SUMIFS(AH$3:AH$251,$A$3:$A$251,$A52) -> 0 | AG52: =SUMIFS(AI$3:AI$77,$A$3:$A$77,$A52) -> 1 | AH52: =IF(SUM(AW52:AZ52)=0,0,IF(SUM(AQ52:AT52)=SUM(AW52:AZ52),1,0)) -> 0 | AI52: 1 | AK52: =SUMIFS(AM$3:AM$251,$A$3:$A$251,$A52) -> 0 | AL52: =SUMIFS(AN$3:AN$251,$A$3:$A$251,$A52) -> 1 | AM52: =IF(SUM(AQ52:AT52)=SUM(AW52:AZ52),1,0) -> 0 | AN52: 1 | AP52: =SUM(AQ52:AT52) -> 0 | AQ52: =IF(OR(E52="",E52="TBD",E52="N/A",E52="SDK",E52="SAAS"),0,1) -> 0 | AR52: =IF(OR(F52="",F52="TBD",F52="N/A",F52="SDK",F52="SAAS"),0,1) -> 0 | AS52: =IF(OR(G52="",G52="TBD",G52="N/A",G52="SDK",G52="SAAS"),0,1) -> 0 | AT52: =IF(OR(H52="",H52="TBD",H52="N/A",H52="SDK",H52="SAAS"),0,1) -> 0 | AV52: =SUM(AW52:AZ52) -> 4 | AW52: =IF(OR(E52="",E52="N/A",E52="SDK",E52="SAAS"),0,1) -> 1 | AX52: =IF(OR(F52="",F52="N/A",F52="SDK",F52="SAAS"),0,1) -> 1 | AY52: =IF(OR(G52="",G52="N/A",G52="SDK",G52="SAAS"),0,1) -> 1 | AZ52: =IF(OR(H52="",H52="N/A",H52="SDK",H52="SAAS"),0,1) -> 1
A53: OB - 004 | B53: Onboarding | C53: Búsqueda por metadata Expediente digital | D53: TBD | E53: TBD | F53: TBD | G53: TBD | H53: TBD | K53: =J53*$J$147 -> 0 | L53: Backlog | M53: Rafael Elizalde | N53: x | V53: Sí | W53: Por definir | AB53: =IF(AG53=0,0,IF(AF53=AG53,1,0))*AD53 -> 0 | AC53: =IF(AK53=AL53,1,0)*AD53 -> 0 | AD53: =IF(ISNUMBER(MATCH(A53,$A$2:A52,0)),0,1) -> 1 | AF53: =SUMIFS(AH$3:AH$251,$A$3:$A$251,$A53) -> 0 | AG53: =SUMIFS(AI$3:AI$77,$A$3:$A$77,$A53) -> 1 | AH53: =IF(SUM(AW53:AZ53)=0,0,IF(SUM(AQ53:AT53)=SUM(AW53:AZ53),1,0)) -> 0 | AI53: 1 | AK53: =SUMIFS(AM$3:AM$251,$A$3:$A$251,$A53) -> 0 | AL53: =SUMIFS(AN$3:AN$251,$A$3:$A$251,$A53) -> 1 | AM53: =IF(SUM(AQ53:AT53)=SUM(AW53:AZ53),1,0) -> 0 | AN53: 1 | AP53: =SUM(AQ53:AT53) -> 0 | AQ53: =IF(OR(E53="",E53="TBD",E53="N/A",E53="SDK",E53="SAAS"),0,1) -> 0 | AR53: =IF(OR(F53="",F53="TBD",F53="N/A",F53="SDK",F53="SAAS"),0,1) -> 0 | AS53: =IF(OR(G53="",G53="TBD",G53="N/A",G53="SDK",G53="SAAS"),0,1) -> 0 | AT53: =IF(OR(H53="",H53="TBD",H53="N/A",H53="SDK",H53="SAAS"),0,1) -> 0 | AV53: =SUM(AW53:AZ53) -> 4 | AW53: =IF(OR(E53="",E53="N/A",E53="SDK",E53="SAAS"),0,1) -> 1 | AX53: =IF(OR(F53="",F53="N/A",F53="SDK",F53="SAAS"),0,1) -> 1 | AY53: =IF(OR(G53="",G53="N/A",G53="SDK",G53="SAAS"),0,1) -> 1 | AZ53: =IF(OR(H53="",H53="N/A",H53="SDK",H53="SAAS"),0,1) -> 1
A54: OB - 005 | B54: Onboarding | C54: Métricas de expediente digital | D54: TBD | E54: TBD | F54: TBD | G54: TBD | H54: TBD | K54: =J54*$J$147 -> 0 | L54: Backlog | M54: Rafael Elizalde | N54: x | V54: Sí | W54: Por definir | AB54: =IF(AG54=0,0,IF(AF54=AG54,1,0))*AD54 -> 0 | AC54: =IF(AK54=AL54,1,0)*AD54 -> 0 | AD54: =IF(ISNUMBER(MATCH(A54,$A$2:A53,0)),0,1) -> 1 | AF54: =SUMIFS(AH$3:AH$251,$A$3:$A$251,$A54) -> 0 | AG54: =SUMIFS(AI$3:AI$77,$A$3:$A$77,$A54) -> 1 | AH54: =IF(SUM(AW54:AZ54)=0,0,IF(SUM(AQ54:AT54)=SUM(AW54:AZ54),1,0)) -> 0 | AI54: 1 | AK54: =SUMIFS(AM$3:AM$251,$A$3:$A$251,$A54) -> 0 | AL54: =SUMIFS(AN$3:AN$251,$A$3:$A$251,$A54) -> 1 | AM54: =IF(SUM(AQ54:AT54)=SUM(AW54:AZ54),1,0) -> 0 | AN54: 1 | AP54: =SUM(AQ54:AT54) -> 0 | AQ54: =IF(OR(E54="",E54="TBD",E54="N/A",E54="SDK",E54="SAAS"),0,1) -> 0 | AR54: =IF(OR(F54="",F54="TBD",F54="N/A",F54="SDK",F54="SAAS"),0,1) -> 0 | AS54: =IF(OR(G54="",G54="TBD",G54="N/A",G54="SDK",G54="SAAS"),0,1) -> 0 | AT54: =IF(OR(H54="",H54="TBD",H54="N/A",H54="SDK",H54="SAAS"),0,1) -> 0 | AV54: =SUM(AW54:AZ54) -> 4 | AW54: =IF(OR(E54="",E54="N/A",E54="SDK",E54="SAAS"),0,1) -> 1 | AX54: =IF(OR(F54="",F54="N/A",F54="SDK",F54="SAAS"),0,1) -> 1 | AY54: =IF(OR(G54="",G54="N/A",G54="SDK",G54="SAAS"),0,1) -> 1 | AZ54: =IF(OR(H54="",H54="N/A",H54="SDK",H54="SAAS"),0,1) -> 1
A55: OB - 006 | B55: Onboarding | C55: Validaciones sobre vigencia de documentos | D55: TBD | E55: TBD | F55: TBD | G55: TBD | H55: TBD | K55: =J55*$J$147 -> 0 | L55: Backlog | M55: Rafael Elizalde | N55: x | V55: Sí | W55: Por definir | AB55: =IF(AG55=0,0,IF(AF55=AG55,1,0))*AD55 -> 0 | AC55: =IF(AK55=AL55,1,0)*AD55 -> 0 | AD55: =IF(ISNUMBER(MATCH(A55,$A$2:A54,0)),0,1) -> 1 | AF55: =SUMIFS(AH$3:AH$251,$A$3:$A$251,$A55) -> 0 | AG55: =SUMIFS(AI$3:AI$77,$A$3:$A$77,$A55) -> 1 | AH55: =IF(SUM(AW55:AZ55)=0,0,IF(SUM(AQ55:AT55)=SUM(AW55:AZ55),1,0)) -> 0 | AI55: 1 | AK55: =SUMIFS(AM$3:AM$251,$A$3:$A$251,$A55) -> 0 | AL55: =SUMIFS(AN$3:AN$251,$A$3:$A$251,$A55) -> 1 | AM55: =IF(SUM(AQ55:AT55)=SUM(AW55:AZ55),1,0) -> 0 | AN55: 1 | AP55: =SUM(AQ55:AT55) -> 0 | AQ55: =IF(OR(E55="",E55="TBD",E55="N/A",E55="SDK",E55="SAAS"),0,1) -> 0 | AR55: =IF(OR(F55="",F55="TBD",F55="N/A",F55="SDK",F55="SAAS"),0,1) -> 0 | AS55: =IF(OR(G55="",G55="TBD",G55="N/A",G55="SDK",G55="SAAS"),0,1) -> 0 | AT55: =IF(OR(H55="",H55="TBD",H55="N/A",H55="SDK",H55="SAAS"),0,1) -> 0 | AV55: =SUM(AW55:AZ55) -> 4 | AW55: =IF(OR(E55="",E55="N/A",E55="SDK",E55="SAAS"),0,1) -> 1 | AX55: =IF(OR(F55="",F55="N/A",F55="SDK",F55="SAAS"),0,1) -> 1 | AY55: =IF(OR(G55="",G55="N/A",G55="SDK",G55="SAAS"),0,1) -> 1 | AZ55: =IF(OR(H55="",H55="N/A",H55="SDK",H55="SAAS"),0,1) -> 1
A56: OB - 007 | B56: Onboarding | C56: Visor de expediente digital | D56: TBD | E56: TBD | F56: TBD | G56: TBD | H56: TBD | K56: =J56*$J$147 -> 0 | L56: Backlog | M56: Rafael Elizalde | N56: x | V56: Sí | W56: Por definir | AB56: =IF(AG56=0,0,IF(AF56=AG56,1,0))*AD56 -> 0 | AC56: =IF(AK56=AL56,1,0)*AD56 -> 0 | AD56: =IF(ISNUMBER(MATCH(A56,$A$2:A55,0)),0,1) -> 1 | AF56: =SUMIFS(AH$3:AH$251,$A$3:$A$251,$A56) -> 0 | AG56: =SUMIFS(AI$3:AI$77,$A$3:$A$77,$A56) -> 1 | AH56: =IF(SUM(AW56:AZ56)=0,0,IF(SUM(AQ56:AT56)=SUM(AW56:AZ56),1,0)) -> 0 | AI56: 1 | AK56: =SUMIFS(AM$3:AM$251,$A$3:$A$251,$A56) -> 0 | AL56: =SUMIFS(AN$3:AN$251,$A$3:$A$251,$A56) -> 1 | AM56: =IF(SUM(AQ56:AT56)=SUM(AW56:AZ56),1,0) -> 0 | AN56: 1 | AP56: =SUM(AQ56:AT56) -> 0 | AQ56: =IF(OR(E56="",E56="TBD",E56="N/A",E56="SDK",E56="SAAS"),0,1) -> 0 | AR56: =IF(OR(F56="",F56="TBD",F56="N/A",F56="SDK",F56="SAAS"),0,1) -> 0 | AS56: =IF(OR(G56="",G56="TBD",G56="N/A",G56="SDK",G56="SAAS"),0,1) -> 0 | AT56: =IF(OR(H56="",H56="TBD",H56="N/A",H56="SDK",H56="SAAS"),0,1) -> 0 | AV56: =SUM(AW56:AZ56) -> 4 | AW56: =IF(OR(E56="",E56="N/A",E56="SDK",E56="SAAS"),0,1) -> 1 | AX56: =IF(OR(F56="",F56="N/A",F56="SDK",F56="SAAS"),0,1) -> 1 | AY56: =IF(OR(G56="",G56="N/A",G56="SDK",G56="SAAS"),0,1) -> 1 | AZ56: =IF(OR(H56="",H56="N/A",H56="SDK",H56="SAAS"),0,1) -> 1
A57: EX - 001 | B57: Onboarding | C57: Motor de reglas de decisión para flujo de proceso | D57: TBD | E57: TBD | F57: TBD | G57: TBD | H57: TBD | J57: 47 | K57: =J57*$J$147 -> 164.5 | L57: Backlog | M57: Rafael Elizalde | N57: x | V57: Sí | W57: Por definir | AB57: =IF(AG57=0,0,IF(AF57=AG57,1,0))*AD57 -> 0 | AC57: =IF(AK57=AL57,1,0)*AD57 -> 0 | AD57: =IF(ISNUMBER(MATCH(A57,$A$2:A56,0)),0,1) -> 1 | AF57: =SUMIFS(AH$3:AH$251,$A$3:$A$251,$A57) -> 0 | AG57: =SUMIFS(AI$3:AI$77,$A$3:$A$77,$A57) -> 1 | AH57: =IF(SUM(AW57:AZ57)=0,0,IF(SUM(AQ57:AT57)=SUM(AW57:AZ57),1,0)) -> 0 | AI57: 1 | AK57: =SUMIFS(AM$3:AM$251,$A$3:$A$251,$A57) -> 0 | AL57: =SUMIFS(AN$3:AN$251,$A$3:$A$251,$A57) -> 1 | AM57: =IF(SUM(AQ57:AT57)=SUM(AW57:AZ57),1,0) -> 0 | AN57: 1 | AP57: =SUM(AQ57:AT57) -> 0 | AQ57: =IF(OR(E57="",E57="TBD",E57="N/A",E57="SDK",E57="SAAS"),0,1) -> 0 | AR57: =IF(OR(F57="",F57="TBD",F57="N/A",F57="SDK",F57="SAAS"),0,1) -> 0 | AS57: =IF(OR(G57="",G57="TBD",G57="N/A",G57="SDK",G57="SAAS"),0,1) -> 0 | AT57: =IF(OR(H57="",H57="TBD",H57="N/A",H57="SDK",H57="SAAS"),0,1) -> 0 | AV57: =SUM(AW57:AZ57) -> 4 | AW57: =IF(OR(E57="",E57="N/A",E57="SDK",E57="SAAS"),0,1) -> 1 | AX57: =IF(OR(F57="",F57="N/A",F57="SDK",F57="SAAS"),0,1) -> 1 | AY57: =IF(OR(G57="",G57="N/A",G57="SDK",G57="SAAS"),0,1) -> 1 | AZ57: =IF(OR(H57="",H57="N/A",H57="SDK",H57="SAAS"),0,1) -> 1
A58: EX - 002 | B58: Onboarding | C58: Inventario de reglas desacoplado | D58: TBD | E58: TBD | F58: TBD | G58: TBD | H58: TBD | J58: 12 | K58: =J58*$J$147 -> 42 | L58: Backlog | M58: Rafael Elizalde | N58: x | V58: Sí | W58: Por definir | AB58: =IF(AG58=0,0,IF(AF58=AG58,1,0))*AD58 -> 0 | AC58: =IF(AK58=AL58,1,0)*AD58 -> 0 | AD58: =IF(ISNUMBER(MATCH(A58,$A$2:A57,0)),0,1) -> 1 | AF58: =SUMIFS(AH$3:AH$251,$A$3:$A$251,$A58) -> 0 | AG58: =SUMIFS(AI$3:AI$77,$A$3:$A$77,$A58) -> 1 | AH58: =IF(SUM(AW58:AZ58)=0,0,IF(SUM(AQ58:AT58)=SUM(AW58:AZ58),1,0)) -> 0 | AI58: 1 | AK58: =SUMIFS(AM$3:AM$251,$A$3:$A$251,$A58) -> 0 | AL58: =SUMIFS(AN$3:AN$251,$A$3:$A$251,$A58) -> 1 | AM58: =IF(SUM(AQ58:AT58)=SUM(AW58:AZ58),1,0) -> 0 | AN58: 1 | AP58: =SUM(AQ58:AT58) -> 0 | AQ58: =IF(OR(E58="",E58="TBD",E58="N/A",E58="SDK",E58="SAAS"),0,1) -> 0 | AR58: =IF(OR(F58="",F58="TBD",F58="N/A",F58="SDK",F58="SAAS"),0,1) -> 0 | AS58: =IF(OR(G58="",G58="TBD",G58="N/A",G58="SDK",G58="SAAS"),0,1) -> 0 | AT58: =IF(OR(H58="",H58="TBD",H58="N/A",H58="SDK",H58="SAAS"),0,1) -> 0 | AV58: =SUM(AW58:AZ58) -> 4 | AW58: =IF(OR(E58="",E58="N/A",E58="SDK",E58="SAAS"),0,1) -> 1 | AX58: =IF(OR(F58="",F58="N/A",F58="SDK",F58="SAAS"),0,1) -> 1 | AY58: =IF(OR(G58="",G58="N/A",G58="SDK",G58="SAAS"),0,1) -> 1 | AZ58: =IF(OR(H58="",H58="N/A",H58="SDK",H58="SAAS"),0,1) -> 1
A59: EX - 003 | B59: Onboarding | C59: Arboles y tablas de decisión para diseño de reglas | D59: TBD | E59: TBD | F59: TBD | G59: TBD | H59: TBD | K59: =J59*$J$147 -> 0 | L59: Backlog | M59: Rafael Elizalde | N59: x | V59: Sí | W59: Por definir | AB59: =IF(AG59=0,0,IF(AF59=AG59,1,0))*AD59 -> 0 | AC59: =IF(AK59=AL59,1,0)*AD59 -> 0 | AD59: =IF(ISNUMBER(MATCH(A59,$A$2:A58,0)),0,1) -> 1 | AF59: =SUMIFS(AH$3:AH$251,$A$3:$A$251,$A59) -> 0 | AG59: =SUMIFS(AI$3:AI$77,$A$3:$A$77,$A59) -> 1 | AH59: =IF(SUM(AW59:AZ59)=0,0,IF(SUM(AQ59:AT59)=SUM(AW59:AZ59),1,0)) -> 0 | AI59: 1 | AK59: =SUMIFS(AM$3:AM$251,$A$3:$A$251,$A59) -> 0 | AL59: =SUMIFS(AN$3:AN$251,$A$3:$A$251,$A59) -> 1 | AM59: =IF(SUM(AQ59:AT59)=SUM(AW59:AZ59),1,0) -> 0 | AN59: 1 | AP59: =SUM(AQ59:AT59) -> 0 | AQ59: =IF(OR(E59="",E59="TBD",E59="N/A",E59="SDK",E59="SAAS"),0,1) -> 0 | AR59: =IF(OR(F59="",F59="TBD",F59="N/A",F59="SDK",F59="SAAS"),0,1) -> 0 | AS59: =IF(OR(G59="",G59="TBD",G59="N/A",G59="SDK",G59="SAAS"),0,1) -> 0 | AT59: =IF(OR(H59="",H59="TBD",H59="N/A",H59="SDK",H59="SAAS"),0,1) -> 0 | AV59: =SUM(AW59:AZ59) -> 4 | AW59: =IF(OR(E59="",E59="N/A",E59="SDK",E59="SAAS"),0,1) -> 1 | AX59: =IF(OR(F59="",F59="N/A",F59="SDK",F59="SAAS"),0,1) -> 1 | AY59: =IF(OR(G59="",G59="N/A",G59="SDK",G59="SAAS"),0,1) -> 1 | AZ59: =IF(OR(H59="",H59="N/A",H59="SDK",H59="SAAS"),0,1) -> 1
A60: EX - 004 | B60: Onboarding | C60: INTL Buro de credito | D60: TBD | E60: TBD | F60: TBD | G60: TBD | H60: TBD | K60: =J60*$J$147 -> 0 | L60: Backlog | M60: Rafael Elizalde | N60: x | V60: Sí | W60: Por definir | AB60: =IF(AG60=0,0,IF(AF60=AG60,1,0))*AD60 -> 0 | AC60: =IF(AK60=AL60,1,0)*AD60 -> 0 | AD60: =IF(ISNUMBER(MATCH(A60,$A$2:A59,0)),0,1) -> 1 | AF60: =SUMIFS(AH$3:AH$251,$A$3:$A$251,$A60) -> 0 | AG60: =SUMIFS(AI$3:AI$77,$A$3:$A$77,$A60) -> 1 | AH60: =IF(SUM(AW60:AZ60)=0,0,IF(SUM(AQ60:AT60)=SUM(AW60:AZ60),1,0)) -> 0 | AI60: 1 | AK60: =SUMIFS(AM$3:AM$251,$A$3:$A$251,$A60) -> 0 | AL60: =SUMIFS(AN$3:AN$251,$A$3:$A$251,$A60) -> 1 | AM60: =IF(SUM(AQ60:AT60)=SUM(AW60:AZ60),1,0) -> 0 | AN60: 1 | AP60: =SUM(AQ60:AT60) -> 0 | AQ60: =IF(OR(E60="",E60="TBD",E60="N/A",E60="SDK",E60="SAAS"),0,1) -> 0 | AR60: =IF(OR(F60="",F60="TBD",F60="N/A",F60="SDK",F60="SAAS"),0,1) -> 0 | AS60: =IF(OR(G60="",G60="TBD",G60="N/A",G60="SDK",G60="SAAS"),0,1) -> 0 | AT60: =IF(OR(H60="",H60="TBD",H60="N/A",H60="SDK",H60="SAAS"),0,1) -> 0 | AV60: =SUM(AW60:AZ60) -> 4 | AW60: =IF(OR(E60="",E60="N/A",E60="SDK",E60="SAAS"),0,1) -> 1 | AX60: =IF(OR(F60="",F60="N/A",F60="SDK",F60="SAAS"),0,1) -> 1 | AY60: =IF(OR(G60="",G60="N/A",G60="SDK",G60="SAAS"),0,1) -> 1 | AZ60: =IF(OR(H60="",H60="N/A",H60="SDK",H60="SAAS"),0,1) -> 1
A61: WM - 001 | B61: Onboarding | C61: Gestion procesos de negocios via BPF | D61: TBD | E61: TBD | F61: TBD | G61: TBD | H61: TBD | K61: =J61*$J$147 -> 0 | L61: Backlog | M61: Rafael Elizalde | N61: x | V61: Sí | W61: Por definir | AB61: =IF(AG61=0,0,IF(AF61=AG61,1,0))*AD61 -> 0 | AC61: =IF(AK61=AL61,1,0)*AD61 -> 0 | AD61: =IF(ISNUMBER(MATCH(A61,$A$2:A60,0)),0,1) -> 1 | AF61: =SUMIFS(AH$3:AH$251,$A$3:$A$251,$A61) -> 0 | AG61: =SUMIFS(AI$3:AI$77,$A$3:$A$77,$A61) -> 1 | AH61: =IF(SUM(AW61:AZ61)=0,0,IF(SUM(AQ61:AT61)=SUM(AW61:AZ61),1,0)) -> 0 | AI61: 1 | AK61: =SUMIFS(AM$3:AM$251,$A$3:$A$251,$A61) -> 0 | AL61: =SUMIFS(AN$3:AN$251,$A$3:$A$251,$A61) -> 1 | AM61: =IF(SUM(AQ61:AT61)=SUM(AW61:AZ61),1,0) -> 0 | AN61: 1 | AP61: =SUM(AQ61:AT61) -> 0 | AQ61: =IF(OR(E61="",E61="TBD",E61="N/A",E61="SDK",E61="SAAS"),0,1) -> 0 | AR61: =IF(OR(F61="",F61="TBD",F61="N/A",F61="SDK",F61="SAAS"),0,1) -> 0 | AS61: =IF(OR(G61="",G61="TBD",G61="N/A",G61="SDK",G61="SAAS"),0,1) -> 0 | AT61: =IF(OR(H61="",H61="TBD",H61="N/A",H61="SDK",H61="SAAS"),0,1) -> 0 | AV61: =SUM(AW61:AZ61) -> 4 | AW61: =IF(OR(E61="",E61="N/A",E61="SDK",E61="SAAS"),0,1) -> 1 | AX61: =IF(OR(F61="",F61="N/A",F61="SDK",F61="SAAS"),0,1) -> 1 | AY61: =IF(OR(G61="",G61="N/A",G61="SDK",G61="SAAS"),0,1) -> 1 | AZ61: =IF(OR(H61="",H61="N/A",H61="SDK",H61="SAAS"),0,1) -> 1
A62: WM - 002 | B62: Onboarding | C62: Medicion y funnel de usuarios basado en BPMS | D62: TBD | E62: TBD | F62: TBD | G62: TBD | H62: TBD | K62: =J62*$J$147 -> 0 | L62: Backlog | M62: Rafael Elizalde | N62: x | V62: Sí | W62: Por definir | AB62: =IF(AG62=0,0,IF(AF62=AG62,1,0))*AD62 -> 0 | AC62: =IF(AK62=AL62,1,0)*AD62 -> 0 | AD62: =IF(ISNUMBER(MATCH(A62,$A$2:A61,0)),0,1) -> 1 | AF62: =SUMIFS(AH$3:AH$251,$A$3:$A$251,$A62) -> 0 | AG62: =SUMIFS(AI$3:AI$77,$A$3:$A$77,$A62) -> 1 | AH62: =IF(SUM(AW62:AZ62)=0,0,IF(SUM(AQ62:AT62)=SUM(AW62:AZ62),1,0)) -> 0 | AI62: 1 | AK62: =SUMIFS(AM$3:AM$251,$A$3:$A$251,$A62) -> 0 | AL62: =SUMIFS(AN$3:AN$251,$A$3:$A$251,$A62) -> 1 | AM62: =IF(SUM(AQ62:AT62)=SUM(AW62:AZ62),1,0) -> 0 | AN62: 1 | AP62: =SUM(AQ62:AT62) -> 0 | AQ62: =IF(OR(E62="",E62="TBD",E62="N/A",E62="SDK",E62="SAAS"),0,1) -> 0 | AR62: =IF(OR(F62="",F62="TBD",F62="N/A",F62="SDK",F62="SAAS"),0,1) -> 0 | AS62: =IF(OR(G62="",G62="TBD",G62="N/A",G62="SDK",G62="SAAS"),0,1) -> 0 | AT62: =IF(OR(H62="",H62="TBD",H62="N/A",H62="SDK",H62="SAAS"),0,1) -> 0 | AV62: =SUM(AW62:AZ62) -> 4 | AW62: =IF(OR(E62="",E62="N/A",E62="SDK",E62="SAAS"),0,1) -> 1 | AX62: =IF(OR(F62="",F62="N/A",F62="SDK",F62="SAAS"),0,1) -> 1 | AY62: =IF(OR(G62="",G62="N/A",G62="SDK",G62="SAAS"),0,1) -> 1 | AZ62: =IF(OR(H62="",H62="N/A",H62="SDK",H62="SAAS"),0,1) -> 1
A63: WM - 003 | B63: Onboarding | C63: Procesos de negocio desacoplados | D63: TBD | E63: TBD | F63: TBD | G63: TBD | H63: TBD | K63: =J63*$J$147 -> 0 | L63: Backlog | M63: Rafael Elizalde | N63: x | V63: Sí | W63: Por definir | AB63: =IF(AG63=0,0,IF(AF63=AG63,1,0))*AD63 -> 0 | AC63: =IF(AK63=AL63,1,0)*AD63 -> 0 | AD63: =IF(ISNUMBER(MATCH(A63,$A$2:A62,0)),0,1) -> 1 | AF63: =SUMIFS(AH$3:AH$251,$A$3:$A$251,$A63) -> 0 | AG63: =SUMIFS(AI$3:AI$77,$A$3:$A$77,$A63) -> 1 | AH63: =IF(SUM(AW63:AZ63)=0,0,IF(SUM(AQ63:AT63)=SUM(AW63:AZ63),1,0)) -> 0 | AI63: 1 | AK63: =SUMIFS(AM$3:AM$251,$A$3:$A$251,$A63) -> 0 | AL63: =SUMIFS(AN$3:AN$251,$A$3:$A$251,$A63) -> 1 | AM63: =IF(SUM(AQ63:AT63)=SUM(AW63:AZ63),1,0) -> 0 | AN63: 1 | AP63: =SUM(AQ63:AT63) -> 0 | AQ63: =IF(OR(E63="",E63="TBD",E63="N/A",E63="SDK",E63="SAAS"),0,1) -> 0 | AR63: =IF(OR(F63="",F63="TBD",F63="N/A",F63="SDK",F63="SAAS"),0,1) -> 0 | AS63: =IF(OR(G63="",G63="TBD",G63="N/A",G63="SDK",G63="SAAS"),0,1) -> 0 | AT63: =IF(OR(H63="",H63="TBD",H63="N/A",H63="SDK",H63="SAAS"),0,1) -> 0 | AV63: =SUM(AW63:AZ63) -> 4 | AW63: =IF(OR(E63="",E63="N/A",E63="SDK",E63="SAAS"),0,1) -> 1 | AX63: =IF(OR(F63="",F63="N/A",F63="SDK",F63="SAAS"),0,1) -> 1 | AY63: =IF(OR(G63="",G63="N/A",G63="SDK",G63="SAAS"),0,1) -> 1 | AZ63: =IF(OR(H63="",H63="N/A",H63="SDK",H63="SAAS"),0,1) -> 1
A64: WM - 004 | B64: Onboarding | C64: Orquestación de proceso de negocio via BPMS | D64: TBD | E64: TBD | F64: TBD | G64: TBD | H64: TBD | J64: 5 | K64: =J64*$J$147 -> 17.5 | L64: Backlog | M64: Rafael Elizalde | N64: x | V64: Sí | W64: Por definir | AB64: =IF(AG64=0,0,IF(AF64=AG64,1,0))*AD64 -> 0 | AC64: =IF(AK64=AL64,1,0)*AD64 -> 0 | AD64: =IF(ISNUMBER(MATCH(A64,$A$2:A63,0)),0,1) -> 1 | AF64: =SUMIFS(AH$3:AH$251,$A$3:$A$251,$A64) -> 0 | AG64: =SUMIFS(AI$3:AI$77,$A$3:$A$77,$A64) -> 1 | AH64: =IF(SUM(AW64:AZ64)=0,0,IF(SUM(AQ64:AT64)=SUM(AW64:AZ64),1,0)) -> 0 | AI64: 1 | AK64: =SUMIFS(AM$3:AM$251,$A$3:$A$251,$A64) -> 0 | AL64: =SUMIFS(AN$3:AN$251,$A$3:$A$251,$A64) -> 1 | AM64: =IF(SUM(AQ64:AT64)=SUM(AW64:AZ64),1,0) -> 0 | AN64: 1 | AP64: =SUM(AQ64:AT64) -> 0 | AQ64: =IF(OR(E64="",E64="TBD",E64="N/A",E64="SDK",E64="SAAS"),0,1) -> 0 | AR64: =IF(OR(F64="",F64="TBD",F64="N/A",F64="SDK",F64="SAAS"),0,1) -> 0 | AS64: =IF(OR(G64="",G64="TBD",G64="N/A",G64="SDK",G64="SAAS"),0,1) -> 0 | AT64: =IF(OR(H64="",H64="TBD",H64="N/A",H64="SDK",H64="SAAS"),0,1) -> 0 | AV64: =SUM(AW64:AZ64) -> 4 | AW64: =IF(OR(E64="",E64="N/A",E64="SDK",E64="SAAS"),0,1) -> 1 | AX64: =IF(OR(F64="",F64="N/A",F64="SDK",F64="SAAS"),0,1) -> 1 | AY64: =IF(OR(G64="",G64="N/A",G64="SDK",G64="SAAS"),0,1) -> 1 | AZ64: =IF(OR(H64="",H64="N/A",H64="SDK",H64="SAAS"),0,1) -> 1
A65: WM - 005 | B65: Onboarding | C65: Contratos de información canónicos | D65: TBD | E65: TBD | F65: TBD | G65: TBD | H65: TBD | K65: =J65*$J$147 -> 0 | L65: Backlog | M65: Rafael Elizalde | N65: x | V65: Sí | W65: Por definir | AB65: =IF(AG65=0,0,IF(AF65=AG65,1,0))*AD65 -> 0 | AC65: =IF(AK65=AL65,1,0)*AD65 -> 0 | AD65: =IF(ISNUMBER(MATCH(A65,$A$2:A64,0)),0,1) -> 1 | AF65: =SUMIFS(AH$3:AH$251,$A$3:$A$251,$A65) -> 0 | AG65: =SUMIFS(AI$3:AI$77,$A$3:$A$77,$A65) -> 1 | AH65: =IF(SUM(AW65:AZ65)=0,0,IF(SUM(AQ65:AT65)=SUM(AW65:AZ65),1,0)) -> 0 | AI65: 1 | AK65: =SUMIFS(AM$3:AM$251,$A$3:$A$251,$A65) -> 0 | AL65: =SUMIFS(AN$3:AN$251,$A$3:$A$251,$A65) -> 1 | AM65: =IF(SUM(AQ65:AT65)=SUM(AW65:AZ65),1,0) -> 0 | AN65: 1 | AP65: =SUM(AQ65:AT65) -> 0 | AQ65: =IF(OR(E65="",E65="TBD",E65="N/A",E65="SDK",E65="SAAS"),0,1) -> 0 | AR65: =IF(OR(F65="",F65="TBD",F65="N/A",F65="SDK",F65="SAAS"),0,1) -> 0 | AS65: =IF(OR(G65="",G65="TBD",G65="N/A",G65="SDK",G65="SAAS"),0,1) -> 0 | AT65: =IF(OR(H65="",H65="TBD",H65="N/A",H65="SDK",H65="SAAS"),0,1) -> 0 | AV65: =SUM(AW65:AZ65) -> 4 | AW65: =IF(OR(E65="",E65="N/A",E65="SDK",E65="SAAS"),0,1) -> 1 | AX65: =IF(OR(F65="",F65="N/A",F65="SDK",F65="SAAS"),0,1) -> 1 | AY65: =IF(OR(G65="",G65="N/A",G65="SDK",G65="SAAS"),0,1) -> 1 | AZ65: =IF(OR(H65="",H65="N/A",H65="SDK",H65="SAAS"),0,1) -> 1
A66: PiPo - 001 | B66: Onboarding | C66: Dispersión de SMS | D66: TBD | E66: TBD | F66: TBD | G66: TBD | H66: TBD | K66: =J66*$J$147 -> 0 | L66: Backlog | M66: Rafael Elizalde | N66: x | V66: Sí | W66: Por definir | AB66: =IF(AG66=0,0,IF(AF66=AG66,1,0))*AD66 -> 0 | AC66: =IF(AK66=AL66,1,0)*AD66 -> 0 | AD66: =IF(ISNUMBER(MATCH(A66,$A$2:A65,0)),0,1) -> 1 | AF66: =SUMIFS(AH$3:AH$251,$A$3:$A$251,$A66) -> 0 | AG66: =SUMIFS(AI$3:AI$77,$A$3:$A$77,$A66) -> 1 | AH66: =IF(SUM(AW66:AZ66)=0,0,IF(SUM(AQ66:AT66)=SUM(AW66:AZ66),1,0)) -> 0 | AI66: 1 | AK66: =SUMIFS(AM$3:AM$251,$A$3:$A$251,$A66) -> 0 | AL66: =SUMIFS(AN$3:AN$251,$A$3:$A$251,$A66) -> 1 | AM66: =IF(SUM(AQ66:AT66)=SUM(AW66:AZ66),1,0) -> 0 | AN66: 1 | AP66: =SUM(AQ66:AT66) -> 0 | AQ66: =IF(OR(E66="",E66="TBD",E66="N/A",E66="SDK",E66="SAAS"),0,1) -> 0 | AR66: =IF(OR(F66="",F66="TBD",F66="N/A",F66="SDK",F66="SAAS"),0,1) -> 0 | AS66: =IF(OR(G66="",G66="TBD",G66="N/A",G66="SDK",G66="SAAS"),0,1) -> 0 | AT66: =IF(OR(H66="",H66="TBD",H66="N/A",H66="SDK",H66="SAAS"),0,1) -> 0 | AV66: =SUM(AW66:AZ66) -> 4 | AW66: =IF(OR(E66="",E66="N/A",E66="SDK",E66="SAAS"),0,1) -> 1 | AX66: =IF(OR(F66="",F66="N/A",F66="SDK",F66="SAAS"),0,1) -> 1 | AY66: =IF(OR(G66="",G66="N/A",G66="SDK",G66="SAAS"),0,1) -> 1 | AZ66: =IF(OR(H66="",H66="N/A",H66="SDK",H66="SAAS"),0,1) -> 1
A67: PiPo - 002 | B67: Onboarding | C67: Dispersión de Email (Welcome Kit) | D67: TBD | E67: TBD | F67: TBD | G67: TBD | H67: TBD | K67: =J67*$J$147 -> 0 | L67: Backlog | M67: Rafael Elizalde | N67: x | V67: Sí | W67: Por definir | AB67: =IF(AG67=0,0,IF(AF67=AG67,1,0))*AD67 -> 0 | AC67: =IF(AK67=AL67,1,0)*AD67 -> 0 | AD67: =IF(ISNUMBER(MATCH(A67,$A$2:A66,0)),0,1) -> 1 | AF67: =SUMIFS(AH$3:AH$251,$A$3:$A$251,$A67) -> 0 | AG67: =SUMIFS(AI$3:AI$77,$A$3:$A$77,$A67) -> 1 | AH67: =IF(SUM(AW67:AZ67)=0,0,IF(SUM(AQ67:AT67)=SUM(AW67:AZ67),1,0)) -> 0 | AI67: 1 | AK67: =SUMIFS(AM$3:AM$251,$A$3:$A$251,$A67) -> 0 | AL67: =SUMIFS(AN$3:AN$251,$A$3:$A$251,$A67) -> 1 | AM67: =IF(SUM(AQ67:AT67)=SUM(AW67:AZ67),1,0) -> 0 | AN67: 1 | AP67: =SUM(AQ67:AT67) -> 0 | AQ67: =IF(OR(E67="",E67="TBD",E67="N/A",E67="SDK",E67="SAAS"),0,1) -> 0 | AR67: =IF(OR(F67="",F67="TBD",F67="N/A",F67="SDK",F67="SAAS"),0,1) -> 0 | AS67: =IF(OR(G67="",G67="TBD",G67="N/A",G67="SDK",G67="SAAS"),0,1) -> 0 | AT67: =IF(OR(H67="",H67="TBD",H67="N/A",H67="SDK",H67="SAAS"),0,1) -> 0 | AV67: =SUM(AW67:AZ67) -> 4 | AW67: =IF(OR(E67="",E67="N/A",E67="SDK",E67="SAAS"),0,1) -> 1 | AX67: =IF(OR(F67="",F67="N/A",F67="SDK",F67="SAAS"),0,1) -> 1 | AY67: =IF(OR(G67="",G67="N/A",G67="SDK",G67="SAAS"),0,1) -> 1 | AZ67: =IF(OR(H67="",H67="N/A",H67="SDK",H67="SAAS"),0,1) -> 1
A68: EXP - 001 | B68: Onboarding | C68: Modelos de dictamen crediticio | D68: TBD | E68: TBD | F68: TBD | G68: TBD | H68: TBD | K68: =J68*$J$147 -> 0 | L68: Backlog | M68: Rafael Elizalde | N68: x | V68: Sí | W68: Por definir | AB68: =IF(AG68=0,0,IF(AF68=AG68,1,0))*AD68 -> 0 | AC68: =IF(AK68=AL68,1,0)*AD68 -> 0 | AD68: =IF(ISNUMBER(MATCH(A68,$A$2:A67,0)),0,1) -> 1 | AF68: =SUMIFS(AH$3:AH$251,$A$3:$A$251,$A68) -> 0 | AG68: =SUMIFS(AI$3:AI$77,$A$3:$A$77,$A68) -> 1 | AH68: =IF(SUM(AW68:AZ68)=0,0,IF(SUM(AQ68:AT68)=SUM(AW68:AZ68),1,0)) -> 0 | AI68: 1 | AK68: =SUMIFS(AM$3:AM$251,$A$3:$A$251,$A68) -> 0 | AL68: =SUMIFS(AN$3:AN$251,$A$3:$A$251,$A68) -> 1 | AM68: =IF(SUM(AQ68:AT68)=SUM(AW68:AZ68),1,0) -> 0 | AN68: 1 | AP68: =SUM(AQ68:AT68) -> 0 | AQ68: =IF(OR(E68="",E68="TBD",E68="N/A",E68="SDK",E68="SAAS"),0,1) -> 0 | AR68: =IF(OR(F68="",F68="TBD",F68="N/A",F68="SDK",F68="SAAS"),0,1) -> 0 | AS68: =IF(OR(G68="",G68="TBD",G68="N/A",G68="SDK",G68="SAAS"),0,1) -> 0 | AT68: =IF(OR(H68="",H68="TBD",H68="N/A",H68="SDK",H68="SAAS"),0,1) -> 0 | AV68: =SUM(AW68:AZ68) -> 4 | AW68: =IF(OR(E68="",E68="N/A",E68="SDK",E68="SAAS"),0,1) -> 1 | AX68: =IF(OR(F68="",F68="N/A",F68="SDK",F68="SAAS"),0,1) -> 1 | AY68: =IF(OR(G68="",G68="N/A",G68="SDK",G68="SAAS"),0,1) -> 1 | AZ68: =IF(OR(H68="",H68="N/A",H68="SDK",H68="SAAS"),0,1) -> 1
A69: BPC - 001 | B69: Onboarding | C69: Validación de clientes existentes en core de tarjetas | D69: TBD | E69: TBD | F69: TBD | G69: TBD | H69: TBD | K69: =J69*$J$147 -> 0 | L69: Backlog | M69: Rafael Elizalde | N69: x | V69: Sí | W69: Por definir | AB69: =IF(AG69=0,0,IF(AF69=AG69,1,0))*AD69 -> 0 | AC69: =IF(AK69=AL69,1,0)*AD69 -> 0 | AD69: =IF(ISNUMBER(MATCH(A69,$A$2:A68,0)),0,1) -> 1 | AF69: =SUMIFS(AH$3:AH$251,$A$3:$A$251,$A69) -> 0 | AG69: =SUMIFS(AI$3:AI$77,$A$3:$A$77,$A69) -> 1 | AH69: =IF(SUM(AW69:AZ69)=0,0,IF(SUM(AQ69:AT69)=SUM(AW69:AZ69),1,0)) -> 0 | AI69: 1 | AK69: =SUMIFS(AM$3:AM$251,$A$3:$A$251,$A69) -> 0 | AL69: =SUMIFS(AN$3:AN$251,$A$3:$A$251,$A69) -> 1 | AM69: =IF(SUM(AQ69:AT69)=SUM(AW69:AZ69),1,0) -> 0 | AN69: 1 | AP69: =SUM(AQ69:AT69) -> 0 | AQ69: =IF(OR(E69="",E69="TBD",E69="N/A",E69="SDK",E69="SAAS"),0,1) -> 0 | AR69: =IF(OR(F69="",F69="TBD",F69="N/A",F69="SDK",F69="SAAS"),0,1) -> 0 | AS69: =IF(OR(G69="",G69="TBD",G69="N/A",G69="SDK",G69="SAAS"),0,1) -> 0 | AT69: =IF(OR(H69="",H69="TBD",H69="N/A",H69="SDK",H69="SAAS"),0,1) -> 0 | AV69: =SUM(AW69:AZ69) -> 4 | AW69: =IF(OR(E69="",E69="N/A",E69="SDK",E69="SAAS"),0,1) -> 1 | AX69: =IF(OR(F69="",F69="N/A",F69="SDK",F69="SAAS"),0,1) -> 1 | AY69: =IF(OR(G69="",G69="N/A",G69="SDK",G69="SAAS"),0,1) -> 1 | AZ69: =IF(OR(H69="",H69="N/A",H69="SDK",H69="SAAS"),0,1) -> 1
A70: BPC - 002 | B70: Onboarding | C70: Alta de clientes en core de tarjetas | D70: TBD | E70: TBD | F70: TBD | G70: TBD | H70: TBD | K70: =J70*$J$147 -> 0 | L70: Backlog | M70: Rafael Elizalde | N70: x | V70: Sí | W70: Por definir | AB70: =IF(AG70=0,0,IF(AF70=AG70,1,0))*AD70 -> 0 | AC70: =IF(AK70=AL70,1,0)*AD70 -> 0 | AD70: =IF(ISNUMBER(MATCH(A70,$A$2:A69,0)),0,1) -> 1 | AF70: =SUMIFS(AH$3:AH$251,$A$3:$A$251,$A70) -> 0 | AG70: =SUMIFS(AI$3:AI$77,$A$3:$A$77,$A70) -> 1 | AH70: =IF(SUM(AW70:AZ70)=0,0,IF(SUM(AQ70:AT70)=SUM(AW70:AZ70),1,0)) -> 0 | AI70: 1 | AK70: =SUMIFS(AM$3:AM$251,$A$3:$A$251,$A70) -> 0 | AL70: =SUMIFS(AN$3:AN$251,$A$3:$A$251,$A70) -> 1 | AM70: =IF(SUM(AQ70:AT70)=SUM(AW70:AZ70),1,0) -> 0 | AN70: 1 | AP70: =SUM(AQ70:AT70) -> 0 | AQ70: =IF(OR(E70="",E70="TBD",E70="N/A",E70="SDK",E70="SAAS"),0,1) -> 0 | AR70: =IF(OR(F70="",F70="TBD",F70="N/A",F70="SDK",F70="SAAS"),0,1) -> 0 | AS70: =IF(OR(G70="",G70="TBD",G70="N/A",G70="SDK",G70="SAAS"),0,1) -> 0 | AT70: =IF(OR(H70="",H70="TBD",H70="N/A",H70="SDK",H70="SAAS"),0,1) -> 0 | AV70: =SUM(AW70:AZ70) -> 4 | AW70: =IF(OR(E70="",E70="N/A",E70="SDK",E70="SAAS"),0,1) -> 1 | AX70: =IF(OR(F70="",F70="N/A",F70="SDK",F70="SAAS"),0,1) -> 1 | AY70: =IF(OR(G70="",G70="N/A",G70="SDK",G70="SAAS"),0,1) -> 1 | AZ70: =IF(OR(H70="",H70="N/A",H70="SDK",H70="SAAS"),0,1) -> 1
A71: BPC - 003 | B71: Onboarding | C71: Alta de TDC asociada a un cliente BanCoppel | D71: TBD | E71: TBD | F71: TBD | G71: TBD | H71: TBD | K71: =J71*$J$147 -> 0 | L71: Backlog | M71: Rafael Elizalde | N71: x | V71: Sí | W71: En proceso | AB71: =IF(AG71=0,0,IF(AF71=AG71,1,0))*AD71 -> 0 | AC71: =IF(AK71=AL71,1,0)*AD71 -> 0 | AD71: =IF(ISNUMBER(MATCH(A71,$A$2:A70,0)),0,1) -> 1 | AF71: =SUMIFS(AH$3:AH$251,$A$3:$A$251,$A71) -> 0 | AG71: =SUMIFS(AI$3:AI$77,$A$3:$A$77,$A71) -> 1 | AH71: =IF(SUM(AW71:AZ71)=0,0,IF(SUM(AQ71:AT71)=SUM(AW71:AZ71),1,0)) -> 0 | AI71: 1 | AK71: =SUMIFS(AM$3:AM$251,$A$3:$A$251,$A71) -> 0 | AL71: =SUMIFS(AN$3:AN$251,$A$3:$A$251,$A71) -> 1 | AM71: =IF(SUM(AQ71:AT71)=SUM(AW71:AZ71),1,0) -> 0 | AN71: 1 | AP71: =SUM(AQ71:AT71) -> 0 | AQ71: =IF(OR(E71="",E71="TBD",E71="N/A",E71="SDK",E71="SAAS"),0,1) -> 0 | AR71: =IF(OR(F71="",F71="TBD",F71="N/A",F71="SDK",F71="SAAS"),0,1) -> 0 | AS71: =IF(OR(G71="",G71="TBD",G71="N/A",G71="SDK",G71="SAAS"),0,1) -> 0 | AT71: =IF(OR(H71="",H71="TBD",H71="N/A",H71="SDK",H71="SAAS"),0,1) -> 0 | AV71: =SUM(AW71:AZ71) -> 4 | AW71: =IF(OR(E71="",E71="N/A",E71="SDK",E71="SAAS"),0,1) -> 1 | AX71: =IF(OR(F71="",F71="N/A",F71="SDK",F71="SAAS"),0,1) -> 1 | AY71: =IF(OR(G71="",G71="N/A",G71="SDK",G71="SAAS"),0,1) -> 1 | AZ71: =IF(OR(H71="",H71="N/A",H71="SDK",H71="SAAS"),0,1) -> 1
A72: AG - 001 | B72: Onboarding | C72: Exposicion de EndPoint BIAN | D72: SAAS | E72: SAAS | F72: SAAS | G72: SAAS | H72: SAAS | K72: =J72*$J$147 -> 0 | L72: Backlog | M72: Rafael Elizalde | N72: x | V72: Sí | W72: Por definir | AB72: =IF(AG72=0,0,IF(AF72=AG72,1,0))*AD72 -> 0 | AC72: =IF(AK72=AL72,1,0)*AD72 -> 1 | AD72: =IF(ISNUMBER(MATCH(A72,$A$2:A71,0)),0,1) -> 1 | AF72: =SUMIFS(AH$3:AH$251,$A$3:$A$251,$A72) -> 0 | AG72: =SUMIFS(AI$3:AI$77,$A$3:$A$77,$A72) -> 1 | AH72: =IF(SUM(AW72:AZ72)=0,0,IF(SUM(AQ72:AT72)=SUM(AW72:AZ72),1,0)) -> 0 | AI72: 1 | AK72: =SUMIFS(AM$3:AM$251,$A$3:$A$251,$A72) -> 1 | AL72: =SUMIFS(AN$3:AN$251,$A$3:$A$251,$A72) -> 1 | AM72: =IF(SUM(AQ72:AT72)=SUM(AW72:AZ72),1,0) -> 1 | AN72: 1 | AP72: =SUM(AQ72:AT72) -> 0 | AQ72: =IF(OR(E72="",E72="TBD",E72="N/A",E72="SDK",E72="SAAS"),0,1) -> 0 | AR72: =IF(OR(F72="",F72="TBD",F72="N/A",F72="SDK",F72="SAAS"),0,1) -> 0 | AS72: =IF(OR(G72="",G72="TBD",G72="N/A",G72="SDK",G72="SAAS"),0,1) -> 0 | AT72: =IF(OR(H72="",H72="TBD",H72="N/A",H72="SDK",H72="SAAS"),0,1) -> 0 | AV72: =SUM(AW72:AZ72) -> 0 | AW72: =IF(OR(E72="",E72="N/A",E72="SDK",E72="SAAS"),0,1) -> 0 | AX72: =IF(OR(F72="",F72="N/A",F72="SDK",F72="SAAS"),0,1) -> 0 | AY72: =IF(OR(G72="",G72="N/A",G72="SDK",G72="SAAS"),0,1) -> 0 | AZ72: =IF(OR(H72="",H72="N/A",H72="SDK",H72="SAAS"),0,1) -> 0
A73: AG- 002 | B73: Onboarding | C73: API Manager: Permitirá administrar las APIs y sus políticas | D73: SAAS | E73: SAAS | F73: SAAS | G73: SAAS | H73: SAAS | K73: =J73*$J$147 -> 0 | L73: Backlog | M73: Rafael Elizalde | N73: x | V73: Sí | W73: Por definir | AB73: =IF(AG73=0,0,IF(AF73=AG73,1,0))*AD73 -> 0 | AC73: =IF(AK73=AL73,1,0)*AD73 -> 1 | AD73: =IF(ISNUMBER(MATCH(A73,$A$2:A72,0)),0,1) -> 1 | AF73: =SUMIFS(AH$3:AH$251,$A$3:$A$251,$A73) -> 0 | AG73: =SUMIFS(AI$3:AI$77,$A$3:$A$77,$A73) -> 1 | AH73: =IF(SUM(AW73:AZ73)=0,0,IF(SUM(AQ73:AT73)=SUM(AW73:AZ73),1,0)) -> 0 | AI73: 1 | AK73: =SUMIFS(AM$3:AM$251,$A$3:$A$251,$A73) -> 1 | AL73: =SUMIFS(AN$3:AN$251,$A$3:$A$251,$A73) -> 1 | AM73: =IF(SUM(AQ73:AT73)=SUM(AW73:AZ73),1,0) -> 1 | AN73: 1 | AP73: =SUM(AQ73:AT73) -> 0 | AQ73: =IF(OR(E73="",E73="TBD",E73="N/A",E73="SDK",E73="SAAS"),0,1) -> 0 | AR73: =IF(OR(F73="",F73="TBD",F73="N/A",F73="SDK",F73="SAAS"),0,1) -> 0 | AS73: =IF(OR(G73="",G73="TBD",G73="N/A",G73="SDK",G73="SAAS"),0,1) -> 0 | AT73: =IF(OR(H73="",H73="TBD",H73="N/A",H73="SDK",H73="SAAS"),0,1) -> 0 | AV73: =SUM(AW73:AZ73) -> 0 | AW73: =IF(OR(E73="",E73="N/A",E73="SDK",E73="SAAS"),0,1) -> 0 | AX73: =IF(OR(F73="",F73="N/A",F73="SDK",F73="SAAS"),0,1) -> 0 | AY73: =IF(OR(G73="",G73="N/A",G73="SDK",G73="SAAS"),0,1) -> 0 | AZ73: =IF(OR(H73="",H73="N/A",H73="SDK",H73="SAAS"),0,1) -> 0
A74: AG - 003 | B74: Onboarding | C74: Monitoreo & Analítica: Permitirá obtener información sobre el consumo de las APIs | D74: SAAS | E74: SAAS | F74: SAAS | G74: SAAS | H74: SAAS | K74: =J74*$J$147 -> 0 | L74: Backlog | M74: Rafael Elizalde | N74: x | V74: Sí | W74: Por definir | AB74: =IF(AG74=0,0,IF(AF74=AG74,1,0))*AD74 -> 0 | AC74: =IF(AK74=AL74,1,0)*AD74 -> 1 | AD74: =IF(ISNUMBER(MATCH(A74,$A$2:A73,0)),0,1) -> 1 | AF74: =SUMIFS(AH$3:AH$251,$A$3:$A$251,$A74) -> 0 | AG74: =SUMIFS(AI$3:AI$77,$A$3:$A$77,$A74) -> 1 | AH74: =IF(SUM(AW74:AZ74)=0,0,IF(SUM(AQ74:AT74)=SUM(AW74:AZ74),1,0)) -> 0 | AI74: 1 | AK74: =SUMIFS(AM$3:AM$251,$A$3:$A$251,$A74) -> 1 | AL74: =SUMIFS(AN$3:AN$251,$A$3:$A$251,$A74) -> 1 | AM74: =IF(SUM(AQ74:AT74)=SUM(AW74:AZ74),1,0) -> 1 | AN74: 1 | AP74: =SUM(AQ74:AT74) -> 0 | AQ74: =IF(OR(E74="",E74="TBD",E74="N/A",E74="SDK",E74="SAAS"),0,1) -> 0 | AR74: =IF(OR(F74="",F74="TBD",F74="N/A",F74="SDK",F74="SAAS"),0,1) -> 0 | AS74: =IF(OR(G74="",G74="TBD",G74="N/A",G74="SDK",G74="SAAS"),0,1) -> 0 | AT74: =IF(OR(H74="",H74="TBD",H74="N/A",H74="SDK",H74="SAAS"),0,1) -> 0 | AV74: =SUM(AW74:AZ74) -> 0 | AW74: =IF(OR(E74="",E74="N/A",E74="SDK",E74="SAAS"),0,1) -> 0 | AX74: =IF(OR(F74="",F74="N/A",F74="SDK",F74="SAAS"),0,1) -> 0 | AY74: =IF(OR(G74="",G74="N/A",G74="SDK",G74="SAAS"),0,1) -> 0 | AZ74: =IF(OR(H74="",H74="N/A",H74="SDK",H74="SAAS"),0,1) -> 0
A75: MS - 001 | B75: Onboarding | C75: API Manager: Permitirá administrar las APIs y sus políticas | D75: SAAS | E75: SAAS | F75: SAAS | G75: SAAS | H75: SAAS | K75: =J75*$J$147 -> 0 | L75: Backlog | M75: Rafael Elizalde | N75: x | V75: Sí | W75: Por definir | AB75: =IF(AG75=0,0,IF(AF75=AG75,1,0))*AD75 -> 0 | AC75: =IF(AK75=AL75,1,0)*AD75 -> 1 | AD75: =IF(ISNUMBER(MATCH(A75,$A$2:A74,0)),0,1) -> 1 | AF75: =SUMIFS(AH$3:AH$251,$A$3:$A$251,$A75) -> 0 | AG75: =SUMIFS(AI$3:AI$77,$A$3:$A$77,$A75) -> 1 | AH75: =IF(SUM(AW75:AZ75)=0,0,IF(SUM(AQ75:AT75)=SUM(AW75:AZ75),1,0)) -> 0 | AI75: 1 | AK75: =SUMIFS(AM$3:AM$251,$A$3:$A$251,$A75) -> 1 | AL75: =SUMIFS(AN$3:AN$251,$A$3:$A$251,$A75) -> 1 | AM75: =IF(SUM(AQ75:AT75)=SUM(AW75:AZ75),1,0) -> 1 | AN75: 1 | AP75: =SUM(AQ75:AT75) -> 0 | AQ75: =IF(OR(E75="",E75="TBD",E75="N/A",E75="SDK",E75="SAAS"),0,1) -> 0 | AR75: =IF(OR(F75="",F75="TBD",F75="N/A",F75="SDK",F75="SAAS"),0,1) -> 0 | AS75: =IF(OR(G75="",G75="TBD",G75="N/A",G75="SDK",G75="SAAS"),0,1) -> 0 | AT75: =IF(OR(H75="",H75="TBD",H75="N/A",H75="SDK",H75="SAAS"),0,1) -> 0 | AV75: =SUM(AW75:AZ75) -> 0 | AW75: =IF(OR(E75="",E75="N/A",E75="SDK",E75="SAAS"),0,1) -> 0 | AX75: =IF(OR(F75="",F75="N/A",F75="SDK",F75="SAAS"),0,1) -> 0 | AY75: =IF(OR(G75="",G75="N/A",G75="SDK",G75="SAAS"),0,1) -> 0 | AZ75: =IF(OR(H75="",H75="N/A",H75="SDK",H75="SAAS"),0,1) -> 0
A76: MS - 002 | B76: Onboarding | C76: Integración: Permitirá orquestar llamados a servicios internos y externos | D76: SAAS | E76: SAAS | F76: SAAS | G76: SAAS | H76: SAAS | K76: =J76*$J$147 -> 0 | L76: Backlog | M76: Rafael Elizalde | N76: x | V76: Sí | W76: Por definir | AB76: =IF(AG76=0,0,IF(AF76=AG76,1,0))*AD76 -> 0 | AC76: =IF(AK76=AL76,1,0)*AD76 -> 1 | AD76: =IF(ISNUMBER(MATCH(A76,$A$2:A75,0)),0,1) -> 1 | AF76: =SUMIFS(AH$3:AH$251,$A$3:$A$251,$A76) -> 0 | AG76: =SUMIFS(AI$3:AI$77,$A$3:$A$77,$A76) -> 1 | AH76: =IF(SUM(AW76:AZ76)=0,0,IF(SUM(AQ76:AT76)=SUM(AW76:AZ76),1,0)) -> 0 | AI76: 1 | AK76: =SUMIFS(AM$3:AM$251,$A$3:$A$251,$A76) -> 1 | AL76: =SUMIFS(AN$3:AN$251,$A$3:$A$251,$A76) -> 1 | AM76: =IF(SUM(AQ76:AT76)=SUM(AW76:AZ76),1,0) -> 1 | AN76: 1 | AP76: =SUM(AQ76:AT76) -> 0 | AQ76: =IF(OR(E76="",E76="TBD",E76="N/A",E76="SDK",E76="SAAS"),0,1) -> 0 | AR76: =IF(OR(F76="",F76="TBD",F76="N/A",F76="SDK",F76="SAAS"),0,1) -> 0 | AS76: =IF(OR(G76="",G76="TBD",G76="N/A",G76="SDK",G76="SAAS"),0,1) -> 0 | AT76: =IF(OR(H76="",H76="TBD",H76="N/A",H76="SDK",H76="SAAS"),0,1) -> 0 | AV76: =SUM(AW76:AZ76) -> 0 | AW76: =IF(OR(E76="",E76="N/A",E76="SDK",E76="SAAS"),0,1) -> 0 | AX76: =IF(OR(F76="",F76="N/A",F76="SDK",F76="SAAS"),0,1) -> 0 | AY76: =IF(OR(G76="",G76="N/A",G76="SDK",G76="SAAS"),0,1) -> 0 | AZ76: =IF(OR(H76="",H76="N/A",H76="SDK",H76="SAAS"),0,1) -> 0
... A81: YB - 004 | B81: Onboarding | C81: Eliminacion de registros en base de datos YugabyteDB | D81: TBD | E81: TBD | F81: TBD | G81: TBD | H81: TBD | K81: =J81*$J$147 -> 0 | L81: Backlog | M81: Rafael Elizalde | N81: x | V81: Sí | W81: Por definir | AB81: =IF(AG81=0,0,IF(AF81=AG81,1,0))*AD81 -> 0 | AC81: =IF(AK81=AL81,1,0)*AD81 -> 0 | AD81: =IF(ISNUMBER(MATCH(A81,$A$2:A80,0)),0,1) -> 1 | AF81: =SUMIFS(AH$3:AH$251,$A$3:$A$251,$A81) -> 0 | AG81: =SUMIFS(AI$3:AI$77,$A$3:$A$77,$A81) -> 0 | AH81: =IF(SUM(AW81:AZ81)=0,0,IF(SUM(AQ81:AT81)=SUM(AW81:AZ81),1,0)) -> 0 | AI81: 1 | AK81: =SUMIFS(AM$3:AM$251,$A$3:$A$251,$A81) -> 0 | AL81: =SUMIFS(AN$3:AN$251,$A$3:$A$251,$A81) -> 1 | AM81: =IF(SUM(AQ81:AT81)=SUM(AW81:AZ81),1,0) -> 0 | AN81: 1 | AP81: =SUM(AQ81:AT81) -> 0 | AQ81: =IF(OR(E81="",E81="TBD",E81="N/A",E81="SDK",E81="SAAS"),0,1) -> 0 | AR81: =IF(OR(F81="",F81="TBD",F81="N/A",F81="SDK",F81="SAAS"),0,1) -> 0 | AS81: =IF(OR(G81="",G81="TBD",G81="N/A",G81="SDK",G81="SAAS"),0,1) -> 0 | AT81: =IF(OR(H81="",H81="TBD",H81="N/A",H81="SDK",H81="SAAS"),0,1) -> 0 | AV81: =SUM(AW81:AZ81) -> 4 | AW81: =IF(OR(E81="",E81="N/A",E81="SDK",E81="SAAS"),0,1) -> 1 | AX81: =IF(OR(F81="",F81="N/A",F81="SDK",F81="SAAS"),0,1) -> 1 | AY81: =IF(OR(G81="",G81="N/A",G81="SDK",G81="SAAS"),0,1) -> 1 | AZ81: =IF(OR(H81="",H81="N/A",H81="SDK",H81="SAAS"),0,1) -> 1
I146: Total SPL | J146: =SUM(J3:J81) -> 84
I147: Factor | J147: 3.5
I148: Total API's Est. | J148: =J146*3.5 -> 294

Sheet BD_OnboardingSim
F1: Apificación | P1: Canal | X1: Avance de Funcionalidad | AH1: Solo APIS | AM1: TOTAL | AS1: diseñadas | AU1: Dominio | AV1: Sistema | AY1: totales | BA1: Dominio | BB1: Sistema
A2: ID | B2: Tipo | C2: DESCRIPCION | F2: Base | G2: Recepción | H2: Negocio | I2: Dominio | J2: Sistema | K2: APIs proceso actual | L2: SPL proceso actual | M2: APIs Estimadas To Be | N2: Estatus de Api | O2: Responsable | P2: Apolo | Q2: Sucursal | R2: MAD | S2: App | T2: CAT | U2: BPI | V2: BO | W2: ATM | X2: Contemplado MVP | Y2: Estatus | Z2: Comentario | AA2: Fecha Inicio | AB2: Fecha Estimada | AD2: Funcionalidades Totales Habilitadas (SOLO APIS) | AE2: Funcionalidades Totales Habilitadas (diseñadas + SDK+ SAAS) | AF2: Conteo Fx | AH2: totales actuales | AI2: totales esperado | AJ2: Completadas actual | AK2: Completas esperado | AM2: totales actuales | AN2: totales esperado | AO2: Completadas actual | AP2: Completas esperado | AR2: Apis diseñadas total | AS2: Recepción | AT2: Negocio | AU2: Transformación | AV2: Sistema | AX2: Apis diseñadas total | AY2: Recepción | AZ2: Negocio | BA2: Transformación | BB2: Sistema
A3: IC-001 | B3: Onboarding | C3: Capturar la identificación | D3: Digitalización de Identificación (INE) | E3: =VLOOKUP(D3,C:C,1,FALSE) -> #N/A | F3: =VLOOKUP(E3,D3,1,FALSE) -> #N/A | G3: /experience/sales/partyLifecycleManagement/v1/documentation/capture | H3: N/A | I3: /sales/partyLifecycleManagement/v1/documentation/capture | J3: /system/sales/partyLifecycleManagement/v1/documentation/capture | L3: 3 | M3: =L3*$L$147 -> 10.5 | N3: Backlog | O3: Rafael Elizalde | P3: x | X3: Sí | Y3: Por definir | AD3: =IF(AI3=0,0,IF(AH3=AI3,1,0))*AF3 -> 0 | AE3: =IF(AM3=AN3,1,0)*AF3 -> 1 | AF3: =IF(ISNUMBER(MATCH(A3,$A$2:A2,0)),0,1) -> 1 | AH3: =SUMIFS(AJ$3:AJ$251,$A$3:$A$251,$A3) -> 1 | AI3: =SUMIFS(AK$3:AK$251,$A$3:$A$251,$A3) -> 2 | AJ3: =IF(SUM(AY3:BB3)=0,0,IF(SUM(AS3:AV3)=SUM(AY3:BB3),1,0)) -> 1 | AK3: 1 | AM3: =SUMIFS(AO$3:AO$251,$A$3:$A$251,$A3) -> 2 | AN3: =SUMIFS(AP$3:AP$251,$A$3:$A$251,$A3) -> 2 | AO3: =IF(SUM(AS3:AV3)=SUM(AY3:BB3),1,0) -> 1 | AP3: 1 | AR3: =SUM(AS3:AV3) -> 3 | AS3: =IF(OR(G3="",G3="TBD",G3="N/A",G3="SDK",G3="SAAS"),0,1) -> 1 | AT3: =IF(OR(H3="",H3="TBD",H3="N/A",H3="SDK",H3="SAAS"),0,1) -> 0 | AU3: =IF(OR(I3="",I3="TBD",I3="N/A",I3="SDK",I3="SAAS"),0,1) -> 1 | AV3: =IF(OR(J3="",J3="TBD",J3="N/A",J3="SDK",J3="SAAS"),0,1) -> 1 | AX3: =SUM(AY3:BB3) -> 3 | AY3: =IF(OR(G3="",G3="N/A",G3="SDK",G3="SAAS"),0,1) -> 1 | AZ3: =IF(OR(H3="",H3="N/A",H3="SDK",H3="SAAS"),0,1) -> 0 | BA3: =IF(OR(I3="",I3="N/A",I3="SDK",I3="SAAS"),0,1) -> 1 | BB3: =IF(OR(J3="",J3="N/A",J3="SDK",J3="SAAS"),0,1) -> 1
A4: IC-001 | B4: Onboarding | C4: Capturar la identificación | D4: Capacidad de Auto-clasificación de la identificación y retroalimentación en tiempo real (INE, Identificación de Extranjeros, Pasaporte) | E4: =VLOOKUP(D4,C:C,1,FALSE) -> Capacidad de Auto-clasificación de la identificación y retroalimentación en tiempo real (INE, Identificación de Extranjeros, Pasaporte) | F4: SDK | G4: SDK | H4: SDK | I4: SDK | J4: SDK | N4: Backlog | O4: Rafael Elizalde | P4: x | X4: Sí | Y4: Por definir | AD4: =IF(AI4=0,0,IF(AH4=AI4,1,0))*AF4 -> 0 | AE4: =IF(AM4=AN4,1,0)*AF4 -> 0 | AF4: =IF(ISNUMBER(MATCH(A4,$A$2:A3,0)),0,1) -> 0 | AH4: =SUMIFS(AJ$3:AJ$251,$A$3:$A$251,$A4) -> 1 | AI4: =SUMIFS(AK$3:AK$77,$A$3:$A$77,$A4) -> 2 | AJ4: =IF(SUM(AY4:BB4)=0,0,IF(SUM(AS4:AV4)=SUM(AY4:BB4),1,0)) -> 0 | AK4: 1 | AM4: =SUMIFS(AO$3:AO$251,$A$3:$A$251,$A4) -> 2 | AN4: =SUMIFS(AP$3:AP$251,$A$3:$A$251,$A4) -> 2 | AO4: =IF(SUM(AS4:AV4)=SUM(AY4:BB4),1,0) -> 1 | AP4: 1 | AR4: =SUM(AS4:AV4) -> 0 | AS4: =IF(OR(G4="",G4="TBD",G4="N/A",G4="SDK",G4="SAAS"),0,1) -> 0 | AT4: =IF(OR(H4="",H4="TBD",H4="N/A",H4="SDK",H4="SAAS"),0,1) -> 0 | AU4: =IF(OR(I4="",I4="TBD",I4="N/A",I4="SDK",I4="SAAS"),0,1) -> 0 | AV4: =IF(OR(J4="",J4="TBD",J4="N/A",J4="SDK",J4="SAAS"),0,1) -> 0 | AX4: =SUM(AY4:BB4) -> 0 | AY4: =IF(OR(G4="",G4="N/A",G4="SDK",G4="SAAS"),0,1) -> 0 | AZ4: =IF(OR(H4="",H4="N/A",H4="SDK",H4="SAAS"),0,1) -> 0 | BA4: =IF(OR(I4="",I4="N/A",I4="SDK",I4="SAAS"),0,1) -> 0 | BB4: =IF(OR(J4="",J4="N/A",J4="SDK",J4="SAAS"),0,1) -> 0
A5: IC-002 | B5: Onboarding | C5: Capacidad de Auto-clasificación de la identificación y retroalimentación en tiempo real (INE, Identificación de Extranjeros, Pasaporte) | D5: Validar y contrastar el rostro del documento utilizado como documento de identificación en el proceso | E5: =VLOOKUP(D5,C:C,1,FALSE) -> Validar y contrastar el rostro del documento utilizado como documento de identificación en el proceso | F5: SDK | G5: SDK | H5: SDK | I5: SDK | J5: SDK | M5: =L5*$L$147 -> 0 | N5: Backlog | O5: Rafael Elizalde | P5: x | X5: Sí | Y5: Por definir | AD5: =IF(AI5=0,0,IF(AH5=AI5,1,0))*AF5 -> 0 | AE5: =IF(AM5=AN5,1,0)*AF5 -> 1 | AF5: =IF(ISNUMBER(MATCH(A5,$A$2:A3,0)),0,1) -> 1 | AH5: =SUMIFS(AJ$3:AJ$251,$A$3:$A$251,$A5) -> 0 | AI5: =SUMIFS(AK$3:AK$77,$A$3:$A$77,$A5) -> 1 | AJ5: =IF(SUM(AY5:BB5)=0,0,IF(SUM(AS5:AV5)=SUM(AY5:BB5),1,0)) -> 0 | AK5: 1 | AM5: =SUMIFS(AO$3:AO$251,$A$3:$A$251,$A5) -> 1 | AN5: =SUMIFS(AP$3:AP$251,$A$3:$A$251,$A5) -> 1 | AO5: =IF(SUM(AS5:AV5)=SUM(AY5:BB5),1,0) -> 1 | AP5: 1 | AR5: =SUM(AS5:AV5) -> 0 | AS5: =IF(OR(G5="",G5="TBD",G5="N/A",G5="SDK",G5="SAAS"),0,1) -> 0 | AT5: =IF(OR(H5="",H5="TBD",H5="N/A",H5="SDK",H5="SAAS"),0,1) -> 0 | AU5: =IF(OR(I5="",I5="TBD",I5="N/A",I5="SDK",I5="SAAS"),0,1) -> 0 | AV5: =IF(OR(J5="",J5="TBD",J5="N/A",J5="SDK",J5="SAAS"),0,1) -> 0 | AX5: =SUM(AY5:BB5) -> 0 | AY5: =IF(OR(G5="",G5="N/A",G5="SDK",G5="SAAS"),0,1) -> 0 | AZ5: =IF(OR(H5="",H5="N/A",H5="SDK",H5="SAAS"),0,1) -> 0 | BA5: =IF(OR(I5="",I5="N/A",I5="SDK",I5="SAAS"),0,1) -> 0 | BB5: =IF(OR(J5="",J5="N/A",J5="SDK",J5="SAAS"),0,1) -> 0
A6: IC-003 | B6: Onboarding | C6: Validar y contrastar el rostro del documento utilizado como documento de identificación en el proceso | D6: Captura automática el rostro del solicitante / cliente de forma segura e inteligente | E6: =VLOOKUP(D6,C:C,1,FALSE) -> Captura automática el rostro del solicitante / cliente de forma segura e inteligente | G6: /experience/crossChannel/sessionDialogue/v1/customerContactSelfieProcedure/initiate | H6: N/A | I6: /crossChannel/sessionDialogue/v1/customerContactSelfieProcedure/initiate | J6: /system/crossChannel/sessionDialogue/v1/customerContactSessionProcedure/initiate | M6: =L6*$L$147 -> 0 | N6: Backlog | O6: Rafael Elizalde | P6: x | X6: Sí | Y6: Por definir | AD6: =IF(AI6=0,0,IF(AH6=AI6,1,0))*AF6 -> 1 | AE6: =IF(AM6=AN6,1,0)*AF6 -> 1 | AF6: =IF(ISNUMBER(MATCH(A6,$A$2:A5,0)),0,1) -> 1 | AH6: =SUMIFS(AJ$3:AJ$251,$A$3:$A$251,$A6) -> 1 | AI6: =SUMIFS(AK$3:AK$77,$A$3:$A$77,$A6) -> 1 | AJ6: =IF(SUM(AY6:BB6)=0,0,IF(SUM(AS6:AV6)=SUM(AY6:BB6),1,0)) -> 1 | AK6: 1 | AM6: =SUMIFS(AO$3:AO$251,$A$3:$A$251,$A6) -> 1 | AN6: =SUMIFS(AP$3:AP$251,$A$3:$A$251,$A6) -> 1 | AO6: =IF(SUM(AS6:AV6)=SUM(AY6:BB6),1,0) -> 1 | AP6: 1 | AR6: =SUM(AS6:AV6) -> 3 | AS6: =IF(OR(G6="",G6="TBD",G6="N/A",G6="SDK",G6="SAAS"),0,1) -> 1 | AT6: =IF(OR(H6="",H6="TBD",H6="N/A",H6="SDK",H6="SAAS"),0,1) -> 0 | AU6: =IF(OR(I6="",I6="TBD",I6="N/A",I6="SDK",I6="SAAS"),0,1) -> 1 | AV6: =IF(OR(J6="",J6="TBD",J6="N/A",J6="SDK",J6="SAAS"),0,1) -> 1 | AX6: =SUM(AY6:BB6) -> 3 | AY6: =IF(OR(G6="",G6="N/A",G6="SDK",G6="SAAS"),0,1) -> 1 | AZ6: =IF(OR(H6="",H6="N/A",H6="SDK",H6="SAAS"),0,1) -> 0 | BA6: =IF(OR(I6="",I6="N/A",I6="SDK",I6="SAAS"),0,1) -> 1 | BB6: =IF(OR(J6="",J6="N/A",J6="SDK",J6="SAAS"),0,1) -> 1
A7: IC-003 | B7: Onboarding | C7: Validar y contrastar el rostro del documento utilizado como documento de identificación en el proceso | D7: Captura automática el rostro del solicitante / cliente de forma segura e inteligente | F7: SDK | G7: SDK | H7: SDK | I7: SDK | J7: SDK
A8: IC-004 | B8: Onboarding | C8: Captura automática el rostro del solicitante / cliente de forma segura e inteligente | D8: Probar la captura de dirección (OCR comprobante domicilio) | E8: =VLOOKUP(D8,C:C,1,FALSE) -> Probar la captura de dirección (OCR comprobante domicilio) | F8: SDK | G8: SDK | H8: SDK | I8: SDK | J8: SDK | M8: =L8*$L$147 -> 0 | N8: Backlog | O8: Rafael Elizalde | P8: x | X8: Sí | Y8: Por definir | AD8: =IF(AI8=0,0,IF(AH8=AI8,1,0))*AF8 -> 0 | AE8: =IF(AM8=AN8,1,0)*AF8 -> 1 | AF8: =IF(ISNUMBER(MATCH(A8,$A$2:A6,0)),0,1) -> 1 | AH8: =SUMIFS(AJ$3:AJ$251,$A$3:$A$251,$A8) -> 0 | AI8: =SUMIFS(AK$3:AK$77,$A$3:$A$77,$A8) -> 1 | AJ8: =IF(SUM(AY8:BB8)=0,0,IF(SUM(AS8:AV8)=SUM(AY8:BB8),1,0)) -> 0 | AK8: 1 | AM8: =SUMIFS(AO$3:AO$251,$A$3:$A$251,$A8) -> 1 | AN8: =SUMIFS(AP$3:AP$251,$A$3:$A$251,$A8) -> 1 | AO8: =IF(SUM(AS8:AV8)=SUM(AY8:BB8),1,0) -> 1 | AP8: 1 | AR8: =SUM(AS8:AV8) -> 0 | AS8: =IF(OR(G8="",G8="TBD",G8="N/A",G8="SDK",G8="SAAS"),0,1) -> 0 | AT8: =IF(OR(H8="",H8="TBD",H8="N/A",H8="SDK",H8="SAAS"),0,1) -> 0 | AU8: =IF(OR(I8="",I8="TBD",I8="N/A",I8="SDK",I8="SAAS"),0,1) -> 0 | AV8: =IF(OR(J8="",J8="TBD",J8="N/A",J8="SDK",J8="SAAS"),0,1) -> 0 | AX8: =SUM(AY8:BB8) -> 0 | AY8: =IF(OR(G8="",G8="N/A",G8="SDK",G8="SAAS"),0,1) -> 0 | AZ8: =IF(OR(H8="",H8="N/A",H8="SDK",H8="SAAS"),0,1) -> 0 | BA8: =IF(OR(I8="",I8="N/A",I8="SDK",I8="SAAS"),0,1) -> 0 | BB8: =IF(OR(J8="",J8="N/A",J8="SDK",J8="SAAS"),0,1) -> 0
A9: IC-005 | B9: Onboarding | C9: Probar la captura de dirección (OCR comprobante domicilio) | D9: Validar el Celular a través de un OTP enviado por SMS | E9: =VLOOKUP(D9,C:C,1,FALSE) -> Validar el Celular a través de un OTP enviado por SMS | F9: SDK | G9: SDK | H9: SDK | I9: SDK | J9: SDK | M9: =L9*$L$147 -> 0 | N9: Backlog | O9: Rafael Elizalde | P9: x | X9: Sí | Y9: Por definir | AD9: =IF(AI9=0,0,IF(AH9=AI9,1,0))*AF9 -> 0 | AE9: =IF(AM9=AN9,1,0)*AF9 -> 1 | AF9: =IF(ISNUMBER(MATCH(A9,$A$2:A8,0)),0,1) -> 1 | AH9: =SUMIFS(AJ$3:AJ$251,$A$3:$A$251,$A9) -> 0 | AI9: =SUMIFS(AK$3:AK$77,$A$3:$A$77,$A9) -> 1 | AJ9: =IF(SUM(AY9:BB9)=0,0,IF(SUM(AS9:AV9)=SUM(AY9:BB9),1,0)) -> 0 | AK9: 1 | AM9: =SUMIFS(AO$3:AO$251,$A$3:$A$251,$A9) -> 1 | AN9: =SUMIFS(AP$3:AP$251,$A$3:$A$251,$A9) -> 1 | AO9: =IF(SUM(AS9:AV9)=SUM(AY9:BB9),1,0) -> 1 | AP9: 1 | AR9: =SUM(AS9:AV9) -> 0 | AS9: =IF(OR(G9="",G9="TBD",G9="N/A",G9="SDK",G9="SAAS"),0,1) -> 0 | AT9: =IF(OR(H9="",H9="TBD",H9="N/A",H9="SDK",H9="SAAS"),0,1) -> 0 | AU9: =IF(OR(I9="",I9="TBD",I9="N/A",I9="SDK",I9="SAAS"),0,1) -> 0 | AV9: =IF(OR(J9="",J9="TBD",J9="N/A",J9="SDK",J9="SAAS"),0,1) -> 0 | AX9: =SUM(AY9:BB9) -> 0 | AY9: =IF(OR(G9="",G9="N/A",G9="SDK",G9="SAAS"),0,1) -> 0 | AZ9: =IF(OR(H9="",H9="N/A",H9="SDK",H9="SAAS"),0,1) -> 0 | BA9: =IF(OR(I9="",I9="N/A",I9="SDK",I9="SAAS"),0,1) -> 0 | BB9: =IF(OR(J9="",J9="N/A",J9="SDK",J9="SAAS"),0,1) -> 0
A10: IC-006 | B10: Onboarding | C10: Validar el Celular a través de un OTP enviado por SMS | D10: Validar el Email a través de un OTP enviado por correo electrónico | E10: =VLOOKUP(D10,C:C,1,FALSE) -> Validar el Email a través de un OTP enviado por correo electrónico | G10: /experience/salesAndService/v1/onBoardingPhoneParty/evaluate | H10: /channels/v1/onBoardingPhoneParty/evaluate | I10: /crossChannel/sessionDialogue/v1/customerContactSessionProcedure/capture /operationalServices/issuedDeviceAdministration/v1/tokenAssignment/initiate | J10: /system/crossChannel/sessionDialogue/v1/customerContactSessionProcedure/capture /system/operationalServices/issuedDeviceAdministration/v1/tokenAssignment/initiate | L10: 4 | M10: =L10*$L$147 -> 14 | N10: Backlog | O10: Rafael Elizalde | P10: x | X10: Sí | Y10: Por definir | AD10: =IF(AI10=0,0,IF(AH10=AI10,1,0))*AF10 -> 1 | AE10: =IF(AM10=AN10,1,0)*AF10 -> 1 | AF10: =IF(ISNUMBER(MATCH(A10,$A$2:A9,0)),0,1) -> 1 | AH10: =SUMIFS(AJ$3:AJ$251,$A$3:$A$251,$A10) -> 2 | AI10: =SUMIFS(AK$3:AK$77,$A$3:$A$77,$A10) -> 2 | AJ10: =IF(SUM(AY10:BB10)=0,0,IF(SUM(AS10:AV10)=SUM(AY10:BB10),1,0)) -> 1 | AK10: 1 | AM10: =SUMIFS(AO$3:AO$251,$A$3:$A$251,$A10) -> 2 | AN10: =SUMIFS(AP$3:AP$251,$A$3:$A$251,$A10) -> 2 | AO10: =IF(SUM(AS10:AV10)=SUM(AY10:BB10),1,0) -> 1 | AP10: 1 | AR10: =SUM(AS10:AV10) -> 4 | AS10: =IF(OR(G10="",G10="TBD",G10="N/A",G10="SDK",G10="SAAS"),0,1) -> 1 | AT10: =IF(OR(H10="",H10="TBD",H10="N/A",H10="SDK",H10="SAAS"),0,1) -> 1 | AU10: =IF(OR(I10="",I10="TBD",I10="N/A",I10="SDK",I10="SAAS"),0,1) -> 1 | AV10: =IF(OR(J10="",J10="TBD",J10="N/A",J10="SDK",J10="SAAS"),0,1) -> 1 | AX10: =SUM(AY10:BB10) -> 4 | AY10: =IF(OR(G10="",G10="N/A",G10="SDK",G10="SAAS"),0,1) -> 1 | AZ10: =IF(OR(H10="",H10="N/A",H10="SDK",H10="SAAS"),0,1) -> 1 | BA10: =IF(OR(I10="",I10="N/A",I10="SDK",I10="SAAS"),0,1) -> 1 | BB10: =IF(OR(J10="",J10="N/A",J10="SDK",J10="SAAS"),0,1) -> 1
A11: IC-006 | B11: Onboarding | C11: Validar el Celular a través de un OTP enviado por SMS | D11: Extraer la información dentro del documento de identificación (OCR) | E11: =VLOOKUP(D11,C:C,1,FALSE) -> Extraer la información dentro del documento de identificación (OCR) | G11: /experience/operationalservices/issueddeviceadministration/v1/tokenAssignment/evaluate | H11: /customers/v1/ocrDocument/retrieve | I11: /operationalServices/issuedDeviceAdministration/v1/tokenAssignment/evaluate | J11: /system/operationalServices/issuedDeviceAdministration | M11: =L11*$L$147 -> 0 | N11: Backlog | O11: Rafael Elizalde | P11: x | X11: Sí | Y11: Por definir | AD11: =IF(AI11=0,0,IF(AH11=AI11,1,0))*AF11 -> 0 | AE11: =IF(AM11=AN11,1,0)*AF11 -> 0 | AF11: =IF(ISNUMBER(MATCH(A11,$A$2:A10,0)),0,1) -> 0 | AH11: =SUMIFS(AJ$3:AJ$251,$A$3:$A$251,$A11) -> 2 | AI11: =SUMIFS(AK$3:AK$77,$A$3:$A$77,$A11) -> 2 | AJ11: =IF(SUM(AY11:BB11)=0,0,IF(SUM(AS11:AV11)=SUM(AY11:BB11),1,0)) -> 1 | AK11: 1 | AM11: =SUMIFS(AO$3:AO$251,$A$3:$A$251,$A11) -> 2 | AN11: =SUMIFS(AP$3:AP$251,$A$3:$A$251,$A11) -> 2 | AO11: =IF(SUM(AS11:AV11)=SUM(AY11:BB11),1,0) -> 1 | AP11: 1 | AR11: =SUM(AS11:AV11) -> 4 | AS11: =IF(OR(G11="",G11="TBD",G11="N/A",G11="SDK",G11="SAAS"),0,1) -> 1 | AT11: =IF(OR(H11="",H11="TBD",H11="N/A",H11="SDK",H11="SAAS"),0,1) -> 1 | AU11: =IF(OR(I11="",I11="TBD",I11="N/A",I11="SDK",I11="SAAS"),0,1) -> 1 | AV11: =IF(OR(J11="",J11="TBD",J11="N/A",J11="SDK",J11="SAAS"),0,1) -> 1 | AX11: =SUM(AY11:BB11) -> 4 | AY11: =IF(OR(G11="",G11="N/A",G11="SDK",G11="SAAS"),0,1) -> 1 | AZ11: =IF(OR(H11="",H11="N/A",H11="SDK",H11="SAAS"),0,1) -> 1 | BA11: =IF(OR(I11="",I11="N/A",I11="SDK",I11="SAAS"),0,1) -> 1 | BB11: =IF(OR(J11="",J11="N/A",J11="SDK",J11="SAAS"),0,1) -> 1
A12: IC-007 | B12: Onboarding | C12: Validar el Email a través de un OTP enviado por correo electrónico | D12: Validar al prospecto / cliente contra la lista nominal del INE | E12: =VLOOKUP(D12,C:C,1,FALSE) -> Validar al prospecto / cliente contra la lista nominal del INE | G12: /experience/channels/v1/onBoardingEmailParty/evaluate | H12: TBD | I12: TBD | J12: TBD | L12: 2 | M12: =L12*$L$147 -> 7 | N12: Backlog | O12: Rafael Elizalde | P12: x | X12: Sí | Y12: Por definir | AD12: =IF(AI12=0,0,IF(AH12=AI12,1,0))*AF12 -> 0 | AE12: =IF(AM12=AN12,1,0)*AF12 -> 0 | AF12: =IF(ISNUMBER(MATCH(A12,$A$2:A11,0)),0,1) -> 1 | AH12: =SUMIFS(AJ$3:AJ$251,$A$3:$A$251,$A12) -> 0 | AI12: =SUMIFS(AK$3:AK$77,$A$3:$A$77,$A12) -> 1 | AJ12: =IF(SUM(AY12:BB12)=0,0,IF(SUM(AS12:AV12)=SUM(AY12:BB12),1,0)) -> 0 | AK12: 1 | AM12: =SUMIFS(AO$3:AO$251,$A$3:$A$251,$A12) -> 0 | AN12: =SUMIFS(AP$3:AP$251,$A$3:$A$251,$A12) -> 1 | AO12: =IF(SUM(AS12:AV12)=SUM(AY12:BB12),1,0) -> 0 | AP12: 1 | AR12: =SUM(AS12:AV12) -> 1 | AS12: =IF(OR(G12="",G12="TBD",G12="N/A",G12="SDK",G12="SAAS"),0,1) -> 1 | AT12: =IF(OR(H12="",H12="TBD",H12="N/A",H12="SDK",H12="SAAS"),0,1) -> 0 | AU12: =IF(OR(I12="",I12="TBD",I12="N/A",I12="SDK",I12="SAAS"),0,1) -> 0 | AV12: =IF(OR(J12="",J12="TBD",J12="N/A",J12="SDK",J12="SAAS"),0,1) -> 0 | AX12: =SUM(AY12:BB12) -> 4 | AY12: =IF(OR(G12="",G12="N/A",G12="SDK",G12="SAAS"),0,1) -> 1 | AZ12: =IF(OR(H12="",H12="N/A",H12="SDK",H12="SAAS"),0,1) -> 1 | BA12: =IF(OR(I12="",I12="N/A",I12="SDK",I12="SAAS"),0,1) -> 1 | BB12: =IF(OR(J12="",J12="N/A",J12="SDK",J12="SAAS"),0,1) -> 1
A13: IC-008 | B13: Onboarding | C13: Extraer la información dentro del documento de identificación (OCR) | D13: Validar la coincidencia facial contra el INE | E13: =VLOOKUP(D13,C:C,1,FALSE) -> Validar la coincidencia facial contra el INE | G13: /experience/customers/v1/ocrDocument/retrieve | H13: /customers/v1/ocrDocument/retrieve | I13: /sales/partyLifecycleManagement/v1/documentation/execute | J13: /system/sales/partyLifecycleManagement/v1/documentation/execute | L13: 1 | M13: =L13*$L$147 -> 3.5 | N13: Backlog | O13: Rafael Elizalde | P13: x | X13: Sí | Y13: Por definir | AD13: =IF(AI13=0,0,IF(AH13=AI13,1,0))*AF13 -> 0 | AE13: =IF(AM13=AN13,1,0)*AF13 -> 1 | AF13: =IF(ISNUMBER(MATCH(A13,$A$2:A12,0)),0,1) -> 1 | AH13: =SUMIFS(AJ$3:AJ$251,$A$3:$A$251,$A13) -> 1 | AI13: =SUMIFS(AK$3:AK$77,$A$3:$A$77,$A13) -> 2 | AJ13: =IF(SUM(AY13:BB13)=0,0,IF(SUM(AS13:AV13)=SUM(AY13:BB13),1,0)) -> 1 | AK13: 1 | AM13: =SUMIFS(AO$3:AO$251,$A$3:$A$251,$A13) -> 2 | AN13: =SUMIFS(AP$3:AP$251,$A$3:$A$251,$A13) -> 2 | AO13: =IF(SUM(AS13:AV13)=SUM(AY13:BB13),1,0) -> 1 | AP13: 1 | AR13: =SUM(AS13:AV13) -> 4 | AS13: =IF(OR(G13="",G13="TBD",G13="N/A",G13="SDK",G13="SAAS"),0,1) -> 1 | AT13: =IF(OR(H13="",H13="TBD",H13="N/A",H13="SDK",H13="SAAS"),0,1) -> 1 | AU13: =IF(OR(I13="",I13="TBD",I13="N/A",I13="SDK",I13="SAAS"),0,1) -> 1 | AV13: =IF(OR(J13="",J13="TBD",J13="N/A",J13="SDK",J13="SAAS"),0,1) -> 1 | AX13: =SUM(AY13:BB13) -> 4 | AY13: =IF(OR(G13="",G13="N/A",G13="SDK",G13="SAAS"),0,1) -> 1 | AZ13: =IF(OR(H13="",H13="N/A",H13="SDK",H13="SAAS"),0,1) -> 1 | BA13: =IF(OR(I13="",I13="N/A",I13="SDK",I13="SAAS"),0,1) -> 1 | BB13: =IF(OR(J13="",J13="N/A",J13="SDK",J13="SAAS"),0,1) -> 1
A14: IC-008 | B14: Onboarding | C14: Extraer la información dentro del documento de identificación (OCR) | D14: Calcular el RFC del cliente / prospecto | E14: =VLOOKUP(D14,C:C,1,FALSE) -> Calcular el RFC del cliente / prospecto | F14: SDK | G14: SDK | H14: N/A | I14: N/A | J14: N/A | M14: =L14*$L$147 -> 0 | N14: Backlog | O14: Rafael Elizalde | P14: x | X14: Sí | Y14: Por definir | AD14: =IF(AI14=0,0,IF(AH14=AI14,1,0))*AF14 -> 0 | AE14: =IF(AM14=AN14,1,0)*AF14 -> 0 | AF14: =IF(ISNUMBER(MATCH(A14,$A$2:A13,0)),0,1) -> 0 | AH14: =SUMIFS(AJ$3:AJ$251,$A$3:$A$251,$A14) -> 1 | AI14: =SUMIFS(AK$3:AK$77,$A$3:$A$77,$A14) -> 2 | AJ14: =IF(SUM(AY14:BB14)=0,0,IF(SUM(AS14:AV14)=SUM(AY14:BB14),1,0)) -> 0 | AK14: 1 | AM14: =SUMIFS(AO$3:AO$251,$A$3:$A$251,$A14) -> 2 | AN14: =SUMIFS(AP$3:AP$251,$A$3:$A$251,$A14) -> 2 | AO14: =IF(SUM(AS14:AV14)=SUM(AY14:BB14),1,0) -> 1 | AP14: 1 | AR14: =SUM(AS14:AV14) -> 0 | AS14: =IF(OR(G14="",G14="TBD",G14="N/A",G14="SDK",G14="SAAS"),0,1) -> 0 | AT14: =IF(OR(H14="",H14="TBD",H14="N/A",H14="SDK",H14="SAAS"),0,1) -> 0 | AU14: =IF(OR(I14="",I14="TBD",I14="N/A",I14="SDK",I14="SAAS"),0,1) -> 0 | AV14: =IF(OR(J14="",J14="TBD",J14="N/A",J14="SDK",J14="SAAS"),0,1) -> 0 | AX14: =SUM(AY14:BB14) -> 0 | AY14: =IF(OR(G14="",G14="N/A",G14="SDK",G14="SAAS"),0,1) -> 0 | AZ14: =IF(OR(H14="",H14="N/A",H14="SDK",H14="SAAS"),0,1) -> 0 | BA14: =IF(OR(I14="",I14="N/A",I14="SDK",I14="SAAS"),0,1) -> 0 | BB14: =IF(OR(J14="",J14="N/A",J14="SDK",J14="SAAS"),0,1) -> 0
A15: IC-009 | B15: Onboarding | C15: Validar al prospecto / cliente contra la lista nominal del INE | D15: Validar el CURP ante RENAPO | E15: =VLOOKUP(D15,C:C,1,FALSE) -> Validar el CURP ante RENAPO | G15: TBD | H15: TBD | I15: /sales/partyLifecycleManagement/v1/ine/evaluate | J15: /system/sales/partyLifecycleManagement/v1/ine/evaluate | M15: =L15*$L$147 -> 0 | N15: Backlog | O15: Rafael Elizalde | P15: x | X15: Sí | Y15: Por definir | AD15: =IF(AI15=0,0,IF(AH15=AI15,1,0))*AF15 -> 0 | AE15: =IF(AM15=AN15,1,0)*AF15 -> 0 | AF15: =IF(ISNUMBER(MATCH(A15,$A$2:A13,0)),0,1) -> 1 | AH15: =SUMIFS(AJ$3:AJ$251,$A$3:$A$251,$A15) -> 0 | AI15: =SUMIFS(AK$3:AK$77,$A$3:$A$77,$A15) -> 2 | AJ15: =IF(SUM(AY15:BB15)=0,0,IF(SUM(AS15:AV15)=SUM(AY15:BB15),1,0)) -> 0 | AK15: 1 | AM15: =SUMIFS(AO$3:AO$251,$A$3:$A$251,$A15) -> 0 | AN15: =SUMIFS(AP$3:AP$251,$A$3:$A$251,$A15) -> 2 | AO15: =IF(SUM(AS15:AV15)=SUM(AY15:BB15),1,0) -> 0 | AP15: 1 | AR15: =SUM(AS15:AV15) -> 2 | AS15: =IF(OR(G15="",G15="TBD",G15="N/A",G15="SDK",G15="SAAS"),0,1) -> 0 | AT15: =IF(OR(H15="",H15="TBD",H15="N/A",H15="SDK",H15="SAAS"),0,1) -> 0 | AU15: =IF(OR(I15="",I15="TBD",I15="N/A",I15="SDK",I15="SAAS"),0,1) -> 1 | AV15: =IF(OR(J15="",J15="TBD",J15="N/A",J15="SDK",J15="SAAS"),0,1) -> 1 | AX15: =SUM(AY15:BB15) -> 4 | AY15: =IF(OR(G15="",G15="N/A",G15="SDK",G15="SAAS"),0,1) -> 1 | AZ15: =IF(OR(H15="",H15="N/A",H15="SDK",H15="SAAS"),0,1) -> 1 | BA15: =IF(OR(I15="",I15="N/A",I15="SDK",I15="SAAS"),0,1) -> 1 | BB15: =IF(OR(J15="",J15="N/A",J15="SDK",J15="SAAS"),0,1) -> 1
A16: IC-009 | B16: Onboarding | C16: Validar al prospecto / cliente contra la lista nominal del INE | D16: Extraer la información dentro del comprobante de domicilio (OCR) | E16: =VLOOKUP(D16,C:C,1,FALSE) -> Extraer la información dentro del comprobante de domicilio (OCR) | G16: TBD | H16: TBD | I16: /sales/partyLifecycleManagement/v1/ine/retrieve | J16: /system/sales/partyLifecycleManagement/v1/ine/retrieve | M16: =L16*$L$147 -> 0 | N16: Backlog | O16: Rafael Elizalde | P16: x | X16: Sí | Y16: Por definir | AD16: =IF(AI16=0,0,IF(AH16=AI16,1,0))*AF16 -> 0 | AE16: =IF(AM16=AN16,1,0)*AF16 -> 0 | AF16: =IF(ISNUMBER(MATCH(A16,$A$2:A14,0)),0,1) -> 1 | AH16: =SUMIFS(AJ$3:AJ$251,$A$3:$A$251,$A16) -> 0 | AI16: =SUMIFS(AK$3:AK$77,$A$3:$A$77,$A16) -> 2 | AJ16: =IF(SUM(AY16:BB16)=0,0,IF(SUM(AS16:AV16)=SUM(AY16:BB16),1,0)) -> 0 | AK16: 1 | AM16: =SUMIFS(AO$3:AO$251,$A$3:$A$251,$A16) -> 0 | AN16: =SUMIFS(AP$3:AP$251,$A$3:$A$251,$A16) -> 2 | AO16: =IF(SUM(AS16:AV16)=SUM(AY16:BB16),1,0) -> 0 | AP16: 1 | AR16: =SUM(AS16:AV16) -> 2 | AS16: =IF(OR(G16="",G16="TBD",G16="N/A",G16="SDK",G16="SAAS"),0,1) -> 0 | AT16: =IF(OR(H16="",H16="TBD",H16="N/A",H16="SDK",H16="SAAS"),0,1) -> 0 | AU16: =IF(OR(I16="",I16="TBD",I16="N/A",I16="SDK",I16="SAAS"),0,1) -> 1 | AV16: =IF(OR(J16="",J16="TBD",J16="N/A",J16="SDK",J16="SAAS"),0,1) -> 1 | AX16: =SUM(AY16:BB16) -> 4 | AY16: =IF(OR(G16="",G16="N/A",G16="SDK",G16="SAAS"),0,1) -> 1 | AZ16: =IF(OR(H16="",H16="N/A",H16="SDK",H16="SAAS"),0,1) -> 1 | BA16: =IF(OR(I16="",I16="N/A",I16="SDK",I16="SAAS"),0,1) -> 1 | BB16: =IF(OR(J16="",J16="N/A",J16="SDK",J16="SAAS"),0,1) -> 1
A17: IC-010 | B17: Onboarding | C17: Validar la coincidencia facial contra el INE | D17: Validar la coincidencia facial contra la identificación (1:1) (Enrolamiento) | E17: x | G17: /experience/CrossChannel/SessionDialogue/v1/customerContactSelfieProcedure/initiate | M17: =L17*$L$147 -> 0 | N17: Backlog | O17: Rafael Elizalde | P17: x | X17: Sí | Y17: Por definir | AD17: =IF(AI17=0,0,IF(AH17=AI17,1,0))*AF17 -> 1 | AE17: =IF(AM17=AN17,1,0)*AF17 -> 1 | AF17: =IF(ISNUMBER(MATCH(A17,$A$2:A15,0)),0,1) -> 1 | AH17: =SUMIFS(AJ$3:AJ$251,$A$3:$A$251,$A17) -> 1 | AI17: =SUMIFS(AK$3:AK$77,$A$3:$A$77,$A17) -> 1 | AJ17: =IF(SUM(AY17:BB17)=0,0,IF(SUM(AS17:AV17)=SUM(AY17:BB17),1,0)) -> 1 | AK17: 1 | AM17: =SUMIFS(AO$3:AO$251,$A$3:$A$251,$A17) -> 1 | AN17: =SUMIFS(AP$3:AP$251,$A$3:$A$251,$A17) -> 1 | AO17: =IF(SUM(AS17:AV17)=SUM(AY17:BB17),1,0) -> 1 | AP17: 1 | AR17: =SUM(AS17:AV17) -> 1 | AS17: =IF(OR(G17="",G17="TBD",G17="N/A",G17="SDK",G17="SAAS"),0,1) -> 1 | AT17: =IF(OR(H17="",H17="TBD",H17="N/A",H17="SDK",H17="SAAS"),0,1) -> 0 | AU17: =IF(OR(I17="",I17="TBD",I17="N/A",I17="SDK",I17="SAAS"),0,1) -> 0 | AV17: =IF(OR(J17="",J17="TBD",J17="N/A",J17="SDK",J17="SAAS"),0,1) -> 0 | AX17: =SUM(AY17:BB17) -> 1 | AY17: =IF(OR(G17="",G17="N/A",G17="SDK",G17="SAAS"),0,1) -> 1 | AZ17: =IF(OR(H17="",H17="N/A",H17="SDK",H17="SAAS"),0,1) -> 0 | BA17: =IF(OR(I17="",I17="N/A",I17="SDK",I17="SAAS"),0,1) -> 0 | BB17: =IF(OR(J17="",J17="N/A",J17="SDK",J17="SAAS"),0,1) -> 0
A18: IC-011 | B18: Onboarding | C18: Calcular el RFC del cliente / prospecto | D18: Reconocimiento facial 1:N para evitar duplicidades (Enrolamiento) | E18: x | G18: N/A | H18: N/A | I18: /sales/partyLifecycleManagement/v1/rfc/evaluate | J18: /system/sales/partyLifecycleManagement/v1/rfc/evaluate | L18: 1 | M18: =L18*$L$147 -> 3.5 | N18: Backlog | O18: Rafael Elizalde | P18: x | X18: Sí | Y18: Por definir | AD18: =IF(AI18=0,0,IF(AH18=AI18,1,0))*AF18 -> 1 | AE18: =IF(AM18=AN18,1,0)*AF18 -> 1 | AF18: =IF(ISNUMBER(MATCH(A18,$A$2:A17,0)),0,1) -> 1 | AH18: =SUMIFS(AJ$3:AJ$251,$A$3:$A$251,$A18) -> 1 | AI18: =SUMIFS(AK$3:AK$77,$A$3:$A$77,$A18) -> 1 | AJ18: =IF(SUM(AY18:BB18)=0,0,IF(SUM(AS18:AV18)=SUM(AY18:BB18),1,0)) -> 1 | AK18: 1 | AM18: =SUMIFS(AO$3:AO$251,$A$3:$A$251,$A18) -> 1 | AN18: =SUMIFS(AP$3:AP$251,$A$3:$A$251,$A18) -> 1 | AO18: =IF(SUM(AS18:AV18)=SUM(AY18:BB18),1,0) -> 1 | AP18: 1 | AR18: =SUM(AS18:AV18) -> 2 | AS18: =IF(OR(G18="",G18="TBD",G18="N/A",G18="SDK",G18="SAAS"),0,1) -> 0 | AT18: =IF(OR(H18="",H18="TBD",H18="N/A",H18="SDK",H18="SAAS"),0,1) -> 0 | AU18: =IF(OR(I18="",I18="TBD",I18="N/A",I18="SDK",I18="SAAS"),0,1) -> 1 | AV18: =IF(OR(J18="",J18="TBD",J18="N/A",J18="SDK",J18="SAAS"),0,1) -> 1 | AX18: =SUM(AY18:BB18) -> 2 | AY18: =IF(OR(G18="",G18="N/A",G18="SDK",G18="SAAS"),0,1) -> 0 | AZ18: =IF(OR(H18="",H18="N/A",H18="SDK",H18="SAAS"),0,1) -> 0 | BA18: =IF(OR(I18="",I18="N/A",I18="SDK",I18="SAAS"),0,1) -> 1 | BB18: =IF(OR(J18="",J18="N/A",J18="SDK",J18="SAAS"),0,1) -> 1
A19: IC-012 | B19: Onboarding | C19: Validar el CURP ante RENAPO | D19: Validación de Personas Políticamente Expuestas (PPEs), Listas Negras Internacionales y locales, así como otras listas de bloqueo | E19: =VLOOKUP(D19,C:C,1,FALSE) -> #N/A | G19: N/A | H19: N/A | I19: /sales/partyLifecycleManagement/v1/renapo/{curp}/retrieve | J19: /system/sales/partyLifecycleManagement/v1/renapo/{curp}/retrieve | L19: 1 | M19: =L19*$L$147 -> 3.5 | N19: Backlog | O19: Rafael Elizalde | P19: x | X19: Sí | Y19: Por definir | AD19: =IF(AI19=0,0,IF(AH19=AI19,1,0))*AF19 -> 1 | AE19: =IF(AM19=AN19,1,0)*AF19 -> 1 | AF19: =IF(ISNUMBER(MATCH(A19,$A$2:A18,0)),0,1) -> 1 | AH19: =SUMIFS(AJ$3:AJ$251,$A$3:$A$251,$A19) -> 1 | AI19: =SUMIFS(AK$3:AK$77,$A$3:$A$77,$A19) -> 1 | AJ19: =IF(SUM(AY19:BB19)=0,0,IF(SUM(AS19:AV19)=SUM(AY19:BB19),1,0)) -> 1 | AK19: 1 | AM19: =SUMIFS(AO$3:AO$251,$A$3:$A$251,$A19) -> 1 | AN19: =SUMIFS(AP$3:AP$251,$A$3:$A$251,$A19) -> 1 | AO19: =IF(SUM(AS19:AV19)=SUM(AY19:BB19),1,0) -> 1 | AP19: 1 | AR19: =SUM(AS19:AV19) -> 2 | AS19: =IF(OR(G19="",G19="TBD",G19="N/A",G19="SDK",G19="SAAS"),0,1) -> 0 | AT19: =IF(OR(H19="",H19="TBD",H19="N/A",H19="SDK",H19="SAAS"),0,1) -> 0 | AU19: =IF(OR(I19="",I19="TBD",I19="N/A",I19="SDK",I19="SAAS"),0,1) -> 1 | AV19: =IF(OR(J19="",J19="TBD",J19="N/A",J19="SDK",J19="SAAS"),0,1) -> 1 | AX19: =SUM(AY19:BB19) -> 2 | AY19: =IF(OR(G19="",G19="N/A",G19="SDK",G19="SAAS"),0,1) -> 0 | AZ19: =IF(OR(H19="",H19="N/A",H19="SDK",H19="SAAS"),0,1) -> 0 | BA19: =IF(OR(I19="",I19="N/A",I19="SDK",I19="SAAS"),0,1) -> 1 | BB19: =IF(OR(J19="",J19="N/A",J19="SDK",J19="SAAS"),0,1) -> 1
A20: IC-013 | B20: Onboarding | C20: Extraer la información dentro del comprobante de domicilio (OCR) | D20: Obtener la Dirección IP del dispositivo en donde se está ejecutando el proceso | E20: =VLOOKUP(D20,C:C,1,FALSE) -> Obtener la Dirección IP del dispositivo en donde se está ejecutando el proceso | G20: /experience/customers/v1/ocrDocument/retrieve | H20: /customers/v1/ocrDocument/retrieve | I20: /sales/partyLifecycleManagement/v1/documentation/execute | J20: /system/sales/partyLifecycleManagement/v1/documentation/execute | M20: =L20*$L$147 -> 0 | N20: Backlog | O20: Rafael Elizalde | P20: x | X20: Sí | Y20: Por definir | AD20: =IF(AI20=0,0,IF(AH20=AI20,1,0))*AF20 -> 1 | AE20: =IF(AM20=AN20,1,0)*AF20 -> 1 | AF20: =IF(ISNUMBER(MATCH(A20,$A$2:A19,0)),0,1) -> 1 | AH20: =SUMIFS(AJ$3:AJ$251,$A$3:$A$251,$A20) -> 1 | AI20: =SUMIFS(AK$3:AK$77,$A$3:$A$77,$A20) -> 1 | AJ20: =IF(SUM(AY20:BB20)=0,0,IF(SUM(AS20:AV20)=SUM(AY20:BB20),1,0)) -> 1 | AK20: 1 | AM20: =SUMIFS(AO$3:AO$251,$A$3:$A$251,$A20) -> 1 | AN20: =SUMIFS(AP$3:AP$251,$A$3:$A$251,$A20) -> 1 | AO20: =IF(SUM(AS20:AV20)=SUM(AY20:BB20),1,0) -> 1 | AP20: 1 | AR20: =SUM(AS20:AV20) -> 4 | AS20: =IF(OR(G20="",G20="TBD",G20="N/A",G20="SDK",G20="SAAS"),0,1) -> 1 | AT20: =IF(OR(H20="",H20="TBD",H20="N/A",H20="SDK",H20="SAAS"),0,1) -> 1 | AU20: =IF(OR(I20="",I20="TBD",I20="N/A",I20="SDK",I20="SAAS"),0,1) -> 1 | AV20: =IF(OR(J20="",J20="TBD",J20="N/A",J20="SDK",J20="SAAS"),0,1) -> 1 | AX20: =SUM(AY20:BB20) -> 4 | AY20: =IF(OR(G20="",G20="N/A",G20="SDK",G20="SAAS"),0,1) -> 1 | AZ20: =IF(OR(H20="",H20="N/A",H20="SDK",H20="SAAS"),0,1) -> 1 | BA20: =IF(OR(I20="",I20="N/A",I20="SDK",I20="SAAS"),0,1) -> 1 | BB20: =IF(OR(J20="",J20="N/A",J20="SDK",J20="SAAS"),0,1) -> 1
A21: IC-016 | B21: Onboarding | C21: Validar la coincidencia facial contra la identificación (1:1) | D21: Obtener la Geolocalización (longitud y altitud) | E21: =VLOOKUP(D21,C:C,1,FALSE) -> Obtener la Geolocalización (longitud y altitud) | F21: SDK | G21: SDK | H21: SDK | I21: SDK | J21: SDK | M21: =L21*$L$147 -> 0 | N21: Backlog | O21: Rafael Elizalde | P21: x | X21: Sí | Y21: Por definir | AD21: =IF(AI21=0,0,IF(AH21=AI21,1,0))*AF21 -> 0 | AE21: =IF(AM21=AN21,1,0)*AF21 -> 1 | AF21: =IF(ISNUMBER(MATCH(A21,$A$2:A20,0)),0,1) -> 1 | AH21: =SUMIFS(AJ$3:AJ$251,$A$3:$A$251,$A21) -> 0 | AI21: =SUMIFS(AK$3:AK$77,$A$3:$A$77,$A21) -> 1 | AJ21: =IF(SUM(AY21:BB21)=0,0,IF(SUM(AS21:AV21)=SUM(AY21:BB21),1,0)) -> 0 | AK21: 1 | AM21: =SUMIFS(AO$3:AO$251,$A$3:$A$251,$A21) -> 1 | AN21: =SUMIFS(AP$3:AP$251,$A$3:$A$251,$A21) -> 1 | AO21: =IF(SUM(AS21:AV21)=SUM(AY21:BB21),1,0) -> 1 | AP21: 1 | AR21: =SUM(AS21:AV21) -> 0 | AS21: =IF(OR(G21="",G21="TBD",G21="N/A",G21="SDK",G21="SAAS"),0,1) -> 0 | AT21: =IF(OR(H21="",H21="TBD",H21="N/A",H21="SDK",H21="SAAS"),0,1) -> 0 | AU21: =IF(OR(I21="",I21="TBD",I21="N/A",I21="SDK",I21="SAAS"),0,1) -> 0 | AV21: =IF(OR(J21="",J21="TBD",J21="N/A",J21="SDK",J21="SAAS"),0,1) -> 0 | AX21: =SUM(AY21:BB21) -> 0 | AY21: =IF(OR(G21="",G21="N/A",G21="SDK",G21="SAAS"),0,1) -> 0 | AZ21: =IF(OR(H21="",H21="N/A",H21="SDK",H21="SAAS"),0,1) -> 0 | BA21: =IF(OR(I21="",I21="N/A",I21="SDK",I21="SAAS"),0,1) -> 0 | BB21: =IF(OR(J21="",J21="N/A",J21="SDK",J21="SAAS"),0,1) -> 0
A22: IC-017 | B22: Onboarding | C22: Reconocimiento facial 1:N para evitar duplicidades | D22: Generar el Hash ID del dispositivo | E22: =VLOOKUP(D22,C:C,1,FALSE) -> Generar el Hash ID del dispositivo | F22: SDK | G22: SDK | H22: SDK | I22: SDK | J22: SDK | M22: =L22*$L$147 -> 0 | N22: Backlog | O22: Rafael Elizalde | P22: x | X22: Sí | Y22: Por definir | AD22: =IF(AI22=0,0,IF(AH22=AI22,1,0))*AF22 -> 0 | AE22: =IF(AM22=AN22,1,0)*AF22 -> 1 | AF22: =IF(ISNUMBER(MATCH(A22,$A$2:A21,0)),0,1) -> 1 | AH22: =SUMIFS(AJ$3:AJ$251,$A$3:$A$251,$A22) -> 0 | AI22: =SUMIFS(AK$3:AK$77,$A$3:$A$77,$A22) -> 1 | AJ22: =IF(SUM(AY22:BB22)=0,0,IF(SUM(AS22:AV22)=SUM(AY22:BB22),1,0)) -> 0 | AK22: 1 | AM22: =SUMIFS(AO$3:AO$251,$A$3:$A$251,$A22) -> 1 | AN22: =SUMIFS(AP$3:AP$251,$A$3:$A$251,$A22) -> 1 | AO22: =IF(SUM(AS22:AV22)=SUM(AY22:BB22),1,0) -> 1 | AP22: 1 | AR22: =SUM(AS22:AV22) -> 0 | AS22: =IF(OR(G22="",G22="TBD",G22="N/A",G22="SDK",G22="SAAS"),0,1) -> 0 | AT22: =IF(OR(H22="",H22="TBD",H22="N/A",H22="SDK",H22="SAAS"),0,1) -> 0 | AU22: =IF(OR(I22="",I22="TBD",I22="N/A",I22="SDK",I22="SAAS"),0,1) -> 0 | AV22: =IF(OR(J22="",J22="TBD",J22="N/A",J22="SDK",J22="SAAS"),0,1) -> 0 | AX22: =SUM(AY22:BB22) -> 0 | AY22: =IF(OR(G22="",G22="N/A",G22="SDK",G22="SAAS"),0,1) -> 0 | AZ22: =IF(OR(H22="",H22="N/A",H22="SDK",H22="SAAS"),0,1) -> 0 | BA22: =IF(OR(I22="",I22="N/A",I22="SDK",I22="SAAS"),0,1) -> 0 | BB22: =IF(OR(J22="",J22="N/A",J22="SDK",J22="SAAS"),0,1) -> 0
A23: IC-018 | B23: Onboarding | C23: Validación de Personas Políticamentes Expuestas (PPEs), Listas negras internacionales y locales, así como otras listas de bloqueo | D23: Generar la videograbación como parte de la prueba de vida (Video Selfie) | E23: =VLOOKUP(D23,C:C,1,FALSE) -> Generar la videograbación como parte de la prueba de vida (Video Selfie) | G23: /experience/Customers/v1/onboardingPartySuitability/evaluate | H23: /customers/v1/onboardingPartySuitability/evaluate | I23: /sales/partyLifecycleManagement/v1/qualification/retrieve | J23: /system/sales/partyLifecycleManagement/v1/qualification/retrieve | L23: 6 | M23: =L23*$L$147 -> 21 | N23: Backlog | O23: Rafael Elizalde | P23: x | X23: Sí | Y23: Por definir | AD23: =IF(AI23=0,0,IF(AH23=AI23,1,0))*AF23 -> 1 | AE23: =IF(AM23=AN23,1,0)*AF23 -> 1 | AF23: =IF(ISNUMBER(MATCH(A23,$A$2:A22,0)),0,1) -> 1 | AH23: =SUMIFS(AJ$3:AJ$251,$A$3:$A$251,$A23) -> 1 | AI23: =SUMIFS(AK$3:AK$77,$A$3:$A$77,$A23) -> 1 | AJ23: =IF(SUM(AY23:BB23)=0,0,IF(SUM(AS23:AV23)=SUM(AY23:BB23),1,0)) -> 1 | AK23: 1 | AM23: =SUMIFS(AO$3:AO$251,$A$3:$A$251,$A23) -> 1 | AN23: =SUMIFS(AP$3:AP$251,$A$3:$A$251,$A23) -> 1 | AO23: =IF(SUM(AS23:AV23)=SUM(AY23:BB23),1,0) -> 1 | AP23: 1 | AR23: =SUM(AS23:AV23) -> 4 | AS23: =IF(OR(G23="",G23="TBD",G23="N/A",G23="SDK",G23="SAAS"),0,1) -> 1 | AT23: =IF(OR(H23="",H23="TBD",H23="N/A",H23="SDK",H23="SAAS"),0,1) -> 1 | AU23: =IF(OR(I23="",I23="TBD",I23="N/A",I23="SDK",I23="SAAS"),0,1) -> 1 | AV23: =IF(OR(J23="",J23="TBD",J23="N/A",J23="SDK",J23="SAAS"),0,1) -> 1 | AX23: =SUM(AY23:BB23) -> 4 | AY23: =IF(OR(G23="",G23="N/A",G23="SDK",G23="SAAS"),0,1) -> 1 | AZ23: =IF(OR(H23="",H23="N/A",H23="SDK",H23="SAAS"),0,1) -> 1 | BA23: =IF(OR(I23="",I23="N/A",I23="SDK",I23="SAAS"),0,1) -> 1 | BB23: =IF(OR(J23="",J23="N/A",J23="SDK",J23="SAAS"),0,1) -> 1
A24: IC-019 | B24: Onboarding | C24: Obtener la Dirección IP del dispositivo en donde se está ejecutando el proceso | D24: Firma del contrato (No Repudio) | E24: =VLOOKUP(D24,C:C,1,FALSE) -> #N/A | G24: /experience/channels/v1/onBoardingParty/initiate | H24: /salesAndService/v1/onBoardingParty/initiate | I24: /crossChannel/sessionDialogue/v1/customerContactSessionProcedure/initiate | M24: =L24*$L$147 -> 0 | N24: Backlog | O24: Rafael Elizalde | P24: x | X24: Sí | Y24: Por definir | AD24: =IF(AI24=0,0,IF(AH24=AI24,1,0))*AF24 -> 1 | AE24: =IF(AM24=AN24,1,0)*AF24 -> 1 | AF24: =IF(ISNUMBER(MATCH(A24,$A$2:A23,0)),0,1) -> 1 | AH24: =SUMIFS(AJ$3:AJ$251,$A$3:$A$251,$A24) -> 1 | AI24: =SUMIFS(AK$3:AK$77,$A$3:$A$77,$A24) -> 1 | AJ24: =IF(SUM(AY24:BB24)=0,0,IF(SUM(AS24:AV24)=SUM(AY24:BB24),1,0)) -> 1 | AK24: 1 | AM24: =SUMIFS(AO$3:AO$251,$A$3:$A$251,$A24) -> 1 | AN24: =SUMIFS(AP$3:AP$251,$A$3:$A$251,$A24) -> 1 | AO24: =IF(SUM(AS24:AV24)=SUM(AY24:BB24),1,0) -> 1 | AP24: 1 | AR24: =SUM(AS24:AV24) -> 3 | AS24: =IF(OR(G24="",G24="TBD",G24="N/A",G24="SDK",G24="SAAS"),0,1) -> 1 | AT24: =IF(OR(H24="",H24="TBD",H24="N/A",H24="SDK",H24="SAAS"),0,1) -> 1 | AU24: =IF(OR(I24="",I24="TBD",I24="N/A",I24="SDK",I24="SAAS"),0,1) -> 1 | AV24: =IF(OR(J24="",J24="TBD",J24="N/A",J24="SDK",J24="SAAS"),0,1) -> 0 | AX24: =SUM(AY24:BB24) -> 3 | AY24: =IF(OR(G24="",G24="N/A",G24="SDK",G24="SAAS"),0,1) -> 1 | AZ24: =IF(OR(H24="",H24="N/A",H24="SDK",H24="SAAS"),0,1) -> 1 | BA24: =IF(OR(I24="",I24="N/A",I24="SDK",I24="SAAS"),0,1) -> 1 | BB24: =IF(OR(J24="",J24="N/A",J24="SDK",J24="SAAS"),0,1) -> 0
A25: IC-020 | B25: Onboarding | C25: Obtener la Geolocalización (longitud y altitud) | D25: Firma con NOM 151 | E25: =VLOOKUP(D25,C:C,1,FALSE) -> #N/A | G25: /experience/channels/v1/onBoardingParty/initiate | H25: /salesAndService/v1/onBoardingParty/initiate | I25: /crossChannel/sessionDialogue/v1/customerContactSessionProcedure/initiate | M25: =L25*$L$147 -> 0 | N25: Backlog | O25: Rafael Elizalde | P25: x | X25: Sí | Y25: Por definir | AD25: =IF(AI25=0,0,IF(AH25=AI25,1,0))*AF25 -> 1 | AE25: =IF(AM25=AN25,1,0)*AF25 -> 1 | AF25: =IF(ISNUMBER(MATCH(A25,$A$2:A24,0)),0,1) -> 1 | AH25: =SUMIFS(AJ$3:AJ$251,$A$3:$A$251,$A25) -> 1 | AI25: =SUMIFS(AK$3:AK$77,$A$3:$A$77,$A25) -> 1 | AJ25: =IF(SUM(AY25:BB25)=0,0,IF(SUM(AS25:AV25)=SUM(AY25:BB25),1,0)) -> 1 | AK25: 1 | AM25: =SUMIFS(AO$3:AO$251,$A$3:$A$251,$A25) -> 1 | AN25: =SUMIFS(AP$3:AP$251,$A$3:$A$251,$A25) -> 1 | AO25: =IF(SUM(AS25:AV25)=SUM(AY25:BB25),1,0) -> 1 | AP25: 1 | AR25: =SUM(AS25:AV25) -> 3 | AS25: =IF(OR(G25="",G25="TBD",G25="N/A",G25="SDK",G25="SAAS"),0,1) -> 1 | AT25: =IF(OR(H25="",H25="TBD",H25="N/A",H25="SDK",H25="SAAS"),0,1) -> 1 | AU25: =IF(OR(I25="",I25="TBD",I25="N/A",I25="SDK",I25="SAAS"),0,1) -> 1 | AV25: =IF(OR(J25="",J25="TBD",J25="N/A",J25="SDK",J25="SAAS"),0,1) -> 0 | AX25: =SUM(AY25:BB25) -> 3 | AY25: =IF(OR(G25="",G25="N/A",G25="SDK",G25="SAAS"),0,1) -> 1 | AZ25: =IF(OR(H25="",H25="N/A",H25="SDK",H25="SAAS"),0,1) -> 1 | BA25: =IF(OR(I25="",I25="N/A",I25="SDK",I25="SAAS"),0,1) -> 1 | BB25: =IF(OR(J25="",J25="N/A",J25="SDK",J25="SAAS"),0,1) -> 0
A26: IC-021 | B26: Onboarding | C26: Generar el Hash ID del dispositivo | D26: Firma los eventos con un certificado | E26: =VLOOKUP(D26,C:C,1,FALSE) -> #N/A | G26: /experience/channels/v1/onBoardingParty/initiate | H26: /salesAndService/v1/onBoardingParty/initiate | I26: /crossChannel/sessionDialogue/v1/customerContactSessionProcedure/initiate | M26: =L26*$L$147 -> 0 | N26: Backlog | O26: Rafael Elizalde | P26: x | X26: Sí | Y26: Por definir | AD26: =IF(AI26=0,0,IF(AH26=AI26,1,0))*AF26 -> 1 | AE26: =IF(AM26=AN26,1,0)*AF26 -> 1 | AF26: =IF(ISNUMBER(MATCH(A26,$A$2:A25,0)),0,1) -> 1 | AH26: =SUMIFS(AJ$3:AJ$251,$A$3:$A$251,$A26) -> 1 | AI26: =SUMIFS(AK$3:AK$77,$A$3:$A$77,$A26) -> 1 | AJ26: =IF(SUM(AY26:BB26)=0,0,IF(SUM(AS26:AV26)=SUM(AY26:BB26),1,0)) -> 1 | AK26: 1 | AM26: =SUMIFS(AO$3:AO$251,$A$3:$A$251,$A26) -> 1 | AN26: =SUMIFS(AP$3:AP$251,$A$3:$A$251,$A26) -> 1 | AO26: =IF(SUM(AS26:AV26)=SUM(AY26:BB26),1,0) -> 1 | AP26: 1 | AR26: =SUM(AS26:AV26) -> 3 | AS26: =IF(OR(G26="",G26="TBD",G26="N/A",G26="SDK",G26="SAAS"),0,1) -> 1 | AT26: =IF(OR(H26="",H26="TBD",H26="N/A",H26="SDK",H26="SAAS"),0,1) -> 1 | AU26: =IF(OR(I26="",I26="TBD",I26="N/A",I26="SDK",I26="SAAS"),0,1) -> 1 | AV26: =IF(OR(J26="",J26="TBD",J26="N/A",J26="SDK",J26="SAAS"),0,1) -> 0 | AX26: =SUM(AY26:BB26) -> 3 | AY26: =IF(OR(G26="",G26="N/A",G26="SDK",G26="SAAS"),0,1) -> 1 | AZ26: =IF(OR(H26="",H26="N/A",H26="SDK",H26="SAAS"),0,1) -> 1 | BA26: =IF(OR(I26="",I26="N/A",I26="SDK",I26="SAAS"),0,1) -> 1 | BB26: =IF(OR(J26="",J26="N/A",J26="SDK",J26="SAAS"),0,1) -> 0
A27: IC-022 | B27: Onboarding | C27: Validar comprobante de ingresos (estados de cuenta bancarios) | D27: Firma los eventos con un certificado | G27: TBD | H27: TBD | I27: TBD | J27: TBD | M27: =L27*$L$147 -> 0 | N27: Backlog | O27: Rafael Elizalde | P27: x | X27: Post MVP | Y27: Por definir | AD27: =IF(AI27=0,0,IF(AH27=AI27,1,0))*AF27 -> 0 | AE27: =IF(AM27=AN27,1,0)*AF27 -> 0 | AF27: =IF(ISNUMBER(MATCH(A27,$A$2:A26,0)),0,1) -> 1 | AH27: =SUMIFS(AJ$3:AJ$251,$A$3:$A$251,$A27) -> 0 | AI27: =SUMIFS(AK$3:AK$77,$A$3:$A$77,$A27) -> 1 | AJ27: =IF(SUM(AY27:BB27)=0,0,IF(SUM(AS27:AV27)=SUM(AY27:BB27),1,0)) -> 0 | AK27: 1 | AM27: =SUMIFS(AO$3:AO$251,$A$3:$A$251,$A27) -> 0 | AN27: =SUMIFS(AP$3:AP$251,$A$3:$A$251,$A27) -> 1 | AO27: =IF(SUM(AS27:AV27)=SUM(AY27:BB27),1,0) -> 0 | AP27: 1 | AR27: =SUM(AS27:AV27) -> 0 | AS27: =IF(OR(G27="",G27="TBD",G27="N/A",G27="SDK",G27="SAAS"),0,1) -> 0 | AT27: =IF(OR(H27="",H27="TBD",H27="N/A",H27="SDK",H27="SAAS"),0,1) -> 0 | AU27: =IF(OR(I27="",I27="TBD",I27="N/A",I27="SDK",I27="SAAS"),0,1) -> 0 | AV27: =IF(OR(J27="",J27="TBD",J27="N/A",J27="SDK",J27="SAAS"),0,1) -> 0 | AX27: =SUM(AY27:BB27) -> 4 | AY27: =IF(OR(G27="",G27="N/A",G27="SDK",G27="SAAS"),0,1) -> 1 | AZ27: =IF(OR(H27="",H27="N/A",H27="SDK",H27="SAAS"),0,1) -> 1 | BA27: =IF(OR(I27="",I27="N/A",I27="SDK",I27="SAAS"),0,1) -> 1 | BB27: =IF(OR(J27="",J27="N/A",J27="SDK",J27="SAAS"),0,1) -> 1
A28: IC-024 | B28: Onboarding | C28: Generar la videograbación como parte de la prueba de vida (Video Selfie) | D28: Supervisar la actividad de los usuarios y/o sitios digitales relacionados con el contenido y las aplicaciones | E28: =VLOOKUP(D28,C:C,1,FALSE) -> Supervisar la actividad de los usuarios y/o sitios digitales relacionados con el contenido y las aplicaciones | G28: /experience/crossChannel/sessionDialogue/v1/customerContactVideoSelfieProcedure/initiate | L28: 1 | M28: =L28*$L$147 -> 3.5 | N28: Backlog | O28: Rafael Elizalde | P28: x | X28: Sí | Y28: Por definir | AD28: =IF(AI28=0,0,IF(AH28=AI28,1,0))*AF28 -> 1 | AE28: =IF(AM28=AN28,1,0)*AF28 -> 1 | AF28: =IF(ISNUMBER(MATCH(A28,$A$2:A27,0)),0,1) -> 1 | AH28: =SUMIFS(AJ$3:AJ$251,$A$3:$A$251,$A28) -> 2 | AI28: =SUMIFS(AK$3:AK$77,$A$3:$A$77,$A28) -> 2 | AJ28: =IF(SUM(AY28:BB28)=0,0,IF(SUM(AS28:AV28)=SUM(AY28:BB28),1,0)) -> 1 | AK28: 1 | AM28: =SUMIFS(AO$3:AO$251,$A$3:$A$251,$A28) -> 2 | AN28: =SUMIFS(AP$3:AP$251,$A$3:$A$251,$A28) -> 2 | AO28: =IF(SUM(AS28:AV28)=SUM(AY28:BB28),1,0) -> 1 | AP28: 1 | AR28: =SUM(AS28:AV28) -> 1 | AS28: =IF(OR(G28="",G28="TBD",G28="N/A",G28="SDK",G28="SAAS"),0,1) -> 1 | AT28: =IF(OR(H28="",H28="TBD",H28="N/A",H28="SDK",H28="SAAS"),0,1) -> 0 | AU28: =IF(OR(I28="",I28="TBD",I28="N/A",I28="SDK",I28="SAAS"),0,1) -> 0 | AV28: =IF(OR(J28="",J28="TBD",J28="N/A",J28="SDK",J28="SAAS"),0,1) -> 0 | AX28: =SUM(AY28:BB28) -> 1 | AY28: =IF(OR(G28="",G28="N/A",G28="SDK",G28="SAAS"),0,1) -> 1 | AZ28: =IF(OR(H28="",H28="N/A",H28="SDK",H28="SAAS"),0,1) -> 0 | BA28: =IF(OR(I28="",I28="N/A",I28="SDK",I28="SAAS"),0,1) -> 0 | BB28: =IF(OR(J28="",J28="N/A",J28="SDK",J28="SAAS"),0,1) -> 0
A29: IC-024 | B29: Onboarding | C29: Generar la videograbación como parte de la prueba de vida (Video Selfie) | D29: Creación de expediente digital cliente BanCoppel | E29: =VLOOKUP(D29,C:C,1,FALSE) -> Creación de expediente digital cliente BanCoppel | G29: /experience/crossChannel/sessionDialogue/v1/customerContactVideoSelfieProcedure/retrieve | L29: 1 | M29: =L29*$L$147 -> 3.5 | N29: Backlog | O29: Rafael Elizalde | P29: x | X29: Sí | Y29: Por definir | AD29: =IF(AI29=0,0,IF(AH29=AI29,1,0))*AF29 -> 0 | AE29: =IF(AM29=AN29,1,0)*AF29 -> 0 | AF29: =IF(ISNUMBER(MATCH(A29,$A$2:A28,0)),0,1) -> 0 | AH29: =SUMIFS(AJ$3:AJ$251,$A$3:$A$251,$A29) -> 2 | AI29: =SUMIFS(AK$3:AK$77,$A$3:$A$77,$A29) -> 2 | AJ29: =IF(SUM(AY29:BB29)=0,0,IF(SUM(AS29:AV29)=SUM(AY29:BB29),1,0)) -> 1 | AK29: 1 | AM29: =SUMIFS(AO$3:AO$251,$A$3:$A$251,$A29) -> 2 | AN29: =SUMIFS(AP$3:AP$251,$A$3:$A$251,$A29) -> 2 | AO29: =IF(SUM(AS29:AV29)=SUM(AY29:BB29),1,0) -> 1 | AP29: 1 | AR29: =SUM(AS29:AV29) -> 1 | AS29: =IF(OR(G29="",G29="TBD",G29="N/A",G29="SDK",G29="SAAS"),0,1) -> 1 | AT29: =IF(OR(H29="",H29="TBD",H29="N/A",H29="SDK",H29="SAAS"),0,1) -> 0 | AU29: =IF(OR(I29="",I29="TBD",I29="N/A",I29="SDK",I29="SAAS"),0,1) -> 0 | AV29: =IF(OR(J29="",J29="TBD",J29="N/A",J29="SDK",J29="SAAS"),0,1) -> 0 | AX29: =SUM(AY29:BB29) -> 1 | AY29: =IF(OR(G29="",G29="N/A",G29="SDK",G29="SAAS"),0,1) -> 1 | AZ29: =IF(OR(H29="",H29="N/A",H29="SDK",H29="SAAS"),0,1) -> 0 | BA29: =IF(OR(I29="",I29="N/A",I29="SDK",I29="SAAS"),0,1) -> 0 | BB29: =IF(OR(J29="",J29="N/A",J29="SDK",J29="SAAS"),0,1) -> 0
A30: IC-025 | B30: Onboarding | C30: Firmar del contrato (Non Repudiation) | D30: Carga de documentos en expediente | E30: =VLOOKUP(D30,C:C,1,FALSE) -> Carga de documentos en expediente | G30: TBD | H30: TBD | I30: TBD | J30: TBD | M30: =L30*$L$147 -> 0 | N30: Backlog | O30: Rafael Elizalde | P30: x | X30: Sí | Y30: Por definir | AD30: =IF(AI30=0,0,IF(AH30=AI30,1,0))*AF30 -> 0 | AE30: =IF(AM30=AN30,1,0)*AF30 -> 0 | AF30: =IF(ISNUMBER(MATCH(A30,$A$2:A28,0)),0,1) -> 1 | AH30: =SUMIFS(AJ$3:AJ$251,$A$3:$A$251,$A30) -> 0 | AI30: =SUMIFS(AK$3:AK$77,$A$3:$A$77,$A30) -> 1 | AJ30: =IF(SUM(AY30:BB30)=0,0,IF(SUM(AS30:AV30)=SUM(AY30:BB30),1,0)) -> 0 | AK30: 1 | AM30: =SUMIFS(AO$3:AO$251,$A$3:$A$251,$A30) -> 0 | AN30: =SUMIFS(AP$3:AP$251,$A$3:$A$251,$A30) -> 1 | AO30: =IF(SUM(AS30:AV30)=SUM(AY30:BB30),1,0) -> 0 | AP30: 1 | AR30: =SUM(AS30:AV30) -> 0 | AS30: =IF(OR(G30="",G30="TBD",G30="N/A",G30="SDK",G30="SAAS"),0,1) -> 0 | AT30: =IF(OR(H30="",H30="TBD",H30="N/A",H30="SDK",H30="SAAS"),0,1) -> 0 | AU30: =IF(OR(I30="",I30="TBD",I30="N/A",I30="SDK",I30="SAAS"),0,1) -> 0 | AV30: =IF(OR(J30="",J30="TBD",J30="N/A",J30="SDK",J30="SAAS"),0,1) -> 0 | AX30: =SUM(AY30:BB30) -> 4 | AY30: =IF(OR(G30="",G30="N/A",G30="SDK",G30="SAAS"),0,1) -> 1 | AZ30: =IF(OR(H30="",H30="N/A",H30="SDK",H30="SAAS"),0,1) -> 1 | BA30: =IF(OR(I30="",I30="N/A",I30="SDK",I30="SAAS"),0,1) -> 1 | BB30: =IF(OR(J30="",J30="N/A",J30="SDK",J30="SAAS"),0,1) -> 1
A31: IC-027 | B31: Onboarding | C31: Firmar con NOM 151 | D31: Búsqueda por metadata Expediente digital | E31: =VLOOKUP(D31,C:C,1,FALSE) -> Búsqueda por metadata Expediente digital | G31: TBD | H31: TBD | I31: TBD | J31: TBD | M31: =L31*$L$147 -> 0 | N31: Backlog | O31: Rafael Elizalde | P31: x | X31: Sí | Y31: Por definir | AD31: =IF(AI31=0,0,IF(AH31=AI31,1,0))*AF31 -> 0 | AE31: =IF(AM31=AN31,1,0)*AF31 -> 0 | AF31: =IF(ISNUMBER(MATCH(A31,$A$2:A30,0)),0,1) -> 1 | AH31: =SUMIFS(AJ$3:AJ$251,$A$3:$A$251,$A31) -> 0 | AI31: =SUMIFS(AK$3:AK$77,$A$3:$A$77,$A31) -> 1 | AJ31: =IF(SUM(AY31:BB31)=0,0,IF(SUM(AS31:AV31)=SUM(AY31:BB31),1,0)) -> 0 | AK31: 1 | AM31: =SUMIFS(AO$3:AO$251,$A$3:$A$251,$A31) -> 0 | AN31: =SUMIFS(AP$3:AP$251,$A$3:$A$251,$A31) -> 1 | AO31: =IF(SUM(AS31:AV31)=SUM(AY31:BB31),1,0) -> 0 | AP31: 1 | AR31: =SUM(AS31:AV31) -> 0 | AS31: =IF(OR(G31="",G31="TBD",G31="N/A",G31="SDK",G31="SAAS"),0,1) -> 0 | AT31: =IF(OR(H31="",H31="TBD",H31="N/A",H31="SDK",H31="SAAS"),0,1) -> 0 | AU31: =IF(OR(I31="",I31="TBD",I31="N/A",I31="SDK",I31="SAAS"),0,1) -> 0 | AV31: =IF(OR(J31="",J31="TBD",J31="N/A",J31="SDK",J31="SAAS"),0,1) -> 0 | AX31: =SUM(AY31:BB31) -> 4 | AY31: =IF(OR(G31="",G31="N/A",G31="SDK",G31="SAAS"),0,1) -> 1 | AZ31: =IF(OR(H31="",H31="N/A",H31="SDK",H31="SAAS"),0,1) -> 1 | BA31: =IF(OR(I31="",I31="N/A",I31="SDK",I31="SAAS"),0,1) -> 1 | BB31: =IF(OR(J31="",J31="N/A",J31="SDK",J31="SAAS"),0,1) -> 1
A32: IC-028 | B32: Onboarding | C32: Firmar los eventos con un certificado | D32: Métricas de expediente digital | E32: =VLOOKUP(D32,C:C,1,FALSE) -> Métricas de expediente digital | G32: TBD | H32: TBD | I32: TBD | J32: TBD | M32: =L32*$L$147 -> 0 | N32: Backlog | O32: Rafael Elizalde | P32: x | X32: Sí | Y32: Por definir | AD32: =IF(AI32=0,0,IF(AH32=AI32,1,0))*AF32 -> 0 | AE32: =IF(AM32=AN32,1,0)*AF32 -> 0 | AF32: =IF(ISNUMBER(MATCH(A32,$A$2:A31,0)),0,1) -> 1 | AH32: =SUMIFS(AJ$3:AJ$251,$A$3:$A$251,$A32) -> 0 | AI32: =SUMIFS(AK$3:AK$77,$A$3:$A$77,$A32) -> 1 | AJ32: =IF(SUM(AY32:BB32)=0,0,IF(SUM(AS32:AV32)=SUM(AY32:BB32),1,0)) -> 0 | AK32: 1 | AM32: =SUMIFS(AO$3:AO$251,$A$3:$A$251,$A32) -> 0 | AN32: =SUMIFS(AP$3:AP$251,$A$3:$A$251,$A32) -> 1 | AO32: =IF(SUM(AS32:AV32)=SUM(AY32:BB32),1,0) -> 0 | AP32: 1 | AR32: =SUM(AS32:AV32) -> 0 | AS32: =IF(OR(G32="",G32="TBD",G32="N/A",G32="SDK",G32="SAAS"),0,1) -> 0 | AT32: =IF(OR(H32="",H32="TBD",H32="N/A",H32="SDK",H32="SAAS"),0,1) -> 0 | AU32: =IF(OR(I32="",I32="TBD",I32="N/A",I32="SDK",I32="SAAS"),0,1) -> 0 | AV32: =IF(OR(J32="",J32="TBD",J32="N/A",J32="SDK",J32="SAAS"),0,1) -> 0 | AX32: =SUM(AY32:BB32) -> 4 | AY32: =IF(OR(G32="",G32="N/A",G32="SDK",G32="SAAS"),0,1) -> 1 | AZ32: =IF(OR(H32="",H32="N/A",H32="SDK",H32="SAAS"),0,1) -> 1 | BA32: =IF(OR(I32="",I32="N/A",I32="SDK",I32="SAAS"),0,1) -> 1 | BB32: =IF(OR(J32="",J32="N/A",J32="SDK",J32="SAAS"),0,1) -> 1
A33: MD - 001 | B33: Onboarding | C33: Generación y versionamiento de Plantillas HTML asociadas a la experiencia digital | D33: Validaciones sobre vigencia de documentos | E33: =VLOOKUP(D33,C:C,1,FALSE) -> Validaciones sobre vigencia de documentos | F33: SAAS | G33: SAAS | H33: SAAS | I33: SAAS | J33: SAAS | M33: =L33*$L$147 -> 0 | N33: Backlog | O33: Rafael Elizalde | P33: x | X33: Sí | Y33: Por definir | AD33: =IF(AI33=0,0,IF(AH33=AI33,1,0))*AF33 -> 0 | AE33: =IF(AM33=AN33,1,0)*AF33 -> 1 | AF33: =IF(ISNUMBER(MATCH(A33,$A$2:A32,0)),0,1) -> 1 | AH33: =SUMIFS(AJ$3:AJ$251,$A$3:$A$251,$A33) -> 0 | AI33: =SUMIFS(AK$3:AK$77,$A$3:$A$77,$A33) -> 1 | AJ33: =IF(SUM(AY33:BB33)=0,0,IF(SUM(AS33:AV33)=SUM(AY33:BB33),1,0)) -> 0 | AK33: 1 | AM33: =SUMIFS(AO$3:AO$251,$A$3:$A$251,$A33) -> 1 | AN33: =SUMIFS(AP$3:AP$251,$A$3:$A$251,$A33) -> 1 | AO33: =IF(SUM(AS33:AV33)=SUM(AY33:BB33),1,0) -> 1 | AP33: 1 | AR33: =SUM(AS33:AV33) -> 0 | AS33: =IF(OR(G33="",G33="TBD",G33="N/A",G33="SDK",G33="SAAS"),0,1) -> 0 | AT33: =IF(OR(H33="",H33="TBD",H33="N/A",H33="SDK",H33="SAAS"),0,1) -> 0 | AU33: =IF(OR(I33="",I33="TBD",I33="N/A",I33="SDK",I33="SAAS"),0,1) -> 0 | AV33: =IF(OR(J33="",J33="TBD",J33="N/A",J33="SDK",J33="SAAS"),0,1) -> 0 | AX33: =SUM(AY33:BB33) -> 0 | AY33: =IF(OR(G33="",G33="N/A",G33="SDK",G33="SAAS"),0,1) -> 0 | AZ33: =IF(OR(H33="",H33="N/A",H33="SDK",H33="SAAS"),0,1) -> 0 | BA33: =IF(OR(I33="",I33="N/A",I33="SDK",I33="SAAS"),0,1) -> 0 | BB33: =IF(OR(J33="",J33="N/A",J33="SDK",J33="SAAS"),0,1) -> 0
A34: MD - 002 | B34: Onboarding | C34: Contar con catálogo de plantillas HTML que permitan la reutilización de código | D34: Visor de expediente digital | E34: =VLOOKUP(D34,C:C,1,FALSE) -> Visor de expediente digital | F34: SAAS | G34: SAAS | H34: SAAS | I34: SAAS | J34: SAAS | M34: =L34*$L$147 -> 0 | N34: Backlog | O34: Rafael Elizalde | P34: x | X34: Sí | Y34: Por definir | AD34: =IF(AI34=0,0,IF(AH34=AI34,1,0))*AF34 -> 0 | AE34: =IF(AM34=AN34,1,0)*AF34 -> 1 | AF34: =IF(ISNUMBER(MATCH(A34,$A$2:A33,0)),0,1) -> 1 | AH34: =SUMIFS(AJ$3:AJ$251,$A$3:$A$251,$A34) -> 0 | AI34: =SUMIFS(AK$3:AK$77,$A$3:$A$77,$A34) -> 1 | AJ34: =IF(SUM(AY34:BB34)=0,0,IF(SUM(AS34:AV34)=SUM(AY34:BB34),1,0)) -> 0 | AK34: 1 | AM34: =SUMIFS(AO$3:AO$251,$A$3:$A$251,$A34) -> 1 | AN34: =SUMIFS(AP$3:AP$251,$A$3:$A$251,$A34) -> 1 | AO34: =IF(SUM(AS34:AV34)=SUM(AY34:BB34),1,0) -> 1 | AP34: 1 | AR34: =SUM(AS34:AV34) -> 0 | AS34: =IF(OR(G34="",G34="TBD",G34="N/A",G34="SDK",G34="SAAS"),0,1) -> 0 | AT34: =IF(OR(H34="",H34="TBD",H34="N/A",H34="SDK",H34="SAAS"),0,1) -> 0 | AU34: =IF(OR(I34="",I34="TBD",I34="N/A",I34="SDK",I34="SAAS"),0,1) -> 0 | AV34: =IF(OR(J34="",J34="TBD",J34="N/A",J34="SDK",J34="SAAS"),0,1) -> 0 | AX34: =SUM(AY34:BB34) -> 0 | AY34: =IF(OR(G34="",G34="N/A",G34="SDK",G34="SAAS"),0,1) -> 0 | AZ34: =IF(OR(H34="",H34="N/A",H34="SDK",H34="SAAS"),0,1) -> 0 | BA34: =IF(OR(I34="",I34="N/A",I34="SDK",I34="SAAS"),0,1) -> 0 | BB34: =IF(OR(J34="",J34="N/A",J34="SDK",J34="SAAS"),0,1) -> 0
A35: MD - 003 | B35: Onboarding | C35: Gestión de sitios para organizar los canales digitales de la compañía | D35: Motor de reglas de decisión para flujo de proceso (Solicitud TDC Visa) | E35: =VLOOKUP(D35,C:C,1,FALSE) -> #N/A | F35: SAAS | G35: SAAS | H35: SAAS | I35: SAAS | J35: SAAS | M35: =L35*$L$147 -> 0 | N35: Backlog | O35: Rafael Elizalde | P35: x | X35: Sí | Y35: Por definir | AD35: =IF(AI35=0,0,IF(AH35=AI35,1,0))*AF35 -> 0 | AE35: =IF(AM35=AN35,1,0)*AF35 -> 1 | AF35: =IF(ISNUMBER(MATCH(A35,$A$2:A34,0)),0,1) -> 1 | AH35: =SUMIFS(AJ$3:AJ$251,$A$3:$A$251,$A35) -> 0 | AI35: =SUMIFS(AK$3:AK$77,$A$3:$A$77,$A35) -> 1 | AJ35: =IF(SUM(AY35:BB35)=0,0,IF(SUM(AS35:AV35)=SUM(AY35:BB35),1,0)) -> 0 | AK35: 1 | AM35: =SUMIFS(AO$3:AO$251,$A$3:$A$251,$A35) -> 1 | AN35: =SUMIFS(AP$3:AP$251,$A$3:$A$251,$A35) -> 1 | AO35: =IF(SUM(AS35:AV35)=SUM(AY35:BB35),1,0) -> 1 | AP35: 1 | AR35: =SUM(AS35:AV35) -> 0 | AS35: =IF(OR(G35="",G35="TBD",G35="N/A",G35="SDK",G35="SAAS"),0,1) -> 0 | AT35: =IF(OR(H35="",H35="TBD",H35="N/A",H35="SDK",H35="SAAS"),0,1) -> 0 | AU35: =IF(OR(I35="",I35="TBD",I35="N/A",I35="SDK",I35="SAAS"),0,1) -> 0 | AV35: =IF(OR(J35="",J35="TBD",J35="N/A",J35="SDK",J35="SAAS"),0,1) -> 0 | AX35: =SUM(AY35:BB35) -> 0 | AY35: =IF(OR(G35="",G35="N/A",G35="SDK",G35="SAAS"),0,1) -> 0 | AZ35: =IF(OR(H35="",H35="N/A",H35="SDK",H35="SAAS"),0,1) -> 0 | BA35: =IF(OR(I35="",I35="N/A",I35="SDK",I35="SAAS"),0,1) -> 0 | BB35: =IF(OR(J35="",J35="N/A",J35="SDK",J35="SAAS"),0,1) -> 0
A36: MD - 004 | B36: Onboarding | C36: Páginas dinámicas para definir la estructura de cada sitio y agregar contenido | D36: Inventario de reglas desacoplado | E36: =VLOOKUP(D36,C:C,1,FALSE) -> Inventario de reglas desacoplado | F36: SAAS | G36: SAAS | H36: SAAS | I36: SAAS | J36: SAAS | M36: =L36*$L$147 -> 0 | N36: Backlog | O36: Rafael Elizalde | P36: x | X36: Sí | Y36: Por definir | AD36: =IF(AI36=0,0,IF(AH36=AI36,1,0))*AF36 -> 0 | AE36: =IF(AM36=AN36,1,0)*AF36 -> 1 | AF36: =IF(ISNUMBER(MATCH(A36,$A$2:A35,0)),0,1) -> 1 | AH36: =SUMIFS(AJ$3:AJ$251,$A$3:$A$251,$A36) -> 0 | AI36: =SUMIFS(AK$3:AK$77,$A$3:$A$77,$A36) -> 1 | AJ36: =IF(SUM(AY36:BB36)=0,0,IF(SUM(AS36:AV36)=SUM(AY36:BB36),1,0)) -> 0 | AK36: 1 | AM36: =SUMIFS(AO$3:AO$251,$A$3:$A$251,$A36) -> 1 | AN36: =SUMIFS(AP$3:AP$251,$A$3:$A$251,$A36) -> 1 | AO36: =IF(SUM(AS36:AV36)=SUM(AY36:BB36),1,0) -> 1 | AP36: 1 | AR36: =SUM(AS36:AV36) -> 0 | AS36: =IF(OR(G36="",G36="TBD",G36="N/A",G36="SDK",G36="SAAS"),0,1) -> 0 | AT36: =IF(OR(H36="",H36="TBD",H36="N/A",H36="SDK",H36="SAAS"),0,1) -> 0 | AU36: =IF(OR(I36="",I36="TBD",I36="N/A",I36="SDK",I36="SAAS"),0,1) -> 0 | AV36: =IF(OR(J36="",J36="TBD",J36="N/A",J36="SDK",J36="SAAS"),0,1) -> 0 | AX36: =SUM(AY36:BB36) -> 0 | AY36: =IF(OR(G36="",G36="N/A",G36="SDK",G36="SAAS"),0,1) -> 0 | AZ36: =IF(OR(H36="",H36="N/A",H36="SDK",H36="SAAS"),0,1) -> 0 | BA36: =IF(OR(I36="",I36="N/A",I36="SDK",I36="SAAS"),0,1) -> 0 | BB36: =IF(OR(J36="",J36="N/A",J36="SDK",J36="SAAS"),0,1) -> 0
A37: MD - 005 | B37: Onboarding | C37: Capacidad de crear componentes reutilizables usando tecnologías de Javascript, HTML y CSS | D37: Árboles y tablas de decisión para diseño de reglas | E37: =VLOOKUP(D37,C:C,1,FALSE) -> #N/A | F37: SAAS | G37: SAAS | H37: SAAS | I37: SAAS | J37: SAAS | M37: =L37*$L$147 -> 0 | N37: Backlog | O37: Rafael Elizalde | P37: x | X37: Sí | Y37: Por definir | AD37: =IF(AI37=0,0,IF(AH37=AI37,1,0))*AF37 -> 0 | AE37: =IF(AM37=AN37,1,0)*AF37 -> 1 | AF37: =IF(ISNUMBER(MATCH(A37,$A$2:A36,0)),0,1) -> 1 | AH37: =SUMIFS(AJ$3:AJ$251,$A$3:$A$251,$A37) -> 0 | AI37: =SUMIFS(AK$3:AK$77,$A$3:$A$77,$A37) -> 1 | AJ37: =IF(SUM(AY37:BB37)=0,0,IF(SUM(AS37:AV37)=SUM(AY37:BB37),1,0)) -> 0 | AK37: 1 | AM37: =SUMIFS(AO$3:AO$251,$A$3:$A$251,$A37) -> 1 | AN37: =SUMIFS(AP$3:AP$251,$A$3:$A$251,$A37) -> 1 | AO37: =IF(SUM(AS37:AV37)=SUM(AY37:BB37),1,0) -> 1 | AP37: 1 | AR37: =SUM(AS37:AV37) -> 0 | AS37: =IF(OR(G37="",G37="TBD",G37="N/A",G37="SDK",G37="SAAS"),0,1) -> 0 | AT37: =IF(OR(H37="",H37="TBD",H37="N/A",H37="SDK",H37="SAAS"),0,1) -> 0 | AU37: =IF(OR(I37="",I37="TBD",I37="N/A",I37="SDK",I37="SAAS"),0,1) -> 0 | AV37: =IF(OR(J37="",J37="TBD",J37="N/A",J37="SDK",J37="SAAS"),0,1) -> 0 | AX37: =SUM(AY37:BB37) -> 0 | AY37: =IF(OR(G37="",G37="N/A",G37="SDK",G37="SAAS"),0,1) -> 0 | AZ37: =IF(OR(H37="",H37="N/A",H37="SDK",H37="SAAS"),0,1) -> 0 | BA37: =IF(OR(I37="",I37="N/A",I37="SDK",I37="SAAS"),0,1) -> 0 | BB37: =IF(OR(J37="",J37="N/A",J37="SDK",J37="SAAS"),0,1) -> 0
A38: MD - 006 | B38: Onboarding | C38: Capacidad para crear micro frontends para múltiples sitios y aplicaciones | D38: INTL Buró de Crédito | E38: =VLOOKUP(D38,C:C,1,FALSE) -> #N/A | F38: SAAS | G38: SAAS | H38: SAAS | I38: SAAS | J38: SAAS | M38: =L38*$L$147 -> 0 | N38: Backlog | O38: Rafael Elizalde | P38: x | X38: Sí | Y38: Por definir | AD38: =IF(AI38=0,0,IF(AH38=AI38,1,0))*AF38 -> 0 | AE38: =IF(AM38=AN38,1,0)*AF38 -> 1 | AF38: =IF(ISNUMBER(MATCH(A38,$A$2:A37,0)),0,1) -> 1 | AH38: =SUMIFS(AJ$3:AJ$251,$A$3:$A$251,$A38) -> 0 | AI38: =SUMIFS(AK$3:AK$77,$A$3:$A$77,$A38) -> 1 | AJ38: =IF(SUM(AY38:BB38)=0,0,IF(SUM(AS38:AV38)=SUM(AY38:BB38),1,0)) -> 0 | AK38: 1 | AM38: =SUMIFS(AO$3:AO$251,$A$3:$A$251,$A38) -> 1 | AN38: =SUMIFS(AP$3:AP$251,$A$3:$A$251,$A38) -> 1 | AO38: =IF(SUM(AS38:AV38)=SUM(AY38:BB38),1,0) -> 1 | AP38: 1 | AR38: =SUM(AS38:AV38) -> 0 | AS38: =IF(OR(G38="",G38="TBD",G38="N/A",G38="SDK",G38="SAAS"),0,1) -> 0 | AT38: =IF(OR(H38="",H38="TBD",H38="N/A",H38="SDK",H38="SAAS"),0,1) -> 0 | AU38: =IF(OR(I38="",I38="TBD",I38="N/A",I38="SDK",I38="SAAS"),0,1) -> 0 | AV38: =IF(OR(J38="",J38="TBD",J38="N/A",J38="SDK",J38="SAAS"),0,1) -> 0 | AX38: =SUM(AY38:BB38) -> 0 | AY38: =IF(OR(G38="",G38="N/A",G38="SDK",G38="SAAS"),0,1) -> 0 | AZ38: =IF(OR(H38="",H38="N/A",H38="SDK",H38="SAAS"),0,1) -> 0 | BA38: =IF(OR(I38="",I38="N/A",I38="SDK",I38="SAAS"),0,1) -> 0 | BB38: =IF(OR(J38="",J38="N/A",J38="SDK",J38="SAAS"),0,1) -> 0
A39: MD - 007 | B39: Onboarding | C39: Capacidad para extender funcionalidades a diferentes sitios y aplicaciones incluso con una entidad separada | D39: Dispersión de SMS | E39: =VLOOKUP(D39,C:C,1,FALSE) -> Dispersión de SMS | F39: SAAS | G39: SAAS | H39: SAAS | I39: SAAS | J39: SAAS | M39: =L39*$L$147 -> 0 | N39: Backlog | O39: Rafael Elizalde | P39: x | X39: Sí | Y39: Por definir | AD39: =IF(AI39=0,0,IF(AH39=AI39,1,0))*AF39 -> 0 | AE39: =IF(AM39=AN39,1,0)*AF39 -> 1 | AF39: =IF(ISNUMBER(MATCH(A39,$A$2:A38,0)),0,1) -> 1 | AH39: =SUMIFS(AJ$3:AJ$251,$A$3:$A$251,$A39) -> 0 | AI39: =SUMIFS(AK$3:AK$77,$A$3:$A$77,$A39) -> 1 | AJ39: =IF(SUM(AY39:BB39)=0,0,IF(SUM(AS39:AV39)=SUM(AY39:BB39),1,0)) -> 0 | AK39: 1 | AM39: =SUMIFS(AO$3:AO$251,$A$3:$A$251,$A39) -> 1 | AN39: =SUMIFS(AP$3:AP$251,$A$3:$A$251,$A39) -> 1 | AO39: =IF(SUM(AS39:AV39)=SUM(AY39:BB39),1,0) -> 1 | AP39: 1 | AR39: =SUM(AS39:AV39) -> 0 | AS39: =IF(OR(G39="",G39="TBD",G39="N/A",G39="SDK",G39="SAAS"),0,1) -> 0 | AT39: =IF(OR(H39="",H39="TBD",H39="N/A",H39="SDK",H39="SAAS"),0,1) -> 0 | AU39: =IF(OR(I39="",I39="TBD",I39="N/A",I39="SDK",I39="SAAS"),0,1) -> 0 | AV39: =IF(OR(J39="",J39="TBD",J39="N/A",J39="SDK",J39="SAAS"),0,1) -> 0 | AX39: =SUM(AY39:BB39) -> 0 | AY39: =IF(OR(G39="",G39="N/A",G39="SDK",G39="SAAS"),0,1) -> 0 | AZ39: =IF(OR(H39="",H39="N/A",H39="SDK",H39="SAAS"),0,1) -> 0 | BA39: =IF(OR(I39="",I39="N/A",I39="SDK",I39="SAAS"),0,1) -> 0 | BB39: =IF(OR(J39="",J39="N/A",J39="SDK",J39="SAAS"),0,1) -> 0
A40: MD - 008 | B40: Onboarding | C40: Segmentación de componentes de acuerdo a su estado, autor, tags o por nombre de la funcionalidad | D40: Dispersión de Email (Welcome Kit) | E40: =VLOOKUP(D40,C:C,1,FALSE) -> Dispersión de Email (Welcome Kit) | F40: SAAS | G40: SAAS | H40: SAAS | I40: SAAS | J40: SAAS | M40: =L40*$L$147 -> 0 | N40: Backlog | O40: Rafael Elizalde | P40: x | X40: Sí | Y40: Por definir | AD40: =IF(AI40=0,0,IF(AH40=AI40,1,0))*AF40 -> 0 | AE40: =IF(AM40=AN40,1,0)*AF40 -> 1 | AF40: =IF(ISNUMBER(MATCH(A40,$A$2:A39,0)),0,1) -> 1 | AH40: =SUMIFS(AJ$3:AJ$251,$A$3:$A$251,$A40) -> 0 | AI40: =SUMIFS(AK$3:AK$77,$A$3:$A$77,$A40) -> 1 | AJ40: =IF(SUM(AY40:BB40)=0,0,IF(SUM(AS40:AV40)=SUM(AY40:BB40),1,0)) -> 0 | AK40: 1 | AM40: =SUMIFS(AO$3:AO$251,$A$3:$A$251,$A40) -> 1 | AN40: =SUMIFS(AP$3:AP$251,$A$3:$A$251,$A40) -> 1 | AO40: =IF(SUM(AS40:AV40)=SUM(AY40:BB40),1,0) -> 1 | AP40: 1 | AR40: =SUM(AS40:AV40) -> 0 | AS40: =IF(OR(G40="",G40="TBD",G40="N/A",G40="SDK",G40="SAAS"),0,1) -> 0 | AT40: =IF(OR(H40="",H40="TBD",H40="N/A",H40="SDK",H40="SAAS"),0,1) -> 0 | AU40: =IF(OR(I40="",I40="TBD",I40="N/A",I40="SDK",I40="SAAS"),0,1) -> 0 | AV40: =IF(OR(J40="",J40="TBD",J40="N/A",J40="SDK",J40="SAAS"),0,1) -> 0 | AX40: =SUM(AY40:BB40) -> 0 | AY40: =IF(OR(G40="",G40="N/A",G40="SDK",G40="SAAS"),0,1) -> 0 | AZ40: =IF(OR(H40="",H40="N/A",H40="SDK",H40="SAAS"),0,1) -> 0 | BA40: =IF(OR(I40="",I40="N/A",I40="SDK",I40="SAAS"),0,1) -> 0 | BB40: =IF(OR(J40="",J40="N/A",J40="SDK",J40="SAAS"),0,1) -> 0
A41: MD - 009 | B41: Onboarding | C41: Capacidad de generar plantillas para organizar estructuras globales del sitio y el sistema de diseño | E41: =VLOOKUP(D41,C:C,1,FALSE) -> #N/A | F41: SAAS | G41: SAAS | H41: SAAS | I41: SAAS | J41: SAAS | M41: =L41*$L$147 -> 0 | N41: Backlog | O41: Rafael Elizalde | P41: x | X41: Sí | Y41: Por definir | AD41: =IF(AI41=0,0,IF(AH41=AI41,1,0))*AF41 -> 0 | AE41: =IF(AM41=AN41,1,0)*AF41 -> 1 | AF41: =IF(ISNUMBER(MATCH(A41,$A$2:A40,0)),0,1) -> 1 | AH41: =SUMIFS(AJ$3:AJ$251,$A$3:$A$251,$A41) -> 0 | AI41: =SUMIFS(AK$3:AK$77,$A$3:$A$77,$A41) -> 1 | AJ41: =IF(SUM(AY41:BB41)=0,0,IF(SUM(AS41:AV41)=SUM(AY41:BB41),1,0)) -> 0 | AK41: 1 | AM41: =SUMIFS(AO$3:AO$251,$A$3:$A$251,$A41) -> 1 | AN41: =SUMIFS(AP$3:AP$251,$A$3:$A$251,$A41) -> 1 | AO41: =IF(SUM(AS41:AV41)=SUM(AY41:BB41),1,0) -> 1 | AP41: 1 | AR41: =SUM(AS41:AV41) -> 0 | AS41: =IF(OR(G41="",G41="TBD",G41="N/A",G41="SDK",G41="SAAS"),0,1) -> 0 | AT41: =IF(OR(H41="",H41="TBD",H41="N/A",H41="SDK",H41="SAAS"),0,1) -> 0 | AU41: =IF(OR(I41="",I41="TBD",I41="N/A",I41="SDK",I41="SAAS"),0,1) -> 0 | AV41: =IF(OR(J41="",J41="TBD",J41="N/A",J41="SDK",J41="SAAS"),0,1) -> 0 | AX41: =SUM(AY41:BB41) -> 0 | AY41: =IF(OR(G41="",G41="N/A",G41="SDK",G41="SAAS"),0,1) -> 0 | AZ41: =IF(OR(H41="",H41="N/A",H41="SDK",H41="SAAS"),0,1) -> 0 | BA41: =IF(OR(I41="",I41="N/A",I41="SDK",I41="SAAS"),0,1) -> 0 | BB41: =IF(OR(J41="",J41="N/A",J41="SDK",J41="SAAS"),0,1) -> 0
A42: MD - 010 | B42: Onboarding | C42: Flexibilidad para modificar las plantillas base y su estructura según se requiera | E42: =VLOOKUP(D42,C:C,1,FALSE) -> #N/A | F42: SAAS | G42: SAAS | H42: SAAS | I42: SAAS | J42: SAAS | M42: =L42*$L$147 -> 0 | N42: Backlog | O42: Rafael Elizalde | P42: x | X42: Sí | Y42: Por definir | AD42: =IF(AI42=0,0,IF(AH42=AI42,1,0))*AF42 -> 0 | AE42: =IF(AM42=AN42,1,0)*AF42 -> 1 | AF42: =IF(ISNUMBER(MATCH(A42,$A$2:A41,0)),0,1) -> 1 | AH42: =SUMIFS(AJ$3:AJ$251,$A$3:$A$251,$A42) -> 0 | AI42: =SUMIFS(AK$3:AK$77,$A$3:$A$77,$A42) -> 1 | AJ42: =IF(SUM(AY42:BB42)=0,0,IF(SUM(AS42:AV42)=SUM(AY42:BB42),1,0)) -> 0 | AK42: 1 | AM42: =SUMIFS(AO$3:AO$251,$A$3:$A$251,$A42) -> 1 | AN42: =SUMIFS(AP$3:AP$251,$A$3:$A$251,$A42) -> 1 | AO42: =IF(SUM(AS42:AV42)=SUM(AY42:BB42),1,0) -> 1 | AP42: 1 | AR42: =SUM(AS42:AV42) -> 0 | AS42: =IF(OR(G42="",G42="TBD",G42="N/A",G42="SDK",G42="SAAS"),0,1) -> 0 | AT42: =IF(OR(H42="",H42="TBD",H42="N/A",H42="SDK",H42="SAAS"),0,1) -> 0 | AU42: =IF(OR(I42="",I42="TBD",I42="N/A",I42="SDK",I42="SAAS"),0,1) -> 0 | AV42: =IF(OR(J42="",J42="TBD",J42="N/A",J42="SDK",J42="SAAS"),0,1) -> 0 | AX42: =SUM(AY42:BB42) -> 0 | AY42: =IF(OR(G42="",G42="N/A",G42="SDK",G42="SAAS"),0,1) -> 0 | AZ42: =IF(OR(H42="",H42="N/A",H42="SDK",H42="SAAS"),0,1) -> 0 | BA42: =IF(OR(I42="",I42="N/A",I42="SDK",I42="SAAS"),0,1) -> 0 | BB42: =IF(OR(J42="",J42="N/A",J42="SDK",J42="SAAS"),0,1) -> 0
A43: MD - 011 | B43: Onboarding | C43: Creación de Snippets de código HTML, JS y CSS para extender la funcionalidad de algún sitio | E43: =VLOOKUP(D43,C:C,1,FALSE) -> #N/A | F43: SAAS | G43: SAAS | H43: SAAS | I43: SAAS | J43: SAAS | M43: =L43*$L$147 -> 0 | N43: Backlog | O43: Rafael Elizalde | P43: x | X43: Sí | Y43: Por definir | AD43: =IF(AI43=0,0,IF(AH43=AI43,1,0))*AF43 -> 0 | AE43: =IF(AM43=AN43,1,0)*AF43 -> 1 | AF43: =IF(ISNUMBER(MATCH(A43,$A$2:A42,0)),0,1) -> 1 | AH43: =SUMIFS(AJ$3:AJ$251,$A$3:$A$251,$A43) -> 0 | AI43: =SUMIFS(AK$3:AK$77,$A$3:$A$77,$A43) -> 1 | AJ43: =IF(SUM(AY43:BB43)=0,0,IF(SUM(AS43:AV43)=SUM(AY43:BB43),1,0)) -> 0 | AK43: 1 | AM43: =SUMIFS(AO$3:AO$251,$A$3:$A$251,$A43) -> 1 | AN43: =SUMIFS(AP$3:AP$251,$A$3:$A$251,$A43) -> 1 | AO43: =IF(SUM(AS43:AV43)=SUM(AY43:BB43),1,0) -> 1 | AP43: 1 | AR43: =SUM(AS43:AV43) -> 0 | AS43: =IF(OR(G43="",G43="TBD",G43="N/A",G43="SDK",G43="SAAS"),0,1) -> 0 | AT43: =IF(OR(H43="",H43="TBD",H43="N/A",H43="SDK",H43="SAAS"),0,1) -> 0 | AU43: =IF(OR(I43="",I43="TBD",I43="N/A",I43="SDK",I43="SAAS"),0,1) -> 0 | AV43: =IF(OR(J43="",J43="TBD",J43="N/A",J43="SDK",J43="SAAS"),0,1) -> 0 | AX43: =SUM(AY43:BB43) -> 0 | AY43: =IF(OR(G43="",G43="N/A",G43="SDK",G43="SAAS"),0,1) -> 0 | AZ43: =IF(OR(H43="",H43="N/A",H43="SDK",H43="SAAS"),0,1) -> 0 | BA43: =IF(OR(I43="",I43="N/A",I43="SDK",I43="SAAS"),0,1) -> 0 | BB43: =IF(OR(J43="",J43="N/A",J43="SDK",J43="SAAS"),0,1) -> 0
A44: MD - 012 | B44: Onboarding | C44: Proceso de aprobación y publicación de plantillas, así como control de versionados | E44: =VLOOKUP(D44,C:C,1,FALSE) -> #N/A | F44: SAAS | G44: SAAS | H44: SAAS | I44: SAAS | J44: SAAS | M44: =L44*$L$147 -> 0 | N44: Backlog | O44: Rafael Elizalde | P44: x | X44: Sí | Y44: Por definir | AD44: =IF(AI44=0,0,IF(AH44=AI44,1,0))*AF44 -> 0 | AE44: =IF(AM44=AN44,1,0)*AF44 -> 1 | AF44: =IF(ISNUMBER(MATCH(A44,$A$2:A43,0)),0,1) -> 1 | AH44: =SUMIFS(AJ$3:AJ$251,$A$3:$A$251,$A44) -> 0 | AI44: =SUMIFS(AK$3:AK$77,$A$3:$A$77,$A44) -> 1 | AJ44: =IF(SUM(AY44:BB44)=0,0,IF(SUM(AS44:AV44)=SUM(AY44:BB44),1,0)) -> 0 | AK44: 1 | AM44: =SUMIFS(AO$3:AO$251,$A$3:$A$251,$A44) -> 1 | AN44: =SUMIFS(AP$3:AP$251,$A$3:$A$251,$A44) -> 1 | AO44: =IF(SUM(AS44:AV44)=SUM(AY44:BB44),1,0) -> 1 | AP44: 1 | AR44: =SUM(AS44:AV44) -> 0 | AS44: =IF(OR(G44="",G44="TBD",G44="N/A",G44="SDK",G44="SAAS"),0,1) -> 0 | AT44: =IF(OR(H44="",H44="TBD",H44="N/A",H44="SDK",H44="SAAS"),0,1) -> 0 | AU44: =IF(OR(I44="",I44="TBD",I44="N/A",I44="SDK",I44="SAAS"),0,1) -> 0 | AV44: =IF(OR(J44="",J44="TBD",J44="N/A",J44="SDK",J44="SAAS"),0,1) -> 0 | AX44: =SUM(AY44:BB44) -> 0 | AY44: =IF(OR(G44="",G44="N/A",G44="SDK",G44="SAAS"),0,1) -> 0 | AZ44: =IF(OR(H44="",H44="N/A",H44="SDK",H44="SAAS"),0,1) -> 0 | BA44: =IF(OR(I44="",I44="N/A",I44="SDK",I44="SAAS"),0,1) -> 0 | BB44: =IF(OR(J44="",J44="N/A",J44="SDK",J44="SAAS"),0,1) -> 0
A45: MD - 013 | B45: Onboarding | C45: Capacidad para restablecer a una versión de Look & Feel anterior de forma rápida y segura | E45: =VLOOKUP(D45,C:C,1,FALSE) -> #N/A | F45: SAAS | G45: SAAS | H45: SAAS | I45: SAAS | J45: SAAS | M45: =L45*$L$147 -> 0 | N45: Backlog | O45: Rafael Elizalde | P45: x | X45: Sí | Y45: Por definir | AD45: =IF(AI45=0,0,IF(AH45=AI45,1,0))*AF45 -> 0 | AE45: =IF(AM45=AN45,1,0)*AF45 -> 1 | AF45: =IF(ISNUMBER(MATCH(A45,$A$2:A44,0)),0,1) -> 1 | AH45: =SUMIFS(AJ$3:AJ$251,$A$3:$A$251,$A45) -> 0 | AI45: =SUMIFS(AK$3:AK$77,$A$3:$A$77,$A45) -> 1 | AJ45: =IF(SUM(AY45:BB45)=0,0,IF(SUM(AS45:AV45)=SUM(AY45:BB45),1,0)) -> 0 | AK45: 1 | AM45: =SUMIFS(AO$3:AO$251,$A$3:$A$251,$A45) -> 1 | AN45: =SUMIFS(AP$3:AP$251,$A$3:$A$251,$A45) -> 1 | AO45: =IF(SUM(AS45:AV45)=SUM(AY45:BB45),1,0) -> 1 | AP45: 1 | AR45: =SUM(AS45:AV45) -> 0 | AS45: =IF(OR(G45="",G45="TBD",G45="N/A",G45="SDK",G45="SAAS"),0,1) -> 0 | AT45: =IF(OR(H45="",H45="TBD",H45="N/A",H45="SDK",H45="SAAS"),0,1) -> 0 | AU45: =IF(OR(I45="",I45="TBD",I45="N/A",I45="SDK",I45="SAAS"),0,1) -> 0 | AV45: =IF(OR(J45="",J45="TBD",J45="N/A",J45="SDK",J45="SAAS"),0,1) -> 0 | AX45: =SUM(AY45:BB45) -> 0 | AY45: =IF(OR(G45="",G45="N/A",G45="SDK",G45="SAAS"),0,1) -> 0 | AZ45: =IF(OR(H45="",H45="N/A",H45="SDK",H45="SAAS"),0,1) -> 0 | BA45: =IF(OR(I45="",I45="N/A",I45="SDK",I45="SAAS"),0,1) -> 0 | BB45: =IF(OR(J45="",J45="N/A",J45="SDK",J45="SAAS"),0,1) -> 0
A46: MD - 014 | B46: Onboarding | C46: Agregar stages para permitir integrar y desplegar continuamente (CI/CD) nuevas funcionalidades en los sitios sin modificar lo que ya está publicado. | F46: SAAS | G46: SAAS | H46: SAAS | I46: SAAS | J46: SAAS | M46: =L46*$L$147 -> 0 | N46: Backlog | O46: Rafael Elizalde | P46: x | X46: Sí | Y46: Por definir | AD46: =IF(AI46=0,0,IF(AH46=AI46,1,0))*AF46 -> 0 | AE46: =IF(AM46=AN46,1,0)*AF46 -> 1 | AF46: =IF(ISNUMBER(MATCH(A46,$A$2:A45,0)),0,1) -> 1 | AH46: =SUMIFS(AJ$3:AJ$251,$A$3:$A$251,$A46) -> 0 | AI46: =SUMIFS(AK$3:AK$77,$A$3:$A$77,$A46) -> 1 | AJ46: =IF(SUM(AY46:BB46)=0,0,IF(SUM(AS46:AV46)=SUM(AY46:BB46),1,0)) -> 0 | AK46: 1 | AM46: =SUMIFS(AO$3:AO$251,$A$3:$A$251,$A46) -> 1 | AN46: =SUMIFS(AP$3:AP$251,$A$3:$A$251,$A46) -> 1 | AO46: =IF(SUM(AS46:AV46)=SUM(AY46:BB46),1,0) -> 1 | AP46: 1 | AR46: =SUM(AS46:AV46) -> 0 | AS46: =IF(OR(G46="",G46="TBD",G46="N/A",G46="SDK",G46="SAAS"),0,1) -> 0 | AT46: =IF(OR(H46="",H46="TBD",H46="N/A",H46="SDK",H46="SAAS"),0,1) -> 0 | AU46: =IF(OR(I46="",I46="TBD",I46="N/A",I46="SDK",I46="SAAS"),0,1) -> 0 | AV46: =IF(OR(J46="",J46="TBD",J46="N/A",J46="SDK",J46="SAAS"),0,1) -> 0 | AX46: =SUM(AY46:BB46) -> 0 | AY46: =IF(OR(G46="",G46="N/A",G46="SDK",G46="SAAS"),0,1) -> 0 | AZ46: =IF(OR(H46="",H46="N/A",H46="SDK",H46="SAAS"),0,1) -> 0 | BA46: =IF(OR(I46="",I46="N/A",I46="SDK",I46="SAAS"),0,1) -> 0 | BB46: =IF(OR(J46="",J46="N/A",J46="SDK",J46="SAAS"),0,1) -> 0
A47: MD - 015 | B47: Onboarding | C47: Creación de repositorios con capacidad de modificar su estructura por tipos de contenido y entradas de información | F47: SAAS | G47: SAAS | H47: SAAS | I47: SAAS | J47: SAAS | M47: =L47*$L$147 -> 0 | N47: Backlog | O47: Rafael Elizalde | P47: x | X47: Sí | Y47: Por definir | AD47: =IF(AI47=0,0,IF(AH47=AI47,1,0))*AF47 -> 0 | AE47: =IF(AM47=AN47,1,0)*AF47 -> 1 | AF47: =IF(ISNUMBER(MATCH(A47,$A$2:A46,0)),0,1) -> 1 | AH47: =SUMIFS(AJ$3:AJ$251,$A$3:$A$251,$A47) -> 0 | AI47: =SUMIFS(AK$3:AK$77,$A$3:$A$77,$A47) -> 1 | AJ47: =IF(SUM(AY47:BB47)=0,0,IF(SUM(AS47:AV47)=SUM(AY47:BB47),1,0)) -> 0 | AK47: 1 | AM47: =SUMIFS(AO$3:AO$251,$A$3:$A$251,$A47) -> 1 | AN47: =SUMIFS(AP$3:AP$251,$A$3:$A$251,$A47) -> 1 | AO47: =IF(SUM(AS47:AV47)=SUM(AY47:BB47),1,0) -> 1 | AP47: 1 | AR47: =SUM(AS47:AV47) -> 0 | AS47: =IF(OR(G47="",G47="TBD",G47="N/A",G47="SDK",G47="SAAS"),0,1) -> 0 | AT47: =IF(OR(H47="",H47="TBD",H47="N/A",H47="SDK",H47="SAAS"),0,1) -> 0 | AU47: =IF(OR(I47="",I47="TBD",I47="N/A",I47="SDK",I47="SAAS"),0,1) -> 0 | AV47: =IF(OR(J47="",J47="TBD",J47="N/A",J47="SDK",J47="SAAS"),0,1) -> 0 | AX47: =SUM(AY47:BB47) -> 0 | AY47: =IF(OR(G47="",G47="N/A",G47="SDK",G47="SAAS"),0,1) -> 0 | AZ47: =IF(OR(H47="",H47="N/A",H47="SDK",H47="SAAS"),0,1) -> 0 | BA47: =IF(OR(I47="",I47="N/A",I47="SDK",I47="SAAS"),0,1) -> 0 | BB47: =IF(OR(J47="",J47="N/A",J47="SDK",J47="SAAS"),0,1) -> 0
A48: MD - 016 | B48: Onboarding | C48: Publicaciones programadas en donde se podrán poner fecha y hora para publicar el contenido cuando el administrador lo desee | F48: SAAS | G48: SAAS | H48: SAAS | I48: SAAS | J48: SAAS | M48: =L48*$L$147 -> 0 | N48: Backlog | O48: Rafael Elizalde | P48: x | X48: Sí | Y48: Por definir | AD48: =IF(AI48=0,0,IF(AH48=AI48,1,0))*AF48 -> 0 | AE48: =IF(AM48=AN48,1,0)*AF48 -> 1 | AF48: =IF(ISNUMBER(MATCH(A48,$A$2:A47,0)),0,1) -> 1 | AH48: =SUMIFS(AJ$3:AJ$251,$A$3:$A$251,$A48) -> 0 | AI48: =SUMIFS(AK$3:AK$77,$A$3:$A$77,$A48) -> 1 | AJ48: =IF(SUM(AY48:BB48)=0,0,IF(SUM(AS48:AV48)=SUM(AY48:BB48),1,0)) -> 0 | AK48: 1 | AM48: =SUMIFS(AO$3:AO$251,$A$3:$A$251,$A48) -> 1 | AN48: =SUMIFS(AP$3:AP$251,$A$3:$A$251,$A48) -> 1 | AO48: =IF(SUM(AS48:AV48)=SUM(AY48:BB48),1,0) -> 1 | AP48: 1 | AR48: =SUM(AS48:AV48) -> 0 | AS48: =IF(OR(G48="",G48="TBD",G48="N/A",G48="SDK",G48="SAAS"),0,1) -> 0 | AT48: =IF(OR(H48="",H48="TBD",H48="N/A",H48="SDK",H48="SAAS"),0,1) -> 0 | AU48: =IF(OR(I48="",I48="TBD",I48="N/A",I48="SDK",I48="SAAS"),0,1) -> 0 | AV48: =IF(OR(J48="",J48="TBD",J48="N/A",J48="SDK",J48="SAAS"),0,1) -> 0 | AX48: =SUM(AY48:BB48) -> 0 | AY48: =IF(OR(G48="",G48="N/A",G48="SDK",G48="SAAS"),0,1) -> 0 | AZ48: =IF(OR(H48="",H48="N/A",H48="SDK",H48="SAAS"),0,1) -> 0 | BA48: =IF(OR(I48="",I48="N/A",I48="SDK",I48="SAAS"),0,1) -> 0 | BB48: =IF(OR(J48="",J48="N/A",J48="SDK",J48="SAAS"),0,1) -> 0
A49: MD - 017 | B49: Onboarding | C49: Crear roles con permisos para los usuarios con el fin de evitar exposición a áreas e información sensible | F49: SAAS | G49: SAAS | H49: SAAS | I49: SAAS | J49: SAAS | M49: =L49*$L$147 -> 0 | N49: Backlog | O49: Rafael Elizalde | P49: x | X49: Sí | Y49: Por definir | AD49: =IF(AI49=0,0,IF(AH49=AI49,1,0))*AF49 -> 0 | AE49: =IF(AM49=AN49,1,0)*AF49 -> 1 | AF49: =IF(ISNUMBER(MATCH(A49,$A$2:A48,0)),0,1) -> 1 | AH49: =SUMIFS(AJ$3:AJ$251,$A$3:$A$251,$A49) -> 0 | AI49: =SUMIFS(AK$3:AK$77,$A$3:$A$77,$A49) -> 1 | AJ49: =IF(SUM(AY49:BB49)=0,0,IF(SUM(AS49:AV49)=SUM(AY49:BB49),1,0)) -> 0 | AK49: 1 | AM49: =SUMIFS(AO$3:AO$251,$A$3:$A$251,$A49) -> 1 | AN49: =SUMIFS(AP$3:AP$251,$A$3:$A$251,$A49) -> 1 | AO49: =IF(SUM(AS49:AV49)=SUM(AY49:BB49),1,0) -> 1 | AP49: 1 | AR49: =SUM(AS49:AV49) -> 0 | AS49: =IF(OR(G49="",G49="TBD",G49="N/A",G49="SDK",G49="SAAS"),0,1) -> 0 | AT49: =IF(OR(H49="",H49="TBD",H49="N/A",H49="SDK",H49="SAAS"),0,1) -> 0 | AU49: =IF(OR(I49="",I49="TBD",I49="N/A",I49="SDK",I49="SAAS"),0,1) -> 0 | AV49: =IF(OR(J49="",J49="TBD",J49="N/A",J49="SDK",J49="SAAS"),0,1) -> 0 | AX49: =SUM(AY49:BB49) -> 0 | AY49: =IF(OR(G49="",G49="N/A",G49="SDK",G49="SAAS"),0,1) -> 0 | AZ49: =IF(OR(H49="",H49="N/A",H49="SDK",H49="SAAS"),0,1) -> 0 | BA49: =IF(OR(I49="",I49="N/A",I49="SDK",I49="SAAS"),0,1) -> 0 | BB49: =IF(OR(J49="",J49="N/A",J49="SDK",J49="SAAS"),0,1) -> 0
A50: OB - 001 | B50: Onboarding | C50: Supervisar la actividad de los usuarios y/o sitios digitales relacionados con el contenido y las aplicaciones | F50: TBD | G50: TBD | H50: TBD | I50: TBD | J50: TBD | M50: =L50*$L$147 -> 0 | N50: Backlog | O50: Rafael Elizalde | P50: x | X50: Sí | Y50: Por definir | AD50: =IF(AI50=0,0,IF(AH50=AI50,1,0))*AF50 -> 0 | AE50: =IF(AM50=AN50,1,0)*AF50 -> 0 | AF50: =IF(ISNUMBER(MATCH(A50,$A$2:A49,0)),0,1) -> 1 | AH50: =SUMIFS(AJ$3:AJ$251,$A$3:$A$251,$A50) -> 0 | AI50: =SUMIFS(AK$3:AK$77,$A$3:$A$77,$A50) -> 1 | AJ50: =IF(SUM(AY50:BB50)=0,0,IF(SUM(AS50:AV50)=SUM(AY50:BB50),1,0)) -> 0 | AK50: 1 | AM50: =SUMIFS(AO$3:AO$251,$A$3:$A$251,$A50) -> 0 | AN50: =SUMIFS(AP$3:AP$251,$A$3:$A$251,$A50) -> 1 | AO50: =IF(SUM(AS50:AV50)=SUM(AY50:BB50),1,0) -> 0 | AP50: 1 | AR50: =SUM(AS50:AV50) -> 0 | AS50: =IF(OR(G50="",G50="TBD",G50="N/A",G50="SDK",G50="SAAS"),0,1) -> 0 | AT50: =IF(OR(H50="",H50="TBD",H50="N/A",H50="SDK",H50="SAAS"),0,1) -> 0 | AU50: =IF(OR(I50="",I50="TBD",I50="N/A",I50="SDK",I50="SAAS"),0,1) -> 0 | AV50: =IF(OR(J50="",J50="TBD",J50="N/A",J50="SDK",J50="SAAS"),0,1) -> 0 | AX50: =SUM(AY50:BB50) -> 4 | AY50: =IF(OR(G50="",G50="N/A",G50="SDK",G50="SAAS"),0,1) -> 1 | AZ50: =IF(OR(H50="",H50="N/A",H50="SDK",H50="SAAS"),0,1) -> 1 | BA50: =IF(OR(I50="",I50="N/A",I50="SDK",I50="SAAS"),0,1) -> 1 | BB50: =IF(OR(J50="",J50="N/A",J50="SDK",J50="SAAS"),0,1) -> 1
A51: OB - 002 | B51: Onboarding | C51: Creación de expediente digital cliente BanCoppel | F51: TBD | G51: TBD | H51: TBD | I51: TBD | J51: TBD | M51: =L51*$L$147 -> 0 | N51: Backlog | O51: Rafael Elizalde | P51: x | X51: Sí | Y51: Por definir | AD51: =IF(AI51=0,0,IF(AH51=AI51,1,0))*AF51 -> 0 | AE51: =IF(AM51=AN51,1,0)*AF51 -> 0 | AF51: =IF(ISNUMBER(MATCH(A51,$A$2:A50,0)),0,1) -> 1 | AH51: =SUMIFS(AJ$3:AJ$251,$A$3:$A$251,$A51) -> 0 | AI51: =SUMIFS(AK$3:AK$77,$A$3:$A$77,$A51) -> 1 | AJ51: =IF(SUM(AY51:BB51)=0,0,IF(SUM(AS51:AV51)=SUM(AY51:BB51),1,0)) -> 0 | AK51: 1 | AM51: =SUMIFS(AO$3:AO$251,$A$3:$A$251,$A51) -> 0 | AN51: =SUMIFS(AP$3:AP$251,$A$3:$A$251,$A51) -> 1 | AO51: =IF(SUM(AS51:AV51)=SUM(AY51:BB51),1,0) -> 0 | AP51: 1 | AR51: =SUM(AS51:AV51) -> 0 | AS51: =IF(OR(G51="",G51="TBD",G51="N/A",G51="SDK",G51="SAAS"),0,1) -> 0 | AT51: =IF(OR(H51="",H51="TBD",H51="N/A",H51="SDK",H51="SAAS"),0,1) -> 0 | AU51: =IF(OR(I51="",I51="TBD",I51="N/A",I51="SDK",I51="SAAS"),0,1) -> 0 | AV51: =IF(OR(J51="",J51="TBD",J51="N/A",J51="SDK",J51="SAAS"),0,1) -> 0 | AX51: =SUM(AY51:BB51) -> 4 | AY51: =IF(OR(G51="",G51="N/A",G51="SDK",G51="SAAS"),0,1) -> 1 | AZ51: =IF(OR(H51="",H51="N/A",H51="SDK",H51="SAAS"),0,1) -> 1 | BA51: =IF(OR(I51="",I51="N/A",I51="SDK",I51="SAAS"),0,1) -> 1 | BB51: =IF(OR(J51="",J51="N/A",J51="SDK",J51="SAAS"),0,1) -> 1
A52: OB - 003 | B52: Onboarding | C52: Carga de documentos en expediente | G52: TBD | H52: TBD | I52: TBD | J52: TBD | M52: =L52*$L$147 -> 0 | N52: Backlog | O52: Rafael Elizalde | P52: x | X52: Sí | Y52: Por definir | AD52: =IF(AI52=0,0,IF(AH52=AI52,1,0))*AF52 -> 0 | AE52: =IF(AM52=AN52,1,0)*AF52 -> 0 | AF52: =IF(ISNUMBER(MATCH(A52,$A$2:A51,0)),0,1) -> 1 | AH52: =SUMIFS(AJ$3:AJ$251,$A$3:$A$251,$A52) -> 0 | AI52: =SUMIFS(AK$3:AK$77,$A$3:$A$77,$A52) -> 1 | AJ52: =IF(SUM(AY52:BB52)=0,0,IF(SUM(AS52:AV52)=SUM(AY52:BB52),1,0)) -> 0 | AK52: 1 | AM52: =SUMIFS(AO$3:AO$251,$A$3:$A$251,$A52) -> 0 | AN52: =SUMIFS(AP$3:AP$251,$A$3:$A$251,$A52) -> 1 | AO52: =IF(SUM(AS52:AV52)=SUM(AY52:BB52),1,0) -> 0 | AP52: 1 | AR52: =SUM(AS52:AV52) -> 0 | AS52: =IF(OR(G52="",G52="TBD",G52="N/A",G52="SDK",G52="SAAS"),0,1) -> 0 | AT52: =IF(OR(H52="",H52="TBD",H52="N/A",H52="SDK",H52="SAAS"),0,1) -> 0 | AU52: =IF(OR(I52="",I52="TBD",I52="N/A",I52="SDK",I52="SAAS"),0,1) -> 0 | AV52: =IF(OR(J52="",J52="TBD",J52="N/A",J52="SDK",J52="SAAS"),0,1) -> 0 | AX52: =SUM(AY52:BB52) -> 4 | AY52: =IF(OR(G52="",G52="N/A",G52="SDK",G52="SAAS"),0,1) -> 1 | AZ52: =IF(OR(H52="",H52="N/A",H52="SDK",H52="SAAS"),0,1) -> 1 | BA52: =IF(OR(I52="",I52="N/A",I52="SDK",I52="SAAS"),0,1) -> 1 | BB52: =IF(OR(J52="",J52="N/A",J52="SDK",J52="SAAS"),0,1) -> 1
A53: OB - 004 | B53: Onboarding | C53: Búsqueda por metadata Expediente digital | F53: TBD | G53: TBD | H53: TBD | I53: TBD | J53: TBD | M53: =L53*$L$147 -> 0 | N53: Backlog | O53: Rafael Elizalde | P53: x | X53: Sí | Y53: Por definir | AD53: =IF(AI53=0,0,IF(AH53=AI53,1,0))*AF53 -> 0 | AE53: =IF(AM53=AN53,1,0)*AF53 -> 0 | AF53: =IF(ISNUMBER(MATCH(A53,$A$2:A52,0)),0,1) -> 1 | AH53: =SUMIFS(AJ$3:AJ$251,$A$3:$A$251,$A53) -> 0 | AI53: =SUMIFS(AK$3:AK$77,$A$3:$A$77,$A53) -> 1 | AJ53: =IF(SUM(AY53:BB53)=0,0,IF(SUM(AS53:AV53)=SUM(AY53:BB53),1,0)) -> 0 | AK53: 1 | AM53: =SUMIFS(AO$3:AO$251,$A$3:$A$251,$A53) -> 0 | AN53: =SUMIFS(AP$3:AP$251,$A$3:$A$251,$A53) -> 1 | AO53: =IF(SUM(AS53:AV53)=SUM(AY53:BB53),1,0) -> 0 | AP53: 1 | AR53: =SUM(AS53:AV53) -> 0 | AS53: =IF(OR(G53="",G53="TBD",G53="N/A",G53="SDK",G53="SAAS"),0,1) -> 0 | AT53: =IF(OR(H53="",H53="TBD",H53="N/A",H53="SDK",H53="SAAS"),0,1) -> 0 | AU53: =IF(OR(I53="",I53="TBD",I53="N/A",I53="SDK",I53="SAAS"),0,1) -> 0 | AV53: =IF(OR(J53="",J53="TBD",J53="N/A",J53="SDK",J53="SAAS"),0,1) -> 0 | AX53: =SUM(AY53:BB53) -> 4 | AY53: =IF(OR(G53="",G53="N/A",G53="SDK",G53="SAAS"),0,1) -> 1 | AZ53: =IF(OR(H53="",H53="N/A",H53="SDK",H53="SAAS"),0,1) -> 1 | BA53: =IF(OR(I53="",I53="N/A",I53="SDK",I53="SAAS"),0,1) -> 1 | BB53: =IF(OR(J53="",J53="N/A",J53="SDK",J53="SAAS"),0,1) -> 1
A54: OB - 005 | B54: Onboarding | C54: Métricas de expediente digital | F54: TBD | G54: TBD | H54: TBD | I54: TBD | J54: TBD | M54: =L54*$L$147 -> 0 | N54: Backlog | O54: Rafael Elizalde | P54: x | X54: Sí | Y54: Por definir | AD54: =IF(AI54=0,0,IF(AH54=AI54,1,0))*AF54 -> 0 | AE54: =IF(AM54=AN54,1,0)*AF54 -> 0 | AF54: =IF(ISNUMBER(MATCH(A54,$A$2:A53,0)),0,1) -> 1 | AH54: =SUMIFS(AJ$3:AJ$251,$A$3:$A$251,$A54) -> 0 | AI54: =SUMIFS(AK$3:AK$77,$A$3:$A$77,$A54) -> 1 | AJ54: =IF(SUM(AY54:BB54)=0,0,IF(SUM(AS54:AV54)=SUM(AY54:BB54),1,0)) -> 0 | AK54: 1 | AM54: =SUMIFS(AO$3:AO$251,$A$3:$A$251,$A54) -> 0 | AN54: =SUMIFS(AP$3:AP$251,$A$3:$A$251,$A54) -> 1 | AO54: =IF(SUM(AS54:AV54)=SUM(AY54:BB54),1,0) -> 0 | AP54: 1 | AR54: =SUM(AS54:AV54) -> 0 | AS54: =IF(OR(G54="",G54="TBD",G54="N/A",G54="SDK",G54="SAAS"),0,1) -> 0 | AT54: =IF(OR(H54="",H54="TBD",H54="N/A",H54="SDK",H54="SAAS"),0,1) -> 0 | AU54: =IF(OR(I54="",I54="TBD",I54="N/A",I54="SDK",I54="SAAS"),0,1) -> 0 | AV54: =IF(OR(J54="",J54="TBD",J54="N/A",J54="SDK",J54="SAAS"),0,1) -> 0 | AX54: =SUM(AY54:BB54) -> 4 | AY54: =IF(OR(G54="",G54="N/A",G54="SDK",G54="SAAS"),0,1) -> 1 | AZ54: =IF(OR(H54="",H54="N/A",H54="SDK",H54="SAAS"),0,1) -> 1 | BA54: =IF(OR(I54="",I54="N/A",I54="SDK",I54="SAAS"),0,1) -> 1 | BB54: =IF(OR(J54="",J54="N/A",J54="SDK",J54="SAAS"),0,1) -> 1
A55: OB - 006 | B55: Onboarding | C55: Validaciones sobre vigencia de documentos | F55: TBD | G55: TBD | H55: TBD | I55: TBD | J55: TBD | M55: =L55*$L$147 -> 0 | N55: Backlog | O55: Rafael Elizalde | P55: x | X55: Sí | Y55: Por definir | AD55: =IF(AI55=0,0,IF(AH55=AI55,1,0))*AF55 -> 0 | AE55: =IF(AM55=AN55,1,0)*AF55 -> 0 | AF55: =IF(ISNUMBER(MATCH(A55,$A$2:A54,0)),0,1) -> 1 | AH55: =SUMIFS(AJ$3:AJ$251,$A$3:$A$251,$A55) -> 0 | AI55: =SUMIFS(AK$3:AK$77,$A$3:$A$77,$A55) -> 1 | AJ55: =IF(SUM(AY55:BB55)=0,0,IF(SUM(AS55:AV55)=SUM(AY55:BB55),1,0)) -> 0 | AK55: 1 | AM55: =SUMIFS(AO$3:AO$251,$A$3:$A$251,$A55) -> 0 | AN55: =SUMIFS(AP$3:AP$251,$A$3:$A$251,$A55) -> 1 | AO55: =IF(SUM(AS55:AV55)=SUM(AY55:BB55),1,0) -> 0 | AP55: 1 | AR55: =SUM(AS55:AV55) -> 0 | AS55: =IF(OR(G55="",G55="TBD",G55="N/A",G55="SDK",G55="SAAS"),0,1) -> 0 | AT55: =IF(OR(H55="",H55="TBD",H55="N/A",H55="SDK",H55="SAAS"),0,1) -> 0 | AU55: =IF(OR(I55="",I55="TBD",I55="N/A",I55="SDK",I55="SAAS"),0,1) -> 0 | AV55: =IF(OR(J55="",J55="TBD",J55="N/A",J55="SDK",J55="SAAS"),0,1) -> 0 | AX55: =SUM(AY55:BB55) -> 4 | AY55: =IF(OR(G55="",G55="N/A",G55="SDK",G55="SAAS"),0,1) -> 1 | AZ55: =IF(OR(H55="",H55="N/A",H55="SDK",H55="SAAS"),0,1) -> 1 | BA55: =IF(OR(I55="",I55="N/A",I55="SDK",I55="SAAS"),0,1) -> 1 | BB55: =IF(OR(J55="",J55="N/A",J55="SDK",J55="SAAS"),0,1) -> 1
A56: OB - 007 | B56: Onboarding | C56: Visor de expediente digital | F56: TBD | G56: TBD | H56: TBD | I56: TBD | J56: TBD | M56: =L56*$L$147 -> 0 | N56: Backlog | O56: Rafael Elizalde | P56: x | X56: Sí | Y56: Por definir | AD56: =IF(AI56=0,0,IF(AH56=AI56,1,0))*AF56 -> 0 | AE56: =IF(AM56=AN56,1,0)*AF56 -> 0 | AF56: =IF(ISNUMBER(MATCH(A56,$A$2:A55,0)),0,1) -> 1 | AH56: =SUMIFS(AJ$3:AJ$251,$A$3:$A$251,$A56) -> 0 | AI56: =SUMIFS(AK$3:AK$77,$A$3:$A$77,$A56) -> 1 | AJ56: =IF(SUM(AY56:BB56)=0,0,IF(SUM(AS56:AV56)=SUM(AY56:BB56),1,0)) -> 0 | AK56: 1 | AM56: =SUMIFS(AO$3:AO$251,$A$3:$A$251,$A56) -> 0 | AN56: =SUMIFS(AP$3:AP$251,$A$3:$A$251,$A56) -> 1 | AO56: =IF(SUM(AS56:AV56)=SUM(AY56:BB56),1,0) -> 0 | AP56: 1 | AR56: =SUM(AS56:AV56) -> 0 | AS56: =IF(OR(G56="",G56="TBD",G56="N/A",G56="SDK",G56="SAAS"),0,1) -> 0 | AT56: =IF(OR(H56="",H56="TBD",H56="N/A",H56="SDK",H56="SAAS"),0,1) -> 0 | AU56: =IF(OR(I56="",I56="TBD",I56="N/A",I56="SDK",I56="SAAS"),0,1) -> 0 | AV56: =IF(OR(J56="",J56="TBD",J56="N/A",J56="SDK",J56="SAAS"),0,1) -> 0 | AX56: =SUM(AY56:BB56) -> 4 | AY56: =IF(OR(G56="",G56="N/A",G56="SDK",G56="SAAS"),0,1) -> 1 | AZ56: =IF(OR(H56="",H56="N/A",H56="SDK",H56="SAAS"),0,1) -> 1 | BA56: =IF(OR(I56="",I56="N/A",I56="SDK",I56="SAAS"),0,1) -> 1 | BB56: =IF(OR(J56="",J56="N/A",J56="SDK",J56="SAAS"),0,1) -> 1
A57: EX - 001 | B57: Onboarding | C57: Motor de reglas de decisión para flujo de proceso | F57: TBD | G57: TBD | H57: TBD | I57: TBD | J57: TBD | L57: 47 | M57: =L57*$L$147 -> 164.5 | N57: Backlog | O57: Rafael Elizalde | P57: x | X57: Sí | Y57: Por definir | AD57: =IF(AI57=0,0,IF(AH57=AI57,1,0))*AF57 -> 0 | AE57: =IF(AM57=AN57,1,0)*AF57 -> 0 | AF57: =IF(ISNUMBER(MATCH(A57,$A$2:A56,0)),0,1) -> 1 | AH57: =SUMIFS(AJ$3:AJ$251,$A$3:$A$251,$A57) -> 0 | AI57: =SUMIFS(AK$3:AK$77,$A$3:$A$77,$A57) -> 1 | AJ57: =IF(SUM(AY57:BB57)=0,0,IF(SUM(AS57:AV57)=SUM(AY57:BB57),1,0)) -> 0 | AK57: 1 | AM57: =SUMIFS(AO$3:AO$251,$A$3:$A$251,$A57) -> 0 | AN57: =SUMIFS(AP$3:AP$251,$A$3:$A$251,$A57) -> 1 | AO57: =IF(SUM(AS57:AV57)=SUM(AY57:BB57),1,0) -> 0 | AP57: 1 | AR57: =SUM(AS57:AV57) -> 0 | AS57: =IF(OR(G57="",G57="TBD",G57="N/A",G57="SDK",G57="SAAS"),0,1) -> 0 | AT57: =IF(OR(H57="",H57="TBD",H57="N/A",H57="SDK",H57="SAAS"),0,1) -> 0 | AU57: =IF(OR(I57="",I57="TBD",I57="N/A",I57="SDK",I57="SAAS"),0,1) -> 0 | AV57: =IF(OR(J57="",J57="TBD",J57="N/A",J57="SDK",J57="SAAS"),0,1) -> 0 | AX57: =SUM(AY57:BB57) -> 4 | AY57: =IF(OR(G57="",G57="N/A",G57="SDK",G57="SAAS"),0,1) -> 1 | AZ57: =IF(OR(H57="",H57="N/A",H57="SDK",H57="SAAS"),0,1) -> 1 | BA57: =IF(OR(I57="",I57="N/A",I57="SDK",I57="SAAS"),0,1) -> 1 | BB57: =IF(OR(J57="",J57="N/A",J57="SDK",J57="SAAS"),0,1) -> 1
A58: EX - 002 | B58: Onboarding | C58: Inventario de reglas desacoplado | F58: TBD | G58: TBD | H58: TBD | I58: TBD | J58: TBD | L58: 12 | M58: =L58*$L$147 -> 42 | N58: Backlog | O58: Rafael Elizalde | P58: x | X58: Sí | Y58: Por definir | AD58: =IF(AI58=0,0,IF(AH58=AI58,1,0))*AF58 -> 0 | AE58: =IF(AM58=AN58,1,0)*AF58 -> 0 | AF58: =IF(ISNUMBER(MATCH(A58,$A$2:A57,0)),0,1) -> 1 | AH58: =SUMIFS(AJ$3:AJ$251,$A$3:$A$251,$A58) -> 0 | AI58: =SUMIFS(AK$3:AK$77,$A$3:$A$77,$A58) -> 1 | AJ58: =IF(SUM(AY58:BB58)=0,0,IF(SUM(AS58:AV58)=SUM(AY58:BB58),1,0)) -> 0 | AK58: 1 | AM58: =SUMIFS(AO$3:AO$251,$A$3:$A$251,$A58) -> 0 | AN58: =SUMIFS(AP$3:AP$251,$A$3:$A$251,$A58) -> 1 | AO58: =IF(SUM(AS58:AV58)=SUM(AY58:BB58),1,0) -> 0 | AP58: 1 | AR58: =SUM(AS58:AV58) -> 0 | AS58: =IF(OR(G58="",G58="TBD",G58="N/A",G58="SDK",G58="SAAS"),0,1) -> 0 | AT58: =IF(OR(H58="",H58="TBD",H58="N/A",H58="SDK",H58="SAAS"),0,1) -> 0 | AU58: =IF(OR(I58="",I58="TBD",I58="N/A",I58="SDK",I58="SAAS"),0,1) -> 0 | AV58: =IF(OR(J58="",J58="TBD",J58="N/A",J58="SDK",J58="SAAS"),0,1) -> 0 | AX58: =SUM(AY58:BB58) -> 4 | AY58: =IF(OR(G58="",G58="N/A",G58="SDK",G58="SAAS"),0,1) -> 1 | AZ58: =IF(OR(H58="",H58="N/A",H58="SDK",H58="SAAS"),0,1) -> 1 | BA58: =IF(OR(I58="",I58="N/A",I58="SDK",I58="SAAS"),0,1) -> 1 | BB58: =IF(OR(J58="",J58="N/A",J58="SDK",J58="SAAS"),0,1) -> 1
A59: EX - 003 | B59: Onboarding | C59: Arboles y tablas de decisión para diseño de reglas | F59: TBD | G59: TBD | H59: TBD | I59: TBD | J59: TBD | M59: =L59*$L$147 -> 0 | N59: Backlog | O59: Rafael Elizalde | P59: x | X59: Sí | Y59: Por definir | AD59: =IF(AI59=0,0,IF(AH59=AI59,1,0))*AF59 -> 0 | AE59: =IF(AM59=AN59,1,0)*AF59 -> 0 | AF59: =IF(ISNUMBER(MATCH(A59,$A$2:A58,0)),0,1) -> 1 | AH59: =SUMIFS(AJ$3:AJ$251,$A$3:$A$251,$A59) -> 0 | AI59: =SUMIFS(AK$3:AK$77,$A$3:$A$77,$A59) -> 1 | AJ59: =IF(SUM(AY59:BB59)=0,0,IF(SUM(AS59:AV59)=SUM(AY59:BB59),1,0)) -> 0 | AK59: 1 | AM59: =SUMIFS(AO$3:AO$251,$A$3:$A$251,$A59) -> 0 | AN59: =SUMIFS(AP$3:AP$251,$A$3:$A$251,$A59) -> 1 | AO59: =IF(SUM(AS59:AV59)=SUM(AY59:BB59),1,0) -> 0 | AP59: 1 | AR59: =SUM(AS59:AV59) -> 0 | AS59: =IF(OR(G59="",G59="TBD",G59="N/A",G59="SDK",G59="SAAS"),0,1) -> 0 | AT59: =IF(OR(H59="",H59="TBD",H59="N/A",H59="SDK",H59="SAAS"),0,1) -> 0 | AU59: =IF(OR(I59="",I59="TBD",I59="N/A",I59="SDK",I59="SAAS"),0,1) -> 0 | AV59: =IF(OR(J59="",J59="TBD",J59="N/A",J59="SDK",J59="SAAS"),0,1) -> 0 | AX59: =SUM(AY59:BB59) -> 4 | AY59: =IF(OR(G59="",G59="N/A",G59="SDK",G59="SAAS"),0,1) -> 1 | AZ59: =IF(OR(H59="",H59="N/A",H59="SDK",H59="SAAS"),0,1) -> 1 | BA59: =IF(OR(I59="",I59="N/A",I59="SDK",I59="SAAS"),0,1) -> 1 | BB59: =IF(OR(J59="",J59="N/A",J59="SDK",J59="SAAS"),0,1) -> 1
A60: EX - 004 | B60: Onboarding | C60: INTL Buro de credito | F60: TBD | G60: TBD | H60: TBD | I60: TBD | J60: TBD | M60: =L60*$L$147 -> 0 | N60: Backlog | O60: Rafael Elizalde | P60: x | X60: Sí | Y60: Por definir | AD60: =IF(AI60=0,0,IF(AH60=AI60,1,0))*AF60 -> 0 | AE60: =IF(AM60=AN60,1,0)*AF60 -> 0 | AF60: =IF(ISNUMBER(MATCH(A60,$A$2:A59,0)),0,1) -> 1 | AH60: =SUMIFS(AJ$3:AJ$251,$A$3:$A$251,$A60) -> 0 | AI60: =SUMIFS(AK$3:AK$77,$A$3:$A$77,$A60) -> 1 | AJ60: =IF(SUM(AY60:BB60)=0,0,IF(SUM(AS60:AV60)=SUM(AY60:BB60),1,0)) -> 0 | AK60: 1 | AM60: =SUMIFS(AO$3:AO$251,$A$3:$A$251,$A60) -> 0 | AN60: =SUMIFS(AP$3:AP$251,$A$3:$A$251,$A60) -> 1 | AO60: =IF(SUM(AS60:AV60)=SUM(AY60:BB60),1,0) -> 0 | AP60: 1 | AR60: =SUM(AS60:AV60) -> 0 | AS60: =IF(OR(G60="",G60="TBD",G60="N/A",G60="SDK",G60="SAAS"),0,1) -> 0 | AT60: =IF(OR(H60="",H60="TBD",H60="N/A",H60="SDK",H60="SAAS"),0,1) -> 0 | AU60: =IF(OR(I60="",I60="TBD",I60="N/A",I60="SDK",I60="SAAS"),0,1) -> 0 | AV60: =IF(OR(J60="",J60="TBD",J60="N/A",J60="SDK",J60="SAAS"),0,1) -> 0 | AX60: =SUM(AY60:BB60) -> 4 | AY60: =IF(OR(G60="",G60="N/A",G60="SDK",G60="SAAS"),0,1) -> 1 | AZ60: =IF(OR(H60="",H60="N/A",H60="SDK",H60="SAAS"),0,1) -> 1 | BA60: =IF(OR(I60="",I60="N/A",I60="SDK",I60="SAAS"),0,1) -> 1 | BB60: =IF(OR(J60="",J60="N/A",J60="SDK",J60="SAAS"),0,1) -> 1
A61: WM - 001 | B61: Onboarding | C61: Gestion procesos de negocios via BPF | F61: TBD | G61: TBD | H61: TBD | I61: TBD | J61: TBD | M61: =L61*$L$147 -> 0 | N61: Backlog | O61: Rafael Elizalde | P61: x | X61: Sí | Y61: Por definir | AD61: =IF(AI61=0,0,IF(AH61=AI61,1,0))*AF61 -> 0 | AE61: =IF(AM61=AN61,1,0)*AF61 -> 0 | AF61: =IF(ISNUMBER(MATCH(A61,$A$2:A60,0)),0,1) -> 1 | AH61: =SUMIFS(AJ$3:AJ$251,$A$3:$A$251,$A61) -> 0 | AI61: =SUMIFS(AK$3:AK$77,$A$3:$A$77,$A61) -> 1 | AJ61: =IF(SUM(AY61:BB61)=0,0,IF(SUM(AS61:AV61)=SUM(AY61:BB61),1,0)) -> 0 | AK61: 1 | AM61: =SUMIFS(AO$3:AO$251,$A$3:$A$251,$A61) -> 0 | AN61: =SUMIFS(AP$3:AP$251,$A$3:$A$251,$A61) -> 1 | AO61: =IF(SUM(AS61:AV61)=SUM(AY61:BB61),1,0) -> 0 | AP61: 1 | AR61: =SUM(AS61:AV61) -> 0 | AS61: =IF(OR(G61="",G61="TBD",G61="N/A",G61="SDK",G61="SAAS"),0,1) -> 0 | AT61: =IF(OR(H61="",H61="TBD",H61="N/A",H61="SDK",H61="SAAS"),0,1) -> 0 | AU61: =IF(OR(I61="",I61="TBD",I61="N/A",I61="SDK",I61="SAAS"),0,1) -> 0 | AV61: =IF(OR(J61="",J61="TBD",J61="N/A",J61="SDK",J61="SAAS"),0,1) -> 0 | AX61: =SUM(AY61:BB61) -> 4 | AY61: =IF(OR(G61="",G61="N/A",G61="SDK",G61="SAAS"),0,1) -> 1 | AZ61: =IF(OR(H61="",H61="N/A",H61="SDK",H61="SAAS"),0,1) -> 1 | BA61: =IF(OR(I61="",I61="N/A",I61="SDK",I61="SAAS"),0,1) -> 1 | BB61: =IF(OR(J61="",J61="N/A",J61="SDK",J61="SAAS"),0,1) -> 1
A62: WM - 002 | B62: Onboarding | C62: Medicion y funnel de usuarios basado en BPMS | F62: TBD | G62: TBD | H62: TBD | I62: TBD | J62: TBD | M62: =L62*$L$147 -> 0 | N62: Backlog | O62: Rafael Elizalde | P62: x | X62: Sí | Y62: Por definir | AD62: =IF(AI62=0,0,IF(AH62=AI62,1,0))*AF62 -> 0 | AE62: =IF(AM62=AN62,1,0)*AF62 -> 0 | AF62: =IF(ISNUMBER(MATCH(A62,$A$2:A61,0)),0,1) -> 1 | AH62: =SUMIFS(AJ$3:AJ$251,$A$3:$A$251,$A62) -> 0 | AI62: =SUMIFS(AK$3:AK$77,$A$3:$A$77,$A62) -> 1 | AJ62: =IF(SUM(AY62:BB62)=0,0,IF(SUM(AS62:AV62)=SUM(AY62:BB62),1,0)) -> 0 | AK62: 1 | AM62: =SUMIFS(AO$3:AO$251,$A$3:$A$251,$A62) -> 0 | AN62: =SUMIFS(AP$3:AP$251,$A$3:$A$251,$A62) -> 1 | AO62: =IF(SUM(AS62:AV62)=SUM(AY62:BB62),1,0) -> 0 | AP62: 1 | AR62: =SUM(AS62:AV62) -> 0 | AS62: =IF(OR(G62="",G62="TBD",G62="N/A",G62="SDK",G62="SAAS"),0,1) -> 0 | AT62: =IF(OR(H62="",H62="TBD",H62="N/A",H62="SDK",H62="SAAS"),0,1) -> 0 | AU62: =IF(OR(I62="",I62="TBD",I62="N/A",I62="SDK",I62="SAAS"),0,1) -> 0 | AV62: =IF(OR(J62="",J62="TBD",J62="N/A",J62="SDK",J62="SAAS"),0,1) -> 0 | AX62: =SUM(AY62:BB62) -> 4 | AY62: =IF(OR(G62="",G62="N/A",G62="SDK",G62="SAAS"),0,1) -> 1 | AZ62: =IF(OR(H62="",H62="N/A",H62="SDK",H62="SAAS"),0,1) -> 1 | BA62: =IF(OR(I62="",I62="N/A",I62="SDK",I62="SAAS"),0,1) -> 1 | BB62: =IF(OR(J62="",J62="N/A",J62="SDK",J62="SAAS"),0,1) -> 1
A63: WM - 003 | B63: Onboarding | C63: Procesos de negocio desacoplados | F63: TBD | G63: TBD | H63: TBD | I63: TBD | J63: TBD | M63: =L63*$L$147 -> 0 | N63: Backlog | O63: Rafael Elizalde | P63: x | X63: Sí | Y63: Por definir | AD63: =IF(AI63=0,0,IF(AH63=AI63,1,0))*AF63 -> 0 | AE63: =IF(AM63=AN63,1,0)*AF63 -> 0 | AF63: =IF(ISNUMBER(MATCH(A63,$A$2:A62,0)),0,1) -> 1 | AH63: =SUMIFS(AJ$3:AJ$251,$A$3:$A$251,$A63) -> 0 | AI63: =SUMIFS(AK$3:AK$77,$A$3:$A$77,$A63) -> 1 | AJ63: =IF(SUM(AY63:BB63)=0,0,IF(SUM(AS63:AV63)=SUM(AY63:BB63),1,0)) -> 0 | AK63: 1 | AM63: =SUMIFS(AO$3:AO$251,$A$3:$A$251,$A63) -> 0 | AN63: =SUMIFS(AP$3:AP$251,$A$3:$A$251,$A63) -> 1 | AO63: =IF(SUM(AS63:AV63)=SUM(AY63:BB63),1,0) -> 0 | AP63: 1 | AR63: =SUM(AS63:AV63) -> 0 | AS63: =IF(OR(G63="",G63="TBD",G63="N/A",G63="SDK",G63="SAAS"),0,1) -> 0 | AT63: =IF(OR(H63="",H63="TBD",H63="N/A",H63="SDK",H63="SAAS"),0,1) -> 0 | AU63: =IF(OR(I63="",I63="TBD",I63="N/A",I63="SDK",I63="SAAS"),0,1) -> 0 | AV63: =IF(OR(J63="",J63="TBD",J63="N/A",J63="SDK",J63="SAAS"),0,1) -> 0 | AX63: =SUM(AY63:BB63) -> 4 | AY63: =IF(OR(G63="",G63="N/A",G63="SDK",G63="SAAS"),0,1) -> 1 | AZ63: =IF(OR(H63="",H63="N/A",H63="SDK",H63="SAAS"),0,1) -> 1 | BA63: =IF(OR(I63="",I63="N/A",I63="SDK",I63="SAAS"),0,1) -> 1 | BB63: =IF(OR(J63="",J63="N/A",J63="SDK",J63="SAAS"),0,1) -> 1
A64: WM - 004 | B64: Onboarding | C64: Orquestación de proceso de negocio via BPMS | F64: TBD | G64: TBD | H64: TBD | I64: TBD | J64: TBD | L64: 5 | M64: =L64*$L$147 -> 17.5 | N64: Backlog | O64: Rafael Elizalde | P64: x | X64: Sí | Y64: Por definir | AD64: =IF(AI64=0,0,IF(AH64=AI64,1,0))*AF64 -> 0 | AE64: =IF(AM64=AN64,1,0)*AF64 -> 0 | AF64: =IF(ISNUMBER(MATCH(A64,$A$2:A63,0)),0,1) -> 1 | AH64: =SUMIFS(AJ$3:AJ$251,$A$3:$A$251,$A64) -> 0 | AI64: =SUMIFS(AK$3:AK$77,$A$3:$A$77,$A64) -> 1 | AJ64: =IF(SUM(AY64:BB64)=0,0,IF(SUM(AS64:AV64)=SUM(AY64:BB64),1,0)) -> 0 | AK64: 1 | AM64: =SUMIFS(AO$3:AO$251,$A$3:$A$251,$A64) -> 0 | AN64: =SUMIFS(AP$3:AP$251,$A$3:$A$251,$A64) -> 1 | AO64: =IF(SUM(AS64:AV64)=SUM(AY64:BB64),1,0) -> 0 | AP64: 1 | AR64: =SUM(AS64:AV64) -> 0 | AS64: =IF(OR(G64="",G64="TBD",G64="N/A",G64="SDK",G64="SAAS"),0,1) -> 0 | AT64: =IF(OR(H64="",H64="TBD",H64="N/A",H64="SDK",H64="SAAS"),0,1) -> 0 | AU64: =IF(OR(I64="",I64="TBD",I64="N/A",I64="SDK",I64="SAAS"),0,1) -> 0 | AV64: =IF(OR(J64="",J64="TBD",J64="N/A",J64="SDK",J64="SAAS"),0,1) -> 0 | AX64: =SUM(AY64:BB64) -> 4 | AY64: =IF(OR(G64="",G64="N/A",G64="SDK",G64="SAAS"),0,1) -> 1 | AZ64: =IF(OR(H64="",H64="N/A",H64="SDK",H64="SAAS"),0,1) -> 1 | BA64: =IF(OR(I64="",I64="N/A",I64="SDK",I64="SAAS"),0,1) -> 1 | BB64: =IF(OR(J64="",J64="N/A",J64="SDK",J64="SAAS"),0,1) -> 1
A65: WM - 005 | B65: Onboarding | C65: Contratos de información canónicos | F65: TBD | G65: TBD | H65: TBD | I65: TBD | J65: TBD | M65: =L65*$L$147 -> 0 | N65: Backlog | O65: Rafael Elizalde | P65: x | X65: Sí | Y65: Por definir | AD65: =IF(AI65=0,0,IF(AH65=AI65,1,0))*AF65 -> 0 | AE65: =IF(AM65=AN65,1,0)*AF65 -> 0 | AF65: =IF(ISNUMBER(MATCH(A65,$A$2:A64,0)),0,1) -> 1 | AH65: =SUMIFS(AJ$3:AJ$251,$A$3:$A$251,$A65) -> 0 | AI65: =SUMIFS(AK$3:AK$77,$A$3:$A$77,$A65) -> 1 | AJ65: =IF(SUM(AY65:BB65)=0,0,IF(SUM(AS65:AV65)=SUM(AY65:BB65),1,0)) -> 0 | AK65: 1 | AM65: =SUMIFS(AO$3:AO$251,$A$3:$A$251,$A65) -> 0 | AN65: =SUMIFS(AP$3:AP$251,$A$3:$A$251,$A65) -> 1 | AO65: =IF(SUM(AS65:AV65)=SUM(AY65:BB65),1,0) -> 0 | AP65: 1 | AR65: =SUM(AS65:AV65) -> 0 | AS65: =IF(OR(G65="",G65="TBD",G65="N/A",G65="SDK",G65="SAAS"),0,1) -> 0 | AT65: =IF(OR(H65="",H65="TBD",H65="N/A",H65="SDK",H65="SAAS"),0,1) -> 0 | AU65: =IF(OR(I65="",I65="TBD",I65="N/A",I65="SDK",I65="SAAS"),0,1) -> 0 | AV65: =IF(OR(J65="",J65="TBD",J65="N/A",J65="SDK",J65="SAAS"),0,1) -> 0 | AX65: =SUM(AY65:BB65) -> 4 | AY65: =IF(OR(G65="",G65="N/A",G65="SDK",G65="SAAS"),0,1) -> 1 | AZ65: =IF(OR(H65="",H65="N/A",H65="SDK",H65="SAAS"),0,1) -> 1 | BA65: =IF(OR(I65="",I65="N/A",I65="SDK",I65="SAAS"),0,1) -> 1 | BB65: =IF(OR(J65="",J65="N/A",J65="SDK",J65="SAAS"),0,1) -> 1
A66: PiPo - 001 | B66: Onboarding | C66: Dispersión de SMS | F66: TBD | G66: TBD | H66: TBD | I66: TBD | J66: TBD | M66: =L66*$L$147 -> 0 | N66: Backlog | O66: Rafael Elizalde | P66: x | X66: Sí | Y66: Por definir | AD66: =IF(AI66=0,0,IF(AH66=AI66,1,0))*AF66 -> 0 | AE66: =IF(AM66=AN66,1,0)*AF66 -> 0 | AF66: =IF(ISNUMBER(MATCH(A66,$A$2:A65,0)),0,1) -> 1 | AH66: =SUMIFS(AJ$3:AJ$251,$A$3:$A$251,$A66) -> 0 | AI66: =SUMIFS(AK$3:AK$77,$A$3:$A$77,$A66) -> 1 | AJ66: =IF(SUM(AY66:BB66)=0,0,IF(SUM(AS66:AV66)=SUM(AY66:BB66),1,0)) -> 0 | AK66: 1 | AM66: =SUMIFS(AO$3:AO$251,$A$3:$A$251,$A66) -> 0 | AN66: =SUMIFS(AP$3:AP$251,$A$3:$A$251,$A66) -> 1 | AO66: =IF(SUM(AS66:AV66)=SUM(AY66:BB66),1,0) -> 0 | AP66: 1 | AR66: =SUM(AS66:AV66) -> 0 | AS66: =IF(OR(G66="",G66="TBD",G66="N/A",G66="SDK",G66="SAAS"),0,1) -> 0 | AT66: =IF(OR(H66="",H66="TBD",H66="N/A",H66="SDK",H66="SAAS"),0,1) -> 0 | AU66: =IF(OR(I66="",I66="TBD",I66="N/A",I66="SDK",I66="SAAS"),0,1) -> 0 | AV66: =IF(OR(J66="",J66="TBD",J66="N/A",J66="SDK",J66="SAAS"),0,1) -> 0 | AX66: =SUM(AY66:BB66) -> 4 | AY66: =IF(OR(G66="",G66="N/A",G66="SDK",G66="SAAS"),0,1) -> 1 | AZ66: =IF(OR(H66="",H66="N/A",H66="SDK",H66="SAAS"),0,1) -> 1 | BA66: =IF(OR(I66="",I66="N/A",I66="SDK",I66="SAAS"),0,1) -> 1 | BB66: =IF(OR(J66="",J66="N/A",J66="SDK",J66="SAAS"),0,1) -> 1
A67: PiPo - 002 | B67: Onboarding | C67: Dispersión de Email (Welcome Kit) | F67: TBD | G67: TBD | H67: TBD | I67: TBD | J67: TBD | M67: =L67*$L$147 -> 0 | N67: Backlog | O67: Rafael Elizalde | P67: x | X67: Sí | Y67: Por definir | AD67: =IF(AI67=0,0,IF(AH67=AI67,1,0))*AF67 -> 0 | AE67: =IF(AM67=AN67,1,0)*AF67 -> 0 | AF67: =IF(ISNUMBER(MATCH(A67,$A$2:A66,0)),0,1) -> 1 | AH67: =SUMIFS(AJ$3:AJ$251,$A$3:$A$251,$A67) -> 0 | AI67: =SUMIFS(AK$3:AK$77,$A$3:$A$77,$A67) -> 1 | AJ67: =IF(SUM(AY67:BB67)=0,0,IF(SUM(AS67:AV67)=SUM(AY67:BB67),1,0)) -> 0 | AK67: 1 | AM67: =SUMIFS(AO$3:AO$251,$A$3:$A$251,$A67) -> 0 | AN67: =SUMIFS(AP$3:AP$251,$A$3:$A$251,$A67) -> 1 | AO67: =IF(SUM(AS67:AV67)=SUM(AY67:BB67),1,0) -> 0 | AP67: 1 | AR67: =SUM(AS67:AV67) -> 0 | AS67: =IF(OR(G67="",G67="TBD",G67="N/A",G67="SDK",G67="SAAS"),0,1) -> 0 | AT67: =IF(OR(H67="",H67="TBD",H67="N/A",H67="SDK",H67="SAAS"),0,1) -> 0 | AU67: =IF(OR(I67="",I67="TBD",I67="N/A",I67="SDK",I67="SAAS"),0,1) -> 0 | AV67: =IF(OR(J67="",J67="TBD",J67="N/A",J67="SDK",J67="SAAS"),0,1) -> 0 | AX67: =SUM(AY67:BB67) -> 4 | AY67: =IF(OR(G67="",G67="N/A",G67="SDK",G67="SAAS"),0,1) -> 1 | AZ67: =IF(OR(H67="",H67="N/A",H67="SDK",H67="SAAS"),0,1) -> 1 | BA67: =IF(OR(I67="",I67="N/A",I67="SDK",I67="SAAS"),0,1) -> 1 | BB67: =IF(OR(J67="",J67="N/A",J67="SDK",J67="SAAS"),0,1) -> 1
A68: EXP - 001 | B68: Onboarding | C68: Modelos de dictamen crediticio | F68: TBD | G68: TBD | H68: TBD | I68: TBD | J68: TBD | M68: =L68*$L$147 -> 0 | N68: Backlog | O68: Rafael Elizalde | P68: x | X68: Sí | Y68: Por definir | AD68: =IF(AI68=0,0,IF(AH68=AI68,1,0))*AF68 -> 0 | AE68: =IF(AM68=AN68,1,0)*AF68 -> 0 | AF68: =IF(ISNUMBER(MATCH(A68,$A$2:A67,0)),0,1) -> 1 | AH68: =SUMIFS(AJ$3:AJ$251,$A$3:$A$251,$A68) -> 0 | AI68: =SUMIFS(AK$3:AK$77,$A$3:$A$77,$A68) -> 1 | AJ68: =IF(SUM(AY68:BB68)=0,0,IF(SUM(AS68:AV68)=SUM(AY68:BB68),1,0)) -> 0 | AK68: 1 | AM68: =SUMIFS(AO$3:AO$251,$A$3:$A$251,$A68) -> 0 | AN68: =SUMIFS(AP$3:AP$251,$A$3:$A$251,$A68) -> 1 | AO68: =IF(SUM(AS68:AV68)=SUM(AY68:BB68),1,0) -> 0 | AP68: 1 | AR68: =SUM(AS68:AV68) -> 0 | AS68: =IF(OR(G68="",G68="TBD",G68="N/A",G68="SDK",G68="SAAS"),0,1) -> 0 | AT68: =IF(OR(H68="",H68="TBD",H68="N/A",H68="SDK",H68="SAAS"),0,1) -> 0 | AU68: =IF(OR(I68="",I68="TBD",I68="N/A",I68="SDK",I68="SAAS"),0,1) -> 0 | AV68: =IF(OR(J68="",J68="TBD",J68="N/A",J68="SDK",J68="SAAS"),0,1) -> 0 | AX68: =SUM(AY68:BB68) -> 4 | AY68: =IF(OR(G68="",G68="N/A",G68="SDK",G68="SAAS"),0,1) -> 1 | AZ68: =IF(OR(H68="",H68="N/A",H68="SDK",H68="SAAS"),0,1) -> 1 | BA68: =IF(OR(I68="",I68="N/A",I68="SDK",I68="SAAS"),0,1) -> 1 | BB68: =IF(OR(J68="",J68="N/A",J68="SDK",J68="SAAS"),0,1) -> 1
A69: BPC - 001 | B69: Onboarding | C69: Validación de clientes existentes en core de tarjetas | F69: TBD | G69: TBD | H69: TBD | I69: TBD | J69: TBD | M69: =L69*$L$147 -> 0 | N69: Backlog | O69: Rafael Elizalde | P69: x | X69: Sí | Y69: Por definir | AD69: =IF(AI69=0,0,IF(AH69=AI69,1,0))*AF69 -> 0 | AE69: =IF(AM69=AN69,1,0)*AF69 -> 0 | AF69: =IF(ISNUMBER(MATCH(A69,$A$2:A68,0)),0,1) -> 1 | AH69: =SUMIFS(AJ$3:AJ$251,$A$3:$A$251,$A69) -> 0 | AI69: =SUMIFS(AK$3:AK$77,$A$3:$A$77,$A69) -> 1 | AJ69: =IF(SUM(AY69:BB69)=0,0,IF(SUM(AS69:AV69)=SUM(AY69:BB69),1,0)) -> 0 | AK69: 1 | AM69: =SUMIFS(AO$3:AO$251,$A$3:$A$251,$A69) -> 0 | AN69: =SUMIFS(AP$3:AP$251,$A$3:$A$251,$A69) -> 1 | AO69: =IF(SUM(AS69:AV69)=SUM(AY69:BB69),1,0) -> 0 | AP69: 1 | AR69: =SUM(AS69:AV69) -> 0 | AS69: =IF(OR(G69="",G69="TBD",G69="N/A",G69="SDK",G69="SAAS"),0,1) -> 0 | AT69: =IF(OR(H69="",H69="TBD",H69="N/A",H69="SDK",H69="SAAS"),0,1) -> 0 | AU69: =IF(OR(I69="",I69="TBD",I69="N/A",I69="SDK",I69="SAAS"),0,1) -> 0 | AV69: =IF(OR(J69="",J69="TBD",J69="N/A",J69="SDK",J69="SAAS"),0,1) -> 0 | AX69: =SUM(AY69:BB69) -> 4 | AY69: =IF(OR(G69="",G69="N/A",G69="SDK",G69="SAAS"),0,1) -> 1 | AZ69: =IF(OR(H69="",H69="N/A",H69="SDK",H69="SAAS"),0,1) -> 1 | BA69: =IF(OR(I69="",I69="N/A",I69="SDK",I69="SAAS"),0,1) -> 1 | BB69: =IF(OR(J69="",J69="N/A",J69="SDK",J69="SAAS"),0,1) -> 1
A70: BPC - 002 | B70: Onboarding | C70: Alta de clientes en core de tarjetas | F70: TBD | G70: TBD | H70: TBD | I70: TBD | J70: TBD | M70: =L70*$L$147 -> 0 | N70: Backlog | O70: Rafael Elizalde | P70: x | X70: Sí | Y70: Por definir | AD70: =IF(AI70=0,0,IF(AH70=AI70,1,0))*AF70 -> 0 | AE70: =IF(AM70=AN70,1,0)*AF70 -> 0 | AF70: =IF(ISNUMBER(MATCH(A70,$A$2:A69,0)),0,1) -> 1 | AH70: =SUMIFS(AJ$3:AJ$251,$A$3:$A$251,$A70) -> 0 | AI70: =SUMIFS(AK$3:AK$77,$A$3:$A$77,$A70) -> 1 | AJ70: =IF(SUM(AY70:BB70)=0,0,IF(SUM(AS70:AV70)=SUM(AY70:BB70),1,0)) -> 0 | AK70: 1 | AM70: =SUMIFS(AO$3:AO$251,$A$3:$A$251,$A70) -> 0 | AN70: =SUMIFS(AP$3:AP$251,$A$3:$A$251,$A70) -> 1 | AO70: =IF(SUM(AS70:AV70)=SUM(AY70:BB70),1,0) -> 0 | AP70: 1 | AR70: =SUM(AS70:AV70) -> 0 | AS70: =IF(OR(G70="",G70="TBD",G70="N/A",G70="SDK",G70="SAAS"),0,1) -> 0 | AT70: =IF(OR(H70="",H70="TBD",H70="N/A",H70="SDK",H70="SAAS"),0,1) -> 0 | AU70: =IF(OR(I70="",I70="TBD",I70="N/A",I70="SDK",I70="SAAS"),0,1) -> 0 | AV70: =IF(OR(J70="",J70="TBD",J70="N/A",J70="SDK",J70="SAAS"),0,1) -> 0 | AX70: =SUM(AY70:BB70) -> 4 | AY70: =IF(OR(G70="",G70="N/A",G70="SDK",G70="SAAS"),0,1) -> 1 | AZ70: =IF(OR(H70="",H70="N/A",H70="SDK",H70="SAAS"),0,1) -> 1 | BA70: =IF(OR(I70="",I70="N/A",I70="SDK",I70="SAAS"),0,1) -> 1 | BB70: =IF(OR(J70="",J70="N/A",J70="SDK",J70="SAAS"),0,1) -> 1
A71: BPC - 003 | B71: Onboarding | C71: Alta de TDC asociada a un cliente BanCoppel | F71: TBD | G71: TBD | H71: TBD | I71: TBD | J71: TBD | M71: =L71*$L$147 -> 0 | N71: Backlog | O71: Rafael Elizalde | P71: x | X71: Sí | Y71: En proceso | AD71: =IF(AI71=0,0,IF(AH71=AI71,1,0))*AF71 -> 0 | AE71: =IF(AM71=AN71,1,0)*AF71 -> 0 | AF71: =IF(ISNUMBER(MATCH(A71,$A$2:A70,0)),0,1) -> 1 | AH71: =SUMIFS(AJ$3:AJ$251,$A$3:$A$251,$A71) -> 0 | AI71: =SUMIFS(AK$3:AK$77,$A$3:$A$77,$A71) -> 1 | AJ71: =IF(SUM(AY71:BB71)=0,0,IF(SUM(AS71:AV71)=SUM(AY71:BB71),1,0)) -> 0 | AK71: 1 | AM71: =SUMIFS(AO$3:AO$251,$A$3:$A$251,$A71) -> 0 | AN71: =SUMIFS(AP$3:AP$251,$A$3:$A$251,$A71) -> 1 | AO71: =IF(SUM(AS71:AV71)=SUM(AY71:BB71),1,0) -> 0 | AP71: 1 | AR71: =SUM(AS71:AV71) -> 0 | AS71: =IF(OR(G71="",G71="TBD",G71="N/A",G71="SDK",G71="SAAS"),0,1) -> 0 | AT71: =IF(OR(H71="",H71="TBD",H71="N/A",H71="SDK",H71="SAAS"),0,1) -> 0 | AU71: =IF(OR(I71="",I71="TBD",I71="N/A",I71="SDK",I71="SAAS"),0,1) -> 0 | AV71: =IF(OR(J71="",J71="TBD",J71="N/A",J71="SDK",J71="SAAS"),0,1) -> 0 | AX71: =SUM(AY71:BB71) -> 4 | AY71: =IF(OR(G71="",G71="N/A",G71="SDK",G71="SAAS"),0,1) -> 1 | AZ71: =IF(OR(H71="",H71="N/A",H71="SDK",H71="SAAS"),0,1) -> 1 | BA71: =IF(OR(I71="",I71="N/A",I71="SDK",I71="SAAS"),0,1) -> 1 | BB71: =IF(OR(J71="",J71="N/A",J71="SDK",J71="SAAS"),0,1) -> 1
