Workbook

Sheet metrics
B2: Layer | C2: API Component | E2: Layer | F2: API Operations | H2: Layer | I2: API Component | K2: Total Of Records
B3: Business Rule | C3: =IFERROR(__xludf.DUMMYFUNCTION("COUNTUNIQUEIFS(develop!F2:F1001,develop!D2:D1001,""BUSINESS RULE"")"),4.0) -> 4 | E3: Business Rule | F3: =COUNTIF(develop!D1:D1001,"BUSINESS RULE") -> 11 | H3: Business Rule | I3: =IFERROR(__xludf.DUMMYFUNCTION("COUNTUNIQUEIFS('api-register-id'!B2:B1001,'api-register-id'!D2:D1001,""BUSINESS RULES"")"),5.0) -> 5 | K3: =IFERROR(__xludf.DUMMYFUNCTION("COUNTUNIQUE(develop!G2:G1001)"),1652.0) -> 1652
B4: Reception | C4: =IFERROR(__xludf.DUMMYFUNCTION("COUNTUNIQUEIFS(develop!F2:F1001,develop!D2:D1001,""RECEPTION"")"),72.0) -> 72 | E4: Reception | F4: =COUNTIF(develop!D2:D1001,"RECEPTION") -> 410 | H4: Reception | I4: =IFERROR(__xludf.DUMMYFUNCTION("COUNTUNIQUEIFS('api-register-id'!B2:B1001,'api-register-id'!D2:D1001,""RECEPTION"")"),72.0) -> 72
B5: Business | C5: =IFERROR(__xludf.DUMMYFUNCTION("COUNTUNIQUEIFS(develop!F2:F1001,develop!D2:D1001,""BUSINESS"")"),26.0) -> 26 | E5: Business | F5: =COUNTIF(develop!D2:D1001,"BUSINESS") -> 138 | H5: Business | I5: =IFERROR(__xludf.DUMMYFUNCTION("COUNTUNIQUEIFS('api-register-id'!B2:B1001,'api-register-id'!D2:D1001,""BUSINESS"")"),28.0) -> 28
B6: Domain | C6: =IFERROR(__xludf.DUMMYFUNCTION("COUNTUNIQUEIFS(develop!F2:F1001,develop!D2:D1001,""DOMAIN"")"),76.0) -> 76 | E6: Domain | F6: =COUNTIF(develop!D2:D1001,"DOMAIN") -> 515 | H6: Domain | I6: =IFERROR(__xludf.DUMMYFUNCTION("COUNTUNIQUEIFS('api-register-id'!B2:B1001,'api-register-id'!D2:D1001,""DOMAIN"")"),74.0) -> 74
B7: Proxy | C7: =IFERROR(__xludf.DUMMYFUNCTION("COUNTUNIQUEIFS(develop!F2:F1001,develop!D2:D1001,""PROXY"")"),91.0) -> 91 | E7: Proxy | F7: =COUNTIF(develop!D2:D1001,"PROXY") -> 554 | H7: Proxy | I7: =IFERROR(__xludf.DUMMYFUNCTION("COUNTUNIQUEIFS('api-register-id'!B2:B1001,'api-register-id'!D2:D1001,""PROXY"")"),89.0) -> 89
B9: Total | C9: =SUM(C3:C7) -> 269 | E9: Total | F9: =SUM(F3:F7) -> 1628 | H9: Total | I9: =SUM(I3:I7) -> 268
B11: Specification | C11: API Component | E11: Specification | F11: API Operations
B12: RAML | C12: =IFERROR(__xludf.DUMMYFUNCTION("COUNTUNIQUEIFS(develop!F2:F1001,develop!C2:C1001,""RAML"")"),195.0) -> 195 | E12: RAML | F12: =COUNTIF(develop!C:C,"RAML") -> 1209
B13: OAS | C13: =IFERROR(__xludf.DUMMYFUNCTION("COUNTUNIQUEIFS(develop!F2:F1001,develop!C2:C1001,""OAS"")"),76.0) -> 76 | E13: OAS | F13: =COUNTIF(develop!C:C,"OAS") -> 419
B15: Total | C15: =IFERROR(__xludf.DUMMYFUNCTION("COUNTUNIQUE(develop!F2:F1001)"),271.0) -> 271 | E15: Total | F15: =SUM(F12:F13) -> 1628

Sheet develop
A1: Organización | B1: API Repository | C1: API Specification | D1: API Type | E1: API Register ID | F1: API Name | G1: API Resource ID | H1: API Operation ID | I1: API Version | J1: API Base Path | K1: Resource Version | L1: HTTP Method | M1: API Operation Resource | N1: API Operation Full Path | O1: API Operation Description | P1: API Error | Q1: Confluence | R1: Status | S1: Link GitHub | T1: Complejidad API | V1: Persona asignada (carga liga Confluence) | W1: Observaciones carga liga de Confluence
A2: {=IFERROR( INDEX( 'api-register-id'!A:A, MATCH(F2, 'api-register-id'!B:B, 0) ), "Not found Organization" )} -> SSFF | B2: =IFERROR(VLOOKUP(F2, 'api-register-id'!B:F, 4, FALSE), "Not found path.") -> mx-api-bc-bus-business-support | C2: RAML | D2: BUSINESS | E2: =IFERROR(VLOOKUP(F2, 'api-register-id'!B:F, 5, FALSE), "Not found path.") -> APIMX000001 | F2: Bus Business Support | G2: RESMX000001 | H2: Bus_ExecuteSmsNotificationV1 | I2: =IFERROR(VLOOKUP(F2, 'api-register-id'!B:I, 8, FALSE), "Not found path.") -> 1.3.0 | J2: /businessSupport | K2: v1 | L2: POST | M2: /v1/smsNotification/execute | N2: =CONCATENATE(L2," ",J2,M2) -> POST /businessSupport/v1/smsNotification/execute | O2: Operación encargada de realizar el envío de notificaciones SMS al cliente. | P2: Invalid Action Term "execute" for HTTP method "POST". For Action Term "execute" use "PUT,PATCH" | Q2: https://coppelmx.atlassian.net/wiki/spaces/GAC/pages/edit-v2/2157347017 | R2: Design | S2: ="https://github.com/SF-Bancoppel/"&B2 -> https://github.com/SF-Bancoppel/mx-api-bc-bus-business-support
A3: {=IFERROR( INDEX( 'api-register-id'!A:A, MATCH(F3, 'api-register-id'!B:B, 0) ), "Not found Organization" )} -> SSFF | B3: =IFERROR(VLOOKUP(F3, 'api-register-id'!B:F, 4, FALSE), "Not found path.") -> mx-api-bc-bus-business-support | C3: RAML | D3: BUSINESS | E3: =IFERROR(VLOOKUP(F3, 'api-register-id'!B:F, 5, FALSE), "Not found path.") -> APIMX000001 | F3: Bus Business Support | G3: RESMX000002 | H3: Bus_ExecuteExecuteOrderConfirmationV1 | I3: =IFERROR(VLOOKUP(F3, 'api-register-id'!B:I, 8, FALSE), "Not found path.") -> 1.3.0 | J3: /businessSupport | K3: v1 | L3: PUT | M3: /v1/executeOrderConfirmation/execute | N3: =CONCATENATE(L3," ",J3,M3) -> PUT /businessSupport/v1/executeOrderConfirmation/execute | O3: Operación encargada de confirmar el registro de un movimiento generado para Coppel. | P3: The Behavior Qualifier cannot include the action term value "execute". Remove the Action Term of "executeOrderConfirmation". | Q3: https://coppelmx.atlassian.net/wiki/spaces/GAC/pages/2158362691/RESMX000002_Bus_ExecuteExecuteOrderConfirmation_V1 | R3: Design | S3: ="https://github.com/SF-Bancoppel/"&B3 -> https://github.com/SF-Bancoppel/mx-api-bc-bus-business-support
A4: {=IFERROR( INDEX( 'api-register-id'!A:A, MATCH(F4, 'api-register-id'!B:B, 0) ), "Not found Organization" )} -> SSFF | B4: =IFERROR(VLOOKUP(F4, 'api-register-id'!B:F, 4, FALSE), "Not found path.") -> mx-api-bc-bus-business-support | C4: RAML | D4: BUSINESS | E4: =IFERROR(VLOOKUP(F4, 'api-register-id'!B:F, 5, FALSE), "Not found path.") -> APIMX000001 | F4: Bus Business Support | G4: RESMX000003 | H4: Bus_RetrieveOrderCancellationV1 | I4: =IFERROR(VLOOKUP(F4, 'api-register-id'!B:I, 8, FALSE), "Not found path.") -> 1.3.0 | J4: /businessSupport | K4: v1 | L4: POST | M4: /v1/orderCancellation/retrieve | N4: =CONCATENATE(L4," ",J4,M4) -> POST /businessSupport/v1/orderCancellation/retrieve | O4: Operación encargada de obtener la información de la orden de cancelación de transferencia. | Q4: https://coppelmx.atlassian.net/wiki/spaces/GAC/pages/2157936745/RESMX000003_Bus_RetrieveOrderCancellation_V1 | R4: Design | S4: ="https://github.com/SF-Bancoppel/"&B4 -> https://github.com/SF-Bancoppel/mx-api-bc-bus-business-support
A5: {=IFERROR( INDEX( 'api-register-id'!A:A, MATCH(F5, 'api-register-id'!B:B, 0) ), "Not found Organization" )} -> SSFF | B5: =IFERROR(VLOOKUP(F5, 'api-register-id'!B:F, 4, FALSE), "Not found path.") -> mx-api-bc-bus-business-support | C5: RAML | D5: BUSINESS | E5: =IFERROR(VLOOKUP(F5, 'api-register-id'!B:F, 5, FALSE), "Not found path.") -> APIMX000001 | F5: Bus Business Support | G5: RESMX000004 | H5: Bus_InitiatePaymentOrderProcedureV1 | I5: =IFERROR(VLOOKUP(F5, 'api-register-id'!B:I, 8, FALSE), "Not found path.") -> 1.3.0 | J5: /businessSupport | K5: v1 | L5: POST | M5: /v1/paymentOrderProcedure/initiate | N5: =CONCATENATE(L5," ",J5,M5) -> POST /businessSupport/v1/paymentOrderProcedure/initiate | O5: Operación encargada de generar la trama de Pago ANTAD para Interact. | Q5: https://coppelmx.atlassian.net/wiki/spaces/GAC/pages/2159214684/RESMX000004_Bus_InitiatePaymentOrderProcedure_V1 | R5: Design | S5: ="https://github.com/SF-Bancoppel/"&B5 -> https://github.com/SF-Bancoppel/mx-api-bc-bus-business-support
A6: {=IFERROR( INDEX( 'api-register-id'!A:A, MATCH(F6, 'api-register-id'!B:B, 0) ), "Not found Organization" )} -> SSFF | B6: =IFERROR(VLOOKUP(F6, 'api-register-id'!B:F, 4, FALSE), "Not found path.") -> mx-api-bc-bus-operations-and-execution | C6: RAML | D6: BUSINESS | E6: =IFERROR(VLOOKUP(F6, 'api-register-id'!B:F, 5, FALSE), "Not found path.") -> APIMX000002 | F6: Bus Operations and Execution | G6: RESMX000005 | H6: Bus_InitiateLoanFacilityV1 | I6: =IFERROR(VLOOKUP(F6, 'api-register-id'!B:I, 8, FALSE), "Not found path.") -> 1.16.1 | J6: /operationsAndExecution | K6: v1 | L6: POST | M6: /v1/loanFacility/initiate | N6: =CONCATENATE(L6," ",J6,M6) -> POST /operationsAndExecution/v1/loanFacility/initiate | O6: API que permite orquestar las funcionalidades para registrar un préstamo de Coppel | Q6: Pending load documentation... | R6: Design | S6: ="https://github.com/SF-Bancoppel/"&B6 -> https://github.com/SF-Bancoppel/mx-api-bc-bus-operations-and-execution | V6: Manuel
A7: {=IFERROR( INDEX( 'api-register-id'!A:A, MATCH(F7, 'api-register-id'!B:B, 0) ), "Not found Organization" )} -> SSFF | B7: =IFERROR(VLOOKUP(F7, 'api-register-id'!B:F, 4, FALSE), "Not found path.") -> mx-api-bc-bus-operations-and-execution | C7: RAML | D7: BUSINESS | E7: =IFERROR(VLOOKUP(F7, 'api-register-id'!B:F, 5, FALSE), "Not found path.") -> APIMX000002 | F7: Bus Operations and Execution | G7: RESMX000006 | H7: Bus_RetrieveCreditDataDocumentV1 | I7: =IFERROR(VLOOKUP(F7, 'api-register-id'!B:I, 8, FALSE), "Not found path.") -> 1.16.1 | J7: /operationsAndExecution | K7: v1 | L7: GET | M7: /v1/creditDataDocument/retrieve | N7: =CONCATENATE(L7," ",J7,M7) -> GET /operationsAndExecution/v1/creditDataDocument/retrieve | O7: API que obtiene los datos de la caratula de los prestamos del cliente. | Q7: Pending load documentation... | R7: Design | S7: ="https://github.com/SF-Bancoppel/"&B7 -> https://github.com/SF-Bancoppel/mx-api-bc-bus-operations-and-execution | V7: Manuel
A8: {=IFERROR( INDEX( 'api-register-id'!A:A, MATCH(F8, 'api-register-id'!B:B, 0) ), "Not found Organization" )} -> SSFF | B8: =IFERROR(VLOOKUP(F8, 'api-register-id'!B:F, 4, FALSE), "Not found path.") -> mx-api-bc-bus-operations-and-execution | C8: RAML | D8: BUSINESS | E8: =IFERROR(VLOOKUP(F8, 'api-register-id'!B:F, 5, FALSE), "Not found path.") -> APIMX000002 | F8: Bus Operations and Execution | G8: RESMX000007 | H8: Bus_RetrieveCustomerCreditBalanceV1 | I8: =IFERROR(VLOOKUP(F8, 'api-register-id'!B:I, 8, FALSE), "Not found path.") -> 1.16.1 | J8: /operationsAndExecution | K8: v1 | L8: GET | M8: /v1/customerCreditBalance/retrieve | N8: =CONCATENATE(L8," ",J8,M8) -> GET /operationsAndExecution/v1/customerCreditBalance/retrieve | O8: API que permite consultar el saldo y plazo del crédito. | Q8: Pending load documentation... | R8: Design | S8: ="https://github.com/SF-Bancoppel/"&B8 -> https://github.com/SF-Bancoppel/mx-api-bc-bus-operations-and-execution | V8: Manuel
A9: {=IFERROR( INDEX( 'api-register-id'!A:A, MATCH(F9, 'api-register-id'!B:B, 0) ), "Not found Organization" )} -> SSFF | B9: =IFERROR(VLOOKUP(F9, 'api-register-id'!B:F, 4, FALSE), "Not found path.") -> mx-api-bc-bus-operations-and-execution | C9: RAML | D9: BUSINESS | E9: =IFERROR(VLOOKUP(F9, 'api-register-id'!B:F, 5, FALSE), "Not found path.") -> APIMX000002 | F9: Bus Operations and Execution | G9: RESMX000008 | H9: Bus_RetrieveCustomerProductInformationV1 | I9: =IFERROR(VLOOKUP(F9, 'api-register-id'!B:I, 8, FALSE), "Not found path.") -> 1.16.1 | J9: /operationsAndExecution | K9: v1 | L9: GET | M9: /v1/customerProductInformation/{companyReference}/retrieve | N9: =CONCATENATE(L9," ",J9,M9) -> GET /operationsAndExecution/v1/customerProductInformation/{companyReference}/retrieve | O9: API que permite consultar los datos generales de un producto (tarjeta de crédito,cheque,préstamos) por número de cliente | Q9: Pending load documentation... | R9: Design | S9: ="https://github.com/SF-Bancoppel/"&B9 -> https://github.com/SF-Bancoppel/mx-api-bc-bus-operations-and-execution | V9: Manuel
A10: {=IFERROR( INDEX( 'api-register-id'!A:A, MATCH(F10, 'api-register-id'!B:B, 0) ), "Not found Organization" )} -> SSFF | B10: =IFERROR(VLOOKUP(F10, 'api-register-id'!B:F, 4, FALSE), "Not found path.") -> mx-api-bc-bus-operations-and-execution | C10: RAML | D10: BUSINESS | E10: =IFERROR(VLOOKUP(F10, 'api-register-id'!B:F, 5, FALSE), "Not found path.") -> APIMX000002 | F10: Bus Operations and Execution | G10: RESMX000009 | H10: Bus_RetrieveBalanceCreditProductV1 | I10: =IFERROR(VLOOKUP(F10, 'api-register-id'!B:I, 8, FALSE), "Not found path.") -> 1.16.1 | J10: /operationsAndExecution | K10: v1 | L10: GET | M10: /v1/balanceCreditProduct/retrieve | N10: =CONCATENATE(L10," ",J10,M10) -> GET /operationsAndExecution/v1/balanceCreditProduct/retrieve | O10: API que permite consultar los saldos generales de un producto de crédito | Q10: Pending load documentation... | R10: Design | S10: ="https://github.com/SF-Bancoppel/"&B10 -> https://github.com/SF-Bancoppel/mx-api-bc-bus-operations-and-execution | V10: Manuel
A11: {=IFERROR( INDEX( 'api-register-id'!A:A, MATCH(F11, 'api-register-id'!B:B, 0) ), "Not found Organization" )} -> SSFF | B11: =IFERROR(VLOOKUP(F11, 'api-register-id'!B:F, 4, FALSE), "Not found path.") -> mx-api-bc-bus-operations-and-execution | C11: RAML | D11: BUSINESS | E11: =IFERROR(VLOOKUP(F11, 'api-register-id'!B:F, 5, FALSE), "Not found path.") -> APIMX000002 | F11: Bus Operations and Execution | G11: RESMX000010 | H11: Bus_RetrieveBalanceCreditInformationV1 | I11: =IFERROR(VLOOKUP(F11, 'api-register-id'!B:I, 8, FALSE), "Not found path.") -> 1.16.1 | J11: /operationsAndExecution | K11: v1 | L11: GET | M11: /v1/balanceCreditInformation/retrieve | N11: =CONCATENATE(L11," ",J11,M11) -> GET /operationsAndExecution/v1/balanceCreditInformation/retrieve | O11: API que permite consultar los saldos generales de un producto de crédito | Q11: Pending load documentation... | R11: Design | S11: ="https://github.com/SF-Bancoppel/"&B11 -> https://github.com/SF-Bancoppel/mx-api-bc-bus-operations-and-execution | V11: Manuel
A12: {=IFERROR( INDEX( 'api-register-id'!A:A, MATCH(F12, 'api-register-id'!B:B, 0) ), "Not found Organization" )} -> SSFF | B12: =IFERROR(VLOOKUP(F12, 'api-register-id'!B:F, 4, FALSE), "Not found path.") -> mx-api-bc-bus-operations-and-execution | C12: RAML | D12: BUSINESS | E12: =IFERROR(VLOOKUP(F12, 'api-register-id'!B:F, 5, FALSE), "Not found path.") -> APIMX000002 | F12: Bus Operations and Execution | G12: RESMX000011 | H12: Bus_RetrieveLoanAgreementV1 | I12: =IFERROR(VLOOKUP(F12, 'api-register-id'!B:I, 8, FALSE), "Not found path.") -> 1.16.1 | J12: /operationsAndExecution | K12: v1 | L12: GET | M12: /v1/loanAgreement/retrieve | N12: =CONCATENATE(L12," ",J12,M12) -> GET /operationsAndExecution/v1/loanAgreement/retrieve | O12: API que permite consulta el saldo y plazo de un préstamo | Q12: Pending load documentation... | R12: Design | S12: ="https://github.com/SF-Bancoppel/"&B12 -> https://github.com/SF-Bancoppel/mx-api-bc-bus-operations-and-execution | V12: Manuel
A13: {=IFERROR( INDEX( 'api-register-id'!A:A, MATCH(F13, 'api-register-id'!B:B, 0) ), "Not found Organization" )} -> SSFF | B13: =IFERROR(VLOOKUP(F13, 'api-register-id'!B:F, 4, FALSE), "Not found path.") -> mx-api-bc-bus-operations-and-execution | C13: RAML | D13: BUSINESS | E13: =IFERROR(VLOOKUP(F13, 'api-register-id'!B:F, 5, FALSE), "Not found path.") -> APIMX000002 | F13: Bus Operations and Execution | G13: RESMX000012 | H13: Bus_RetrieveSavingAccountBalanceV1 | I13: =IFERROR(VLOOKUP(F13, 'api-register-id'!B:I, 8, FALSE), "Not found path.") -> 1.16.1 | J13: /operationsAndExecution | K13: v1 | L13: GET | M13: /v1/savingAccountBalance/{companyReference}/retrieve | N13: =CONCATENATE(L13," ",J13,M13) -> GET /operationsAndExecution/v1/savingAccountBalance/{companyReference}/retrieve | O13: API que permite orquestar la consulta de saldo de cuenta de ahorro | Q13: Pending load documentation... | R13: Design | S13: ="https://github.com/SF-Bancoppel/"&B13 -> https://github.com/SF-Bancoppel/mx-api-bc-bus-operations-and-execution | V13: Manuel
A14: {=IFERROR( INDEX( 'api-register-id'!A:A, MATCH(F14, 'api-register-id'!B:B, 0) ), "Not found Organization" )} -> SSFF | B14: =IFERROR(VLOOKUP(F14, 'api-register-id'!B:F, 4, FALSE), "Not found path.") -> mx-api-bc-bus-operations-and-execution | C14: RAML | D14: BUSINESS | E14: =IFERROR(VLOOKUP(F14, 'api-register-id'!B:F, 5, FALSE), "Not found path.") -> APIMX000002 | F14: Bus Operations and Execution | G14: RESMX000013 | H14: Bus_RequestCreditCardFacilityApplicationV1 | I14: =IFERROR(VLOOKUP(F14, 'api-register-id'!B:I, 8, FALSE), "Not found path.") -> 1.16.1 | J14: /operationsAndExecution | K14: v1 | L14: POST | M14: /v1/creditCardFacilityApplication/request | N14: =CONCATENATE(L14," ",J14,M14) -> POST /operationsAndExecution/v1/creditCardFacilityApplication/request | O14: Permite ejecutar diferentes acciones sobre el producto Tarjeta de Crédito Oro (1- Verifica si aplica a TDC Oro, 2- Clonar Información Clásica a Oro, 3- Limpiar Clonación Clásica a Oro) | P14: Invalid Action Term "request" for HTTP method "POST". For Action Term "request" use "PUT,PATCH" | Q14: Pending load documentation... | R14: Design | S14: ="https://github.com/SF-Bancoppel/"&B14 -> https://github.com/SF-Bancoppel/mx-api-bc-bus-operations-and-execution | V14: Manuel
A15: {=IFERROR( INDEX( 'api-register-id'!A:A, MATCH(F15, 'api-register-id'!B:B, 0) ), "Not found Organization" )} -> SSFF | B15: =IFERROR(VLOOKUP(F15, 'api-register-id'!B:F, 4, FALSE), "Not found path.") -> mx-api-bc-bus-operations-and-execution | C15: RAML | D15: BUSINESS | E15: =IFERROR(VLOOKUP(F15, 'api-register-id'!B:F, 5, FALSE), "Not found path.") -> APIMX000002 | F15: Bus Operations and Execution | G15: RESMX000014 | H15: Bus_InitiateCreditCardFacilityV1 | I15: =IFERROR(VLOOKUP(F15, 'api-register-id'!B:I, 8, FALSE), "Not found path.") -> 1.16.1 | J15: /operationsAndExecution | K15: v1 | L15: POST | M15: /v1/creditCardFacility/initiate | N15: =CONCATENATE(L15," ",J15,M15) -> POST /operationsAndExecution/v1/creditCardFacility/initiate | O15: Apertura y asignación de tarjeta de crédito | Q15: Pending load documentation... | R15: Design | S15: ="https://github.com/SF-Bancoppel/"&B15 -> https://github.com/SF-Bancoppel/mx-api-bc-bus-operations-and-execution | V15: Manuel
A16: {=IFERROR( INDEX( 'api-register-id'!A:A, MATCH(F16, 'api-register-id'!B:B, 0) ), "Not found Organization" )} -> SSFF | B16: =IFERROR(VLOOKUP(F16, 'api-register-id'!B:F, 4, FALSE), "Not found path.") -> mx-api-bc-bus-operations-and-execution | C16: RAML | D16: BUSINESS | E16: =IFERROR(VLOOKUP(F16, 'api-register-id'!B:F, 5, FALSE), "Not found path.") -> APIMX000002 | F16: Bus Operations and Execution | G16: RESMX000015 | H16: Bus_RetrieveCreditCardInformationV1 | I16: =IFERROR(VLOOKUP(F16, 'api-register-id'!B:I, 8, FALSE), "Not found path.") -> 1.16.1 | J16: /operationsAndExecution | K16: v1 | L16: GET | M16: /v1/creditCardInformation/retrieve | N16: =CONCATENATE(L16," ",J16,M16) -> GET /operationsAndExecution/v1/creditCardInformation/retrieve | O16: API que permite consultar una tarjeta de crédito por número de tarjeta | Q16: Pending load documentation... | R16: Design | S16: ="https://github.com/SF-Bancoppel/"&B16 -> https://github.com/SF-Bancoppel/mx-api-bc-bus-operations-and-execution | V16: Manuel
A17: {=IFERROR( INDEX( 'api-register-id'!A:A, MATCH(F17, 'api-register-id'!B:B, 0) ), "Not found Organization" )} -> SSFF | B17: =IFERROR(VLOOKUP(F17, 'api-register-id'!B:F, 4, FALSE), "Not found path.") -> mx-api-bc-bus-operations-and-execution | C17: RAML | D17: BUSINESS | E17: =IFERROR(VLOOKUP(F17, 'api-register-id'!B:F, 5, FALSE), "Not found path.") -> APIMX000002 | F17: Bus Operations and Execution | G17: RESMX000016 | H17: Bus_RetrieveCreditCardCashProvisionV1 | I17: =IFERROR(VLOOKUP(F17, 'api-register-id'!B:I, 8, FALSE), "Not found path.") -> 1.16.1 | J17: /operationsAndExecution | K17: v1 | L17: GET | M17: /v1/creditCardCashProvision/retrieve | N17: =CONCATENATE(L17," ",J17,M17) -> GET /operationsAndExecution/v1/creditCardCashProvision/retrieve | O17: API que permite orquestar la consulta de disposición de efectivo y la regla de negocio asociada a la funcionalidad | Q17: Pending load documentation... | R17: Design | S17: ="https://github.com/SF-Bancoppel/"&B17 -> https://github.com/SF-Bancoppel/mx-api-bc-bus-operations-and-execution | V17: Manuel
A18: {=IFERROR( INDEX( 'api-register-id'!A:A, MATCH(F18, 'api-register-id'!B:B, 0) ), "Not found Organization" )} -> SSFF | B18: =IFERROR(VLOOKUP(F18, 'api-register-id'!B:F, 4, FALSE), "Not found path.") -> mx-api-bc-bus-operations-and-execution | C18: RAML | D18: BUSINESS | E18: =IFERROR(VLOOKUP(F18, 'api-register-id'!B:F, 5, FALSE), "Not found path.") -> APIMX000002 | F18: Bus Operations and Execution | G18: RESMX000017 | H18: Bus_InitiateCreditCardActivationLogV1 | I18: =IFERROR(VLOOKUP(F18, 'api-register-id'!B:I, 8, FALSE), "Not found path.") -> 1.16.1 | J18: /operationsAndExecution | K18: v1 | L18: POST | M18: /v1/creditCardActivationLog/initiate | N18: =CONCATENATE(L18," ",J18,M18) -> POST /operationsAndExecution/v1/creditCardActivationLog/initiate | O18: Permite grabar una bitácora de la activación de las tarjetas de crédito Bancoppel en ventanilla | Q18: Pending load documentation... | R18: Design | S18: ="https://github.com/SF-Bancoppel/"&B18 -> https://github.com/SF-Bancoppel/mx-api-bc-bus-operations-and-execution | V18: Manuel
A19: {=IFERROR( INDEX( 'api-register-id'!A:A, MATCH(F19, 'api-register-id'!B:B, 0) ), "Not found Organization" )} -> SSFF | B19: =IFERROR(VLOOKUP(F19, 'api-register-id'!B:F, 4, FALSE), "Not found path.") -> mx-api-bc-bus-operations-and-execution | C19: RAML | D19: BUSINESS | E19: =IFERROR(VLOOKUP(F19, 'api-register-id'!B:F, 5, FALSE), "Not found path.") -> APIMX000002 | F19: Bus Operations and Execution | G19: RESMX000018 | H19: Bus_RetrieveCreditCardHolderV1 | I19: =IFERROR(VLOOKUP(F19, 'api-register-id'!B:I, 8, FALSE), "Not found path.") -> 1.16.1 | J19: /operationsAndExecution | K19: v1 | L19: POST | M19: /v1/creditCardHolder/retrieve | N19: =CONCATENATE(L19," ",J19,M19) -> POST /operationsAndExecution/v1/creditCardHolder/retrieve | O19: Permite consultar los tarjetahabientes asociados a una cuenta | Q19: Pending load documentation... | R19: Design | S19: ="https://github.com/SF-Bancoppel/"&B19 -> https://github.com/SF-Bancoppel/mx-api-bc-bus-operations-and-execution | V19: Manuel
A20: {=IFERROR( INDEX( 'api-register-id'!A:A, MATCH(F20, 'api-register-id'!B:B, 0) ), "Not found Organization" )} -> SSFF | B20: =IFERROR(VLOOKUP(F20, 'api-register-id'!B:F, 4, FALSE), "Not found path.") -> mx-api-bc-bus-operations-and-execution | C20: RAML | D20: BUSINESS | E20: =IFERROR(VLOOKUP(F20, 'api-register-id'!B:F, 5, FALSE), "Not found path.") -> APIMX000002 | F20: Bus Operations and Execution | G20: RESMX000019 | H20: Bus_RegisterCustomerUpgradeV1 | I20: =IFERROR(VLOOKUP(F20, 'api-register-id'!B:I, 8, FALSE), "Not found path.") -> 1.16.1 | J20: /operationsAndExecution | K20: v1 | L20: POST | M20: /v1/customerUpgrade/register | N20: =CONCATENATE(L20," ",J20,M20) -> POST /operationsAndExecution/v1/customerUpgrade/register | O20: Api que permite guarda la información del reporte referente a la solicitud de la mejora del producto y plásticos para reposición | Q20: Pending load documentation... | R20: Design | S20: ="https://github.com/SF-Bancoppel/"&B20 -> https://github.com/SF-Bancoppel/mx-api-bc-bus-operations-and-execution | V20: Manuel
A21: {=IFERROR( INDEX( 'api-register-id'!A:A, MATCH(F21, 'api-register-id'!B:B, 0) ), "Not found Organization" )} -> SSFF | B21: =IFERROR(VLOOKUP(F21, 'api-register-id'!B:F, 4, FALSE), "Not found path.") -> mx-api-bc-bus-operations-and-execution | C21: RAML | D21: BUSINESS | E21: =IFERROR(VLOOKUP(F21, 'api-register-id'!B:F, 5, FALSE), "Not found path.") -> APIMX000002 | F21: Bus Operations and Execution | G21: RESMX000020 | H21: Bus_InitiateCustomerUpgradeV1 | I21: =IFERROR(VLOOKUP(F21, 'api-register-id'!B:I, 8, FALSE), "Not found path.") -> 1.16.1 | J21: /operationsAndExecution | K21: v1 | L21: POST | M21: /v1/customerUpgrade/initiate | N21: =CONCATENATE(L21," ",J21,M21) -> POST /operationsAndExecution/v1/customerUpgrade/initiate | O21: Api que permite grabar la información referente a la solicitud del upgrade del producto | Q21: Pending load documentation... | R21: Design | S21: ="https://github.com/SF-Bancoppel/"&B21 -> https://github.com/SF-Bancoppel/mx-api-bc-bus-operations-and-execution | V21: Manuel
A22: {=IFERROR( INDEX( 'api-register-id'!A:A, MATCH(F22, 'api-register-id'!B:B, 0) ), "Not found Organization" )} -> SSFF | B22: =IFERROR(VLOOKUP(F22, 'api-register-id'!B:F, 4, FALSE), "Not found path.") -> mx-api-bc-bus-operations-and-execution | C22: RAML | D22: BUSINESS | E22: =IFERROR(VLOOKUP(F22, 'api-register-id'!B:F, 5, FALSE), "Not found path.") -> APIMX000002 | F22: Bus Operations and Execution | G22: RESMX000021 | H22: Bus_RetrieveCustomerUpgradeV1 | I22: =IFERROR(VLOOKUP(F22, 'api-register-id'!B:I, 8, FALSE), "Not found path.") -> 1.16.1 | J22: /operationsAndExecution | K22: v1 | L22: POST | M22: /v1/customerUpgrade/retrieve | N22: =CONCATENATE(L22," ",J22,M22) -> POST /operationsAndExecution/v1/customerUpgrade/retrieve | O22: Api que permite consultar la información referente a la solicitud del upgrade del producto | Q22: Pending load documentation... | R22: Design | S22: ="https://github.com/SF-Bancoppel/"&B22 -> https://github.com/SF-Bancoppel/mx-api-bc-bus-operations-and-execution | V22: Manuel
A23: {=IFERROR( INDEX( 'api-register-id'!A:A, MATCH(F23, 'api-register-id'!B:B, 0) ), "Not found Organization" )} -> SSFF | B23: =IFERROR(VLOOKUP(F23, 'api-register-id'!B:F, 4, FALSE), "Not found path.") -> mx-api-bc-bus-operations-and-execution | C23: RAML | D23: BUSINESS | E23: =IFERROR(VLOOKUP(F23, 'api-register-id'!B:F, 5, FALSE), "Not found path.") -> APIMX000002 | F23: Bus Operations and Execution | G23: RESMX000022 | H23: Bus_RetrieveBalanceProductV1 | I23: =IFERROR(VLOOKUP(F23, 'api-register-id'!B:I, 8, FALSE), "Not found path.") -> 1.16.1 | J23: /operationsAndExecution | K23: v1 | L23: POST | M23: /v1/balanceProduct/retrieve | N23: =CONCATENATE(L23," ",J23,M23) -> POST /operationsAndExecution/v1/balanceProduct/retrieve | O23: API que permite consultar si un producto posee un saldo pendiente | Q23: Pending load documentation... | R23: Design | S23: ="https://github.com/SF-Bancoppel/"&B23 -> https://github.com/SF-Bancoppel/mx-api-bc-bus-operations-and-execution | V23: Manuel
A24: {=IFERROR( INDEX( 'api-register-id'!A:A, MATCH(F24, 'api-register-id'!B:B, 0) ), "Not found Organization" )} -> SSFF | B24: =IFERROR(VLOOKUP(F24, 'api-register-id'!B:F, 4, FALSE), "Not found path.") -> mx-api-bc-bus-operations-and-execution | C24: RAML | D24: BUSINESS | E24: =IFERROR(VLOOKUP(F24, 'api-register-id'!B:F, 5, FALSE), "Not found path.") -> APIMX000002 | F24: Bus Operations and Execution | G24: RESMX000023 | H24: Bus_ControlCreditCardStatusV1 | I24: =IFERROR(VLOOKUP(F24, 'api-register-id'!B:I, 8, FALSE), "Not found path.") -> 1.16.1 | J24: /operationsAndExecution | K24: v1 | L24: PUT | M24: /v1/creditCardStatus/control | N24: =CONCATENATE(L24," ",J24,M24) -> PUT /operationsAndExecution/v1/creditCardStatus/control | O24: Consulta los datos de la tarjeta de credito y actualiza el estatus a "A" desde caja. | Q24: Pending load documentation... | R24: Design | S24: ="https://github.com/SF-Bancoppel/"&B24 -> https://github.com/SF-Bancoppel/mx-api-bc-bus-operations-and-execution | V24: Manuel
A25: {=IFERROR( INDEX( 'api-register-id'!A:A, MATCH(F25, 'api-register-id'!B:B, 0) ), "Not found Organization" )} -> SSFF | B25: =IFERROR(VLOOKUP(F25, 'api-register-id'!B:F, 4, FALSE), "Not found path.") -> mx-api-bc-bus-operations-and-execution | C25: RAML | D25: BUSINESS | E25: =IFERROR(VLOOKUP(F25, 'api-register-id'!B:F, 5, FALSE), "Not found path.") -> APIMX000002 | F25: Bus Operations and Execution | G25: RESMX000024 | H25: Bus_InitiateExecutionCashAdvanceV1 | I25: =IFERROR(VLOOKUP(F25, 'api-register-id'!B:I, 8, FALSE), "Not found path.") -> 1.16.1 | J25: /operationsAndExecution | K25: v1 | L25: POST | M25: /v1/executionCashAdvance/initiate | N25: =CONCATENATE(L25," ",J25,M25) -> POST /operationsAndExecution/v1/executionCashAdvance/initiate | O25: Api de negocio que realiza cálculos de comisiones e intereses, cancelación de anualidad o devolución de anualidad. Los movimientos calculados son registrados en la base de datos de TDC. | Q25: Pending load documentation... | R25: Design | S25: ="https://github.com/SF-Bancoppel/"&B25 -> https://github.com/SF-Bancoppel/mx-api-bc-bus-operations-and-execution | V25: Martha
A26: {=IFERROR( INDEX( 'api-register-id'!A:A, MATCH(F26, 'api-register-id'!B:B, 0) ), "Not found Organization" )} -> SSFF | B26: =IFERROR(VLOOKUP(F26, 'api-register-id'!B:F, 4, FALSE), "Not found path.") -> mx-api-bc-bus-reference-data | C26: RAML | D26: BUSINESS | E26: =IFERROR(VLOOKUP(F26, 'api-register-id'!B:F, 5, FALSE), "Not found path.") -> APIMX000003 | F26: Bus Reference Data | G26: RESMX000025 | H26: Bus_RetrieveOcrDocumentV1 | I26: =IFERROR(VLOOKUP(F26, 'api-register-id'!B:I, 8, FALSE), "Not found path.") -> 1.7.0 | J26: /referenceData | K26: v1 | L26: GET | M26: /v1/ocrDocument/retrieve | N26: =CONCATENATE(L26," ",J26,M26) -> GET /referenceData/v1/ocrDocument/retrieve | O26: Servicio de experiencia que se encarga de retornar datos sobre la lectura del usuario de la declaración de identificación y dirección envuelta en el objeto ocrData. | Q26: https://coppelmx.atlassian.net/wiki/x/GgDpPQ | R26: Design | S26: ="https://github.com/SF-Bancoppel/"&B26 -> https://github.com/SF-Bancoppel/mx-api-bc-bus-reference-data
A27: {=IFERROR( INDEX( 'api-register-id'!A:A, MATCH(F27, 'api-register-id'!B:B, 0) ), "Not found Organization" )} -> SSFF | B27: =IFERROR(VLOOKUP(F27, 'api-register-id'!B:F, 4, FALSE), "Not found path.") -> mx-api-bc-bus-reference-data | C27: RAML | D27: BUSINESS | E27: =IFERROR(VLOOKUP(F27, 'api-register-id'!B:F, 5, FALSE), "Not found path.") -> APIMX000003 | F27: Bus Reference Data | G27: RESMX000026 | H27: Bus_EvaluateOnboardingPartySuitabilityV1 | I27: =IFERROR(VLOOKUP(F27, 'api-register-id'!B:I, 8, FALSE), "Not found path.") -> 1.7.0 | J27: /referenceData | K27: v1 | L27: POST | M27: /v1/onboardingPartySuitability/evaluate | N27: =CONCATENATE(L27," ",J27,M27) -> POST /referenceData/v1/onboardingPartySuitability/evaluate | O27: Servicio de negocio que se encarga de consultar al cliente en las listas negras respectivas | Q27: https://coppelmx.atlassian.net/wiki/x/GgDpPQ | R27: Design | S27: ="https://github.com/SF-Bancoppel/"&B27 -> https://github.com/SF-Bancoppel/mx-api-bc-bus-reference-data
A28: {=IFERROR( INDEX( 'api-register-id'!A:A, MATCH(F28, 'api-register-id'!B:B, 0) ), "Not found Organization" )} -> SSFF | B28: =IFERROR(VLOOKUP(F28, 'api-register-id'!B:F, 4, FALSE), "Not found path.") -> mx-api-bc-bus-reference-data | C28: RAML | D28: BUSINESS | E28: =IFERROR(VLOOKUP(F28, 'api-register-id'!B:F, 5, FALSE), "Not found path.") -> APIMX000003 | F28: Bus Reference Data | G28: RESMX000027 | H28: Bus_EvaluateReviewCustomerAccountV1 | I28: =IFERROR(VLOOKUP(F28, 'api-register-id'!B:I, 8, FALSE), "Not found path.") -> 1.7.0 | J28: /referenceData | K28: v1 | L28: POST | M28: /v1/reviewCustomerAccount/evaluate | N28: =CONCATENATE(L28," ",J28,M28) -> POST /referenceData/v1/reviewCustomerAccount/evaluate | O28: Servicio encargado de evaluar datos específicos del cliente. | Q28: Pending load documentation... | R28: Design | S28: ="https://github.com/SF-Bancoppel/"&B28 -> https://github.com/SF-Bancoppel/mx-api-bc-bus-reference-data | V28: Martha
A29: {=IFERROR( INDEX( 'api-register-id'!A:A, MATCH(F29, 'api-register-id'!B:B, 0) ), "Not found Organization" )} -> SSFF | B29: =IFERROR(VLOOKUP(F29, 'api-register-id'!B:F, 4, FALSE), "Not found path.") -> mx-api-bc-bus-reference-data | C29: RAML | D29: BUSINESS | E29: =IFERROR(VLOOKUP(F29, 'api-register-id'!B:F, 5, FALSE), "Not found path.") -> APIMX000003 | F29: Bus Reference Data | G29: RESMX000028 | H29: Bus_RegisterGeneratePartyV1 | I29: =IFERROR(VLOOKUP(F29, 'api-register-id'!B:I, 8, FALSE), "Not found path.") -> 1.7.0 | J29: /referenceData | K29: v1 | L29: POST | M29: /v1/generateParty/register | N29: =CONCATENATE(L29," ",J29,M29) -> POST /referenceData/v1/generateParty/register | O29: Operación encargada de realizar el registro de un cliente físico. | Q29: Pending load documentation... | R29: Design | S29: ="https://github.com/SF-Bancoppel/"&B29 -> https://github.com/SF-Bancoppel/mx-api-bc-bus-reference-data | V29: Martha
A30: {=IFERROR( INDEX( 'api-register-id'!A:A, MATCH(F30, 'api-register-id'!B:B, 0) ), "Not found Organization" )} -> SSFF | B30: =IFERROR(VLOOKUP(F30, 'api-register-id'!B:F, 4, FALSE), "Not found path.") -> mx-api-bc-bus-reference-data | C30: RAML | D30: BUSINESS | E30: =IFERROR(VLOOKUP(F30, 'api-register-id'!B:F, 5, FALSE), "Not found path.") -> APIMX000003 | F30: Bus Reference Data | G30: RESMX000029 | H30: Bus_RetrieveRetrievePaymentBalancesV1 | I30: =IFERROR(VLOOKUP(F30, 'api-register-id'!B:I, 8, FALSE), "Not found path.") -> 1.7.0 | J30: /referenceData | K30: v1 | L30: POST | M30: /v1/retrievePaymentBalances/retrieve | N30: =CONCATENATE(L30," ",J30,M30) -> POST /referenceData/v1/retrievePaymentBalances/retrieve | O30: Obtener los totales de pagos referenciados, pagos de WU/OV/VG para que se consultan las transacciones de abono a cuenta. | P30: The Behavior Qualifier cannot include the action term value "retrieve". Remove the Action Term of "retrievePaymentBalances". | Q30: Pending load documentation... | R30: Design | S30: ="https://github.com/SF-Bancoppel/"&B30 -> https://github.com/SF-Bancoppel/mx-api-bc-bus-reference-data | V30: Martha
A31: {=IFERROR( INDEX( 'api-register-id'!A:A, MATCH(F31, 'api-register-id'!B:B, 0) ), "Not found Organization" )} -> SSFF | B31: =IFERROR(VLOOKUP(F31, 'api-register-id'!B:F, 4, FALSE), "Not found path.") -> mx-api-bc-bus-reference-data | C31: RAML | D31: BUSINESS | E31: =IFERROR(VLOOKUP(F31, 'api-register-id'!B:F, 5, FALSE), "Not found path.") -> APIMX000003 | F31: Bus Reference Data | G31: RESMX000030 | H31: Bus_ExecuteOnboardingPartyV1 | I31: =IFERROR(VLOOKUP(F31, 'api-register-id'!B:I, 8, FALSE), "Not found path.") -> 1.7.0 | J31: /referenceData | K31: v1 | L31: PUT | M31: /v1/onboardingParty/execute | N31: =CONCATENATE(L31," ",J31,M31) -> PUT /referenceData/v1/onboardingParty/execute | O31: Servicio de negocio encargado de ejecutar el proceso de onboarding de consultar el prospecto de cliente y guardar sus información. | Q31: https://coppelmx.atlassian.net/wiki/x/NwDmPQ | R31: Design | S31: ="https://github.com/SF-Bancoppel/"&B31 -> https://github.com/SF-Bancoppel/mx-api-bc-bus-reference-data
A32: {=IFERROR( INDEX( 'api-register-id'!A:A, MATCH(F32, 'api-register-id'!B:B, 0) ), "Not found Organization" )} -> SSFF | B32: =IFERROR(VLOOKUP(F32, 'api-register-id'!B:F, 4, FALSE), "Not found path.") -> mx-api-bc-bus-reference-data | C32: RAML | D32: BUSINESS | E32: =IFERROR(VLOOKUP(F32, 'api-register-id'!B:F, 5, FALSE), "Not found path.") -> APIMX000003 | F32: Bus Reference Data | G32: RESMX000031 | H32: Bus_RetrieveCustomerV1 | I32: =IFERROR(VLOOKUP(F32, 'api-register-id'!B:I, 8, FALSE), "Not found path.") -> 1.7.0 | J32: /referenceData | K32: v1 | L32: POST | M32: /v1/customer/retrieve | N32: =CONCATENATE(L32," ",J32,M32) -> POST /referenceData/v1/customer/retrieve | O32: Realiza la consulta del cliente por diferentes parámetros. | Q32: https://coppelmx.atlassian.net/wiki/x/A4AHPg | R32: Design | S32: ="https://github.com/SF-Bancoppel/"&B32 -> https://github.com/SF-Bancoppel/mx-api-bc-bus-reference-data
A33: {=IFERROR( INDEX( 'api-register-id'!A:A, MATCH(F33, 'api-register-id'!B:B, 0) ), "Not found Organization" )} -> SSFF | B33: =IFERROR(VLOOKUP(F33, 'api-register-id'!B:F, 4, FALSE), "Not found path.") -> mx-api-bc-bus-reference-data | C33: RAML | D33: BUSINESS | E33: =IFERROR(VLOOKUP(F33, 'api-register-id'!B:F, 5, FALSE), "Not found path.") -> APIMX000003 | F33: Bus Reference Data | G33: RESMX000032 | H33: Bus_RetrieveCustomerCardV1 | I33: =IFERROR(VLOOKUP(F33, 'api-register-id'!B:I, 8, FALSE), "Not found path.") -> 1.7.0 | J33: /referenceData | K33: v1 | L33: POST | M33: /v1/customerCard/retrieve | N33: =CONCATENATE(L33," ",J33,M33) -> POST /referenceData/v1/customerCard/retrieve | O33: En este microservicio se realiza la consulta de datos (nombre(s), apellido(s), RFC y número de tarjeta) del cliente titular de una tarjeta de crédito de las tablas sd_maecred, sd_tarjeta y si_cliente. Estas consultas se realizan para consultar los datos del cliente titular. | Q33: Pending load documentation... | R33: Design | S33: ="https://github.com/SF-Bancoppel/"&B33 -> https://github.com/SF-Bancoppel/mx-api-bc-bus-reference-data | V33: Martha
A34: {=IFERROR( INDEX( 'api-register-id'!A:A, MATCH(F34, 'api-register-id'!B:B, 0) ), "Not found Organization" )} -> SSFF | B34: =IFERROR(VLOOKUP(F34, 'api-register-id'!B:F, 4, FALSE), "Not found path.") -> mx-api-bc-bus-reference-data | C34: RAML | D34: BUSINESS | E34: =IFERROR(VLOOKUP(F34, 'api-register-id'!B:F, 5, FALSE), "Not found path.") -> APIMX000003 | F34: Bus Reference Data | G34: RESMX000033 | H34: Bus_RetrieveLifeInsuranceV1 | I34: =IFERROR(VLOOKUP(F34, 'api-register-id'!B:I, 8, FALSE), "Not found path.") -> 1.7.0 | J34: /referenceData | K34: v1 | L34: POST | M34: /v1/lifeInsurance/retrieve | N34: =CONCATENATE(L34," ",J34,M34) -> POST /referenceData/v1/lifeInsurance/retrieve | O34: Este microservicio realiza la validación según el estado en que se encuentre el club de protección del cliente y valida que mensaje mostrar al usuario.. | Q34: Pending load documentation... | R34: Design | S34: ="https://github.com/SF-Bancoppel/"&B34 -> https://github.com/SF-Bancoppel/mx-api-bc-bus-reference-data | V34: Martha
A35: {=IFERROR( INDEX( 'api-register-id'!A:A, MATCH(F35, 'api-register-id'!B:B, 0) ), "Not found Organization" )} -> SSFF | B35: =IFERROR(VLOOKUP(F35, 'api-register-id'!B:F, 4, FALSE), "Not found path.") -> mx-api-bc-bus-sales-and-service | C35: RAML | D35: BUSINESS | E35: =IFERROR(VLOOKUP(F35, 'api-register-id'!B:F, 5, FALSE), "Not found path.") -> APIMX000004 | F35: Bus Sales and Service | G35: RESMX000034 | H35: Bus_InitiateOnBoardingPartyV1 | I35: =IFERROR(VLOOKUP(F35, 'api-register-id'!B:I, 8, FALSE), "Not found path.") -> 1.12.0 | J35: /salesAndService | K35: v1 | L35: POST | M35: /v1/onBoardingParty/initiate | N35: =CONCATENATE(L35," ",J35,M35) -> POST /salesAndService/v1/onBoardingParty/initiate | O35: Servicio de Negocio encargado de iniciar el proceso de onboarding. | Q35: https://coppelmx.atlassian.net/wiki/x/BoBhPQ | R35: Design | S35: ="https://github.com/SF-Bancoppel/"&B35 -> https://github.com/SF-Bancoppel/mx-api-bc-bus-sales-and-service
A36: {=IFERROR( INDEX( 'api-register-id'!A:A, MATCH(F36, 'api-register-id'!B:B, 0) ), "Not found Organization" )} -> SSFF | B36: =IFERROR(VLOOKUP(F36, 'api-register-id'!B:F, 4, FALSE), "Not found path.") -> mx-api-bc-bus-sales-and-service | C36: RAML | D36: BUSINESS | E36: =IFERROR(VLOOKUP(F36, 'api-register-id'!B:F, 5, FALSE), "Not found path.") -> APIMX000004 | F36: Bus Sales and Service | G36: RESMX000035 | H36: Bus_EvaluateOnBoardingPhonePartyV1 | I36: =IFERROR(VLOOKUP(F36, 'api-register-id'!B:I, 8, FALSE), "Not found path.") -> 1.12.0 | J36: /salesAndService | K36: v1 | L36: POST | M36: /v1/onBoardingPhoneParty/evaluate | N36: =CONCATENATE(L36," ",J36,M36) -> POST /salesAndService/v1/onBoardingPhoneParty/evaluate | O36: Servicio de experiencia encargado de agregar, consultar y validar número de teléfono. | Q36: https://coppelmx.atlassian.net/wiki/x/JgBiPQ | R36: Design | S36: ="https://github.com/SF-Bancoppel/"&B36 -> https://github.com/SF-Bancoppel/mx-api-bc-bus-sales-and-service
A37: {=IFERROR( INDEX( 'api-register-id'!A:A, MATCH(F37, 'api-register-id'!B:B, 0) ), "Not found Organization" )} -> SSFF | B37: =IFERROR(VLOOKUP(F37, 'api-register-id'!B:F, 4, FALSE), "Not found path.") -> mx-api-bc-bus-sales-and-service | C37: RAML | D37: BUSINESS | E37: =IFERROR(VLOOKUP(F37, 'api-register-id'!B:F, 5, FALSE), "Not found path.") -> APIMX000004 | F37: Bus Sales and Service | G37: RESMX000036 | H37: Bus_ExecuteGenerateBiometricManagementV1 | I37: =IFERROR(VLOOKUP(F37, 'api-register-id'!B:I, 8, FALSE), "Not found path.") -> 1.12.0 | J37: /salesAndService | K37: v1 | L37: PUT | M37: /v1/generateBiometricManagement/execute | N37: =CONCATENATE(L37," ",J37,M37) -> PUT /salesAndService/v1/generateBiometricManagement/execute | O37: Operación encargada de gestionar los datos biométricos del cliente. | Q37: https://coppelmx.atlassian.net/wiki/spaces/GAC/pages/2158821554/RESMX000036_Bus_ExecuteBiometricManagement_V1 | R37: Design | S37: ="https://github.com/SF-Bancoppel/"&B37 -> https://github.com/SF-Bancoppel/mx-api-bc-bus-sales-and-service
A38: {=IFERROR( INDEX( 'api-register-id'!A:A, MATCH(F38, 'api-register-id'!B:B, 0) ), "Not found Organization" )} -> SSFF | B38: =IFERROR(VLOOKUP(F38, 'api-register-id'!B:F, 4, FALSE), "Not found path.") -> mx-api-bc-bus-sales-and-service | C38: RAML | D38: BUSINESS | E38: =IFERROR(VLOOKUP(F38, 'api-register-id'!B:F, 5, FALSE), "Not found path.") -> APIMX000004 | F38: Bus Sales and Service | G38: RESMX000037 | H38: Bus_EvaluateCustomerContactOperationV1 | I38: =IFERROR(VLOOKUP(F38, 'api-register-id'!B:I, 8, FALSE), "Not found path.") -> 1.12.0 | J38: /salesAndService | K38: v1 | L38: POST | M38: /v1/customerContactOperation/evaluate | N38: =CONCATENATE(L38," ",J38,M38) -> POST /salesAndService/v1/customerContactOperation/evaluate | O38: API que permite verificar si el folio sms ya fue validado para un cliente | Q38: https://coppelmx.atlassian.net/wiki/spaces/GAC/pages/2159313123/RESMX000037_Bus_EvaluateCustomerContactOperation_V1 | R38: Design | S38: ="https://github.com/SF-Bancoppel/"&B38 -> https://github.com/SF-Bancoppel/mx-api-bc-bus-sales-and-service
A39: {=IFERROR( INDEX( 'api-register-id'!A:A, MATCH(F39, 'api-register-id'!B:B, 0) ), "Not found Organization" )} -> SSFF | B39: =IFERROR(VLOOKUP(F39, 'api-register-id'!B:F, 4, FALSE), "Not found path.") -> mx-api-bc-bus-sales-and-service | C39: RAML | D39: BUSINESS | E39: =IFERROR(VLOOKUP(F39, 'api-register-id'!B:F, 5, FALSE), "Not found path.") -> APIMX000004 | F39: Bus Sales and Service | G39: RESMX000038 | H39: Bus_EvaluateCustomerWorkbenchFinancialTransactionV1 | I39: =IFERROR(VLOOKUP(F39, 'api-register-id'!B:I, 8, FALSE), "Not found path.") -> 1.12.0 | J39: /salesAndService | K39: v1 | L39: POST | M39: /v1/customerWorkbenchFinancialTransaction/evaluate | N39: =CONCATENATE(L39," ",J39,M39) -> POST /salesAndService/v1/customerWorkbenchFinancialTransaction/evaluate | O39: Servicio encargado de validar si la información proporcionada por el cliente a través del IVR es correcta y si está registrada en la base de datos de Bancoppel. | Q39: https://coppelmx.atlassian.net/wiki/x/xYC4g | R39: Design | S39: ="https://github.com/SF-Bancoppel/"&B39 -> https://github.com/SF-Bancoppel/mx-api-bc-bus-sales-and-service
A40: {=IFERROR( INDEX( 'api-register-id'!A:A, MATCH(F40, 'api-register-id'!B:B, 0) ), "Not found Organization" )} -> SSFF | B40: =IFERROR(VLOOKUP(F40, 'api-register-id'!B:F, 4, FALSE), "Not found path.") -> mx-api-bc-bus-sales-and-service | C40: RAML | D40: BUSINESS | E40: =IFERROR(VLOOKUP(F40, 'api-register-id'!B:F, 5, FALSE), "Not found path.") -> APIMX000004 | F40: Bus Sales and Service | G40: RESMX000039 | H40: Bus_UpdateContactPointV1 | I40: =IFERROR(VLOOKUP(F40, 'api-register-id'!B:I, 8, FALSE), "Not found path.") -> 1.12.0 | J40: /salesAndService | K40: v1 | L40: PUT | M40: /v1/contactPoint/update | N40: =CONCATENATE(L40," ",J40,M40) -> PUT /salesAndService/v1/contactPoint/update | O40: API que permite actualizar la información de contacto del cliente, el telefono y el email | Q40: Pending load documentation... | R40: Design | S40: ="https://github.com/SF-Bancoppel/"&B40 -> https://github.com/SF-Bancoppel/mx-api-bc-bus-sales-and-service | V40: Martha
A41: {=IFERROR( INDEX( 'api-register-id'!A:A, MATCH(F41, 'api-register-id'!B:B, 0) ), "Not found Organization" )} -> SSFF | B41: =IFERROR(VLOOKUP(F41, 'api-register-id'!B:F, 4, FALSE), "Not found path.") -> mx-api-bc-bus-sales-and-service | C41: RAML | D41: BUSINESS | E41: =IFERROR(VLOOKUP(F41, 'api-register-id'!B:F, 5, FALSE), "Not found path.") -> APIMX000004 | F41: Bus Sales and Service | G41: RESMX000040 | H41: Bus_UpdatePersonProfileV1 | I41: =IFERROR(VLOOKUP(F41, 'api-register-id'!B:I, 8, FALSE), "Not found path.") -> 1.12.0 | J41: /salesAndService | K41: v1 | L41: PUT | M41: /v1/personProfile/update | N41: =CONCATENATE(L41," ",J41,M41) -> PUT /salesAndService/v1/personProfile/update | O41: API que permite actualizar la información del perfil del cliente | Q41: https://coppelmx.atlassian.net/wiki/x/vQCsg | R41: Design | S41: ="https://github.com/SF-Bancoppel/"&B41 -> https://github.com/SF-Bancoppel/mx-api-bc-bus-sales-and-service
A42: {=IFERROR( INDEX( 'api-register-id'!A:A, MATCH(F42, 'api-register-id'!B:B, 0) ), "Not found Organization" )} -> SSFF | B42: =IFERROR(VLOOKUP(F42, 'api-register-id'!B:F, 4, FALSE), "Not found path.") -> mx-api-bc-bus-sales-and-service | C42: RAML | D42: BUSINESS | E42: =IFERROR(VLOOKUP(F42, 'api-register-id'!B:F, 5, FALSE), "Not found path.") -> APIMX000004 | F42: Bus Sales and Service | G42: RESMX000041 | H42: Bus_UpdateOnBoardingEmailPartyV1 | I42: =IFERROR(VLOOKUP(F42, 'api-register-id'!B:I, 8, FALSE), "Not found path.") -> 1.12.0 | J42: /salesAndService | K42: v1 | L42: PATCH | M42: /v1/onBoardingEmailParty/update | N42: =CONCATENATE(L42," ",J42,M42) -> PATCH /salesAndService/v1/onBoardingEmailParty/update | O42: API que permite Consultar información OCR del Comprobante de domicilio en Incode, Insertar Domicilio del Comprobante Domicilio en tabla Address y Actualizar Tabla Address (Actualiza domicilio del prospecto) | Q42: https://coppelmx.atlassian.net/wiki/x/JoBhPQ | R42: Design | S42: ="https://github.com/SF-Bancoppel/"&B42 -> https://github.com/SF-Bancoppel/mx-api-bc-bus-sales-and-service
A43: {=IFERROR( INDEX( 'api-register-id'!A:A, MATCH(F43, 'api-register-id'!B:B, 0) ), "Not found Organization" )} -> SSFF | B43: =IFERROR(VLOOKUP(F43, 'api-register-id'!B:F, 4, FALSE), "Not found path.") -> mx-api-bc-bus-sales-and-service | C43: RAML | D43: BUSINESS | E43: =IFERROR(VLOOKUP(F43, 'api-register-id'!B:F, 5, FALSE), "Not found path.") -> APIMX000004 | F43: Bus Sales and Service | G43: RESMX000042 | H43: Bus_EvaluateOnBoardingEmailPartyV1 | I43: =IFERROR(VLOOKUP(F43, 'api-register-id'!B:I, 8, FALSE), "Not found path.") -> 1.12.0 | J43: /salesAndService | K43: v1 | L43: POST | M43: /v1/onBoardingEmailParty/evaluate | N43: =CONCATENATE(L43," ",J43,M43) -> POST /salesAndService/v1/onBoardingEmailParty/evaluate | O43: Servicio de negocio encargado del manejo del OTP del cliente, y de las plantillas de la tabla Template | Q43: https://coppelmx.atlassian.net/wiki/x/KwCpPQ | R43: Design | S43: ="https://github.com/SF-Bancoppel/"&B43 -> https://github.com/SF-Bancoppel/mx-api-bc-bus-sales-and-service
A44: {=IFERROR( INDEX( 'api-register-id'!A:A, MATCH(F44, 'api-register-id'!B:B, 0) ), "Not found Organization" )} -> SSFF | B44: =IFERROR(VLOOKUP(F44, 'api-register-id'!B:F, 4, FALSE), "Not found path.") -> mx-api-bc-bus-sales-and-service | C44: RAML | D44: BUSINESS | E44: =IFERROR(VLOOKUP(F44, 'api-register-id'!B:F, 5, FALSE), "Not found path.") -> APIMX000004 | F44: Bus Sales and Service | G44: RESMX000043 | H44: Bus_RetrieveGenerateCustomerOfferProcedureV1 | I44: =IFERROR(VLOOKUP(F44, 'api-register-id'!B:I, 8, FALSE), "Not found path.") -> 1.12.0 | J44: /salesAndService | K44: v1 | L44: POST | M44: /v1/generateCustomerOfferProcedure/retrieve | N44: =CONCATENATE(L44," ",J44,M44) -> POST /salesAndService/v1/generateCustomerOfferProcedure/retrieve | O44: Api que permite consultar si un cliente tiene una oferta de credito disponible | Q44: https://coppelmx.atlassian.net/wiki/x/yIC8g | R44: Design | S44: ="https://github.com/SF-Bancoppel/"&B44 -> https://github.com/SF-Bancoppel/mx-api-bc-bus-sales-and-service
A45: {=IFERROR( INDEX( 'api-register-id'!A:A, MATCH(F45, 'api-register-id'!B:B, 0) ), "Not found Organization" )} -> SSFF | B45: =IFERROR(VLOOKUP(F45, 'api-register-id'!B:F, 4, FALSE), "Not found path.") -> mx-api-bc-bus-sales-and-service | C45: RAML | D45: BUSINESS | E45: =IFERROR(VLOOKUP(F45, 'api-register-id'!B:F, 5, FALSE), "Not found path.") -> APIMX000004 | F45: Bus Sales and Service | G45: RESMX000044 | H45: Bus_RetrieveCustomerCreditRatingV1 | I45: =IFERROR(VLOOKUP(F45, 'api-register-id'!B:I, 8, FALSE), "Not found path.") -> 1.12.0 | J45: /salesAndService | K45: v1 | L45: POST | M45: /v1/customerCreditRating/retrieve | N45: =CONCATENATE(L45," ",J45,M45) -> POST /salesAndService/v1/customerCreditRating/retrieve | O45: Permite consultar si un cliente se encuentra een una lista negra | Q45: https://coppelmx.atlassian.net/wiki/x/lIGZg | R45: Design | S45: ="https://github.com/SF-Bancoppel/"&B45 -> https://github.com/SF-Bancoppel/mx-api-bc-bus-sales-and-service
A46: {=IFERROR( INDEX( 'api-register-id'!A:A, MATCH(F46, 'api-register-id'!B:B, 0) ), "Not found Organization" )} -> SSFF | B46: =IFERROR(VLOOKUP(F46, 'api-register-id'!B:F, 4, FALSE), "Not found path.") -> mx-api-bc-bus-sales-and-service | C46: RAML | D46: BUSINESS | E46: =IFERROR(VLOOKUP(F46, 'api-register-id'!B:F, 5, FALSE), "Not found path.") -> APIMX000004 | F46: Bus Sales and Service | G46: RESMX000045 | H46: Bus_UpdateOnBoardingPartyLocationV1 | I46: =IFERROR(VLOOKUP(F46, 'api-register-id'!B:I, 8, FALSE), "Not found path.") -> 1.12.0 | J46: /salesAndService | K46: v1 | L46: PATCH | M46: /v1/onBoardingPartyLocation/{sessionDialogueIdentification}/update | N46: =CONCATENATE(L46," ",J46,M46) -> PATCH /salesAndService/v1/onBoardingPartyLocation/{sessionDialogueIdentification}/update | O46: API que permite Consultar información OCR del Comprobante de domicilio en Incode, Insertar Domicilio del Comprobante Domicilio en tabla Address y Actualizar Tabla Address (Actualiza domicilio del prospecto) | Q46: https://coppelmx.atlassian.net/wiki/x/IYCvPQ | R46: Design | S46: ="https://github.com/SF-Bancoppel/"&B46 -> https://github.com/SF-Bancoppel/mx-api-bc-bus-sales-and-service
A47: {=IFERROR( INDEX( 'api-register-id'!A:A, MATCH(F47, 'api-register-id'!B:B, 0) ), "Not found Organization" )} -> SSFF | B47: =IFERROR(VLOOKUP(F47, 'api-register-id'!B:F, 4, FALSE), "Not found path.") -> mx-api-bc-bus-sales-and-service | C47: RAML | D47: BUSINESS | E47: =IFERROR(VLOOKUP(F47, 'api-register-id'!B:F, 5, FALSE), "Not found path.") -> APIMX000004 | F47: Bus Sales and Service | G47: RESMX000046 | H47: Bus_EvaluateOnboardingPartySICV1 | I47: =IFERROR(VLOOKUP(F47, 'api-register-id'!B:I, 8, FALSE), "Not found path.") -> 1.12.0 | J47: /salesAndService | K47: v1 | L47: POST | M47: /v1/onboardingPartySIC/evaluate | N47: =CONCATENATE(L47," ",J47,M47) -> POST /salesAndService/v1/onboardingPartySIC/evaluate | O47: API que permite la validación OTP en INCODE (SICs) y guardar Validación OTP (SICs) | Q47: https://coppelmx.atlassian.net/wiki/x/rQClPQ | R47: Design | S47: ="https://github.com/SF-Bancoppel/"&B47 -> https://github.com/SF-Bancoppel/mx-api-bc-bus-sales-and-service
A48: {=IFERROR( INDEX( 'api-register-id'!A:A, MATCH(F48, 'api-register-id'!B:B, 0) ), "Not found Organization" )} -> SSFF | B48: =IFERROR(VLOOKUP(F48, 'api-register-id'!B:F, 4, FALSE), "Not found path.") -> mx-api-bc-dom-account-reconciliation | C48: RAML | D48: DOMAIN | E48: =IFERROR(VLOOKUP(F48, 'api-register-id'!B:F, 5, FALSE), "Not found path.") -> APIMX000005 | F48: Dom Account Reconciliation | G48: RESMX000047 | H48: Dom_CaptureAccountReconciliationProcedureV1 | I48: =IFERROR(VLOOKUP(F48, 'api-register-id'!B:I, 8, FALSE), "Not found path.") -> 1.1.0 | J48: /accountManagement/accountReconciliation | K48: v1 | L48: PATCH | M48: /v1/accountReconciliationProcedure/capture | N48: =CONCATENATE(L48," ",J48,M48) -> PATCH /accountManagement/accountReconciliation/v1/accountReconciliationProcedure/capture | O48: Este procedimiento realiza la conciliación de saldos retenidos y realiza los cargos correspondientes a la cuenta. | Q48: Pending load documentation... | R48: Design | S48: ="https://github.com/SF-Bancoppel/"&B48 -> https://github.com/SF-Bancoppel/mx-api-bc-dom-account-reconciliation | V48: Martha
A49: {=IFERROR( INDEX( 'api-register-id'!A:A, MATCH(F49, 'api-register-id'!B:B, 0) ), "Not found Organization" )} -> SSFF | B49: =IFERROR(VLOOKUP(F49, 'api-register-id'!B:F, 4, FALSE), "Not found path.") -> mx-api-bc-dom-branch-location-operations | C49: RAML | D49: DOMAIN | E49: =IFERROR(VLOOKUP(F49, 'api-register-id'!B:F, 5, FALSE), "Not found path.") -> APIMX000006 | F49: Dom Branch Location Operations | G49: RESMX000048 | H49: Dom_RetrieveBranchLocationV1 | I49: =IFERROR(VLOOKUP(F49, 'api-register-id'!B:I, 8, FALSE), "Not found path.") -> 1.2.0 | J49: /channelSpecific/branchLocationOperations | K49: v1 | L49: POST | M49: /v1/branchLocation/retrieve | N49: =CONCATENATE(L49," ",J49,M49) -> POST /channelSpecific/branchLocationOperations/v1/branchLocation/retrieve | O49: Operación encargada de obtener información geográfica de las suscursales bancarias. | Q49: Pending load documentation... | R49: Design | S49: ="https://github.com/SF-Bancoppel/"&B49 -> https://github.com/SF-Bancoppel/mx-api-bc-dom-branch-location-operations | V49: Martha
A50: {=IFERROR( INDEX( 'api-register-id'!A:A, MATCH(F50, 'api-register-id'!B:B, 0) ), "Not found Organization" )} -> SSFF | B50: =IFERROR(VLOOKUP(F50, 'api-register-id'!B:F, 4, FALSE), "Not found path.") -> mx-api-bc-dom-card-ecommerce-gateway | C50: RAML | D50: DOMAIN | E50: =IFERROR(VLOOKUP(F50, 'api-register-id'!B:F, 5, FALSE), "Not found path.") -> APIMX000008 | F50: Dom Card eCommerce Gateway | G50: RESMX000049 | H50: Dom_CreateTokenAssignmentV1 | I50: =IFERROR(VLOOKUP(F50, 'api-register-id'!B:I, 8, FALSE), "Not found path.") -> 1.0.0 | J50: /payments/cardeCommerceGateway | K50: v1 | L50: POST | M50: /v1/tokenAssignment/create | N50: =CONCATENATE(L50," ",J50,M50) -> POST /payments/cardeCommerceGateway/v1/tokenAssignment/create | O50: Esta API se encarga de consultar el código CVC2 dinámico de las tarjetas de crédito, lo que permite realizar compras de manera segura y validada. | Q50: https://coppelmx.atlassian.net/wiki/x/LIB_PQ | R50: Design | S50: ="https://github.com/SF-Bancoppel/"&B50 -> https://github.com/SF-Bancoppel/mx-api-bc-dom-card-ecommerce-gateway
A51: {=IFERROR( INDEX( 'api-register-id'!A:A, MATCH(F51, 'api-register-id'!B:B, 0) ), "Not found Organization" )} -> SSFF | B51: =IFERROR(VLOOKUP(F51, 'api-register-id'!B:F, 4, FALSE), "Not found path.") -> mx-api-bc-dom-corporate-current-account | C51: RAML | D51: DOMAIN | E51: =IFERROR(VLOOKUP(F51, 'api-register-id'!B:F, 5, FALSE), "Not found path.") -> APIMX000009 | F51: Dom Corporate Current Account | G51: RESMX000050 | H51: Dom_InitiateCorporateCurrentAccountFacilityV1 | I51: =IFERROR(VLOOKUP(F51, 'api-register-id'!B:I, 8, FALSE), "Not found path.") -> 1.1.0 | J51: /loansAndDeposits/corporateCurrentAccount | K51: v1 | L51: POST | M51: /v1/corporateCurrentAccountFacility/initiate | N51: =CONCATENATE(L51," ",J51,M51) -> POST /loansAndDeposits/corporateCurrentAccount/v1/corporateCurrentAccountFacility/initiate | O51: Esta API permite la creacion de una cuenta empresarial en transact | Q51: Pending load documentation... | R51: Design | S51: ="https://github.com/SF-Bancoppel/"&B51 -> https://github.com/SF-Bancoppel/mx-api-bc-dom-corporate-current-account | V51: Martha
A52: {=IFERROR( INDEX( 'api-register-id'!A:A, MATCH(F52, 'api-register-id'!B:B, 0) ), "Not found Organization" )} -> SSFF | B52: =IFERROR(VLOOKUP(F52, 'api-register-id'!B:F, 4, FALSE), "Not found path.") -> mx-api-bc-dom-correspondence | C52: RAML | D52: DOMAIN | E52: =IFERROR(VLOOKUP(F52, 'api-register-id'!B:F, 5, FALSE), "Not found path.") -> APIMX000010 | F52: Dom Correspondence | G52: RESMX000051 | H52: Dom_RegisterOutboundV1 | I52: =IFERROR(VLOOKUP(F52, 'api-register-id'!B:I, 8, FALSE), "Not found path.") -> 1.0.0 | J52: /documentManagementAndArchive/correspondence | K52: v1 | L52: POST | M52: /v1/outbound/register | N52: =CONCATENATE(L52," ",J52,M52) -> POST /documentManagementAndArchive/correspondence/v1/outbound/register | O52: Permite registrar un evento para un envío de sms o correo | Q52: https://coppelmx.atlassian.net/wiki/x/BgDVPQ | R52: Design | S52: ="https://github.com/SF-Bancoppel/"&B52 -> https://github.com/SF-Bancoppel/mx-api-bc-dom-correspondence
A53: {=IFERROR( INDEX( 'api-register-id'!A:A, MATCH(F53, 'api-register-id'!B:B, 0) ), "Not found Organization" )} -> SSFF | B53: =IFERROR(VLOOKUP(F53, 'api-register-id'!B:F, 4, FALSE), "Not found path.") -> mx-api-bc-dom-counterparty-risk | C53: RAML | D53: DOMAIN | E53: =IFERROR(VLOOKUP(F53, 'api-register-id'!B:F, 5, FALSE), "Not found path.") -> APIMX000011 | F53: Dom Counterparty Risk | G53: RESMX000052 | H53: Dom_RetrieveCustomerCreditRatingV1 | I53: =IFERROR(VLOOKUP(F53, 'api-register-id'!B:I, 8, FALSE), "Not found path.") -> 1.2.0 | J53: /accountManagement/counterpartyRisk | K53: v1 | L53: POST | M53: /v1/customerCreditRating/retrieve | N53: =CONCATENATE(L53," ",J53,M53) -> POST /accountManagement/counterpartyRisk/v1/customerCreditRating/retrieve | O53: se encarga de realizar consultas a buró de crédito para obtener los antecedentes crediticios de los clientes que están realizando un trámite para una solicitud de tarjeta de crédito con el fin de considerar estos antecedentes para su posible aprobación o rechazo a la solicitud. | Q53: https://coppelmx.atlassian.net/wiki/x/ZwBoPQ | R53: Design | S53: ="https://github.com/SF-Bancoppel/"&B53 -> https://github.com/SF-Bancoppel/mx-api-bc-dom-counterparty-risk
A54: {=IFERROR( INDEX( 'api-register-id'!A:A, MATCH(F54, 'api-register-id'!B:B, 0) ), "Not found Organization" )} -> SSFF | B54: =IFERROR(VLOOKUP(F54, 'api-register-id'!B:F, 4, FALSE), "Not found path.") -> mx-api-bc-dom-counterparty-risk | C54: RAML | D54: DOMAIN | E54: =IFERROR(VLOOKUP(F54, 'api-register-id'!B:F, 5, FALSE), "Not found path.") -> APIMX000011 | F54: Dom Counterparty Risk | G54: RESMX000053 | H54: Dom_EvaluateCustomerCreditRatingV1 | I54: =IFERROR(VLOOKUP(F54, 'api-register-id'!B:I, 8, FALSE), "Not found path.") -> 1.2.0 | J54: /accountManagement/counterpartyRisk | K54: v1 | L54: POST | M54: /v1/customerCreditRating/evaluate | N54: =CONCATENATE(L54," ",J54,M54) -> POST /accountManagement/counterpartyRisk/v1/customerCreditRating/evaluate | O54: Operación encargada de obtener la información crediticia de un cliente. | Q54: https://coppelmx.atlassian.net/wiki/x/VABiPQ | R54: Design | S54: ="https://github.com/SF-Bancoppel/"&B54 -> https://github.com/SF-Bancoppel/mx-api-bc-dom-counterparty-risk
A55: {=IFERROR( INDEX( 'api-register-id'!A:A, MATCH(F55, 'api-register-id'!B:B, 0) ), "Not found Organization" )} -> SSFF | B55: =IFERROR(VLOOKUP(F55, 'api-register-id'!B:F, 4, FALSE), "Not found path.") -> mx-api-bc-dom-counterparty-risk | C55: RAML | D55: DOMAIN | E55: =IFERROR(VLOOKUP(F55, 'api-register-id'!B:F, 5, FALSE), "Not found path.") -> APIMX000011 | F55: Dom Counterparty Risk | G55: RESMX000054 | H55: Dom_RetrieveReasonsRejectionV1 | I55: =IFERROR(VLOOKUP(F55, 'api-register-id'!B:I, 8, FALSE), "Not found path.") -> 1.2.0 | J55: /accountManagement/counterpartyRisk | K55: v1 | L55: GET | M55: /v1/reasonsRejection/retrieve | N55: =CONCATENATE(L55," ",J55,M55) -> GET /accountManagement/counterpartyRisk/v1/reasonsRejection/retrieve | O55: Operación encargada de obtener la información de los motivos de rechazo de un cliente | Q55: Pending load documentation... | R55: Design | S55: ="https://github.com/SF-Bancoppel/"&B55 -> https://github.com/SF-Bancoppel/mx-api-bc-dom-counterparty-risk | V55: Martha
A56: {=IFERROR( INDEX( 'api-register-id'!A:A, MATCH(F56, 'api-register-id'!B:B, 0) ), "Not found Organization" )} -> SSFF | B56: =IFERROR(VLOOKUP(F56, 'api-register-id'!B:F, 4, FALSE), "Not found path.") -> mx-api-bc-dom-credit-card | C56: RAML | D56: DOMAIN | E56: =IFERROR(VLOOKUP(F56, 'api-register-id'!B:F, 5, FALSE), "Not found path.") -> APIMX000012 | F56: Dom Credit Card | G56: RESMX000055 | H56: Dom_RetrieveCreditCardApplicationV1 | I56: =IFERROR(VLOOKUP(F56, 'api-register-id'!B:I, 8, FALSE), "Not found path.") -> 1.31.0 | J56: /cards/creditCard | K56: v1 | L56: POST | M56: /v1/creditCardApplication/retrieve | N56: =CONCATENATE(L56," ",J56,M56) -> POST /cards/creditCard/v1/creditCardApplication/retrieve | O56: Permite consultar la información de solicitud de crédito. | Q56: https://coppelmx.atlassian.net/wiki/x/KgBpPQ | R56: Design | S56: ="https://github.com/SF-Bancoppel/"&B56 -> https://github.com/SF-Bancoppel/mx-api-bc-dom-credit-card
A57: {=IFERROR( INDEX( 'api-register-id'!A:A, MATCH(F57, 'api-register-id'!B:B, 0) ), "Not found Organization" )} -> SSFF | B57: =IFERROR(VLOOKUP(F57, 'api-register-id'!B:F, 4, FALSE), "Not found path.") -> mx-api-bc-dom-credit-card | C57: RAML | D57: DOMAIN | E57: =IFERROR(VLOOKUP(F57, 'api-register-id'!B:F, 5, FALSE), "Not found path.") -> APIMX000012 | F57: Dom Credit Card | G57: RESMX000056 | H57: Dom_InitiateCreditCardApplicationV1 | I57: =IFERROR(VLOOKUP(F57, 'api-register-id'!B:I, 8, FALSE), "Not found path.") -> 1.31.0 | J57: /cards/creditCard | K57: v1 | L57: POST | M57: /v1/creditCardApplication/initiate | N57: =CONCATENATE(L57," ",J57,M57) -> POST /cards/creditCard/v1/creditCardApplication/initiate | O57: Servicio de dominio que guarda la solicitud de un producto de tarjeta de crédito en la tabla Application. | Q57: https://coppelmx.atlassian.net/wiki/x/WYBrPQ | R57: Design | S57: ="https://github.com/SF-Bancoppel/"&B57 -> https://github.com/SF-Bancoppel/mx-api-bc-dom-credit-card
A58: {=IFERROR( INDEX( 'api-register-id'!A:A, MATCH(F58, 'api-register-id'!B:B, 0) ), "Not found Organization" )} -> SSFF | B58: =IFERROR(VLOOKUP(F58, 'api-register-id'!B:F, 4, FALSE), "Not found path.") -> mx-api-bc-dom-credit-card | C58: RAML | D58: DOMAIN | E58: =IFERROR(VLOOKUP(F58, 'api-register-id'!B:F, 5, FALSE), "Not found path.") -> APIMX000012 | F58: Dom Credit Card | G58: RESMX000057 | H58: Dom_ExchangeCreditCardApplicationV1 | I58: =IFERROR(VLOOKUP(F58, 'api-register-id'!B:I, 8, FALSE), "Not found path.") -> 1.31.0 | J58: /cards/creditCard | K58: v1 | L58: POST | M58: /v1/creditCardApplication/exchange | N58: =CONCATENATE(L58," ",J58,M58) -> POST /cards/creditCard/v1/creditCardApplication/exchange | O58: Permite limpiar la información de Clonación de tarjeta de crédito Clásica a Oro | P58: Invalid Action Term "exchange" for HTTP method "POST". For Action Term "exchange" use "PUT,PATCH" | Q58: Pending load documentation... | R58: Design | S58: ="https://github.com/SF-Bancoppel/"&B58 -> https://github.com/SF-Bancoppel/mx-api-bc-dom-credit-card | V58: Martha
A59: {=IFERROR( INDEX( 'api-register-id'!A:A, MATCH(F59, 'api-register-id'!B:B, 0) ), "Not found Organization" )} -> SSFF | B59: =IFERROR(VLOOKUP(F59, 'api-register-id'!B:F, 4, FALSE), "Not found path.") -> mx-api-bc-dom-credit-card | C59: RAML | D59: DOMAIN | E59: =IFERROR(VLOOKUP(F59, 'api-register-id'!B:F, 5, FALSE), "Not found path.") -> APIMX000012 | F59: Dom Credit Card | G59: RESMX000058 | H59: Dom_UpdateCreditCardApplicationV1 | I59: =IFERROR(VLOOKUP(F59, 'api-register-id'!B:I, 8, FALSE), "Not found path.") -> 1.31.0 | J59: /cards/creditCard | K59: v1 | L59: PATCH | M59: /v1/creditCardApplication/update | N59: =CONCATENATE(L59," ",J59,M59) -> PATCH /cards/creditCard/v1/creditCardApplication/update | O59: Permite actualizar el estado de una solicitud de tarjeta de crédito y guarda la oferta generada en el paramétrico | Q59: https://coppelmx.atlassian.net/wiki/x/FwB-PQ | R59: Design | S59: ="https://github.com/SF-Bancoppel/"&B59 -> https://github.com/SF-Bancoppel/mx-api-bc-dom-credit-card
A60: {=IFERROR( INDEX( 'api-register-id'!A:A, MATCH(F60, 'api-register-id'!B:B, 0) ), "Not found Organization" )} -> SSFF | B60: =IFERROR(VLOOKUP(F60, 'api-register-id'!B:F, 4, FALSE), "Not found path.") -> mx-api-bc-dom-credit-card | C60: RAML | D60: DOMAIN | E60: =IFERROR(VLOOKUP(F60, 'api-register-id'!B:F, 5, FALSE), "Not found path.") -> APIMX000012 | F60: Dom Credit Card | G60: RESMX000059 | H60: Dom_RegisterCreditCardFacilityV1 | I60: =IFERROR(VLOOKUP(F60, 'api-register-id'!B:I, 8, FALSE), "Not found path.") -> 1.31.0 | J60: /cards/creditCard | K60: v1 | L60: POST | M60: /v1/creditCardFacility/register | N60: =CONCATENATE(L60," ",J60,M60) -> POST /cards/creditCard/v1/creditCardFacility/register | O60: Crea una tarjeta de crédito con sus saldos | Q60: https://coppelmx.atlassian.net/wiki/x/AQCaPQ | R60: Design | S60: ="https://github.com/SF-Bancoppel/"&B60 -> https://github.com/SF-Bancoppel/mx-api-bc-dom-credit-card
A61: {=IFERROR( INDEX( 'api-register-id'!A:A, MATCH(F61, 'api-register-id'!B:B, 0) ), "Not found Organization" )} -> SSFF | B61: =IFERROR(VLOOKUP(F61, 'api-register-id'!B:F, 4, FALSE), "Not found path.") -> mx-api-bc-dom-credit-card | C61: RAML | D61: DOMAIN | E61: =IFERROR(VLOOKUP(F61, 'api-register-id'!B:F, 5, FALSE), "Not found path.") -> APIMX000012 | F61: Dom Credit Card | G61: RESMX000060 | H61: Dom_RetrieveCreditCardFacilityV1 | I61: =IFERROR(VLOOKUP(F61, 'api-register-id'!B:I, 8, FALSE), "Not found path.") -> 1.31.0 | J61: /cards/creditCard | K61: v1 | L61: POST | M61: /v1/creditCardFacility/retrieve | N61: =CONCATENATE(L61," ",J61,M61) -> POST /cards/creditCard/v1/creditCardFacility/retrieve | O61: Este domain API realiza la consulta de información de tarjeta de crédito por cliente | Q61: https://coppelmx.atlassian.net/wiki/x/CoCPPQ | R61: Design | S61: ="https://github.com/SF-Bancoppel/"&B61 -> https://github.com/SF-Bancoppel/mx-api-bc-dom-credit-card
A62: {=IFERROR( INDEX( 'api-register-id'!A:A, MATCH(F62, 'api-register-id'!B:B, 0) ), "Not found Organization" )} -> SSFF | B62: =IFERROR(VLOOKUP(F62, 'api-register-id'!B:F, 4, FALSE), "Not found path.") -> mx-api-bc-dom-credit-card | C62: RAML | D62: DOMAIN | E62: =IFERROR(VLOOKUP(F62, 'api-register-id'!B:F, 5, FALSE), "Not found path.") -> APIMX000012 | F62: Dom Credit Card | G62: RESMX000061 | H62: Dom_UpdateCreditCardBalanceV1 | I62: =IFERROR(VLOOKUP(F62, 'api-register-id'!B:I, 8, FALSE), "Not found path.") -> 1.31.0 | J62: /cards/creditCard | K62: v1 | L62: POST | M62: /v1/creditCardBalance/update | N62: =CONCATENATE(L62," ",J62,M62) -> POST /cards/creditCard/v1/creditCardBalance/update | O62: Permite actualizar el indicador de disposición de efectivo de una tarjeta de crédito | P62: Invalid Action Term "update" for HTTP method "POST". For Action Term "update" use "PUT,PATCH" | Q62: Pending load documentation... | R62: Design | S62: ="https://github.com/SF-Bancoppel/"&B62 -> https://github.com/SF-Bancoppel/mx-api-bc-dom-credit-card | V62: Martha
A63: {=IFERROR( INDEX( 'api-register-id'!A:A, MATCH(F63, 'api-register-id'!B:B, 0) ), "Not found Organization" )} -> SSFF | B63: =IFERROR(VLOOKUP(F63, 'api-register-id'!B:F, 4, FALSE), "Not found path.") -> mx-api-bc-dom-credit-card | C63: RAML | D63: DOMAIN | E63: =IFERROR(VLOOKUP(F63, 'api-register-id'!B:F, 5, FALSE), "Not found path.") -> APIMX000012 | F63: Dom Credit Card | G63: RESMX000062 | H63: Dom_RetrieveCreditCardBalanceV1 | I63: =IFERROR(VLOOKUP(F63, 'api-register-id'!B:I, 8, FALSE), "Not found path.") -> 1.31.0 | J63: /cards/creditCard | K63: v1 | L63: POST | M63: /v1/creditCardBalance/retrieve | N63: =CONCATENATE(L63," ",J63,M63) -> POST /cards/creditCard/v1/creditCardBalance/retrieve | O63: Este domain API realiza la consulta de disposición de efectivo de una tarjeta de crédito con un monto solicitado. | Q63: https://coppelmx.atlassian.net/wiki/x/CIClPQ | R63: Design | S63: ="https://github.com/SF-Bancoppel/"&B63 -> https://github.com/SF-Bancoppel/mx-api-bc-dom-credit-card
A64: {=IFERROR( INDEX( 'api-register-id'!A:A, MATCH(F64, 'api-register-id'!B:B, 0) ), "Not found Organization" )} -> SSFF | B64: =IFERROR(VLOOKUP(F64, 'api-register-id'!B:F, 4, FALSE), "Not found path.") -> mx-api-bc-dom-credit-card | C64: RAML | D64: DOMAIN | E64: =IFERROR(VLOOKUP(F64, 'api-register-id'!B:F, 5, FALSE), "Not found path.") -> APIMX000012 | F64: Dom Credit Card | G64: RESMX000063 | H64: Dom_RetrieveInterestV1 | I64: =IFERROR(VLOOKUP(F64, 'api-register-id'!B:I, 8, FALSE), "Not found path.") -> 1.31.0 | J64: /cards/creditCard | K64: v1 | L64: GET | M64: /v1/interest/{companyReference}/{applicationReferenceId}/retrieve | N64: =CONCATENATE(L64," ",J64,M64) -> GET /cards/creditCard/v1/interest/{companyReference}/{applicationReferenceId}/retrieve | O64: Permite consultar los intereses y tasas para tarjeta de crédito | Q64: Pending load documentation... | R64: Design | S64: ="https://github.com/SF-Bancoppel/"&B64 -> https://github.com/SF-Bancoppel/mx-api-bc-dom-credit-card | V64: Martha
A65: {=IFERROR( INDEX( 'api-register-id'!A:A, MATCH(F65, 'api-register-id'!B:B, 0) ), "Not found Organization" )} -> SSFF | B65: =IFERROR(VLOOKUP(F65, 'api-register-id'!B:F, 4, FALSE), "Not found path.") -> mx-api-bc-dom-credit-card | C65: RAML | D65: DOMAIN | E65: =IFERROR(VLOOKUP(F65, 'api-register-id'!B:F, 5, FALSE), "Not found path.") -> APIMX000012 | F65: Dom Credit Card | G65: RESMX000064 | H65: Dom_UpdateInterestV1 | I65: =IFERROR(VLOOKUP(F65, 'api-register-id'!B:I, 8, FALSE), "Not found path.") -> 1.31.0 | J65: /cards/creditCard | K65: v1 | L65: POST | M65: /v1/interest/update | N65: =CONCATENATE(L65," ",J65,M65) -> POST /cards/creditCard/v1/interest/update | O65: Permite actualizar la información de intereses y tasas preferenciales en la nueva tarjeta de crédito | P65: Invalid Action Term "update" for HTTP method "POST". For Action Term "update" use "PUT,PATCH" | Q65: Pending load documentation... | R65: Design | S65: ="https://github.com/SF-Bancoppel/"&B65 -> https://github.com/SF-Bancoppel/mx-api-bc-dom-credit-card | V65: Martha
A66: {=IFERROR( INDEX( 'api-register-id'!A:A, MATCH(F66, 'api-register-id'!B:B, 0) ), "Not found Organization" )} -> SSFF | B66: =IFERROR(VLOOKUP(F66, 'api-register-id'!B:F, 4, FALSE), "Not found path.") -> mx-api-bc-dom-credit-card | C66: RAML | D66: DOMAIN | E66: =IFERROR(VLOOKUP(F66, 'api-register-id'!B:F, 5, FALSE), "Not found path.") -> APIMX000012 | F66: Dom Credit Card | G66: RESMX000065 | H66: Dom_RetrieveCardPaymentAgreementV1 | I66: =IFERROR(VLOOKUP(F66, 'api-register-id'!B:I, 8, FALSE), "Not found path.") -> 1.31.0 | J66: /cards/creditCard | K66: v1 | L66: POST | M66: /v1/cardPaymentAgreement/retrieve | N66: =CONCATENATE(L66," ",J66,M66) -> POST /cards/creditCard/v1/cardPaymentAgreement/retrieve | O66: API que obtiene los datos de la caratula de tarjeta de crédito del cliente. | Q66: https://coppelmx.atlassian.net/wiki/x/Q4CpPQ | R66: Design | S66: ="https://github.com/SF-Bancoppel/"&B66 -> https://github.com/SF-Bancoppel/mx-api-bc-dom-credit-card
A67: {=IFERROR( INDEX( 'api-register-id'!A:A, MATCH(F67, 'api-register-id'!B:B, 0) ), "Not found Organization" )} -> SSFF | B67: =IFERROR(VLOOKUP(F67, 'api-register-id'!B:F, 4, FALSE), "Not found path.") -> mx-api-bc-dom-credit-card | C67: RAML | D67: DOMAIN | E67: =IFERROR(VLOOKUP(F67, 'api-register-id'!B:F, 5, FALSE), "Not found path.") -> APIMX000012 | F67: Dom Credit Card | G67: RESMX000066 | H67: Dom_RetrievePaymentCardV1 | I67: =IFERROR(VLOOKUP(F67, 'api-register-id'!B:I, 8, FALSE), "Not found path.") -> 1.31.0 | J67: /cards/creditCard | K67: v1 | L67: POST | M67: /v1/paymentCard/retrieve | N67: =CONCATENATE(L67," ",J67,M67) -> POST /cards/creditCard/v1/paymentCard/retrieve | O67: Este servicio realiza de la consulta la información de tarjeta de crédito por número de tarjeta | P67: Invalid Request Header "authorization" | Q67: https://coppelmx.atlassian.net/wiki/x/M4CyPQ | R67: Design | S67: ="https://github.com/SF-Bancoppel/"&B67 -> https://github.com/SF-Bancoppel/mx-api-bc-dom-credit-card
A68: {=IFERROR( INDEX( 'api-register-id'!A:A, MATCH(F68, 'api-register-id'!B:B, 0) ), "Not found Organization" )} -> SSFF | B68: =IFERROR(VLOOKUP(F68, 'api-register-id'!B:F, 4, FALSE), "Not found path.") -> mx-api-bc-dom-credit-card | C68: RAML | D68: DOMAIN | E68: =IFERROR(VLOOKUP(F68, 'api-register-id'!B:F, 5, FALSE), "Not found path.") -> APIMX000012 | F68: Dom Credit Card | G68: RESMX000067 | H68: Dom_RegisterCreditCardActivationLogV1 | I68: =IFERROR(VLOOKUP(F68, 'api-register-id'!B:I, 8, FALSE), "Not found path.") -> 1.31.0 | J68: /cards/creditCard | K68: v1 | L68: POST | M68: /v1/creditCardActivationLog/register | N68: =CONCATENATE(L68," ",J68,M68) -> POST /cards/creditCard/v1/creditCardActivationLog/register | O68: Este servicio realiza de la consulta la información de tarjeta de crédito por número de tarjeta | Q68: Pending load documentation... | R68: Design | S68: ="https://github.com/SF-Bancoppel/"&B68 -> https://github.com/SF-Bancoppel/mx-api-bc-dom-credit-card | V68: Martha
A69: {=IFERROR( INDEX( 'api-register-id'!A:A, MATCH(F69, 'api-register-id'!B:B, 0) ), "Not found Organization" )} -> SSFF | B69: =IFERROR(VLOOKUP(F69, 'api-register-id'!B:F, 4, FALSE), "Not found path.") -> mx-api-bc-dom-credit-card | C69: RAML | D69: DOMAIN | E69: =IFERROR(VLOOKUP(F69, 'api-register-id'!B:F, 5, FALSE), "Not found path.") -> APIMX000012 | F69: Dom Credit Card | G69: RESMX000068 | H69: Dom_UpdateCreditCardActivationLogV1 | I69: =IFERROR(VLOOKUP(F69, 'api-register-id'!B:I, 8, FALSE), "Not found path.") -> 1.31.0 | J69: /cards/creditCard | K69: v1 | L69: PATCH | M69: /v1/creditCardActivationLog/update | N69: =CONCATENATE(L69," ",J69,M69) -> PATCH /cards/creditCard/v1/creditCardActivationLog/update | O69: Este servicio realiza de la consulta la información de tarjeta de crédito por número de tarjeta | Q69: Pending load documentation... | R69: Design | S69: ="https://github.com/SF-Bancoppel/"&B69 -> https://github.com/SF-Bancoppel/mx-api-bc-dom-credit-card | V69: Martha
A70: {=IFERROR( INDEX( 'api-register-id'!A:A, MATCH(F70, 'api-register-id'!B:B, 0) ), "Not found Organization" )} -> SSFF | B70: =IFERROR(VLOOKUP(F70, 'api-register-id'!B:F, 4, FALSE), "Not found path.") -> mx-api-bc-dom-credit-card | C70: RAML | D70: DOMAIN | E70: =IFERROR(VLOOKUP(F70, 'api-register-id'!B:F, 5, FALSE), "Not found path.") -> APIMX000012 | F70: Dom Credit Card | G70: RESMX000069 | H70: Dom_ControlPaymentCardV1 | I70: =IFERROR(VLOOKUP(F70, 'api-register-id'!B:I, 8, FALSE), "Not found path.") -> 1.31.0 | J70: /cards/creditCard | K70: v1 | L70: PUT | M70: /v1/paymentCard/control | N70: =CONCATENATE(L70," ",J70,M70) -> PUT /cards/creditCard/v1/paymentCard/control | O70: Permite validar si hay registros de la tarjeta en la tabla sd_tarjeta y eliminarlos. Es un rollback. | Q70: Pending load documentation... | R70: Design | S70: ="https://github.com/SF-Bancoppel/"&B70 -> https://github.com/SF-Bancoppel/mx-api-bc-dom-credit-card | V70: Martha
A71: {=IFERROR( INDEX( 'api-register-id'!A:A, MATCH(F71, 'api-register-id'!B:B, 0) ), "Not found Organization" )} -> SSFF | B71: =IFERROR(VLOOKUP(F71, 'api-register-id'!B:F, 4, FALSE), "Not found path.") -> mx-api-bc-dom-credit-card | C71: RAML | D71: DOMAIN | E71: =IFERROR(VLOOKUP(F71, 'api-register-id'!B:F, 5, FALSE), "Not found path.") -> APIMX000012 | F71: Dom Credit Card | G71: RESMX000070 | H71: Dom_RegisterPaymentCardV1 | I71: =IFERROR(VLOOKUP(F71, 'api-register-id'!B:I, 8, FALSE), "Not found path.") -> 1.31.0 | J71: /cards/creditCard | K71: v1 | L71: POST | M71: /v1/paymentCard/register | N71: =CONCATENATE(L71," ",J71,M71) -> POST /cards/creditCard/v1/paymentCard/register | O71: Este servicio realiza de la consulta la información de tarjeta de crédito por número de tarjeta | Q71: Pending load documentation... | R71: Design | S71: ="https://github.com/SF-Bancoppel/"&B71 -> https://github.com/SF-Bancoppel/mx-api-bc-dom-credit-card | V71: Martha
A72: {=IFERROR( INDEX( 'api-register-id'!A:A, MATCH(F72, 'api-register-id'!B:B, 0) ), "Not found Organization" )} -> SSFF | B72: =IFERROR(VLOOKUP(F72, 'api-register-id'!B:F, 4, FALSE), "Not found path.") -> mx-api-bc-dom-credit-card | C72: RAML | D72: DOMAIN | E72: =IFERROR(VLOOKUP(F72, 'api-register-id'!B:F, 5, FALSE), "Not found path.") -> APIMX000012 | F72: Dom Credit Card | G72: RESMX000071 | H72: Dom_EvaluateCreditCardApplicationV1 | I72: =IFERROR(VLOOKUP(F72, 'api-register-id'!B:I, 8, FALSE), "Not found path.") -> 1.31.0 | J72: /cards/creditCard | K72: v1 | L72: POST | M72: /v1/creditCardApplication/evaluate | N72: =CONCATENATE(L72," ",J72,M72) -> POST /cards/creditCard/v1/creditCardApplication/evaluate | O72: Permite realizar validaciones para verificar si el número de solicitud ingresado ya se encuentra en una tabla de asignaciones de tarjetas incompletas. | Q72: Pending load documentation... | R72: Design | S72: ="https://github.com/SF-Bancoppel/"&B72 -> https://github.com/SF-Bancoppel/mx-api-bc-dom-credit-card | V72: Martha
A73: {=IFERROR( INDEX( 'api-register-id'!A:A, MATCH(F73, 'api-register-id'!B:B, 0) ), "Not found Organization" )} -> SSFF | B73: =IFERROR(VLOOKUP(F73, 'api-register-id'!B:F, 4, FALSE), "Not found path.") -> mx-api-bc-dom-credit-card | C73: RAML | D73: DOMAIN | E73: =IFERROR(VLOOKUP(F73, 'api-register-id'!B:F, 5, FALSE), "Not found path.") -> APIMX000012 | F73: Dom Credit Card | G73: RESMX000072 | H73: Dom_EvaluateCreditCardFacilityV1 | I73: =IFERROR(VLOOKUP(F73, 'api-register-id'!B:I, 8, FALSE), "Not found path.") -> 1.31.0 | J73: /cards/creditCard | K73: v1 | L73: POST | M73: /v1/creditCardFacility/evaluate | N73: =CONCATENATE(L73," ",J73,M73) -> POST /cards/creditCard/v1/creditCardFacility/evaluate | O73: Operación encargada de obtenerla información necesaria para indicar el estado del crédito utilizado. | Q73: https://coppelmx.atlassian.net/wiki/x/O4ClPQ | R73: Design | S73: ="https://github.com/SF-Bancoppel/"&B73 -> https://github.com/SF-Bancoppel/mx-api-bc-dom-credit-card
A74: {=IFERROR( INDEX( 'api-register-id'!A:A, MATCH(F74, 'api-register-id'!B:B, 0) ), "Not found Organization" )} -> SSFF | B74: =IFERROR(VLOOKUP(F74, 'api-register-id'!B:F, 4, FALSE), "Not found path.") -> mx-api-bc-dom-credit-card | C74: RAML | D74: DOMAIN | E74: =IFERROR(VLOOKUP(F74, 'api-register-id'!B:F, 5, FALSE), "Not found path.") -> APIMX000012 | F74: Dom Credit Card | G74: RESMX000073 | H74: Dom_RetrieveCardTransactionV1 | I74: =IFERROR(VLOOKUP(F74, 'api-register-id'!B:I, 8, FALSE), "Not found path.") -> 1.31.0 | J74: /cards/creditCard | K74: v1 | L74: POST | M74: /v1/cardTransaction/retrieve | N74: =CONCATENATE(L74," ",J74,M74) -> POST /cards/creditCard/v1/cardTransaction/retrieve | O74: Esta Api realiza la consulta de las transacciones realizadas con la tarjeta de credito | Q74: https://coppelmx.atlassian.net/wiki/x/YQBUQg | R74: Design | S74: ="https://github.com/SF-Bancoppel/"&B74 -> https://github.com/SF-Bancoppel/mx-api-bc-dom-credit-card
A75: {=IFERROR( INDEX( 'api-register-id'!A:A, MATCH(F75, 'api-register-id'!B:B, 0) ), "Not found Organization" )} -> SSFF | B75: =IFERROR(VLOOKUP(F75, 'api-register-id'!B:F, 4, FALSE), "Not found path.") -> mx-api-bc-dom-credit-card | C75: RAML | D75: DOMAIN | E75: =IFERROR(VLOOKUP(F75, 'api-register-id'!B:F, 5, FALSE), "Not found path.") -> APIMX000012 | F75: Dom Credit Card | G75: RESMX000074 | H75: Dom_RetrieveCreditCardHolderV1 | I75: =IFERROR(VLOOKUP(F75, 'api-register-id'!B:I, 8, FALSE), "Not found path.") -> 1.31.0 | J75: /cards/creditCard | K75: v1 | L75: POST | M75: /v1/creditCardHolder/retrieve | N75: =CONCATENATE(L75," ",J75,M75) -> POST /cards/creditCard/v1/creditCardHolder/retrieve | O75: Esta Api realiza la consulta de los tarjetahabientes (titular, adicionales) | P75: Invalid Request Header "authorization" | Q75: https://coppelmx.atlassian.net/wiki/x/gYCpPQ | R75: Design | S75: ="https://github.com/SF-Bancoppel/"&B75 -> https://github.com/SF-Bancoppel/mx-api-bc-dom-credit-card
A76: {=IFERROR( INDEX( 'api-register-id'!A:A, MATCH(F76, 'api-register-id'!B:B, 0) ), "Not found Organization" )} -> SSFF | B76: =IFERROR(VLOOKUP(F76, 'api-register-id'!B:F, 4, FALSE), "Not found path.") -> mx-api-bc-dom-credit-card | C76: RAML | D76: DOMAIN | E76: =IFERROR(VLOOKUP(F76, 'api-register-id'!B:F, 5, FALSE), "Not found path.") -> APIMX000012 | F76: Dom Credit Card | G76: RESMX000075 | H76: Dom_ControlCreditCardFacilityV1 | I76: =IFERROR(VLOOKUP(F76, 'api-register-id'!B:I, 8, FALSE), "Not found path.") -> 1.31.0 | J76: /cards/creditCard | K76: v1 | L76: PUT | M76: /v1/creditCardFacility/control | N76: =CONCATENATE(L76," ",J76,M76) -> PUT /cards/creditCard/v1/creditCardFacility/control | O76: Actualiza el estatus de la tarjeta de credito | Q76: Pending load documentation... | R76: Design | S76: ="https://github.com/SF-Bancoppel/"&B76 -> https://github.com/SF-Bancoppel/mx-api-bc-dom-credit-card
A77: {=IFERROR( INDEX( 'api-register-id'!A:A, MATCH(F77, 'api-register-id'!B:B, 0) ), "Not found Organization" )} -> SSFF | B77: =IFERROR(VLOOKUP(F77, 'api-register-id'!B:F, 4, FALSE), "Not found path.") -> mx-api-bc-dom-credit-card | C77: RAML | D77: DOMAIN | E77: =IFERROR(VLOOKUP(F77, 'api-register-id'!B:F, 5, FALSE), "Not found path.") -> APIMX000012 | F77: Dom Credit Card | G77: RESMX000076 | H77: Dom_RetrieveCreditCardPositionV1 | I77: =IFERROR(VLOOKUP(F77, 'api-register-id'!B:I, 8, FALSE), "Not found path.") -> 1.31.0 | J77: /cards/creditCard | K77: v1 | L77: POST | M77: /v1/creditCardPosition/retrieve | N77: =CONCATENATE(L77," ",J77,M77) -> POST /cards/creditCard/v1/creditCardPosition/retrieve | O77: En esta Api se realiza una consulta para obtener los movimientos detallados del crédito (cuenta de crédito Bancoppel) que se está consultando. | Q77: https://coppelmx.atlassian.net/wiki/x/C4DSPQ | R77: Design | S77: ="https://github.com/SF-Bancoppel/"&B77 -> https://github.com/SF-Bancoppel/mx-api-bc-dom-credit-card
A78: {=IFERROR( INDEX( 'api-register-id'!A:A, MATCH(F78, 'api-register-id'!B:B, 0) ), "Not found Organization" )} -> SSFF | B78: =IFERROR(VLOOKUP(F78, 'api-register-id'!B:F, 4, FALSE), "Not found path.") -> mx-api-bc-dom-credit-card | C78: RAML | D78: DOMAIN | E78: =IFERROR(VLOOKUP(F78, 'api-register-id'!B:F, 5, FALSE), "Not found path.") -> APIMX000012 | F78: Dom Credit Card | G78: RESMX000077 | H78: Dom_EvaluatePaymentCardV1 | I78: =IFERROR(VLOOKUP(F78, 'api-register-id'!B:I, 8, FALSE), "Not found path.") -> 1.31.0 | J78: /cards/creditCard | K78: v1 | L78: POST | M78: /v1/paymentCard/evaluate | N78: =CONCATENATE(L78," ",J78,M78) -> POST /cards/creditCard/v1/paymentCard/evaluate | O78: Este servicio realiza la consulta a un servicio externo (Interact). Está consulta se realiza para verificar que la tarjeta a cancelar no se encuentre en estatus de robo/extravío, para continuar con su cancelación de manera correcta. | Q78: Pending load documentation... | R78: Design | S78: ="https://github.com/SF-Bancoppel/"&B78 -> https://github.com/SF-Bancoppel/mx-api-bc-dom-credit-card
A79: {=IFERROR( INDEX( 'api-register-id'!A:A, MATCH(F79, 'api-register-id'!B:B, 0) ), "Not found Organization" )} -> SSFF | B79: =IFERROR(VLOOKUP(F79, 'api-register-id'!B:F, 4, FALSE), "Not found path.") -> mx-api-bc-dom-credit-card | C79: RAML | D79: DOMAIN | E79: =IFERROR(VLOOKUP(F79, 'api-register-id'!B:F, 5, FALSE), "Not found path.") -> APIMX000012 | F79: Dom Credit Card | G79: RESMX000078 | H79: Dom_UpdatePaymentCardV1 | I79: =IFERROR(VLOOKUP(F79, 'api-register-id'!B:I, 8, FALSE), "Not found path.") -> 1.31.0 | J79: /cards/creditCard | K79: v1 | L79: PATCH | M79: /v1/paymentCard/update | N79: =CONCATENATE(L79," ",J79,M79) -> PATCH /cards/creditCard/v1/paymentCard/update | O79: En este microservicio se realiza la actualización del status de la tarjeta de crédito (activar o desactivar tarjeta). | P79: Invalid Request Header "authorization" | Q79: https://coppelmx.atlassian.net/wiki/x/IoDYPQ | R79: Design | S79: ="https://github.com/SF-Bancoppel/"&B79 -> https://github.com/SF-Bancoppel/mx-api-bc-dom-credit-card
A80: {=IFERROR( INDEX( 'api-register-id'!A:A, MATCH(F80, 'api-register-id'!B:B, 0) ), "Not found Organization" )} -> SSFF | B80: =IFERROR(VLOOKUP(F80, 'api-register-id'!B:F, 4, FALSE), "Not found path.") -> mx-api-bc-dom-credit-card | C80: RAML | D80: DOMAIN | E80: =IFERROR(VLOOKUP(F80, 'api-register-id'!B:F, 5, FALSE), "Not found path.") -> APIMX000012 | F80: Dom Credit Card | G80: RESMX000079 | H80: Dom_RetrievePositionLimitV1 | I80: =IFERROR(VLOOKUP(F80, 'api-register-id'!B:I, 8, FALSE), "Not found path.") -> 1.31.0 | J80: /cards/creditCard | K80: v1 | L80: POST | M80: /v1/positionLimit/retrieve | N80: =CONCATENATE(L80," ",J80,M80) -> POST /cards/creditCard/v1/positionLimit/retrieve | O80: En este microservicio retorna las cuentas y los límites asociados a un usuario. | Q80: Pending load documentation... | R80: Design | S80: ="https://github.com/SF-Bancoppel/"&B80 -> https://github.com/SF-Bancoppel/mx-api-bc-dom-credit-card
A81: {=IFERROR( INDEX( 'api-register-id'!A:A, MATCH(F81, 'api-register-id'!B:B, 0) ), "Not found Organization" )} -> SSFF | B81: =IFERROR(VLOOKUP(F81, 'api-register-id'!B:F, 4, FALSE), "Not found path.") -> mx-api-bc-dom-credit-card | C81: RAML | D81: DOMAIN | E81: =IFERROR(VLOOKUP(F81, 'api-register-id'!B:F, 5, FALSE), "Not found path.") -> APIMX000012 | F81: Dom Credit Card | G81: RESMX000080 | H81: Dom_RetrieveSpecialCreditCardConditionsV1 | I81: =IFERROR(VLOOKUP(F81, 'api-register-id'!B:I, 8, FALSE), "Not found path.") -> 1.31.0 | J81: /cards/creditCard | K81: v1 | L81: POST | M81: /v1/specialCreditCardConditions/retrieve | N81: =CONCATENATE(L81," ",J81,M81) -> POST /cards/creditCard/v1/specialCreditCardConditions/retrieve | O81: Esta Api realiza la consulta de los cualquier situacion especial de la tarjetas de credito | Q81: Pending load documentation... | R81: Design | S81: ="https://github.com/SF-Bancoppel/"&B81 -> https://github.com/SF-Bancoppel/mx-api-bc-dom-credit-card
A82: {=IFERROR( INDEX( 'api-register-id'!A:A, MATCH(F82, 'api-register-id'!B:B, 0) ), "Not found Organization" )} -> SSFF | B82: =IFERROR(VLOOKUP(F82, 'api-register-id'!B:F, 4, FALSE), "Not found path.") -> mx-api-bc-dom-credit-card | C82: RAML | D82: DOMAIN | E82: =IFERROR(VLOOKUP(F82, 'api-register-id'!B:F, 5, FALSE), "Not found path.") -> APIMX000012 | F82: Dom Credit Card | G82: RESMX000081 | H82: Dom_RetrievePaymentCardTypeV1 | I82: =IFERROR(VLOOKUP(F82, 'api-register-id'!B:I, 8, FALSE), "Not found path.") -> 1.31.0 | J82: /cards/creditCard | K82: v1 | L82: POST | M82: /v1/paymentCardType/retrieve | N82: =CONCATENATE(L82," ",J82,M82) -> POST /cards/creditCard/v1/paymentCardType/retrieve | O82: Esta Api realiza la consulta de los catalogos de los tipos de tarjeta | Q82: Pending load documentation... | R82: Design | S82: ="https://github.com/SF-Bancoppel/"&B82 -> https://github.com/SF-Bancoppel/mx-api-bc-dom-credit-card
A83: {=IFERROR( INDEX( 'api-register-id'!A:A, MATCH(F83, 'api-register-id'!B:B, 0) ), "Not found Organization" )} -> SSFF | B83: =IFERROR(VLOOKUP(F83, 'api-register-id'!B:F, 4, FALSE), "Not found path.") -> mx-api-bc-dom-credit-card | C83: RAML | D83: DOMAIN | E83: =IFERROR(VLOOKUP(F83, 'api-register-id'!B:F, 5, FALSE), "Not found path.") -> APIMX000012 | F83: Dom Credit Card | G83: RESMX000082 | H83: Dom_RetrieveRefundV1 | I83: =IFERROR(VLOOKUP(F83, 'api-register-id'!B:I, 8, FALSE), "Not found path.") -> 1.31.0 | J83: /cards/creditCard | K83: v1 | L83: POST | M83: /v1/refund/retrieve | N83: =CONCATENATE(L83," ",J83,M83) -> POST /cards/creditCard/v1/refund/retrieve | O83: En este microservicio se realiza para validar si existe el crédito en la tabla sd_indicador_cred. Está consulta se realiza para validar si existe el crédito. | Q83: https://coppelmx.atlassian.net/wiki/x/AgDpPQ | R83: Design | S83: ="https://github.com/SF-Bancoppel/"&B83 -> https://github.com/SF-Bancoppel/mx-api-bc-dom-credit-card
A84: {=IFERROR( INDEX( 'api-register-id'!A:A, MATCH(F84, 'api-register-id'!B:B, 0) ), "Not found Organization" )} -> SSFF | B84: =IFERROR(VLOOKUP(F84, 'api-register-id'!B:F, 4, FALSE), "Not found path.") -> mx-api-bc-dom-credit-card | C84: RAML | D84: DOMAIN | E84: =IFERROR(VLOOKUP(F84, 'api-register-id'!B:F, 5, FALSE), "Not found path.") -> APIMX000012 | F84: Dom Credit Card | G84: RESMX000083 | H84: Dom_ControlTraceAssignmentV1 | I84: =IFERROR(VLOOKUP(F84, 'api-register-id'!B:I, 8, FALSE), "Not found path.") -> 1.31.0 | J84: /cards/creditCard | K84: v1 | L84: PUT | M84: /v1/traceAssignment/control | N84: =CONCATENATE(L84," ",J84,M84) -> PUT /cards/creditCard/v1/traceAssignment/control | O84: Elimina los registros de la tabla bitacoracambiosstatustarjeta y bitacoracambiostarjeta | Q84: Pending load documentation... | R84: Design | S84: ="https://github.com/SF-Bancoppel/"&B84 -> https://github.com/SF-Bancoppel/mx-api-bc-dom-credit-card
A85: {=IFERROR( INDEX( 'api-register-id'!A:A, MATCH(F85, 'api-register-id'!B:B, 0) ), "Not found Organization" )} -> SSFF | B85: =IFERROR(VLOOKUP(F85, 'api-register-id'!B:F, 4, FALSE), "Not found path.") -> mx-api-bc-dom-credit-card | C85: RAML | D85: DOMAIN | E85: =IFERROR(VLOOKUP(F85, 'api-register-id'!B:F, 5, FALSE), "Not found path.") -> APIMX000012 | F85: Dom Credit Card | G85: RESMX000084 | H85: Dom_InitiatePaymentCardV1 | I85: =IFERROR(VLOOKUP(F85, 'api-register-id'!B:I, 8, FALSE), "Not found path.") -> 1.31.0 | J85: /cards/creditCard | K85: v1 | L85: POST | M85: /v1/paymentCard/initiate | N85: =CONCATENATE(L85," ",J85,M85) -> POST /cards/creditCard/v1/paymentCard/initiate | O85: Este microservicio se utiliza para asignar una tarjeta de crédito | Q85: Pending load documentation... | R85: Design | S85: ="https://github.com/SF-Bancoppel/"&B85 -> https://github.com/SF-Bancoppel/mx-api-bc-dom-credit-card
A86: {=IFERROR( INDEX( 'api-register-id'!A:A, MATCH(F86, 'api-register-id'!B:B, 0) ), "Not found Organization" )} -> SSFF | B86: =IFERROR(VLOOKUP(F86, 'api-register-id'!B:F, 4, FALSE), "Not found path.") -> mx-api-bc-dom-credit-card | C86: RAML | D86: DOMAIN | E86: =IFERROR(VLOOKUP(F86, 'api-register-id'!B:F, 5, FALSE), "Not found path.") -> APIMX000012 | F86: Dom Credit Card | G86: RESMX000085 | H86: Dom_RetrieveFeesV1 | I86: =IFERROR(VLOOKUP(F86, 'api-register-id'!B:I, 8, FALSE), "Not found path.") -> 1.31.0 | J86: /cards/creditCard | K86: v1 | L86: POST | M86: /v1/fees/retrieve | N86: =CONCATENATE(L86," ",J86,M86) -> POST /cards/creditCard/v1/fees/retrieve | O86: Se obtiene información de montos, saldos e Iva. En la primer consulta de obtiene el Iva(Impuesto al valor agregado), en la segunda consulta de obtiene monto comision suma todas las cantidades que se encuentran en el campo monto_com(si existen uno o más registros con los filtros indicados suma las cantidades que existen en el campo monto_com) | Q86: Pending load documentation... | R86: Design | S86: ="https://github.com/SF-Bancoppel/"&B86 -> https://github.com/SF-Bancoppel/mx-api-bc-dom-credit-card
A87: {=IFERROR( INDEX( 'api-register-id'!A:A, MATCH(F87, 'api-register-id'!B:B, 0) ), "Not found Organization" )} -> SSFF | B87: =IFERROR(VLOOKUP(F87, 'api-register-id'!B:F, 4, FALSE), "Not found path.") -> mx-api-bc-dom-credit-card | C87: RAML | D87: DOMAIN | E87: =IFERROR(VLOOKUP(F87, 'api-register-id'!B:F, 5, FALSE), "Not found path.") -> APIMX000012 | F87: Dom Credit Card | G87: RESMX000086 | H87: Dom_RetrieveCashAdvanceOfferV1 | I87: =IFERROR(VLOOKUP(F87, 'api-register-id'!B:I, 8, FALSE), "Not found path.") -> 1.31.0 | J87: /cards/creditCard | K87: v1 | L87: POST | M87: /v1/cashAdvanceOffer/retrieve | N87: =CONCATENATE(L87," ",J87,M87) -> POST /cards/creditCard/v1/cashAdvanceOffer/retrieve | O87: API encargado obtener el saldo del préstamo, calculando monto, interés, interese moratorios, iva, iva moratorio entro otros cargos que puedan cargarse al cliente, así como mostrar el crédito que cuenta libre o a apagar segun sea la cuenta del cliente. | Q87: Pending load documentation... | R87: Design | S87: ="https://github.com/SF-Bancoppel/"&B87 -> https://github.com/SF-Bancoppel/mx-api-bc-dom-credit-card
A88: {=IFERROR( INDEX( 'api-register-id'!A:A, MATCH(F88, 'api-register-id'!B:B, 0) ), "Not found Organization" )} -> SSFF | B88: =IFERROR(VLOOKUP(F88, 'api-register-id'!B:F, 4, FALSE), "Not found path.") -> mx-api-bc-dom-credit-card | C88: RAML | D88: DOMAIN | E88: =IFERROR(VLOOKUP(F88, 'api-register-id'!B:F, 5, FALSE), "Not found path.") -> APIMX000012 | F88: Dom Credit Card | G88: RESMX000087 | H88: Dom_UpdateCreditCardFacilityV1 | I88: =IFERROR(VLOOKUP(F88, 'api-register-id'!B:I, 8, FALSE), "Not found path.") -> 1.31.0 | J88: /cards/creditCard | K88: v1 | L88: PATCH | M88: /v1/creditCardFacility/update | N88: =CONCATENATE(L88," ",J88,M88) -> PATCH /cards/creditCard/v1/creditCardFacility/update | O88: En este microservicio se encarga de realizar los bloqueos de tarjetas en BPC. | Q88: Pending load documentation... | R88: Design | S88: ="https://github.com/SF-Bancoppel/"&B88 -> https://github.com/SF-Bancoppel/mx-api-bc-dom-credit-card
A89: {=IFERROR( INDEX( 'api-register-id'!A:A, MATCH(F89, 'api-register-id'!B:B, 0) ), "Not found Organization" )} -> SSFF | B89: =IFERROR(VLOOKUP(F89, 'api-register-id'!B:F, 4, FALSE), "Not found path.") -> mx-api-bc-dom-credit-card | C89: RAML | D89: DOMAIN | E89: =IFERROR(VLOOKUP(F89, 'api-register-id'!B:F, 5, FALSE), "Not found path.") -> APIMX000012 | F89: Dom Credit Card | G89: RESMX000088 | H89: Dom_ControlCashAdvanceOfferV1 | I89: =IFERROR(VLOOKUP(F89, 'api-register-id'!B:I, 8, FALSE), "Not found path.") -> 1.31.0 | J89: /cards/creditCard | K89: v1 | L89: PATCH | M89: /v1/cashAdvanceOffer/control | N89: =CONCATENATE(L89," ",J89,M89) -> PATCH /cards/creditCard/v1/cashAdvanceOffer/control | O89: Realiza actualización a la tabla sd_promocion_credito de la base de datos Bdicred. La actualización se realiza en el campo status. utilizando como filtro numero de credito y folio de la promoción. | Q89: Pending load documentation... | R89: Design | S89: ="https://github.com/SF-Bancoppel/"&B89 -> https://github.com/SF-Bancoppel/mx-api-bc-dom-credit-card
A90: {=IFERROR( INDEX( 'api-register-id'!A:A, MATCH(F90, 'api-register-id'!B:B, 0) ), "Not found Organization" )} -> SSFF | B90: =IFERROR(VLOOKUP(F90, 'api-register-id'!B:F, 4, FALSE), "Not found path.") -> mx-api-bc-dom-credit-card | C90: RAML | D90: DOMAIN | E90: =IFERROR(VLOOKUP(F90, 'api-register-id'!B:F, 5, FALSE), "Not found path.") -> APIMX000012 | F90: Dom Credit Card | G90: RESMX000089 | H90: Dom_UpdateCashAdvanceBalanceV1 | I90: =IFERROR(VLOOKUP(F90, 'api-register-id'!B:I, 8, FALSE), "Not found path.") -> 1.31.0 | J90: /cards/creditCard | K90: v1 | L90: PATCH | M90: /v1/cashAdvanceBalance/update | N90: =CONCATENATE(L90," ",J90,M90) -> PATCH /cards/creditCard/v1/cashAdvanceBalance/update | O90: Realiza actualización del saldo retenido en dado un solicitud de CREDISOLUCIONES | Q90: Pending load documentation... | R90: Design | S90: ="https://github.com/SF-Bancoppel/"&B90 -> https://github.com/SF-Bancoppel/mx-api-bc-dom-credit-card
A91: {=IFERROR( INDEX( 'api-register-id'!A:A, MATCH(F91, 'api-register-id'!B:B, 0) ), "Not found Organization" )} -> SSFF | B91: =IFERROR(VLOOKUP(F91, 'api-register-id'!B:F, 4, FALSE), "Not found path.") -> mx-api-bc-dom-credit-card-position-keeping | C91: RAML | D91: DOMAIN | E91: =IFERROR(VLOOKUP(F91, 'api-register-id'!B:F, 5, FALSE), "Not found path.") -> APIMX000013 | F91: Dom Credit Card Position Keeping | G91: RESMX000090 | H91: Dom_RegisterCardTransactionEventV1 | I91: =IFERROR(VLOOKUP(F91, 'api-register-id'!B:I, 8, FALSE), "Not found path.") -> 1.4.3 | J91: /cards/creditCardPositionKeeping | K91: v1 | L91: POST | M91: /v1/cardTransactionEvent/register | N91: =CONCATENATE(L91," ",J91,M91) -> POST /cards/creditCardPositionKeeping/v1/cardTransactionEvent/register | O91: Operación encargada de guardar en bitácora los pagos realizados de un cliente. | Q91: Pending load documentation... | R91: Design | S91: ="https://github.com/SF-Bancoppel/"&B91 -> https://github.com/SF-Bancoppel/mx-api-bc-dom-credit-card-position-keeping
... A93: {=IFERROR( INDEX( 'api-register-id'!A:A, MATCH(F93, 'api-register-id'!B:B, 0) ), "Not found Organization" )} -> SSFF | B93: =IFERROR(VLOOKUP(F93, 'api-register-id'!B:F, 4, FALSE), "Not found path.") -> mx-api-bc-dom-credit-card-position-keeping | C93: RAML | D93: DOMAIN | E93: =IFERROR(VLOOKUP(F93, 'api-register-id'!B:F, 5, FALSE), "Not found path.") -> APIMX000013 | F93: Dom Credit Card Position Keeping | G93: RESMX000092 | H93: Dom_RetrieveCreditCardAssessmentV1 | I93: =IFERROR(VLOOKUP(F93, 'api-register-id'!B:I, 8, FALSE), "Not found path.") -> 1.4.3 | J93: /cards/creditCardPositionKeeping | K93: v1 | L93: POST | M93: /v1/creditCardAssessment/retrieve | N93: =CONCATENATE(L93," ",J93,M93) -> POST /cards/creditCardPositionKeeping/v1/creditCardAssessment/retrieve | O93: API encargado de obtenner el saldo de un corte teniendo como entrada el número asociado a una cuenta y el tipo de consulta. | Q93: Pending load documentation... | R93: Design | S93: ="https://github.com/SF-Bancoppel/"&B93 -> https://github.com/SF-Bancoppel/mx-api-bc-dom-credit-card-position-keeping
A94: {=IFERROR( INDEX( 'api-register-id'!A:A, MATCH(F94, 'api-register-id'!B:B, 0) ), "Not found Organization" )} -> SSFF | B94: =IFERROR(VLOOKUP(F94, 'api-register-id'!B:F, 4, FALSE), "Not found path.") -> mx-api-bc-dom-credit-card-position-keeping | C94: RAML | D94: DOMAIN | E94: =IFERROR(VLOOKUP(F94, 'api-register-id'!B:F, 5, FALSE), "Not found path.") -> APIMX000013 | F94: Dom Credit Card Position Keeping | G94: RESMX000093 | H94: Dom_RetrieveCreditCardStatementV1 | I94: =IFERROR(VLOOKUP(F94, 'api-register-id'!B:I, 8, FALSE), "Not found path.") -> 1.4.3 | J94: /cards/creditCardPositionKeeping | K94: v1 | L94: POST | M94: /v1/creditCardStatement/retrieve | N94: =CONCATENATE(L94," ",J94,M94) -> POST /cards/creditCardPositionKeeping/v1/creditCardStatement/retrieve | O94: En esta Api se realiza una consulta de datos de las cuentas de una tarjeta de crédito y el extracto de la tarjeta. | P94: Invalid Request Header "authorization" | Q94: https://coppelmx.atlassian.net/wiki/x/mIBsPQ | R94: Design | S94: ="https://github.com/SF-Bancoppel/"&B94 -> https://github.com/SF-Bancoppel/mx-api-bc-dom-credit-card-position-keeping
A95: {=IFERROR( INDEX( 'api-register-id'!A:A, MATCH(F95, 'api-register-id'!B:B, 0) ), "Not found Organization" )} -> SSFF | B95: =IFERROR(VLOOKUP(F95, 'api-register-id'!B:F, 4, FALSE), "Not found path.") -> mx-api-bc-dom-credit-card-position-keeping | C95: RAML | D95: DOMAIN | E95: =IFERROR(VLOOKUP(F95, 'api-register-id'!B:F, 5, FALSE), "Not found path.") -> APIMX000013 | F95: Dom Credit Card Position Keeping | G95: RESMX000094 | H95: Dom_RetrieveCreditCardHolderV1 | I95: =IFERROR(VLOOKUP(F95, 'api-register-id'!B:I, 8, FALSE), "Not found path.") -> 1.4.3 | J95: /cards/creditCardPositionKeeping | K95: v1 | L95: POST | M95: /v1/creditCardHolder/retrieve | N95: =CONCATENATE(L95," ",J95,M95) -> POST /cards/creditCardPositionKeeping/v1/creditCardHolder/retrieve | O95: En esta Api se realiza una consulta para obtener los movimientos detallados del crédito (cuenta de crédito Bancoppel) que se está consultando. | P95: Invalid Request Header "authorization" | Q95: https://coppelmx.atlassian.net/wiki/x/J4BrPQ | R95: Design | S95: ="https://github.com/SF-Bancoppel/"&B95 -> https://github.com/SF-Bancoppel/mx-api-bc-dom-credit-card-position-keeping
A96: {=IFERROR( INDEX( 'api-register-id'!A:A, MATCH(F96, 'api-register-id'!B:B, 0) ), "Not found Organization" )} -> SSFF | B96: =IFERROR(VLOOKUP(F96, 'api-register-id'!B:F, 4, FALSE), "Not found path.") -> mx-api-bc-dom-credit-facility | C96: RAML | D96: DOMAIN | E96: =IFERROR(VLOOKUP(F96, 'api-register-id'!B:F, 5, FALSE), "Not found path.") -> APIMX000014 | F96: Dom Credit Facility | G96: RESMX000095 | H96: Dom_UpdateCreditLineFacilityV1 | I96: =IFERROR(VLOOKUP(F96, 'api-register-id'!B:I, 8, FALSE), "Not found path.") -> 1.2.1 | J96: /corporateBanking/creditFacility | K96: v1 | L96: PATCH | M96: /v1/creditLineFacility/update | N96: =CONCATENATE(L96," ",J96,M96) -> PATCH /corporateBanking/creditFacility/v1/creditLineFacility/update | O96: Servicio que actualiza el incremento o cancelación de la línea de crédito asociada a una solicitud en específico. Por Ejemplo (TARJETA DE CREDITO BANCOPPEL VISA , TARJETA DE CREDITO BANCOPPEL VISA , TARJETA DE CREDITO COPPEL, TARJETA DE CREDITO BASICA BANCOPPEL, CUENTA DE CREDITO PLATINO, etc) | P96: Invalid business domain value "corporateBanking", in the path "/corporateBanking/creditFacility".\nFor the service domain "creditFacility" in the path "/corporateBanking/creditFacility" use the business domain "Trade Banking". | Q96: Pending load documentation... | R96: Design | S96: ="https://github.com/SF-Bancoppel/"&B96 -> https://github.com/SF-Bancoppel/mx-api-bc-dom-credit-facility
A97: {=IFERROR( INDEX( 'api-register-id'!A:A, MATCH(F97, 'api-register-id'!B:B, 0) ), "Not found Organization" )} -> SSFF | B97: =IFERROR(VLOOKUP(F97, 'api-register-id'!B:F, 4, FALSE), "Not found path.") -> mx-api-bc-dom-currency-exchange | C97: RAML | D97: DOMAIN | E97: =IFERROR(VLOOKUP(F97, 'api-register-id'!B:F, 5, FALSE), "Not found path.") -> APIMX000015 | F97: Dom Currency Exchange | G97: RESMX000096 | H97: Dom_RetrieveCurrencyExchangeTransactionV1 | I97: =IFERROR(VLOOKUP(F97, 'api-register-id'!B:I, 8, FALSE), "Not found path.") -> 1.0.0 | J97: /consumerServices/currencyExchange | K97: v1 | L97: POST | M97: /v1/currencyExchangeTransaction/retrieve | N97: =CONCATENATE(L97," ",J97,M97) -> POST /consumerServices/currencyExchange/v1/currencyExchangeTransaction/retrieve | O97: Este servicio realiza la consulta de una tasa de cambio | Q97: Pending load documentation... | R97: Design | S97: ="https://github.com/SF-Bancoppel/"&B97 -> https://github.com/SF-Bancoppel/mx-api-bc-dom-currency-exchange
A98: {=IFERROR( INDEX( 'api-register-id'!A:A, MATCH(F98, 'api-register-id'!B:B, 0) ), "Not found Organization" )} -> SSFF | B98: =IFERROR(VLOOKUP(F98, 'api-register-id'!B:F, 4, FALSE), "Not found path.") -> mx-api-bc-dom-current-account | C98: RAML | D98: DOMAIN | E98: =IFERROR(VLOOKUP(F98, 'api-register-id'!B:F, 5, FALSE), "Not found path.") -> APIMX000016 | F98: Dom Current Account | G98: RESMX000097 | H98: Dom_RetrieveCurrentAccountFacilityV1 | I98: =IFERROR(VLOOKUP(F98, 'api-register-id'!B:I, 8, FALSE), "Not found path.") -> 1.0.0 | J98: /loansAndDeposits/currentAccount | K98: v1 | L98: POST | M98: /v1/currentAccountFacility/retrieve | N98: =CONCATENATE(L98," ",J98,M98) -> POST /loansAndDeposits/currentAccount/v1/currentAccountFacility/retrieve | O98: Este servicio realiza la consulta de una cuenta corriente (cuenta nomina) | Q98: Pending load documentation... | R98: Design | S98: ="https://github.com/SF-Bancoppel/"&B98 -> https://github.com/SF-Bancoppel/mx-api-bc-dom-current-account
A99: {=IFERROR( INDEX( 'api-register-id'!A:A, MATCH(F99, 'api-register-id'!B:B, 0) ), "Not found Organization" )} -> SSFF | B99: =IFERROR(VLOOKUP(F99, 'api-register-id'!B:F, 4, FALSE), "Not found path.") -> mx-api-bc-dom-customer-access-entitlement | C99: RAML | D99: DOMAIN | E99: =IFERROR(VLOOKUP(F99, 'api-register-id'!B:F, 5, FALSE), "Not found path.") -> APIMX000017 | F99: Dom Customer Access Entitlement | G99: RESMX000098 | H99: Dom_RetrieveRestrictionsV1 | I99: =IFERROR(VLOOKUP(F99, 'api-register-id'!B:I, 8, FALSE), "Not found path.") -> 1.1.1 | J99: /customerManagement/customerAccessEntitlement | K99: v1 | L99: POST | M99: /v1/restrictions/retrieve | N99: =CONCATENATE(L99," ",J99,M99) -> POST /customerManagement/customerAccessEntitlement/v1/restrictions/retrieve | O99: Servicio de dominio que consultará los intentos por actividad | Q99: Pending load documentation... | R99: Design | S99: ="https://github.com/SF-Bancoppel/"&B99 -> https://github.com/SF-Bancoppel/mx-api-bc-dom-customer-access-entitlement
A100: {=IFERROR( INDEX( 'api-register-id'!A:A, MATCH(F100, 'api-register-id'!B:B, 0) ), "Not found Organization" )} -> SSFF | B100: =IFERROR(VLOOKUP(F100, 'api-register-id'!B:F, 4, FALSE), "Not found path.") -> mx-api-bc-dom-customer-agreement | C100: RAML | D100: DOMAIN | E100: =IFERROR(VLOOKUP(F100, 'api-register-id'!B:F, 5, FALSE), "Not found path.") -> APIMX000018 | F100: Dom Customer Agreement | G100: RESMX000099 | H100: Dom_EvaluateLegalTermsV1 | I100: =IFERROR(VLOOKUP(F100, 'api-register-id'!B:I, 8, FALSE), "Not found path.") -> 1.3.0 | K100: v1 | L100: POST | M100: /v1/legalTerms/evaluate | N100: =CONCATENATE(L100," ",J100,M100) -> POST /v1/legalTerms/evaluate | O100: Servicio de dominio encargado de consultar los términos legales | Q100: https://coppelmx.atlassian.net/wiki/x/EwDyPQ | R100: Design | S100: ="https://github.com/SF-Bancoppel/"&B100 -> https://github.com/SF-Bancoppel/mx-api-bc-dom-customer-agreement
A101: {=IFERROR( INDEX( 'api-register-id'!A:A, MATCH(F101, 'api-register-id'!B:B, 0) ), "Not found Organization" )} -> SSFF | B101: =IFERROR(VLOOKUP(F101, 'api-register-id'!B:F, 4, FALSE), "Not found path.") -> mx-api-bc-dom-customer-agreement | C101: RAML | D101: DOMAIN | E101: =IFERROR(VLOOKUP(F101, 'api-register-id'!B:F, 5, FALSE), "Not found path.") -> APIMX000018 | F101: Dom Customer Agreement | G101: RESMX000100 | H101: Dom_EvaluateCustomerAgreementV1 | I101: =IFERROR(VLOOKUP(F101, 'api-register-id'!B:I, 8, FALSE), "Not found path.") -> 1.3.0 | J101: /customerManagement/customerAgreement | K101: v1 | L101: POST | M101: /v1/customerAgreement/evaluate | N101: =CONCATENATE(L101," ",J101,M101) -> POST /customerManagement/customerAgreement/v1/customerAgreement/evaluate | O101: Servicio de dominio encargado de consultar el acuerdo con el cliente | Q101: https://coppelmx.atlassian.net/wiki/x/QID1PQ | R101: Design | S101: ="https://github.com/SF-Bancoppel/"&B101 -> https://github.com/SF-Bancoppel/mx-api-bc-dom-customer-agreement
...

Sheet api-register-id
A1: Organization | B1: API Name | C1: API Operations | D1: API Type | E1: API Repository Name | F1: ID API | G1: Exchange Name | H1: Exchange Publish | I1: Exchange Publish Version | J1: MS Repository Name | K1: Deploy Type | L1: Deploy Name | M1: Deploy Name Target | N1: is Valid | O1: Longitud | P1: Deploy Publish | Q1: Deploy Version
A2: SSFF | B2: Bus Business Support | C2: =COUNTIF(develop!F2:F980,B2) -> 6 | D2: BUSINESS | E2: mx-api-bc-bus-business-support | F2: APIMX000001 | G2: =E2 -> mx-api-bc-bus-business-support | H2: =CONCATENATE("https://anypoint.mulesoft.com/exchange/834f46f4-ef08-4c50-81ae-56f917b413cc/", G2) -> https://anypoint.mulesoft.com/exchange/834f46f4-ef08-4c50-81ae-56f917b413cc/mx-api-bc-bus-business-support | I2: 1.3.0 | J2: =obtenerRepoMS(E2) -> mx-ms-bc-bus-business-support-mule | K2: MuleSoft | L2: =IFERROR(__xludf.DUMMYFUNCTION("REGEXREPLACE(REGEXREPLACE(REGEXREPLACE(J2, ""mx-ms-bc-"", """"), ""-mule"", ""-api-dev""), ""-apigee"", ""-api-dev"")"),"bus-business-support-api-dev") -> bus-business-support-api-dev | M2: =generarNombreDeploy(J2) -> bus-business-support-api-dev | N2: =validateAPIName(M2,D2) -> Valid | O2: =LEN(M2) -> 28
A3: SSFF | B3: Bus Operations and Execution | C3: =COUNTIF(develop!F3:F980,B3) -> 32 | D3: BUSINESS | E3: mx-api-bc-bus-operations-and-execution | F3: APIMX000002 | G3: =E3 -> mx-api-bc-bus-operations-and-execution | H3: =CONCATENATE("https://anypoint.mulesoft.com/exchange/834f46f4-ef08-4c50-81ae-56f917b413cc/", G3) -> https://anypoint.mulesoft.com/exchange/834f46f4-ef08-4c50-81ae-56f917b413cc/mx-api-bc-bus-operations-and-execution | I3: 1.16.1 | J3: =obtenerRepoMS(E3) -> mx-ms-bc-bus-operations-and-execution-mule | K3: MuleSoft | L3: =IFERROR(__xludf.DUMMYFUNCTION("REGEXREPLACE(REGEXREPLACE(REGEXREPLACE(J3, ""mx-ms-bc-"", """"), ""-mule"", ""-api-dev""), ""-apigee"", ""-api-dev"")"),"bus-operations-and-execution-api-dev") -> bus-operations-and-execution-api-dev | M3: =generarNombreDeploy(J3) -> bus-operations-and-execution-api-dev | N3: =validateAPIName(M3,D3) -> Valid | O3: =LEN(M3) -> 36
A4: SSFF | B4: Bus Reference Data | C4: =COUNTIF(develop!F4:F980,B4) -> 14 | D4: BUSINESS | E4: mx-api-bc-bus-reference-data | F4: APIMX000003 | G4: =E4 -> mx-api-bc-bus-reference-data | H4: =CONCATENATE("https://anypoint.mulesoft.com/exchange/834f46f4-ef08-4c50-81ae-56f917b413cc/", G4) -> https://anypoint.mulesoft.com/exchange/834f46f4-ef08-4c50-81ae-56f917b413cc/mx-api-bc-bus-reference-data | I4: 1.7.0 | J4: =obtenerRepoMS(E4) -> mx-ms-bc-bus-reference-data-mule | K4: MuleSoft | L4: bus-reference-data-api-dev | M4: =generarNombreDeploy(J4) -> bus-reference-data-api-dev | N4: =validateAPIName(M4,D4) -> Valid | O4: =LEN(M4) -> 26
A5: SSFF | B5: Bus Sales and Service | C5: =COUNTIF(develop!F5:F980,B5) -> 27 | D5: BUSINESS | E5: mx-api-bc-bus-sales-and-service | F5: APIMX000004 | G5: =E5 -> mx-api-bc-bus-sales-and-service | H5: =CONCATENATE("https://anypoint.mulesoft.com/exchange/834f46f4-ef08-4c50-81ae-56f917b413cc/", G5) -> https://anypoint.mulesoft.com/exchange/834f46f4-ef08-4c50-81ae-56f917b413cc/mx-api-bc-bus-sales-and-service | I5: 1.12.0 | J5: =obtenerRepoMS(E5) -> mx-ms-bc-bus-sales-and-service-mule | K5: MuleSoft | L5: bus-sales-and-service-api-dev | M5: =generarNombreDeploy(J5) -> bus-sales-and-service-api-dev | N5: =validateAPIName(M5,D5) -> Valid | O5: =LEN(M5) -> 29
A6: SSFF | B6: Dom Account Reconciliation | C6: =COUNTIF(develop!F6:F980,B6) -> 1 | D6: DOMAIN | E6: mx-api-bc-dom-account-reconciliation | F6: APIMX000005 | G6: =E6 -> mx-api-bc-dom-account-reconciliation | H6: =CONCATENATE("https://anypoint.mulesoft.com/exchange/834f46f4-ef08-4c50-81ae-56f917b413cc/", G6) -> https://anypoint.mulesoft.com/exchange/834f46f4-ef08-4c50-81ae-56f917b413cc/mx-api-bc-dom-account-reconciliation | I6: 1.1.0 | J6: =obtenerRepoMS(E6) -> mx-ms-bc-dom-account-reconciliation-mule | K6: MuleSoft | L6: =IFERROR(__xludf.DUMMYFUNCTION("REGEXREPLACE(REGEXREPLACE(REGEXREPLACE(J6, ""mx-ms-bc-"", """"), ""-mule"", ""-api-dev""), ""-apigee"", ""-api-dev"")"),"dom-account-reconciliation-api-dev") -> dom-account-reconciliation-api-dev | M6: =generarNombreDeploy(J6) -> dom-account-reconciliation-api-dev | N6: =validateAPIName(M6,D6) -> Valid | O6: =LEN(M6) -> 34
A7: SSFF | B7: Dom Branch Location Operations | C7: =COUNTIF(develop!F7:F980,B7) -> 2 | D7: DOMAIN | E7: mx-api-bc-dom-branch-location-operations | F7: APIMX000006 | G7: =E7 -> mx-api-bc-dom-branch-location-operations | H7: =CONCATENATE("https://anypoint.mulesoft.com/exchange/834f46f4-ef08-4c50-81ae-56f917b413cc/", G7) -> https://anypoint.mulesoft.com/exchange/834f46f4-ef08-4c50-81ae-56f917b413cc/mx-api-bc-dom-branch-location-operations | I7: 1.2.0 | J7: =obtenerRepoMS(E7) -> mx-ms-bc-dom-branch-location-operations-mule | K7: MuleSoft | L7: =IFERROR(__xludf.DUMMYFUNCTION("REGEXREPLACE(REGEXREPLACE(REGEXREPLACE(J7, ""mx-ms-bc-"", """"), ""-mule"", ""-api-dev""), ""-apigee"", ""-api-dev"")"),"dom-branch-location-operations-api-dev") -> dom-branch-location-operations-api-dev | M7: =generarNombreDeploy(J7) -> dom-branch-location-operations-api-dev | N7: =validateAPIName(M7,D7) -> Valid | O7: =LEN(M7) -> 38
A8: SSFF | B8: Dom Branch Network Management | C8: =COUNTIF(develop!F8:F980,B8) -> 1 | D8: DOMAIN | E8: mx-api-bc-dom-branch-network-management | F8: APIMX000007 | G8: =E8 -> mx-api-bc-dom-branch-network-management | H8: =CONCATENATE("https://anypoint.mulesoft.com/exchange/834f46f4-ef08-4c50-81ae-56f917b413cc/", G8) -> https://anypoint.mulesoft.com/exchange/834f46f4-ef08-4c50-81ae-56f917b413cc/mx-api-bc-dom-branch-network-management | I8: 1.1.0 | J8: =obtenerRepoMS(E8) -> mx-ms-bc-dom-branch-network-management-mule | K8: MuleSoft | L8: dom-branch-network-management-api-dev | M8: =generarNombreDeploy(J8) -> dom-branch-network-management-api-dev | N8: =validateAPIName(M8,D8) -> Valid | O8: =LEN(M8) -> 37
A9: SSFF | B9: Dom Card eCommerce Gateway | C9: =COUNTIF(develop!F9:F980,B9) -> 1 | D9: DOMAIN | E9: mx-api-bc-dom-card-ecommerce-gateway | F9: APIMX000008 | G9: =E9 -> mx-api-bc-dom-card-ecommerce-gateway | H9: =CONCATENATE("https://anypoint.mulesoft.com/exchange/834f46f4-ef08-4c50-81ae-56f917b413cc/", G9) -> https://anypoint.mulesoft.com/exchange/834f46f4-ef08-4c50-81ae-56f917b413cc/mx-api-bc-dom-card-ecommerce-gateway | I9: 1.0.0 | J9: =obtenerRepoMS(E9) -> mx-ms-bc-dom-card-ecommerce-gateway-mule | K9: MuleSoft | L9: =IFERROR(__xludf.DUMMYFUNCTION("REGEXREPLACE(REGEXREPLACE(REGEXREPLACE(J9, ""mx-ms-bc-"", """"), ""-mule"", ""-api-dev""), ""-apigee"", ""-api-dev"")"),"dom-card-ecommerce-gateway-api-dev") -> dom-card-ecommerce-gateway-api-dev | M9: =generarNombreDeploy(J9) -> dom-card-ecommerce-gateway-api-dev | N9: =validateAPIName(M9,D9) -> Valid | O9: =LEN(M9) -> 34
A10: SSFF | B10: Dom Corporate Current Account | C10: =COUNTIF(develop!F10:F980,B10) -> 1 | D10: DOMAIN | E10: mx-api-bc-dom-corporate-current-account | F10: APIMX000009 | G10: =E10 -> mx-api-bc-dom-corporate-current-account | H10: =CONCATENATE("https://anypoint.mulesoft.com/exchange/834f46f4-ef08-4c50-81ae-56f917b413cc/", G10) -> https://anypoint.mulesoft.com/exchange/834f46f4-ef08-4c50-81ae-56f917b413cc/mx-api-bc-dom-corporate-current-account | I10: 1.1.0 | J10: =obtenerRepoMS(E10) -> mx-ms-bc-dom-corporate-current-account-mule | K10: MuleSoft | L10: dom-corporate-current-account-api-dev | M10: =generarNombreDeploy(J10) -> dom-corporate-current-account-api-dev | N10: =validateAPIName(M10,D10) -> Valid | O10: =LEN(M10) -> 37
A11: SSFF | B11: Dom Correspondence | C11: =COUNTIF(develop!F11:F980,B11) -> 1 | D11: DOMAIN | E11: mx-api-bc-dom-correspondence | F11: APIMX000010 | G11: =E11 -> mx-api-bc-dom-correspondence | H11: =CONCATENATE("https://anypoint.mulesoft.com/exchange/834f46f4-ef08-4c50-81ae-56f917b413cc/", G11) -> https://anypoint.mulesoft.com/exchange/834f46f4-ef08-4c50-81ae-56f917b413cc/mx-api-bc-dom-correspondence | I11: 1.0.0 | J11: =obtenerRepoMS(E11) -> mx-ms-bc-dom-correspondence-mule | K11: MuleSoft | L11: =IFERROR(__xludf.DUMMYFUNCTION("REGEXREPLACE(REGEXREPLACE(REGEXREPLACE(J11, ""mx-ms-bc-"", """"), ""-mule"", ""-api-dev""), ""-apigee"", ""-api-dev"")"),"dom-correspondence-api-dev") -> dom-correspondence-api-dev | M11: =generarNombreDeploy(J11) -> dom-correspondence-api-dev | N11: =validateAPIName(M11,D11) -> Valid | O11: =LEN(M11) -> 26
A12: SSFF | B12: Dom Counterparty Risk | C12: =COUNTIF(develop!F12:F980,B12) -> 15 | D12: DOMAIN | E12: mx-api-bc-dom-counterparty-risk | F12: APIMX000011 | G12: =E12 -> mx-api-bc-dom-counterparty-risk | H12: =CONCATENATE("https://anypoint.mulesoft.com/exchange/834f46f4-ef08-4c50-81ae-56f917b413cc/", G12) -> https://anypoint.mulesoft.com/exchange/834f46f4-ef08-4c50-81ae-56f917b413cc/mx-api-bc-dom-counterparty-risk | I12: 1.2.0 | J12: =obtenerRepoMS(E12) -> mx-ms-bc-dom-counterparty-risk-mule | K12: MuleSoft | L12: =IFERROR(__xludf.DUMMYFUNCTION("REGEXREPLACE(REGEXREPLACE(REGEXREPLACE(J12, ""mx-ms-bc-"", """"), ""-mule"", ""-api-dev""), ""-apigee"", ""-api-dev"")"),"dom-counterparty-risk-api-dev") -> dom-counterparty-risk-api-dev | M12: =generarNombreDeploy(J12) -> dom-counterparty-risk-api-dev | N12: =validateAPIName(M12,D12) -> Valid | O12: =LEN(M12) -> 29
A13: SSFF | B13: Dom Credit Card | C13: =COUNTIF(develop!F13:F980,B13) -> 55 | D13: DOMAIN | E13: mx-api-bc-dom-credit-card | F13: APIMX000012 | G13: =E13 -> mx-api-bc-dom-credit-card | H13: =CONCATENATE("https://anypoint.mulesoft.com/exchange/834f46f4-ef08-4c50-81ae-56f917b413cc/", G13) -> https://anypoint.mulesoft.com/exchange/834f46f4-ef08-4c50-81ae-56f917b413cc/mx-api-bc-dom-credit-card | I13: 1.31.0 | J13: mx-ms-bc-dom-credit-card-mule | K13: MuleSoft | L13: dom-credit-card-api-dev | M13: =generarNombreDeploy(J13) -> dom-credit-card-api-dev | N13: =validateAPIName(M13,D13) -> Valid | O13: =LEN(M13) -> 23
A14: SSFF | B14: Dom Credit Card Position Keeping | C14: =COUNTIF(develop!F14:F980,B14) -> 5 | D14: DOMAIN | E14: mx-api-bc-dom-credit-card-position-keeping | F14: APIMX000013 | G14: =E14 -> mx-api-bc-dom-credit-card-position-keeping | H14: =CONCATENATE("https://anypoint.mulesoft.com/exchange/834f46f4-ef08-4c50-81ae-56f917b413cc/", G14) -> https://anypoint.mulesoft.com/exchange/834f46f4-ef08-4c50-81ae-56f917b413cc/mx-api-bc-dom-credit-card-position-keeping | I14: 1.4.3 | J14: =obtenerRepoMS(E14) -> mx-ms-bc-dom-credit-card-position-keeping-mule | K14: MuleSoft | L14: dom-credit-card-position-keeping-api-dev | M14: =generarNombreDeploy(J14) -> dom-credit-card-position-keeping-api-dev | N14: =validateAPIName(M14,D14) -> Valid | O14: =LEN(M14) -> 40
A15: SSFF | B15: Dom Credit Facility | C15: =COUNTIF(develop!F15:F980,B15) -> 2 | D15: DOMAIN | E15: mx-api-bc-dom-credit-facility | F15: APIMX000014 | G15: =E15 -> mx-api-bc-dom-credit-facility | H15: =CONCATENATE("https://anypoint.mulesoft.com/exchange/834f46f4-ef08-4c50-81ae-56f917b413cc/", G15) -> https://anypoint.mulesoft.com/exchange/834f46f4-ef08-4c50-81ae-56f917b413cc/mx-api-bc-dom-credit-facility | I15: 1.2.1 | J15: =obtenerRepoMS(E15) -> mx-ms-bc-dom-credit-facility-mule | K15: MuleSoft | L15: =IFERROR(__xludf.DUMMYFUNCTION("REGEXREPLACE(REGEXREPLACE(REGEXREPLACE(J15, ""mx-ms-bc-"", """"), ""-mule"", ""-api-dev""), ""-apigee"", ""-api-dev"")"),"dom-credit-facility-api-dev") -> dom-credit-facility-api-dev | M15: =generarNombreDeploy(J15) -> dom-credit-facility-api-dev | N15: =validateAPIName(M15,D15) -> Valid | O15: =LEN(M15) -> 27
A16: SSFF | B16: Dom Currency Exchange | C16: =COUNTIF(develop!F16:F980,B16) -> 1 | D16: DOMAIN | E16: mx-api-bc-dom-currency-exchange | F16: APIMX000015 | G16: =E16 -> mx-api-bc-dom-currency-exchange | H16: =CONCATENATE("https://anypoint.mulesoft.com/exchange/834f46f4-ef08-4c50-81ae-56f917b413cc/", G16) -> https://anypoint.mulesoft.com/exchange/834f46f4-ef08-4c50-81ae-56f917b413cc/mx-api-bc-dom-currency-exchange | I16: 1.0.0 | J16: =obtenerRepoMS(E16) -> mx-ms-bc-dom-currency-exchange-mule | K16: MuleSoft | L16: =IFERROR(__xludf.DUMMYFUNCTION("REGEXREPLACE(REGEXREPLACE(REGEXREPLACE(J16, ""mx-ms-bc-"", """"), ""-mule"", ""-api-dev""), ""-apigee"", ""-api-dev"")"),"dom-currency-exchange-api-dev") -> dom-currency-exchange-api-dev | M16: =generarNombreDeploy(J16) -> dom-currency-exchange-api-dev | N16: =validateAPIName(M16,D16) -> Valid | O16: =LEN(M16) -> 29
A17: SSFF | B17: Dom Current Account | C17: =COUNTIF(develop!F17:F980,B17) -> 1 | D17: DOMAIN | E17: mx-api-bc-dom-current-account | F17: APIMX000016 | G17: =E17 -> mx-api-bc-dom-current-account | H17: =CONCATENATE("https://anypoint.mulesoft.com/exchange/834f46f4-ef08-4c50-81ae-56f917b413cc/", G17) -> https://anypoint.mulesoft.com/exchange/834f46f4-ef08-4c50-81ae-56f917b413cc/mx-api-bc-dom-current-account | I17: 1.0.0 | J17: =obtenerRepoMS(E17) -> mx-ms-bc-dom-current-account-mule | K17: MuleSoft | L17: =IFERROR(__xludf.DUMMYFUNCTION("REGEXREPLACE(REGEXREPLACE(REGEXREPLACE(J17, ""mx-ms-bc-"", """"), ""-mule"", ""-api-dev""), ""-apigee"", ""-api-dev"")"),"dom-current-account-api-dev") -> dom-current-account-api-dev | M17: =generarNombreDeploy(J17) -> dom-current-account-api-dev | N17: =validateAPIName(M17,D17) -> Valid | O17: =LEN(M17) -> 27
A18: SSFF | B18: Dom Customer Access Entitlement | C18: =COUNTIF(develop!F18:F980,B18) -> 2 | D18: DOMAIN | E18: mx-api-bc-dom-customer-access-entitlement | F18: APIMX000017 | G18: =E18 -> mx-api-bc-dom-customer-access-entitlement | H18: =CONCATENATE("https://anypoint.mulesoft.com/exchange/834f46f4-ef08-4c50-81ae-56f917b413cc/", G18) -> https://anypoint.mulesoft.com/exchange/834f46f4-ef08-4c50-81ae-56f917b413cc/mx-api-bc-dom-customer-access-entitlement | I18: 1.1.1 | J18: =obtenerRepoMS(E18) -> mx-ms-bc-dom-customer-access-entitlement-mule | K18: MuleSoft | L18: =IFERROR(__xludf.DUMMYFUNCTION("REGEXREPLACE(REGEXREPLACE(REGEXREPLACE(J18, ""mx-ms-bc-"", """"), ""-mule"", ""-api-dev""), ""-apigee"", ""-api-dev"")"),"dom-customer-access-entitlement-api-dev") -> dom-customer-access-entitlement-api-dev | M18: =generarNombreDeploy(J18) -> dom-customer-access-entitlement-api-dev | N18: =validateAPIName(M18,D18) -> Valid | O18: =LEN(M18) -> 39
A19: SSFF | B19: Dom Customer Agreement | C19: =COUNTIF(develop!F19:F980,B19) -> 6 | D19: DOMAIN | E19: mx-api-bc-dom-customer-agreement | F19: APIMX000018 | G19: =E19 -> mx-api-bc-dom-customer-agreement | H19: =CONCATENATE("https://anypoint.mulesoft.com/exchange/834f46f4-ef08-4c50-81ae-56f917b413cc/", G19) -> https://anypoint.mulesoft.com/exchange/834f46f4-ef08-4c50-81ae-56f917b413cc/mx-api-bc-dom-customer-agreement | I19: 1.3.0 | J19: =obtenerRepoMS(E19) -> mx-ms-bc-dom-customer-agreement-mule | K19: MuleSoft | L19: dom-customer-agreement-api-dev | M19: =generarNombreDeploy(J19) -> dom-customer-agreement-api-dev | N19: =validateAPIName(M19,D19) -> Valid | O19: =LEN(M19) -> 30
A20: SSFF | B20: Dom Customer Credit Rating | C20: =COUNTIF(develop!F20:F980,B20) -> 17 | D20: DOMAIN | E20: mx-api-bc-dom-customer-credit-rating | F20: APIMX000019 | G20: =E20 -> mx-api-bc-dom-customer-credit-rating | H20: =CONCATENATE("https://anypoint.mulesoft.com/exchange/834f46f4-ef08-4c50-81ae-56f917b413cc/", G20) -> https://anypoint.mulesoft.com/exchange/834f46f4-ef08-4c50-81ae-56f917b413cc/mx-api-bc-dom-customer-credit-rating | I20: 1.5.1 | J20: =obtenerRepoMS(E20) -> mx-ms-bc-dom-customer-credit-rating-mule | K20: MuleSoft | L20: =IFERROR(__xludf.DUMMYFUNCTION("REGEXREPLACE(REGEXREPLACE(REGEXREPLACE(J20, ""mx-ms-bc-"", """"), ""-mule"", ""-api-dev""), ""-apigee"", ""-api-dev"")"),"dom-customer-credit-rating-api-dev") -> dom-customer-credit-rating-api-dev | M20: =generarNombreDeploy(J20) -> dom-customer-credit-rating-api-dev | N20: =validateAPIName(M20,D20) -> Valid | O20: =LEN(M20) -> 34
A21: SSFF | B21: Dom Customer Offer | C21: =COUNTIF(develop!F21:F980,B21) -> 4 | D21: DOMAIN | E21: mx-api-bc-dom-customer-offer | F21: APIMX000020 | G21: =E21 -> mx-api-bc-dom-customer-offer | H21: =CONCATENATE("https://anypoint.mulesoft.com/exchange/834f46f4-ef08-4c50-81ae-56f917b413cc/", G21) -> https://anypoint.mulesoft.com/exchange/834f46f4-ef08-4c50-81ae-56f917b413cc/mx-api-bc-dom-customer-offer | I21: 1.0.0 | J21: =obtenerRepoMS(E21) -> mx-ms-bc-dom-customer-offer-mule | K21: MuleSoft | L21: =IFERROR(__xludf.DUMMYFUNCTION("REGEXREPLACE(REGEXREPLACE(REGEXREPLACE(J21, ""mx-ms-bc-"", """"), ""-mule"", ""-api-dev""), ""-apigee"", ""-api-dev"")"),"dom-customer-offer-api-dev") -> dom-customer-offer-api-dev | M21: =generarNombreDeploy(J21) -> dom-customer-offer-api-dev | N21: =validateAPIName(M21,D21) -> Valid | O21: =LEN(M21) -> 26
A22: SSFF | B22: Dom Customer Position | C22: =COUNTIF(develop!F22:F980,B22) -> 5 | D22: DOMAIN | E22: mx-api-bc-dom-customer-position | F22: APIMX000021 | G22: =E22 -> mx-api-bc-dom-customer-position | H22: =CONCATENATE("https://anypoint.mulesoft.com/exchange/834f46f4-ef08-4c50-81ae-56f917b413cc/", G22) -> https://anypoint.mulesoft.com/exchange/834f46f4-ef08-4c50-81ae-56f917b413cc/mx-api-bc-dom-customer-position | I22: 1.3.0 | J22: =obtenerRepoMS(E22) -> mx-ms-bc-dom-customer-position-mule | K22: MuleSoft | L22: dom-customer-position-api-dev | M22: =generarNombreDeploy(J22) -> dom-customer-position-api-dev | N22: =validateAPIName(M22,D22) -> Valid | O22: =LEN(M22) -> 29
A23: SSFF | B23: Dom Customer Product And Service Eligibility | C23: =COUNTIF(develop!F23:F980,B23) -> 4 | D23: DOMAIN | E23: mx-api-bc-dom-customer-product-and-service-eligibility | F23: APIMX000022 | G23: =E23 -> mx-api-bc-dom-customer-product-and-service-eligibility | H23: =CONCATENATE("https://anypoint.mulesoft.com/exchange/834f46f4-ef08-4c50-81ae-56f917b413cc/", G23) -> https://anypoint.mulesoft.com/exchange/834f46f4-ef08-4c50-81ae-56f917b413cc/mx-api-bc-dom-customer-product-and-service-eligibility | I23: 1.1.0 | J23: =obtenerRepoMS(E23) -> mx-ms-bc-dom-customer-product-and-service-eligibility-mule | K23: MuleSoft | L23: dom-cust-prod-and-svc-elig-dev | M23: dom-cust-prod-and-svc-elig-dev | N23: =validateAPIName(M23,D23) -> Valid | O23: =LEN(M23) -> 30
A24: SSFF | B24: Dom Customer Products And Services | C24: =COUNTIF(develop!F24:F980,B24) -> 16 | D24: DOMAIN | E24: mx-api-bc-dom-customer-products-and-services | F24: APIMX000023 | G24: =E24 -> mx-api-bc-dom-customer-products-and-services | H24: =CONCATENATE("https://anypoint.mulesoft.com/exchange/834f46f4-ef08-4c50-81ae-56f917b413cc/", G24) -> https://anypoint.mulesoft.com/exchange/834f46f4-ef08-4c50-81ae-56f917b413cc/mx-api-bc-dom-customer-products-and-services | I24: 1.2.1 | J24: =obtenerRepoMS(E24) -> mx-ms-bc-dom-customer-products-and-services-mule | K24: MuleSoft | L24: dom-customer-workbench-api-dev | M24: =generarNombreDeploy(J24) -> dom-customer-products-and-services-api-dev | N24: =validateAPIName(M24,D24) -> Valid | O24: =LEN(M24) -> 42
A25: SSFF | B25: Dom Customer Relationship Management | C25: =COUNTIF(develop!F25:F980,B25) -> 3 | D25: DOMAIN | E25: mx-api-bc-dom-customer-relationship-management | F25: APIMX000024 | G25: =E25 -> mx-api-bc-dom-customer-relationship-management | H25: =CONCATENATE("https://anypoint.mulesoft.com/exchange/834f46f4-ef08-4c50-81ae-56f917b413cc/", G25) -> https://anypoint.mulesoft.com/exchange/834f46f4-ef08-4c50-81ae-56f917b413cc/mx-api-bc-dom-customer-relationship-management | I25: 1.1.0 | J25: =obtenerRepoMS(E25) -> mx-ms-bc-dom-customer-relationship-management-mule | K25: MuleSoft | L25: dom-cust-rel-mgmt-api-dev | M25: dom-cust-rel-mgmt-api-dev | N25: =validateAPIName(M25,D25) -> Valid | O25: =LEN(M25) -> 25
A26: SSFF | B26: Dom Customer Workbench | C26: =COUNTIF(develop!F26:F980,B26) -> 1 | D26: DOMAIN | E26: mx-api-bc-dom-customer-workbench | F26: APIMX000025 | G26: =E26 -> mx-api-bc-dom-customer-workbench | H26: =CONCATENATE("https://anypoint.mulesoft.com/exchange/834f46f4-ef08-4c50-81ae-56f917b413cc/", G26) -> https://anypoint.mulesoft.com/exchange/834f46f4-ef08-4c50-81ae-56f917b413cc/mx-api-bc-dom-customer-workbench | I26: 1.0.0 | J26: =obtenerRepoMS(E26) -> mx-ms-bc-dom-customer-workbench-mule | K26: MuleSoft | L26: dom-customer-products-and-services-api-dev | M26: =generarNombreDeploy(J26) -> dom-customer-workbench-api-dev | N26: =validateAPIName(M26,D26) -> Valid | O26: =LEN(M26) -> 30
A27: SSFF | B27: Dom Direct Debit | C27: =COUNTIF(develop!F27:F980,B27) -> 1 | D27: DOMAIN | E27: mx-api-bc-dom-direct-debit | F27: APIMX000026 | G27: =E27 -> mx-api-bc-dom-direct-debit | H27: =CONCATENATE("https://anypoint.mulesoft.com/exchange/834f46f4-ef08-4c50-81ae-56f917b413cc/", G27) -> https://anypoint.mulesoft.com/exchange/834f46f4-ef08-4c50-81ae-56f917b413cc/mx-api-bc-dom-direct-debit | I27: 1.0.0 | J27: =obtenerRepoMS(E27) -> mx-ms-bc-dom-direct-debit-mule | K27: MuleSoft | L27: =IFERROR(__xludf.DUMMYFUNCTION("REGEXREPLACE(REGEXREPLACE(REGEXREPLACE(J27, ""mx-ms-bc-"", """"), ""-mule"", ""-api-dev""), ""-apigee"", ""-api-dev"")"),"dom-direct-debit-api-dev") -> dom-direct-debit-api-dev | M27: =generarNombreDeploy(J27) -> dom-direct-debit-api-dev | N27: =validateAPIName(M27,D27) -> Valid | O27: =LEN(M27) -> 24
A28: SSFF | B28: Dom Document Directory | C28: =COUNTIF(develop!F28:F980,B28) -> 3 | D28: DOMAIN | E28: mx-api-bc-dom-document-directory | F28: APIMX000027 | G28: =E28 -> mx-api-bc-dom-document-directory | H28: =CONCATENATE("https://anypoint.mulesoft.com/exchange/834f46f4-ef08-4c50-81ae-56f917b413cc/", G28) -> https://anypoint.mulesoft.com/exchange/834f46f4-ef08-4c50-81ae-56f917b413cc/mx-api-bc-dom-document-directory | I28: 1.0.0 | J28: =obtenerRepoMS(E28) -> mx-ms-bc-dom-document-directory-mule | K28: MuleSoft | L28: =IFERROR(__xludf.DUMMYFUNCTION("REGEXREPLACE(REGEXREPLACE(REGEXREPLACE(J28, ""mx-ms-bc-"", """"), ""-mule"", ""-api-dev""), ""-apigee"", ""-api-dev"")"),"dom-document-directory-api-dev") -> dom-document-directory-api-dev | M28: =generarNombreDeploy(J28) -> dom-document-directory-api-dev | N28: =validateAPIName(M28,D28) -> Valid | O28: =LEN(M28) -> 30
A29: SSFF | B29: Dom Document Services | C29: =COUNTIF(develop!F29:F980,B29) -> 7 | D29: DOMAIN | E29: mx-api-bc-dom-document-services | F29: APIMX000028 | G29: =E29 -> mx-api-bc-dom-document-services | H29: =CONCATENATE("https://anypoint.mulesoft.com/exchange/834f46f4-ef08-4c50-81ae-56f917b413cc/", G29) -> https://anypoint.mulesoft.com/exchange/834f46f4-ef08-4c50-81ae-56f917b413cc/mx-api-bc-dom-document-services | I29: 1.7.0 | J29: =obtenerRepoMS(E29) -> mx-ms-bc-dom-document-services-mule | K29: MuleSoft | L29: dom-document-services-api-dev | M29: =generarNombreDeploy(J29) -> dom-document-services-api-dev | N29: =validateAPIName(M29,D29) -> Valid | O29: =LEN(M29) -> 29
A30: SSFF | B30: Dom Financial Accounting | C30: =COUNTIF(develop!F30:F980,B30) -> 4 | D30: DOMAIN | E30: mx-api-bc-dom-financial-accounting | F30: APIMX000029 | G30: =E30 -> mx-api-bc-dom-financial-accounting | H30: =CONCATENATE("https://anypoint.mulesoft.com/exchange/834f46f4-ef08-4c50-81ae-56f917b413cc/", G30) -> https://anypoint.mulesoft.com/exchange/834f46f4-ef08-4c50-81ae-56f917b413cc/mx-api-bc-dom-financial-accounting | I30: 1.0.0 | J30: =obtenerRepoMS(E30) -> mx-ms-bc-dom-financial-accounting-mule | K30: MuleSoft | L30: =IFERROR(__xludf.DUMMYFUNCTION("REGEXREPLACE(REGEXREPLACE(REGEXREPLACE(J30, ""mx-ms-bc-"", """"), ""-mule"", ""-api-dev""), ""-apigee"", ""-api-dev"")"),"dom-financial-accounting-api-dev") -> dom-financial-accounting-api-dev | M30: =generarNombreDeploy(J30) -> dom-financial-accounting-api-dev | N30: =validateAPIName(M30,D30) -> Valid | O30: =LEN(M30) -> 32
A31: SSFF | B31: Dom Fraud Resolution | C31: =COUNTIF(develop!F31:F980,B31) -> 1 | D31: DOMAIN | E31: mx-api-bc-dom-fraud-resolution | F31: APIMX000030 | G31: =E31 -> mx-api-bc-dom-fraud-resolution | H31: =CONCATENATE("https://anypoint.mulesoft.com/exchange/834f46f4-ef08-4c50-81ae-56f917b413cc/", G31) -> https://anypoint.mulesoft.com/exchange/834f46f4-ef08-4c50-81ae-56f917b413cc/mx-api-bc-dom-fraud-resolution | I31: 1.0.0 | J31: =obtenerRepoMS(E31) -> mx-ms-bc-dom-fraud-resolution-mule | K31: MuleSoft | L31: =IFERROR(__xludf.DUMMYFUNCTION("REGEXREPLACE(REGEXREPLACE(REGEXREPLACE(J31, ""mx-ms-bc-"", """"), ""-mule"", ""-api-dev""), ""-apigee"", ""-api-dev"")"),"dom-fraud-resolution-api-dev") -> dom-fraud-resolution-api-dev | M31: =generarNombreDeploy(J31) -> dom-fraud-resolution-api-dev | N31: =validateAPIName(M31,D31) -> Valid | O31: =LEN(M31) -> 28
A32: SSFF | B32: Dom Interactive Help | C32: =COUNTIF(develop!F32:F980,B32) -> 2 | D32: DOMAIN | E32: mx-api-bc-dom-interactive-help | F32: APIMX000031 | G32: =E32 -> mx-api-bc-dom-interactive-help | H32: =CONCATENATE("https://anypoint.mulesoft.com/exchange/834f46f4-ef08-4c50-81ae-56f917b413cc/", G32) -> https://anypoint.mulesoft.com/exchange/834f46f4-ef08-4c50-81ae-56f917b413cc/mx-api-bc-dom-interactive-help | I32: 1.0.0 | J32: =obtenerRepoMS(E32) -> mx-ms-bc-dom-interactive-help-mule | K32: MuleSoft | L32: =IFERROR(__xludf.DUMMYFUNCTION("REGEXREPLACE(REGEXREPLACE(REGEXREPLACE(J32, ""mx-ms-bc-"", """"), ""-mule"", ""-api-dev""), ""-apigee"", ""-api-dev"")"),"dom-interactive-help-api-dev") -> dom-interactive-help-api-dev | M32: =generarNombreDeploy(J32) -> dom-interactive-help-api-dev | N32: =validateAPIName(M32,D32) -> Valid | O32: =LEN(M32) -> 28
A33: SSFF | B33: Dom Internal Bank Account | C33: =COUNTIF(develop!F33:F980,B33) -> 2 | D33: DOMAIN | E33: mx-api-bc-dom-internal-bank-account | F33: APIMX000032 | G33: =E33 -> mx-api-bc-dom-internal-bank-account | H33: =CONCATENATE("https://anypoint.mulesoft.com/exchange/834f46f4-ef08-4c50-81ae-56f917b413cc/", G33) -> https://anypoint.mulesoft.com/exchange/834f46f4-ef08-4c50-81ae-56f917b413cc/mx-api-bc-dom-internal-bank-account | I33: 1.0.0 | J33: =obtenerRepoMS(E33) -> mx-ms-bc-dom-internal-bank-account-mule | K33: MuleSoft | L33: =IFERROR(__xludf.DUMMYFUNCTION("REGEXREPLACE(REGEXREPLACE(REGEXREPLACE(J33, ""mx-ms-bc-"", """"), ""-mule"", ""-api-dev""), ""-apigee"", ""-api-dev"")"),"dom-internal-bank-account-api-dev") -> dom-internal-bank-account-api-dev | M33: =generarNombreDeploy(J33) -> dom-internal-bank-account-api-dev | N33: =validateAPIName(M33,D33) -> Valid | O33: =LEN(M33) -> 33
A34: SSFF | B34: Dom Investment Account | C34: =COUNTIF(develop!F34:F980,B34) -> 1 | D34: DOMAIN | E34: mx-api-bc-dom-investment-account | F34: APIMX000033 | G34: =E34 -> mx-api-bc-dom-investment-account | H34: =CONCATENATE("https://anypoint.mulesoft.com/exchange/834f46f4-ef08-4c50-81ae-56f917b413cc/", G34) -> https://anypoint.mulesoft.com/exchange/834f46f4-ef08-4c50-81ae-56f917b413cc/mx-api-bc-dom-investment-account | I34: 1.0.0 | J34: =obtenerRepoMS(E34) -> mx-ms-bc-dom-investment-account-mule | K34: MuleSoft | L34: =IFERROR(__xludf.DUMMYFUNCTION("REGEXREPLACE(REGEXREPLACE(REGEXREPLACE(J34, ""mx-ms-bc-"", """"), ""-mule"", ""-api-dev""), ""-apigee"", ""-api-dev"")"),"dom-investment-account-api-dev") -> dom-investment-account-api-dev | M34: =generarNombreDeploy(J34) -> dom-investment-account-api-dev | N34: =validateAPIName(M34,D34) -> Valid | O34: =LEN(M34) -> 30
A35: SSFF | B35: Dom Issued Device Administration | C35: =COUNTIF(develop!F35:F980,B35) -> 17 | D35: DOMAIN | E35: mx-api-bc-dom-issued-device-administration | F35: APIMX000034 | G35: =E35 -> mx-api-bc-dom-issued-device-administration | H35: =CONCATENATE("https://anypoint.mulesoft.com/exchange/834f46f4-ef08-4c50-81ae-56f917b413cc/", G35) -> https://anypoint.mulesoft.com/exchange/834f46f4-ef08-4c50-81ae-56f917b413cc/mx-api-bc-dom-issued-device-administration | I35: 1.2.1 | J35: =obtenerRepoMS(E35) -> mx-ms-bc-dom-issued-device-administration-mule | K35: MuleSoft | L35: dom-issued-device-administration-api-dev | M35: =generarNombreDeploy(J35) -> dom-issued-device-administration-api-dev | N35: =validateAPIName(M35,D35) -> Valid | O35: =LEN(M35) -> 40
A36: SSFF | B36: Dom Issued Device Tracking | C36: =COUNTIF(develop!F36:F980,B36) -> 2 | D36: DOMAIN | E36: mx-api-bc-dom-issued-device-tracking | F36: APIMX000035 | G36: =E36 -> mx-api-bc-dom-issued-device-tracking | H36: =CONCATENATE("https://anypoint.mulesoft.com/exchange/834f46f4-ef08-4c50-81ae-56f917b413cc/", G36) -> https://anypoint.mulesoft.com/exchange/834f46f4-ef08-4c50-81ae-56f917b413cc/mx-api-bc-dom-issued-device-tracking | I36: 1.1.0 | J36: =obtenerRepoMS(E36) -> mx-ms-bc-dom-issued-device-tracking-mule | K36: MuleSoft | L36: dom-issued-device-tracking-api-dev | M36: =generarNombreDeploy(J36) -> dom-issued-device-tracking-api-dev | N36: =validateAPIName(M36,D36) -> Valid | O36: =LEN(M36) -> 34
A37: SSFF | B37: Dom Legal Entity Directory | C37: =COUNTIF(develop!F37:F980,B37) -> 2 | D37: DOMAIN | E37: mx-api-bc-dom-legal-entity-directory | F37: APIMX000036 | G37: =E37 -> mx-api-bc-dom-legal-entity-directory | H37: =CONCATENATE("https://anypoint.mulesoft.com/exchange/834f46f4-ef08-4c50-81ae-56f917b413cc/", G37) -> https://anypoint.mulesoft.com/exchange/834f46f4-ef08-4c50-81ae-56f917b413cc/mx-api-bc-dom-legal-entity-directory | I37: 1.0.0 | J37: =obtenerRepoMS(E37) -> mx-ms-bc-dom-legal-entity-directory-mule | K37: MuleSoft | L37: dom-legal-entity-directory-api-dev | M37: =generarNombreDeploy(J37) -> dom-legal-entity-directory-api-dev | N37: =validateAPIName(M37,D37) -> Valid | O37: =LEN(M37) -> 34
A38: SSFF | B38: Dom Loan | C38: =COUNTIF(develop!F38:F980,B38) -> 11 | D38: DOMAIN | E38: mx-api-bc-dom-loan | F38: APIMX000037 | G38: =E38 -> mx-api-bc-dom-loan | H38: =CONCATENATE("https://anypoint.mulesoft.com/exchange/834f46f4-ef08-4c50-81ae-56f917b413cc/", G38) -> https://anypoint.mulesoft.com/exchange/834f46f4-ef08-4c50-81ae-56f917b413cc/mx-api-bc-dom-loan | I38: 1.2.0 | J38: =obtenerRepoMS(E38) -> mx-ms-bc-dom-loan-mule | K38: MuleSoft | L38: dom-loan-api-dev | M38: =generarNombreDeploy(J38) -> dom-loan-api-dev | N38: =validateAPIName(M38,D38) -> Valid | O38: =LEN(M38) -> 16
A39: SSFF | B39: Dom Location Data Management | C39: =COUNTIF(develop!F39:F980,B39) -> 12 | D39: DOMAIN | E39: mx-api-bc-dom-location-data-management | F39: APIMX000038 | G39: =E39 -> mx-api-bc-dom-location-data-management | H39: =CONCATENATE("https://anypoint.mulesoft.com/exchange/834f46f4-ef08-4c50-81ae-56f917b413cc/", G39) -> https://anypoint.mulesoft.com/exchange/834f46f4-ef08-4c50-81ae-56f917b413cc/mx-api-bc-dom-location-data-management | I39: 1.2.1 | J39: =obtenerRepoMS(E39) -> mx-ms-bc-dom-location-data-management-mule | K39: MuleSoft | L39: dom-location-data-management-api-dev | M39: =generarNombreDeploy(J39) -> dom-location-data-management-api-dev | N39: =validateAPIName(M39,D39) -> Valid | O39: =LEN(M39) -> 36
A40: SSFF | B40: Dom Party Authentication | C40: =COUNTIF(develop!F40:F980,B40) -> 5 | D40: DOMAIN | E40: mx-api-bc-dom-party-authentication | F40: APIMX000039 | G40: =E40 -> mx-api-bc-dom-party-authentication | H40: =CONCATENATE("https://anypoint.mulesoft.com/exchange/834f46f4-ef08-4c50-81ae-56f917b413cc/", G40) -> https://anypoint.mulesoft.com/exchange/834f46f4-ef08-4c50-81ae-56f917b413cc/mx-api-bc-dom-party-authentication | I40: 1.1.0 | J40: =obtenerRepoMS(E40) -> mx-ms-bc-dom-party-authentication-mule | K40: MuleSoft | L40: dom-party-authentication-api-dev | M40: =generarNombreDeploy(J40) -> dom-party-authentication-api-dev | N40: =validateAPIName(M40,D40) -> Valid | O40: =LEN(M40) -> 32
A41: SSFF | B41: Dom Party Lifecycle Management | C41: =COUNTIF(develop!F41:F980,B41) -> 52 | D41: DOMAIN | E41: mx-api-bc-dom-party-lifecycle-management | F41: APIMX000040 | G41: =E41 -> mx-api-bc-dom-party-lifecycle-management | H41: =CONCATENATE("https://anypoint.mulesoft.com/exchange/834f46f4-ef08-4c50-81ae-56f917b413cc/", G41) -> https://anypoint.mulesoft.com/exchange/834f46f4-ef08-4c50-81ae-56f917b413cc/mx-api-bc-dom-party-lifecycle-management | I41: 2.2.2 | J41: =obtenerRepoMS(E41) -> mx-ms-bc-dom-party-lifecycle-management-mule | K41: MuleSoft | L41: dom-party-lifecycle-management-api-dev | M41: =generarNombreDeploy(J41) -> dom-party-lifecycle-management-api-dev | N41: =validateAPIName(M41,D41) -> Valid | O41: =LEN(M41) -> 38
A42: SSFF | B42: Dom Party Reference Data Directory | C42: =COUNTIF(develop!F42:F980,B42) -> 28 | D42: DOMAIN | E42: mx-api-bc-dom-party-reference-data-directory | F42: APIMX000041 | G42: =E42 -> mx-api-bc-dom-party-reference-data-directory | H42: =CONCATENATE("https://anypoint.mulesoft.com/exchange/834f46f4-ef08-4c50-81ae-56f917b413cc/", G42) -> https://anypoint.mulesoft.com/exchange/834f46f4-ef08-4c50-81ae-56f917b413cc/mx-api-bc-dom-party-reference-data-directory | I42: 1.7.2 | J42: =obtenerRepoMS(E42) -> mx-ms-bc-dom-party-reference-data-directory-mule | K42: MuleSoft | L42: dom-party-reference-data-directory-api-dev | M42: =generarNombreDeploy(J42) -> dom-party-reference-data-directory-api-dev | N42: =validateAPIName(M42,D42) -> Valid | O42: =LEN(M42) -> 42
A43: SSFF | B43: Dom Party Retail Reference Data Directory | C43: =COUNTIF(develop!F43:F980,B43) -> 6 | D43: DOMAIN | E43: mx-api-cpp-dom-party-retail-reference-data-directory | F43: APIMX000042 | G43: =E43 -> mx-api-cpp-dom-party-retail-reference-data-directory | H43: =CONCATENATE("https://anypoint.mulesoft.com/exchange/834f46f4-ef08-4c50-81ae-56f917b413cc/", G43) -> https://anypoint.mulesoft.com/exchange/834f46f4-ef08-4c50-81ae-56f917b413cc/mx-api-cpp-dom-party-retail-reference-data-directory | I43: 1.1.0 | J43: mx-ms-cpp-dom-party-retail-reference-data-directory-mule | K43: MuleSoft | L43: d-party-r-reference-data-directory-dev | M43: d-party-r-reference-data-directory-dev | N43: =validateAPIName(M43,D43) -> Valid | O43: =LEN(M43) -> 38
A44: SSFF | B44: Dom Payment Execution | C44: =COUNTIF(develop!F44:F980,B44) -> 7 | D44: DOMAIN | E44: mx-api-bc-dom-payment-execution | F44: APIMX000043 | G44: =E44 -> mx-api-bc-dom-payment-execution | H44: =CONCATENATE("https://anypoint.mulesoft.com/exchange/834f46f4-ef08-4c50-81ae-56f917b413cc/", G44) -> https://anypoint.mulesoft.com/exchange/834f46f4-ef08-4c50-81ae-56f917b413cc/mx-api-bc-dom-payment-execution | I44: 1.1.2 | J44: =obtenerRepoMS(E44) -> mx-ms-bc-dom-payment-execution-mule | K44: MuleSoft | L44: =IFERROR(__xludf.DUMMYFUNCTION("REGEXREPLACE(REGEXREPLACE(REGEXREPLACE(J44, ""mx-ms-bc-"", """"), ""-mule"", ""-api-dev""), ""-apigee"", ""-api-dev"")"),"dom-payment-execution-api-dev") -> dom-payment-execution-api-dev | M44: =generarNombreDeploy(J44) -> dom-payment-execution-api-dev | N44: =validateAPIName(M44,D44) -> Valid | O44: =LEN(M44) -> 29
A45: SSFF | B45: Dom Payment Order | C45: =COUNTIF(develop!F45:F980,B45) -> 11 | D45: DOMAIN | E45: mx-api-bc-dom-payment-order | F45: APIMX000044 | G45: =E45 -> mx-api-bc-dom-payment-order | H45: =CONCATENATE("https://anypoint.mulesoft.com/exchange/834f46f4-ef08-4c50-81ae-56f917b413cc/", G45) -> https://anypoint.mulesoft.com/exchange/834f46f4-ef08-4c50-81ae-56f917b413cc/mx-api-bc-dom-payment-order | I45: 1.1.0 | J45: =obtenerRepoMS(E45) -> mx-ms-bc-dom-payment-order-mule | K45: MuleSoft | L45: =IFERROR(__xludf.DUMMYFUNCTION("REGEXREPLACE(REGEXREPLACE(REGEXREPLACE(J45, ""mx-ms-bc-"", """"), ""-mule"", ""-api-dev""), ""-apigee"", ""-api-dev"")"),"dom-payment-order-api-dev") -> dom-payment-order-api-dev | M45: =generarNombreDeploy(J45) -> dom-payment-order-api-dev | N45: =validateAPIName(M45,D45) -> Valid | O45: =LEN(M45) -> 25
A46: SSFF | B46: Dom Payment Rail Operations | C46: =COUNTIF(develop!F46:F980,B46) -> 1 | D46: DOMAIN | E46: mx-api-bc-dom-payment-rail-operations | F46: APIMX000045 | G46: =E46 -> mx-api-bc-dom-payment-rail-operations | H46: =CONCATENATE("https://anypoint.mulesoft.com/exchange/834f46f4-ef08-4c50-81ae-56f917b413cc/", G46) -> https://anypoint.mulesoft.com/exchange/834f46f4-ef08-4c50-81ae-56f917b413cc/mx-api-bc-dom-payment-rail-operations | I46: 1.0.0 | J46: =obtenerRepoMS(E46) -> mx-ms-bc-dom-payment-rail-operations-mule | K46: MuleSoft | L46: =IFERROR(__xludf.DUMMYFUNCTION("REGEXREPLACE(REGEXREPLACE(REGEXREPLACE(J46, ""mx-ms-bc-"", """"), ""-mule"", ""-api-dev""), ""-apigee"", ""-api-dev"")"),"dom-payment-rail-operations-api-dev") -> dom-payment-rail-operations-api-dev | M46: =generarNombreDeploy(J46) -> dom-payment-rail-operations-api-dev | N46: =validateAPIName(M46,D46) -> Valid | O46: =LEN(M46) -> 35
A47: SSFF | B47: Dom Platform Operations | C47: =COUNTIF(develop!F47:F980,B47) -> 3 | D47: DOMAIN | E47: mx-api-bc-dom-platform-operations | F47: APIMX000046 | G47: =E47 -> mx-api-bc-dom-platform-operations | H47: =CONCATENATE("https://anypoint.mulesoft.com/exchange/834f46f4-ef08-4c50-81ae-56f917b413cc/", G47) -> https://anypoint.mulesoft.com/exchange/834f46f4-ef08-4c50-81ae-56f917b413cc/mx-api-bc-dom-platform-operations | I47: 1.0.0 | J47: =obtenerRepoMS(E47) -> mx-ms-bc-dom-platform-operations-mule | K47: MuleSoft | L47: =IFERROR(__xludf.DUMMYFUNCTION("REGEXREPLACE(REGEXREPLACE(REGEXREPLACE(J47, ""mx-ms-bc-"", """"), ""-mule"", ""-api-dev""), ""-apigee"", ""-api-dev"")"),"dom-platform-operations-api-dev") -> dom-platform-operations-api-dev | M47: =generarNombreDeploy(J47) -> dom-platform-operations-api-dev | N47: =validateAPIName(M47,D47) -> Valid | O47: =LEN(M47) -> 31
A48: SSFF | B48: Dom Position Keeping | C48: =COUNTIF(develop!F48:F980,B48) -> 3 | D48: DOMAIN | E48: mx-api-bc-dom-position-keeping | F48: APIMX000047 | G48: =E48 -> mx-api-bc-dom-position-keeping | H48: =CONCATENATE("https://anypoint.mulesoft.com/exchange/834f46f4-ef08-4c50-81ae-56f917b413cc/", G48) -> https://anypoint.mulesoft.com/exchange/834f46f4-ef08-4c50-81ae-56f917b413cc/mx-api-bc-dom-position-keeping | I48: 1.1.0 | J48: =obtenerRepoMS(E48) -> mx-ms-bc-dom-position-keeping-mule | K48: MuleSoft | L48: =IFERROR(__xludf.DUMMYFUNCTION("REGEXREPLACE(REGEXREPLACE(REGEXREPLACE(J48, ""mx-ms-bc-"", """"), ""-mule"", ""-api-dev""), ""-apigee"", ""-api-dev"")"),"dom-position-keeping-api-dev") -> dom-position-keeping-api-dev | M48: =generarNombreDeploy(J48) -> dom-position-keeping-api-dev | N48: =validateAPIName(M48,D48) -> Valid | O48: =LEN(M48) -> 28
A49: SSFF | B49: Dom Product Directory | C49: =COUNTIF(develop!F49:F980,B49) -> 4 | D49: DOMAIN | E49: mx-api-bc-dom-product-directory | F49: APIMX000048 | G49: =E49 -> mx-api-bc-dom-product-directory | H49: =CONCATENATE("https://anypoint.mulesoft.com/exchange/834f46f4-ef08-4c50-81ae-56f917b413cc/", G49) -> https://anypoint.mulesoft.com/exchange/834f46f4-ef08-4c50-81ae-56f917b413cc/mx-api-bc-dom-product-directory | I49: 1.0.0 | J49: =obtenerRepoMS(E49) -> mx-ms-bc-dom-product-directory-mule | K49: MuleSoft | L49: =IFERROR(__xludf.DUMMYFUNCTION("REGEXREPLACE(REGEXREPLACE(REGEXREPLACE(J49, ""mx-ms-bc-"", """"), ""-mule"", ""-api-dev""), ""-apigee"", ""-api-dev"")"),"dom-product-directory-api-dev") -> dom-product-directory-api-dev | M49: =generarNombreDeploy(J49) -> dom-product-directory-api-dev | N49: =validateAPIName(M49,D49) -> Valid | O49: =LEN(M49) -> 29
A50: SSFF | B50: Dom Product Matching | C50: =COUNTIF(develop!F50:F980,B50) -> 11 | D50: DOMAIN | E50: mx-api-bc-dom-product-matching | F50: APIMX000049 | G50: =E50 -> mx-api-bc-dom-product-matching | H50: =CONCATENATE("https://anypoint.mulesoft.com/exchange/834f46f4-ef08-4c50-81ae-56f917b413cc/", G50) -> https://anypoint.mulesoft.com/exchange/834f46f4-ef08-4c50-81ae-56f917b413cc/mx-api-bc-dom-product-matching | I50: 1.0.0 | J50: =obtenerRepoMS(E50) -> mx-ms-bc-dom-product-matching-mule | K50: MuleSoft | L50: =IFERROR(__xludf.DUMMYFUNCTION("REGEXREPLACE(REGEXREPLACE(REGEXREPLACE(J50, ""mx-ms-bc-"", """"), ""-mule"", ""-api-dev""), ""-apigee"", ""-api-dev"")"),"dom-product-matching-api-dev") -> dom-product-matching-api-dev | M50: =generarNombreDeploy(J50) -> dom-product-matching-api-dev | N50: =validateAPIName(M50,D50) -> Valid | O50: =LEN(M50) -> 28
A51: SSFF | B51: Dom Regulatory Compliance | C51: =COUNTIF(develop!F51:F980,B51) -> 1 | D51: DOMAIN | E51: mx-api-bc-dom-regulatory-compliance | F51: APIMX000050 | G51: =E51 -> mx-api-bc-dom-regulatory-compliance | H51: =CONCATENATE("https://anypoint.mulesoft.com/exchange/834f46f4-ef08-4c50-81ae-56f917b413cc/", G51) -> https://anypoint.mulesoft.com/exchange/834f46f4-ef08-4c50-81ae-56f917b413cc/mx-api-bc-dom-regulatory-compliance | I51: 1.0.0 | J51: =obtenerRepoMS(E51) -> mx-ms-bc-dom-regulatory-compliance-mule | K51: MuleSoft | L51: =IFERROR(__xludf.DUMMYFUNCTION("REGEXREPLACE(REGEXREPLACE(REGEXREPLACE(J51, ""mx-ms-bc-"", """"), ""-mule"", ""-api-dev""), ""-apigee"", ""-api-dev"")"),"dom-regulatory-compliance-api-dev") -> dom-regulatory-compliance-api-dev | M51: =generarNombreDeploy(J51) -> dom-regulatory-compliance-api-dev | N51: =validateAPIName(M51,D51) -> Valid | O51: =LEN(M51) -> 33
A52: SSFF | B52: Dom Remittances | C52: =COUNTIF(develop!F52:F980,B52) -> 1 | D52: DOMAIN | E52: mx-api-bc-dom-remittances | F52: APIMX000051 | G52: =E52 -> mx-api-bc-dom-remittances | H52: =CONCATENATE("https://anypoint.mulesoft.com/exchange/834f46f4-ef08-4c50-81ae-56f917b413cc/", G52) -> https://anypoint.mulesoft.com/exchange/834f46f4-ef08-4c50-81ae-56f917b413cc/mx-api-bc-dom-remittances | I52: 1.0.0 | J52: =obtenerRepoMS(E52) -> mx-ms-bc-dom-remittances-mule | K52: MuleSoft | L52: =IFERROR(__xludf.DUMMYFUNCTION("REGEXREPLACE(REGEXREPLACE(REGEXREPLACE(J52, ""mx-ms-bc-"", """"), ""-mule"", ""-api-dev""), ""-apigee"", ""-api-dev"")"),"dom-remittances-api-dev") -> dom-remittances-api-dev | M52: =generarNombreDeploy(J52) -> dom-remittances-api-dev | N52: =validateAPIName(M52,D52) -> Valid | O52: =LEN(M52) -> 23
A53: SSFF | B53: Dom Sales Product Agreement | C53: =COUNTIF(develop!F53:F980,B53) -> 3 | D53: DOMAIN | E53: mx-api-bc-dom-sales-product-agreement | F53: APIMX000052 | G53: =E53 -> mx-api-bc-dom-sales-product-agreement | H53: =CONCATENATE("https://anypoint.mulesoft.com/exchange/834f46f4-ef08-4c50-81ae-56f917b413cc/", G53) -> https://anypoint.mulesoft.com/exchange/834f46f4-ef08-4c50-81ae-56f917b413cc/mx-api-bc-dom-sales-product-agreement | I53: 1.0.0 | J53: =obtenerRepoMS(E53) -> mx-ms-bc-dom-sales-product-agreement-mule | K53: MuleSoft | L53: =IFERROR(__xludf.DUMMYFUNCTION("REGEXREPLACE(REGEXREPLACE(REGEXREPLACE(J53, ""mx-ms-bc-"", """"), ""-mule"", ""-api-dev""), ""-apigee"", ""-api-dev"")"),"dom-sales-product-agreement-api-dev") -> dom-sales-product-agreement-api-dev | M53: =generarNombreDeploy(J53) -> dom-sales-product-agreement-api-dev | N53: =validateAPIName(M53,D53) -> Valid | O53: =LEN(M53) -> 35
A54: SSFF | B54: Dom Savings Account | C54: =COUNTIF(develop!F54:F980,B54) -> 3 | D54: DOMAIN | E54: mx-api-bc-dom-savings-account | F54: APIMX000053 | G54: =E54 -> mx-api-bc-dom-savings-account | H54: =CONCATENATE("https://anypoint.mulesoft.com/exchange/834f46f4-ef08-4c50-81ae-56f917b413cc/", G54) -> https://anypoint.mulesoft.com/exchange/834f46f4-ef08-4c50-81ae-56f917b413cc/mx-api-bc-dom-savings-account | I54: 1.0.0 | J54: =obtenerRepoMS(E54) -> mx-ms-bc-dom-savings-account-mule | K54: MuleSoft | L54: =IFERROR(__xludf.DUMMYFUNCTION("REGEXREPLACE(REGEXREPLACE(REGEXREPLACE(J54, ""mx-ms-bc-"", """"), ""-mule"", ""-api-dev""), ""-apigee"", ""-api-dev"")"),"dom-savings-account-api-dev") -> dom-savings-account-api-dev | M54: =generarNombreDeploy(J54) -> dom-savings-account-api-dev | N54: =validateAPIName(M54,D54) -> Valid | O54: =LEN(M54) -> 27
A55: SSFF | B55: Dom Servicing Order | C55: =COUNTIF(develop!F55:F980,B55) -> 1 | D55: DOMAIN | E55: mx-api-bc-dom-servicing-order | F55: APIMX000054 | G55: =E55 -> mx-api-bc-dom-servicing-order | H55: =CONCATENATE("https://anypoint.mulesoft.com/exchange/834f46f4-ef08-4c50-81ae-56f917b413cc/", G55) -> https://anypoint.mulesoft.com/exchange/834f46f4-ef08-4c50-81ae-56f917b413cc/mx-api-bc-dom-servicing-order | I55: 1.0.0 | J55: =obtenerRepoMS(E55) -> mx-ms-bc-dom-servicing-order-mule | K55: MuleSoft | L55: =IFERROR(__xludf.DUMMYFUNCTION("REGEXREPLACE(REGEXREPLACE(REGEXREPLACE(J55, ""mx-ms-bc-"", """"), ""-mule"", ""-api-dev""), ""-apigee"", ""-api-dev"")"),"dom-servicing-order-api-dev") -> dom-servicing-order-api-dev | M55: =generarNombreDeploy(J55) -> dom-servicing-order-api-dev | N55: =validateAPIName(M55,D55) -> Valid | O55: =LEN(M55) -> 27
A56: SSFF | B56: Dom Session Dialogue | C56: =COUNTIF(develop!F56:F980,B56) -> 9 | D56: DOMAIN | E56: mx-api-bc-dom-session-dialogue | F56: APIMX000055 | G56: =E56 -> mx-api-bc-dom-session-dialogue | H56: =CONCATENATE("https://anypoint.mulesoft.com/exchange/834f46f4-ef08-4c50-81ae-56f917b413cc/", G56) -> https://anypoint.mulesoft.com/exchange/834f46f4-ef08-4c50-81ae-56f917b413cc/mx-api-bc-dom-session-dialogue | I56: 1.1.0 | J56: =obtenerRepoMS(E56) -> mx-ms-bc-dom-session-dialogue-mule | K56: MuleSoft | L56: dom-session-dialogue-api-dev | M56: =generarNombreDeploy(J56) -> dom-session-dialogue-api-dev | N56: =validateAPIName(M56,D56) -> Valid | O56: =LEN(M56) -> 28
A57: SSFF | B57: Dom Systems Operations | C57: =COUNTIF(develop!F57:F980,B57) -> 3 | D57: DOMAIN | E57: mx-api-bc-dom-systems-operations | F57: APIMX000056 | G57: =E57 -> mx-api-bc-dom-systems-operations | H57: =CONCATENATE("https://anypoint.mulesoft.com/exchange/834f46f4-ef08-4c50-81ae-56f917b413cc/", G57) -> https://anypoint.mulesoft.com/exchange/834f46f4-ef08-4c50-81ae-56f917b413cc/mx-api-bc-dom-systems-operations | I57: 1.0.0 | J57: =obtenerRepoMS(E57) -> mx-ms-bc-dom-systems-operations-mule | K57: MuleSoft | L57: =IFERROR(__xludf.DUMMYFUNCTION("REGEXREPLACE(REGEXREPLACE(REGEXREPLACE(J57, ""mx-ms-bc-"", """"), ""-mule"", ""-api-dev""), ""-apigee"", ""-api-dev"")"),"dom-systems-operations-api-dev") -> dom-systems-operations-api-dev | M57: =generarNombreDeploy(J57) -> dom-systems-operations-api-dev | N57: =validateAPIName(M57,D57) -> Valid | O57: =LEN(M57) -> 30
A58: SSFF | B58: Dom Transaction Engine | C58: =COUNTIF(develop!F58:F980,B58) -> 3 | D58: DOMAIN | E58: mx-api-bc-dom-transaction-engine | F58: APIMX000057 | G58: =E58 -> mx-api-bc-dom-transaction-engine | H58: =CONCATENATE("https://anypoint.mulesoft.com/exchange/834f46f4-ef08-4c50-81ae-56f917b413cc/", G58) -> https://anypoint.mulesoft.com/exchange/834f46f4-ef08-4c50-81ae-56f917b413cc/mx-api-bc-dom-transaction-engine | I58: 1.0.0 | J58: =obtenerRepoMS(E58) -> mx-ms-bc-dom-transaction-engine-mule | K58: MuleSoft | L58: =IFERROR(__xludf.DUMMYFUNCTION("REGEXREPLACE(REGEXREPLACE(REGEXREPLACE(J58, ""mx-ms-bc-"", """"), ""-mule"", ""-api-dev""), ""-apigee"", ""-api-dev"")"),"dom-transaction-engine-api-dev") -> dom-transaction-engine-api-dev | M58: =generarNombreDeploy(J58) -> dom-transaction-engine-api-dev | N58: =validateAPIName(M58,D58) -> Valid | O58: =LEN(M58) -> 30
A59: SSFF | B59: Dom Utility | C59: =COUNTIF(develop!F59:F980,B59) -> 14 | D59: DOMAIN | E59: mx-api-bc-dom-utility | F59: APIMX000058 | G59: =E59 -> mx-api-bc-dom-utility | H59: =CONCATENATE("https://anypoint.mulesoft.com/exchange/834f46f4-ef08-4c50-81ae-56f917b413cc/", G59) -> https://anypoint.mulesoft.com/exchange/834f46f4-ef08-4c50-81ae-56f917b413cc/mx-api-bc-dom-utility | I59: 1.1.0 | J59: =obtenerRepoMS(E59) -> mx-ms-bc-dom-utility-mule | K59: MuleSoft | L59: =IFERROR(__xludf.DUMMYFUNCTION("REGEXREPLACE(REGEXREPLACE(REGEXREPLACE(J59, ""mx-ms-bc-"", """"), ""-mule"", ""-api-dev""), ""-apigee"", ""-api-dev"")"),"dom-utility-api-dev") -> dom-utility-api-dev | M59: =generarNombreDeploy(J59) -> dom-utility-api-dev | N59: =validateAPIName(M59,D59) -> Valid | O59: =LEN(M59) -> 19
A60: SSFF | B60: Pro Account Reconciliation | C60: =COUNTIF(develop!F60:F980,B60) -> 1 | D60: PROXY | E60: mx-api-bc-pro-account-reconciliation | F60: APIMX000059 | G60: =E60 -> mx-api-bc-pro-account-reconciliation | H60: =CONCATENATE("https://anypoint.mulesoft.com/exchange/834f46f4-ef08-4c50-81ae-56f917b413cc/", G60) -> https://anypoint.mulesoft.com/exchange/834f46f4-ef08-4c50-81ae-56f917b413cc/mx-api-bc-pro-account-reconciliation | I60: 1.0.0 | J60: =obtenerRepoMS(E60) -> mx-ms-bc-pro-account-reconciliation | K60: EKS | L60: =IFERROR(__xludf.DUMMYFUNCTION("REGEXREPLACE(REGEXREPLACE(REGEXREPLACE(J60, ""mx-ms-bc-"", """"), ""-mule"", ""-api-dev""), ""-apigee"", ""-api-dev"")"),"pro-account-reconciliation") -> pro-account-reconciliation | M60: =generarNombreDeploy(J60) -> mx-ms-bc-pro-account-reconciliation | N60: =validateAPIName(M60,D60) -> Valid | O60: =LEN(M60) -> 35
A61: SSFF | B61: Pro Branch Location Operations | C61: =COUNTIF(develop!F61:F980,B61) -> 2 | D61: PROXY | E61: mx-api-bc-pro-branch-location-operations | F61: APIMX000060 | G61: =E61 -> mx-api-bc-pro-branch-location-operations | H61: =CONCATENATE("https://anypoint.mulesoft.com/exchange/834f46f4-ef08-4c50-81ae-56f917b413cc/", G61) -> https://anypoint.mulesoft.com/exchange/834f46f4-ef08-4c50-81ae-56f917b413cc/mx-api-bc-pro-branch-location-operations | I61: 1.2.0 | J61: =obtenerRepoMS(E61) -> mx-ms-bc-pro-branch-location-operations | K61: EKS | L61: =IFERROR(__xludf.DUMMYFUNCTION("REGEXREPLACE(REGEXREPLACE(REGEXREPLACE(J61, ""mx-ms-bc-"", """"), ""-mule"", ""-api-dev""), ""-apigee"", ""-api-dev"")"),"pro-branch-location-operations") -> pro-branch-location-operations | M61: =generarNombreDeploy(J61) -> mx-ms-bc-pro-branch-location-operations | N61: =validateAPIName(M61,D61) -> Valid | O61: =LEN(M61) -> 39
A62: SSFF | B62: Pro Branch Network Management | C62: =COUNTIF(develop!F62:F980,B62) -> 1 | D62: PROXY | E62: mx-api-bc-pro-branch-network-management | F62: APIMX000061 | G62: =E62 -> mx-api-bc-pro-branch-network-management | H62: =CONCATENATE("https://anypoint.mulesoft.com/exchange/834f46f4-ef08-4c50-81ae-56f917b413cc/", G62) -> https://anypoint.mulesoft.com/exchange/834f46f4-ef08-4c50-81ae-56f917b413cc/mx-api-bc-pro-branch-network-management | I62: 1.1.0 | J62: =obtenerRepoMS(E62) -> mx-ms-bc-pro-branch-network-management | K62: EKS | L62: =IFERROR(__xludf.DUMMYFUNCTION("REGEXREPLACE(REGEXREPLACE(REGEXREPLACE(J62, ""mx-ms-bc-"", """"), ""-mule"", ""-api-dev""), ""-apigee"", ""-api-dev"")"),"pro-branch-network-management") -> pro-branch-network-management | M62: =generarNombreDeploy(J62) -> mx-ms-bc-pro-branch-network-management | N62: =validateAPIName(M62,D62) -> Valid | O62: =LEN(M62) -> 38
A63: SSFF | B63: Pro Card eCommerce Gateway | C63: =COUNTIF(develop!F63:F980,B63) -> 1 | D63: PROXY | E63: mx-api-bc-pro-card-ecommerce-gateway | F63: APIMX000062 | G63: =E63 -> mx-api-bc-pro-card-ecommerce-gateway | H63: =CONCATENATE("https://anypoint.mulesoft.com/exchange/834f46f4-ef08-4c50-81ae-56f917b413cc/", G63) -> https://anypoint.mulesoft.com/exchange/834f46f4-ef08-4c50-81ae-56f917b413cc/mx-api-bc-pro-card-ecommerce-gateway | I63: 1.0.0 | J63: =obtenerRepoMS(E63) -> mx-ms-bc-pro-card-ecommerce-gateway | K63: EKS | L63: =IFERROR(__xludf.DUMMYFUNCTION("REGEXREPLACE(REGEXREPLACE(REGEXREPLACE(J63, ""mx-ms-bc-"", """"), ""-mule"", ""-api-dev""), ""-apigee"", ""-api-dev"")"),"pro-card-ecommerce-gateway") -> pro-card-ecommerce-gateway | M63: =generarNombreDeploy(J63) -> mx-ms-bc-pro-card-ecommerce-gateway | N63: =validateAPIName(M63,D63) -> Valid | O63: =LEN(M63) -> 35
A64: SSFF | B64: Pro Cash Management And Account Services | C64: =COUNTIF(develop!F64:F980,B64) -> 1 | D64: PROXY | E64: mx-api-bc-pro-cash-management-and-account-services | F64: APIMX000063 | G64: =E64 -> mx-api-bc-pro-cash-management-and-account-services | H64: =CONCATENATE("https://anypoint.mulesoft.com/exchange/834f46f4-ef08-4c50-81ae-56f917b413cc/", G64) -> https://anypoint.mulesoft.com/exchange/834f46f4-ef08-4c50-81ae-56f917b413cc/mx-api-bc-pro-cash-management-and-account-services | I64: 1.0.0 | J64: =obtenerRepoMS(E64) -> mx-ms-bc-pro-cash-management-and-account-services | K64: EKS | L64: =IFERROR(__xludf.DUMMYFUNCTION("REGEXREPLACE(REGEXREPLACE(REGEXREPLACE(J64, ""mx-ms-bc-"", """"), ""-mule"", ""-api-dev""), ""-apigee"", ""-api-dev"")"),"pro-cash-management-and-account-services") -> pro-cash-management-and-account-services | M64: =generarNombreDeploy(J64) -> mx-ms-bc-pro-cash-management-and-account-services | N64: =validateAPIName(M64,D64) -> Valid | O64: =LEN(M64) -> 49
A65: SSFF | B65: Pro Cheque Processing | C65: =COUNTIF(develop!F65:F980,B65) -> 1 | D65: PROXY | E65: mx-api-bc-pro-cheque-processing | F65: APIMX000064 | G65: =E65 -> mx-api-bc-pro-cheque-processing | H65: =CONCATENATE("https://anypoint.mulesoft.com/exchange/834f46f4-ef08-4c50-81ae-56f917b413cc/", G65) -> https://anypoint.mulesoft.com/exchange/834f46f4-ef08-4c50-81ae-56f917b413cc/mx-api-bc-pro-cheque-processing | I65: 1.0.0 | J65: =obtenerRepoMS(E65) -> mx-ms-bc-pro-cheque-processing | K65: EKS | L65: =IFERROR(__xludf.DUMMYFUNCTION("REGEXREPLACE(REGEXREPLACE(REGEXREPLACE(J65, ""mx-ms-bc-"", """"), ""-mule"", ""-api-dev""), ""-apigee"", ""-api-dev"")"),"pro-cheque-processing") -> pro-cheque-processing | M65: =generarNombreDeploy(J65) -> mx-ms-bc-pro-cheque-processing | N65: =validateAPIName(M65,D65) -> Valid | O65: =LEN(M65) -> 30
A66: SSFF | B66: Pro Corporate Current Account | C66: =COUNTIF(develop!F66:F980,B66) -> 1 | D66: PROXY | E66: mx-api-bc-pro-corporate-current-account | F66: APIMX000065 | G66: =E66 -> mx-api-bc-pro-corporate-current-account | H66: =CONCATENATE("https://anypoint.mulesoft.com/exchange/834f46f4-ef08-4c50-81ae-56f917b413cc/", G66) -> https://anypoint.mulesoft.com/exchange/834f46f4-ef08-4c50-81ae-56f917b413cc/mx-api-bc-pro-corporate-current-account | I66: 1.1.0 | J66: =obtenerRepoMS(E66) -> mx-ms-bc-pro-corporate-current-account | K66: EKS | L66: =IFERROR(__xludf.DUMMYFUNCTION("REGEXREPLACE(REGEXREPLACE(REGEXREPLACE(J66, ""mx-ms-bc-"", """"), ""-mule"", ""-api-dev""), ""-apigee"", ""-api-dev"")"),"pro-corporate-current-account") -> pro-corporate-current-account | M66: =generarNombreDeploy(J66) -> mx-ms-bc-pro-corporate-current-account | N66: =validateAPIName(M66,D66) -> Valid | O66: =LEN(M66) -> 38
A67: SSFF | B67: Pro Correspondence | C67: =COUNTIF(develop!F67:F980,B67) -> 1 | D67: PROXY | E67: mx-api-bc-pro-correspondence | F67: APIMX000066 | G67: =E67 -> mx-api-bc-pro-correspondence | H67: =CONCATENATE("https://anypoint.mulesoft.com/exchange/834f46f4-ef08-4c50-81ae-56f917b413cc/", G67) -> https://anypoint.mulesoft.com/exchange/834f46f4-ef08-4c50-81ae-56f917b413cc/mx-api-bc-pro-correspondence | I67: 1.0.0 | J67: =obtenerRepoMS(E67) -> mx-ms-bc-pro-correspondence | K67: EKS | L67: =IFERROR(__xludf.DUMMYFUNCTION("REGEXREPLACE(REGEXREPLACE(REGEXREPLACE(J67, ""mx-ms-bc-"", """"), ""-mule"", ""-api-dev""), ""-apigee"", ""-api-dev"")"),"pro-correspondence") -> pro-correspondence | M67: =generarNombreDeploy(J67) -> mx-ms-bc-pro-correspondence | N67: =validateAPIName(M67,D67) -> Valid | O67: =LEN(M67) -> 27
A68: SSFF | B68: Pro Counterparty Risk | C68: =COUNTIF(develop!F68:F980,B68) -> 15 | D68: PROXY | E68: mx-api-bc-pro-counterparty-risk | F68: APIMX000067 | G68: =E68 -> mx-api-bc-pro-counterparty-risk | H68: =CONCATENATE("https://anypoint.mulesoft.com/exchange/834f46f4-ef08-4c50-81ae-56f917b413cc/", G68) -> https://anypoint.mulesoft.com/exchange/834f46f4-ef08-4c50-81ae-56f917b413cc/mx-api-bc-pro-counterparty-risk | I68: 1.2.0 | J68: =obtenerRepoMS(E68) -> mx-ms-bc-pro-counterparty-risk | K68: EKS | L68: =IFERROR(__xludf.DUMMYFUNCTION("REGEXREPLACE(REGEXREPLACE(REGEXREPLACE(J68, ""mx-ms-bc-"", """"), ""-mule"", ""-api-dev""), ""-apigee"", ""-api-dev"")"),"pro-counterparty-risk") -> pro-counterparty-risk | M68: =generarNombreDeploy(J68) -> mx-ms-bc-pro-counterparty-risk | N68: =validateAPIName(M68,D68) -> Valid | O68: =LEN(M68) -> 30
A69: SSFF | B69: Pro Credit Card | C69: =COUNTIF(develop!F69:F980,B69) -> 55 | D69: PROXY | E69: mx-api-bc-pro-credit-card | F69: APIMX000068 | G69: =E69 -> mx-api-bc-pro-credit-card | H69: =CONCATENATE("https://anypoint.mulesoft.com/exchange/834f46f4-ef08-4c50-81ae-56f917b413cc/", G69) -> https://anypoint.mulesoft.com/exchange/834f46f4-ef08-4c50-81ae-56f917b413cc/mx-api-bc-pro-credit-card | I69: 1.31.0 | J69: =obtenerRepoMS(E69) -> mx-ms-bc-pro-credit-card | K69: EKS | L69: =IFERROR(__xludf.DUMMYFUNCTION("REGEXREPLACE(REGEXREPLACE(REGEXREPLACE(J69, ""mx-ms-bc-"", """"), ""-mule"", ""-api-dev""), ""-apigee"", ""-api-dev"")"),"pro-credit-card") -> pro-credit-card | M69: =generarNombreDeploy(J69) -> mx-ms-bc-pro-credit-card | N69: =validateAPIName(M69,D69) -> Valid | O69: =LEN(M69) -> 24
A70: SSFF | B70: Pro Credit Card Position Keeping | C70: =COUNTIF(develop!F70:F980,B70) -> 5 | D70: PROXY | E70: mx-api-bc-pro-credit-card-position-keeping | F70: APIMX000069 | G70: =E70 -> mx-api-bc-pro-credit-card-position-keeping | H70: =CONCATENATE("https://anypoint.mulesoft.com/exchange/834f46f4-ef08-4c50-81ae-56f917b413cc/", G70) -> https://anypoint.mulesoft.com/exchange/834f46f4-ef08-4c50-81ae-56f917b413cc/mx-api-bc-pro-credit-card-position-keeping | I70: 1.5.1 | J70: =obtenerRepoMS(E70) -> mx-ms-bc-pro-credit-card-position-keeping | K70: EKS | L70: =IFERROR(__xludf.DUMMYFUNCTION("REGEXREPLACE(REGEXREPLACE(REGEXREPLACE(J70, ""mx-ms-bc-"", """"), ""-mule"", ""-api-dev""), ""-apigee"", ""-api-dev"")"),"pro-credit-card-position-keeping") -> pro-credit-card-position-keeping | M70: =generarNombreDeploy(J70) -> mx-ms-bc-pro-credit-card-position-keeping | N70: =validateAPIName(M70,D70) -> Valid | O70: =LEN(M70) -> 41
A71: SSFF | B71: Pro Credit Facility | C71: =COUNTIF(develop!F71:F980,B71) -> 2 | D71: PROXY | E71: mx-api-bc-pro-credit-facility | F71: APIMX000070 | G71: =E71 -> mx-api-bc-pro-credit-facility | H71: =CONCATENATE("https://anypoint.mulesoft.com/exchange/834f46f4-ef08-4c50-81ae-56f917b413cc/", G71) -> https://anypoint.mulesoft.com/exchange/834f46f4-ef08-4c50-81ae-56f917b413cc/mx-api-bc-pro-credit-facility | I71: 1.2.1 | J71: =obtenerRepoMS(E71) -> mx-ms-bc-pro-credit-facility | K71: EKS | L71: =IFERROR(__xludf.DUMMYFUNCTION("REGEXREPLACE(REGEXREPLACE(REGEXREPLACE(J71, ""mx-ms-bc-"", """"), ""-mule"", ""-api-dev""), ""-apigee"", ""-api-dev"")"),"pro-credit-facility") -> pro-credit-facility | M71: =generarNombreDeploy(J71) -> mx-ms-bc-pro-credit-facility | N71: =validateAPIName(M71,D71) -> Valid | O71: =LEN(M71) -> 28
A72: SSFF | B72: Pro Currency Exchange | C72: =COUNTIF(develop!F72:F980,B72) -> 1 | D72: PROXY | E72: mx-api-bc-pro-currency-exchange | F72: APIMX000071 | G72: =E72 -> mx-api-bc-pro-currency-exchange | H72: =CONCATENATE("https://anypoint.mulesoft.com/exchange/834f46f4-ef08-4c50-81ae-56f917b413cc/", G72) -> https://anypoint.mulesoft.com/exchange/834f46f4-ef08-4c50-81ae-56f917b413cc/mx-api-bc-pro-currency-exchange | I72: 1.0.0 | J72: =obtenerRepoMS(E72) -> mx-ms-bc-pro-currency-exchange | K72: EKS | L72: =IFERROR(__xludf.DUMMYFUNCTION("REGEXREPLACE(REGEXREPLACE(REGEXREPLACE(J72, ""mx-ms-bc-"", """"), ""-mule"", ""-api-dev""), ""-apigee"", ""-api-dev"")"),"pro-currency-exchange") -> pro-currency-exchange | M72: =generarNombreDeploy(J72) -> mx-ms-bc-pro-currency-exchange | N72: =validateAPIName(M72,D72) -> Valid | O72: =LEN(M72) -> 30
A73: SSFF | B73: Pro Current Account | C73: =COUNTIF(develop!F73:F980,B73) -> 1 | D73: PROXY | E73: mx-api-bc-pro-current-account | F73: APIMX000072 | G73: =E73 -> mx-api-bc-pro-current-account | H73: =CONCATENATE("https://anypoint.mulesoft.com/exchange/834f46f4-ef08-4c50-81ae-56f917b413cc/", G73) -> https://anypoint.mulesoft.com/exchange/834f46f4-ef08-4c50-81ae-56f917b413cc/mx-api-bc-pro-current-account | I73: 1.0.0 | J73: =obtenerRepoMS(E73) -> mx-ms-bc-pro-current-account | K73: EKS | L73: =IFERROR(__xludf.DUMMYFUNCTION("REGEXREPLACE(REGEXREPLACE(REGEXREPLACE(J73, ""mx-ms-bc-"", """"), ""-mule"", ""-api-dev""), ""-apigee"", ""-api-dev"")"),"pro-current-account") -> pro-current-account | M73: =generarNombreDeploy(J73) -> mx-ms-bc-pro-current-account | N73: =validateAPIName(M73,D73) -> Valid | O73: =LEN(M73) -> 28
A74: SSFF | B74: Pro Customer Access Entitlement | C74: =COUNTIF(develop!F74:F980,B74) -> 2 | D74: PROXY | E74: mx-api-bc-pro-customer-access-entitlement | F74: APIMX000073 | G74: =E74 -> mx-api-bc-pro-customer-access-entitlement | H74: =CONCATENATE("https://anypoint.mulesoft.com/exchange/834f46f4-ef08-4c50-81ae-56f917b413cc/", G74) -> https://anypoint.mulesoft.com/exchange/834f46f4-ef08-4c50-81ae-56f917b413cc/mx-api-bc-pro-customer-access-entitlement | I74: 1.2.0 | J74: =obtenerRepoMS(E74) -> mx-ms-bc-pro-customer-access-entitlement | K74: EKS | L74: =IFERROR(__xludf.DUMMYFUNCTION("REGEXREPLACE(REGEXREPLACE(REGEXREPLACE(J74, ""mx-ms-bc-"", """"), ""-mule"", ""-api-dev""), ""-apigee"", ""-api-dev"")"),"pro-customer-access-entitlement") -> pro-customer-access-entitlement | M74: =generarNombreDeploy(J74) -> mx-ms-bc-pro-customer-access-entitlement | N74: =validateAPIName(M74,D74) -> Valid | O74: =LEN(M74) -> 40
A75: SSFF | B75: Pro Customer Agreement | C75: =COUNTIF(develop!F75:F980,B75) -> 6 | D75: PROXY | E75: mx-api-bc-pro-customer-agreement | F75: APIMX000074 | G75: =E75 -> mx-api-bc-pro-customer-agreement | H75: =CONCATENATE("https://anypoint.mulesoft.com/exchange/834f46f4-ef08-4c50-81ae-56f917b413cc/", G75) -> https://anypoint.mulesoft.com/exchange/834f46f4-ef08-4c50-81ae-56f917b413cc/mx-api-bc-pro-customer-agreement | I75: 1.3.0 | J75: =obtenerRepoMS(E75) -> mx-ms-bc-pro-customer-agreement | K75: EKS | L75: =IFERROR(__xludf.DUMMYFUNCTION("REGEXREPLACE(REGEXREPLACE(REGEXREPLACE(J75, ""mx-ms-bc-"", """"), ""-mule"", ""-api-dev""), ""-apigee"", ""-api-dev"")"),"pro-customer-agreement") -> pro-customer-agreement | M75: =generarNombreDeploy(J75) -> mx-ms-bc-pro-customer-agreement | N75: =validateAPIName(M75,D75) -> Valid | O75: =LEN(M75) -> 31
A76: SSFF | B76: Pro Customer Credit Rating | C76: =COUNTIF(develop!F76:F980,B76) -> 17 | D76: PROXY | E76: mx-api-bc-pro-customer-credit-rating | F76: APIMX000075 | G76: =E76 -> mx-api-bc-pro-customer-credit-rating | H76: =CONCATENATE("https://anypoint.mulesoft.com/exchange/834f46f4-ef08-4c50-81ae-56f917b413cc/", G76) -> https://anypoint.mulesoft.com/exchange/834f46f4-ef08-4c50-81ae-56f917b413cc/mx-api-bc-pro-customer-credit-rating | I76: 1.3.1 | J76: =obtenerRepoMS(E76) -> mx-ms-bc-pro-customer-credit-rating | K76: EKS | L76: =IFERROR(__xludf.DUMMYFUNCTION("REGEXREPLACE(REGEXREPLACE(REGEXREPLACE(J76, ""mx-ms-bc-"", """"), ""-mule"", ""-api-dev""), ""-apigee"", ""-api-dev"")"),"pro-customer-credit-rating") -> pro-customer-credit-rating | M76: =generarNombreDeploy(J76) -> mx-ms-bc-pro-customer-credit-rating | N76: =validateAPIName(M76,D76) -> Valid | O76: =LEN(M76) -> 35
A77: SSFF | B77: Pro Customer Offer | C77: =COUNTIF(develop!F77:F980,B77) -> 4 | D77: PROXY | E77: mx-api-bc-pro-customer-offer | F77: APIMX000076 | G77: =E77 -> mx-api-bc-pro-customer-offer | H77: =CONCATENATE("https://anypoint.mulesoft.com/exchange/834f46f4-ef08-4c50-81ae-56f917b413cc/", G77) -> https://anypoint.mulesoft.com/exchange/834f46f4-ef08-4c50-81ae-56f917b413cc/mx-api-bc-pro-customer-offer | I77: 1.0.0 | J77: =obtenerRepoMS(E77) -> mx-ms-bc-pro-customer-offer | K77: EKS | L77: =IFERROR(__xludf.DUMMYFUNCTION("REGEXREPLACE(REGEXREPLACE(REGEXREPLACE(J77, ""mx-ms-bc-"", """"), ""-mule"", ""-api-dev""), ""-apigee"", ""-api-dev"")"),"pro-customer-offer") -> pro-customer-offer | M77: =generarNombreDeploy(J77) -> mx-ms-bc-pro-customer-offer | N77: =validateAPIName(M77,D77) -> Valid | O77: =LEN(M77) -> 27
A78: SSFF | B78: Pro Customer Position | C78: =COUNTIF(develop!F78:F980,B78) -> 7 | D78: PROXY | E78: mx-api-bc-pro-customer-position | F78: APIMX000077 | G78: =E78 -> mx-api-bc-pro-customer-position | H78: =CONCATENATE("https://anypoint.mulesoft.com/exchange/834f46f4-ef08-4c50-81ae-56f917b413cc/", G78) -> https://anypoint.mulesoft.com/exchange/834f46f4-ef08-4c50-81ae-56f917b413cc/mx-api-bc-pro-customer-position | I78: 1.3.0 | J78: =obtenerRepoMS(E78) -> mx-ms-bc-pro-customer-position | K78: EKS | L78: =IFERROR(__xludf.DUMMYFUNCTION("REGEXREPLACE(REGEXREPLACE(REGEXREPLACE(J78, ""mx-ms-bc-"", """"), ""-mule"", ""-api-dev""), ""-apigee"", ""-api-dev"")"),"pro-customer-position") -> pro-customer-position | M78: =generarNombreDeploy(J78) -> mx-ms-bc-pro-customer-position | N78: =validateAPIName(M78,D78) -> Valid | O78: =LEN(M78) -> 30
A79: SSFF | B79: Pro Customer Product And Service Eligibility | C79: =COUNTIF(develop!F79:F980,B79) -> 4 | D79: PROXY | E79: mx-api-bc-pro-customer-product-and-service-eligibility | F79: APIMX000078 | G79: =E79 -> mx-api-bc-pro-customer-product-and-service-eligibility | H79: =CONCATENATE("https://anypoint.mulesoft.com/exchange/834f46f4-ef08-4c50-81ae-56f917b413cc/", G79) -> https://anypoint.mulesoft.com/exchange/834f46f4-ef08-4c50-81ae-56f917b413cc/mx-api-bc-pro-customer-product-and-service-eligibility | I79: 1.1.0 | J79: =obtenerRepoMS(E79) -> mx-ms-bc-pro-customer-product-and-service-eligibility | K79: EKS | L79: =IFERROR(__xludf.DUMMYFUNCTION("REGEXREPLACE(REGEXREPLACE(REGEXREPLACE(J79, ""mx-ms-bc-"", """"), ""-mule"", ""-api-dev""), ""-apigee"", ""-api-dev"")"),"pro-customer-product-and-service-eligibility") -> pro-customer-product-and-service-eligibility | M79: =generarNombreDeploy(J79) -> mx-ms-bc-pro-customer-product-and-service-eligibility | N79: =validateAPIName(M79,D79) -> Valid | O79: =LEN(M79) -> 53
A80: SSFF | B80: Pro Customer Products And Services | C80: =COUNTIF(develop!F80:F980,B80) -> 16 | D80: PROXY | E80: mx-api-bc-pro-customer-products-and-services | F80: APIMX000079 | G80: =E80 -> mx-api-bc-pro-customer-products-and-services | H80: =CONCATENATE("https://anypoint.mulesoft.com/exchange/834f46f4-ef08-4c50-81ae-56f917b413cc/", G80) -> https://anypoint.mulesoft.com/exchange/834f46f4-ef08-4c50-81ae-56f917b413cc/mx-api-bc-pro-customer-products-and-services | I80: 1.2.0 | J80: =obtenerRepoMS(E80) -> mx-ms-bc-pro-customer-products-and-services | K80: EKS | L80: =IFERROR(__xludf.DUMMYFUNCTION("REGEXREPLACE(REGEXREPLACE(REGEXREPLACE(J80, ""mx-ms-bc-"", """"), ""-mule"", ""-api-dev""), ""-apigee"", ""-api-dev"")"),"pro-customer-products-and-services") -> pro-customer-products-and-services | M80: =generarNombreDeploy(J80) -> mx-ms-bc-pro-customer-products-and-services | N80: =validateAPIName(M80,D80) -> Valid | O80: =LEN(M80) -> 43
A81: SSFF | B81: Pro Customer Relationship Management | C81: =COUNTIF(develop!F81:F980,B81) -> 3 | D81: PROXY | E81: mx-api-bc-pro-customer-relationship-management | F81: APIMX000080 | G81: =E81 -> mx-api-bc-pro-customer-relationship-management | H81: =CONCATENATE("https://anypoint.mulesoft.com/exchange/834f46f4-ef08-4c50-81ae-56f917b413cc/", G81) -> https://anypoint.mulesoft.com/exchange/834f46f4-ef08-4c50-81ae-56f917b413cc/mx-api-bc-pro-customer-relationship-management | I81: 1.0.0 | J81: =obtenerRepoMS(E81) -> mx-ms-bc-pro-customer-relationship-management | K81: EKS | L81: =IFERROR(__xludf.DUMMYFUNCTION("REGEXREPLACE(REGEXREPLACE(REGEXREPLACE(J81, ""mx-ms-bc-"", """"), ""-mule"", ""-api-dev""), ""-apigee"", ""-api-dev"")"),"pro-customer-relationship-management") -> pro-customer-relationship-management | M81: =generarNombreDeploy(J81) -> mx-ms-bc-pro-customer-relationship-management | N81: =validateAPIName(M81,D81) -> Valid | O81: =LEN(M81) -> 45
A82: SSFF | B82: Pro Customer Workbench | C82: =COUNTIF(develop!F82:F980,B82) -> 1 | D82: PROXY | E82: mx-api-bc-pro-customer-workbench | F82: APIMX000081 | G82: =E82 -> mx-api-bc-pro-customer-workbench | H82: =CONCATENATE("https://anypoint.mulesoft.com/exchange/834f46f4-ef08-4c50-81ae-56f917b413cc/", G82) -> https://anypoint.mulesoft.com/exchange/834f46f4-ef08-4c50-81ae-56f917b413cc/mx-api-bc-pro-customer-workbench | I82: 1.0.0 | J82: =obtenerRepoMS(E82) -> mx-ms-bc-pro-customer-workbench | K82: EKS | L82: =IFERROR(__xludf.DUMMYFUNCTION("REGEXREPLACE(REGEXREPLACE(REGEXREPLACE(J82, ""mx-ms-bc-"", """"), ""-mule"", ""-api-dev""), ""-apigee"", ""-api-dev"")"),"pro-customer-workbench") -> pro-customer-workbench | M82: =generarNombreDeploy(J82) -> mx-ms-bc-pro-customer-workbench | N82: =validateAPIName(M82,D82) -> Valid | O82: =LEN(M82) -> 31
A83: SSFF | B83: Pro Direct Debit | C83: =COUNTIF(develop!F83:F980,B83) -> 1 | D83: PROXY | E83: mx-api-bc-pro-direct-debit | F83: APIMX000082 | G83: =E83 -> mx-api-bc-pro-direct-debit | H83: =CONCATENATE("https://anypoint.mulesoft.com/exchange/834f46f4-ef08-4c50-81ae-56f917b413cc/", G83) -> https://anypoint.mulesoft.com/exchange/834f46f4-ef08-4c50-81ae-56f917b413cc/mx-api-bc-pro-direct-debit | I83: 1.0.0 | J83: =obtenerRepoMS(E83) -> mx-ms-bc-pro-direct-debit | K83: EKS | L83: =IFERROR(__xludf.DUMMYFUNCTION("REGEXREPLACE(REGEXREPLACE(REGEXREPLACE(J83, ""mx-ms-bc-"", """"), ""-mule"", ""-api-dev""), ""-apigee"", ""-api-dev"")"),"pro-direct-debit") -> pro-direct-debit | M83: =generarNombreDeploy(J83) -> mx-ms-bc-pro-direct-debit | N83: =validateAPIName(M83,D83) -> Valid | O83: =LEN(M83) -> 25
A84: SSFF | B84: Pro Document Directory | C84: =COUNTIF(develop!F84:F980,B84) -> 3 | D84: PROXY | E84: mx-api-bc-pro-document-directory | F84: APIMX000083 | G84: =E84 -> mx-api-bc-pro-document-directory | H84: =CONCATENATE("https://anypoint.mulesoft.com/exchange/834f46f4-ef08-4c50-81ae-56f917b413cc/", G84) -> https://anypoint.mulesoft.com/exchange/834f46f4-ef08-4c50-81ae-56f917b413cc/mx-api-bc-pro-document-directory | I84: 1.0.0 | J84: =obtenerRepoMS(E84) -> mx-ms-bc-pro-document-directory | K84: EKS | L84: =IFERROR(__xludf.DUMMYFUNCTION("REGEXREPLACE(REGEXREPLACE(REGEXREPLACE(J84, ""mx-ms-bc-"", """"), ""-mule"", ""-api-dev""), ""-apigee"", ""-api-dev"")"),"pro-document-directory") -> pro-document-directory | M84: =generarNombreDeploy(J84) -> mx-ms-bc-pro-document-directory | N84: =validateAPIName(M84,D84) -> Valid | O84: =LEN(M84) -> 31
A85: SSFF | B85: Pro Document Services | C85: =COUNTIF(develop!F85:F980,B85) -> 7 | D85: PROXY | E85: mx-api-bc-pro-document-services | F85: APIMX000084 | G85: =E85 -> mx-api-bc-pro-document-services | H85: =CONCATENATE("https://anypoint.mulesoft.com/exchange/834f46f4-ef08-4c50-81ae-56f917b413cc/", G85) -> https://anypoint.mulesoft.com/exchange/834f46f4-ef08-4c50-81ae-56f917b413cc/mx-api-bc-pro-document-services | I85: 1.7.0 | J85: =obtenerRepoMS(E85) -> mx-ms-bc-pro-document-services | K85: EKS | L85: =IFERROR(__xludf.DUMMYFUNCTION("REGEXREPLACE(REGEXREPLACE(REGEXREPLACE(J85, ""mx-ms-bc-"", """"), ""-mule"", ""-api-dev""), ""-apigee"", ""-api-dev"")"),"pro-document-services") -> pro-document-services | M85: =generarNombreDeploy(J85) -> mx-ms-bc-pro-document-services | N85: =validateAPIName(M85,D85) -> Valid | O85: =LEN(M85) -> 30
A86: SSFF | B86: Pro Financial Accounting | C86: =COUNTIF(develop!F86:F980,B86) -> 4 | D86: PROXY | E86: mx-api-bc-pro-financial-accounting | F86: APIMX000085 | G86: =E86 -> mx-api-bc-pro-financial-accounting | H86: =CONCATENATE("https://anypoint.mulesoft.com/exchange/834f46f4-ef08-4c50-81ae-56f917b413cc/", G86) -> https://anypoint.mulesoft.com/exchange/834f46f4-ef08-4c50-81ae-56f917b413cc/mx-api-bc-pro-financial-accounting | I86: 1.0.0 | J86: =obtenerRepoMS(E86) -> mx-ms-bc-pro-financial-accounting | K86: EKS | L86: =IFERROR(__xludf.DUMMYFUNCTION("REGEXREPLACE(REGEXREPLACE(REGEXREPLACE(J86, ""mx-ms-bc-"", """"), ""-mule"", ""-api-dev""), ""-apigee"", ""-api-dev"")"),"pro-financial-accounting") -> pro-financial-accounting | M86: =generarNombreDeploy(J86) -> mx-ms-bc-pro-financial-accounting | N86: =validateAPIName(M86,D86) -> Valid | O86: =LEN(M86) -> 33
A87: SSFF | B87: Pro Fraud Resolution | C87: =COUNTIF(develop!F87:F980,B87) -> 1 | D87: PROXY | E87: mx-api-bc-pro-fraud-resolution | F87: APIMX000086 | G87: =E87 -> mx-api-bc-pro-fraud-resolution | H87: =CONCATENATE("https://anypoint.mulesoft.com/exchange/834f46f4-ef08-4c50-81ae-56f917b413cc/", G87) -> https://anypoint.mulesoft.com/exchange/834f46f4-ef08-4c50-81ae-56f917b413cc/mx-api-bc-pro-fraud-resolution | I87: 1.0.0 | J87: =obtenerRepoMS(E87) -> mx-ms-bc-pro-fraud-resolution | K87: EKS | L87: =IFERROR(__xludf.DUMMYFUNCTION("REGEXREPLACE(REGEXREPLACE(REGEXREPLACE(J87, ""mx-ms-bc-"", """"), ""-mule"", ""-api-dev""), ""-apigee"", ""-api-dev"")"),"pro-fraud-resolution") -> pro-fraud-resolution | M87: =generarNombreDeploy(J87) -> mx-ms-bc-pro-fraud-resolution | N87: =validateAPIName(M87,D87) -> Valid | O87: =LEN(M87) -> 29
A88: SSFF | B88: Pro Interactive Help | C88: =COUNTIF(develop!F88:F980,B88) -> 2 | D88: PROXY | E88: mx-api-bc-pro-interactive-help | F88: APIMX000087 | G88: =E88 -> mx-api-bc-pro-interactive-help | H88: =CONCATENATE("https://anypoint.mulesoft.com/exchange/834f46f4-ef08-4c50-81ae-56f917b413cc/", G88) -> https://anypoint.mulesoft.com/exchange/834f46f4-ef08-4c50-81ae-56f917b413cc/mx-api-bc-pro-interactive-help | I88: 1.0.0 | J88: =obtenerRepoMS(E88) -> mx-ms-bc-pro-interactive-help | K88: EKS | L88: =IFERROR(__xludf.DUMMYFUNCTION("REGEXREPLACE(REGEXREPLACE(REGEXREPLACE(J88, ""mx-ms-bc-"", """"), ""-mule"", ""-api-dev""), ""-apigee"", ""-api-dev"")"),"pro-interactive-help") -> pro-interactive-help | M88: =generarNombreDeploy(J88) -> mx-ms-bc-pro-interactive-help | N88: =validateAPIName(M88,D88) -> Valid | O88: =LEN(M88) -> 29
A89: SSFF | B89: Pro Internal Bank Account | C89: =COUNTIF(develop!F89:F980,B89) -> 2 | D89: PROXY | E89: mx-api-bc-pro-internal-bank-account | F89: APIMX000088 | G89: =E89 -> mx-api-bc-pro-internal-bank-account | H89: =CONCATENATE("https://anypoint.mulesoft.com/exchange/834f46f4-ef08-4c50-81ae-56f917b413cc/", G89) -> https://anypoint.mulesoft.com/exchange/834f46f4-ef08-4c50-81ae-56f917b413cc/mx-api-bc-pro-internal-bank-account | I89: 1.0.0 | J89: =obtenerRepoMS(E89) -> mx-ms-bc-pro-internal-bank-account | K89: EKS | L89: =IFERROR(__xludf.DUMMYFUNCTION("REGEXREPLACE(REGEXREPLACE(REGEXREPLACE(J89, ""mx-ms-bc-"", """"), ""-mule"", ""-api-dev""), ""-apigee"", ""-api-dev"")"),"pro-internal-bank-account") -> pro-internal-bank-account | M89: =generarNombreDeploy(J89) -> mx-ms-bc-pro-internal-bank-account | N89: =validateAPIName(M89,D89) -> Valid | O89: =LEN(M89) -> 34
A90: SSFF | B90: Pro Investment Account | C90: =COUNTIF(develop!F90:F980,B90) -> 1 | D90: PROXY | E90: mx-api-bc-pro-investment-account | F90: APIMX000089 | G90: =E90 -> mx-api-bc-pro-investment-account | H90: =CONCATENATE("https://anypoint.mulesoft.com/exchange/834f46f4-ef08-4c50-81ae-56f917b413cc/", G90) -> https://anypoint.mulesoft.com/exchange/834f46f4-ef08-4c50-81ae-56f917b413cc/mx-api-bc-pro-investment-account | I90: 1.0.0 | J90: =obtenerRepoMS(E90) -> mx-ms-bc-pro-investment-account | K90: EKS | L90: =IFERROR(__xludf.DUMMYFUNCTION("REGEXREPLACE(REGEXREPLACE(REGEXREPLACE(J90, ""mx-ms-bc-"", """"), ""-mule"", ""-api-dev""), ""-apigee"", ""-api-dev"")"),"pro-investment-account") -> pro-investment-account | M90: =generarNombreDeploy(J90) -> mx-ms-bc-pro-investment-account | N90: =validateAPIName(M90,D90) -> Valid | O90: =LEN(M90) -> 31
A91: SSFF | B91: Pro Issued Device Administration | C91: =COUNTIF(develop!F91:F980,B91) -> 17 | D91: PROXY | E91: mx-api-bc-pro-issued-device-administration | F91: APIMX000090 | G91: =E91 -> mx-api-bc-pro-issued-device-administration | H91: =CONCATENATE("https://anypoint.mulesoft.com/exchange/834f46f4-ef08-4c50-81ae-56f917b413cc/", G91) -> https://anypoint.mulesoft.com/exchange/834f46f4-ef08-4c50-81ae-56f917b413cc/mx-api-bc-pro-issued-device-administration | I91: 1.3.0 | J91: =obtenerRepoMS(E91) -> mx-ms-bc-pro-issued-device-administration | K91: MuleSoft | L91: pro-issued-device-administration-api-dev | M91: =generarNombreDeploy(J91) -> mx-ms-bc-pro-issued-device-administration | N91: =validateAPIName(M91,D91) -> Valid | O91: =LEN(M91) -> 41
A92: SSFF | B92: Pro Issued Device Tracking | C92: =COUNTIF(develop!F92:F980,B92) -> 2 | D92: PROXY | E92: mx-api-bc-pro-issued-device-tracking | F92: APIMX000091 | G92: =E92 -> mx-api-bc-pro-issued-device-tracking | H92: =CONCATENATE("https://anypoint.mulesoft.com/exchange/834f46f4-ef08-4c50-81ae-56f917b413cc/", G92) -> https://anypoint.mulesoft.com/exchange/834f46f4-ef08-4c50-81ae-56f917b413cc/mx-api-bc-pro-issued-device-tracking | I92: 1.1.0 | J92: =obtenerRepoMS(E92) -> mx-ms-bc-pro-issued-device-tracking | K92: EKS | L92: =IFERROR(__xludf.DUMMYFUNCTION("REGEXREPLACE(REGEXREPLACE(REGEXREPLACE(J92, ""mx-ms-bc-"", """"), ""-mule"", ""-api-dev""), ""-apigee"", ""-api-dev"")"),"pro-issued-device-tracking") -> pro-issued-device-tracking | M92: =generarNombreDeploy(J92) -> mx-ms-bc-pro-issued-device-tracking | N92: =validateAPIName(M92,D92) -> Valid | O92: =LEN(M92) -> 35
A93: SSFF | B93: Pro Legal Entity Directory | C93: =COUNTIF(develop!F93:F980,B93) -> 2 | D93: PROXY | E93: mx-api-bc-pro-legal-entity-directory | F93: APIMX000092 | G93: =E93 -> mx-api-bc-pro-legal-entity-directory | H93: =CONCATENATE("https://anypoint.mulesoft.com/exchange/834f46f4-ef08-4c50-81ae-56f917b413cc/", G93) -> https://anypoint.mulesoft.com/exchange/834f46f4-ef08-4c50-81ae-56f917b413cc/mx-api-bc-pro-legal-entity-directory | I93: 1.0.0 | J93: =obtenerRepoMS(E93) -> mx-ms-bc-pro-legal-entity-directory | K93: EKS | L93: =IFERROR(__xludf.DUMMYFUNCTION("REGEXREPLACE(REGEXREPLACE(REGEXREPLACE(J93, ""mx-ms-bc-"", """"), ""-mule"", ""-api-dev""), ""-apigee"", ""-api-dev"")"),"pro-legal-entity-directory") -> pro-legal-entity-directory | M93: =generarNombreDeploy(J93) -> mx-ms-bc-pro-legal-entity-directory | N93: =validateAPIName(M93,D93) -> Valid | O93: =LEN(M93) -> 35
A94: SSFF | B94: Pro Loan | C94: =COUNTIF(develop!F94:F980,B94) -> 11 | D94: PROXY | E94: mx-api-bc-pro-loan | F94: APIMX000093 | G94: =E94 -> mx-api-bc-pro-loan | H94: =CONCATENATE("https://anypoint.mulesoft.com/exchange/834f46f4-ef08-4c50-81ae-56f917b413cc/", G94) -> https://anypoint.mulesoft.com/exchange/834f46f4-ef08-4c50-81ae-56f917b413cc/mx-api-bc-pro-loan | I94: 2.2.0 | J94: =obtenerRepoMS(E94) -> mx-ms-bc-pro-loan | K94: EKS | L94: =IFERROR(__xludf.DUMMYFUNCTION("REGEXREPLACE(REGEXREPLACE(REGEXREPLACE(J94, ""mx-ms-bc-"", """"), ""-mule"", ""-api-dev""), ""-apigee"", ""-api-dev"")"),"pro-loan") -> pro-loan | M94: =generarNombreDeploy(J94) -> mx-ms-bc-pro-loan | N94: =validateAPIName(M94,D94) -> Valid | O94: =LEN(M94) -> 17
A95: SSFF | B95: Pro Location Data Management | C95: =COUNTIF(develop!F95:F980,B95) -> 11 | D95: PROXY | E95: mx-api-bc-pro-location-data-management | F95: APIMX000094 | G95: =E95 -> mx-api-bc-pro-location-data-management | H95: =CONCATENATE("https://anypoint.mulesoft.com/exchange/834f46f4-ef08-4c50-81ae-56f917b413cc/", G95) -> https://anypoint.mulesoft.com/exchange/834f46f4-ef08-4c50-81ae-56f917b413cc/mx-api-bc-pro-location-data-management | I95: 1.3.1 | J95: =obtenerRepoMS(E95) -> mx-ms-bc-pro-location-data-management | K95: EKS | L95: =IFERROR(__xludf.DUMMYFUNCTION("REGEXREPLACE(REGEXREPLACE(REGEXREPLACE(J95, ""mx-ms-bc-"", """"), ""-mule"", ""-api-dev""), ""-apigee"", ""-api-dev"")"),"pro-location-data-management") -> pro-location-data-management | M95: =generarNombreDeploy(J95) -> mx-ms-bc-pro-location-data-management | N95: =validateAPIName(M95,D95) -> Valid | O95: =LEN(M95) -> 37
A96: SSFF | B96: Pro Party Authentication | C96: =COUNTIF(develop!F96:F980,B96) -> 5 | D96: PROXY | E96: mx-api-bc-pro-party-authentication | F96: APIMX000095 | G96: =E96 -> mx-api-bc-pro-party-authentication | H96: =CONCATENATE("https://anypoint.mulesoft.com/exchange/834f46f4-ef08-4c50-81ae-56f917b413cc/", G96) -> https://anypoint.mulesoft.com/exchange/834f46f4-ef08-4c50-81ae-56f917b413cc/mx-api-bc-pro-party-authentication | I96: 1.1.0 | J96: =obtenerRepoMS(E96) -> mx-ms-bc-pro-party-authentication | K96: EKS | L96: =IFERROR(__xludf.DUMMYFUNCTION("REGEXREPLACE(REGEXREPLACE(REGEXREPLACE(J96, ""mx-ms-bc-"", """"), ""-mule"", ""-api-dev""), ""-apigee"", ""-api-dev"")"),"pro-party-authentication") -> pro-party-authentication | M96: =generarNombreDeploy(J96) -> mx-ms-bc-pro-party-authentication | N96: =validateAPIName(M96,D96) -> Valid | O96: =LEN(M96) -> 33
A97: SSFF | B97: Pro Party Lifecycle Management | C97: =COUNTIF(develop!F97:F980,B97) -> 52 | D97: PROXY | E97: mx-api-bc-pro-party-lifecycle-management | F97: APIMX000096 | G97: =E97 -> mx-api-bc-pro-party-lifecycle-management | H97: =CONCATENATE("https://anypoint.mulesoft.com/exchange/834f46f4-ef08-4c50-81ae-56f917b413cc/", G97) -> https://anypoint.mulesoft.com/exchange/834f46f4-ef08-4c50-81ae-56f917b413cc/mx-api-bc-pro-party-lifecycle-management | I97: 2.3.2 | J97: =obtenerRepoMS(E97) -> mx-ms-bc-pro-party-lifecycle-management | K97: MuleSoft | L97: pro-party-lifecycle-management-api-dev | M97: =generarNombreDeploy(J97) -> mx-ms-bc-pro-party-lifecycle-management | N97: =validateAPIName(M97,D97) -> Valid | O97: =LEN(M97) -> 39
A98: SSFF | B98: Pro Party Reference Data Directory | C98: =COUNTIF(develop!F98:F980,B98) -> 27 | D98: PROXY | E98: mx-api-bc-pro-party-reference-data-directory | F98: APIMX000097 | G98: =E98 -> mx-api-bc-pro-party-reference-data-directory | H98: =CONCATENATE("https://anypoint.mulesoft.com/exchange/834f46f4-ef08-4c50-81ae-56f917b413cc/", G98) -> https://anypoint.mulesoft.com/exchange/834f46f4-ef08-4c50-81ae-56f917b413cc/mx-api-bc-pro-party-reference-data-directory | I98: 1.8.1 | J98: =obtenerRepoMS(E98) -> mx-ms-bc-pro-party-reference-data-directory | K98: EKS | L98: =IFERROR(__xludf.DUMMYFUNCTION("REGEXREPLACE(REGEXREPLACE(REGEXREPLACE(J98, ""mx-ms-bc-"", """"), ""-mule"", ""-api-dev""), ""-apigee"", ""-api-dev"")"),"pro-party-reference-data-directory") -> pro-party-reference-data-directory | M98: =generarNombreDeploy(J98) -> mx-ms-bc-pro-party-reference-data-directory | N98: =validateAPIName(M98,D98) -> Valid | O98: =LEN(M98) -> 43
A99: SSFF | B99: Pro Party Retail Reference Data Directory | C99: =COUNTIF(develop!F99:F980,B99) -> 6 | D99: PROXY | E99: mx-api-cpp-pro-party-retail-reference-data-directory | F99: APIMX000098 | G99: =E99 -> mx-api-cpp-pro-party-retail-reference-data-directory | H99: =CONCATENATE("https://anypoint.mulesoft.com/exchange/834f46f4-ef08-4c50-81ae-56f917b413cc/", G99) -> https://anypoint.mulesoft.com/exchange/834f46f4-ef08-4c50-81ae-56f917b413cc/mx-api-cpp-pro-party-retail-reference-data-directory | I99: 1.1.1 | J99: mx-ms-cpp-pro-party-retail-reference-data-directory | K99: EKS | L99: =IFERROR(__xludf.DUMMYFUNCTION("REGEXREPLACE(REGEXREPLACE(REGEXREPLACE(REGEXREPLACE(J99, ""mx-ms-bc-"", """"), ""-mule"", ""-api-dev""), ""-apigee"", ""-api-dev""), ""mx-ms-cpp-"", """")"),"pro-party-retail-reference-data-directory") -> pro-party-retail-reference-data-directory | M99: mx-ms-cpp-pro-party-retail-reference-data-directory | N99: =validateAPIName(M99,D99) -> Valid | O99: =LEN(M99) -> 51
A100: SSFF | B100: Pro Payment Execution | C100: =COUNTIF(develop!F100:F980,B100) -> 7 | D100: PROXY | E100: mx-api-bc-pro-payment-execution | F100: APIMX000099 | G100: =E100 -> mx-api-bc-pro-payment-execution | H100: =CONCATENATE("https://anypoint.mulesoft.com/exchange/834f46f4-ef08-4c50-81ae-56f917b413cc/", G100) -> https://anypoint.mulesoft.com/exchange/834f46f4-ef08-4c50-81ae-56f917b413cc/mx-api-bc-pro-payment-execution | I100: 1.0.1 | J100: =obtenerRepoMS(E100) -> mx-ms-bc-pro-payment-execution | K100: EKS | L100: =IFERROR(__xludf.DUMMYFUNCTION("REGEXREPLACE(REGEXREPLACE(REGEXREPLACE(J100, ""mx-ms-bc-"", """"), ""-mule"", ""-api-dev""), ""-apigee"", ""-api-dev"")"),"pro-payment-execution") -> pro-payment-execution | M100: =generarNombreDeploy(J100) -> mx-ms-bc-pro-payment-execution | N100: =validateAPIName(M100,D100) -> Valid | O100: =LEN(M100) -> 30
...

Sheet matriz BIAN
A1: operations (BA) | B1: cards (BA)
A2: Business Support | B2: creditCard

Sheet unity-ms-api-operations
A1: Organization | B1: API Repository | C1: API Specification | D1: API Type | E1: API Register ID | F1: API Name | G1: API Resource ID | H1: API Operation ID | I1: API Version | J1: API Base Path | K1: Resource Version | L1: HTTP Method | M1: API Operation Resource | N1: API Operation Full Path | O1: API Operation Description | P1: API Error | Q1: Confluence | R1: Status | S1: Link GitHub | T1: Complejidad API
A2: =IFERROR(__xludf.DUMMYFUNCTION("FILTER(develop!A:Z, ISNUMBER(MATCH(develop!B:B, 'unity-ms'!D:D, 0)))"),"#N/A") -> #N/A

Sheet unity-ms
A1: Unity Repositories | B1: API Name | C1: API Type | D1: API Repository Name | E1: MS Repository Name | F1: API Operations | G1: Observaciones
A2: https://github.com/SF-Bancoppel/mx-ms-bc-br-counterparty-risk | B2: =IFERROR(__xludf.DUMMYFUNCTION("IFERROR( INDEX( IMPORTRANGE(""13G8fPsBFu2GexfFEa1WV07s1XBlkJUT6lht1aLlmcKg"", ""api-register-id!B:B""), MATCH(E2, IMPORTRANGE(""13G8fPsBFu2GexfFEa1WV07s1XBlkJUT6lht1aLlmcKg"", ""api-register-id!J:J""), 0) ), ""Not Found API Name"" )"),"Not Found API Name") -> Not Found API Name | C2: =IFERROR(__xludf.DUMMYFUNCTION("IFERROR( INDEX( IMPORTRANGE(""13G8fPsBFu2GexfFEa1WV07s1XBlkJUT6lht1aLlmcKg"", ""api-register-id!D:D""), MATCH(E2, IMPORTRANGE(""13G8fPsBFu2GexfFEa1WV07s1XBlkJUT6lht1aLlmcKg"", ""api-register-id!J:J""), 0) ), ""Not Found API Name"" )"),"Not Found API Name") -> Not Found API Name | D2: =IFERROR(__xludf.DUMMYFUNCTION("IFERROR( INDEX( IMPORTRANGE(""13G8fPsBFu2GexfFEa1WV07s1XBlkJUT6lht1aLlmcKg"", ""api-register-id!E:E""), MATCH(E2, IMPORTRANGE(""13G8fPsBFu2GexfFEa1WV07s1XBlkJUT6lht1aLlmcKg"", ""api-register-id!J:J""), 0) ), ""Not Found API Name"" )"),"Not Found API Name") -> Not Found API Name | E2: mx-ms-bc-br-counterparty-risk-apigee | F2: 0 | G2: Registrar esta API y sus operaciones.
A3: https://github.com/SF-Bancoppel/mx-ms-bc-br-customer-product-and-service-eligibility-apigee | B3: =IFERROR(__xludf.DUMMYFUNCTION("IFERROR( INDEX( IMPORTRANGE(""13G8fPsBFu2GexfFEa1WV07s1XBlkJUT6lht1aLlmcKg"", ""api-register-id!B:B""), MATCH(E3, IMPORTRANGE(""13G8fPsBFu2GexfFEa1WV07s1XBlkJUT6lht1aLlmcKg"", ""api-register-id!J:J""), 0) ), ""Not Found API Name"" )"),"Not Found API Name") -> Not Found API Name | C3: =IFERROR(__xludf.DUMMYFUNCTION("IFERROR( INDEX( IMPORTRANGE(""13G8fPsBFu2GexfFEa1WV07s1XBlkJUT6lht1aLlmcKg"", ""api-register-id!D:D""), MATCH(E3, IMPORTRANGE(""13G8fPsBFu2GexfFEa1WV07s1XBlkJUT6lht1aLlmcKg"", ""api-register-id!J:J""), 0) ), ""Not Found API Name"" )"),"Not Found API Name") -> Not Found API Name | D3: =IFERROR(__xludf.DUMMYFUNCTION("IFERROR( INDEX( IMPORTRANGE(""13G8fPsBFu2GexfFEa1WV07s1XBlkJUT6lht1aLlmcKg"", ""api-register-id!E:E""), MATCH(E3, IMPORTRANGE(""13G8fPsBFu2GexfFEa1WV07s1XBlkJUT6lht1aLlmcKg"", ""api-register-id!J:J""), 0) ), ""Not Found API Name"" )"),"Not Found API Name") -> Not Found API Name | E3: =SUBSTITUTE(A3,"https://github.com/SF-Bancoppel/", "") -> mx-ms-bc-br-customer-product-and-service-eligibility-apigee | F3: =IFERROR(__xludf.DUMMYFUNCTION("IFERROR( INDEX( IMPORTRANGE(""13G8fPsBFu2GexfFEa1WV07s1XBlkJUT6lht1aLlmcKg"", ""api-register-id!C:C""), MATCH(E3, IMPORTRANGE(""13G8fPsBFu2GexfFEa1WV07s1XBlkJUT6lht1aLlmcKg"", ""api-register-id!J:J""), 0) ), ""Not Found API Name"" )"),"Not Found API Name") -> Not Found API Name
A4: https://github.com/SF-Bancoppel/mx-ms-bc-bus-business-support-mule | B4: =IFERROR(__xludf.DUMMYFUNCTION("IFERROR( INDEX( IMPORTRANGE(""13G8fPsBFu2GexfFEa1WV07s1XBlkJUT6lht1aLlmcKg"", ""api-register-id!B:B""), MATCH(E4, IMPORTRANGE(""13G8fPsBFu2GexfFEa1WV07s1XBlkJUT6lht1aLlmcKg"", ""api-register-id!J:J""), 0) ), ""Not Found API Name"" )"),"Not Found API Name") -> Not Found API Name | C4: =IFERROR(__xludf.DUMMYFUNCTION("IFERROR( INDEX( IMPORTRANGE(""13G8fPsBFu2GexfFEa1WV07s1XBlkJUT6lht1aLlmcKg"", ""api-register-id!D:D""), MATCH(E4, IMPORTRANGE(""13G8fPsBFu2GexfFEa1WV07s1XBlkJUT6lht1aLlmcKg"", ""api-register-id!J:J""), 0) ), ""Not Found API Name"" )"),"Not Found API Name") -> Not Found API Name | D4: =IFERROR(__xludf.DUMMYFUNCTION("IFERROR( INDEX( IMPORTRANGE(""13G8fPsBFu2GexfFEa1WV07s1XBlkJUT6lht1aLlmcKg"", ""api-register-id!E:E""), MATCH(E4, IMPORTRANGE(""13G8fPsBFu2GexfFEa1WV07s1XBlkJUT6lht1aLlmcKg"", ""api-register-id!J:J""), 0) ), ""Not Found API Name"" )"),"Not Found API Name") -> Not Found API Name | E4: =SUBSTITUTE(A4,"https://github.com/SF-Bancoppel/", "") -> mx-ms-bc-bus-business-support-mule | F4: =IFERROR(__xludf.DUMMYFUNCTION("IFERROR( INDEX( IMPORTRANGE(""13G8fPsBFu2GexfFEa1WV07s1XBlkJUT6lht1aLlmcKg"", ""api-register-id!C:C""), MATCH(E4, IMPORTRANGE(""13G8fPsBFu2GexfFEa1WV07s1XBlkJUT6lht1aLlmcKg"", ""api-register-id!J:J""), 0) ), ""Not Found API Name"" )"),"Not Found API Name") -> Not Found API Name
A5: https://github.com/SF-Bancoppel/mx-ms-bc-bus-cards-mule | B5: =IFERROR(__xludf.DUMMYFUNCTION("IFERROR( INDEX( IMPORTRANGE(""13G8fPsBFu2GexfFEa1WV07s1XBlkJUT6lht1aLlmcKg"", ""api-register-id!B:B""), MATCH(E5, IMPORTRANGE(""13G8fPsBFu2GexfFEa1WV07s1XBlkJUT6lht1aLlmcKg"", ""api-register-id!J:J""), 0) ), ""Not Found API Name"" )"),"Not Found API Name") -> Not Found API Name | C5: =IFERROR(__xludf.DUMMYFUNCTION("IFERROR( INDEX( IMPORTRANGE(""13G8fPsBFu2GexfFEa1WV07s1XBlkJUT6lht1aLlmcKg"", ""api-register-id!D:D""), MATCH(E5, IMPORTRANGE(""13G8fPsBFu2GexfFEa1WV07s1XBlkJUT6lht1aLlmcKg"", ""api-register-id!J:J""), 0) ), ""Not Found API Name"" )"),"Not Found API Name") -> Not Found API Name | D5: =IFERROR(__xludf.DUMMYFUNCTION("IFERROR( INDEX( IMPORTRANGE(""13G8fPsBFu2GexfFEa1WV07s1XBlkJUT6lht1aLlmcKg"", ""api-register-id!E:E""), MATCH(E5, IMPORTRANGE(""13G8fPsBFu2GexfFEa1WV07s1XBlkJUT6lht1aLlmcKg"", ""api-register-id!J:J""), 0) ), ""Not Found API Name"" )"),"Not Found API Name") -> Not Found API Name | E5: =SUBSTITUTE(A5,"https://github.com/SF-Bancoppel/", "") -> mx-ms-bc-bus-cards-mule | F5: =IFERROR(__xludf.DUMMYFUNCTION("IFERROR( INDEX( IMPORTRANGE(""13G8fPsBFu2GexfFEa1WV07s1XBlkJUT6lht1aLlmcKg"", ""api-register-id!C:C""), MATCH(E5, IMPORTRANGE(""13G8fPsBFu2GexfFEa1WV07s1XBlkJUT6lht1aLlmcKg"", ""api-register-id!J:J""), 0) ), ""Not Found API Name"" )"),"Not Found API Name") -> Not Found API Name
A6: https://github.com/SF-Bancoppel/mx-ms-bc-bus-channel-specific-mule | B6: =IFERROR(__xludf.DUMMYFUNCTION("IFERROR( INDEX( IMPORTRANGE(""13G8fPsBFu2GexfFEa1WV07s1XBlkJUT6lht1aLlmcKg"", ""api-register-id!B:B""), MATCH(E6, IMPORTRANGE(""13G8fPsBFu2GexfFEa1WV07s1XBlkJUT6lht1aLlmcKg"", ""api-register-id!J:J""), 0) ), ""Not Found API Name"" )"),"Not Found API Name") -> Not Found API Name | C6: =IFERROR(__xludf.DUMMYFUNCTION("IFERROR( INDEX( IMPORTRANGE(""13G8fPsBFu2GexfFEa1WV07s1XBlkJUT6lht1aLlmcKg"", ""api-register-id!D:D""), MATCH(E6, IMPORTRANGE(""13G8fPsBFu2GexfFEa1WV07s1XBlkJUT6lht1aLlmcKg"", ""api-register-id!J:J""), 0) ), ""Not Found API Name"" )"),"Not Found API Name") -> Not Found API Name | D6: =IFERROR(__xludf.DUMMYFUNCTION("IFERROR( INDEX( IMPORTRANGE(""13G8fPsBFu2GexfFEa1WV07s1XBlkJUT6lht1aLlmcKg"", ""api-register-id!E:E""), MATCH(E6, IMPORTRANGE(""13G8fPsBFu2GexfFEa1WV07s1XBlkJUT6lht1aLlmcKg"", ""api-register-id!J:J""), 0) ), ""Not Found API Name"" )"),"Not Found API Name") -> Not Found API Name | E6: =SUBSTITUTE(A6,"https://github.com/SF-Bancoppel/", "") -> mx-ms-bc-bus-channel-specific-mule | F6: =IFERROR(__xludf.DUMMYFUNCTION("IFERROR( INDEX( IMPORTRANGE(""13G8fPsBFu2GexfFEa1WV07s1XBlkJUT6lht1aLlmcKg"", ""api-register-id!C:C""), MATCH(E6, IMPORTRANGE(""13G8fPsBFu2GexfFEa1WV07s1XBlkJUT6lht1aLlmcKg"", ""api-register-id!J:J""), 0) ), ""Not Found API Name"" )"),"Not Found API Name") -> Not Found API Name
A7: https://github.com/SF-Bancoppel/mx-ms-bc-bus-cross-product-operations-mule | B7: =IFERROR(__xludf.DUMMYFUNCTION("IFERROR( INDEX( IMPORTRANGE(""13G8fPsBFu2GexfFEa1WV07s1XBlkJUT6lht1aLlmcKg"", ""api-register-id!B:B""), MATCH(E7, IMPORTRANGE(""13G8fPsBFu2GexfFEa1WV07s1XBlkJUT6lht1aLlmcKg"", ""api-register-id!J:J""), 0) ), ""Not Found API Name"" )"),"Not Found API Name") -> Not Found API Name | C7: =IFERROR(__xludf.DUMMYFUNCTION("IFERROR( INDEX( IMPORTRANGE(""13G8fPsBFu2GexfFEa1WV07s1XBlkJUT6lht1aLlmcKg"", ""api-register-id!D:D""), MATCH(E7, IMPORTRANGE(""13G8fPsBFu2GexfFEa1WV07s1XBlkJUT6lht1aLlmcKg"", ""api-register-id!J:J""), 0) ), ""Not Found API Name"" )"),"Not Found API Name") -> Not Found API Name | D7: =IFERROR(__xludf.DUMMYFUNCTION("IFERROR( INDEX( IMPORTRANGE(""13G8fPsBFu2GexfFEa1WV07s1XBlkJUT6lht1aLlmcKg"", ""api-register-id!E:E""), MATCH(E7, IMPORTRANGE(""13G8fPsBFu2GexfFEa1WV07s1XBlkJUT6lht1aLlmcKg"", ""api-register-id!J:J""), 0) ), ""Not Found API Name"" )"),"Not Found API Name") -> Not Found API Name | E7: =SUBSTITUTE(A7,"https://github.com/SF-Bancoppel/", "") -> mx-ms-bc-bus-cross-product-operations-mule | F7: =IFERROR(__xludf.DUMMYFUNCTION("IFERROR( INDEX( IMPORTRANGE(""13G8fPsBFu2GexfFEa1WV07s1XBlkJUT6lht1aLlmcKg"", ""api-register-id!C:C""), MATCH(E7, IMPORTRANGE(""13G8fPsBFu2GexfFEa1WV07s1XBlkJUT6lht1aLlmcKg"", ""api-register-id!J:J""), 0) ), ""Not Found API Name"" )"),"Not Found API Name") -> Not Found API Name
A8: https://github.com/SF-Bancoppel/mx-ms-bc-bus-customer-management-mule | B8: =IFERROR(__xludf.DUMMYFUNCTION("IFERROR( INDEX( IMPORTRANGE(""13G8fPsBFu2GexfFEa1WV07s1XBlkJUT6lht1aLlmcKg"", ""api-register-id!B:B""), MATCH(E8, IMPORTRANGE(""13G8fPsBFu2GexfFEa1WV07s1XBlkJUT6lht1aLlmcKg"", ""api-register-id!J:J""), 0) ), ""Not Found API Name"" )"),"Not Found API Name") -> Not Found API Name | C8: =IFERROR(__xludf.DUMMYFUNCTION("IFERROR( INDEX( IMPORTRANGE(""13G8fPsBFu2GexfFEa1WV07s1XBlkJUT6lht1aLlmcKg"", ""api-register-id!D:D""), MATCH(E8, IMPORTRANGE(""13G8fPsBFu2GexfFEa1WV07s1XBlkJUT6lht1aLlmcKg"", ""api-register-id!J:J""), 0) ), ""Not Found API Name"" )"),"Not Found API Name") -> Not Found API Name | D8: =IFERROR(__xludf.DUMMYFUNCTION("IFERROR( INDEX( IMPORTRANGE(""13G8fPsBFu2GexfFEa1WV07s1XBlkJUT6lht1aLlmcKg"", ""api-register-id!E:E""), MATCH(E8, IMPORTRANGE(""13G8fPsBFu2GexfFEa1WV07s1XBlkJUT6lht1aLlmcKg"", ""api-register-id!J:J""), 0) ), ""Not Found API Name"" )"),"Not Found API Name") -> Not Found API Name | E8: =SUBSTITUTE(A8,"https://github.com/SF-Bancoppel/", "") -> mx-ms-bc-bus-customer-management-mule | F8: =IFERROR(__xludf.DUMMYFUNCTION("IFERROR( INDEX( IMPORTRANGE(""13G8fPsBFu2GexfFEa1WV07s1XBlkJUT6lht1aLlmcKg"", ""api-register-id!C:C""), MATCH(E8, IMPORTRANGE(""13G8fPsBFu2GexfFEa1WV07s1XBlkJUT6lht1aLlmcKg"", ""api-register-id!J:J""), 0) ), ""Not Found API Name"" )"),"Not Found API Name") -> Not Found API Name
