Workbook

Sheet PH Vertical Expansion
A4: Nivel | B4: Secuencia | C4: =SUBSTITUTE(TRANSLATE(SUBSTITUTE('__TR_VERTICAL'!C1,"PID","XQZ0QX"),"en","es"),"XQZ0QX","PID") | D4: Nombre | E4: Descripción | F4: Propietario del proceso | G4: Nivel de interoperabilidad | H4: Núcleo o dominio | I4: Propósito en la arquitectura interoperable | J4: Estrategia de Abastecimiento (Indicativo) | K4: Soluciones BanCoppel utilizadas (proyecto)
A5: 1 | B5: 1 | C5: 5 | D5: Gestión API | E5: La capacidad de diseñar, publicar, asegurar, versionar, medir y retirar los contratos de servicios síncronos del banco, junto con el conjunto de viviendas orientadas al promotor que los rodea (catálogo, portal, sandbox). Cubre tanto el plano de ejecución (mediación de pasarela, enrutamiento, política de tráfico) como el plano de control (ciclo de vida, administración de políticas, análisis). | F5: Jefe de API y Arquitectura de Integración | G5: L0 | H5: Núcleo y Plataforma | I5: Instrumento principal de desacoplamiento de la arquitectura interoperable. Un contrato estable basado en estándares (alineado con BIAN o personalizado canónico) permite que un canal se re-platforme sin tocar un núcleo, y que un núcleo sea reemplazado sin tocar un canal. También es el punto de control semántico donde una petición deja de ser una llamada a un sistema específico y pasa a llamar a una capacidad bancaria. | J5: Plataforma de terceros + políticas personalizadas | K5: Apigee API Management/Gateway; MuleSoft; WebMethods; BIAN alineado APIs; Transact OFS/IRIS REST APIs; Modyo Connect/Amazon API Gateway para flujos Apolo.
A6: 2 | B6: 1 | C6: 5.1 | D6: Pasarela API y Mediación en tiempo de ejecución | E6: Plano de ejecución que termina, valida, media y enruta el tráfico API entre consumidores y proveedores, aplicando la política en el punto de invocación en lugar de dentro del código de la aplicación. | F6: Jefe de API y Arquitectura de Integración | G6: L1 | H6: Núcleo y Plataforma | I6: Hace cumplir el contrato en tiempo de ejecución, así que el desacoplamiento está garantizado por la plataforma en lugar de por la disciplina del desarrollador. | J6: Terceros | K6: Apigee API Gateway/API Management; integración/orquestación MuleSoft; WebMethods BPM/BRM; BIAN alineado APIs; Transact OFS/IRIS REST APIs.
A7: 3 | B7: 1 | C7: 5.1.1 | D7: Enrutamiento | E7: Resolución de un contrato lógico API a uno o más puntos finales físicos de servicio, incluyendo enrutamiento basado en host, versión y entorno. | F7: Jefe de API y Arquitectura de Integración | G7: L2 | H7: Núcleo y Plataforma | I7: Permite la reubicación del backend, la re-plataforma y el doble funcionamiento de procesadores antiguos y nuevos sin ningún cambio de consumidor. | J7: Terceros | K7: Apigee API Gateway/API Management; integración/orquestación MuleSoft; WebMethods BPM/BRM; BIAN alineado APIs; Transact OFS/IRIS REST APIs.
A8: 3 | B8: 2 | C8: 5.1.2 | D8: Mediación y transformación del mensaje | E8: Adaptación de protocolos y cargas útiles en el edge (REST, SOAP, gRPC, protocolos heredados), incluyendo manipulación de cabeceras y mapeo canónico-nativo. | F8: Jefe de API y Arquitectura de Integración | G8: L2 | H8: Núcleo y Plataforma | I8: Absorbe la heterogeneidad técnica de un conjunto híbrido de núcleo, de modo que los consumidores solo ven un estilo de interfaz. | J8: Terceros | K8: Apigee API Gateway/API Management; integración/orquestación MuleSoft; WebMethods BPM/BRM; BIAN alineado APIs; Transact OFS/IRIS REST APIs.
A9: 3 | B9: 3 | C9: 5.1.3 | D9: API Gestión de Tráfico | E9: Cuotas, límite de tarifa, limitación, arresto de picos y políticas de calidad de servicio aplicadas por consumidor, por API y por nivel. | F9: Jefe de API y Arquitectura de Integración | G9: L2 | H9: Núcleo y Plataforma | I9: Protege la capacidad finita heredada (MIPS, pools de conexión) frente a una demanda digital ilimitada y convierte la capacidad en un recurso gobernado y con precio. | J9: Terceros | K9: Apigee API Gateway/API Management; integración/orquestación MuleSoft; WebMethods BPM/BRM; BIAN alineado APIs; Transact OFS/IRIS REST APIs.
A10: 3 | B10: 4 | C10: 5.1.4 | D10: Validación de mensajes y protección de carga útil | E10: Validación de esquema, tamaño y contenido de mensajes entrantes y salientes, incluyendo protección contra ataques basados en contenido. | F10: Jefe de API y Arquitectura de Integración | G10: L2 | H10: Núcleo y Plataforma | I10: Detiene el tráfico malformado y hostil antes de que llegue al parque de procesamiento, donde la remediación es mucho más cara. | J10: Terceros | K10: Apigee API Gateway/API Management; integración/orquestación MuleSoft; WebMethods BPM/BRM; BIAN alineado APIs; Transact OFS/IRIS REST APIs.
A11: 3 | B11: 5 | C11: 5.1.5 | D11: Gestión de errores y normalización de fallos | E11: Taxonomía de errores estandarizada, mapeo de fallos y códigos de respuesta a través de backends heterogéneos. | F11: Jefe de API y Arquitectura de Integración | G11: L2 | H11: Núcleo y Plataforma | I11: Evita que la semántica de error específica del backend se filtre en los canales, que es una de las fuentes más comunes de acoplamiento oculto. | J11: Terceros | K11: Apigee API Gateway/API Management; integración/orquestación MuleSoft; WebMethods BPM/BRM; BIAN alineado APIs; Transact OFS/IRIS REST APIs.
A12: 2 | B12: 2 | C12: 5.2 | D12: Gestión del ciclo de vida API | E12: Plano de control que gobierna un API desde el diseño y la definición del contrato hasta la publicación, el cambio de versiones, la notificación de cambios y su eventual retirada. | F12: Jefe de API y Arquitectura de Integración | G12: L1 | H12: Núcleo y Plataforma | I12: Convierte las interfaces en activos empresariales gestionados con una ruta de cambio controlada, que es la condición previa para su reutilización entre entidades y países. | J12: Proceso de terceros + gobernanza | K12: Estándares BIAN API; Apigee API ciclo de vida/gobernanza; documentación al estilo OpenAPI/Swagger API para OfiWeb/Canales; El cambio API está controlado por la gobernanza de la arquitectura.
A13: 3 | B13: 1 | C13: 5.2.1 | D13: Normas de diseño y contratos API | E13: Definición y aplicación de estándares de interfaz, nombres canónicos o alineados con BIAN, y puertas de revisión de diseño antes de la publicación. | F13: Jefe de API y Arquitectura de Integración | G13: L2 | H13: Núcleo y Plataforma | I13: Garantiza que las nuevas interfaces aumenten la reutilización en lugar de añadir otra integración personalizada para mantener. | J13: Proceso de terceros + gobernanza | K13: Estándares BIAN API; Apigee API ciclo de vida/gobernanza; documentación al estilo OpenAPI/Swagger API para OfiWeb/Canales; El cambio API está controlado por la gobernanza de la arquitectura.
A14: 3 | B14: 2 | C14: 5.2.2 | D14: Versionado API | E14: Soporte simultáneo de múltiples versiones de contrato con reglas definidas de compatibilidad y deprecación. | F14: Jefe de API y Arquitectura de Integración | G14: L2 | H14: Núcleo y Plataforma | I14: Desacopla los ciclos de lanzamiento entre consumidores y proveedores, de modo que ningún cambio individual requiera un despliegue sincronizado de big bang. | J14: Proceso de terceros + gobernanza | K14: Estándares BIAN API; Apigee API ciclo de vida/gobernanza; documentación al estilo OpenAPI/Swagger API para OfiWeb/Canales; El cambio API está controlado por la gobernanza de la arquitectura.
A15: 3 | B15: 3 | C15: 5.2.3 | D15: Notificación de publicación y cambio API | E15: Promoción de APIs en entornos y notificación proactiva de cambios de contrato a los consumidores registrados. | F15: Jefe de API y Arquitectura de Integración | G15: L2 | H15: Núcleo y Plataforma | I15: Elimina la sobrecarga de coordinación que de otro modo hace que los equipos eviten reutilizar una interfaz compartida. | J15: Proceso de terceros + gobernanza | K15: Estándares BIAN API; Apigee API ciclo de vida/gobernanza; documentación al estilo OpenAPI/Swagger API para OfiWeb/Canales; El cambio API está controlado por la gobernanza de la arquitectura.
A16: 3 | B16: 4 | C16: 5.2.4 | D16: API Depreciación y Retiro | E16: Un control de la desaparición de interfaces, incluyendo el seguimiento de migración del consumidor y la aplicación de fechas de fin de vida. | F16: Jefe de API y Arquitectura de Integración | G16: L2 | H16: Núcleo y Plataforma | I16: Evita que la capa de interoperabilidad acumule la misma deuda de interfaz que fue creada para eliminar. | J16: Proceso de terceros + gobernanza | K16: Estándares BIAN API; Apigee API ciclo de vida/gobernanza; documentación al estilo OpenAPI/Swagger API para OfiWeb/Canales; El cambio API está controlado por la gobernanza de la arquitectura.
A17: 2 | B17: 3 | C17: 5.3 | D17: API Manager (Administración de Plataforma) | E17: Administración, configuración de políticas, operación e instrumentación comercial de la propia plataforma de gestión API, tanto en topologías locales, en la nube como en la nube o híbridas. | F17: Jefe de API y Arquitectura de Integración | G17: L1 | H17: Núcleo y Plataforma | I17: Mantiene la política administrada de forma centralizada y aplicada de forma consistente, para que las normas de seguridad y tráfico no se fragmenten por equipo API. | J17: Terceros | K17: Administración y políticas de la plataforma Apigee; Monitorización DataDog/API; tuberías DevSecOps; GCP alojado en Apigee con proveedores AWS/locales.
A18: 3 | B18: 1 | C18: 5.3.1 | D18: Administración y Seguimiento de Políticas | E18: Definición central, asignación y auditoría de políticas de pasarela (seguridad, tráfico, mediación, caché) a lo largo del patrimonio API. | F18: Jefe de API y Arquitectura de Integración | G18: L2 | H18: Núcleo y Plataforma | I18: Convierte la política en un elemento de configuración gobernado en lugar de código embebido, permitiendo cambios a nivel de estado en una sola acción. | J18: Terceros | K18: Administración y políticas de la plataforma Apigee; Monitorización DataDog/API; tuberías DevSecOps; GCP alojado en Apigee con proveedores AWS/locales.
A19: 3 | B19: 2 | C19: 5.3.2 | D19: API Monitorización, Analítica y Monetización | E19: Métricas de consumo, latencia y análisis de errores por API y por consumidor, con base de medición para devolución interna o monetización de socios. | F19: Jefe de API y Arquitectura de Integración | G19: L2 | H19: Núcleo y Plataforma | I19: Proporciona la base de evidencia para las afirmaciones de reutilización, la planificación de capacidades y los modelos comerciales de ecosistemas. | J19: Terceros | K19: Administración y políticas de la plataforma Apigee; Monitorización DataDog/API; tuberías DevSecOps; GCP alojado en Apigee con proveedores AWS/locales.
A20: 3 | B20: 3 | C20: 5.3.3 | D20: Despliegue y operaciones de la plataforma | E20: Topología de despliegue, automatización, actualización y soporte operativo de la plataforma de gestión API. | F20: Jefe de API y Arquitectura de Integración | G20: L2 | H20: Núcleo y Plataforma | I20: Garantiza que la capa de desacoplamiento sea en sí misma resiliente y actualizable, ya que se convierte en un punto único de dependencia para todo el tráfico. | J20: Terceros | K20: Administración y políticas de la plataforma Apigee; Monitorización DataDog/API; tuberías DevSecOps; GCP alojado en Apigee con proveedores AWS/locales.
A21: 2 | B21: 4 | C21: 5.4 | D21: Portal y catálogo para desarrolladores | E21: Superficie de autoservicio donde desarrolladores internos y externos descubren, evalúan, se registran y se apoyan en interfaces publicadas. | F21: Jefe de API y Arquitectura de Integración | G21: L1 | H21: Núcleo y Plataforma | I21: La reutilización solo ocurre si se pueden encontrar capacidades. El portal convierte un inventario técnico en un catálogo de productos consumibles. | J21: Terceros | K21: Catálogo/gobernanza API para Apificación de Canales y OfiWeb; Apigee como plano de gestión API. No se evidencia explícitamente ninguna herramienta de portal para desarrolladores independiente.
A22: 3 | B22: 1 | C22: 5.4.1 | D22: Catálogo, documentación y descubrimiento de metadatos API | E22: Inventario consultable de interfaces publicadas con especificaciones, ejemplos y metadatos. | F22: Jefe de API y Arquitectura de Integración | G22: L2 | H22: Núcleo y Plataforma | I22: Elimina el coste de redescubrimiento que impulsa a los equipos a construir una integración paralela punto a punto. | J22: Terceros | K22: Catálogo/gobernanza API para Apificación de Canales y OfiWeb; Apigee como plano de gestión API. No se evidencia explícitamente ninguna herramienta de portal para desarrolladores independiente.
A23: 3 | B23: 2 | C23: 5.4.2 | D23: Registro de desarrolladores y autoservicio | E23: Incorporación, emisión de credenciales, registro de solicitudes y gestión de derechos para consumidores de API. | F23: Jefe de API y Arquitectura de Integración | G23: L2 | H23: Núcleo y Plataforma | I23: Elimina el control humano del camino de consumo, que es lo que hace que la reutilización interna y la incorporación de parejas sea rápida. | J23: Terceros | K23: Catálogo/gobernanza API para Apificación de Canales y OfiWeb; Apigee como plano de gestión API. No se evidencia explícitamente ninguna herramienta de portal para desarrolladores independiente.
A24: 3 | B24: 3 | C24: 5.4.3 | D24: Colaboración, comunidad y autoapoyo | E24: Informes de problemas, bucles de retroalimentación, guía de uso, SDKs y ejemplos de referencia para equipos que consumen. | F24: Jefe de API y Arquitectura de Integración | G24: L2 | H24: Núcleo y Plataforma | I24: Proporciona la capa de habilitación sin la cual una capacidad publicada está técnicamente disponible pero prácticamente no se utiliza. | J24: Terceros | K24: Catálogo/gobernanza API para Apificación de Canales y OfiWeb; Apigee como plano de gestión API. No se evidencia explícitamente ninguna herramienta de portal para desarrolladores independiente.
A25: 1 | B25: 2 | C25: 4 | D25: Servicios de Gateway | E25: Controlado la entrada y salida a través del límite de confianza del banco en tres modalidades - API, archivo y evento - tanto en direcciones entrantes como salientes, además de los bordes especializados necesarios para tráfico regulado y de socios (borde de Open Banking, borde de filtro, servicio de token de seguridad, sandbox de socios, conmutación). | F25: Jefe de Perímetro y Arquitectura de Conectividad | G25: L0 | H25: Núcleo y Plataforma | I25: La interoperabilidad no es solo interna. Este dominio concentra la zonificación de red, terminación de protocolos, cifrado y política de tráfico para todas las contrapartes externas (banco central, procesadores de tarjetas, esquemas de pago, agencias, fintechs, canales corporativos) de modo que la participación en el ecosistema se convierta en un ejercicio de configuración en lugar de un proyecto. También es donde la mayoría de los bancos encuentran asimetría: las pasarelas API entrantes están maduras mientras que las pasarelas de archivos y eventos salientes están indefinidas, y esa brecha queda en la ruta crítica. | J25: Plataforma de terceros + servicios personalizados de borde | K25: Gateway Apigee de entrada/salida API; integración MuleSoft/WebMethods; Amazon API Gateway vía Modyo Connect; Borde de servicio EKS/Istio.
A26: 2 | B26: 1 | C26: 4.1 | D26: Servicios de pasarela entrantes | E26: Puntos de entrada gestionados para tráfico que se origina fuera del límite de confianza del banco, a través de API, canales de archivos y eventos, incluyendo el intercambio de aserturas de identidad en el borde. | F26: Jefe de Perímetro y Arquitectura de Conectividad | G26: L1 | H26: Núcleo y Plataforma | I26: Da al banco una puerta principal gobernada por modalidad en lugar de una proliferación de conexiones bilaterales con controles inconsistentes. | J26: Terceros | K26: Gateway Apigee de entrada/salida API; integración MuleSoft/WebMethods; Amazon API Gateway vía Modyo Connect; Borde de servicio EKS/Istio.
A27: 3 | B27: 1 | C27: 4.1.1 | D27: Pasarela entrante API | E27: Terminación, autenticación, aplicación de políticas y enrutamiento del tráfico API síncrono procedente de canales, socios y terceros. | F27: Jefe de Perímetro y Arquitectura de Conectividad | G27: L2 | H27: Núcleo y Plataforma | I27: Punto único de aplicación para demanda síncrona externa, desacoplando a las contrapartes de la topología interna del servicio. | J27: Terceros | K27: Gateway Apigee de entrada/salida API; integración MuleSoft/WebMethods; Amazon API Gateway vía Modyo Connect; Borde de servicio EKS/Istio.
A28: 3 | B28: 2 | C28: 4.1.2 | D28: Pasarela de Archivos Entrantes | E28: Recepción segura, validación, escaneo de virus y transferencia de archivos originados externamente, reemplazando la transferencia punto a punto no gestionada. | F28: Jefe de Perímetro y Arquitectura de Conectividad | G28: L2 | H28: Núcleo y Plataforma | I28: Coloca el gran conjunto residual de lotes bajo el mismo régimen de control y observabilidad que el tráfico API. | J28: Terceros | K28: DataStage ETL; interfaces batch/COB; Flujos de documentos OnBase; Interfaces de archivos/datos heredados PISA/Informix. No se evidencia explícitamente ningún producto dedicado MFT.
A29: 3 | B29: 3 | C29: 4.1.3 | D29: Pasarela entrante EventHub | E29: Gestión controlada de eventos y mensajes publicados externamente en la columna vertebral interna de eventos. | F29: Jefe de Perímetro y Arquitectura de Conectividad | G29: L2 | H29: Núcleo y Plataforma | I29: Permite la integración en tiempo real del ecosistema (esquemas, agregadores, datos de mercado) sin exponer temas internos. | J29: Terceros | K29: Kafka/Confluent; Amazon MQ; Amazon Kinesis; Temenos Events Framework; Componentes de procesador de eventos/router de eventos/limpieza de eventos.
A30: 3 | B30: 4 | C30: 4.1.4 | D30: Servicio de Token de Seguridad (STS) | E30: Emisión, intercambio y validación de tokens de seguridad en el perímetro, traduciendo las afirmaciones de identidad externas en credenciales internas. | F30: Jefe de Perímetro y Arquitectura de Conectividad | G30: L2 | H30: Núcleo y Plataforma | I30: Permite respetar las identidades federadas y de socios sin extender los límites internos de fideicomiso. | J30: Terceros | K30: OAuth 2.0 vía Apigee; Azure AD / Microsoft Entra ID; Token Party Identity; tokens de aplicación/usuario gestionados mediante la seguridad API.
A31: 2 | B31: 2 | C31: 4.2 | D31: Servicios de Pasarela de Salida | E31: Gestionó puntos de salida para tráfico originado por bancos hacia contrapartes aguas abajo, a través de API, canales de archivos y eventos, incluyendo el cambio de transacciones a esquemas y procesadores. | F31: Jefe de Perímetro y Arquitectura de Conectividad | G31: L1 | H31: Núcleo y Plataforma | I31: Externaliza la conectividad y credenciales específicas de la contraparte del código de la aplicación, de modo que un proveedor puede ser reemplazado sin tocar los servicios empresariales. | J31: Tercero + personalizado | K31: Gateway Apigee de entrada/salida API; integración MuleSoft/WebMethods; Amazon API Gateway vía Modyo Connect; Borde de servicio EKS/Istio.
A32: 3 | B32: 1 | C32: 4.2.1 | D32: Pasarela API de salida | E32: Mediación de salida, inyección de credenciales, reintentos y control de circuitos para llamadas a proveedores externos, expuesto a través de un DMZ. | F32: Jefe de Perímetro y Arquitectura de Conectividad | G32: L2 | H32: Núcleo y Plataforma | I32: Convierte la sustitución por terceros en un cambio de configuración de gateway en lugar de un proyecto de desarrollo. | J32: Tercero + personalizado | K32: Gateway Apigee de entrada/salida API; integración MuleSoft/WebMethods; Amazon API Gateway vía Modyo Connect; Borde de servicio EKS/Istio.
A33: 3 | B33: 2 | C33: 4.2.2 | D33: Pasarela de Archivos Salientes | E33: Generación, cifrado, programación y transmisión gestionada de archivos salientes, sustituyendo a los arreglos SFTP no gestionados. | F33: Jefe de Perímetro y Arquitectura de Conectividad | G33: L2 | H33: Núcleo y Plataforma | I33: Cierra la brecha de control y observabilidad más común en el estado externo. | J33: Tercero + personalizado | K33: DataStage ETL; interfaces batch/COB; Flujos de documentos OnBase; Interfaces de archivos/datos heredados PISA/Informix. No se evidencia explícitamente ningún producto dedicado MFT.
A34: 3 | B34: 3 | C34: 4.2.3 | D34: Pasarela EventHub de salida | E34: Publicación controlada de eventos internos a suscriptores externos mediante filtrado y gobernanza contractual. | F34: Jefe de Perímetro y Arquitectura de Conectividad | G34: L2 | H34: Núcleo y Plataforma | I34: Permite al banco ofrecer productos de datos en tiempo real al ecosistema sin conceder acceso a temas internos. | J34: Tercero + personalizado | K34: Kafka/Confluent; Amazon MQ; Amazon Kinesis; Temenos Events Framework; Componentes de procesador de eventos/router de eventos/limpieza de eventos.
A35: 3 | B35: 4 | C35: 4.2.4 | D35: Conmutación | E35: Enrutamiento y adaptación de protocolos del tráfico de transacciones a esquemas, procesadores y redes interbancarias, incluyendo la conmutación por error entre proveedores. | F35: Jefe de Perímetro y Arquitectura de Conectividad | G35: L2 | H35: Núcleo y Plataforma | I35: Proporciona redundancia de proveedores y enrutamiento de menor coste como propiedad arquitectónica más que como resultado de negociación. | J35: Tercero + personalizado | K35: BPC SmartVista/SVIP para conmutación y procesamiento de tarjetas; Hub de Pagos para SPEI, dispersión de nóminas y pagos multiplataforma; coexistencia legada con IST/PISA.
A36: 2 | B36: 3 | C36: 4.3 | D36: Ecosistema y ventaja bancaria abierta | E36: Bordes externos especializados para tráfico regulado de banca abierta, incorporación de socios y experimentación controlada, incluyendo bordes de filtrado y exposición al mercado. | F36: Jefe de Perímetro y Arquitectura de Conectividad | G36: L1 | H36: Núcleo y Plataforma | I36: Donde la capa de interoperabilidad se convierte en un canal de negocio: convierte capacidades internas en productos consumibles y contratados para terceros. | J36: Tercero + personalizado | K36: No se evidencia ningún producto específico de mercado abierto o sandbox asociado; las capacidades adyacentes utilizan entornos Apigee, API Gateway, BIAN APIs y entornos sandbox/UAT.
A37: 3 | B37: 1 | C37: 4.3.1 | D37: Borde de la Banca Abierta | E37: Exposición conforme a la normativa de cuentas, pagos y datos APIs con consentimiento, obligaciones sólidas de autenticación e informe. | F37: Jefe de Perímetro y Arquitectura de Conectividad | G37: L2 | H37: Núcleo y Plataforma | I37: Cumple con los mandatos regulatorios en una plataforma compartida en lugar de como un silo aislado de cumplimiento. | J37: Tercero + personalizado | K37: No se evidencia ningún producto específico de mercado abierto o sandbox asociado; las capacidades adyacentes utilizan entornos Apigee, API Gateway, BIAN APIs y entornos sandbox/UAT.
A38: 3 | B38: 2 | C38: 4.3.2 | D38: Borde del filtro | E38: Filtrado y filtro de tráfico externo basado en contenido, consumidores y geografía antes de la pasarela API. | F38: Jefe de Perímetro y Arquitectura de Conectividad | G38: L2 | H38: Núcleo y Plataforma | I38: Reduce la carga hostil y fuera de la política antes de que consuma la capacidad de gateway o backend. | J38: Tercero + personalizado | K38: Imperva WAF / Cloud Armor; AWS Shield; Zscaler TLS terminación; VPN/Direct Connect; Reglas Tetration; AWS/GCP/zonificación de red local.
A39: 3 | B39: 3 | C39: 4.3.3 | D39: Sandbox de socios | E39: Entorno aislado no productivo con datos representativos para el desarrollo y certificación de socios y fintech. | F39: Jefe de Perímetro y Arquitectura de Conectividad | G39: L2 | H39: Núcleo y Plataforma | I39: Comprime la incorporación de socios de meses a semanas, que es la limitación práctica en la estrategia del ecosistema. | J39: Tercero + personalizado | K39: No se evidencia ningún producto específico de mercado abierto o sandbox asociado; las capacidades adyacentes utilizan entornos Apigee, API Gateway, BIAN APIs y entornos sandbox/UAT.
A40: 3 | B40: 4 | C40: 4.3.4 | D40: Mercado API | E40: Catálogo comercial para envases, publicaciones y capacidades de contratación bancarias para consumidores externos. | F40: Jefe de Perímetro y Arquitectura de Conectividad | G40: L2 | H40: Núcleo y Plataforma | I40: Proporciona la interfaz para modelos de negocio no lineales de capacidad como producto. | J40: Tercero + personalizado | K40: No se evidencia ningún producto específico de mercado abierto o sandbox asociado; las capacidades adyacentes utilizan entornos Apigee, API Gateway, BIAN APIs y entornos sandbox/UAT.
A41: 2 | B41: 4 | C41: 4.4 | D41: Zonificación perimetral y conectividad | E41: Segmentación de red, modelo de exposición DMZ, terminación de seguridad del transporte y gestión de conectividad que sustentan todas las modalidades de gateway. | F41: Jefe de Perímetro y Arquitectura de Conectividad | G41: L1 | H41: Núcleo y Plataforma | I41: Establece la topología de confianza dentro de la cual operan todas las demás capacidades de pasarela; Sin él, el desacoplamiento aumenta la exposición en lugar de contenerla. | J41: Terceros | K41: Imperva WAF / Cloud Armor; AWS Shield; Zscaler TLS terminación; VPN/Direct Connect; Reglas Tetration; AWS/GCP/zonificación de red local.
A42: 3 | B42: 1 | C42: 4.4.1 | D42: Zonificación de red y exposición DMZ | E42: Definición y aplicación de zonas de seguridad, y el patrón DMZ mediante el cual las capacidades internas se exponen externamente. | F42: Jefe de Perímetro y Arquitectura de Conectividad | G42: L2 | H42: Núcleo y Plataforma | I42: Garantiza que las nuevas interfaces externas hereden un modelo de exposición aprobado en lugar de negociar uno por proyecto. | J42: Terceros | K42: Imperva WAF / Cloud Armor; AWS Shield; Zscaler TLS terminación; VPN/Direct Connect; Reglas Tetration; AWS/GCP/zonificación de red local.
A43: 3 | B43: 2 | C43: 4.4.2 | D43: Terminación de la seguridad del transporte | E43: Terminación TLS, autenticación mutua y gestión de políticas de cifrado en el edge. | F43: Jefe de Perímetro y Arquitectura de Conectividad | G43: L2 | H43: Núcleo y Plataforma | I43: Centraliza la moneda criptográfica, de modo que las deprecaciones de protocolo se gestionan una vez en vez de por aplicación. | J43: Terceros | K43: Imperva WAF / Cloud Armor; AWS Shield; Zscaler TLS terminación; VPN/Direct Connect; Reglas Tetration; AWS/GCP/zonificación de red local.
A44: 3 | B44: 3 | C44: 4.4.3 | D44: Gestión de la conectividad externa | E44: Registro, credenciales, endpoints y monitorización operativa de las conexiones de contraparte. | F44: Jefe de Perímetro y Arquitectura de Conectividad | G44: L2 | H44: Núcleo y Plataforma | I44: Crea un inventario autoritativo de dependencias externas, que es un requisito previo para la gestión de riesgos de terceros. | J44: Terceros | K44: Imperva WAF / Cloud Armor; AWS Shield; Zscaler TLS terminación; VPN/Direct Connect; Reglas Tetration; AWS/GCP/zonificación de red local.
A45: 1 | B45: 3 | C45: 1 | D45: Seguridad | E45: Protección de extremo a extremo de la propia capa de interoperabilidad: gestión de identidad y acceso, servicios criptográficos, gestión de certificados y secretos, protección contra amenazas, gestión de vulnerabilidades y amenazas, y monitorización y respuesta de seguridad en los conjuntos API, eventos, archivos y contenedores. | F45: CISO / Responsable de Arquitectura de Seguridad | G45: L0 | H45: Núcleo y Plataforma | I45: El desacoplamiento multiplica el número de saltos de red, credenciales y relaciones de confianza en el patrimonio. Sin una capacidad de seguridad a nivel de núcleo, cada nuevo servicio reimplementa sus propios controles y la superficie de ataque crece más rápido que la funcionalidad. El objetivo de diseño es que la seguridad se herede de la plataforma, no se codifica por servicio, lo que también aplana la curva de costes de remediación de vulnerabilidades a medida que el número de servicios crece hasta cientos. | J45: Servicios heredados de terceros + plataforma | K45: OAuth 2.0/Apigee; Azure AD/Microsoft Entra; Incode KYC; Imperva WAF; HashiCorp Vault; AWS Secrets Manager; Exabeam; Istio; AWS Shield.
A46: 2 | B46: 1 | C46: 1.1 | D46: Gestión de Identidad y Acceso | E46: Servicios de autenticación, autorización, token y sesión para clientes, empleados, socios e identidades de máquinas que consumen la capa de interoperabilidad. | F46: CISO / Responsable de Arquitectura de Seguridad | G46: L1 | H46: Núcleo y Plataforma | I46: Proporciona la única respuesta autorizada sobre quién llama y qué puede hacer, por lo que la lógica de derechos se elimina de los servicios empresariales. | J46: Terceros | K46: OAuth 2.0 vía Apigee; Azure AD / Microsoft Entra ID; Token Party Identity; Incode identidad/KYC; HashiCorp Vault para soporte de credenciales.
A47: 3 | B47: 1 | C47: 1.1.1 | D47: Servicios de autenticación | E47: Verificación de la identidad del usuario y del sistema, incluyendo autenticación multifactor y step-up, como un servicio compartido. | F47: CISO / Responsable de Arquitectura de Seguridad | G47: L2 | H47: Núcleo y Plataforma | I47: Elimina las implementaciones de autenticación por aplicación, que son la principal fuente de una fuerza de control inconsistente. | J47: Terceros | K47: OAuth 2.0 vía Apigee; Azure AD / Microsoft Entra ID; Token Party Identity; Incode identidad/KYC; HashiCorp Vault para soporte de credenciales.
A48: 3 | B48: 2 | C48: 1.1.2 | D48: Servicios de autorización | E48: Evaluación centralizada de derechos y invocación de políticas en servicio, incluyendo decisiones basadas en roles y atributos. | F48: CISO / Responsable de Arquitectura de Seguridad | G48: L2 | H48: Núcleo y Plataforma | I48: Mantiene la coherencia de la autorización mientras los servicios se recomponen entre proveedores tradicionales, de nueva generación y terceros. | J48: Terceros | K48: OAuth 2.0 vía Apigee; Azure AD / Microsoft Entra ID; Token Party Identity; Incode identidad/KYC; HashiCorp Vault para soporte de credenciales.
A49: 3 | B49: 3 | C49: 1.1.3 | D49: Token de acceso y inicio de sesión único | E49: Emisión, actualización, introspección y revocación de tokens de acceso, y propagación de identidad entre salto de servicio. | F49: CISO / Responsable de Arquitectura de Seguridad | G49: L2 | H49: Núcleo y Plataforma | I49: Preserva la identidad del llamante de extremo a extremo mediante orquestaciones, lo que hace posible la auditoría distribuida. | J49: Terceros | K49: OAuth 2.0 vía Apigee; Azure AD / Microsoft Entra ID; Token Party Identity; Incode identidad/KYC; HashiCorp Vault para soporte de credenciales.
A50: 3 | B50: 4 | C50: 1.1.4 | D50: Servicios de Sesión | E50: Creación, validación, tiempo de espera y terminación de sesiones entre canales y dominios. | F50: CISO / Responsable de Arquitectura de Seguridad | G50: L2 | H50: Núcleo y Plataforma | I50: Permite la continuidad omnicanal sin que cada canal mantenga el estado de sesión privada. | J50: Terceros | K50: OAuth 2.0 vía Apigee; Azure AD / Microsoft Entra ID; Token Party Identity; Incode identidad/KYC; HashiCorp Vault para soporte de credenciales.
A51: 3 | B51: 5 | C51: 1.1.5 | D51: Administración de Usuarios, Políticas y Credenciales | E51: Administración de identidades, derechos, almacenes de pólizas y credenciales de máquinas. | F51: CISO / Responsable de Arquitectura de Seguridad | G51: L2 | H51: Núcleo y Plataforma | I51: Ofrece a auditores y operadores un lugar para evidenciar y cambiar el acceso en todo el ámbito de interoperabilidad. | J51: Terceros | K51: OAuth 2.0 vía Apigee; Azure AD / Microsoft Entra ID; Token Party Identity; Incode identidad/KYC; HashiCorp Vault para soporte de credenciales.
A52: 2 | B52: 2 | C52: 1.2 | D52: Servicios cripto | E52: Operaciones criptográficas compartidas —firma, cifrado, protección de carga útil de extremo a extremo— se entregaban como servicios llamables respaldados por módulos de seguridad de hardware y almacenes de claves gestionados. | F52: CISO / Responsable de Arquitectura de Seguridad | G52: L1 | H52: Núcleo y Plataforma | I52: Concentra los controles de mayor garantía en un solo componente certificado, de modo que la criptografía se consume en lugar de reimplementarse. | J52: Terceros (respaldado por HSM) | K52: cifrado AES-256; TLS/SSL; Gestión de claves HSM; Oracle TDE; Istio mTLS; Firma Incode/NOM-151 para contratos de incorporación.
A53: 3 | B53: 1 | C53: 1.2.1 | D53: Operaciones Emblemáticas | E53: Generación y verificación de firma digital para transacciones, documentos y mensajes intersistemas. | F53: CISO / Responsable de Arquitectura de Seguridad | G53: L2 | H53: Núcleo y Plataforma | I53: Proporciona la no repudiación a través de los límites del sistema, lo cual se vuelve esencial una vez que una transacción abarca varias plataformas. | J53: Terceros (respaldado por HSM) | K53: cifrado AES-256; TLS/SSL; Gestión de claves HSM; Oracle TDE; Istio mTLS; Firma Incode/NOM-151 para contratos de incorporación.
A54: 3 | B54: 2 | C54: 1.2.2 | D54: Operaciones de cifrado | E54: Servicios de cifrado y descifrado para datos en tránsito y en reposo, incluyendo la tokenización de campos sensibles. | F54: CISO / Responsable de Arquitectura de Seguridad | G54: L2 | H54: Núcleo y Plataforma | I54: Permite que los datos sensibles atraviesen un patrimonio distribuido sin ampliar el alcance de cumplimiento de cada componente que pasa. | J54: Terceros (respaldado por HSM) | K54: cifrado AES-256; TLS/SSL; Gestión de claves HSM; Oracle TDE; Istio mTLS; Firma Incode/NOM-151 para contratos de incorporación.
A55: 3 | B55: 3 | C55: 1.2.3 | D55: Cifrado de extremo a extremo | E55: Protección a nivel de carga útil mantenida desde el canal de origen hasta el procesador final, independientemente de los saltos de transporte. | F55: CISO / Responsable de Arquitectura de Seguridad | G55: L2 | H55: Núcleo y Plataforma | I55: Mantiene los datos confidenciales entre intermediarios, lo cual es una condición previa para usar procesadores de terceros y SaaS. | J55: Terceros (respaldado por HSM) | K55: cifrado AES-256; TLS/SSL; Gestión de claves HSM; Oracle TDE; Istio mTLS; Firma Incode/NOM-151 para contratos de incorporación.
A56: 3 | B56: 4 | C56: 1.2.4 | D56: Almacenamiento de claves y gestión HSM | E56: Gestión del ciclo de vida de las claves criptográficas y los módulos de hardware que las protegen. | F56: CISO / Responsable de Arquitectura de Seguridad | G56: L2 | H56: Núcleo y Plataforma | I56: Previene la expansión de llaves, el modo de fallo que suele bloquear la migración en la nube de cargas de trabajo reguladas. | J56: Terceros (respaldado por HSM) | K56: cifrado AES-256; TLS/SSL; Gestión de claves HSM; Oracle TDE; Istio mTLS; Firma Incode/NOM-151 para contratos de incorporación.
A57: 2 | B57: 3 | C57: 1.3 | D57: Gestión de certificados y secretos | E57: Emisión, distribución, rotación, revocación y auditoría de certificados y secretos de aplicaciones consumidos por servicios, gateways y pipelines. | F57: CISO / Responsable de Arquitectura de Seguridad | G57: L1 | H57: Núcleo y Plataforma | I57: Automatiza la higiene operativa que suele fallar a gran escala; Los certificados caducados y los secretos codificados en forma dura son algunas de las causas más frecuentes de interrupciones y hallazgos de auditorías en herencias distribuidas. | J57: Terceros | K57: HashiCorp Vault; AWS Secrets Manager; Kubernetes Secretos; gestión de certificados SSL; HSM para operaciones clave críticas.
A58: 3 | B58: 1 | C58: 1.3.1 | D58: Gestión de Certificados | E58: Emisión automatizada de certificados, inventario, monitorización de caducidad, renovación y revocación en toda la herencia. | F58: CISO / Responsable de Arquitectura de Seguridad | G58: L2 | H58: Núcleo y Plataforma | I58: Elimina una causa principal de interrupciones autoinfligidas a medida que el número de puntos finales cifrados se multiplica. | J58: Terceros | K58: HashiCorp Vault; AWS Secrets Manager; Kubernetes Secretos; gestión de certificados SSL; HSM para operaciones clave críticas.
A59: 3 | B59: 2 | C59: 1.3.2 | D59: Gestión secreta | E59: Almacenamiento centralizado, inyección dinámica, rotación y auditoría de credenciales, claves API y cadenas de conexión. | F59: CISO / Responsable de Arquitectura de Seguridad | G59: L2 | H59: Núcleo y Plataforma | I59: Elimina secretos del código y la configuración, convirtiendo la rotación de credenciales en una operación rutinaria de plataforma. | J59: Terceros | K59: HashiCorp Vault; AWS Secrets Manager; Kubernetes Secretos; gestión de certificados SSL; HSM para operaciones clave críticas.
A60: 2 | B60: 4 | C60: 1.4 | D60: Protección contra amenazas | E60: Detección y mitigación de tráfico hostil y técnicas de ataque en tiempo de ejecución en el perímetro, en la capa API y dentro del contenedor y plataformas de streaming. | F60: CISO / Responsable de Arquitectura de Seguridad | G60: L1 | H60: Núcleo y Plataforma | I60: Protege la superficie de ataque ensanchada que necesariamente crea el desacoplamiento, en las capas donde la exposición es mayor. | J60: Terceros | K60: Imperva WAF; Cloud Armor; AWS Shield; Apigee OAuth/limitación de tasa; malla de servicio Istio; Exabeam SIEM; HashiCorp Vault y controles de endurecimiento.
A61: 3 | B61: 1 | C61: 1.4.1 | D61: API Seguridad y Protección por Inyección | E61: Protección contra inyección, manipulación de parámetros, autorizaciones fallidas y otras clases de ataque de la capa API, con aplicación de políticas en la puerta de enlace. | F61: CISO / Responsable de Arquitectura de Seguridad | G61: L2 | H61: Núcleo y Plataforma | I61: Protege las interfaces de las que depende el caso de negocio para exponer, por lo que la apertura no se traduce en riesgo. | J61: Terceros | K61: Imperva WAF; Cloud Armor; AWS Shield; Apigee OAuth/limitación de tasa; malla de servicio Istio; Exabeam SIEM; HashiCorp Vault y controles de endurecimiento.
A62: 3 | B62: 2 | C62: 1.4.2 | D62: Protección contra amenazas perimetrales | E62: Cortafuegos de aplicaciones web, mitigación de denegación de servicio y gestión de bots en el borde de la red. | F62: CISO / Responsable de Arquitectura de Seguridad | G62: L2 | H62: Núcleo y Plataforma | I62: Absorbe tráfico de ataque volumétrico y automatizado antes de que alcance la capacidad de la pasarela o la aplicación. | J62: Terceros | K62: Imperva WAF; Cloud Armor; AWS Shield; Apigee OAuth/limitación de tasa; malla de servicio Istio; Exabeam SIEM; HashiCorp Vault y controles de endurecimiento.
A63: 3 | B63: 3 | C63: 1.4.3 | D63: Protección de Carga Útil y Cumplimiento de Cuotas | E63: Inspección de cargas útiles, límites de tamaño y esquema, y aplicación de cuotas orientada al abuso. | F63: CISO / Responsable de Arquitectura de Seguridad | G63: L2 | H63: Núcleo y Plataforma | I63: Previene ataques por agotamiento de recursos contra componentes compartidos usados por todos los consumidores. | J63: Terceros | K63: Imperva WAF; Cloud Armor; AWS Shield; Apigee OAuth/limitación de tasa; malla de servicio Istio; Exabeam SIEM; HashiCorp Vault y controles de endurecimiento.
A64: 3 | B64: 4 | C64: 1.4.4 | D64: Seguridad en contenedores y streaming | E64: Escaneo de imágenes, protección de cargas de trabajo en tiempo de ejecución, validación de políticas de malla de servicio y control de acceso en temas de eventos. | F64: CISO / Responsable de Arquitectura de Seguridad | G64: L2 | H64: Núcleo y Plataforma | I64: Extiende el control a los tiempos de ejecución donde los servicios modernos realmente se ejecutan, en lugar de solo al perímetro. | J64: Terceros | K64: Imperva WAF; Cloud Armor; AWS Shield; Apigee OAuth/limitación de tasa; malla de servicio Istio; Exabeam SIEM; HashiCorp Vault y controles de endurecimiento.
A65: 2 | B65: 5 | C65: 1.5 | D65: Gestión de vulnerabilidades y amenazas (VTM) | E65: Identificación, priorización y remediación continua de vulnerabilidades en bibliotecas, imágenes, plataformas e interfaces, incluyendo pruebas adversariales. | F65: CISO / Responsable de Arquitectura de Seguridad | G65: L1 | H65: Núcleo y Plataforma | I65: Aborda directamente el coste y el tiempo dedicado a gestionar vulnerabilidades en un gran conjunto de microservicios, el objetivo declarado detrás de curar bibliotecas base y eliminar dependencias innecesarias. | J65: Tercero + proceso | K65: compuertas de seguridad DevSecOps; Prácticas SAST/DAST; SonarQube y OWASP ZAP referenciados para la seguridad de la canalización; endurecer la validación; escaneos de vulnerabilidades.
A66: 3 | B66: 1 | C66: 1.5.1 | D66: Escaneo y Remediación de Vulnerabilidades | E66: Escaneo automatizado de código, dependencias, imágenes e infraestructura con flujo de trabajo de remediación seguido. | F66: CISO / Responsable de Arquitectura de Seguridad | G66: L2 | H66: Núcleo y Plataforma | I66: Convierte un atraso de alertas manuales ilimitado en una pipeline gobernada y medible. | J66: Tercero + proceso | K66: compuertas de seguridad DevSecOps; Prácticas SAST/DAST; SonarQube y OWASP ZAP referenciados para la seguridad de la canalización; endurecer la validación; escaneos de vulnerabilidades.
A67: 3 | B67: 2 | C67: 1.5.2 | D67: Pruebas de penetración y evaluación adversarial | E67: Pruebas programadas y dirigidas de interfaces expuestas y componentes de interoperabilidad por equipos especializados. | F67: CISO / Responsable de Arquitectura de Seguridad | G67: L2 | H67: Núcleo y Plataforma | I67: Valida que los controles heredados de la plataforma realmente se mantienen bajo ataque, no solo en el papel. | J67: Tercero + proceso | K67: compuertas de seguridad DevSecOps; Prácticas SAST/DAST; SonarQube y OWASP ZAP referenciados para la seguridad de la canalización; endurecer la validación; escaneos de vulnerabilidades.
A68: 3 | B68: 3 | C68: 1.5.3 | D68: Línea Base de Seguridad y Aplicación de Políticas | E68: Definición y aplicación automatizada de librerías aprobadas, tiempos de ejecución y líneas base de configuración. | F68: CISO / Responsable de Arquitectura de Seguridad | G68: L2 | H68: Núcleo y Plataforma | I68: Los estándares centrales controlados por un solo equipo son los que mantienen el esfuerzo de remediación sublineal a medida que crecen los servicios. | J68: Tercero + proceso | K68: compuertas de seguridad DevSecOps; Prácticas SAST/DAST; SonarQube y OWASP ZAP referenciados para la seguridad de la canalización; endurecer la validación; escaneos de vulnerabilidades.
A69: 2 | B69: 6 | C69: 1.6 | D69: Observabilidad y respuesta de seguridad | E69: Telemetría, correlación, alertas, paneles de control y respuesta automatizada específicos de seguridad se basan en la columna vertebral de observabilidad compartida. | F69: CISO / Responsable de Arquitectura de Seguridad | G69: L1 | H69: Núcleo y Plataforma | I69: Cierra la brecha más observada en los programas de interoperabilidad: la telemetría de seguridad existe en fragmentos y no existe capacidad de respuesta automatizada. | J69: Terceros + casos de uso personalizados | K69: Exabeam SIEM para detección de amenazas; DataDog para paneles de seguridad/operativos; CloudTrail/CloudWatch donde se utilizan servicios AWS; escalada de incidentes a través de Operaciones/Seguridad.
A70: 3 | B70: 1 | C70: 1.6.1 | D70: Alertas de seguridad, métricas y paneles de control | E70: Recopilación consolidada de eventos de seguridad, correlación y paneles que abarcan capas perimeter, API, contenedor y streaming. | F70: CISO / Responsable de Arquitectura de Seguridad | G70: L2 | H70: Núcleo y Plataforma | I70: Proporciona a la función de seguridad la misma visibilidad de extremo a extremo que el trazado distribuido da a la ingeniería. | J70: Terceros + casos de uso personalizados | K70: Exabeam SIEM para detección de amenazas; DataDog para paneles de seguridad/operativos; CloudTrail/CloudWatch donde se utilizan servicios AWS; escalada de incidentes a través de Operaciones/Seguridad.
A71: 3 | B71: 2 | C71: 1.6.2 | D71: Automatización de la Respuesta a Incidentes de Seguridad | E71: Manuales de contención y remediación orquestados y parcialmente automatizados activados por detecciones de seguridad. | F71: CISO / Responsable de Arquitectura de Seguridad | G71: L2 | H71: Núcleo y Plataforma | I71: Comprime el tiempo de respuesta a un nivel coherente con los canales de distribución en tiempo real y siempre activos. | J71: Terceros + casos de uso personalizados | K71: Exabeam SIEM para detección de amenazas; DataDog para paneles de seguridad/operativos; CloudTrail/CloudWatch donde se utilizan servicios AWS; escalada de incidentes a través de Operaciones/Seguridad.
A72: 1 | B72: 4 | C72: 2 | D72: Observabilidad | E72: Instrumentación y evidencia en todo el patrimonio distribuido: agregación de registros y registro operativo, registro de auditorías, rastreo distribuido y de extremo a extremo, monitorización de salud y API, alertas, métricas y analíticas, y paneles técnicos y empresariales. | F72: Jefe de Ingeniería de Plataformas y SRE | G72: L0 | H72: Núcleo y Plataforma | I72: La consecuencia más difícil de la componibilidad es que ningún sistema único mantiene ya la verdad de extremo a extremo sobre una transacción; La observabilidad la restaura. Ejecutivamente, esta capacidad convierte la capa de interoperabilidad de un activo técnico en un instrumento de riesgo y rendimiento a nivel de servicio empresarial; la misma telemetría que impulsa la respuesta a incidentes impulsa la visión de riesgo por servicio empresarial de IT utilizada para guiar el programa de modernización. | J72: Plataforma de terceros + casos de uso personalizados | K72: DataDog; Exabeam; CloudWatch/CloudTrail; Apigee analítica; Google Analytics; Data Warehouse informando.
A73: 2 | B73: 1 | C73: 2.1 | D73: Monitorización | E73: Recogida y evaluación continua del estado y disponibilidad de componentes, interfaces y dependencias de la plataforma, con alertas basadas en umbrales y anomalías. | F73: Jefe de Ingeniería de Plataformas y SRE | G73: L1 | H73: Núcleo y Plataforma | I73: Detecta la degradación antes que los clientes, lo cual importa más en una urbanización compuesta donde una dependencia débil degrada muchos viajes. | J73: Terceros | K73: Monitorización DataDog, paneles de control y alertas; CloudWatch/CloudTrail para componentes AWS; Apigee analítica; comprobaciones de salud de la plataforma en Apolo, Transact y SmartVista.
A74: 3 | B74: 1 | C74: 2.1.1 | D74: Monitorización de la salud | E74: Comprobaciones de vivencia, preparación y salud de dependencias para servicios, tiempos de ejecución y componentes de infraestructura. | F74: Jefe de Ingeniería de Plataformas y SRE | G74: L2 | H74: Núcleo y Plataforma | I74: Permite la recuperación automatizada y el desplazamiento de tráfico en lugar de diagnósticos manuales. | J74: Terceros | K74: Monitorización DataDog, paneles de control y alertas; CloudWatch/CloudTrail para componentes AWS; Apigee analítica; comprobaciones de salud de la plataforma en Apolo, Transact y SmartVista.
A75: 3 | B75: 2 | C75: 2.1.2 | D75: Monitorización de la salud y disponibilidad API | E75: Monitorización de disponibilidad, latencia, saturación y tasa de errores por interfaz y por consumidor. | F75: Jefe de Ingeniería de Plataformas y SRE | G75: L2 | H75: Núcleo y Plataforma | I75: Hace que los contratos publicados sean medibles en función de los niveles de servicio, lo que permite confiar en la reutilización interna. | J75: Terceros | K75: Monitorización DataDog, paneles de control y alertas; CloudWatch/CloudTrail para componentes AWS; Apigee analítica; comprobaciones de salud de la plataforma en Apolo, Transact y SmartVista.
A76: 3 | B76: 3 | C76: 2.1.3 | D76: Alertas y notificaciones | E76: Generación de alertas basadas en reglas y umbrales con enrutamiento al canal correspondiente (ITSM, mensajería, correo, llamada de guardia). | F76: Jefe de Ingeniería de Plataformas y SRE | G76: L2 | H76: Núcleo y Plataforma | I76: Garantiza que la detección llegue a un propietario responsable; la telemetría no enrutada no tiene valor operativo. | J76: Terceros | K76: Monitorización DataDog, paneles de control y alertas; CloudWatch/CloudTrail para componentes AWS; Apigee analítica; comprobaciones de salud de la plataforma en Apolo, Transact y SmartVista.
A77: 3 | B77: 4 | C77: 2.1.4 | D77: Monitorización de capacidad y tasa de eventos | E77: Medición del rendimiento, tasas de eventos y consumo de recursos para apoyar la planificación de capacidad. | F77: Jefe de Ingeniería de Plataformas y SRE | G77: L2 | H77: Núcleo y Plataforma | I77: Aborda directamente las brechas de rendimiento y planes de capacidad que normalmente se encuentran en el estado de integración en estado actual. | J77: Terceros | K77: Monitorización DataDog, paneles de control y alertas; CloudWatch/CloudTrail para componentes AWS; Apigee analítica; comprobaciones de salud de la plataforma en Apolo, Transact y SmartVista.
A78: 2 | B78: 2 | C78: 2.2 | D78: Logging | E78: Recogida estructurada, normalización, indexación, retención y rotación de registros técnicos, operativos y de auditoría de cada componente de la capa de interoperabilidad. | F78: Jefe de Ingeniería de Plataformas y SRE | G78: L1 | H78: Núcleo y Plataforma | I78: Proporciona el fundamento forense y de auditoría para un patrimonio distribuido donde ningún registro de aplicación único cuente toda la historia. | J78: Terceros | K78: Registros/monitores DataDog; Exabeam SIEM; AWS CloudTrail/CloudWatch; registros de auditoría de Apigee, Transact, SmartVista y flujos regulatorios/de reportes.
A79: 3 | B79: 1 | C79: 2.2.1 | D79: Agregación de logarítmicas | E79: Recogida centralizada e indexación de registros de servicios, gateways, tiempos de ejecución y pipelines. | F79: Jefe de Ingeniería de Plataformas y SRE | G79: L2 | H79: Núcleo y Plataforma | I79: Elimina la búsqueda de troncos por sistema, que es el mayor componente individual del tiempo medio de diagnóstico. | J79: Terceros | K79: Registros/monitores DataDog; Exabeam SIEM; AWS CloudTrail/CloudWatch; registros de auditoría de Apigee, Transact, SmartVista y flujos regulatorios/de reportes.
A80: 3 | B80: 2 | C80: 2.2.2 | D80: Servicios de Registro Operativo | E80: Bibliotecas estándar de registro, formatos y convenciones de severidad consumidos por los equipos de aplicaciones. | F80: Jefe de Ingeniería de Plataformas y SRE | G80: L2 | H80: Núcleo y Plataforma | I80: Hace que los registros sean correlacionados con la máquina por diseño en lugar de analizados retrospectivamente. | J80: Terceros | K80: Registros/monitores DataDog; Exabeam SIEM; AWS CloudTrail/CloudWatch; registros de auditoría de Apigee, Transact, SmartVista y flujos regulatorios/de reportes.
A81: 3 | B81: 3 | C81: 2.2.3 | D81: Registro de auditoría | E81: Registro inmutable de eventos relevantes para la seguridad y para el negocio con retención definida. | F81: Jefe de Ingeniería de Plataformas y SRE | G81: L2 | H81: Núcleo y Plataforma | I81: Cumple obligaciones de evidencia regulatoria que los núcleos heredados cumplían implícitamente a través de sus propias revistas. | J81: Terceros | K81: Registros/monitores DataDog; Exabeam SIEM; AWS CloudTrail/CloudWatch; registros de auditoría de Apigee, Transact, SmartVista y flujos regulatorios/de reportes.
A82: 3 | B82: 4 | C82: 2.2.4 | D82: Retención y rotación de troncos | E82: Niveles de retención basados en políticas, archivo y rotación entre almacenamiento caliente, caliente y frío. | F82: Jefe de Ingeniería de Plataformas y SRE | G82: L2 | H82: Núcleo y Plataforma | I82: Controla la curva de coste de observabilidad, que de otro modo escala más rápido que el propio conjunto. | J82: Terceros | K82: Registros/monitores DataDog; Exabeam SIEM; AWS CloudTrail/CloudWatch; registros de auditoría de Apigee, Transact, SmartVista y flujos regulatorios/de reportes.
A83: 2 | B83: 3 | C83: 2.3 | D83: Trazado | E83: Propagación y reconstrucción del camino completo de ejecución de una solicitud a través de servicios, plataformas, protocolos y saltos asincrónicos, basándose en un identificador de correlación propagado de forma consistente. | F83: Jefe de Ingeniería de Plataformas y SRE | G83: L1 | H83: Núcleo y Plataforma | I83: La capacidad de observabilidad más importante en una arquitectura interoperable: es lo que hace que una transacción distribuida sea explicable de principio a fin, tanto en la generación heredada como en la de próxima generación. | J83: Instrumentación de terceros + personalizada | K83: DataDog APM/trazado está previsto como observabilidad avanzada; Istio soporta telemetría a nivel de servicio. El servicio de identidad de correlación no se menciona explícitamente.
A84: 3 | B84: 1 | C84: 2.3.1 | D84: Trazado distribuido | E84: Recogida y ensamblado entre invocaciones de servicio síncronas, con atribución de latencia por salto. | F84: Jefe de Ingeniería de Plataformas y SRE | G84: L2 | H84: Núcleo y Plataforma | I84: Localiza la verdadera limitación en un viaje compuesto en lugar de asignar la culpa por inferencia. | J84: Instrumentación de terceros + personalizada | K84: DataDog APM/trazado está previsto como observabilidad avanzada; Istio soporta telemetría a nivel de servicio. El servicio de identidad de correlación no se menciona explícitamente.
A85: 3 | B85: 2 | C85: 2.3.2 | D85: Trazado de extremo a extremo (identidad de correlación) | E85: Propagación consistente de identificadores de correlación a través de canales, orquestaciones, eventos y adaptadores heredados. | F85: Jefe de Ingeniería de Plataformas y SRE | G85: L2 | H85: Núcleo y Plataforma | I85: Ofrece trazabilidad a lo largo de toda la arquitectura técnica, incluyendo segmentos asincrónicos y mainframe. | J85: Instrumentación de terceros + personalizada | K85: DataDog APM/trazado está previsto como observabilidad avanzada; Istio soporta telemetría a nivel de servicio. El servicio de identidad de correlación no se menciona explícitamente.
A86: 2 | B86: 4 | C86: 2.4 | D86: Métricas, Análisis e Informes | E86: Derivación, almacenamiento y análisis de métricas técnicas y empresariales a partir de la telemetría, incluyendo correlación automatizada y detección asistida por aprendizaje automático, así como informes periódicos. | F86: Jefe de Ingeniería de Plataformas y SRE | G86: L1 | H86: Núcleo y Plataforma | I86: Convierte la telemetría en bruto en la información de gestión utilizada para demostrar el caso de negocio de interoperabilidad y dirigir la inversión de la plataforma. | J86: Tercero + personalizado | K86: KPIs DataDog; Apigee analítica; Google Analytics para comportamiento digital; Data Warehouse/DataStage para reportar alimentaciones; salpicaderos ejecutivos PMO.
A87: 3 | B87: 1 | C87: 2.4.1 | D87: Métricas y Analítica | E87: Recogida, agregación y análisis de métricas de series temporales, incluyendo correlación negocio-evento y detección de anomalías. | F87: Jefe de Ingeniería de Plataformas y SRE | G87: L2 | H87: Núcleo y Plataforma | I87: Proporciona la base de medición para las reclamaciones de reutilización, tiempo de lanzamiento al mercado y costes presentadas en el caso de negocio del programa. | J87: Tercero + personalizado | K87: KPIs DataDog; Apigee analítica; Google Analytics para comportamiento digital; Data Warehouse/DataStage para reportar alimentaciones; salpicaderos ejecutivos PMO.
A88: 3 | B88: 2 | C88: 2.4.2 | D88: Reportajes | E88: Informes operativos programados y bajo demanda, de nivel de servicio y de cumplimiento. | F88: Jefe de Ingeniería de Plataformas y SRE | G88: L2 | H88: Núcleo y Plataforma | I88: Proporciona el paquete de evidencia recurrente para foros de riesgo, auditoría y gobernanza de servicios. | J88: Tercero + personalizado | K88: KPIs DataDog; Apigee analítica; Google Analytics para comportamiento digital; Data Warehouse/DataStage para reportar alimentaciones; salpicaderos ejecutivos PMO.
A89: 2 | B89: 5 | C89: 2.5 | D89: Paneles | E89: Visualización orientada a roles de la plataforma y la telemetría empresarial para audiencias de ingeniería, operaciones, seguridad, empresarial y ejecutivos. | F89: Jefe de Ingeniería de Plataformas y SRE | G89: L1 | H89: Núcleo y Plataforma | I89: Convierte la observabilidad de una herramienta de ingeniería en un instrumento de gestión compartido, incluyendo la vista de riesgo a nivel de servicio empresarial IT. | J89: Terceros | K89: paneles técnicos DataDog; PMO / paneles ejecutivos; paneles regulatorios y empresariales mediante Data Warehouse, Bajaware/Risklogic e informes de proyectos.
A90: 3 | B90: 1 | C90: 2.5.1 | D90: Paneles técnicos | E90: Vistas de componentes, servicios e infraestructura para los equipos de ingeniería y operaciones. | F90: Jefe de Ingeniería de Plataformas y SRE | G90: L2 | H90: Núcleo y Plataforma | I90: Reduce el triaje y apoya la propiedad de los servicios a nivel de equipo. | J90: Terceros | K90: paneles técnicos DataDog; PMO / paneles ejecutivos; paneles regulatorios y empresariales mediante Data Warehouse, Bajaware/Risklogic e informes de proyectos.
A91: 3 | B91: 2 | C91: 2.5.2 | D91: Paneles de control empresariales | E91: Vistas a nivel de negocio y de trayectos sobre volumen, tasa de éxito y flujo de valor. | F91: Jefe de Ingeniería de Plataformas y SRE | G91: L2 | H91: Núcleo y Plataforma | I91: Permite a los directivos ver la modernización, el progreso y el riesgo en términos empresariales en lugar de en términos componentes. | J91: Terceros | K91: paneles técnicos DataDog; PMO / paneles ejecutivos; paneles regulatorios y empresariales mediante Data Warehouse, Bajaware/Risklogic e informes de proyectos.
A92: 1 | B92: 5 | C92: 13 | D92: Infraestructura (Pila Tecnológica) | E92: La base en tiempo de ejecución de la capa de interoperabilidad: el marco de microservicios y los servicios del núcleo, bibliotecas base y tiempos de ejecución del lenguaje, plataforma contenedor y serverless, descubrimiento y malla de servicios, automatización de configuración, ingeniería de despliegue y pruebas, y resiliencia de infraestructura. | F92: Jefe de Ingeniería de la Nube y Plataformas | G92: L0 | H92: Núcleo y Plataforma | I92: Determina el coste marginal de añadir un componente a la arquitectura. Una pila curada y aplicada por estándares —permitió tecnologías gobernadas centralmente, eliminar bibliotecas innecesarias— ofrece agilidad de despliegue y elástica escalando los atributos del caso de negocio hasta la componibilidad, y mantiene cientos de servicios gobernables por un pequeño equipo de plataforma. | J92: Código abierto + de terceros, comisariado centralmente | K92: AWS, GCP e infraestructura híbrida local; EKS/Kubernetes; Terraform/Packer/GitHub IaC; DevSecOps CI/CD; DataDog; Bóveda.
A93: 2 | B93: 1 | C93: 13.1 | D93: Marco de Microservicios | E93: El marco de desarrollo y ejecución opinado que aloja servicios autosuficientes independientemente del dominio de negocio, incluyendo bibliotecas base compartidas, entornos de ejecución aprobados por lenguajes, servicios del kernel, descubrimiento de servicios e integración de mallas de servicios. | F93: Jefe de Ingeniería de la Nube y Plataformas | G93: L1 | H93: Núcleo y Plataforma | I93: El marco es donde se heredan las preocupaciones transversales en lugar de reconstruirse; Su calidad establece el techo de productividad para cada equipo de dominio. | J93: Código abierto, seleccionado internamente | K93: microservicios Spring Boot; microservicios Modyo Connect; Temenos DES API/componentes; EKS/ECS/Fargate; Kubernetes; Mesh de servicio Istio.
A94: 3 | B94: 1 | C94: 13.1.1 | D94: Bibliotecas base | E94: Bibliotecas comunes seleccionadas y versionadas que proporcionan registro, seguridad, resiliencia, configuración e integración de telemetría. | F94: Jefe de Ingeniería de la Nube y Plataformas | G94: L2 | H94: Núcleo y Plataforma | I94: Estandariza el comportamiento no funcional y reduce la superficie de vulnerabilidad eliminando dependencias innecesarias. | J94: Código abierto, seleccionado internamente | K94: microservicios Spring Boot; microservicios Modyo Connect; Temenos DES API/componentes; EKS/ECS/Fargate; Kubernetes; Mesh de servicio Istio.
A95: 3 | B95: 2 | C95: 13.1.2 | D95: Tiempos de ejecución del lenguaje | E95: Conjunto regulado de tiempos de ejecución aprobados y versiones con rutas de actualización definidas. | F95: Jefe de Ingeniería de la Nube y Plataformas | G95: L2 | H95: Núcleo y Plataforma | I95: Previene la expansión tecnológica que haría imposible la remediación a nivel de plataforma y la planificación de competencias. | J95: Código abierto, seleccionado internamente | K95: microservicios Spring Boot; microservicios Modyo Connect; Temenos DES API/componentes; EKS/ECS/Fargate; Kubernetes; Mesh de servicio Istio.
A96: 3 | B96: 3 | C96: 13.1.3 | D96: Servicios del núcleo | E96: Servicios fundacionales de plataforma consumidos por todos los dominios, incluido el inventario formal de servicios que los registra. | F96: Jefe de Ingeniería de la Nube y Plataformas | G96: L2 | H96: Núcleo y Plataforma | I96: Un inventario autorizado es la condición previa para regular la reutilización y para calcular el coste del patrimonio. | J96: Código abierto, seleccionado internamente | K96: microservicios Spring Boot; microservicios Modyo Connect; Temenos DES API/componentes; EKS/ECS/Fargate; Kubernetes; Mesh de servicio Istio.
A97: 3 | B97: 4 | C97: 13.1.4 | D97: Descubrimiento del servicio | E97: Registro dinámico y resolución de instancias de servicio en tiempo de ejecución. | F97: Jefe de Ingeniería de la Nube y Plataformas | G97: L2 | H97: Núcleo y Plataforma | I97: Permite un escalado elástico y reubicación sin configuración estática del extremo. | J97: Código abierto, seleccionado internamente | K97: Mesh de servicio Istio en Kubernetes/EKS; Descubrimiento de servicios EKS y balanceo de carga para microservicios.
A98: 3 | B98: 5 | C98: 13.1.5 | D98: Malla de servicio | E98: Control basado en sidecar del tráfico de servicio a servicio, incluyendo autenticación mutua y validación de token en la capa de plataforma. | F98: Jefe de Ingeniería de la Nube y Plataformas | G98: L2 | H98: Núcleo y Plataforma | I98: Desplaza la seguridad interservicios y el control de tráfico fuera del código de la aplicación, simplificando cada servicio. | J98: Código abierto, seleccionado internamente | K98: Mesh de servicio Istio en Kubernetes/EKS; Descubrimiento de servicios EKS y balanceo de carga para microservicios.
A99: 2 | B99: 2 | C99: 13.2 | D99: Contenedor y plataforma de ejecución | E99: Orquestación de contenedores, ejecución serverless y gestión de imágenes proporcionan el sustrato elástico de cómputo para componentes de interoperabilidad. | F99: Jefe de Ingeniería de la Nube y Plataformas | G99: L1 | H99: Núcleo y Plataforma | I99: Proporciona agilidad en el despliegue y escalabilidad impulsada por la demanda, y es el vehículo práctico para la portabilidad entre proveedores de nube y entornos híbridos. | J99: Terceros | K99: Amazon EKS/Kubernetes; ECS/Fargate para Modyo Connect; OpenShift referenciado en el panel técnico; Docker/registro de contenedores.
A100: 3 | B100: 1 | C100: 13.2.1 | D100: Orquestación en contenedores | E100: Programación, escalado, auto-reparación y colocación de carga de trabajo de servicios contenedores. | F100: Jefe de Ingeniería de la Nube y Plataformas | G100: L2 | H100: Núcleo y Plataforma | I100: Ofrece la elasticidad que las arquitecturas desacopladas necesitan para atender económicamente la demanda digital de forma económica. | J100: Terceros | K100: Amazon EKS/Kubernetes; ECS/Fargate para Modyo Connect; OpenShift referenciado en el panel técnico; Docker/registro de contenedores.
A101: 3 | B101: 2 | C101: 13.2.2 | D101: Tiempo de ejecución sin servidor | E101: Ejecución activada por eventos y basada en consumo para funciones ligeras y de ráfagas. | F101: Jefe de Ingeniería de la Nube y Plataformas | G101: L2 | H101: Núcleo y Plataforma | I101: Extiende los modelos de costes basados en el consumo a cargas de trabajo de integración y transformación de datos. | J101: Terceros | K101: No se evidencia explícitamente ningún tiempo de ejecución serverless dedicado; los servicios gestionados adyacentes AWS incluyen Amazon API Gateway, CloudFront, Pinpoint, MQ y Kinesis.
A102: 3 | B102: 3 | C102: 13.2.3 | D102: Gestión de imágenes y artefactos | E102: Registro, streaming, firma y promoción de imágenes en tiempo real y artefactos de construcción. | F102: Jefe de Ingeniería de la Nube y Plataformas | G102: L2 | H102: Núcleo y Plataforma | I102: Garantiza la procedencia y la velocidad de despliegue, ambos requisitos previos para una alta frecuencia de lanzamientos. | J102: Terceros | K102: Imágenes doradas Packer; repositorios GitHub; registro de contenedores/ECR área de decisión; Helm Charts; Tuberías de artefactos DevSecOps.
A103: 2 | B103: 3 | C103: 13.3 | D103: Automatización de configuración de plataformas | E103: Provisión y configuración declarativa y automatizada de componentes y entornos de plataforma, incluyendo servicios centralizados de configuración de aplicaciones. | F103: Jefe de Ingeniería de la Nube y Plataformas | G103: L1 | H103: Núcleo y Plataforma | I103: Elimina la inconsistencia en el entorno que hace que las pruebas distribuidas sean poco fiables y las versiones impredecibles. | J103: Código abierto + terceros | K103: Terraform + Packer + GitHub; módulos IaC; Homologación de Ambientes; posibles patrones Ansible/CloudFormation; Vault/Secrets para seguridad de configuración.
...

Sheet PH Horizontal Expansion
A1: Arquitectura de Interoperabilidad / Componibilidad - Jerarquía de Capacidades | Plataforma = dominio de capacidad L0, Subplataforma = grupo de capacidades L1, Proceso = capacidad L2
A4: PID de Plataforma | B4: Plataforma | C4: Descripción de la Plataforma | D4: PID de Subplataforma | E4: Subplataforma | F4: Descripción de la Subplataforma | G4: ID de Proceso | H4: Procesos | I4: Descripción/Definición | J4: Propósito en la Arquitectura Interoperable | K4: Soluciones BanCoppel Utilizadas (Proyecto)
A5: 5 | B5: =SUBSTITUTE(_xlfn.TRANSLATE(SUBSTITUTE(__TR_HORIZONTAL!B5,"API","XQZ0QX"),"en","es"),"XQZ0QX","API") -> Gestión API | C5: =SUBSTITUTE(_xlfn.TRANSLATE(SUBSTITUTE(__TR_HORIZONTAL!C5,"BIAN","XQZ0QX"),"en","es"),"XQZ0QX","BIAN") -> La capacidad de diseñar, publicar, asegurar, versionar, medir y retirar los contratos de servicios síncronos del banco, junto con el conjunto de viviendas orientadas al promotor que los rodea (catálogo, portal, sandbox). Cubre tanto el plano de ejecución (mediación de pasarela, enrutamiento, política de tráfico) como el plano de control (ciclo de vida, administración de políticas, análisis). | PROPÓSITO: Instrumento principal de desacoplamiento de la arquitectura interoperable. Un contrato estable basado en estándares (alineado con BIAN o personalizado canónico) permite que un canal se re-platforme sin tocar un núcleo, y que un núcleo sea reemplazado sin tocar un canal. También es el punto de control semántico donde una petición deja de ser una llamada a un sistema específico y pasa a llamar a una capacidad bancaria. | D5: 5.1 | E5: =SUBSTITUTE(_xlfn.TRANSLATE(SUBSTITUTE(__TR_HORIZONTAL!E5,"API","XQZ0QX"),"en","es"),"XQZ0QX","API") -> Pasarela API y Mediación en tiempo de ejecución | F5: =SUBSTITUTE(_xlfn.TRANSLATE(SUBSTITUTE(__TR_HORIZONTAL!F5,"API","XQZ0QX"),"en","es"),"XQZ0QX","API") -> Plano de ejecución que termina, valida, media y enruta el tráfico API entre consumidores y proveedores, aplicando la política en el punto de invocación en lugar de dentro del código de la aplicación. | PROPÓSITO: Hacer cumplir el contrato en tiempo de ejecución, para que el desacoplamiento esté garantizado por la plataforma en lugar de por la disciplina del desarrollador. | G5: 5.1.1 | H5: =_xlfn.TRANSLATE(__TR_HORIZONTAL!H5,"en","es") -> Enrutamiento | I5: =SUBSTITUTE(_xlfn.TRANSLATE(SUBSTITUTE(__TR_HORIZONTAL!I5,"API","XQZ0QX"),"en","es"),"XQZ0QX","API") -> Resolución de un contrato lógico API a uno o más puntos finales físicos de servicio, incluyendo enrutamiento basado en host, versión y entorno. | J5: =_xlfn.TRANSLATE(__TR_HORIZONTAL!J5,"en","es") -> Permite la reubicación del backend, la re-plataforma y el doble funcionamiento de procesadores antiguos y nuevos sin ningún cambio de consumidor. | K5: =SUBSTITUTE(SUBSTITUTE(SUBSTITUTE(SUBSTITUTE(SUBSTITUTE(SUBSTITUTE(SUBSTITUTE(SUBSTITUTE(SUBSTITUTE(_xlfn.TRANSLATE(SUBSTITUTE(SUBSTITUTE(SUBSTITUTE(SUBSTITUTE(SUBSTITUTE(SUBSTITUTE(SUBSTITUTE(SUBSTITUTE(SUBSTITUTE(__TR_HORIZONTAL!K5,"Apigee API Gateway/API Management","XQZ0QX"),"WebMethods","XQZ1QX"),"MuleSoft","XQZ2QX"),"BPM/BRM","XQZ3QX"),"OFS/IRIS","XQZ4QX"),"REST","XQZ5QX"),"BIAN","XQZ6QX"),"APIs","XQZ7QX"),"API","XQZ8QX"),"en","es"),"XQZ0QX","Apigee API Gateway/API Management"),"XQZ1QX","WebMethods"),"XQZ2QX","MuleSoft"),"XQZ3QX","BPM/BRM"),"XQZ4QX","OFS/IRIS"),"XQZ5QX","REST"),"XQZ6QX","BIAN"),"XQZ7QX","APIs"),"XQZ8QX","API") -> Apigee API Gateway/API Management; integración/orquestación MuleSoft; WebMethods BPM/BRM; BIAN alineado APIs; Transacta OFS/IRIS REST APIs.
G6: 5.1.2 | H6: =_xlfn.TRANSLATE(__TR_HORIZONTAL!H6,"en","es") -> Mediación y transformación del mensaje | I6: =SUBSTITUTE(SUBSTITUTE(SUBSTITUTE(_xlfn.TRANSLATE(SUBSTITUTE(SUBSTITUTE(SUBSTITUTE(__TR_HORIZONTAL!I6,"REST","XQZ0QX"),"SOAP","XQZ1QX"),"gRPC","XQZ2QX"),"en","es"),"XQZ0QX","REST"),"XQZ1QX","SOAP"),"XQZ2QX","gRPC") -> Adaptación de protocolos y cargas útiles en el edge (REST, SOAP, gRPC, protocolos heredados), incluyendo manipulación de cabeceras y mapeo canónico-nativo. | J6: =_xlfn.TRANSLATE(__TR_HORIZONTAL!J6,"en","es") -> Absorbe la heterogeneidad técnica de un conjunto híbrido de núcleo, de modo que los consumidores solo ven un estilo de interfaz. | K6: =SUBSTITUTE(SUBSTITUTE(SUBSTITUTE(SUBSTITUTE(SUBSTITUTE(SUBSTITUTE(SUBSTITUTE(SUBSTITUTE(SUBSTITUTE(_xlfn.TRANSLATE(SUBSTITUTE(SUBSTITUTE(SUBSTITUTE(SUBSTITUTE(SUBSTITUTE(SUBSTITUTE(SUBSTITUTE(SUBSTITUTE(SUBSTITUTE(__TR_HORIZONTAL!K6,"Apigee API Gateway/API Management","XQZ0QX"),"WebMethods","XQZ1QX"),"MuleSoft","XQZ2QX"),"BPM/BRM","XQZ3QX"),"OFS/IRIS","XQZ4QX"),"REST","XQZ5QX"),"BIAN","XQZ6QX"),"APIs","XQZ7QX"),"API","XQZ8QX"),"en","es"),"XQZ0QX","Apigee API Gateway/API Management"),"XQZ1QX","WebMethods"),"XQZ2QX","MuleSoft"),"XQZ3QX","BPM/BRM"),"XQZ4QX","OFS/IRIS"),"XQZ5QX","REST"),"XQZ6QX","BIAN"),"XQZ7QX","APIs"),"XQZ8QX","API") -> Apigee API Gateway/API Management; integración/orquestación MuleSoft; WebMethods BPM/BRM; BIAN alineado APIs; Transacta OFS/IRIS REST APIs.
G7: 5.1.3 | H7: =SUBSTITUTE(_xlfn.TRANSLATE(SUBSTITUTE(__TR_HORIZONTAL!H7,"API","XQZ0QX"),"en","es"),"XQZ0QX","API") -> API Gestión de Tráfico | I7: =SUBSTITUTE(_xlfn.TRANSLATE(SUBSTITUTE(__TR_HORIZONTAL!I7,"API","XQZ0QX"),"en","es"),"XQZ0QX","API") -> Cuotas, límites de tarifa, limitación, arresto de picos y políticas de calidad de servicio aplicadas por consumidor, por API y por nivel. | J7: =_xlfn.TRANSLATE(__TR_HORIZONTAL!J7,"en","es") -> Protege la capacidad finita heredada (MIPS, pools de conexión) frente a la demanda digital ilimitada y convierte la capacidad en un recurso gobernado y con precio. | K7: =SUBSTITUTE(SUBSTITUTE(SUBSTITUTE(SUBSTITUTE(SUBSTITUTE(SUBSTITUTE(SUBSTITUTE(SUBSTITUTE(SUBSTITUTE(_xlfn.TRANSLATE(SUBSTITUTE(SUBSTITUTE(SUBSTITUTE(SUBSTITUTE(SUBSTITUTE(SUBSTITUTE(SUBSTITUTE(SUBSTITUTE(SUBSTITUTE(__TR_HORIZONTAL!K7,"Apigee API Gateway/API Management","XQZ0QX"),"WebMethods","XQZ1QX"),"MuleSoft","XQZ2QX"),"BPM/BRM","XQZ3QX"),"OFS/IRIS","XQZ4QX"),"REST","XQZ5QX"),"BIAN","XQZ6QX"),"APIs","XQZ7QX"),"API","XQZ8QX"),"en","es"),"XQZ0QX","Apigee API Gateway/API Management"),"XQZ1QX","WebMethods"),"XQZ2QX","MuleSoft"),"XQZ3QX","BPM/BRM"),"XQZ4QX","OFS/IRIS"),"XQZ5QX","REST"),"XQZ6QX","BIAN"),"XQZ7QX","APIs"),"XQZ8QX","API") -> Apigee API Gateway/API Management; integración/orquestación MuleSoft; WebMethods BPM/BRM; BIAN alineado APIs; Transacta OFS/IRIS REST APIs.
G8: 5.1.4 | H8: =_xlfn.TRANSLATE(__TR_HORIZONTAL!H8,"en","es") -> Validación de mensajes y protección de carga útil | I8: =_xlfn.TRANSLATE(__TR_HORIZONTAL!I8,"en","es") -> Validación de esquema, tamaño y contenido de mensajes entrantes y salientes, incluyendo protección contra ataques basados en contenido. | J8: =_xlfn.TRANSLATE(__TR_HORIZONTAL!J8,"en","es") -> Detiene el tráfico malformado y hostil antes de que llegue al parque de procesamiento, donde la remediación es mucho más cara. | K8: =SUBSTITUTE(SUBSTITUTE(SUBSTITUTE(SUBSTITUTE(SUBSTITUTE(SUBSTITUTE(SUBSTITUTE(SUBSTITUTE(SUBSTITUTE(_xlfn.TRANSLATE(SUBSTITUTE(SUBSTITUTE(SUBSTITUTE(SUBSTITUTE(SUBSTITUTE(SUBSTITUTE(SUBSTITUTE(SUBSTITUTE(SUBSTITUTE(__TR_HORIZONTAL!K8,"Apigee API Gateway/API Management","XQZ0QX"),"WebMethods","XQZ1QX"),"MuleSoft","XQZ2QX"),"BPM/BRM","XQZ3QX"),"OFS/IRIS","XQZ4QX"),"REST","XQZ5QX"),"BIAN","XQZ6QX"),"APIs","XQZ7QX"),"API","XQZ8QX"),"en","es"),"XQZ0QX","Apigee API Gateway/API Management"),"XQZ1QX","WebMethods"),"XQZ2QX","MuleSoft"),"XQZ3QX","BPM/BRM"),"XQZ4QX","OFS/IRIS"),"XQZ5QX","REST"),"XQZ6QX","BIAN"),"XQZ7QX","APIs"),"XQZ8QX","API") -> Apigee API Gateway/API Management; integración/orquestación MuleSoft; WebMethods BPM/BRM; BIAN alineado APIs; Transacta OFS/IRIS REST APIs.
G9: 5.1.5 | H9: =_xlfn.TRANSLATE(__TR_HORIZONTAL!H9,"en","es") -> Gestión de errores y normalización de fallos | I9: =_xlfn.TRANSLATE(__TR_HORIZONTAL!I9,"en","es") -> Taxonomía de errores estandarizada, mapeo de fallos y códigos de respuesta a través de backends heterogéneos. | J9: =_xlfn.TRANSLATE(__TR_HORIZONTAL!J9,"en","es") -> Evita que la semántica de error específica del backend se filtre en los canales, que es una de las fuentes más comunes de acoplamiento oculto. | K9: =SUBSTITUTE(SUBSTITUTE(SUBSTITUTE(SUBSTITUTE(SUBSTITUTE(SUBSTITUTE(SUBSTITUTE(SUBSTITUTE(SUBSTITUTE(_xlfn.TRANSLATE(SUBSTITUTE(SUBSTITUTE(SUBSTITUTE(SUBSTITUTE(SUBSTITUTE(SUBSTITUTE(SUBSTITUTE(SUBSTITUTE(SUBSTITUTE(__TR_HORIZONTAL!K9,"Apigee API Gateway/API Management","XQZ0QX"),"WebMethods","XQZ1QX"),"MuleSoft","XQZ2QX"),"BPM/BRM","XQZ3QX"),"OFS/IRIS","XQZ4QX"),"REST","XQZ5QX"),"BIAN","XQZ6QX"),"APIs","XQZ7QX"),"API","XQZ8QX"),"en","es"),"XQZ0QX","Apigee API Gateway/API Management"),"XQZ1QX","WebMethods"),"XQZ2QX","MuleSoft"),"XQZ3QX","BPM/BRM"),"XQZ4QX","OFS/IRIS"),"XQZ5QX","REST"),"XQZ6QX","BIAN"),"XQZ7QX","APIs"),"XQZ8QX","API") -> Apigee API Gateway/API Management; integración/orquestación MuleSoft; WebMethods BPM/BRM; BIAN alineado APIs; Transacta OFS/IRIS REST APIs.
D10: 5.2 | E10: =SUBSTITUTE(_xlfn.TRANSLATE(SUBSTITUTE(__TR_HORIZONTAL!E10,"API","XQZ0QX"),"en","es"),"XQZ0QX","API") -> Gestión del ciclo de vida API | F10: =SUBSTITUTE(_xlfn.TRANSLATE(SUBSTITUTE(__TR_HORIZONTAL!F10,"API","XQZ0QX"),"en","es"),"XQZ0QX","API") -> Plano de control que gobierna un API desde el diseño y la definición del contrato hasta la publicación, el cambio de versiones, la notificación de cambios y su eventual retirada. | PROPÓSITO: Convierte las interfaces en activos empresariales gestionados con una ruta de cambio controlada, que es la condición previa para su reutilización entre entidades y países. | G10: 5.2.1 | H10: =SUBSTITUTE(_xlfn.TRANSLATE(SUBSTITUTE(__TR_HORIZONTAL!H10,"API","XQZ0QX"),"en","es"),"XQZ0QX","API") -> Normas de diseño y contratos API | I10: =SUBSTITUTE(_xlfn.TRANSLATE(SUBSTITUTE(__TR_HORIZONTAL!I10,"BIAN","XQZ0QX"),"en","es"),"XQZ0QX","BIAN") -> Definición y aplicación de estándares de interfaz, nombres canónicos o alineados con BIAN, y puertas de revisión de diseño antes de la publicación. | J10: =_xlfn.TRANSLATE(__TR_HORIZONTAL!J10,"en","es") -> Garantiza que las nuevas interfaces aumenten la reutilización en lugar de añadir otra integración personalizada para mantener. | K10: =SUBSTITUTE(SUBSTITUTE(SUBSTITUTE(SUBSTITUTE(_xlfn.TRANSLATE(SUBSTITUTE(SUBSTITUTE(SUBSTITUTE(SUBSTITUTE(__TR_HORIZONTAL!K10,"OpenAPI","XQZ0QX"),"Swagger","XQZ1QX"),"BIAN","XQZ2QX"),"API","XQZ3QX"),"en","es"),"XQZ0QX","OpenAPI"),"XQZ1QX","Swagger"),"XQZ2QX","BIAN"),"XQZ3QX","API") -> Estándares BIAN API; Apigee API ciclo de vida/gobernanza; Documentación al estilo OpenAPI/Swagger para OfiWeb/Canales; El cambio API está controlado por la gobernanza de la arquitectura.
G11: 5.2.2 | H11: =SUBSTITUTE(_xlfn.TRANSLATE(SUBSTITUTE(__TR_HORIZONTAL!H11,"API","XQZ0QX"),"en","es"),"XQZ0QX","API") -> Versionado API | I11: =_xlfn.TRANSLATE(__TR_HORIZONTAL!I11,"en","es") -> Soporte simultáneo de múltiples versiones de contrato con reglas definidas de compatibilidad y deprecación. | J11: =_xlfn.TRANSLATE(__TR_HORIZONTAL!J11,"en","es") -> Desacopla los ciclos de lanzamiento entre consumidores y proveedores, de modo que ningún cambio individual requiera un despliegue sincronizado de big bang. | K11: =SUBSTITUTE(SUBSTITUTE(SUBSTITUTE(SUBSTITUTE(_xlfn.TRANSLATE(SUBSTITUTE(SUBSTITUTE(SUBSTITUTE(SUBSTITUTE(__TR_HORIZONTAL!K11,"OpenAPI","XQZ0QX"),"Swagger","XQZ1QX"),"BIAN","XQZ2QX"),"API","XQZ3QX"),"en","es"),"XQZ0QX","OpenAPI"),"XQZ1QX","Swagger"),"XQZ2QX","BIAN"),"XQZ3QX","API") -> Estándares BIAN API; Apigee API ciclo de vida/gobernanza; Documentación al estilo OpenAPI/Swagger para OfiWeb/Canales; El cambio API está controlado por la gobernanza de la arquitectura.
G12: 5.2.3 | H12: =SUBSTITUTE(_xlfn.TRANSLATE(SUBSTITUTE(__TR_HORIZONTAL!H12,"API","XQZ0QX"),"en","es"),"XQZ0QX","API") -> Notificación de publicación y cambio API | I12: =SUBSTITUTE(SUBSTITUTE(_xlfn.TRANSLATE(SUBSTITUTE(SUBSTITUTE(__TR_HORIZONTAL!I12,"APIs","XQZ0QX"),"API","XQZ1QX"),"en","es"),"XQZ0QX","APIs"),"XQZ1QX","API") -> Promoción de APIs en entornos y notificación proactiva de cambios de contrato a los consumidores registrados. | J12: =_xlfn.TRANSLATE(__TR_HORIZONTAL!J12,"en","es") -> Elimina la sobrecarga de coordinación que de otro modo hace que los equipos eviten reutilizar una interfaz compartida. | K12: =SUBSTITUTE(SUBSTITUTE(SUBSTITUTE(SUBSTITUTE(_xlfn.TRANSLATE(SUBSTITUTE(SUBSTITUTE(SUBSTITUTE(SUBSTITUTE(__TR_HORIZONTAL!K12,"OpenAPI","XQZ0QX"),"Swagger","XQZ1QX"),"BIAN","XQZ2QX"),"API","XQZ3QX"),"en","es"),"XQZ0QX","OpenAPI"),"XQZ1QX","Swagger"),"XQZ2QX","BIAN"),"XQZ3QX","API") -> Estándares BIAN API; Apigee API ciclo de vida/gobernanza; Documentación al estilo OpenAPI/Swagger para OfiWeb/Canales; El cambio API está controlado por la gobernanza de la arquitectura.
G13: 5.2.4 | H13: =SUBSTITUTE(_xlfn.TRANSLATE(SUBSTITUTE(__TR_HORIZONTAL!H13,"API","XQZ0QX"),"en","es"),"XQZ0QX","API") -> API Depreciación y Retiro | I13: =_xlfn.TRANSLATE(__TR_HORIZONTAL!I13,"en","es") -> Un control de la desaparición de interfaces, incluyendo el seguimiento de migración del consumidor y la aplicación de fechas de fin de vida. | J13: =_xlfn.TRANSLATE(__TR_HORIZONTAL!J13,"en","es") -> Evita que la capa de interoperabilidad acumule la misma deuda de interfaz que fue creada para eliminar. | K13: =SUBSTITUTE(SUBSTITUTE(SUBSTITUTE(SUBSTITUTE(_xlfn.TRANSLATE(SUBSTITUTE(SUBSTITUTE(SUBSTITUTE(SUBSTITUTE(__TR_HORIZONTAL!K13,"OpenAPI","XQZ0QX"),"Swagger","XQZ1QX"),"BIAN","XQZ2QX"),"API","XQZ3QX"),"en","es"),"XQZ0QX","OpenAPI"),"XQZ1QX","Swagger"),"XQZ2QX","BIAN"),"XQZ3QX","API") -> Estándares BIAN API; Apigee API ciclo de vida/gobernanza; Documentación al estilo OpenAPI/Swagger para OfiWeb/Canales; El cambio API está controlado por la gobernanza de la arquitectura.
D14: 5.3 | E14: =SUBSTITUTE(_xlfn.TRANSLATE(SUBSTITUTE(__TR_HORIZONTAL!E14,"API","XQZ0QX"),"en","es"),"XQZ0QX","API") -> API Manager (Administración de Plataforma) | F14: =SUBSTITUTE(_xlfn.TRANSLATE(SUBSTITUTE(__TR_HORIZONTAL!F14,"API","XQZ0QX"),"en","es"),"XQZ0QX","API") -> Administración, configuración de políticas, operación e instrumentación comercial de la propia plataforma de gestión API, tanto en topologías locales, en la nube como en la nube o híbridas. | PROPÓSITO: Mantiene la política administrada de forma centralizada y aplicada de forma consistente, para que las normas de seguridad y tráfico no se fragmenten por equipo API. | G14: 5.3.1 | H14: =_xlfn.TRANSLATE(__TR_HORIZONTAL!H14,"en","es") -> Administración y Seguimiento de Políticas | I14: =SUBSTITUTE(_xlfn.TRANSLATE(SUBSTITUTE(__TR_HORIZONTAL!I14,"API","XQZ0QX"),"en","es"),"XQZ0QX","API") -> Definición central, asignación y auditoría de políticas de pasarela (seguridad, tráfico, mediación, caché) a lo largo del patrimonio API. | J14: =_xlfn.TRANSLATE(__TR_HORIZONTAL!J14,"en","es") -> Convierte la política en un elemento de configuración gobernado en lugar de código embebido, permitiendo cambios a nivel de estado en una sola acción. | K14: =SUBSTITUTE(SUBSTITUTE(SUBSTITUTE(SUBSTITUTE(SUBSTITUTE(_xlfn.TRANSLATE(SUBSTITUTE(SUBSTITUTE(SUBSTITUTE(SUBSTITUTE(SUBSTITUTE(__TR_HORIZONTAL!K14,"DataDog","XQZ0QX"),"DevSecOps","XQZ1QX"),"API","XQZ2QX"),"AWS","XQZ3QX"),"GCP","XQZ4QX"),"en","es"),"XQZ0QX","DataDog"),"XQZ1QX","DevSecOps"),"XQZ2QX","API"),"XQZ3QX","AWS"),"XQZ4QX","GCP") -> Administración y políticas de plataformas Apigee; Monitorización DataDog/API; tuberías DevSecOps; Apigee alojado en GCP con proveedores AWS/locales.
G15: 5.3.2 | H15: =SUBSTITUTE(_xlfn.TRANSLATE(SUBSTITUTE(__TR_HORIZONTAL!H15,"API","XQZ0QX"),"en","es"),"XQZ0QX","API") -> API Monitorización, Analítica y Monetización | I15: =SUBSTITUTE(_xlfn.TRANSLATE(SUBSTITUTE(__TR_HORIZONTAL!I15,"API","XQZ0QX"),"en","es"),"XQZ0QX","API") -> Métricas de consumo, latencia y análisis de errores por API y por consumidor, con base de medición para devolución interna o monetización de socios. | J15: =_xlfn.TRANSLATE(__TR_HORIZONTAL!J15,"en","es") -> Proporciona la base de evidencia para las afirmaciones de reutilización, la planificación de capacidades y los modelos comerciales de ecosistemas. | K15: =SUBSTITUTE(SUBSTITUTE(SUBSTITUTE(SUBSTITUTE(SUBSTITUTE(_xlfn.TRANSLATE(SUBSTITUTE(SUBSTITUTE(SUBSTITUTE(SUBSTITUTE(SUBSTITUTE(__TR_HORIZONTAL!K15,"DataDog","XQZ0QX"),"DevSecOps","XQZ1QX"),"API","XQZ2QX"),"AWS","XQZ3QX"),"GCP","XQZ4QX"),"en","es"),"XQZ0QX","DataDog"),"XQZ1QX","DevSecOps"),"XQZ2QX","API"),"XQZ3QX","AWS"),"XQZ4QX","GCP") -> Administración y políticas de plataformas Apigee; Monitorización DataDog/API; tuberías DevSecOps; Apigee alojado en GCP con proveedores AWS/locales.
G16: 5.3.3 | H16: =_xlfn.TRANSLATE(__TR_HORIZONTAL!H16,"en","es") -> Despliegue y operaciones de la plataforma | I16: =SUBSTITUTE(_xlfn.TRANSLATE(SUBSTITUTE(__TR_HORIZONTAL!I16,"API","XQZ0QX"),"en","es"),"XQZ0QX","API") -> Topología de despliegue, automatización, actualización y soporte operativo de la plataforma de gestión API. | J16: =_xlfn.TRANSLATE(__TR_HORIZONTAL!J16,"en","es") -> Garantiza que la capa de desacoplamiento sea en sí misma resiliente y actualizable, ya que se convierte en un punto único de dependencia para todo el tráfico. | K16: =SUBSTITUTE(SUBSTITUTE(SUBSTITUTE(SUBSTITUTE(SUBSTITUTE(_xlfn.TRANSLATE(SUBSTITUTE(SUBSTITUTE(SUBSTITUTE(SUBSTITUTE(SUBSTITUTE(__TR_HORIZONTAL!K16,"DataDog","XQZ0QX"),"DevSecOps","XQZ1QX"),"API","XQZ2QX"),"AWS","XQZ3QX"),"GCP","XQZ4QX"),"en","es"),"XQZ0QX","DataDog"),"XQZ1QX","DevSecOps"),"XQZ2QX","API"),"XQZ3QX","AWS"),"XQZ4QX","GCP") -> Administración y políticas de plataformas Apigee; Monitorización DataDog/API; tuberías DevSecOps; Apigee alojado en GCP con proveedores AWS/locales.
D17: 5.4 | E17: =_xlfn.TRANSLATE(__TR_HORIZONTAL!E17,"en","es") -> Portal y catálogo para desarrolladores | F17: =_xlfn.TRANSLATE(__TR_HORIZONTAL!F17,"en","es") -> Superficie de autoservicio donde desarrolladores internos y externos descubren, evalúan, se registran y se apoyan en interfaces publicadas. | PROPÓSITO: La reutilización solo ocurre si se pueden encontrar capacidades. El portal convierte un inventario técnico en un catálogo de productos consumibles. | G17: 5.4.1 | H17: =SUBSTITUTE(_xlfn.TRANSLATE(SUBSTITUTE(__TR_HORIZONTAL!H17,"API","XQZ0QX"),"en","es"),"XQZ0QX","API") -> Catálogo, documentación y descubrimiento de metadatos API | I17: =_xlfn.TRANSLATE(__TR_HORIZONTAL!I17,"en","es") -> Inventario consultable de interfaces publicadas con especificaciones, ejemplos y metadatos. | J17: =_xlfn.TRANSLATE(__TR_HORIZONTAL!J17,"en","es") -> Elimina el coste de redescubrimiento que impulsa a los equipos a construir una integración paralela punto a punto. | K17: =SUBSTITUTE(_xlfn.TRANSLATE(SUBSTITUTE(__TR_HORIZONTAL!K17,"API","XQZ0QX"),"en","es"),"XQZ0QX","API") -> Catálogo/gobernanza API para Apificación de Canales y OfiWeb; Apígeo como plano de gestión API. No se evidencia explícitamente ninguna herramienta de portal para desarrolladores independiente.
G18: 5.4.2 | H18: =_xlfn.TRANSLATE(__TR_HORIZONTAL!H18,"en","es") -> Registro de desarrolladores y autoservicio | I18: =SUBSTITUTE(_xlfn.TRANSLATE(SUBSTITUTE(__TR_HORIZONTAL!I18,"API","XQZ0QX"),"en","es"),"XQZ0QX","API") -> Incorporación, emisión de credenciales, registro de solicitudes y gestión de derechos para consumidores de API. | J18: =_xlfn.TRANSLATE(__TR_HORIZONTAL!J18,"en","es") -> Elimina el control humano del camino de consumo, que es lo que hace que la reutilización interna y la incorporación de parejas sea rápida. | K18: =SUBSTITUTE(_xlfn.TRANSLATE(SUBSTITUTE(__TR_HORIZONTAL!K18,"API","XQZ0QX"),"en","es"),"XQZ0QX","API") -> Catálogo/gobernanza API para Apificación de Canales y OfiWeb; Apígeo como plano de gestión API. No se evidencia explícitamente ninguna herramienta de portal para desarrolladores independiente.
G19: 5.4.3 | H19: =_xlfn.TRANSLATE(__TR_HORIZONTAL!H19,"en","es") -> Colaboración, comunidad y autoapoyo | I19: =_xlfn.TRANSLATE(__TR_HORIZONTAL!I19,"en","es") -> Informes de problemas, bucles de retroalimentación, guías de uso, SDKs y ejemplos de referencia para equipos que consumen. | J19: =_xlfn.TRANSLATE(__TR_HORIZONTAL!J19,"en","es") -> Proporciona la capa de habilitación sin la cual una capacidad publicada está técnicamente disponible pero prácticamente no se utiliza. | K19: =SUBSTITUTE(_xlfn.TRANSLATE(SUBSTITUTE(__TR_HORIZONTAL!K19,"API","XQZ0QX"),"en","es"),"XQZ0QX","API") -> Catálogo/gobernanza API para Apificación de Canales y OfiWeb; Apígeo como plano de gestión API. No se evidencia explícitamente ninguna herramienta de portal para desarrolladores independiente.
A20: 4 | B20: =_xlfn.TRANSLATE(__TR_HORIZONTAL!B20,"en","es") -> Servicios de Gateway | C20: =SUBSTITUTE(SUBSTITUTE(_xlfn.TRANSLATE(SUBSTITUTE(SUBSTITUTE(__TR_HORIZONTAL!C20,"Open Banking","XQZ0QX"),"API","XQZ1QX"),"en","es"),"XQZ0QX","Open Banking"),"XQZ1QX","API") -> Controlaba la entrada y salida a través del límite de confianza del banco en tres modalidades - API, archivo y evento - tanto en direcciones entrantes como salientes, además de los bordes especializados necesarios para tráfico regulado y de socios (borde Open Banking, borde de filtro, servicio de token de seguridad, sandbox de socios, conmutación). | PROPÓSITO: La interoperabilidad no es solo interna. Este dominio concentra la zonificación de red, terminación de protocolos, cifrado y política de tráfico para todas las contrapartes externas (banco central, procesadores de tarjetas, esquemas de pago, agencias, fintechs, canales corporativos) de modo que la participación en el ecosistema se convierta en un ejercicio de configuración en lugar de un proyecto. También es donde la mayoría de los bancos encuentran asimetría: las gateways entrantes API están maduras mientras que las gateways de archivos y eventos salientes no están definidas, y esa brecha queda en el camino crítico. | D20: 4.1 | E20: =_xlfn.TRANSLATE(__TR_HORIZONTAL!E20,"en","es") -> Servicios de pasarela entrantes | F20: =SUBSTITUTE(_xlfn.TRANSLATE(SUBSTITUTE(__TR_HORIZONTAL!F20,"API","XQZ0QX"),"en","es"),"XQZ0QX","API") -> Puntos de entrada gestionados para tráfico que se origina fuera del límite de confianza del banco, a través de API, canales de archivos y eventos, incluyendo el intercambio de aserturas de identidad en el borde. | PROPÓSITO: Da al banco una puerta principal gobernada por modalidad en lugar de una proliferación de conexiones bilaterales con controles inconsistentes. | G20: 4.1.1 | H20: =SUBSTITUTE(_xlfn.TRANSLATE(SUBSTITUTE(__TR_HORIZONTAL!H20,"API","XQZ0QX"),"en","es"),"XQZ0QX","API") -> Pasarela entrante API | I20: =SUBSTITUTE(_xlfn.TRANSLATE(SUBSTITUTE(__TR_HORIZONTAL!I20,"API","XQZ0QX"),"en","es"),"XQZ0QX","API") -> Terminación, autenticación, aplicación de políticas y enrutamiento del tráfico API síncrono procedente de canales, socios y terceros. | J20: =_xlfn.TRANSLATE(__TR_HORIZONTAL!J20,"en","es") -> Punto único de aplicación para demanda síncrona externa, desacoplando a las contrapartes de la topología interna del servicio. | K20: =SUBSTITUTE(SUBSTITUTE(SUBSTITUTE(SUBSTITUTE(SUBSTITUTE(SUBSTITUTE(_xlfn.TRANSLATE(SUBSTITUTE(SUBSTITUTE(SUBSTITUTE(SUBSTITUTE(SUBSTITUTE(SUBSTITUTE(__TR_HORIZONTAL!K20,"Amazon API Gateway","XQZ0QX"),"Modyo Connect","XQZ1QX"),"WebMethods","XQZ2QX"),"MuleSoft","XQZ3QX"),"API","XQZ4QX"),"EKS","XQZ5QX"),"en","es"),"XQZ0QX","Amazon API Gateway"),"XQZ1QX","Modyo Connect"),"XQZ2QX","WebMethods"),"XQZ3QX","MuleSoft"),"XQZ4QX","API"),"XQZ5QX","EKS") -> Gateway de entrada/salida API de Apigee; integración MuleSoft/WebMethods; Amazon API Gateway vía Modyo Connect; EKS/Istio Service Edge.
G21: 4.1.2 | H21: =_xlfn.TRANSLATE(__TR_HORIZONTAL!H21,"en","es") -> Pasarela de Archivos Entrantes | I21: =_xlfn.TRANSLATE(__TR_HORIZONTAL!I21,"en","es") -> Recepción segura, validación, escaneo de virus y transferencia de archivos originados externamente, reemplazando la transferencia punto a punto no gestionada. | J21: =SUBSTITUTE(_xlfn.TRANSLATE(SUBSTITUTE(__TR_HORIZONTAL!J21,"API","XQZ0QX"),"en","es"),"XQZ0QX","API") -> Coloca el gran conjunto residual de lotes bajo el mismo régimen de control y observabilidad que el tráfico API. | K21: =_xlfn.TRANSLATE(__TR_HORIZONTAL!K21,"en","es") -> DataStage ETL; interfaces por lotes/COB; Flujos de documentos OnBase; Interfaces heredadas de archivos/datos de PISA/Informix. No hay ningún producto MFT dedicado a evidencia explícita.
G22: 4.1.3 | H22: =SUBSTITUTE(_xlfn.TRANSLATE(SUBSTITUTE(__TR_HORIZONTAL!H22,"EventHub","XQZ0QX"),"en","es"),"XQZ0QX","EventHub") -> Pasarela entrante EventHub | I22: =_xlfn.TRANSLATE(__TR_HORIZONTAL!I22,"en","es") -> Gestión controlada de eventos y mensajes publicados externamente en la columna vertebral interna de eventos. | J22: =_xlfn.TRANSLATE(__TR_HORIZONTAL!J22,"en","es") -> Permite la integración en tiempo real del ecosistema (esquemas, agregadores, datos de mercado) sin exponer temas internos. | K22: =_xlfn.TRANSLATE(__TR_HORIZONTAL!K22,"en","es") -> Kafka/Confluent; Amazon MQ; Kinesis amazónica; Marco de Eventos Temenos; Componentes de procesador de eventos/router de eventos/limpieza de eventos.
G23: 4.1.4 | H23: =_xlfn.TRANSLATE(__TR_HORIZONTAL!H23,"en","es") -> Servicio de Token de Seguridad (STS) | I23: =_xlfn.TRANSLATE(__TR_HORIZONTAL!I23,"en","es") -> Emisión, intercambio y validación de tokens de seguridad en el perímetro, traduciendo las afirmaciones de identidad externas en credenciales internas. | J23: =_xlfn.TRANSLATE(__TR_HORIZONTAL!J23,"en","es") -> Permite respetar las identidades federadas y de socios sin extender los límites internos de fideicomiso. | K23: =SUBSTITUTE(SUBSTITUTE(SUBSTITUTE(_xlfn.TRANSLATE(SUBSTITUTE(SUBSTITUTE(SUBSTITUTE(__TR_HORIZONTAL!K23,"Microsoft Entra ID","XQZ0QX"),"API","XQZ1QX"),"OAuth 2.0","XQZ2QX"),"en","es"),"XQZ0QX","Microsoft Entra ID"),"XQZ1QX","API"),"XQZ2QX","OAuth 2.0") -> OAuth 2.0 vía Apigee; Azure AD / Microsoft Entra ID; Identidad del Partido Token; tokens de aplicación/usuario gestionados mediante la seguridad API.
D24: 4.2 | E24: =_xlfn.TRANSLATE(__TR_HORIZONTAL!E24,"en","es") -> Servicios de Pasarela de Salida | F24: =SUBSTITUTE(_xlfn.TRANSLATE(SUBSTITUTE(__TR_HORIZONTAL!F24,"API","XQZ0QX"),"en","es"),"XQZ0QX","API") -> Gestionó puntos de salida para tráfico originado por bancos hacia contrapartes aguas abajo, a través de API, canales de archivos y eventos, incluyendo el cambio de transacciones a esquemas y procesadores. | PROPÓSITO: Externaliza la conectividad y credenciales específicas de la contraparte del código de la aplicación, para que un proveedor pueda ser reemplazado sin tocar los servicios empresariales. | G24: 4.2.1 | H24: =SUBSTITUTE(_xlfn.TRANSLATE(SUBSTITUTE(__TR_HORIZONTAL!H24,"API","XQZ0QX"),"en","es"),"XQZ0QX","API") -> Pasarela API de salida | I24: =_xlfn.TRANSLATE(__TR_HORIZONTAL!I24,"en","es") -> Mediación de salida, inyección de credenciales, reintentos y control de circuitos para llamadas a proveedores externos, expuestas a través de una DMZ. | J24: =_xlfn.TRANSLATE(__TR_HORIZONTAL!J24,"en","es") -> Convierte la sustitución por terceros en un cambio de configuración de gateway en lugar de un proyecto de desarrollo. | K24: =SUBSTITUTE(SUBSTITUTE(SUBSTITUTE(SUBSTITUTE(SUBSTITUTE(SUBSTITUTE(_xlfn.TRANSLATE(SUBSTITUTE(SUBSTITUTE(SUBSTITUTE(SUBSTITUTE(SUBSTITUTE(SUBSTITUTE(__TR_HORIZONTAL!K24,"Amazon API Gateway","XQZ0QX"),"Modyo Connect","XQZ1QX"),"WebMethods","XQZ2QX"),"MuleSoft","XQZ3QX"),"API","XQZ4QX"),"EKS","XQZ5QX"),"en","es"),"XQZ0QX","Amazon API Gateway"),"XQZ1QX","Modyo Connect"),"XQZ2QX","WebMethods"),"XQZ3QX","MuleSoft"),"XQZ4QX","API"),"XQZ5QX","EKS") -> Gateway de entrada/salida API de Apigee; integración MuleSoft/WebMethods; Amazon API Gateway vía Modyo Connect; EKS/Istio Service Edge.
G25: 4.2.2 | H25: =_xlfn.TRANSLATE(__TR_HORIZONTAL!H25,"en","es") -> Pasarela de Archivos Salientes | I25: =_xlfn.TRANSLATE(__TR_HORIZONTAL!I25,"en","es") -> Generación, cifrado, programación y transmisión gestionadas de archivos salientes, sustituyendo a los arreglos SFTP no gestionados. | J25: =_xlfn.TRANSLATE(__TR_HORIZONTAL!J25,"en","es") -> Cierra la brecha de control y observabilidad más común en el estado externo. | K25: =_xlfn.TRANSLATE(__TR_HORIZONTAL!K25,"en","es") -> DataStage ETL; interfaces por lotes/COB; Flujos de documentos OnBase; Interfaces heredadas de archivos/datos de PISA/Informix. No hay ningún producto MFT dedicado a evidencia explícita.
G26: 4.2.3 | H26: =SUBSTITUTE(_xlfn.TRANSLATE(SUBSTITUTE(__TR_HORIZONTAL!H26,"EventHub","XQZ0QX"),"en","es"),"XQZ0QX","EventHub") -> Pasarela EventHub de salida | I26: =_xlfn.TRANSLATE(__TR_HORIZONTAL!I26,"en","es") -> Publicación controlada de eventos internos a suscriptores externos mediante filtrado y gobernanza contractual. | J26: =_xlfn.TRANSLATE(__TR_HORIZONTAL!J26,"en","es") -> Permite al banco ofrecer productos de datos en tiempo real al ecosistema sin conceder acceso a temas internos. | K26: =_xlfn.TRANSLATE(__TR_HORIZONTAL!K26,"en","es") -> Kafka/Confluent; Amazon MQ; Kinesis amazónica; Marco de Eventos Temenos; Componentes de procesador de eventos/router de eventos/limpieza de eventos.
G27: 4.2.4 | H27: =_xlfn.TRANSLATE(__TR_HORIZONTAL!H27,"en","es") -> Conmutación | I27: =_xlfn.TRANSLATE(__TR_HORIZONTAL!I27,"en","es") -> Enrutamiento y adaptación de protocolos del tráfico de transacciones a esquemas, procesadores y redes interbancarias, incluyendo la conmutación por error entre proveedores. | J27: =_xlfn.TRANSLATE(__TR_HORIZONTAL!J27,"en","es") -> Proporciona redundancia de proveedores y enrutamiento de menor coste como propiedad arquitectónica más que como resultado de negociación. | K27: =SUBSTITUTE(_xlfn.TRANSLATE(SUBSTITUTE(__TR_HORIZONTAL!K27,"SmartVista","XQZ0QX"),"en","es"),"XQZ0QX","SmartVista") -> BPC SmartVista/SVIP para conmutación y procesamiento de tarjetas; Hub de Pagos para SPEI, dispersión de nóminas y pagos multiplataforma; coexistencia legada entre IST y PISA.
D28: 4.3 | E28: =SUBSTITUTE(_xlfn.TRANSLATE(SUBSTITUTE(__TR_HORIZONTAL!E28,"Open Banking","XQZ0QX"),"en","es"),"XQZ0QX","Open Banking") -> Ecosistema & Open Banking Edge | F28: =_xlfn.TRANSLATE(__TR_HORIZONTAL!F28,"en","es") -> Bordes externos especializados para tráfico regulado de banca abierta, incorporación de socios y experimentación controlada, incluyendo bordes de filtrado y exposición al mercado. | PROPÓSITO: Cuando la capa de interoperabilidad se convierte en un canal de negocio: convierte capacidades internas en productos consumibles y contratados para terceros. | G28: 4.3.1 | H28: =SUBSTITUTE(_xlfn.TRANSLATE(SUBSTITUTE(__TR_HORIZONTAL!H28,"Open Banking","XQZ0QX"),"en","es"),"XQZ0QX","Open Banking") -> Open Banking Edge | I28: =SUBSTITUTE(SUBSTITUTE(_xlfn.TRANSLATE(SUBSTITUTE(SUBSTITUTE(__TR_HORIZONTAL!I28,"APIs","XQZ0QX"),"API","XQZ1QX"),"en","es"),"XQZ0QX","APIs"),"XQZ1QX","API") -> Exposición conforme a la normativa de cuentas, pagos y datos APIs con consentimiento, obligaciones sólidas de autenticación e informe. | J28: =_xlfn.TRANSLATE(__TR_HORIZONTAL!J28,"en","es") -> Cumple con los mandatos regulatorios en una plataforma compartida en lugar de como un silo aislado de cumplimiento. | K28: =SUBSTITUTE(SUBSTITUTE(SUBSTITUTE(SUBSTITUTE(_xlfn.TRANSLATE(SUBSTITUTE(SUBSTITUTE(SUBSTITUTE(SUBSTITUTE(__TR_HORIZONTAL!K28,"Open Banking","XQZ0QX"),"BIAN","XQZ1QX"),"APIs","XQZ2QX"),"API","XQZ3QX"),"en","es"),"XQZ0QX","Open Banking"),"XQZ1QX","BIAN"),"XQZ2QX","APIs"),"XQZ3QX","API") -> No se evidencia ningún producto sandbox específico de Open Banking en el marketplace o socio; las capacidades adyacentes utilizan Apigee, API Gateway, BIAN APIs y entornos sandbox/UAT.
G29: 4.3.2 | H29: =_xlfn.TRANSLATE(__TR_HORIZONTAL!H29,"en","es") -> Borde del filtro | I29: =SUBSTITUTE(_xlfn.TRANSLATE(SUBSTITUTE(__TR_HORIZONTAL!I29,"API","XQZ0QX"),"en","es"),"XQZ0QX","API") -> Filtrado y filtro de tráfico externo basado en contenido, consumidores y geografía antes de la pasarela API. | J29: =_xlfn.TRANSLATE(__TR_HORIZONTAL!J29,"en","es") -> Reduce la carga hostil y fuera de la política antes de que consuma la capacidad de gateway o backend. | K29: =SUBSTITUTE(SUBSTITUTE(SUBSTITUTE(SUBSTITUTE(_xlfn.TRANSLATE(SUBSTITUTE(SUBSTITUTE(SUBSTITUTE(SUBSTITUTE(__TR_HORIZONTAL!K29,"Cloud Armor","XQZ0QX"),"AWS","XQZ1QX"),"GCP","XQZ2QX"),"TLS","XQZ3QX"),"en","es"),"XQZ0QX","Cloud Armor"),"XQZ1QX","AWS"),"XQZ2QX","GCP"),"XQZ3QX","TLS") -> Imperva WAF / Cloud Armor; Escudo AWS; Terminación Zscaler TLS; VPN/Conexión Directa; Reglas de la tetración; AWS/GCP/zonificación de red local.
G30: 4.3.3 | H30: =_xlfn.TRANSLATE(__TR_HORIZONTAL!H30,"en","es") -> Sandbox de socios | I30: =_xlfn.TRANSLATE(__TR_HORIZONTAL!I30,"en","es") -> Entorno aislado no productivo con datos representativos para el desarrollo y certificación de socios y fintech. | J30: =_xlfn.TRANSLATE(__TR_HORIZONTAL!J30,"en","es") -> Comprime la incorporación de socios de meses a semanas, que es la limitación práctica en la estrategia del ecosistema. | K30: =SUBSTITUTE(SUBSTITUTE(SUBSTITUTE(SUBSTITUTE(_xlfn.TRANSLATE(SUBSTITUTE(SUBSTITUTE(SUBSTITUTE(SUBSTITUTE(__TR_HORIZONTAL!K30,"Open Banking","XQZ0QX"),"BIAN","XQZ1QX"),"APIs","XQZ2QX"),"API","XQZ3QX"),"en","es"),"XQZ0QX","Open Banking"),"XQZ1QX","BIAN"),"XQZ2QX","APIs"),"XQZ3QX","API") -> No se evidencia ningún producto sandbox específico de Open Banking en el marketplace o socio; las capacidades adyacentes utilizan Apigee, API Gateway, BIAN APIs y entornos sandbox/UAT.
G31: 4.3.4 | H31: =SUBSTITUTE(_xlfn.TRANSLATE(SUBSTITUTE(__TR_HORIZONTAL!H31,"API","XQZ0QX"),"en","es"),"XQZ0QX","API") -> Mercado API | I31: =_xlfn.TRANSLATE(__TR_HORIZONTAL!I31,"en","es") -> Catálogo comercial para envases, publicaciones y capacidades de contratación bancarias para consumidores externos. | J31: =_xlfn.TRANSLATE(__TR_HORIZONTAL!J31,"en","es") -> Proporciona la interfaz para modelos de negocio no lineales de capacidad como producto. | K31: =SUBSTITUTE(SUBSTITUTE(SUBSTITUTE(SUBSTITUTE(_xlfn.TRANSLATE(SUBSTITUTE(SUBSTITUTE(SUBSTITUTE(SUBSTITUTE(__TR_HORIZONTAL!K31,"Open Banking","XQZ0QX"),"BIAN","XQZ1QX"),"APIs","XQZ2QX"),"API","XQZ3QX"),"en","es"),"XQZ0QX","Open Banking"),"XQZ1QX","BIAN"),"XQZ2QX","APIs"),"XQZ3QX","API") -> No se evidencia ningún producto sandbox específico de Open Banking en el marketplace o socio; las capacidades adyacentes utilizan Apigee, API Gateway, BIAN APIs y entornos sandbox/UAT.
D32: 4.4 | E32: =_xlfn.TRANSLATE(__TR_HORIZONTAL!E32,"en","es") -> Zonificación perimetral y conectividad | F32: =_xlfn.TRANSLATE(__TR_HORIZONTAL!F32,"en","es") -> Segmentación de red, modelo de exposición DMZ, terminación de seguridad del transporte y gestión de conectividad que sustentan todas las modalidades de pasarela. | PROPÓSITO: Establece la topología de confianza dentro de la cual opera cualquier otra capacidad de pasarela; Sin él, el desacoplamiento aumenta la exposición en lugar de contenerla. | G32: 4.4.1 | H32: =_xlfn.TRANSLATE(__TR_HORIZONTAL!H32,"en","es") -> Zonificación de redes y exposición a la DMZ | I32: =_xlfn.TRANSLATE(__TR_HORIZONTAL!I32,"en","es") -> Definición y aplicación de las zonas de seguridad, y el patrón DMZ a través del cual las capacidades internas se exponen externamente. | J32: =_xlfn.TRANSLATE(__TR_HORIZONTAL!J32,"en","es") -> Garantiza que las nuevas interfaces externas hereden un modelo de exposición aprobado en lugar de negociar uno por proyecto. | K32: =SUBSTITUTE(SUBSTITUTE(SUBSTITUTE(SUBSTITUTE(_xlfn.TRANSLATE(SUBSTITUTE(SUBSTITUTE(SUBSTITUTE(SUBSTITUTE(__TR_HORIZONTAL!K32,"Cloud Armor","XQZ0QX"),"AWS","XQZ1QX"),"GCP","XQZ2QX"),"TLS","XQZ3QX"),"en","es"),"XQZ0QX","Cloud Armor"),"XQZ1QX","AWS"),"XQZ2QX","GCP"),"XQZ3QX","TLS") -> Imperva WAF / Cloud Armor; Escudo AWS; Terminación Zscaler TLS; VPN/Conexión Directa; Reglas de la tetración; AWS/GCP/zonificación de red local.
G33: 4.4.2 | H33: =_xlfn.TRANSLATE(__TR_HORIZONTAL!H33,"en","es") -> Terminación de la seguridad del transporte | I33: =SUBSTITUTE(_xlfn.TRANSLATE(SUBSTITUTE(__TR_HORIZONTAL!I33,"TLS","XQZ0QX"),"en","es"),"XQZ0QX","TLS") -> Terminación TLS, autenticación mutua y gestión de políticas de cifrado en el edge. | J33: =_xlfn.TRANSLATE(__TR_HORIZONTAL!J33,"en","es") -> Centraliza la moneda criptográfica, de modo que las deprecaciones de protocolo se gestionan una vez en vez de por aplicación. | K33: =SUBSTITUTE(SUBSTITUTE(SUBSTITUTE(SUBSTITUTE(_xlfn.TRANSLATE(SUBSTITUTE(SUBSTITUTE(SUBSTITUTE(SUBSTITUTE(__TR_HORIZONTAL!K33,"Cloud Armor","XQZ0QX"),"AWS","XQZ1QX"),"GCP","XQZ2QX"),"TLS","XQZ3QX"),"en","es"),"XQZ0QX","Cloud Armor"),"XQZ1QX","AWS"),"XQZ2QX","GCP"),"XQZ3QX","TLS") -> Imperva WAF / Cloud Armor; Escudo AWS; Terminación Zscaler TLS; VPN/Conexión Directa; Reglas de la tetración; AWS/GCP/zonificación de red local.
G34: 4.4.3 | H34: =_xlfn.TRANSLATE(__TR_HORIZONTAL!H34,"en","es") -> Gestión de la conectividad externa | I34: =_xlfn.TRANSLATE(__TR_HORIZONTAL!I34,"en","es") -> Registro, credenciales, endpoints y monitorización operativa de las conexiones de contraparte. | J34: =_xlfn.TRANSLATE(__TR_HORIZONTAL!J34,"en","es") -> Crea un inventario autoritativo de dependencias externas, que es un requisito previo para la gestión de riesgos de terceros. | K34: =SUBSTITUTE(SUBSTITUTE(SUBSTITUTE(SUBSTITUTE(_xlfn.TRANSLATE(SUBSTITUTE(SUBSTITUTE(SUBSTITUTE(SUBSTITUTE(__TR_HORIZONTAL!K34,"Cloud Armor","XQZ0QX"),"AWS","XQZ1QX"),"GCP","XQZ2QX"),"TLS","XQZ3QX"),"en","es"),"XQZ0QX","Cloud Armor"),"XQZ1QX","AWS"),"XQZ2QX","GCP"),"XQZ3QX","TLS") -> Imperva WAF / Cloud Armor; Escudo AWS; Terminación Zscaler TLS; VPN/Conexión Directa; Reglas de la tetración; AWS/GCP/zonificación de red local.
A35: 1 | B35: =_xlfn.TRANSLATE(__TR_HORIZONTAL!B35,"en","es") -> Seguridad | C35: =SUBSTITUTE(_xlfn.TRANSLATE(SUBSTITUTE(__TR_HORIZONTAL!C35,"API","XQZ0QX"),"en","es"),"XQZ0QX","API") -> Protección de extremo a extremo de la propia capa de interoperabilidad: gestión de identidad y acceso, servicios criptográficos, gestión de certificados y secretos, protección contra amenazas, gestión de vulnerabilidades y amenazas, y monitorización y respuesta de seguridad en los conjuntos API, eventos, archivos y contenedores. | OBJETIVO: El desacoplamiento multiplica el número de saltos de red, credenciales y relaciones de confianza en el patrimonio. Sin una capacidad de seguridad a nivel de núcleo, cada nuevo servicio reimplementa sus propios controles y la superficie de ataque crece más rápido que la funcionalidad. El objetivo de diseño es que la seguridad se herede de la plataforma, no se codifica por servicio, lo que también aplana la curva de costes de remediación de vulnerabilidades a medida que el número de servicios crece hasta cientos. | D35: 1.1 | E35: =_xlfn.TRANSLATE(__TR_HORIZONTAL!E35,"en","es") -> Gestión de Identidad y Acceso | F35: =_xlfn.TRANSLATE(__TR_HORIZONTAL!F35,"en","es") -> Servicios de autenticación, autorización, token y sesión para clientes, empleados, socios e identidades de máquinas que consumen la capa de interoperabilidad. | PROPÓSITO: Proporciona la única respuesta autorizada a quién llama y qué puede hacer, para que la lógica de derechos se elimine de los servicios empresariales. | G35: 1.1.1 | H35: =_xlfn.TRANSLATE(__TR_HORIZONTAL!H35,"en","es") -> Servicios de autenticación | I35: =_xlfn.TRANSLATE(__TR_HORIZONTAL!I35,"en","es") -> Verificación de la identidad del usuario y del sistema, incluyendo autenticación multifactor y step-up, como un servicio compartido. | J35: =_xlfn.TRANSLATE(__TR_HORIZONTAL!J35,"en","es") -> Elimina las implementaciones de autenticación por aplicación, que son la principal fuente de una fuerza de control inconsistente. | K35: =SUBSTITUTE(SUBSTITUTE(SUBSTITUTE(_xlfn.TRANSLATE(SUBSTITUTE(SUBSTITUTE(SUBSTITUTE(__TR_HORIZONTAL!K35,"Microsoft Entra ID","XQZ0QX"),"HashiCorp Vault","XQZ1QX"),"OAuth 2.0","XQZ2QX"),"en","es"),"XQZ0QX","Microsoft Entra ID"),"XQZ1QX","HashiCorp Vault"),"XQZ2QX","OAuth 2.0") -> OAuth 2.0 vía Apigee; Azure AD / Microsoft Entra ID; Identidad del Partido Token; Identidad de código/KYC; HashiCorp Vault para soporte de credenciales.
G36: 1.1.2 | H36: =_xlfn.TRANSLATE(__TR_HORIZONTAL!H36,"en","es") -> Servicios de autorización | I36: =_xlfn.TRANSLATE(__TR_HORIZONTAL!I36,"en","es") -> Evaluación centralizada de derechos y invocación de políticas en servicio, incluyendo decisiones basadas en roles y atributos. | J36: =_xlfn.TRANSLATE(__TR_HORIZONTAL!J36,"en","es") -> Mantiene la coherencia de la autorización mientras los servicios se recomponen entre proveedores tradicionales, de nueva generación y terceros. | K36: =SUBSTITUTE(SUBSTITUTE(SUBSTITUTE(_xlfn.TRANSLATE(SUBSTITUTE(SUBSTITUTE(SUBSTITUTE(__TR_HORIZONTAL!K36,"Microsoft Entra ID","XQZ0QX"),"HashiCorp Vault","XQZ1QX"),"OAuth 2.0","XQZ2QX"),"en","es"),"XQZ0QX","Microsoft Entra ID"),"XQZ1QX","HashiCorp Vault"),"XQZ2QX","OAuth 2.0") -> OAuth 2.0 vía Apigee; Azure AD / Microsoft Entra ID; Identidad del Partido Token; Identidad de código/KYC; HashiCorp Vault para soporte de credenciales.
G37: 1.1.3 | H37: =_xlfn.TRANSLATE(__TR_HORIZONTAL!H37,"en","es") -> Token de acceso y inicio de sesión único | I37: =_xlfn.TRANSLATE(__TR_HORIZONTAL!I37,"en","es") -> Emisión, actualización, introspección y revocación de tokens de acceso, y propagación de identidad entre salto de servicio. | J37: =_xlfn.TRANSLATE(__TR_HORIZONTAL!J37,"en","es") -> Preserva la identidad del llamante de extremo a extremo mediante orquestaciones, lo que hace posible la auditoría distribuida. | K37: =SUBSTITUTE(SUBSTITUTE(SUBSTITUTE(_xlfn.TRANSLATE(SUBSTITUTE(SUBSTITUTE(SUBSTITUTE(__TR_HORIZONTAL!K37,"Microsoft Entra ID","XQZ0QX"),"HashiCorp Vault","XQZ1QX"),"OAuth 2.0","XQZ2QX"),"en","es"),"XQZ0QX","Microsoft Entra ID"),"XQZ1QX","HashiCorp Vault"),"XQZ2QX","OAuth 2.0") -> OAuth 2.0 vía Apigee; Azure AD / Microsoft Entra ID; Identidad del Partido Token; Identidad de código/KYC; HashiCorp Vault para soporte de credenciales.
G38: 1.1.4 | H38: =_xlfn.TRANSLATE(__TR_HORIZONTAL!H38,"en","es") -> Servicios de Sesión | I38: =_xlfn.TRANSLATE(__TR_HORIZONTAL!I38,"en","es") -> Creación, validación, tiempo de espera y terminación de sesiones entre canales y dominios. | J38: =_xlfn.TRANSLATE(__TR_HORIZONTAL!J38,"en","es") -> Permite la continuidad omnicanal sin que cada canal mantenga el estado de sesión privada. | K38: =SUBSTITUTE(SUBSTITUTE(SUBSTITUTE(_xlfn.TRANSLATE(SUBSTITUTE(SUBSTITUTE(SUBSTITUTE(__TR_HORIZONTAL!K38,"Microsoft Entra ID","XQZ0QX"),"HashiCorp Vault","XQZ1QX"),"OAuth 2.0","XQZ2QX"),"en","es"),"XQZ0QX","Microsoft Entra ID"),"XQZ1QX","HashiCorp Vault"),"XQZ2QX","OAuth 2.0") -> OAuth 2.0 vía Apigee; Azure AD / Microsoft Entra ID; Identidad del Partido Token; Identidad de código/KYC; HashiCorp Vault para soporte de credenciales.
G39: 1.1.5 | H39: =_xlfn.TRANSLATE(__TR_HORIZONTAL!H39,"en","es") -> Administración de Usuarios, Políticas y Credenciales | I39: =_xlfn.TRANSLATE(__TR_HORIZONTAL!I39,"en","es") -> Administración de identidades, derechos, almacenes de pólizas y credenciales de máquinas. | J39: =_xlfn.TRANSLATE(__TR_HORIZONTAL!J39,"en","es") -> Ofrece a auditores y operadores un lugar para evidenciar y cambiar el acceso en todo el ámbito de interoperabilidad. | K39: =SUBSTITUTE(SUBSTITUTE(SUBSTITUTE(_xlfn.TRANSLATE(SUBSTITUTE(SUBSTITUTE(SUBSTITUTE(__TR_HORIZONTAL!K39,"Microsoft Entra ID","XQZ0QX"),"HashiCorp Vault","XQZ1QX"),"OAuth 2.0","XQZ2QX"),"en","es"),"XQZ0QX","Microsoft Entra ID"),"XQZ1QX","HashiCorp Vault"),"XQZ2QX","OAuth 2.0") -> OAuth 2.0 vía Apigee; Azure AD / Microsoft Entra ID; Identidad del Partido Token; Identidad de código/KYC; HashiCorp Vault para soporte de credenciales.
D40: 1.2 | E40: =_xlfn.TRANSLATE(__TR_HORIZONTAL!E40,"en","es") -> Servicios cripto | F40: =_xlfn.TRANSLATE(__TR_HORIZONTAL!F40,"en","es") -> Operaciones criptográficas compartidas —firma, cifrado, protección de carga útil de extremo a extremo— se entregaban como servicios llamables respaldados por módulos de seguridad de hardware y almacenes de claves gestionados. | PROPÓSITO: Concentra los controles de mayor garantía en un solo componente certificado, para que la criptografía se consuma en lugar de reimplemente. | G40: 1.2.1 | H40: =_xlfn.TRANSLATE(__TR_HORIZONTAL!H40,"en","es") -> Operaciones Emblemáticas | I40: =_xlfn.TRANSLATE(__TR_HORIZONTAL!I40,"en","es") -> Generación y verificación de firma digital para transacciones, documentos y mensajes intersistemas. | J40: =_xlfn.TRANSLATE(__TR_HORIZONTAL!J40,"en","es") -> Proporciona la no repudiación a través de los límites del sistema, lo cual se vuelve esencial una vez que una transacción abarca varias plataformas. | K40: =SUBSTITUTE(SUBSTITUTE(SUBSTITUTE(_xlfn.TRANSLATE(SUBSTITUTE(SUBSTITUTE(SUBSTITUTE(__TR_HORIZONTAL!K40,"HSM","XQZ0QX"),"TLS","XQZ1QX"),"SSL","XQZ2QX"),"en","es"),"XQZ0QX","HSM"),"XQZ1QX","TLS"),"XQZ2QX","SSL") -> cifrado AES-256; TLS/SSL; Gestión de claves HSM; Oracle TDE; Istio mTLS; Firma de código/NOM-151 para contratos de incorporación.
G41: 1.2.2 | H41: =_xlfn.TRANSLATE(__TR_HORIZONTAL!H41,"en","es") -> Operaciones de cifrado | I41: =_xlfn.TRANSLATE(__TR_HORIZONTAL!I41,"en","es") -> Servicios de cifrado y descifrado para datos en tránsito y en reposo, incluyendo la tokenización de campos sensibles. | J41: =_xlfn.TRANSLATE(__TR_HORIZONTAL!J41,"en","es") -> Permite que los datos sensibles atraviesen un patrimonio distribuido sin ampliar el alcance de cumplimiento de cada componente que pasa. | K41: =SUBSTITUTE(SUBSTITUTE(SUBSTITUTE(_xlfn.TRANSLATE(SUBSTITUTE(SUBSTITUTE(SUBSTITUTE(__TR_HORIZONTAL!K41,"HSM","XQZ0QX"),"TLS","XQZ1QX"),"SSL","XQZ2QX"),"en","es"),"XQZ0QX","HSM"),"XQZ1QX","TLS"),"XQZ2QX","SSL") -> cifrado AES-256; TLS/SSL; Gestión de claves HSM; Oracle TDE; Istio mTLS; Firma de código/NOM-151 para contratos de incorporación.
G42: 1.2.3 | H42: =_xlfn.TRANSLATE(__TR_HORIZONTAL!H42,"en","es") -> Cifrado de extremo a extremo | I42: =_xlfn.TRANSLATE(__TR_HORIZONTAL!I42,"en","es") -> Protección a nivel de carga útil mantenida desde el canal de origen hasta el procesador final, independientemente de los saltos de transporte. | J42: =_xlfn.TRANSLATE(__TR_HORIZONTAL!J42,"en","es") -> Mantiene los datos confidenciales entre intermediarios, lo cual es un requisito previo para el uso de procesadores de terceros y SaaS. | K42: =SUBSTITUTE(SUBSTITUTE(SUBSTITUTE(_xlfn.TRANSLATE(SUBSTITUTE(SUBSTITUTE(SUBSTITUTE(__TR_HORIZONTAL!K42,"HSM","XQZ0QX"),"TLS","XQZ1QX"),"SSL","XQZ2QX"),"en","es"),"XQZ0QX","HSM"),"XQZ1QX","TLS"),"XQZ2QX","SSL") -> cifrado AES-256; TLS/SSL; Gestión de claves HSM; Oracle TDE; Istio mTLS; Firma de código/NOM-151 para contratos de incorporación.
G43: 1.2.4 | H43: =SUBSTITUTE(_xlfn.TRANSLATE(SUBSTITUTE(__TR_HORIZONTAL!H43,"HSM","XQZ0QX"),"en","es"),"XQZ0QX","HSM") -> Almacenamiento de claves y gestión HSM | I43: =_xlfn.TRANSLATE(__TR_HORIZONTAL!I43,"en","es") -> Gestión del ciclo de vida de las claves criptográficas y los módulos de hardware que las protegen. | J43: =_xlfn.TRANSLATE(__TR_HORIZONTAL!J43,"en","es") -> Previene la expansión de llaves, el modo de fallo que suele bloquear la migración en la nube de cargas de trabajo reguladas. | K43: =SUBSTITUTE(SUBSTITUTE(SUBSTITUTE(_xlfn.TRANSLATE(SUBSTITUTE(SUBSTITUTE(SUBSTITUTE(__TR_HORIZONTAL!K43,"HSM","XQZ0QX"),"TLS","XQZ1QX"),"SSL","XQZ2QX"),"en","es"),"XQZ0QX","HSM"),"XQZ1QX","TLS"),"XQZ2QX","SSL") -> cifrado AES-256; TLS/SSL; Gestión de claves HSM; Oracle TDE; Istio mTLS; Firma de código/NOM-151 para contratos de incorporación.
D44: 1.3 | E44: =_xlfn.TRANSLATE(__TR_HORIZONTAL!E44,"en","es") -> Gestión de certificados y secretos | F44: =_xlfn.TRANSLATE(__TR_HORIZONTAL!F44,"en","es") -> Emisión, distribución, rotación, revocación y auditoría de certificados y secretos de aplicaciones consumidos por servicios, gateways y pipelines. | PROPÓSITO: Automatiza la higiene operativa que falla con mayor frecuencia a gran escala; Los certificados caducados y los secretos codificados en forma dura son algunas de las causas más frecuentes de interrupciones y hallazgos de auditorías en herencias distribuidas. | G44: 1.3.1 | H44: =_xlfn.TRANSLATE(__TR_HORIZONTAL!H44,"en","es") -> Gestión de Certificados | I44: =_xlfn.TRANSLATE(__TR_HORIZONTAL!I44,"en","es") -> Emisión automatizada de certificados, inventario, monitorización de caducidad, renovación y revocación en toda la herencia. | J44: =_xlfn.TRANSLATE(__TR_HORIZONTAL!J44,"en","es") -> Elimina una causa principal de interrupciones autoinfligidas a medida que el número de puntos finales cifrados se multiplica. | K44: =SUBSTITUTE(SUBSTITUTE(SUBSTITUTE(SUBSTITUTE(SUBSTITUTE(SUBSTITUTE(_xlfn.TRANSLATE(SUBSTITUTE(SUBSTITUTE(SUBSTITUTE(SUBSTITUTE(SUBSTITUTE(SUBSTITUTE(__TR_HORIZONTAL!K44,"HashiCorp Vault","XQZ0QX"),"AWS Secrets Manager","XQZ1QX"),"Kubernetes","XQZ2QX"),"AWS","XQZ3QX"),"HSM","XQZ4QX"),"SSL","XQZ5QX"),"en","es"),"XQZ0QX","HashiCorp Vault"),"XQZ1QX","AWS Secrets Manager"),"XQZ2QX","Kubernetes"),"XQZ3QX","AWS"),"XQZ4QX","HSM"),"XQZ5QX","SSL") -> HashiCorp Vault; AWS Secrets Manager; Kubernetes Secretos; gestión de certificados SSL; HSM para operaciones clave críticas.
G45: 1.3.2 | H45: =_xlfn.TRANSLATE(__TR_HORIZONTAL!H45,"en","es") -> Gestión secreta | I45: =SUBSTITUTE(_xlfn.TRANSLATE(SUBSTITUTE(__TR_HORIZONTAL!I45,"API","XQZ0QX"),"en","es"),"XQZ0QX","API") -> Almacenamiento centralizado, inyección dinámica, rotación y auditoría de credenciales, claves API y cadenas de conexión. | J45: =_xlfn.TRANSLATE(__TR_HORIZONTAL!J45,"en","es") -> Elimina secretos del código y la configuración, convirtiendo la rotación de credenciales en una operación rutinaria de plataforma. | K45: =SUBSTITUTE(SUBSTITUTE(SUBSTITUTE(SUBSTITUTE(SUBSTITUTE(SUBSTITUTE(_xlfn.TRANSLATE(SUBSTITUTE(SUBSTITUTE(SUBSTITUTE(SUBSTITUTE(SUBSTITUTE(SUBSTITUTE(__TR_HORIZONTAL!K45,"HashiCorp Vault","XQZ0QX"),"AWS Secrets Manager","XQZ1QX"),"Kubernetes","XQZ2QX"),"AWS","XQZ3QX"),"HSM","XQZ4QX"),"SSL","XQZ5QX"),"en","es"),"XQZ0QX","HashiCorp Vault"),"XQZ1QX","AWS Secrets Manager"),"XQZ2QX","Kubernetes"),"XQZ3QX","AWS"),"XQZ4QX","HSM"),"XQZ5QX","SSL") -> HashiCorp Vault; AWS Secrets Manager; Kubernetes Secretos; gestión de certificados SSL; HSM para operaciones clave críticas.
D46: 1.4 | E46: =_xlfn.TRANSLATE(__TR_HORIZONTAL!E46,"en","es") -> Protección contra amenazas | F46: =SUBSTITUTE(_xlfn.TRANSLATE(SUBSTITUTE(__TR_HORIZONTAL!F46,"API","XQZ0QX"),"en","es"),"XQZ0QX","API") -> Detección y mitigación de tráfico hostil y técnicas de ataque en tiempo de ejecución en el perímetro, en la capa API y dentro del contenedor y plataformas de streaming. | PROPÓSITO: Protege la superficie de ataque ensanchada que necesariamente crea el desacoplamiento, en las capas donde la exposición es mayor. | G46: 1.4.1 | H46: =SUBSTITUTE(_xlfn.TRANSLATE(SUBSTITUTE(__TR_HORIZONTAL!H46,"API","XQZ0QX"),"en","es"),"XQZ0QX","API") -> API Seguridad y Protección por Inyección | I46: =SUBSTITUTE(_xlfn.TRANSLATE(SUBSTITUTE(__TR_HORIZONTAL!I46,"API","XQZ0QX"),"en","es"),"XQZ0QX","API") -> Protección contra inyección, manipulación de parámetros, autorizaciones fallidas y otras clases de ataque de la capa API, con aplicación de políticas en la puerta de enlace. | J46: =_xlfn.TRANSLATE(__TR_HORIZONTAL!J46,"en","es") -> Protege las interfaces de las que depende el caso de negocio para exponer, por lo que la apertura no se traduce en riesgo. | K46: =SUBSTITUTE(SUBSTITUTE(SUBSTITUTE(_xlfn.TRANSLATE(SUBSTITUTE(SUBSTITUTE(SUBSTITUTE(__TR_HORIZONTAL!K46,"HashiCorp Vault","XQZ0QX"),"Cloud Armor","XQZ1QX"),"AWS","XQZ2QX"),"en","es"),"XQZ0QX","HashiCorp Vault"),"XQZ1QX","Cloud Armor"),"XQZ2QX","AWS") -> Imperva WAF; Cloud Armor; AWS Shield; Apigee OAuth/limitación de tasa; Malla de servicio Istio; Exabeam SIEM; HashiCorp Vault y controles de endurecimiento.
G47: 1.4.2 | H47: =_xlfn.TRANSLATE(__TR_HORIZONTAL!H47,"en","es") -> Protección contra amenazas perimetrales | I47: =_xlfn.TRANSLATE(__TR_HORIZONTAL!I47,"en","es") -> Cortafuegos de aplicaciones web, mitigación de denegación de servicio y gestión de bots en el borde de la red. | J47: =_xlfn.TRANSLATE(__TR_HORIZONTAL!J47,"en","es") -> Absorbe tráfico de ataque volumétrico y automatizado antes de que alcance la capacidad de la pasarela o la aplicación. | K47: =SUBSTITUTE(SUBSTITUTE(SUBSTITUTE(_xlfn.TRANSLATE(SUBSTITUTE(SUBSTITUTE(SUBSTITUTE(__TR_HORIZONTAL!K47,"HashiCorp Vault","XQZ0QX"),"Cloud Armor","XQZ1QX"),"AWS","XQZ2QX"),"en","es"),"XQZ0QX","HashiCorp Vault"),"XQZ1QX","Cloud Armor"),"XQZ2QX","AWS") -> Imperva WAF; Cloud Armor; AWS Shield; Apigee OAuth/limitación de tasa; Malla de servicio Istio; Exabeam SIEM; HashiCorp Vault y controles de endurecimiento.
G48: 1.4.3 | H48: =_xlfn.TRANSLATE(__TR_HORIZONTAL!H48,"en","es") -> Protección de Carga Útil y Cumplimiento de Cuotas | I48: =_xlfn.TRANSLATE(__TR_HORIZONTAL!I48,"en","es") -> Inspección de cargas útiles, límites de tamaño y esquema, y aplicación de cuotas orientada al abuso. | J48: =_xlfn.TRANSLATE(__TR_HORIZONTAL!J48,"en","es") -> Previene ataques por agotamiento de recursos contra componentes compartidos usados por todos los consumidores. | K48: =SUBSTITUTE(SUBSTITUTE(SUBSTITUTE(_xlfn.TRANSLATE(SUBSTITUTE(SUBSTITUTE(SUBSTITUTE(__TR_HORIZONTAL!K48,"HashiCorp Vault","XQZ0QX"),"Cloud Armor","XQZ1QX"),"AWS","XQZ2QX"),"en","es"),"XQZ0QX","HashiCorp Vault"),"XQZ1QX","Cloud Armor"),"XQZ2QX","AWS") -> Imperva WAF; Cloud Armor; AWS Shield; Apigee OAuth/limitación de tasa; Malla de servicio Istio; Exabeam SIEM; HashiCorp Vault y controles de endurecimiento.
G49: 1.4.4 | H49: =_xlfn.TRANSLATE(__TR_HORIZONTAL!H49,"en","es") -> Seguridad en contenedores y streaming | I49: =_xlfn.TRANSLATE(__TR_HORIZONTAL!I49,"en","es") -> Escaneo de imágenes, protección de cargas de trabajo en tiempo de ejecución, validación de políticas de malla de servicio y control de acceso en temas de eventos. | J49: =_xlfn.TRANSLATE(__TR_HORIZONTAL!J49,"en","es") -> Extiende el control a los tiempos de ejecución donde los servicios modernos realmente se ejecutan, en lugar de solo al perímetro. | K49: =SUBSTITUTE(SUBSTITUTE(SUBSTITUTE(_xlfn.TRANSLATE(SUBSTITUTE(SUBSTITUTE(SUBSTITUTE(__TR_HORIZONTAL!K49,"HashiCorp Vault","XQZ0QX"),"Cloud Armor","XQZ1QX"),"AWS","XQZ2QX"),"en","es"),"XQZ0QX","HashiCorp Vault"),"XQZ1QX","Cloud Armor"),"XQZ2QX","AWS") -> Imperva WAF; Cloud Armor; AWS Shield; Apigee OAuth/limitación de tasa; Malla de servicio Istio; Exabeam SIEM; HashiCorp Vault y controles de endurecimiento.
D50: 1.5 | E50: =_xlfn.TRANSLATE(__TR_HORIZONTAL!E50,"en","es") -> Gestión de vulnerabilidades y amenazas (VTM) | F50: =_xlfn.TRANSLATE(__TR_HORIZONTAL!F50,"en","es") -> Identificación, priorización y remediación continua de vulnerabilidades en bibliotecas, imágenes, plataformas e interfaces, incluyendo pruebas adversariales. | PROPÓSITO: Abordar directamente el coste y el tiempo dedicados a gestionar vulnerabilidades en un gran conjunto de microservicios, el objetivo declarado detrás de la curación de bibliotecas base y la eliminación de dependencias innecesarias. | G50: 1.5.1 | H50: =_xlfn.TRANSLATE(__TR_HORIZONTAL!H50,"en","es") -> Escaneo y Remediación de Vulnerabilidades | I50: =_xlfn.TRANSLATE(__TR_HORIZONTAL!I50,"en","es") -> Escaneo automatizado de código, dependencias, imágenes e infraestructura con flujo de trabajo de remediación seguido. | J50: =_xlfn.TRANSLATE(__TR_HORIZONTAL!J50,"en","es") -> Convierte un atraso de alertas manuales ilimitado en una pipeline gobernada y medible. | K50: =SUBSTITUTE(SUBSTITUTE(SUBSTITUTE(_xlfn.TRANSLATE(SUBSTITUTE(SUBSTITUTE(SUBSTITUTE(__TR_HORIZONTAL!K50,"SonarQube","XQZ0QX"),"OWASP ZAP","XQZ1QX"),"DevSecOps","XQZ2QX"),"en","es"),"XQZ0QX","SonarQube"),"XQZ1QX","OWASP ZAP"),"XQZ2QX","DevSecOps") -> puertas de seguridad DevSecOps; Prácticas SAST/DAST; SonarQube y OWASP ZAP referenciados para la seguridad de la canalización; endurecer la validación; escaneos de vulnerabilidades.
G51: 1.5.2 | H51: =_xlfn.TRANSLATE(__TR_HORIZONTAL!H51,"en","es") -> Pruebas de penetración y evaluación adversarial | I51: =_xlfn.TRANSLATE(__TR_HORIZONTAL!I51,"en","es") -> Pruebas programadas y dirigidas de interfaces expuestas y componentes de interoperabilidad por equipos especializados. | J51: =_xlfn.TRANSLATE(__TR_HORIZONTAL!J51,"en","es") -> Valida que los controles heredados de la plataforma realmente se mantienen bajo ataque, no solo en el papel. | K51: =SUBSTITUTE(SUBSTITUTE(SUBSTITUTE(_xlfn.TRANSLATE(SUBSTITUTE(SUBSTITUTE(SUBSTITUTE(__TR_HORIZONTAL!K51,"SonarQube","XQZ0QX"),"OWASP ZAP","XQZ1QX"),"DevSecOps","XQZ2QX"),"en","es"),"XQZ0QX","SonarQube"),"XQZ1QX","OWASP ZAP"),"XQZ2QX","DevSecOps") -> puertas de seguridad DevSecOps; Prácticas SAST/DAST; SonarQube y OWASP ZAP referenciados para la seguridad de la canalización; endurecer la validación; escaneos de vulnerabilidades.
G52: 1.5.3 | H52: =_xlfn.TRANSLATE(__TR_HORIZONTAL!H52,"en","es") -> Línea Base de Seguridad y Aplicación de Políticas | I52: =_xlfn.TRANSLATE(__TR_HORIZONTAL!I52,"en","es") -> Definición y aplicación automatizada de librerías aprobadas, tiempos de ejecución y líneas base de configuración. | J52: =_xlfn.TRANSLATE(__TR_HORIZONTAL!J52,"en","es") -> Los estándares centrales controlados por un solo equipo son los que mantienen el esfuerzo de remediación sublineal a medida que crecen los servicios. | K52: =SUBSTITUTE(SUBSTITUTE(SUBSTITUTE(_xlfn.TRANSLATE(SUBSTITUTE(SUBSTITUTE(SUBSTITUTE(__TR_HORIZONTAL!K52,"SonarQube","XQZ0QX"),"OWASP ZAP","XQZ1QX"),"DevSecOps","XQZ2QX"),"en","es"),"XQZ0QX","SonarQube"),"XQZ1QX","OWASP ZAP"),"XQZ2QX","DevSecOps") -> puertas de seguridad DevSecOps; Prácticas SAST/DAST; SonarQube y OWASP ZAP referenciados para la seguridad de la canalización; endurecer la validación; escaneos de vulnerabilidades.
D53: 1.6 | E53: =_xlfn.TRANSLATE(__TR_HORIZONTAL!E53,"en","es") -> Observabilidad y respuesta de seguridad | F53: =_xlfn.TRANSLATE(__TR_HORIZONTAL!F53,"en","es") -> Telemetría, correlación, alertas, paneles de control y respuesta automatizada específicos de seguridad se basan en la columna vertebral de observabilidad compartida. | PROPÓSITO: Cerrar la brecha más observada en los programas de interoperabilidad: la telemetría de seguridad existe en fragmentos y no existe capacidad de respuesta automatizada. | G53: 1.6.1 | H53: =_xlfn.TRANSLATE(__TR_HORIZONTAL!H53,"en","es") -> Alertas de seguridad, métricas y paneles de control | I53: =SUBSTITUTE(_xlfn.TRANSLATE(SUBSTITUTE(__TR_HORIZONTAL!I53,"API","XQZ0QX"),"en","es"),"XQZ0QX","API") -> Recopilación consolidada de eventos de seguridad, correlación y paneles que abarcan capas perimeter, API, contenedor y streaming. | J53: =_xlfn.TRANSLATE(__TR_HORIZONTAL!J53,"en","es") -> Proporciona a la función de seguridad la misma visibilidad de extremo a extremo que el trazado distribuido da a la ingeniería. | K53: =SUBSTITUTE(SUBSTITUTE(SUBSTITUTE(SUBSTITUTE(_xlfn.TRANSLATE(SUBSTITUTE(SUBSTITUTE(SUBSTITUTE(SUBSTITUTE(__TR_HORIZONTAL!K53,"DataDog","XQZ0QX"),"CloudWatch","XQZ1QX"),"CloudTrail","XQZ2QX"),"AWS","XQZ3QX"),"en","es"),"XQZ0QX","DataDog"),"XQZ1QX","CloudWatch"),"XQZ2QX","CloudTrail"),"XQZ3QX","AWS") -> Exabeam SIEM para detección de amenazas; DataDog para paneles de seguridad/operativos; CloudTrail/CloudWatch donde se utilizan los servicios AWS; escalada de incidentes a través de Operaciones/Seguridad.
G54: 1.6.2 | H54: =_xlfn.TRANSLATE(__TR_HORIZONTAL!H54,"en","es") -> Automatización de la Respuesta a Incidentes de Seguridad | I54: =_xlfn.TRANSLATE(__TR_HORIZONTAL!I54,"en","es") -> Manuales de contención y remediación orquestados y parcialmente automatizados activados por detecciones de seguridad. | J54: =_xlfn.TRANSLATE(__TR_HORIZONTAL!J54,"en","es") -> Comprime el tiempo de respuesta a un nivel coherente con los canales de distribución en tiempo real y siempre activos. | K54: =SUBSTITUTE(SUBSTITUTE(SUBSTITUTE(SUBSTITUTE(_xlfn.TRANSLATE(SUBSTITUTE(SUBSTITUTE(SUBSTITUTE(SUBSTITUTE(__TR_HORIZONTAL!K54,"DataDog","XQZ0QX"),"CloudWatch","XQZ1QX"),"CloudTrail","XQZ2QX"),"AWS","XQZ3QX"),"en","es"),"XQZ0QX","DataDog"),"XQZ1QX","CloudWatch"),"XQZ2QX","CloudTrail"),"XQZ3QX","AWS") -> Exabeam SIEM para detección de amenazas; DataDog para paneles de seguridad/operativos; CloudTrail/CloudWatch donde se utilizan los servicios AWS; escalada de incidentes a través de Operaciones/Seguridad.
A55: 2 | B55: =_xlfn.TRANSLATE(__TR_HORIZONTAL!B55,"en","es") -> Observabilidad | C55: =SUBSTITUTE(_xlfn.TRANSLATE(SUBSTITUTE(__TR_HORIZONTAL!C55,"API","XQZ0QX"),"en","es"),"XQZ0QX","API") -> Instrumentación y evidencia en todo el patrimonio distribuido: agregación de registros y registro operativo, registro de auditorías, rastreo distribuido y de extremo a extremo, monitorización de salud y API, alertas, métricas y analíticas, y paneles técnicos y empresariales. | PROPÓSITO: La consecuencia más difícil de la componibilidad es que ningún sistema único posee la verdad de extremo a extremo sobre una transacción; La observabilidad la restaura. A nivel ejecutivo, esta capacidad convierte la capa de interoperabilidad de un activo técnico en un instrumento de riesgo y rendimiento a nivel de servicio empresarial; la misma telemetría que impulsa la respuesta a incidentes impulsa la visión de riesgo de TI por servicio utilizada para guiar el programa de modernización. | D55: 2.1 | E55: =_xlfn.TRANSLATE(__TR_HORIZONTAL!E55,"en","es") -> Monitorización | F55: =_xlfn.TRANSLATE(__TR_HORIZONTAL!F55,"en","es") -> Recogida y evaluación continua del estado y disponibilidad de componentes, interfaces y dependencias de la plataforma, con alertas basadas en umbrales y anomalías. | PROPÓSITO: Detecta la degradación antes que los clientes, lo cual importa más en una urbanización compuesta donde una dependencia débil degrada muchos viajes. | G55: 2.1.1 | H55: =_xlfn.TRANSLATE(__TR_HORIZONTAL!H55,"en","es") -> Monitorización de la salud | I55: =_xlfn.TRANSLATE(__TR_HORIZONTAL!I55,"en","es") -> Comprobaciones de vivencia, preparación y salud de dependencias para servicios, tiempos de ejecución y componentes de infraestructura. | J55: =_xlfn.TRANSLATE(__TR_HORIZONTAL!J55,"en","es") -> Permite la recuperación automatizada y el desplazamiento de tráfico en lugar de diagnósticos manuales. | K55: =SUBSTITUTE(SUBSTITUTE(SUBSTITUTE(SUBSTITUTE(SUBSTITUTE(_xlfn.TRANSLATE(SUBSTITUTE(SUBSTITUTE(SUBSTITUTE(SUBSTITUTE(SUBSTITUTE(__TR_HORIZONTAL!K55,"SmartVista","XQZ0QX"),"DataDog","XQZ1QX"),"CloudWatch","XQZ2QX"),"CloudTrail","XQZ3QX"),"AWS","XQZ4QX"),"en","es"),"XQZ0QX","SmartVista"),"XQZ1QX","DataDog"),"XQZ2QX","CloudWatch"),"XQZ3QX","CloudTrail"),"XQZ4QX","AWS") -> Monitorización, paneles de control y alertas DataDog; CloudWatch/CloudTrail para componentes AWS; Análisis de apigee; comprobaciones de salud de la plataforma en Apolo, Transact y SmartVista.
G56: 2.1.2 | H56: =SUBSTITUTE(_xlfn.TRANSLATE(SUBSTITUTE(__TR_HORIZONTAL!H56,"API","XQZ0QX"),"en","es"),"XQZ0QX","API") -> Monitorización de la salud y disponibilidad API | I56: =_xlfn.TRANSLATE(__TR_HORIZONTAL!I56,"en","es") -> Monitorización de disponibilidad, latencia, saturación y tasa de errores por interfaz y por consumidor. | J56: =_xlfn.TRANSLATE(__TR_HORIZONTAL!J56,"en","es") -> Hace que los contratos publicados sean medibles en función de los niveles de servicio, lo que permite confiar en la reutilización interna. | K56: =SUBSTITUTE(SUBSTITUTE(SUBSTITUTE(SUBSTITUTE(SUBSTITUTE(_xlfn.TRANSLATE(SUBSTITUTE(SUBSTITUTE(SUBSTITUTE(SUBSTITUTE(SUBSTITUTE(__TR_HORIZONTAL!K56,"SmartVista","XQZ0QX"),"DataDog","XQZ1QX"),"CloudWatch","XQZ2QX"),"CloudTrail","XQZ3QX"),"AWS","XQZ4QX"),"en","es"),"XQZ0QX","SmartVista"),"XQZ1QX","DataDog"),"XQZ2QX","CloudWatch"),"XQZ3QX","CloudTrail"),"XQZ4QX","AWS") -> Monitorización, paneles de control y alertas DataDog; CloudWatch/CloudTrail para componentes AWS; Análisis de apigee; comprobaciones de salud de la plataforma en Apolo, Transact y SmartVista.
G57: 2.1.3 | H57: =_xlfn.TRANSLATE(__TR_HORIZONTAL!H57,"en","es") -> Alertas y notificaciones | I57: =_xlfn.TRANSLATE(__TR_HORIZONTAL!I57,"en","es") -> Generación de alertas basada en reglas y umbrales con enrutamiento al canal correspondiente (ITSM, mensajería, correo, guardia). | J57: =_xlfn.TRANSLATE(__TR_HORIZONTAL!J57,"en","es") -> Garantiza que la detección llegue a un propietario responsable; la telemetría no enrutada no tiene valor operativo. | K57: =SUBSTITUTE(SUBSTITUTE(SUBSTITUTE(SUBSTITUTE(SUBSTITUTE(_xlfn.TRANSLATE(SUBSTITUTE(SUBSTITUTE(SUBSTITUTE(SUBSTITUTE(SUBSTITUTE(__TR_HORIZONTAL!K57,"SmartVista","XQZ0QX"),"DataDog","XQZ1QX"),"CloudWatch","XQZ2QX"),"CloudTrail","XQZ3QX"),"AWS","XQZ4QX"),"en","es"),"XQZ0QX","SmartVista"),"XQZ1QX","DataDog"),"XQZ2QX","CloudWatch"),"XQZ3QX","CloudTrail"),"XQZ4QX","AWS") -> Monitorización, paneles de control y alertas DataDog; CloudWatch/CloudTrail para componentes AWS; Análisis de apigee; comprobaciones de salud de la plataforma en Apolo, Transact y SmartVista.
G58: 2.1.4 | H58: =_xlfn.TRANSLATE(__TR_HORIZONTAL!H58,"en","es") -> Monitorización de capacidad y tasa de eventos | I58: =_xlfn.TRANSLATE(__TR_HORIZONTAL!I58,"en","es") -> Medición del rendimiento, tasas de eventos y consumo de recursos para apoyar la planificación de capacidad. | J58: =_xlfn.TRANSLATE(__TR_HORIZONTAL!J58,"en","es") -> Aborda directamente las brechas de rendimiento y planes de capacidad que normalmente se encuentran en el estado de integración en estado actual. | K58: =SUBSTITUTE(SUBSTITUTE(SUBSTITUTE(SUBSTITUTE(SUBSTITUTE(_xlfn.TRANSLATE(SUBSTITUTE(SUBSTITUTE(SUBSTITUTE(SUBSTITUTE(SUBSTITUTE(__TR_HORIZONTAL!K58,"SmartVista","XQZ0QX"),"DataDog","XQZ1QX"),"CloudWatch","XQZ2QX"),"CloudTrail","XQZ3QX"),"AWS","XQZ4QX"),"en","es"),"XQZ0QX","SmartVista"),"XQZ1QX","DataDog"),"XQZ2QX","CloudWatch"),"XQZ3QX","CloudTrail"),"XQZ4QX","AWS") -> Monitorización, paneles de control y alertas DataDog; CloudWatch/CloudTrail para componentes AWS; Análisis de apigee; comprobaciones de salud de la plataforma en Apolo, Transact y SmartVista.
D59: 2.2 | E59: =_xlfn.TRANSLATE(__TR_HORIZONTAL!E59,"en","es") -> Tala | F59: =_xlfn.TRANSLATE(__TR_HORIZONTAL!F59,"en","es") -> Recogida estructurada, normalización, indexación, retención y rotación de registros técnicos, operativos y de auditoría de cada componente de la capa de interoperabilidad. | PROPÓSITO: Proporciona el fundamento forense y de auditoría para un patrimonio distribuido donde ningún registro de aplicaciones único cuente toda la historia. | G59: 2.2.1 | H59: =_xlfn.TRANSLATE(__TR_HORIZONTAL!H59,"en","es") -> Agregación de logarítmicas | I59: =_xlfn.TRANSLATE(__TR_HORIZONTAL!I59,"en","es") -> Recogida centralizada e indexación de registros de servicios, gateways, tiempos de ejecución y pipelines. | J59: =_xlfn.TRANSLATE(__TR_HORIZONTAL!J59,"en","es") -> Elimina la búsqueda de troncos por sistema, que es el mayor componente individual del tiempo medio de diagnóstico. | K59: =SUBSTITUTE(SUBSTITUTE(SUBSTITUTE(SUBSTITUTE(SUBSTITUTE(_xlfn.TRANSLATE(SUBSTITUTE(SUBSTITUTE(SUBSTITUTE(SUBSTITUTE(SUBSTITUTE(__TR_HORIZONTAL!K59,"SmartVista","XQZ0QX"),"DataDog","XQZ1QX"),"CloudWatch","XQZ2QX"),"CloudTrail","XQZ3QX"),"AWS","XQZ4QX"),"en","es"),"XQZ0QX","SmartVista"),"XQZ1QX","DataDog"),"XQZ2QX","CloudWatch"),"XQZ3QX","CloudTrail"),"XQZ4QX","AWS") -> Registros/monitores DataDog; Exabeam SIEM; AWS CloudTrail/CloudWatch; pruebas de auditoría de Apigee, Transact, SmartVista y de los flujos regulatorios/de reportes.
G60: 2.2.2 | H60: =_xlfn.TRANSLATE(__TR_HORIZONTAL!H60,"en","es") -> Servicios de Registro Operativo | I60: =_xlfn.TRANSLATE(__TR_HORIZONTAL!I60,"en","es") -> Bibliotecas estándar de registro, formatos y convenciones de severidad consumidos por los equipos de aplicaciones. | J60: =_xlfn.TRANSLATE(__TR_HORIZONTAL!J60,"en","es") -> Hace que los registros sean correlacionados con la máquina por diseño en lugar de analizados retrospectivamente. | K60: =SUBSTITUTE(SUBSTITUTE(SUBSTITUTE(SUBSTITUTE(SUBSTITUTE(_xlfn.TRANSLATE(SUBSTITUTE(SUBSTITUTE(SUBSTITUTE(SUBSTITUTE(SUBSTITUTE(__TR_HORIZONTAL!K60,"SmartVista","XQZ0QX"),"DataDog","XQZ1QX"),"CloudWatch","XQZ2QX"),"CloudTrail","XQZ3QX"),"AWS","XQZ4QX"),"en","es"),"XQZ0QX","SmartVista"),"XQZ1QX","DataDog"),"XQZ2QX","CloudWatch"),"XQZ3QX","CloudTrail"),"XQZ4QX","AWS") -> Registros/monitores DataDog; Exabeam SIEM; AWS CloudTrail/CloudWatch; pruebas de auditoría de Apigee, Transact, SmartVista y de los flujos regulatorios/de reportes.
G61: 2.2.3 | H61: =_xlfn.TRANSLATE(__TR_HORIZONTAL!H61,"en","es") -> Registro de auditoría | I61: =_xlfn.TRANSLATE(__TR_HORIZONTAL!I61,"en","es") -> Registro inmutable de eventos relevantes para la seguridad y para el negocio con retención definida. | J61: =_xlfn.TRANSLATE(__TR_HORIZONTAL!J61,"en","es") -> Cumple obligaciones de evidencia regulatoria que los núcleos heredados cumplían implícitamente a través de sus propias revistas. | K61: =SUBSTITUTE(SUBSTITUTE(SUBSTITUTE(SUBSTITUTE(SUBSTITUTE(_xlfn.TRANSLATE(SUBSTITUTE(SUBSTITUTE(SUBSTITUTE(SUBSTITUTE(SUBSTITUTE(__TR_HORIZONTAL!K61,"SmartVista","XQZ0QX"),"DataDog","XQZ1QX"),"CloudWatch","XQZ2QX"),"CloudTrail","XQZ3QX"),"AWS","XQZ4QX"),"en","es"),"XQZ0QX","SmartVista"),"XQZ1QX","DataDog"),"XQZ2QX","CloudWatch"),"XQZ3QX","CloudTrail"),"XQZ4QX","AWS") -> Registros/monitores DataDog; Exabeam SIEM; AWS CloudTrail/CloudWatch; pruebas de auditoría de Apigee, Transact, SmartVista y de los flujos regulatorios/de reportes.
G62: 2.2.4 | H62: =_xlfn.TRANSLATE(__TR_HORIZONTAL!H62,"en","es") -> Retención y rotación de troncos | I62: =_xlfn.TRANSLATE(__TR_HORIZONTAL!I62,"en","es") -> Niveles de retención basados en políticas, archivo y rotación entre almacenamiento caliente, caliente y frío. | J62: =_xlfn.TRANSLATE(__TR_HORIZONTAL!J62,"en","es") -> Controla la curva de coste de observabilidad, que de otro modo escala más rápido que el propio conjunto. | K62: =SUBSTITUTE(SUBSTITUTE(SUBSTITUTE(SUBSTITUTE(SUBSTITUTE(_xlfn.TRANSLATE(SUBSTITUTE(SUBSTITUTE(SUBSTITUTE(SUBSTITUTE(SUBSTITUTE(__TR_HORIZONTAL!K62,"SmartVista","XQZ0QX"),"DataDog","XQZ1QX"),"CloudWatch","XQZ2QX"),"CloudTrail","XQZ3QX"),"AWS","XQZ4QX"),"en","es"),"XQZ0QX","SmartVista"),"XQZ1QX","DataDog"),"XQZ2QX","CloudWatch"),"XQZ3QX","CloudTrail"),"XQZ4QX","AWS") -> Registros/monitores DataDog; Exabeam SIEM; AWS CloudTrail/CloudWatch; pruebas de auditoría de Apigee, Transact, SmartVista y de los flujos regulatorios/de reportes.
D63: 2.3 | E63: =_xlfn.TRANSLATE(__TR_HORIZONTAL!E63,"en","es") -> Trazado | F63: =_xlfn.TRANSLATE(__TR_HORIZONTAL!F63,"en","es") -> Propagación y reconstrucción del camino completo de ejecución de una solicitud a través de servicios, plataformas, protocolos y saltos asincrónicos, basándose en un identificador de correlación propagado de forma consistente. | PROPÓSITO: La capacidad de observabilidad más importante en una arquitectura interoperable: es lo que hace que una transacción distribuida sea explicable de principio a fin, tanto en la generación heredada como en la siguiente. | G63: 2.3.1 | H63: =_xlfn.TRANSLATE(__TR_HORIZONTAL!H63,"en","es") -> Trazado distribuido | I63: =_xlfn.TRANSLATE(__TR_HORIZONTAL!I63,"en","es") -> Recogida y ensamblado entre invocaciones de servicio síncronas, con atribución de latencia por salto. | J63: =_xlfn.TRANSLATE(__TR_HORIZONTAL!J63,"en","es") -> Localiza la verdadera limitación en un viaje compuesto en lugar de asignar la culpa por inferencia. | K63: =SUBSTITUTE(_xlfn.TRANSLATE(SUBSTITUTE(__TR_HORIZONTAL!K63,"DataDog","XQZ0QX"),"en","es"),"XQZ0QX","DataDog") -> El APM/trazado DataDog está planificado como observabilidad avanzada; Istio soporta telemetría a nivel de servicio. El servicio de identidad de correlación no se menciona explícitamente.
G64: 2.3.2 | H64: =_xlfn.TRANSLATE(__TR_HORIZONTAL!H64,"en","es") -> Trazado de extremo a extremo (identidad de correlación) | I64: =_xlfn.TRANSLATE(__TR_HORIZONTAL!I64,"en","es") -> Propagación consistente de identificadores de correlación a través de canales, orquestaciones, eventos y adaptadores heredados. | J64: =_xlfn.TRANSLATE(__TR_HORIZONTAL!J64,"en","es") -> Ofrece trazabilidad a lo largo de toda la arquitectura técnica, incluyendo segmentos asincrónicos y mainframe. | K64: =SUBSTITUTE(_xlfn.TRANSLATE(SUBSTITUTE(__TR_HORIZONTAL!K64,"DataDog","XQZ0QX"),"en","es"),"XQZ0QX","DataDog") -> El APM/trazado DataDog está planificado como observabilidad avanzada; Istio soporta telemetría a nivel de servicio. El servicio de identidad de correlación no se menciona explícitamente.
D65: 2.4 | E65: =_xlfn.TRANSLATE(__TR_HORIZONTAL!E65,"en","es") -> Métricas, Análisis e Informes | F65: =_xlfn.TRANSLATE(__TR_HORIZONTAL!F65,"en","es") -> Derivación, almacenamiento y análisis de métricas técnicas y empresariales a partir de la telemetría, incluyendo correlación automatizada y detección asistida por aprendizaje automático, así como informes periódicos. | OBJETIVO: Convierte la telemetría en bruto en la información de gestión utilizada para demostrar el caso de negocio de interoperabilidad y orientar la inversión de la plataforma. | G65: 2.4.1 | H65: =_xlfn.TRANSLATE(__TR_HORIZONTAL!H65,"en","es") -> Métricas y Analítica | I65: =_xlfn.TRANSLATE(__TR_HORIZONTAL!I65,"en","es") -> Recogida, agregación y análisis de métricas de series temporales, incluyendo correlación negocio-evento y detección de anomalías. | J65: =_xlfn.TRANSLATE(__TR_HORIZONTAL!J65,"en","es") -> Proporciona la base de medición para las reclamaciones de reutilización, tiempo de lanzamiento al mercado y costes presentadas en el caso de negocio del programa. | K65: =SUBSTITUTE(SUBSTITUTE(_xlfn.TRANSLATE(SUBSTITUTE(SUBSTITUTE(__TR_HORIZONTAL!K65,"Google Analytics","XQZ0QX"),"DataDog","XQZ1QX"),"en","es"),"XQZ0QX","Google Analytics"),"XQZ1QX","DataDog") -> KPIs DataDog; Análisis de apigee; Google Analytics para comportamiento digital; Data Warehouse/DataStage para fuentes de informes; Paneles ejecutivos de PMO.
G66: 2.4.2 | H66: =_xlfn.TRANSLATE(__TR_HORIZONTAL!H66,"en","es") -> Reportajes | I66: =_xlfn.TRANSLATE(__TR_HORIZONTAL!I66,"en","es") -> Informes operativos programados y bajo demanda, de nivel de servicio y de cumplimiento. | J66: =_xlfn.TRANSLATE(__TR_HORIZONTAL!J66,"en","es") -> Proporciona el paquete de evidencia recurrente para foros de riesgo, auditoría y gobernanza de servicios. | K66: =SUBSTITUTE(SUBSTITUTE(_xlfn.TRANSLATE(SUBSTITUTE(SUBSTITUTE(__TR_HORIZONTAL!K66,"Google Analytics","XQZ0QX"),"DataDog","XQZ1QX"),"en","es"),"XQZ0QX","Google Analytics"),"XQZ1QX","DataDog") -> KPIs DataDog; Análisis de apigee; Google Analytics para comportamiento digital; Data Warehouse/DataStage para fuentes de informes; Paneles ejecutivos de PMO.
D67: 2.5 | E67: =_xlfn.TRANSLATE(__TR_HORIZONTAL!E67,"en","es") -> Paneles | F67: =_xlfn.TRANSLATE(__TR_HORIZONTAL!F67,"en","es") -> Visualización orientada a roles de la plataforma y la telemetría empresarial para audiencias de ingeniería, operaciones, seguridad, empresarial y ejecutivos. | PROPÓSITO: Convierte la observabilidad de una herramienta de ingeniería en un instrumento de gestión compartida, incluyendo la visión de riesgo de TI a nivel de negocio y servicio. | G67: 2.5.1 | H67: =_xlfn.TRANSLATE(__TR_HORIZONTAL!H67,"en","es") -> Paneles técnicos | I67: =_xlfn.TRANSLATE(__TR_HORIZONTAL!I67,"en","es") -> Vistas de componentes, servicios e infraestructura para los equipos de ingeniería y operaciones. | J67: =_xlfn.TRANSLATE(__TR_HORIZONTAL!J67,"en","es") -> Reduce el triaje y apoya la propiedad de los servicios a nivel de equipo. | K67: =SUBSTITUTE(_xlfn.TRANSLATE(SUBSTITUTE(__TR_HORIZONTAL!K67,"DataDog","XQZ0QX"),"en","es"),"XQZ0QX","DataDog") -> paneles técnicos DataDog; paneles de PMO / ejecutivos; paneles regulatorios y empresariales a través de Data Warehouse, Bajaware/Risklogic y reportes de proyectos.
G68: 2.5.2 | H68: =_xlfn.TRANSLATE(__TR_HORIZONTAL!H68,"en","es") -> Paneles de control empresariales | I68: =_xlfn.TRANSLATE(__TR_HORIZONTAL!I68,"en","es") -> Vistas a nivel de negocio y de trayectos sobre volumen, tasa de éxito y flujo de valor. | J68: =_xlfn.TRANSLATE(__TR_HORIZONTAL!J68,"en","es") -> Permite a los directivos ver la modernización, el progreso y el riesgo en términos empresariales en lugar de en términos componentes. | K68: =SUBSTITUTE(_xlfn.TRANSLATE(SUBSTITUTE(__TR_HORIZONTAL!K68,"DataDog","XQZ0QX"),"en","es"),"XQZ0QX","DataDog") -> paneles técnicos DataDog; paneles de PMO / ejecutivos; paneles regulatorios y empresariales a través de Data Warehouse, Bajaware/Risklogic y reportes de proyectos.
A69: 13 | B69: =_xlfn.TRANSLATE(__TR_HORIZONTAL!B69,"en","es") -> Infraestructura (Pila Tecnológica) | C69: =_xlfn.TRANSLATE(__TR_HORIZONTAL!C69,"en","es") -> La base en tiempo de ejecución de la capa de interoperabilidad: el marco de microservicios y los servicios del núcleo, bibliotecas base y tiempos de ejecución del lenguaje, plataforma contenedor y serverless, descubrimiento y malla de servicios, automatización de configuración, ingeniería de despliegue y pruebas, y resiliencia de infraestructura. | PROPÓSITO: Determina el coste marginal de añadir un componente a la arquitectura. Una pila curada y aplicada por estándares —permitió tecnologías gobernadas centralmente, eliminar bibliotecas innecesarias— ofrece agilidad de despliegue y elástica escalando los atributos del caso de negocio hasta la componibilidad, y mantiene cientos de servicios gobernables por un pequeño equipo de plataforma. | D69: 13.1 | E69: =_xlfn.TRANSLATE(__TR_HORIZONTAL!E69,"en","es") -> Marco de Microservicios | F69: =_xlfn.TRANSLATE(__TR_HORIZONTAL!F69,"en","es") -> El marco de desarrollo y ejecución opinado que aloja servicios autosuficientes independientemente del dominio de negocio, incluyendo bibliotecas base compartidas, entornos de ejecución aprobados por lenguajes, servicios del kernel, descubrimiento de servicios e integración de mallas de servicios. | PROPÓSITO: El marco es donde se heredan las preocupaciones transversales en lugar de reconstruirse; Su calidad establece el techo de productividad para cada equipo de dominio. | G69: 13.1.1 | H69: =_xlfn.TRANSLATE(__TR_HORIZONTAL!H69,"en","es") -> Bibliotecas base | I69: =_xlfn.TRANSLATE(__TR_HORIZONTAL!I69,"en","es") -> Bibliotecas comunes seleccionadas y versionadas que proporcionan registro, seguridad, resiliencia, configuración e integración de telemetría. | J69: =_xlfn.TRANSLATE(__TR_HORIZONTAL!J69,"en","es") -> Estandariza el comportamiento no funcional y reduce la superficie de vulnerabilidad eliminando dependencias innecesarias. | K69: =SUBSTITUTE(SUBSTITUTE(SUBSTITUTE(SUBSTITUTE(SUBSTITUTE(SUBSTITUTE(_xlfn.TRANSLATE(SUBSTITUTE(SUBSTITUTE(SUBSTITUTE(SUBSTITUTE(SUBSTITUTE(SUBSTITUTE(__TR_HORIZONTAL!K69,"Modyo Connect","XQZ0QX"),"Kubernetes","XQZ1QX"),"Spring Boot","XQZ2QX"),"API","XQZ3QX"),"EKS","XQZ4QX"),"ECS","XQZ5QX"),"en","es"),"XQZ0QX","Modyo Connect"),"XQZ1QX","Kubernetes"),"XQZ2QX","Spring Boot"),"XQZ3QX","API"),"XQZ4QX","EKS"),"XQZ5QX","ECS") -> microservicios Spring Boot; microservicios Modyo Connect; Temenos DES API/components; EKS/ECS/Fargate; Kubernetes; Malla de servicio Istio.
G70: 13.1.2 | H70: =_xlfn.TRANSLATE(__TR_HORIZONTAL!H70,"en","es") -> Tiempos de ejecución del lenguaje | I70: =_xlfn.TRANSLATE(__TR_HORIZONTAL!I70,"en","es") -> Conjunto regulado de tiempos de ejecución aprobados y versiones con rutas de actualización definidas. | J70: =_xlfn.TRANSLATE(__TR_HORIZONTAL!J70,"en","es") -> Previene la expansión tecnológica que haría imposible la remediación a nivel de plataforma y la planificación de competencias. | K70: =SUBSTITUTE(SUBSTITUTE(SUBSTITUTE(SUBSTITUTE(SUBSTITUTE(SUBSTITUTE(_xlfn.TRANSLATE(SUBSTITUTE(SUBSTITUTE(SUBSTITUTE(SUBSTITUTE(SUBSTITUTE(SUBSTITUTE(__TR_HORIZONTAL!K70,"Modyo Connect","XQZ0QX"),"Kubernetes","XQZ1QX"),"Spring Boot","XQZ2QX"),"API","XQZ3QX"),"EKS","XQZ4QX"),"ECS","XQZ5QX"),"en","es"),"XQZ0QX","Modyo Connect"),"XQZ1QX","Kubernetes"),"XQZ2QX","Spring Boot"),"XQZ3QX","API"),"XQZ4QX","EKS"),"XQZ5QX","ECS") -> microservicios Spring Boot; microservicios Modyo Connect; Temenos DES API/components; EKS/ECS/Fargate; Kubernetes; Malla de servicio Istio.
G71: 13.1.3 | H71: =_xlfn.TRANSLATE(__TR_HORIZONTAL!H71,"en","es") -> Servicios del núcleo | I71: =_xlfn.TRANSLATE(__TR_HORIZONTAL!I71,"en","es") -> Servicios fundacionales de plataforma consumidos por todos los dominios, incluido el inventario formal de servicios que los registra. | J71: =_xlfn.TRANSLATE(__TR_HORIZONTAL!J71,"en","es") -> Un inventario autorizado es la condición previa para regular la reutilización y para calcular el coste del patrimonio. | K71: =SUBSTITUTE(SUBSTITUTE(SUBSTITUTE(SUBSTITUTE(SUBSTITUTE(SUBSTITUTE(_xlfn.TRANSLATE(SUBSTITUTE(SUBSTITUTE(SUBSTITUTE(SUBSTITUTE(SUBSTITUTE(SUBSTITUTE(__TR_HORIZONTAL!K71,"Modyo Connect","XQZ0QX"),"Kubernetes","XQZ1QX"),"Spring Boot","XQZ2QX"),"API","XQZ3QX"),"EKS","XQZ4QX"),"ECS","XQZ5QX"),"en","es"),"XQZ0QX","Modyo Connect"),"XQZ1QX","Kubernetes"),"XQZ2QX","Spring Boot"),"XQZ3QX","API"),"XQZ4QX","EKS"),"XQZ5QX","ECS") -> microservicios Spring Boot; microservicios Modyo Connect; Temenos DES API/components; EKS/ECS/Fargate; Kubernetes; Malla de servicio Istio.
G72: 13.1.4 | H72: =_xlfn.TRANSLATE(__TR_HORIZONTAL!H72,"en","es") -> Descubrimiento del servicio | I72: =_xlfn.TRANSLATE(__TR_HORIZONTAL!I72,"en","es") -> Registro dinámico y resolución de instancias de servicio en tiempo de ejecución. | J72: =_xlfn.TRANSLATE(__TR_HORIZONTAL!J72,"en","es") -> Permite un escalado elástico y reubicación sin configuración estática del extremo. | K72: =SUBSTITUTE(SUBSTITUTE(_xlfn.TRANSLATE(SUBSTITUTE(SUBSTITUTE(__TR_HORIZONTAL!K72,"Kubernetes","XQZ0QX"),"EKS","XQZ1QX"),"en","es"),"XQZ0QX","Kubernetes"),"XQZ1QX","EKS") -> Istio Service Mesh en Kubernetes/EKS; Descubrimiento de servicios EKS y balanceo de carga para microservicios.
G73: 13.1.5 | H73: =_xlfn.TRANSLATE(__TR_HORIZONTAL!H73,"en","es") -> Malla de servicio | I73: =_xlfn.TRANSLATE(__TR_HORIZONTAL!I73,"en","es") -> Control basado en sidecar del tráfico de servicio a servicio, incluyendo autenticación mutua y validación de token en la capa de plataforma. | J73: =_xlfn.TRANSLATE(__TR_HORIZONTAL!J73,"en","es") -> Desplaza la seguridad interservicios y el control de tráfico fuera del código de la aplicación, simplificando cada servicio. | K73: =SUBSTITUTE(SUBSTITUTE(_xlfn.TRANSLATE(SUBSTITUTE(SUBSTITUTE(__TR_HORIZONTAL!K73,"Kubernetes","XQZ0QX"),"EKS","XQZ1QX"),"en","es"),"XQZ0QX","Kubernetes"),"XQZ1QX","EKS") -> Istio Service Mesh en Kubernetes/EKS; Descubrimiento de servicios EKS y balanceo de carga para microservicios.
D74: 13.2 | E74: =_xlfn.TRANSLATE(__TR_HORIZONTAL!E74,"en","es") -> Contenedor y plataforma de ejecución | F74: =_xlfn.TRANSLATE(__TR_HORIZONTAL!F74,"en","es") -> Orquestación de contenedores, ejecución serverless y gestión de imágenes proporcionan el sustrato elástico de cómputo para componentes de interoperabilidad. | OBJETIVO: Proporciona agilidad en el despliegue y escalado impulsado por la demanda, y es el vehículo práctico para la portabilidad entre proveedores de nube y entornos híbridos. | G74: 13.2.1 | H74: =_xlfn.TRANSLATE(__TR_HORIZONTAL!H74,"en","es") -> Orquestación en contenedores | I74: =_xlfn.TRANSLATE(__TR_HORIZONTAL!I74,"en","es") -> Programación, escalado, auto-reparación y colocación de carga de trabajo de servicios contenedores. | J74: =_xlfn.TRANSLATE(__TR_HORIZONTAL!J74,"en","es") -> Ofrece la elasticidad que las arquitecturas desacopladas necesitan para atender económicamente la demanda digital de forma económica. | K74: =SUBSTITUTE(SUBSTITUTE(SUBSTITUTE(SUBSTITUTE(_xlfn.TRANSLATE(SUBSTITUTE(SUBSTITUTE(SUBSTITUTE(SUBSTITUTE(__TR_HORIZONTAL!K74,"Modyo Connect","XQZ0QX"),"Kubernetes","XQZ1QX"),"EKS","XQZ2QX"),"ECS","XQZ3QX"),"en","es"),"XQZ0QX","Modyo Connect"),"XQZ1QX","Kubernetes"),"XQZ2QX","EKS"),"XQZ3QX","ECS") -> Amazon EKS/Kubernetes; ECS/Fargate para Modyo Connect; OpenShift referenciado en el panel técnico; Docker/registro de contenedores.
G75: 13.2.2 | H75: =_xlfn.TRANSLATE(__TR_HORIZONTAL!H75,"en","es") -> Tiempo de ejecución sin servidor | I75: =_xlfn.TRANSLATE(__TR_HORIZONTAL!I75,"en","es") -> Ejecución activada por eventos y basada en consumo para funciones ligeras y de ráfagas. | J75: =_xlfn.TRANSLATE(__TR_HORIZONTAL!J75,"en","es") -> Extiende los modelos de costes basados en el consumo a cargas de trabajo de integración y transformación de datos. | K75: =SUBSTITUTE(SUBSTITUTE(SUBSTITUTE(_xlfn.TRANSLATE(SUBSTITUTE(SUBSTITUTE(SUBSTITUTE(__TR_HORIZONTAL!K75,"Amazon API Gateway","XQZ0QX"),"API","XQZ1QX"),"AWS","XQZ2QX"),"en","es"),"XQZ0QX","Amazon API Gateway"),"XQZ1QX","API"),"XQZ2QX","AWS") -> No se evidencia explícitamente ningún tiempo de ejecución serverless dedicado; los servicios gestionados adyacentes AWS incluyen Amazon API Gateway, CloudFront, Pinpoint, MQ y Kinesis.
G76: 13.2.3 | H76: =_xlfn.TRANSLATE(__TR_HORIZONTAL!H76,"en","es") -> Gestión de imágenes y artefactos | I76: =_xlfn.TRANSLATE(__TR_HORIZONTAL!I76,"en","es") -> Registro, streaming, firma y promoción de imágenes en tiempo real y artefactos de construcción. | J76: =_xlfn.TRANSLATE(__TR_HORIZONTAL!J76,"en","es") -> Garantiza la procedencia y la velocidad de despliegue, ambos requisitos previos para una alta frecuencia de lanzamientos. | K76: =SUBSTITUTE(SUBSTITUTE(SUBSTITUTE(_xlfn.TRANSLATE(SUBSTITUTE(SUBSTITUTE(SUBSTITUTE(__TR_HORIZONTAL!K76,"GitHub","XQZ0QX"),"Helm Charts","XQZ1QX"),"DevSecOps","XQZ2QX"),"en","es"),"XQZ0QX","GitHub"),"XQZ1QX","Helm Charts"),"XQZ2QX","DevSecOps") -> Imágenes doradas de Packer; repositorios GitHub; área de decisión del registro de contenedores/ECR; Helm Charts; Pipelines de artefactos DevSecOps.
D77: 13.3 | E77: =_xlfn.TRANSLATE(__TR_HORIZONTAL!E77,"en","es") -> Automatización de configuración de plataformas | F77: =_xlfn.TRANSLATE(__TR_HORIZONTAL!F77,"en","es") -> Provisión y configuración declarativa y automatizada de componentes y entornos de plataforma, incluyendo servicios centralizados de configuración de aplicaciones. | PROPÓSITO: Elimina la inconsistencia ambiental que de otro modo hace que las pruebas distribuidas sean poco fiables y las versiones impredecibles. | G77: 13.3.1 | H77: =_xlfn.TRANSLATE(__TR_HORIZONTAL!H77,"en","es") -> Infraestructura y Provisión de Plataformas | I77: =_xlfn.TRANSLATE(__TR_HORIZONTAL!I77,"en","es") -> Provisión automatizada y controlada por versiones de los componentes de infraestructura y plataforma de los que depende la capa. | J77: =_xlfn.TRANSLATE(__TR_HORIZONTAL!J77,"en","es") -> Hace que la capa de interoperabilidad sea reproducible entre entornos, regiones y entidades. | K77: =SUBSTITUTE(SUBSTITUTE(_xlfn.TRANSLATE(SUBSTITUTE(SUBSTITUTE(__TR_HORIZONTAL!K77,"Terraform","XQZ0QX"),"GitHub","XQZ1QX"),"en","es"),"XQZ0QX","Terraform"),"XQZ1QX","GitHub") -> Terraform + Packer + GitHub; módulos IaC; Homologación de Ambientes; posibles patrones Ansible/CloudFormation; Vault/Secrets para seguridad de configuración.
G78: 13.3.2 | H78: =_xlfn.TRANSLATE(__TR_HORIZONTAL!H78,"en","es") -> Gestión de configuración | I78: =_xlfn.TRANSLATE(__TR_HORIZONTAL!I78,"en","es") -> La configuración externalizada y consciente del entorno sirvió a los servicios en tiempo de ejecución. | J78: =_xlfn.TRANSLATE(__TR_HORIZONTAL!J78,"en","es") -> Permite el cambio de comportamiento sin reubicación, lo cual es esencial para el control de la coexistencia. | K78: =SUBSTITUTE(SUBSTITUTE(_xlfn.TRANSLATE(SUBSTITUTE(SUBSTITUTE(__TR_HORIZONTAL!K78,"Terraform","XQZ0QX"),"GitHub","XQZ1QX"),"en","es"),"XQZ0QX","Terraform"),"XQZ1QX","GitHub") -> Terraform + Packer + GitHub; módulos IaC; Homologación de Ambientes; posibles patrones Ansible/CloudFormation; Vault/Secrets para seguridad de configuración.
G79: 13.3.3 | H79: =_xlfn.TRANSLATE(__TR_HORIZONTAL!H79,"en","es") -> Gestión del medio ambiente | I79: =_xlfn.TRANSLATE(__TR_HORIZONTAL!I79,"en","es") -> Definición, provisión y ciclo de vida de toda la cadena de entorno con sus correspondientes backends. | J79: =_xlfn.TRANSLATE(__TR_HORIZONTAL!J79,"en","es") -> Aborda el bloqueador común donde no existe una cadena de entorno completa alineada con backend para las pruebas de integración. | K79: =SUBSTITUTE(SUBSTITUTE(_xlfn.TRANSLATE(SUBSTITUTE(SUBSTITUTE(__TR_HORIZONTAL!K79,"Terraform","XQZ0QX"),"GitHub","XQZ1QX"),"en","es"),"XQZ0QX","Terraform"),"XQZ1QX","GitHub") -> Terraform + Packer + GitHub; módulos IaC; Homologación de Ambientes; posibles patrones Ansible/CloudFormation; Vault/Secrets para seguridad de configuración.
D80: 13.4 | E80: =_xlfn.TRANSLATE(__TR_HORIZONTAL!E80,"en","es") -> Despliegue e ingeniería de lanzamiento | F80: =_xlfn.TRANSLATE(__TR_HORIZONTAL!F80,"en","es") -> Mecánicas automatizadas de compilación, prueba y lanzamiento para componentes de interoperabilidad, incluyendo técnicas de despliegue controlado y pruebas de regresión automatizadas. | PROPÓSITO: El control del despliegue es lo que hace posible la modernización incremental y reversible en la práctica, y no solo en la hoja de ruta. | G80: 13.4.1 | H80: =_xlfn.TRANSLATE(__TR_HORIZONTAL!H80,"en","es") -> Estrategias de despliegue | I80: =_xlfn.TRANSLATE(__TR_HORIZONTAL!I80,"en","es") -> Mecanismos de despliegue controlados con exposición progresiva y capacidad de retroceso rápido. | J80: =_xlfn.TRANSLATE(__TR_HORIZONTAL!J80,"en","es") -> Permite desplazar y revertir gradualmente el tráfico de migración de núcleos sin un evento de liberación. | K80: =SUBSTITUTE(SUBSTITUTE(SUBSTITUTE(SUBSTITUTE(_xlfn.TRANSLATE(SUBSTITUTE(SUBSTITUTE(SUBSTITUTE(SUBSTITUTE(__TR_HORIZONTAL!K80,"GitLab CI","XQZ0QX"),"Jenkins","XQZ1QX"),"Helm Charts","XQZ2QX"),"DevSecOps","XQZ3QX"),"en","es"),"XQZ0QX","GitLab CI"),"XQZ1QX","Jenkins"),"XQZ2QX","Helm Charts"),"XQZ3QX","DevSecOps") -> tuberías CI/CD DevSecOps; GitLab CI o Jenkins bajo decisión; Helm Charts; pruebas automatizadas; Prácticas de despliegue azul-verde/canario.
G81: 13.4.2 | H81: =_xlfn.TRANSLATE(__TR_HORIZONTAL!H81,"en","es") -> Pruebas automatizadas | I81: =_xlfn.TRANSLATE(__TR_HORIZONTAL!I81,"en","es") -> Pruebas automatizadas de unidades, contratos, integración y regresión a través de los límites de servicio e interfaz. | J81: =_xlfn.TRANSLATE(__TR_HORIZONTAL!J81,"en","es") -> Las pruebas por contrato son la única forma económica de mantener la compatibilidad de cientos de servicios lanzados de forma independiente. | K81: =SUBSTITUTE(SUBSTITUTE(SUBSTITUTE(SUBSTITUTE(_xlfn.TRANSLATE(SUBSTITUTE(SUBSTITUTE(SUBSTITUTE(SUBSTITUTE(__TR_HORIZONTAL!K81,"GitLab CI","XQZ0QX"),"Jenkins","XQZ1QX"),"Helm Charts","XQZ2QX"),"DevSecOps","XQZ3QX"),"en","es"),"XQZ0QX","GitLab CI"),"XQZ1QX","Jenkins"),"XQZ2QX","Helm Charts"),"XQZ3QX","DevSecOps") -> tuberías CI/CD DevSecOps; GitLab CI o Jenkins bajo decisión; Helm Charts; pruebas automatizadas; Prácticas de despliegue azul-verde/canario.
D82: 13.5 | E82: =_xlfn.TRANSLATE(__TR_HORIZONTAL!E82,"en","es") -> Resiliencia de infraestructuras | F82: =_xlfn.TRANSLATE(__TR_HORIZONTAL!F82,"en","es") -> Ingeniería y validación de la capacidad de la capa para resistir y recuperarse de fallos en componentes, incluyendo inyección deliberada de fallos, diseño de alta disponibilidad y servicios de recuperación. | PROPÓSITO: En una arquitectura compuesta, la disponibilidad agregada es producto de muchas dependencias; Por tanto, la resiliencia debe ser diseñada y puesta a prueba, no asumida. | G82: 13.5.1 | H82: =_xlfn.TRANSLATE(__TR_HORIZONTAL!H82,"en","es") -> Alta Disponibilidad y Conmutación por Error | I82: =_xlfn.TRANSLATE(__TR_HORIZONTAL!I82,"en","es") -> Redundancia, despliegue multizona y conmutación automática por error para componentes de interoperabilidad. | J82: =_xlfn.TRANSLATE(__TR_HORIZONTAL!J82,"en","es") -> Evita que la capa de abstracción se convierta en un único punto de fallo para cada canal y producto. | K82: =SUBSTITUTE(SUBSTITUTE(SUBSTITUTE(_xlfn.TRANSLATE(SUBSTITUTE(SUBSTITUTE(SUBSTITUTE(__TR_HORIZONTAL!K82,"Oracle Data Guard","XQZ0QX"),"SmartVista","XQZ1QX"),"AWS","XQZ2QX"),"en","es"),"XQZ0QX","Oracle Data Guard"),"XQZ1QX","SmartVista"),"XQZ2QX","AWS") -> Arquitectura multi-AZ/DR AWS; Producción y DR Entornos de producción; Oracle Data Guard/R-SYNC para SmartVista; Copia de seguridad/restauración y recuperación regional de datos.
G83: 13.5.2 | H83: =_xlfn.TRANSLATE(__TR_HORIZONTAL!H83,"en","es") -> Pruebas de resiliencia e inyección de fallos | I83: =_xlfn.TRANSLATE(__TR_HORIZONTAL!I83,"en","es") -> Introducción deliberada y controlada de condiciones de fallo en entornos no productivos para validar el comportamiento de recuperación. | J83: =_xlfn.TRANSLATE(__TR_HORIZONTAL!J83,"en","es") -> Aflora modos de fallo no reproducibles antes de que aparezcan en incidentes de producción. | K83: =SUBSTITUTE(SUBSTITUTE(SUBSTITUTE(_xlfn.TRANSLATE(SUBSTITUTE(SUBSTITUTE(SUBSTITUTE(__TR_HORIZONTAL!K83,"Oracle Data Guard","XQZ0QX"),"SmartVista","XQZ1QX"),"AWS","XQZ2QX"),"en","es"),"XQZ0QX","Oracle Data Guard"),"XQZ1QX","SmartVista"),"XQZ2QX","AWS") -> Arquitectura multi-AZ/DR AWS; Producción y DR Entornos de producción; Oracle Data Guard/R-SYNC para SmartVista; Copia de seguridad/restauración y recuperación regional de datos.
G84: 13.5.3 | H84: =_xlfn.TRANSLATE(__TR_HORIZONTAL!H84,"en","es") -> Servicios de Recuperación | I84: =_xlfn.TRANSLATE(__TR_HORIZONTAL!I84,"en","es") -> Procedimientos automatizados de detección, aislamiento y restauración de componentes degradados. | J84: =_xlfn.TRANSLATE(__TR_HORIZONTAL!J84,"en","es") -> Reduce el coste operativo de gestionar una urbanización distribuida a gran escala. | K84: =SUBSTITUTE(SUBSTITUTE(SUBSTITUTE(_xlfn.TRANSLATE(SUBSTITUTE(SUBSTITUTE(SUBSTITUTE(__TR_HORIZONTAL!K84,"Oracle Data Guard","XQZ0QX"),"SmartVista","XQZ1QX"),"AWS","XQZ2QX"),"en","es"),"XQZ0QX","Oracle Data Guard"),"XQZ1QX","SmartVista"),"XQZ2QX","AWS") -> Arquitectura multi-AZ/DR AWS; Producción y DR Entornos de producción; Oracle Data Guard/R-SYNC para SmartVista; Copia de seguridad/restauración y recuperación regional de datos.
A85: 8 | B85: =_xlfn.TRANSLATE(__TR_HORIZONTAL!B85,"en","es") -> Orquestación de Servicio | C85: =_xlfn.TRANSLATE(__TR_HORIZONTAL!C85,"en","es") -> Composición de servicios de grano fino en servicios empresariales complejos a través de plataformas heterogéneas —de forma sincrónica o asíncrona, secuencial o en paralelo— a través de un orquestador de servicios, un marco de integración y mediación, gestión de contexto y adaptadores heredados. | PROPÓSITO: Aquí es donde la convivencia de mejor generación deja de ser un diagrama y se convierte en ejecutable: un servicio empresarial puede abarcar un núcleo de próxima generación, un procesador SaaS de producto y un subdominio de mainframe mientras el consumidor ve una sola llamada. Mover la orquestación de programas centrales codificados directamente a un marco declarativo suele ser la mayor ganancia de productividad individual en la capa y la condición previa para desmantelar middleware heredado. | D85: 8.1 | E85: =_xlfn.TRANSLATE(__TR_HORIZONTAL!E85,"en","es") -> Orquestador de Servicio | F85: =_xlfn.TRANSLATE(__TR_HORIZONTAL!F85,"en","es") -> El motor que descompone un servicio complejo en un conjunto ordenado o paralelo de invocaciones de servicio de grano minucioso y gestiona su ejecución, resultados y excepciones. | PROPÓSITO: Concentra la lógica de negocio entre sistemas en un solo lugar gobernado y visible en lugar de dispersarla entre canales y núcleos. | G85: 8.1.1 | H85: =_xlfn.TRANSLATE(__TR_HORIZONTAL!H85,"en","es") -> Composición y secuenciación de servicios | I85: =_xlfn.TRANSLATE(__TR_HORIZONTAL!I85,"en","es") -> Definición y ejecución de servicios compuestos a partir de pasos detallados, con configuración declarativa o visual. | J85: =_xlfn.TRANSLATE(__TR_HORIZONTAL!J85,"en","es") -> Aumenta la productividad en la entrega y hace que la lógica entre sistemas sea revisable por arquitectura y auditoría. | K85: =SUBSTITUTE(SUBSTITUTE(SUBSTITUTE(SUBSTITUTE(SUBSTITUTE(_xlfn.TRANSLATE(SUBSTITUTE(SUBSTITUTE(SUBSTITUTE(SUBSTITUTE(SUBSTITUTE(__TR_HORIZONTAL!K85,"Modyo Connect","XQZ0QX"),"WebMethods","XQZ1QX"),"MuleSoft","XQZ2QX"),"DataDog","XQZ3QX"),"BPM/BRM","XQZ4QX"),"en","es"),"XQZ0QX","Modyo Connect"),"XQZ1QX","WebMethods"),"XQZ2QX","MuleSoft"),"XQZ3QX","DataDog"),"XQZ4QX","BPM/BRM") -> orquestación MuleSoft; Software AG WebMethods BPM/BRM; Gestión de invocaciones de Apigee; Orquestación de flujo estilo máquina de estados Modyo Connect; Diagnóstico DataDog.
G86: 8.1.2 | H86: =_xlfn.TRANSLATE(__TR_HORIZONTAL!H86,"en","es") -> Control de ejecución paralela y condicional | I86: =_xlfn.TRANSLATE(__TR_HORIZONTAL!I86,"en","es") -> Ejecución concurrente y condicionada por reglas de pasos de orquestación con agregación de resultados. | J86: =_xlfn.TRANSLATE(__TR_HORIZONTAL!J86,"en","es") -> Mantiene los tiempos de respuesta aceptables cuando un viaje requiere varios sistemas de backend. | K86: =SUBSTITUTE(SUBSTITUTE(SUBSTITUTE(SUBSTITUTE(SUBSTITUTE(_xlfn.TRANSLATE(SUBSTITUTE(SUBSTITUTE(SUBSTITUTE(SUBSTITUTE(SUBSTITUTE(__TR_HORIZONTAL!K86,"Modyo Connect","XQZ0QX"),"WebMethods","XQZ1QX"),"MuleSoft","XQZ2QX"),"DataDog","XQZ3QX"),"BPM/BRM","XQZ4QX"),"en","es"),"XQZ0QX","Modyo Connect"),"XQZ1QX","WebMethods"),"XQZ2QX","MuleSoft"),"XQZ3QX","DataDog"),"XQZ4QX","BPM/BRM") -> orquestación MuleSoft; Software AG WebMethods BPM/BRM; Gestión de invocaciones de Apigee; Orquestación de flujo estilo máquina de estados Modyo Connect; Diagnóstico DataDog.
G87: 8.1.3 | H87: =_xlfn.TRANSLATE(__TR_HORIZONTAL!H87,"en","es") -> Gestión de invocaciones | I87: =_xlfn.TRANSLATE(__TR_HORIZONTAL!I87,"en","es") -> Gestión de estilos de invocación síncronos y asíncronos, tiempos de espera, intentos de repetición y manejo de fallos parciales. | J87: =_xlfn.TRANSLATE(__TR_HORIZONTAL!J87,"en","es") -> Permite que cada plataforma participante se integre en el estilo que realmente soporta, sin penalizar al consumidor. | K87: =SUBSTITUTE(SUBSTITUTE(SUBSTITUTE(SUBSTITUTE(SUBSTITUTE(_xlfn.TRANSLATE(SUBSTITUTE(SUBSTITUTE(SUBSTITUTE(SUBSTITUTE(SUBSTITUTE(__TR_HORIZONTAL!K87,"Modyo Connect","XQZ0QX"),"WebMethods","XQZ1QX"),"MuleSoft","XQZ2QX"),"DataDog","XQZ3QX"),"BPM/BRM","XQZ4QX"),"en","es"),"XQZ0QX","Modyo Connect"),"XQZ1QX","WebMethods"),"XQZ2QX","MuleSoft"),"XQZ3QX","DataDog"),"XQZ4QX","BPM/BRM") -> orquestación MuleSoft; Software AG WebMethods BPM/BRM; Gestión de invocaciones de Apigee; Orquestación de flujo estilo máquina de estados Modyo Connect; Diagnóstico DataDog.
G88: 8.1.4 | H88: =_xlfn.TRANSLATE(__TR_HORIZONTAL!H88,"en","es") -> Monitorización y diagnóstico de orquestación | I88: =_xlfn.TRANSLATE(__TR_HORIZONTAL!I88,"en","es") -> Instrumentación de la ejecución de orquestación con emisión de eventos técnicos y empresariales. | J88: =_xlfn.TRANSLATE(__TR_HORIZONTAL!J88,"en","es") -> Hace que los servicios compuestos sean operativos, lo cual es la condición práctica para confiarles los viajes de ingresos. | K88: =SUBSTITUTE(SUBSTITUTE(SUBSTITUTE(SUBSTITUTE(SUBSTITUTE(_xlfn.TRANSLATE(SUBSTITUTE(SUBSTITUTE(SUBSTITUTE(SUBSTITUTE(SUBSTITUTE(__TR_HORIZONTAL!K88,"Modyo Connect","XQZ0QX"),"WebMethods","XQZ1QX"),"MuleSoft","XQZ2QX"),"DataDog","XQZ3QX"),"BPM/BRM","XQZ4QX"),"en","es"),"XQZ0QX","Modyo Connect"),"XQZ1QX","WebMethods"),"XQZ2QX","MuleSoft"),"XQZ3QX","DataDog"),"XQZ4QX","BPM/BRM") -> orquestación MuleSoft; Software AG WebMethods BPM/BRM; Gestión de invocaciones de Apigee; Orquestación de flujo estilo máquina de estados Modyo Connect; Diagnóstico DataDog.
D89: 8.2 | E89: =_xlfn.TRANSLATE(__TR_HORIZONTAL!E89,"en","es") -> Marco de Integración y Mediación | F89: =_xlfn.TRANSLATE(__TR_HORIZONTAL!F89,"en","es") -> Servicios de transformación, mapeo y puente de protocolos que reconcilian diferentes contratos, formatos y mecanismos de comunicación entre plataformas participantes. | PROPÓSITO: Absorbe la heterogeneidad para que añadir un nuevo procesador o proveedor sea un ejercicio de adaptación en lugar de un cambio en el patrimonio consumidor. | G89: 8.2.1 | H89: =_xlfn.TRANSLATE(__TR_HORIZONTAL!H89,"en","es") -> Transformación y Mapeo de Mensajes | I89: =_xlfn.TRANSLATE(__TR_HORIZONTAL!I89,"en","es") -> Mapeado declarativo entre estructuras de mensajes canónicas y nativas, incluyendo enriquecimiento y predeterminación. | J89: =_xlfn.TRANSLATE(__TR_HORIZONTAL!J89,"en","es") -> Mantiene el contrato canónico estable mientras los formatos nativos cambian por debajo. | K89: =SUBSTITUTE(SUBSTITUTE(SUBSTITUTE(SUBSTITUTE(SUBSTITUTE(_xlfn.TRANSLATE(SUBSTITUTE(SUBSTITUTE(SUBSTITUTE(SUBSTITUTE(SUBSTITUTE(__TR_HORIZONTAL!K89,"MuleSoft","XQZ0QX"),"OpenAPI","XQZ1QX"),"Swagger","XQZ2QX"),"BIAN","XQZ3QX"),"API","XQZ4QX"),"en","es"),"XQZ0QX","MuleSoft"),"XQZ1QX","OpenAPI"),"XQZ2QX","Swagger"),"XQZ3QX","BIAN"),"XQZ4QX","API") -> Transformación MuleSoft y puente de protocolo; Contratos Apigee API; diseño canónico de servicios BIAN; DataStage para la transformación de datos; Documentación OpenAPI/Swagger API.
G90: 8.2.2 | H90: =_xlfn.TRANSLATE(__TR_HORIZONTAL!H90,"en","es") -> Puente de protocolo | I90: =SUBSTITUTE(SUBSTITUTE(_xlfn.TRANSLATE(SUBSTITUTE(SUBSTITUTE(__TR_HORIZONTAL!I90,"REST","XQZ0QX"),"gRPC","XQZ1QX"),"en","es"),"XQZ0QX","REST"),"XQZ1QX","gRPC") -> Adaptación entre mecanismos de comunicación (REST, gRPC, mensajería, archivos, protocolos de transacciones heredados). | J90: =_xlfn.TRANSLATE(__TR_HORIZONTAL!J90,"en","es") -> Permite que los protocolos heredados participen en los viajes modernos sin forzar una reescritura como condición previa. | K90: =SUBSTITUTE(SUBSTITUTE(SUBSTITUTE(SUBSTITUTE(SUBSTITUTE(_xlfn.TRANSLATE(SUBSTITUTE(SUBSTITUTE(SUBSTITUTE(SUBSTITUTE(SUBSTITUTE(__TR_HORIZONTAL!K90,"MuleSoft","XQZ0QX"),"OpenAPI","XQZ1QX"),"Swagger","XQZ2QX"),"BIAN","XQZ3QX"),"API","XQZ4QX"),"en","es"),"XQZ0QX","MuleSoft"),"XQZ1QX","OpenAPI"),"XQZ2QX","Swagger"),"XQZ3QX","BIAN"),"XQZ4QX","API") -> Transformación MuleSoft y puente de protocolo; Contratos Apigee API; diseño canónico de servicios BIAN; DataStage para la transformación de datos; Documentación OpenAPI/Swagger API.
G91: 8.2.3 | H91: =_xlfn.TRANSLATE(__TR_HORIZONTAL!H91,"en","es") -> Mapeo dinámico de datos y gobernanza de esquemas | I91: =_xlfn.TRANSLATE(__TR_HORIZONTAL!I91,"en","es") -> Definiciones de mapeo configurables y versionadas y contratos de esquema mantenidos fuera del código de aplicación. | J91: =_xlfn.TRANSLATE(__TR_HORIZONTAL!J91,"en","es") -> Convierte el cambio de contrato en un evento de configuración controlado, aislando la plataforma de cambios externos en el sistema. | K91: =SUBSTITUTE(SUBSTITUTE(SUBSTITUTE(SUBSTITUTE(SUBSTITUTE(_xlfn.TRANSLATE(SUBSTITUTE(SUBSTITUTE(SUBSTITUTE(SUBSTITUTE(SUBSTITUTE(__TR_HORIZONTAL!K91,"MuleSoft","XQZ0QX"),"OpenAPI","XQZ1QX"),"Swagger","XQZ2QX"),"BIAN","XQZ3QX"),"API","XQZ4QX"),"en","es"),"XQZ0QX","MuleSoft"),"XQZ1QX","OpenAPI"),"XQZ2QX","Swagger"),"XQZ3QX","BIAN"),"XQZ4QX","API") -> Transformación MuleSoft y puente de protocolo; Contratos Apigee API; diseño canónico de servicios BIAN; DataStage para la transformación de datos; Documentación OpenAPI/Swagger API.
D92: 8.3 | E92: =_xlfn.TRANSLATE(__TR_HORIZONTAL!E92,"en","es") -> Gestión del contexto | F92: =_xlfn.TRANSLATE(__TR_HORIZONTAL!F92,"en","es") -> Captura, propagación y disponibilidad consistente del contexto de ejecución —identidad, canal, entidad, ubicación, correlación, derechos— en cada salto de un servicio compuesto. | PROPÓSITO: Sin contexto propagado, auditoría distribuida, aplicación de derechos y rastreo se rompen en el primer límite del sistema. | G92: 8.3.1 | H92: =_xlfn.TRANSLATE(__TR_HORIZONTAL!H92,"en","es") -> Propagación del contexto de la solicitud | I92: =_xlfn.TRANSLATE(__TR_HORIZONTAL!I92,"en","es") -> Transmisión estandarizada del contexto del llamador, canal y correlación a través de todos los saltos de orquestación. | J92: =_xlfn.TRANSLATE(__TR_HORIZONTAL!J92,"en","es") -> Permite una autorización, auditoría y rastreo consistentes independientemente de cuántos sistemas participen. | K92: =SUBSTITUTE(_xlfn.TRANSLATE(SUBSTITUTE(__TR_HORIZONTAL!K92,"MuleSoft","XQZ0QX"),"en","es"),"XQZ0QX","MuleSoft") -> Disco de Oro / Party-CIF; Catálogo de productos y marco de AA; BRM; Propagación del contexto Apigee/MuleSoft; No es un producto de registro separado en las fuentes.
G93: 8.3.2 | H93: =_xlfn.TRANSLATE(__TR_HORIZONTAL!H93,"en","es") -> Registro de Servicios y Configuración de Reglas | I93: =_xlfn.TRANSLATE(__TR_HORIZONTAL!I93,"en","es") -> Registro de servicios con sus características de ejecución, reglas y metadatos administrativos. | J93: =_xlfn.TRANSLATE(__TR_HORIZONTAL!J93,"en","es") -> Hace que el comportamiento del servicio (atomicidad, aprobaciones, elegibilidad para reintentos) sea declarativo y gobernado centralmente. | K93: =SUBSTITUTE(_xlfn.TRANSLATE(SUBSTITUTE(__TR_HORIZONTAL!K93,"MuleSoft","XQZ0QX"),"en","es"),"XQZ0QX","MuleSoft") -> Disco de Oro / Party-CIF; Catálogo de productos y marco de AA; BRM; Propagación del contexto Apigee/MuleSoft; No es un producto de registro separado en las fuentes.
D94: 8.4 | E94: =_xlfn.TRANSLATE(__TR_HORIZONTAL!E94,"en","es") -> Adaptadores heredados | F94: =SUBSTITUTE(SUBSTITUTE(_xlfn.TRANSLATE(SUBSTITUTE(SUBSTITUTE(__TR_HORIZONTAL!F94,"APIs","XQZ0QX"),"API","XQZ1QX"),"en","es"),"XQZ0QX","APIs"),"XQZ1QX","API") -> envoltorios de servicio y adaptadores específicos de plataforma que exponen funciones residentes heredadas como APIs estándar y eventos, conectando desde la arquitectura de microservicios hasta mainframes y plataformas propietarias. | PROPÓSITO: La capacidad de coexistencia de caballo de batalla: hace que la función heredada sea consumible por los viajes modernos sin modificar el código heredado, lo que permite que la modernización sea incremental y reversible. | G94: 8.4.1 | H94: =_xlfn.TRANSLATE(__TR_HORIZONTAL!H94,"en","es") -> Envoltorios de servicio y exposición de servicios heredados | I94: =SUBSTITUTE(SUBSTITUTE(_xlfn.TRANSLATE(SUBSTITUTE(SUBSTITUTE(__TR_HORIZONTAL!I94,"APIs","XQZ0QX"),"API","XQZ1QX"),"en","es"),"XQZ0QX","APIs"),"XQZ1QX","API") -> Microservicios que exponen transacciones heredadas como APIs adecuados para orquestación. | J94: =_xlfn.TRANSLATE(__TR_HORIZONTAL!J94,"en","es") -> Desbloquea décadas de funciones empresariales integradas para su reutilización sin necesidad de reescribir. | K94: =_xlfn.TRANSLATE(__TR_HORIZONTAL!K94,"en","es") -> Interfaces temporales usando Strangler Fig/ByPass; envoltorios PISA/Informix; Apificación OfiWeb; Teller Multi Core; interfaces batch/COB y hoja de ruta de desmantelamiento.
G95: 8.4.2 | H95: =_xlfn.TRANSLATE(__TR_HORIZONTAL!H95,"en","es") -> Adaptadores de plataforma | I95: =_xlfn.TRANSLATE(__TR_HORIZONTAL!I95,"en","es") -> Conectividad específica de la plataforma y adaptadores de protocolo para mainframe y entornos propietarios, incluyendo enrutamiento de transacciones. | J95: =_xlfn.TRANSLATE(__TR_HORIZONTAL!J95,"en","es") -> Aísla mecánicas específicas de la plataforma en un componente reemplazable, por lo que el familiar no está acoplado a opciones tecnológicas heredadas. | K95: =_xlfn.TRANSLATE(__TR_HORIZONTAL!K95,"en","es") -> Interfaces temporales usando Strangler Fig/ByPass; envoltorios PISA/Informix; Apificación OfiWeb; Teller Multi Core; interfaces batch/COB y hoja de ruta de desmantelamiento.
G96: 8.4.3 | H96: =_xlfn.TRANSLATE(__TR_HORIZONTAL!H96,"en","es") -> Interfaces de lote y sincronización de datos heredadas | I96: =_xlfn.TRANSLATE(__TR_HORIZONTAL!I96,"en","es") -> Se requieren mecanismos de sincronización por lotes y de datos junto con acceso en tiempo real a plataformas heredadas. | J96: =SUBSTITUTE(_xlfn.TRANSLATE(SUBSTITUTE(__TR_HORIZONTAL!J96,"API","XQZ0QX"),"en","es"),"XQZ0QX","API") -> Cubre la realidad residual por lotes que las estrategias puras API suelen subestimar. | K96: =_xlfn.TRANSLATE(__TR_HORIZONTAL!K96,"en","es") -> Interfaces temporales usando Strangler Fig/ByPass; envoltorios PISA/Informix; Apificación OfiWeb; Teller Multi Core; interfaces batch/COB y hoja de ruta de desmantelamiento.
G97: 8.4.4 | H97: =_xlfn.TRANSLATE(__TR_HORIZONTAL!H97,"en","es") -> Ciclo de vida del adaptador y desmantelamiento | I97: =_xlfn.TRANSLATE(__TR_HORIZONTAL!I97,"en","es") -> Introducción controlada, doble funcionamiento y retirada de adaptadores a medida que las funciones migran fuera del legado. | J97: =_xlfn.TRANSLATE(__TR_HORIZONTAL!J97,"en","es") -> Garantiza que los adaptadores tácticos se retiren activamente en lugar de convertirse en arquitectura permanente. | K97: =_xlfn.TRANSLATE(__TR_HORIZONTAL!K97,"en","es") -> Interfaces temporales usando Strangler Fig/ByPass; envoltorios PISA/Informix; Apificación OfiWeb; Teller Multi Core; interfaces batch/COB y hoja de ruta de desmantelamiento.
A98: 9 | B98: =_xlfn.TRANSLATE(__TR_HORIZONTAL!B98,"en","es") -> Orquestación de procesos | C98: =_xlfn.TRANSLATE(__TR_HORIZONTAL!C98,"en","es") -> Ejecución y control de procesos empresariales de mayor duración que combinan pasos del sistema y humanos —definición de flujos de trabajo, gestión de tareas, persistencia de estados, gestión de excepciones y escalada— implementados en motores de flujo de trabajo ligeros en lugar de suites BPM empresariales de gran tamaño. | PROPÓSITO: Separa el flujo técnico de milisegundos del flujo de negocio de varios días. Ofrece al banco un lugar para expresar jerarquías de autorización, controles de cuatro ojos, gestión de excepciones y viajes reanudables sin incrustarlos ni en el canal ni en el núcleo, lo que hace que los viajes sean portátiles entre productos y canales. | D98: 9.1 | E98: =_xlfn.TRANSLATE(__TR_HORIZONTAL!E98,"en","es") -> Servicios de flujo de trabajo | F98: =_xlfn.TRANSLATE(__TR_HORIZONTAL!F98,"en","es") -> Definición, versión y ejecución de procesos empresariales de varios pasos que abarcan servicios, sistemas y participantes humanos. | PROPÓSITO: Hace que la lógica del proceso sea explícita y modificable según la autoridad de diseño en lugar de implícita en el código entre varios sistemas. | G98: 9.1.1 | H98: =_xlfn.TRANSLATE(__TR_HORIZONTAL!H98,"en","es") -> Definición y Versionado de Flujos de Trabajo | I98: =_xlfn.TRANSLATE(__TR_HORIZONTAL!I98,"en","es") -> Modelado y control de versiones de definiciones de procesos, con promoción controlada entre entornos. | J98: =_xlfn.TRANSLATE(__TR_HORIZONTAL!J98,"en","es") -> Permite cambiar procesos a ritmo empresarial sin necesidad de una liberación de núcleos. | K98: =SUBSTITUTE(SUBSTITUTE(SUBSTITUTE(_xlfn.TRANSLATE(SUBSTITUTE(SUBSTITUTE(SUBSTITUTE(__TR_HORIZONTAL!K98,"Modyo Connect","XQZ0QX"),"WebMethods","XQZ1QX"),"SmartVista","XQZ2QX"),"en","es"),"XQZ0QX","Modyo Connect"),"XQZ1QX","WebMethods"),"XQZ2QX","SmartVista") -> WebMethods BPM; Flujo de trabajo/máquina de estados Modyo Connect; Gestión de trabajos de Ingeniería de Flujos/Jira para la entrega; fluye a través de Apolo, SmartVista y Transact.
G99: 9.1.2 | H99: =_xlfn.TRANSLATE(__TR_HORIZONTAL!H99,"en","es") -> Ejecución de flujos de trabajo y coordinación de pasos | I99: =_xlfn.TRANSLATE(__TR_HORIZONTAL!I99,"en","es") -> Ejecución en tiempo de ejecución de instancias de proceso, invocación de servicios y espera de resultados externos. | J99: =_xlfn.TRANSLATE(__TR_HORIZONTAL!J99,"en","es") -> Proporciona una ejecución fiable de viajes que abarcan días y múltiples sistemas. | K99: =SUBSTITUTE(SUBSTITUTE(SUBSTITUTE(_xlfn.TRANSLATE(SUBSTITUTE(SUBSTITUTE(SUBSTITUTE(__TR_HORIZONTAL!K99,"Modyo Connect","XQZ0QX"),"WebMethods","XQZ1QX"),"SmartVista","XQZ2QX"),"en","es"),"XQZ0QX","Modyo Connect"),"XQZ1QX","WebMethods"),"XQZ2QX","SmartVista") -> WebMethods BPM; Flujo de trabajo/máquina de estados Modyo Connect; Gestión de trabajos de Ingeniería de Flujos/Jira para la entrega; fluye a través de Apolo, SmartVista y Transact.
G100: 9.1.3 | H100: =_xlfn.TRANSLATE(__TR_HORIZONTAL!H100,"en","es") -> Configuración de reglas de negocio | I100: =_xlfn.TRANSLATE(__TR_HORIZONTAL!I100,"en","es") -> Normas externalizadas que regulan el enrutamiento, umbrales, elegibilidad y los participantes requeridos por tipo de proceso. | J100: =_xlfn.TRANSLATE(__TR_HORIZONTAL!J100,"en","es") -> Mantiene configurables las diferencias de políticas entre productos, entidades y países en lugar de bifurcadas en el código. | K100: =SUBSTITUTE(SUBSTITUTE(_xlfn.TRANSLATE(SUBSTITUTE(SUBSTITUTE(__TR_HORIZONTAL!K100,"WebMethods","XQZ0QX"),"SmartVista","XQZ1QX"),"en","es"),"XQZ0QX","WebMethods"),"XQZ1QX","SmartVista") -> BRM; WebMethods BRM; Marco de Transacción/Catálogo de Productos AA; Parametrización SmartVista; Reglas de puntuación de Merit Crediticio.
D101: 9.2 | E101: =_xlfn.TRANSLATE(__TR_HORIZONTAL!E101,"en","es") -> Gestión de tareas humanas | F101: =_xlfn.TRANSLATE(__TR_HORIZONTAL!F101,"en","es") -> Creación, asignación, priorización y finalización de tareas humanas derivadas de procesos automatizados, incluyendo listas de trabajo y delegación. | PROPÓSITO: Integra los pasos humanos que permanecen en los procesos bancarios regulados sin empujarlos de nuevo a las aplicaciones de canal. | G101: 9.2.1 | H101: =_xlfn.TRANSLATE(__TR_HORIZONTAL!H101,"en","es") -> Asignación de tareas y gestión de listas de trabajo | I101: =_xlfn.TRANSLATE(__TR_HORIZONTAL!I101,"en","es") -> Enrutamiento de elementos de trabajo a roles, colas e individuos con priorización y reasignación. | J101: =_xlfn.TRANSLATE(__TR_HORIZONTAL!J101,"en","es") -> Da a las operaciones una bandeja de entrada gobernada en lugar de colas por tarea por aplicación. | K101: =_xlfn.TRANSLATE(__TR_HORIZONTAL!K101,"en","es") -> Teller Multi Core para tareas de ramificación asistida; Flujo de trabajo OnBase/documentos; Filas de trabajo SIWEB/OFI y sucursales/centros de llamadas. No hay ninguna herramienta de tarea BPM completamente evidenciada.
G102: 9.2.2 | H102: =_xlfn.TRANSLATE(__TR_HORIZONTAL!H102,"en","es") -> Intercepción y Reanudación de Tareas | I102: =_xlfn.TRANSLATE(__TR_HORIZONTAL!I102,"en","es") -> Suspensión de la ejecución de un servicio pendiente de acción humana y reanudación al finalizar. | J102: =_xlfn.TRANSLATE(__TR_HORIZONTAL!J102,"en","es") -> Permite insertar controles en viajes automatizados sin necesidad de rediseñar el recorrido. | K102: =_xlfn.TRANSLATE(__TR_HORIZONTAL!K102,"en","es") -> Teller Multi Core para tareas de ramificación asistida; Flujo de trabajo OnBase/documentos; Filas de trabajo SIWEB/OFI y sucursales/centros de llamadas. No hay ninguna herramienta de tarea BPM completamente evidenciada.
...

Sheet __TR_VERTICAL
A1: Level | B1: Sequence | C1: PID | D1: Name | E1: Description | F1: Process Owner | G1: Interop Level | H1: Kernel or Domain | I1: Purpose in Interoperable Architecture | J1: Sourcing Strategy (Indicative) | K1: BanCoppel Solutions Used (Project)
A2: 1 | B2: 1 | C2: 5 | D2: API Management | E2: The capability to design, publish, secure, version, meter and retire the bank's synchronous service contracts, together with the developer-facing estate that surrounds them (catalogue, portal, sandbox). Covers both the runtime plane (gateway mediation, routing, traffic policy) and the control plane (lifecycle, policy administration, analytics). | F2: Head of API & Integration Architecture | G2: L0 | H2: Kernel & Platform | I2: Primary decoupling instrument of the interoperable architecture. A stable, standards-based contract (BIAN-aligned or canonical-custom) allows a channel to be re-platformed without touching a core, and a core to be replaced without touching a channel. It is also the semantic control point where a request stops being a call to a specific system and becomes a call to a banking capability. | J2: Third party platform + custom policies | K2: Apigee API Management/Gateway; MuleSoft; WebMethods; BIAN-aligned APIs; Transact OFS/IRIS REST APIs; Modyo Connect/Amazon API Gateway for Apolo flows.
A3: 2 | B3: 1 | C3: 5.1 | D3: API Gateway & Runtime Mediation | E3: Runtime plane that terminates, validates, mediates and routes API traffic between consumers and providers, applying policy at the point of invocation rather than inside application code. | F3: Head of API & Integration Architecture | G3: L1 | H3: Kernel & Platform | I3: Enforces the contract at runtime, so decoupling is guaranteed by the platform instead of by developer discipline. | J3: Third party | K3: Apigee API Gateway/API Management; MuleSoft integration/orchestration; WebMethods BPM/BRM; BIAN-aligned APIs; Transact OFS/IRIS REST APIs.
A4: 3 | B4: 1 | C4: 5.1.1 | D4: Routing | E4: Resolution of a logical API contract to one or more physical service endpoints, including host, version and environment-based routing. | F4: Head of API & Integration Architecture | G4: L2 | H4: Kernel & Platform | I4: Allows backend relocation, re-platforming and dual-running of old and new processors without any consumer change. | J4: Third party | K4: Apigee API Gateway/API Management; MuleSoft integration/orchestration; WebMethods BPM/BRM; BIAN-aligned APIs; Transact OFS/IRIS REST APIs.
A5: 3 | B5: 2 | C5: 5.1.2 | D5: Mediation & Message Transformation | E5: Protocol and payload adaptation at the edge (REST, SOAP, gRPC, legacy protocols), including header manipulation and canonical-to-native mapping. | F5: Head of API & Integration Architecture | G5: L2 | H5: Kernel & Platform | I5: Absorbs the technical heterogeneity of a hybrid core estate so consumers only ever see one interface style. | J5: Third party | K5: Apigee API Gateway/API Management; MuleSoft integration/orchestration; WebMethods BPM/BRM; BIAN-aligned APIs; Transact OFS/IRIS REST APIs.
A6: 3 | B6: 3 | C6: 5.1.3 | D6: API Traffic Management | E6: Quota, rate limit, throttling, spike arrest and quality-of-service policies applied per consumer, per API and per tier. | F6: Head of API & Integration Architecture | G6: L2 | H6: Kernel & Platform | I6: Protects finite legacy capacity (MIPS, connection pools) from unbounded digital demand and makes capacity a governed, priced resource. | J6: Third party | K6: Apigee API Gateway/API Management; MuleSoft integration/orchestration; WebMethods BPM/BRM; BIAN-aligned APIs; Transact OFS/IRIS REST APIs.
A7: 3 | B7: 4 | C7: 5.1.4 | D7: Message Validation & Payload Protection | E7: Schema, size and content validation of inbound and outbound messages, including protection against content-based attacks. | F7: Head of API & Integration Architecture | G7: L2 | H7: Kernel & Platform | I7: Stops malformed and hostile traffic before it reaches the processing estate, where remediation is far more expensive. | J7: Third party | K7: Apigee API Gateway/API Management; MuleSoft integration/orchestration; WebMethods BPM/BRM; BIAN-aligned APIs; Transact OFS/IRIS REST APIs.
A8: 3 | B8: 5 | C8: 5.1.5 | D8: Error Handling & Fault Normalisation | E8: Standardised error taxonomy, fault mapping and response codes across heterogeneous backends. | F8: Head of API & Integration Architecture | G8: L2 | H8: Kernel & Platform | I8: Prevents backend-specific error semantics leaking into channels, which is one of the commonest sources of hidden coupling. | J8: Third party | K8: Apigee API Gateway/API Management; MuleSoft integration/orchestration; WebMethods BPM/BRM; BIAN-aligned APIs; Transact OFS/IRIS REST APIs.
A9: 2 | B9: 2 | C9: 5.2 | D9: API Lifecycle Management | E9: Control plane that governs an API from design and contract definition through publication, versioning, change notification and eventual retirement. | F9: Head of API & Integration Architecture | G9: L1 | H9: Kernel & Platform | I9: Turns interfaces into managed enterprise assets with a controlled change path, which is the precondition for reuse across entities and countries. | J9: Third party + governance process | K9: BIAN API standards; Apigee API lifecycle/governance; OpenAPI/Swagger-style API documentation for OfiWeb/Canales; API change controlled by architecture governance.
A10: 3 | B10: 1 | C10: 5.2.1 | D10: API Design & Contract Standards | E10: Definition and enforcement of interface standards, canonical or BIAN-aligned naming, and design review gates before publication. | F10: Head of API & Integration Architecture | G10: L2 | H10: Kernel & Platform | I10: Ensures new interfaces increase reuse rather than adding another bespoke integration to maintain. | J10: Third party + governance process | K10: BIAN API standards; Apigee API lifecycle/governance; OpenAPI/Swagger-style API documentation for OfiWeb/Canales; API change controlled by architecture governance.
A11: 3 | B11: 2 | C11: 5.2.2 | D11: API Versioning | E11: Concurrent support of multiple contract versions with defined compatibility and deprecation rules. | F11: Head of API & Integration Architecture | G11: L2 | H11: Kernel & Platform | I11: Decouples consumer and provider release cycles, so no single change requires a synchronised big-bang deployment. | J11: Third party + governance process | K11: BIAN API standards; Apigee API lifecycle/governance; OpenAPI/Swagger-style API documentation for OfiWeb/Canales; API change controlled by architecture governance.
A12: 3 | B12: 3 | C12: 5.2.3 | D12: API Publication & Change Notification | E12: Promotion of APIs across environments and proactive notification of contract change to registered consumers. | F12: Head of API & Integration Architecture | G12: L2 | H12: Kernel & Platform | I12: Removes the coordination overhead that otherwise makes teams avoid reusing a shared interface. | J12: Third party + governance process | K12: BIAN API standards; Apigee API lifecycle/governance; OpenAPI/Swagger-style API documentation for OfiWeb/Canales; API change controlled by architecture governance.
A13: 3 | B13: 4 | C13: 5.2.4 | D13: API Deprecation & Retirement | E13: Controlled sunset of interfaces, including consumer migration tracking and enforcement of end-of-life dates. | F13: Head of API & Integration Architecture | G13: L2 | H13: Kernel & Platform | I13: Prevents the interoperability layer accumulating the same interface debt it was created to remove. | J13: Third party + governance process | K13: BIAN API standards; Apigee API lifecycle/governance; OpenAPI/Swagger-style API documentation for OfiWeb/Canales; API change controlled by architecture governance.
A14: 2 | B14: 3 | C14: 5.3 | D14: API Manager (Platform Administration) | E14: Administration, policy configuration, operation and commercial instrumentation of the API management platform itself, across on-premise, cloud or hybrid topologies. | F14: Head of API & Integration Architecture | G14: L1 | H14: Kernel & Platform | I14: Keeps policy centrally administered and consistently applied, so security and traffic rules do not fragment per API team. | J14: Third party | K14: Apigee platform administration and policies; DataDog/API monitoring; DevSecOps pipelines; GCP-hosted Apigee with AWS/on-prem providers.
A15: 3 | B15: 1 | C15: 5.3.1 | D15: Policy Administration & Tracking | E15: Central definition, assignment and audit of gateway policies (security, traffic, mediation, caching) across the API estate. | F15: Head of API & Integration Architecture | G15: L2 | H15: Kernel & Platform | I15: Makes policy a governed configuration item rather than embedded code, enabling estate-wide change in one action. | J15: Third party | K15: Apigee platform administration and policies; DataDog/API monitoring; DevSecOps pipelines; GCP-hosted Apigee with AWS/on-prem providers.
A16: 3 | B16: 2 | C16: 5.3.2 | D16: API Monitoring, Analytics & Monetisation | E16: Consumption metrics, latency and error analytics per API and per consumer, with the metering basis for internal chargeback or partner monetisation. | F16: Head of API & Integration Architecture | G16: L2 | H16: Kernel & Platform | I16: Provides the evidence base for reuse claims, capacity planning and ecosystem commercial models. | J16: Third party | K16: Apigee platform administration and policies; DataDog/API monitoring; DevSecOps pipelines; GCP-hosted Apigee with AWS/on-prem providers.
A17: 3 | B17: 3 | C17: 5.3.3 | D17: Platform Deployment & Operations | E17: Deployment topology, automation, upgrade and operational support of the API management platform. | F17: Head of API & Integration Architecture | G17: L2 | H17: Kernel & Platform | I17: Ensures the decoupling layer is itself resilient and upgradeable, since it becomes a single point of dependency for all traffic. | J17: Third party | K17: Apigee platform administration and policies; DataDog/API monitoring; DevSecOps pipelines; GCP-hosted Apigee with AWS/on-prem providers.
A18: 2 | B18: 4 | C18: 5.4 | D18: Developer Portal & Catalogue | E18: Self-service surface where internal and external developers discover, evaluate, register for and support themselves on published interfaces. | F18: Head of API & Integration Architecture | G18: L1 | H18: Kernel & Platform | I18: Reuse only happens if capabilities are findable. The portal converts a technical inventory into a consumable product catalogue. | J18: Third party | K18: API catalogue/governance for Apificación de Canales and OfiWeb; Apigee as API management plane. No standalone developer portal tool is explicitly evidenced.
A19: 3 | B19: 1 | C19: 5.4.1 | D19: API Catalogue, Documentation & Metadata Discovery | E19: Searchable inventory of published interfaces with specifications, examples and metadata. | F19: Head of API & Integration Architecture | G19: L2 | H19: Kernel & Platform | I19: Eliminates the rediscovery cost that drives teams to build a parallel point-to-point integration. | J19: Third party | K19: API catalogue/governance for Apificación de Canales and OfiWeb; Apigee as API management plane. No standalone developer portal tool is explicitly evidenced.
A20: 3 | B20: 2 | C20: 5.4.2 | D20: Developer Registration & Self-Service | E20: Onboarding, credential issuance, application registration and entitlement management for API consumers. | F20: Head of API & Integration Architecture | G20: L2 | H20: Kernel & Platform | I20: Removes human gatekeeping from the consumption path, which is what makes internal reuse and partner onboarding fast. | J20: Third party | K20: API catalogue/governance for Apificación de Canales and OfiWeb; Apigee as API management plane. No standalone developer portal tool is explicitly evidenced.
A21: 3 | B21: 3 | C21: 5.4.3 | D21: Collaboration, Community & Self-Support | E21: Issue reporting, feedback loops, usage guidance, SDKs and reference examples for consuming teams. | F21: Head of API & Integration Architecture | G21: L2 | H21: Kernel & Platform | I21: Delivers the enablement layer without which a published capability is technically available but practically unused. | J21: Third party | K21: API catalogue/governance for Apificación de Canales and OfiWeb; Apigee as API management plane. No standalone developer portal tool is explicitly evidenced.
A22: 1 | B22: 2 | C22: 4 | D22: Gateway Services | E22: Controlled ingress and egress across the bank's trust boundary in three modalities - API, file and event - in both inbound and outbound directions, plus the specialised edges required for regulated and partner traffic (Open Banking edge, filter edge, security token service, partner sandbox, switching). | F22: Head of Perimeter & Connectivity Architecture | G22: L0 | H22: Kernel & Platform | I22: Interoperability is not only internal. This domain concentrates network zoning, protocol termination, encryption and traffic policy for all external counterparties (central bank, card processors, payment schemes, bureaus, fintechs, corporate channels) so that ecosystem participation becomes a configuration exercise rather than a project. It is also where most banks find asymmetry: inbound API gateways are mature while outbound file and event gateways are undefined, and that gap sits on the critical path. | J22: Third party platform + custom edge services | K22: Apigee inbound/outbound API gateway; MuleSoft/WebMethods integration; Amazon API Gateway via Modyo Connect; EKS/Istio service edge.
A23: 2 | B23: 1 | C23: 4.1 | D23: Inbound Gateway Services | E23: Managed entry points for traffic originating outside the bank's trust boundary, across API, file and event channels, including identity assertion exchange at the edge. | F23: Head of Perimeter & Connectivity Architecture | G23: L1 | H23: Kernel & Platform | I23: Gives the bank one governed front door per modality instead of a proliferation of bilateral connections with inconsistent controls. | J23: Third party | K23: Apigee inbound/outbound API gateway; MuleSoft/WebMethods integration; Amazon API Gateway via Modyo Connect; EKS/Istio service edge.
A24: 3 | B24: 1 | C24: 4.1.1 | D24: Inbound API Gateway | E24: Termination, authentication, policy enforcement and routing of synchronous API traffic from channels, partners and third parties. | F24: Head of Perimeter & Connectivity Architecture | G24: L2 | H24: Kernel & Platform | I24: Single enforcement point for external synchronous demand, decoupling counterparties from internal service topology. | J24: Third party | K24: Apigee inbound/outbound API gateway; MuleSoft/WebMethods integration; Amazon API Gateway via Modyo Connect; EKS/Istio service edge.
A25: 3 | B25: 2 | C25: 4.1.2 | D25: Inbound File Gateway | E25: Secure receipt, validation, virus scanning and hand-off of externally originated files, replacing unmanaged point-to-point transfer. | F25: Head of Perimeter & Connectivity Architecture | G25: L2 | H25: Kernel & Platform | I25: Brings the large residual batch estate under the same control and observability regime as API traffic. | J25: Third party | K25: DataStage ETL; batch/COB interfaces; OnBase document flows; PISA/Informix legacy file/data interfaces. No dedicated MFT product is explicitly evidenced.
A26: 3 | B26: 3 | C26: 4.1.3 | D26: Inbound EventHub Gateway | E26: Controlled ingestion of externally published events and messages into the internal event backbone. | F26: Head of Perimeter & Connectivity Architecture | G26: L2 | H26: Kernel & Platform | I26: Enables real-time ecosystem integration (schemes, aggregators, market data) without exposing internal topics. | J26: Third party | K26: Kafka/Confluent; Amazon MQ; Amazon Kinesis; Temenos Events Framework; Event Processor/Event Router/Event Cleanup components.
A27: 3 | B27: 4 | C27: 4.1.4 | D27: Security Token Service (STS) | E27: Issuance, exchange and validation of security tokens at the perimeter, translating external identity assertions into internal credentials. | F27: Head of Perimeter & Connectivity Architecture | G27: L2 | H27: Kernel & Platform | I27: Allows federated and partner identities to be honoured without extending internal trust boundaries outward. | J27: Third party | K27: OAuth 2.0 via Apigee; Azure AD / Microsoft Entra ID; Token Party Identity; application/user tokens managed through API security.
A28: 2 | B28: 2 | C28: 4.2 | D28: Outbound Gateway Services | E28: Managed exit points for bank-originated traffic to downstream counterparties, across API, file and event channels, including transaction switching to schemes and processors. | F28: Head of Perimeter & Connectivity Architecture | G28: L1 | H28: Kernel & Platform | I28: Externalises counterparty-specific connectivity and credentials from application code, so a provider can be replaced without touching business services. | J28: Third party + custom | K28: Apigee inbound/outbound API gateway; MuleSoft/WebMethods integration; Amazon API Gateway via Modyo Connect; EKS/Istio service edge.
A29: 3 | B29: 1 | C29: 4.2.1 | D29: Outbound API Gateway | E29: Egress mediation, credential injection, retry and circuit control for calls to external providers, exposed through a DMZ. | F29: Head of Perimeter & Connectivity Architecture | G29: L2 | H29: Kernel & Platform | I29: Makes third-party substitution a gateway configuration change rather than a development project. | J29: Third party + custom | K29: Apigee inbound/outbound API gateway; MuleSoft/WebMethods integration; Amazon API Gateway via Modyo Connect; EKS/Istio service edge.
A30: 3 | B30: 2 | C30: 4.2.2 | D30: Outbound File Gateway | E30: Managed generation, encryption, scheduling and transmission of outbound files, superseding unmanaged SFTP arrangements. | F30: Head of Perimeter & Connectivity Architecture | G30: L2 | H30: Kernel & Platform | I30: Closes the most common control and observability gap in the external estate. | J30: Third party + custom | K30: DataStage ETL; batch/COB interfaces; OnBase document flows; PISA/Informix legacy file/data interfaces. No dedicated MFT product is explicitly evidenced.
A31: 3 | B31: 3 | C31: 4.2.3 | D31: Outbound EventHub Gateway | E31: Controlled publication of internal events to external subscribers with filtering and contract governance. | F31: Head of Perimeter & Connectivity Architecture | G31: L2 | H31: Kernel & Platform | I31: Lets the bank offer real-time data products to the ecosystem without granting access to internal topics. | J31: Third party + custom | K31: Kafka/Confluent; Amazon MQ; Amazon Kinesis; Temenos Events Framework; Event Processor/Event Router/Event Cleanup components.
A32: 3 | B32: 4 | C32: 4.2.4 | D32: Switching | E32: Routing and protocol adaptation of transaction traffic to schemes, processors and interbank networks, including failover between providers. | F32: Head of Perimeter & Connectivity Architecture | G32: L2 | H32: Kernel & Platform | I32: Provides provider redundancy and least-cost routing as an architectural property rather than a negotiation outcome. | J32: Third party + custom | K32: BPC SmartVista/SVIP for card switching and processing; Hub de Pagos for SPEI, payroll dispersion and multi-platform payments; legacy IST/PISA coexistence.
A33: 2 | B33: 3 | C33: 4.3 | D33: Ecosystem & Open Banking Edge | E33: Specialised external-facing edges for regulated open banking traffic, partner onboarding and controlled experimentation, including filtering edges and marketplace exposure. | F33: Head of Perimeter & Connectivity Architecture | G33: L1 | H33: Kernel & Platform | I33: Where the interoperability layer becomes a business channel: it turns internal capabilities into consumable, contracted products for third parties. | J33: Third party + custom | K33: No specific Open Banking marketplace/partner sandbox product is evidenced; adjacent capabilities use Apigee, API Gateway, BIAN APIs and sandbox/UAT environments.
