Workbook

Sheet Definiciones
B2: Inventario de HUs — Programa Unity / R4
B11: Definición de criterios
B13: Prioridad MoSCoW
B14: Must | C14: La historia es absolutamente necesaria para que R4 pueda salir a producción y cumplir sus objetivos. Si esta Historia no se implementa: - El release no puede desplegarse. - Se incumple un requisito regulatorio. - Se genera un riesgo operativo crítico. - El cliente no puede utilizar el producto. - Se rompe un proceso end-to-end imprescindible Pregunta clave --> ¿Cancelaríamos o retrasaríamos R4 si esta historia no estuviera disponible? Si la respuesta es "Sí", probablemente sea un MUST. Ejemplos:Alta de tarjeta de crédito clásica física para nuevos clientes desde canales digitales, creación de cuenta crédito en Apolo, generación y sincronización del contrato de crédito, Interfaces obligatorias con SmartVista para creación de tarjeta, validaciones regulatorias de KYC requeridas para la contratación, contabilización obligatoria de la apertura de producto, Servicios críticos necesarios para autorización de transacciones.
B15: Should | C15: La historia aporta mucho valor al negocio, pero el release podría salir sin ella mediante una solución temporal o con ciertas restricciones operativas. No compromete la viabilidad del Go-Live. Debe estar en R4 si la capacidad lo permite; si no, va a R4.1 Pregunta clave --> ¿Podemos salir a producción sin esta historia durante algunas semanas o meses, aunque genere incomodidades o trabajo manual? Si la respuesta es "Sí", probablemente sea un SHOULD. Ejemplos: Mejoras de experiencia de usuario en la solicitud, Notificaciones push adicionales, Consultas ampliadas de estatus de tarjeta., Automatización parcial de reportes internos., Dashboard operativo para monitoreo del proceso, Automatización de conciliaciones no críticas
B16: Could | C16: Historias deseables que aportan valor incremental, pero cuyo impacto es limitado. Si no llegan a R4, prácticamente no afectan los objetivos del release. Pregunta clave --> ¿El negocio seguiría funcionando prácticamente igual si esta historia se implementa después del Go-Live? Si la respuesta es "Sí", probablemente sea un COULD. Ejemplos: nuevos filtros de búsqueda, mejoras estéticas de pantalla, mensajería enriquecida al cliente, reportes complementarios, métricas avanzadas de monitoreo, funcionalidades de convivencia para usuarios internos
B17: Won't | C17: Historias explícitamente excluidas de R4/R4.1. No significa que sean malas ideas, significa que no forman parte del alcance comprometido para este release. Pregunta clave --> ¿Estamos de acuerdo en que esta historia se moverá a un release futuro? Ejemplos: funcionalidades previstas para R5 o posteriores, mejoras arquitectónicas no necesarias para R4, automatizaciones futuras, capacidades avanzadas que no afectan la expansión actual de TDC Física.
B19: Complejidad técnica
B20: Alta | C20: Basado en reglas que involucran número de integraciones, impacto y reusabilidad de la solución, número de pantallas y criterios de aceptación de la solución. Ver pestaña "Scoring Complejidad" donde se describe la lógica de estas reglas
B21: Media
B22: Baja
B24: Tipo de HU Solución / Integración
B25: Solución | C25: Los cambios necesarios se realizan exclusivamente dentro de una o varias aplicaciones o plataformas, sin necesidad de crear nuevas integraciones ni modificar integraciones existentes. La historia puede consumir información procedente de otras aplicaciones siempre que las interfaces existentes puedan reutilizarse sin cambios. Pregunta guia--> ¿La historia puede implementarse sin crear ni modificar ninguna interfaz existente? Si la respuesta es Sí, la HU debe clasificarse como Solución. Ejemplo 1: Nueva pantalla para visualizar información de una tarjeta utilizando APIs ya existentes (Motivo: existe desarrollo funcional, pero ninguna integración requiere cambios) Ejemplo 2: Nueva regla para determinar la elegibilidad de clientes para una Tarjeta de Crédito (Motivo: el cambio ocurre dentro del motor de negocio) Ejemplo 3: Nuevo dashboard operativo utilizando información ya disponible en la plataforma.(Motivo: no se crean ni modifican interfaces)
B26: Integración | C26: El objetivo principal es crear una nueva integración o modificar una integración existente entre sistemas — vía API, Batch, Evento, Archivo, MQ, SOAP o REST — . El valor de la historia reside en habilitar o modificar el intercambio de información entre aplicaciones. Importante: La simple utilización de una integración existente NO convierte una HU en Integración. Para ser considerada Integración debe existir: una nueva integración o una modificación de una interfaz existente Pregunta guia--> ¿La historia requiere crear una nueva integración o modificar una integración existente? Si la respuesta es Sí y no existen cambios funcionales relevantes, la HU debe clasificarse como Integración Ejemplo 1: Nueva API entre Apolo y SmartVista para creación de tarjetas Ejemplo 2: Modificación de una interfaz existente para incorporar nuevos atributos de la Tarjeta de Crédito Clásica Física. Ejemplo 3: Nuevo archivo batch diario para enviar movimientos a Contabilidad.
B27: Solución e integración | C27: Requiere simultáneamente: 1) Cambios funcionales dentro de una aplicación. 2) Creación de nuevas integraciones o modificaciones de integraciones existentes. Pregunta guia--> ¿La funcionalidad requiere cambios en la experiencia o proceso de negocio y además intercambio de información entre sistemas? Si la respuesta es sí, estamos ante una HU de Solución + Integración.
B29: Impacto Solución
B30: Caja | C30: La funcionalidad requerida ya está disponible y puede utilizarse sin realizar configuraciones relevantes ni desarrollos adicionales para R4.Esto incluye dos escenarios: -Funcionalidad estándar de la plataforma: la capacidad ya existe de forma nativa en la solución. -Funcionalidad ya desarrollada en releases previos:Aunque originalmente requirió desarrollo, dicho desarrollo ya existe y puede reutilizarse en R4 sin cambios adicionales
B31: Configuración | C31: La funcionalidad existe en la plataforma, pero requiere parametrización o ajustes de configuración para adaptarla a las necesidades de R4. No es necesario desarrollar software nuevo, lo que cambia son los parámetros, reglas o datos maestros Ejemplos: parametrización de productos, configuración de tarifas/límites/perfiles/catálogos, configuración de reglas ya soportadas por la plataforma
B32: Desarrollo | C32: Se requiere construir capacidades nuevas que actualmente no existen en la plataforma y que no pueden resolverse mediante configuración. La plataforma necesita código nuevo para satisfacer el requerimiento.
B33: Desarrollo + Configuración | C33: Una Historia de Usuario se clasifica como Desarrollo + Configuración cuando requiere simultáneamente: - Construcción de nuevas capacidades. - Parametrización de funcionalidades. - Configuración de productos o reglas. - Ajustes de la solución para habilitar el funcionamiento final.
B34: No Aplica | C34: La HU es de integración pura, por lo que el impacto de la solución no aplica como categoría de clasificación.

Sheet Inventario HUs
A1: IDENTIFICACIÓN | F1: ALCANCE | J1: PRIORIDAD E IMPACTO | Q1: MEDICIÓN DE COMPLEJIDAD | W1: Analisis (DEF, Mesas Trabajo, Refinamiento, VoBo) | Y1: Diseño (DTM, DTC , certificaciones Diagramas de flujo) | AA1: Implementación (construcción, pruebas unitarias, y pruebas Product Test) | AC1: Comentarios | AD1: Fecha de última modificación
A2: ID HU | B2: Track / Plataforma | C2: Descripción corta | D2: Producto | E2: Funcionalidad / BB | F2: Descripción Funcional (qué hace) | G2: Reglas de Negocio Clave | H2: Canal(es) Afectado(s) | I2: Usuario Final / Actor Principal | J2: Prioridad MoSCoW | K2: Solución / Integración | L2: # Integraciones | M2: Impacto Solución | N2: Reusabilidad de Solución | O2: # de Criterios de aceptación | P2: # de Pantallas (nuevas o modificadas) | Q2: Calificación Criterios de Aceptación | R2: Calificación Pantallas Asociadas | S2: Calificación Reusabilidad | T2: Calificación de Integraciones | U2: Score Ponderado | V2: Complejidad Total | W2: Fecha Inicio | X2: Fecha Fin | Y2: Fecha Inicio | Z2: Fecha Fin | AA2: Fecha Inicio | AB2: Fecha Fin+J1:ABW1:AB2
A3: HDU-SMART-R4-01 | B3: Smart Vista | C3: Certificar layouts de maquila con proveedores. | D3: TDC | E3: Automatización de Maquila | F3: Habilitar la certificación de layouts posicionales/planos homologados para los 4 proveedores de maquila (GID, Forza, TGS, Thomas Greg & Sons), con cifrado PGP por proveedor y HSM por tarjeta, para emitir tarjetas del producto 4900 de forma controlada y trazable. | G3: Layout único homologado para los 4 maquiladores. Campos alfanuméricos validados para rechazar caracteres no embosables. Cifrado PGP+HSM; vigencia de llaves validada antes de generar. Reproceso de archivo sin alterar números de tarjeta. Solo producto 4900 parametrizado en | H3: Smart Vista | I3: Área de Suministros / Administración de Tarjetas | J3: Must | K3: Solución | L3: 0 | M3: Desarrollo + Configuración | N3: Componentes existentes reutilizables >80% | O3: 5 | P3: 0 | Q3: {=+_xlfn.IFS(O3="","",O3<=1,"Baja",O3<=3,"Media",O3>3,"Alta")} -> Alta | R3: {=+_xlfn.IFS(P3="","",P3<=0,"Baja",P3<=2,"Media",P3>2,"Alta")} -> Baja | S3: {=+_xlfn.IFS(N3="","",N3="Componentes existentes reutilizables >80%","Baja",N3="No Aplica","Baja",N3="Reutilización parcial 30-70%","Media",N3="Nuevo Desarrollo <20%","Alta")} -> Baja | T3: {=+_xlfn.IFS(L3="","",L3=0,"Baja",L3<=2,"Media",L3>=3,"Alta")} -> Baja | U3: {=+IFERROR((+_xlfn.IFS(Q3="",0,Q3="Baja",1,Q3="Media",2,Q3="Alta",3)*'Scoring Complejidad'!$C$8+_xlfn.IFS(R3="Baja",1,R3="Media",2,R3="Alta",3)*'Scoring Complejidad'!$C$9+_xlfn.IFS(S3="Baja",1,S3="Media",2,S3="Alta",3)*'Scoring Complejidad'!$C$7+_xlfn.IFS(T3="",1,T3="Baja",1,T3="Media",2,T3="Alta",3)*'Scoring Complejidad'!$C$5+_xlfn.IFS(M3="Caja",1,M3="Configuración",2,M3="Desarrollo",3,M3="Desarrollo + Configuración",3,M3="No Aplica",0)*'Scoring Complejidad'!$C$6),"")} -> 1.8 | V3: {=IFERROR(_xlfn.IFS(U3="","",U3<=1.69,"Baja",U3<=2.29,"Media",U3<=3,"Alta",U3>3,"Error"),"")} -> Media | W3: 06/07/206 | X3: 20/07/206 | Y3: 21/07/206 | Z3: 04/09/206 | AA3: 17/08/206 | AB3: 30/10/206 | AC3: Certificación de layouts y llaves de PGP- Diseño Con tiempos controlados de desarrollo de la HU Considerar 15 días menos de implementación como supuesto de reducción de alcance a un solo proveedor (proveedor prioritario) de maquila. Considerar que Pruebas de maquila son independientes y no van por la ruta crítica | AD3: 46240
A4: HDU-SMART-R4-02 | B4: Smart Vista | C4: Consultar inventario de tarjetas por sucursal. | D4: TDC | E4: Automatización de Maquila | F4: Consulta del stock de tarjetas disponibles por sucursal distinguiendo 'en existencia', 'en ruta' y 'por fabricar'; cálculo de stock semanal sobre existencias reales; filtro por tipo de sucursal. El inventario vive íntegramente en Smart Vista, sin dependencia de Macweb. | G4: Stock semanal basado SOLO en existencias físicas (no en ruta/por fabricar). Filtro por Tipo de Sucursal. Detalle de lotes en proceso por producto/sucursal. Datos provienen de SV, ruptura con . | H4: Smart Vista | I4: Área de Suministros | J4: Should | K4: Solución | L4: 0 | M4: Desarrollo + Configuración | N4: Nuevo Desarrollo <20% | O4: 4 | P4: 1 | Q4: {=+_xlfn.IFS(O4="","",O4<=1,"Baja",O4<=3,"Media",O4>3,"Alta")} -> Alta | R4: {=+_xlfn.IFS(P4="","",P4<=0,"Baja",P4<=2,"Media",P4>2,"Alta")} -> Media | S4: {=+_xlfn.IFS(N4="","",N4="Componentes existentes reutilizables >80%","Baja",N4="No Aplica","Baja",N4="Reutilización parcial 30-70%","Media",N4="Nuevo Desarrollo <20%","Alta")} -> Alta | T4: {=+_xlfn.IFS(L4="","",L4=0,"Baja",L4<=2,"Media",L4>=3,"Alta")} -> Baja | U4: {=+IFERROR((+_xlfn.IFS(Q4="",0,Q4="Baja",1,Q4="Media",2,Q4="Alta",3)*'Scoring Complejidad'!$C$8+_xlfn.IFS(R4="Baja",1,R4="Media",2,R4="Alta",3)*'Scoring Complejidad'!$C$9+_xlfn.IFS(S4="Baja",1,S4="Media",2,S4="Alta",3)*'Scoring Complejidad'!$C$7+_xlfn.IFS(T4="",1,T4="Baja",1,T4="Media",2,T4="Alta",3)*'Scoring Complejidad'!$C$5+_xlfn.IFS(M4="Caja",1,M4="Configuración",2,M4="Desarrollo",3,M4="Desarrollo + Configuración",3,M4="No Aplica",0)*'Scoring Complejidad'!$C$6),"")} -> 2.3 | V4: {=IFERROR(_xlfn.IFS(U4="","",U4<=1.69,"Baja",U4<=2.29,"Media",U4<=3,"Alta",U4>3,"Error"),"")} -> Alta | W4: 06/07/206 | X4: 20/07/206 | Y4: 21/07/206 | Z4: 04/09/206 | AA4: 17/08/206 | AB4: 30/10/206 | AC4: Considerar 15 días menos de implementación como supuesto de reducción de alcance a un solo proveedor (proveedor prioritario) de maquila. Considerar que Pruebas de maquila son independientes y no van por la ruta crítica | AD4: 46240
A5: HDU-SMART-R4-03 | B5: Smart Vista | C5: Calcular maquila con parámetros de abasto. | D5: TDC | E5: Automatización de Maquila | F5: Cálculo diario automatizado (batch 6:00 AM) de la cantidad de tarjetas a reordenar por sucursal/producto, usando piso mínimo y semanas-a-dotar parametrizables, con redondeo a múltiplos de 250 plásticos y consumo calculado sobre mes calendario completo. | G5: Corrida batch 6:00 AM. Piso mínimo default 4 semanas, parametrizable por producto/sucursal . Semanas a dotar de 1 a N (hoy topado a 3). Redondeo a múltiplos de 250. Consumo sobre mes calendario completo, no ventana fija. | H5: Smart Vista | I5: Área de Suministros | J5: Should | K5: Solución | L5: 0 | M5: Desarrollo + Configuración | N5: Nuevo Desarrollo <20% | O5: 4 | P5: 0 | Q5: {=+_xlfn.IFS(O5="","",O5<=1,"Baja",O5<=3,"Media",O5>3,"Alta")} -> Alta | R5: {=+_xlfn.IFS(P5="","",P5<=0,"Baja",P5<=2,"Media",P5>2,"Alta")} -> Baja | S5: {=+_xlfn.IFS(N5="","",N5="Componentes existentes reutilizables >80%","Baja",N5="No Aplica","Baja",N5="Reutilización parcial 30-70%","Media",N5="Nuevo Desarrollo <20%","Alta")} -> Alta | T5: {=+_xlfn.IFS(L5="","",L5=0,"Baja",L5<=2,"Media",L5>=3,"Alta")} -> Baja | U5: {=+IFERROR((+_xlfn.IFS(Q5="",0,Q5="Baja",1,Q5="Media",2,Q5="Alta",3)*'Scoring Complejidad'!$C$8+_xlfn.IFS(R5="Baja",1,R5="Media",2,R5="Alta",3)*'Scoring Complejidad'!$C$9+_xlfn.IFS(S5="Baja",1,S5="Media",2,S5="Alta",3)*'Scoring Complejidad'!$C$7+_xlfn.IFS(T5="",1,T5="Baja",1,T5="Media",2,T5="Alta",3)*'Scoring Complejidad'!$C$5+_xlfn.IFS(M5="Caja",1,M5="Configuración",2,M5="Desarrollo",3,M5="Desarrollo + Configuración",3,M5="No Aplica",0)*'Scoring Complejidad'!$C$6),"")} -> 2.2 | V5: {=IFERROR(_xlfn.IFS(U5="","",U5<=1.69,"Baja",U5<=2.29,"Media",U5<=3,"Alta",U5>3,"Error"),"")} -> Media | W5: 06/07/206 | X5: 20/07/206 | Y5: 21/07/206 | Z5: 04/09/206 | AA5: 17/08/206 | AB5: 30/10/206 | AC5: Mayor complejidad para llegar a tiempo en fin de análisis Considerar 15 días menos de implementación como supuesto de reducción de alcance a un solo proveedor (proveedor prioritario) de maquila. Considerar que Pruebas de maquila son independientes y no van por la ruta crítica | AD5: 46240
A6: HDU-SMART-R4-04 | B6: Smart Vista | C6: Ejecutar solicitud automatizada de maquila. | D6: TDC | E6: Automatización de Maquila | F6: Detona el proceso de emisión masiva de tarjetas tras el cálculo de reorden. Incluye validación anti-duplicidad, pre-asignación de proveedor, notificación por correo a ~30 destinatarios usando número de lote. Dos pasos pendientes de automatizar en R4: generación OCG vía Cron y entrega Connect Direct. | G6: Solicitud se detona solo si layout tiene datos completos . Anti-duplicidad: si existe solicitud en mismo layout se rechaza . Pre-asignación de proveedor por matriz de capacidades o manual. Correo diario ~30 destinatarios con número de lote. | H6: Smart Vista | I6: Área de Suministros | J6: Must | K6: Solución | L6: 0 | M6: Desarrollo + Configuración | N6: Nuevo Desarrollo <20% | O6: 3 | P6: 0 | Q6: {=+_xlfn.IFS(O6="","",O6<=1,"Baja",O6<=3,"Media",O6>3,"Alta")} -> Media | R6: {=+_xlfn.IFS(P6="","",P6<=0,"Baja",P6<=2,"Media",P6>2,"Alta")} -> Baja | S6: {=+_xlfn.IFS(N6="","",N6="Componentes existentes reutilizables >80%","Baja",N6="No Aplica","Baja",N6="Reutilización parcial 30-70%","Media",N6="Nuevo Desarrollo <20%","Alta")} -> Alta | T6: {=+_xlfn.IFS(L6="","",L6=0,"Baja",L6<=2,"Media",L6>=3,"Alta")} -> Baja | U6: {=+IFERROR((+_xlfn.IFS(Q6="",0,Q6="Baja",1,Q6="Media",2,Q6="Alta",3)*'Scoring Complejidad'!$C$8+_xlfn.IFS(R6="Baja",1,R6="Media",2,R6="Alta",3)*'Scoring Complejidad'!$C$9+_xlfn.IFS(S6="Baja",1,S6="Media",2,S6="Alta",3)*'Scoring Complejidad'!$C$7+_xlfn.IFS(T6="",1,T6="Baja",1,T6="Media",2,T6="Alta",3)*'Scoring Complejidad'!$C$5+_xlfn.IFS(M6="Caja",1,M6="Configuración",2,M6="Desarrollo",3,M6="Desarrollo + Configuración",3,M6="No Aplica",0)*'Scoring Complejidad'!$C$6),"")} -> 2.05 | V6: {=IFERROR(_xlfn.IFS(U6="","",U6<=1.69,"Baja",U6<=2.29,"Media",U6<=3,"Alta",U6>3,"Error"),"")} -> Media | W6: 06/07/206 | X6: 20/07/206 | Y6: 21/07/206 | Z6: 04/09/206 | AA6: 17/08/206 | AB6: 30/10/206 | AC6: Mayor complejidad para llegar a tiempo en fin de análisis Considerar 15 días menos de implementación como supuesto de reducción de alcance a un solo proveedor (proveedor prioritario) de maquila. Considerar que Pruebas de maquila son independientes y no van por la ruta crítica | AD6: 46240
A7: HDU-SMART-R4-05 | B7: Smart Vista | C7: Ejecutar solicitud manual de maquila. | D7: TDC | E7: Automatización de Maquila | F7: Permite al área de Suministros generar solicitudes manuales de maquila para casos específicos (ej. apertura de sucursal), usando el mismo layout que la maquila automática. Restricción: un lote por día por sucursal. | G7: Solicitud manual usa layout único compartido con la automática. Dotación inicial garantizada ante apertura de sucursal nueva. Restricción: 1 lote/día/sucursal (proceso tarda 2-3 semanas). Funcionalidad demo confirmada en S1/S2. | H7: Smart Vista | I7: Área de Suministros | J7: Must | K7: Solución | L7: 0 | M7: Desarrollo + Configuración | N7: Reutilización parcial 30-70% | O7: 3 | P7: 1 | Q7: {=+_xlfn.IFS(O7="","",O7<=1,"Baja",O7<=3,"Media",O7>3,"Alta")} -> Media | R7: {=+_xlfn.IFS(P7="","",P7<=0,"Baja",P7<=2,"Media",P7>2,"Alta")} -> Media | S7: {=+_xlfn.IFS(N7="","",N7="Componentes existentes reutilizables >80%","Baja",N7="No Aplica","Baja",N7="Reutilización parcial 30-70%","Media",N7="Nuevo Desarrollo <20%","Alta")} -> Media | T7: {=+_xlfn.IFS(L7="","",L7=0,"Baja",L7<=2,"Media",L7>=3,"Alta")} -> Baja | U7: {=+IFERROR((+_xlfn.IFS(Q7="",0,Q7="Baja",1,Q7="Media",2,Q7="Alta",3)*'Scoring Complejidad'!$C$8+_xlfn.IFS(R7="Baja",1,R7="Media",2,R7="Alta",3)*'Scoring Complejidad'!$C$9+_xlfn.IFS(S7="Baja",1,S7="Media",2,S7="Alta",3)*'Scoring Complejidad'!$C$7+_xlfn.IFS(T7="",1,T7="Baja",1,T7="Media",2,T7="Alta",3)*'Scoring Complejidad'!$C$5+_xlfn.IFS(M7="Caja",1,M7="Configuración",2,M7="Desarrollo",3,M7="Desarrollo + Configuración",3,M7="No Aplica",0)*'Scoring Complejidad'!$C$6),"")} -> 1.95 | V7: {=IFERROR(_xlfn.IFS(U7="","",U7<=1.69,"Baja",U7<=2.29,"Media",U7<=3,"Alta",U7>3,"Error"),"")} -> Media | W7: 06/07/206 | X7: 20/07/206 | Y7: 21/07/206 | Z7: 04/09/206 | AA7: 17/08/206 | AB7: 30/10/206 | AC7: Considerar 15 días menos de implementación como supuesto de reducción de alcance a un solo proveedor (proveedor prioritario) de maquila. Considerar que Pruebas de maquila son independientes y no van por la ruta crítica | AD7: 46240
A8: HDU-SMART-R4-06 | B8: Smart Vista | C8: Generar archivos seguros de maquila. | D8: TDC | E8: Automatización de Maquila | F8: Generación y resguardo del archivo para el maquilador tras procesar la solicitud. Incluye cifrado PGP/HSM, flujo de 4 pasos (SVBO→OCG→Cargen→PGP→Connect Direct), trazabilidad Orden→Lote→Tarjeta, y alertamiento/reproceso ante error del maquilador. | G8: Flujo técnico: SVBO→OCG→Cargen→PGP→Connect Direct [Comentado en sesión]. Archivo cifrado con PGP del proveedor destino. Trazabilidad completa Orden→Lote→Tarjeta. Alertamiento y reproceso ante error de procesamiento en maquilador. | H8: Smart Vista | I8: Administrador de Maquila / Suministros | J8: Must | K8: Solución e Integración | L8: 2 | M8: Desarrollo + Configuración | N8: Reutilización parcial 30-70% | O8: 3 | P8: 1 | Q8: {=+_xlfn.IFS(O8="","",O8<=1,"Baja",O8<=3,"Media",O8>3,"Alta")} -> Media | R8: {=+_xlfn.IFS(P8="","",P8<=0,"Baja",P8<=2,"Media",P8>2,"Alta")} -> Media | S8: {=+_xlfn.IFS(N8="","",N8="Componentes existentes reutilizables >80%","Baja",N8="No Aplica","Baja",N8="Reutilización parcial 30-70%","Media",N8="Nuevo Desarrollo <20%","Alta")} -> Media | T8: {=+_xlfn.IFS(L8="","",L8=0,"Baja",L8<=2,"Media",L8>=3,"Alta")} -> Media | U8: {=+IFERROR((+_xlfn.IFS(Q8="",0,Q8="Baja",1,Q8="Media",2,Q8="Alta",3)*'Scoring Complejidad'!$C$8+_xlfn.IFS(R8="Baja",1,R8="Media",2,R8="Alta",3)*'Scoring Complejidad'!$C$9+_xlfn.IFS(S8="Baja",1,S8="Media",2,S8="Alta",3)*'Scoring Complejidad'!$C$7+_xlfn.IFS(T8="",1,T8="Baja",1,T8="Media",2,T8="Alta",3)*'Scoring Complejidad'!$C$5+_xlfn.IFS(M8="Caja",1,M8="Configuración",2,M8="Desarrollo",3,M8="Desarrollo + Configuración",3,M8="No Aplica",0)*'Scoring Complejidad'!$C$6),"")} -> 2.25 | V8: {=IFERROR(_xlfn.IFS(U8="","",U8<=1.69,"Baja",U8<=2.29,"Media",U8<=3,"Alta",U8>3,"Error"),"")} -> Media | W8: 06/07/206 | X8: 20/07/206 | Y8: 21/07/206 | Z8: 04/09/206 | AA8: 17/08/206 | AB8: 30/10/206 | AC8: Con tiempos controlados de desarrollo de la HU. Complejidad posterior podría estar en tiempos de llaves Integraciones archivo se baja a on premise y tarea programada que se manda a proveedor a través del canal seguro Considerar 15 días menos de implementación como supuesto de reducción de alcance a un solo proveedor (proveedor prioritario) de maquila. Considerar que Pruebas de maquila son independientes y no van por la ruta crítica | AD8: 46240
A9: HDU-SMART-R4-07 | B9: Smart Vista | C9: Dar seguimiento a estatus de lotes. | D9: TDC | E9: Automatización de Maquila | F9: Consulta del estatus de emisión y entrega de lotes por sucursal (Inventario POS), incluyendo seguimiento de paquetería desde recolección hasta entrega, reportería de existencia y detalle de lotes en proceso. | G9: Seguimiento de paquetería recolección→entrega, confirmación de recepción [DEF RF-01 Escenarios 5/6]. Consulta limitada al periodo máximo. Sin reposición proactiva ante vencimiento: cliente acude a sucursal. | H9: Smart Vista | I9: Área de Suministros / Operaciones | J9: Should | K9: Solución | L9: 0 | M9: Desarrollo + Configuración | N9: Nuevo Desarrollo <20% | O9: 2 | P9: 1 | Q9: {=+_xlfn.IFS(O9="","",O9<=1,"Baja",O9<=3,"Media",O9>3,"Alta")} -> Media | R9: {=+_xlfn.IFS(P9="","",P9<=0,"Baja",P9<=2,"Media",P9>2,"Alta")} -> Media | S9: {=+_xlfn.IFS(N9="","",N9="Componentes existentes reutilizables >80%","Baja",N9="No Aplica","Baja",N9="Reutilización parcial 30-70%","Media",N9="Nuevo Desarrollo <20%","Alta")} -> Alta | T9: {=+_xlfn.IFS(L9="","",L9=0,"Baja",L9<=2,"Media",L9>=3,"Alta")} -> Baja | U9: {=+IFERROR((+_xlfn.IFS(Q9="",0,Q9="Baja",1,Q9="Media",2,Q9="Alta",3)*'Scoring Complejidad'!$C$8+_xlfn.IFS(R9="Baja",1,R9="Media",2,R9="Alta",3)*'Scoring Complejidad'!$C$9+_xlfn.IFS(S9="Baja",1,S9="Media",2,S9="Alta",3)*'Scoring Complejidad'!$C$7+_xlfn.IFS(T9="",1,T9="Baja",1,T9="Media",2,T9="Alta",3)*'Scoring Complejidad'!$C$5+_xlfn.IFS(M9="Caja",1,M9="Configuración",2,M9="Desarrollo",3,M9="Desarrollo + Configuración",3,M9="No Aplica",0)*'Scoring Complejidad'!$C$6),"")} -> 2.15 | V9: {=IFERROR(_xlfn.IFS(U9="","",U9<=1.69,"Baja",U9<=2.29,"Media",U9<=3,"Alta",U9>3,"Error"),"")} -> Media | W9: 06/07/206 | X9: 20/07/206 | Y9: 21/07/206 | Z9: 04/09/206 | AA9: 17/08/206 | AB9: 30/10/206 | AC9: Considerar 15 días menos de implementación como supuesto de reducción de alcance a un solo proveedor (proveedor prioritario) de maquila. Considerar que Pruebas de maquila son independientes y no van por la ruta crítica | AD9: 46240
A10: HDU-SMART-R4-08 | B10: Smart Vista | C10: Controlar recepción y cancelación de lotes. | D10: TDC | E10: Automatización de Maquila | F10: Recepción de lotes en sucursal desde SIWEB con validación de lote correcto, baja de tarjetas dañadas/inexistentes, bloqueo de asignación para créditos vencidos, y validación obligatoria de huella del Gerente para cancelaciones. | G10: Recepción desde SIWEB; rechazo de lote incorrecto o de otra sucursal . Mensaje corregido 'tarjeta no existe' (hoy muestra erróneamente 'ya reportada'). Bloqueo con crédito vencido >1 mes. Huella de Gerente obligatoria para cancelar dañadas. Gap: baja por daño solo si tarjeta asignada (candidato R4.5). | H10: Smart Vista, SIWEB | I10: Gerente de Sucursal / Ejecutivo de Sucursal | J10: Must | K10: Integración | L10: 3 | M10: No Aplica | N10: No Aplica | O10: 0 | P10: 0 | Q10: {=+_xlfn.IFS(O10="","",O10<=1,"Baja",O10<=3,"Media",O10>3,"Alta")} -> Baja | R10: {=+_xlfn.IFS(P10="","",P10<=0,"Baja",P10<=2,"Media",P10>2,"Alta")} -> Baja | S10: {=+_xlfn.IFS(N10="","",N10="Componentes existentes reutilizables >80%","Baja",N10="No Aplica","Baja",N10="Reutilización parcial 30-70%","Media",N10="Nuevo Desarrollo <20%","Alta")} -> Baja | T10: {=+_xlfn.IFS(L10="","",L10=0,"Baja",L10<=2,"Media",L10>=3,"Alta")} -> Alta | U10: {=+IFERROR((+_xlfn.IFS(Q10="",0,Q10="Baja",1,Q10="Media",2,Q10="Alta",3)*'Scoring Complejidad'!$C$8+_xlfn.IFS(R10="Baja",1,R10="Media",2,R10="Alta",3)*'Scoring Complejidad'!$C$9+_xlfn.IFS(S10="Baja",1,S10="Media",2,S10="Alta",3)*'Scoring Complejidad'!$C$7+_xlfn.IFS(T10="",1,T10="Baja",1,T10="Media",2,T10="Alta",3)*'Scoring Complejidad'!$C$5+_xlfn.IFS(M10="Caja",1,M10="Configuración",2,M10="Desarrollo",3,M10="Desarrollo + Configuración",3,M10="No Aplica",0)*'Scoring Complejidad'!$C$6),"")} -> 1.35 | V10: {=IFERROR(_xlfn.IFS(U10="","",U10<=1.69,"Baja",U10<=2.29,"Media",U10<=3,"Alta",U10>3,"Error"),"")} -> Baja | W10: 06/07/206 | X10: 20/07/206 | Y10: 21/07/206 | Z10: 04/09/206 | AA10: 17/08/206 | AB10: 30/10/206 | AC10: Considerar 15 días menos de implementación como supuesto de reducción de alcance a un solo proveedor (proveedor prioritario) de maquila. Considerar que Pruebas de maquila son independientes y no van por la ruta crítica | AD10: 46240
A11: HDU-SMART-R4-09 | B11: Smart Vista | C11: Homologar conceptos de comisiones TDC. | D11: TDC | E11: Homologación omnicanal de comisiones | F11: Definición del catálogo normativo único de comisiones para TDC 4900 (17 comisiones replicando esquema 8500), alineado a BANXICO. Solo cambia la etiqueta visible; caídas y cuentas contables permanecen idénticas. Límites de longitud: 40 caracteres en EDC, 26 en ticket SIWEB. | G11: Catálogo normativo único alineado a BANXICO. 17 comisiones 4900=esquema 8500. Solo cambia etiqueta, NO la contabilidad [RF-03 Acuerdo S3]. Límites: 40 chars EDC / 26 chars ticket. Mapeo nombre-actual→nombre-nuevo con ID de comisión. | H11: Smart Vista, App, SIWEB | I11: Área Normativa / Negocio | J11: Must | K11: Solución | L11: 0 | M11: Desarrollo | N11: Componentes existentes reutilizables >80% | O11: 3 | P11: 0 | Q11: {=+_xlfn.IFS(O11="","",O11<=1,"Baja",O11<=3,"Media",O11>3,"Alta")} -> Media | R11: {=+_xlfn.IFS(P11="","",P11<=0,"Baja",P11<=2,"Media",P11>2,"Alta")} -> Baja | S11: {=+_xlfn.IFS(N11="","",N11="Componentes existentes reutilizables >80%","Baja",N11="No Aplica","Baja",N11="Reutilización parcial 30-70%","Media",N11="Nuevo Desarrollo <20%","Alta")} -> Baja | T11: {=+_xlfn.IFS(L11="","",L11=0,"Baja",L11<=2,"Media",L11>=3,"Alta")} -> Baja | U11: {=+IFERROR((+_xlfn.IFS(Q11="",0,Q11="Baja",1,Q11="Media",2,Q11="Alta",3)*'Scoring Complejidad'!$C$8+_xlfn.IFS(R11="Baja",1,R11="Media",2,R11="Alta",3)*'Scoring Complejidad'!$C$9+_xlfn.IFS(S11="Baja",1,S11="Media",2,S11="Alta",3)*'Scoring Complejidad'!$C$7+_xlfn.IFS(T11="",1,T11="Baja",1,T11="Media",2,T11="Alta",3)*'Scoring Complejidad'!$C$5+_xlfn.IFS(M11="Caja",1,M11="Configuración",2,M11="Desarrollo",3,M11="Desarrollo + Configuración",3,M11="No Aplica",0)*'Scoring Complejidad'!$C$6),"")} -> 1.65 | V11: {=IFERROR(_xlfn.IFS(U11="","",U11<=1.69,"Baja",U11<=2.29,"Media",U11<=3,"Alta",U11>3,"Error"),"")} -> Baja | W11: 46202 | X11: 46234 | Y11: Dependencia DTMs | Z11: Dependencia DTMs | AA11: Dependencia DTMs | AB11: Dependencia DTMs | AC11: Solicitudes de normatividad. Se parte de una base de APIs existentes en los canales SIWEB y App; IVR y CAT no requieren la homologación Pendiente verificación de fechas de Diseño (DTMs) e implementación - equipo APIFICACIÓN (Juan Carlos Valenzuela y Oscar Melo) asignados como responsables 7-Agosto Dependencia para generar DTMs insumos: Catalogo de reglas de negocio, errores, dependencias, diagrama funcional | AD11: 46241
A12: HDU-SMART-R4-10 | B12: Smart Vista | C12: Sincronizar nombres de comisiones en canales. | D12: TDC | E12: Homologación omnicanal de comisiones | F12: Verificación de que los nombres homologados de comisiones se muestran de forma idéntica en todos los canales de consulta (Smart Vista, App, SIWEB, EDC), cumpliendo la regulación BANXICO y los límites de longitud por canal. | G12: Nombres idénticos en SV, App, SIWEB, EDC . Verificación por punto de consulta. Auditoría BANXICO sin inconsistencias. Límites 40 EDC / 26 ticket. Depende de catálogo HDU-SMART-R4-09. | H12: Smart Vista, App, SIWEB, EDC | I12: Área Normativa / Todos los canales | J12: Must | K12: Solución e Integración | L12: 2 | M12: Desarrollo + Configuración | N12: Reutilización parcial 30-70% | O12: 3 | P12: 0 | Q12: {=+_xlfn.IFS(O12="","",O12<=1,"Baja",O12<=3,"Media",O12>3,"Alta")} -> Media | R12: {=+_xlfn.IFS(P12="","",P12<=0,"Baja",P12<=2,"Media",P12>2,"Alta")} -> Baja | S12: {=+_xlfn.IFS(N12="","",N12="Componentes existentes reutilizables >80%","Baja",N12="No Aplica","Baja",N12="Reutilización parcial 30-70%","Media",N12="Nuevo Desarrollo <20%","Alta")} -> Media | T12: {=+_xlfn.IFS(L12="","",L12=0,"Baja",L12<=2,"Media",L12>=3,"Alta")} -> Media | U12: {=+IFERROR((+_xlfn.IFS(Q12="",0,Q12="Baja",1,Q12="Media",2,Q12="Alta",3)*'Scoring Complejidad'!$C$8+_xlfn.IFS(R12="Baja",1,R12="Media",2,R12="Alta",3)*'Scoring Complejidad'!$C$9+_xlfn.IFS(S12="Baja",1,S12="Media",2,S12="Alta",3)*'Scoring Complejidad'!$C$7+_xlfn.IFS(T12="",1,T12="Baja",1,T12="Media",2,T12="Alta",3)*'Scoring Complejidad'!$C$5+_xlfn.IFS(M12="Caja",1,M12="Configuración",2,M12="Desarrollo",3,M12="Desarrollo + Configuración",3,M12="No Aplica",0)*'Scoring Complejidad'!$C$6),"")} -> 2.15 | V12: {=IFERROR(_xlfn.IFS(U12="","",U12<=1.69,"Baja",U12<=2.29,"Media",U12<=3,"Alta",U12>3,"Error"),"")} -> Media | W12: 46202 | X12: 46234 | Y12: Dependencia DTMs | Z12: Dependencia DTMs | AA12: Dependencia DTMs | AB12: Dependencia DTMs | AC12: Solicitudes de normatividad; Una integración por canal App, SIWEB, EDC, Smartvista Pendiente verificación de fechas de DTM- equipo APIFICACIÓN | AD12: 46241
A13: HDU-SMART-R4-11 | B13: Smart Vista | C13: Incorporar reglas del autorizador BPC. | D13: TDC | E13: Reglas del autorizador (88 reglas) | F13: Motor de 88 reglas del autorizador BPC en tiempo real: Módulo 1 (estatus/ISO 8583) y Fraud Management. Incluye rechazo con códigos ISO específicos, validación MIT sin OTID contra Whitelist, y mapeo de rechazos por bloqueo temporal. | G13: 88 reglas BPC divididas entre SV Frontend y Fraud Management [RF-06a Acuerdo S3]. Módulo 1: rechazo con código ISO (BIN desconocido ISO 14, robada ISO 43, extraviada ISO 41). MIT sin OTID: Regla 45 vs Whitelist + umbrales Regla 88. Sin afectación contable hasta batch cierre de día. Alerta 000916 por bloqueo temporal . | H13: Smart Vista (Autorizador BPC) | I13: Administrador de Tarjetas / BPC | J13: Must | K13: Solución | L13: 0 | M13: Desarrollo + Configuración | N13: Nuevo Desarrollo <20% | O13: 1 | P13: 0 | Q13: {=+_xlfn.IFS(O13="","",O13<=1,"Baja",O13<=3,"Media",O13>3,"Alta")} -> Baja | R13: {=+_xlfn.IFS(P13="","",P13<=0,"Baja",P13<=2,"Media",P13>2,"Alta")} -> Baja | S13: {=+_xlfn.IFS(N13="","",N13="Componentes existentes reutilizables >80%","Baja",N13="No Aplica","Baja",N13="Reutilización parcial 30-70%","Media",N13="Nuevo Desarrollo <20%","Alta")} -> Alta | T13: {=+_xlfn.IFS(L13="","",L13=0,"Baja",L13<=2,"Media",L13>=3,"Alta")} -> Baja | U13: {=+IFERROR((+_xlfn.IFS(Q13="",0,Q13="Baja",1,Q13="Media",2,Q13="Alta",3)*'Scoring Complejidad'!$C$8+_xlfn.IFS(R13="Baja",1,R13="Media",2,R13="Alta",3)*'Scoring Complejidad'!$C$9+_xlfn.IFS(S13="Baja",1,S13="Media",2,S13="Alta",3)*'Scoring Complejidad'!$C$7+_xlfn.IFS(T13="",1,T13="Baja",1,T13="Media",2,T13="Alta",3)*'Scoring Complejidad'!$C$5+_xlfn.IFS(M13="Caja",1,M13="Configuración",2,M13="Desarrollo",3,M13="Desarrollo + Configuración",3,M13="No Aplica",0)*'Scoring Complejidad'!$C$6),"")} -> 1.9 | V13: {=IFERROR(_xlfn.IFS(U13="","",U13<=1.69,"Baja",U13<=2.29,"Media",U13<=3,"Alta",U13>3,"Error"),"")} -> Media | W13: 46179 | X13: 46311 | Y13: No Aplica | Z13: No Aplica | AA13: 46223 | AB13: 46311 | AC13: Análisis y pruebas de comfort de las 88 reglas se trabaja en ciclos; Depende de ventana de pruebas con Eglobal , quien ejecuta esas reglas de confort y los resultados se comparten con negocio. Punto pendiente: seguimiento proceso de pruebas de Eglobal ; Dependencia con BPC para desarrollo y configuración de nuevas reglas, con fechas mostradas en las columnas de Implementación No aplica diseño porque BPC es el que hace el desarrollo y configuración, no SmartVista. | AD13: 46237
A14: HDU-SMART-R4-12 | B14: Smart Vista | C14: Parametrizar límite de saldo a favor. | D14: TDC | E14: Control de saldo a favor | F14: Interfaz de administración para configurar el parámetro único de límite de saldo a favor por TDC (monto o % de la línea), con switch on/off para TDC clásica 4900 y propagación consistente a todos los canales. | G14: Parámetro único: monto o % sobre línea de crédito. Switch apagar/prender para TDC clásica (4900); extensible a legado [RF-25]. Aplica a productos 6001 y 4900. Propagación automática a todos los canales. Solo rol autorizado puede modificar [RN-HU-021]. | H14: Smart Vista (todos los canales) | I14: Área de Negocio / Administrador | J14: Must | K14: Solución | L14: 0 | M14: Desarrollo + Configuración | N14: Reutilización parcial 30-70% | O14: 3 | P14: 0 | Q14: {=+_xlfn.IFS(O14="","",O14<=1,"Baja",O14<=3,"Media",O14>3,"Alta")} -> Media | R14: {=+_xlfn.IFS(P14="","",P14<=0,"Baja",P14<=2,"Media",P14>2,"Alta")} -> Baja | S14: {=+_xlfn.IFS(N14="","",N14="Componentes existentes reutilizables >80%","Baja",N14="No Aplica","Baja",N14="Reutilización parcial 30-70%","Media",N14="Nuevo Desarrollo <20%","Alta")} -> Media | T14: {=+_xlfn.IFS(L14="","",L14=0,"Baja",L14<=2,"Media",L14>=3,"Alta")} -> Baja | U14: {=+IFERROR((+_xlfn.IFS(Q14="",0,Q14="Baja",1,Q14="Media",2,Q14="Alta",3)*'Scoring Complejidad'!$C$8+_xlfn.IFS(R14="Baja",1,R14="Media",2,R14="Alta",3)*'Scoring Complejidad'!$C$9+_xlfn.IFS(S14="Baja",1,S14="Media",2,S14="Alta",3)*'Scoring Complejidad'!$C$7+_xlfn.IFS(T14="",1,T14="Baja",1,T14="Media",2,T14="Alta",3)*'Scoring Complejidad'!$C$5+_xlfn.IFS(M14="Caja",1,M14="Configuración",2,M14="Desarrollo",3,M14="Desarrollo + Configuración",3,M14="No Aplica",0)*'Scoring Complejidad'!$C$6),"")} -> 1.85 | V14: {=IFERROR(_xlfn.IFS(U14="","",U14<=1.69,"Baja",U14<=2.29,"Media",U14<=3,"Alta",U14>3,"Error"),"")} -> Media | W14: 46181 | X14: 46234 | Y14: No Aplica | Z14: No Aplica | AA14: 46237 | AB14: 46265 | AC14: No aplica diseño | AD14: 46237
A15: HDU-SMART-R4-13 | B15: Smart Vista | C15: Validar límite por línea de crédito. | D15: TDC | E15: Control de saldo a favor | F15: Validación transaccional del límite de saldo a favor según la línea: tope fijo $15,000 para líneas <$25,000; 20% para líneas ≥$25,000. Aplica acumulado mensual. Rechaza pago/depósito que excede el tope. | G15: Límite dinámico: $15,000 fijo (líneas ≤$24,999) o 20% de línea (líneas ≥$25,000) [RF-05 Acuerdo S3, RN-OP-APP-21]. Acumulado o en una sola exhibición. Rechazo si inicio de periodo ya con límite alcanzado. Conectado al HUB de Pagos. Reportería desde SV [RN-HU-022]. | H15: Smart Vista (todos los canales de pago) | I15: Cliente Final / Sistema | J15: Must | K15: Solución | L15: 0 | M15: Desarrollo + Configuración | N15: Nuevo Desarrollo <20% | O15: 2 | P15: 0 | Q15: {=+_xlfn.IFS(O15="","",O15<=1,"Baja",O15<=3,"Media",O15>3,"Alta")} -> Media | R15: {=+_xlfn.IFS(P15="","",P15<=0,"Baja",P15<=2,"Media",P15>2,"Alta")} -> Baja | S15: {=+_xlfn.IFS(N15="","",N15="Componentes existentes reutilizables >80%","Baja",N15="No Aplica","Baja",N15="Reutilización parcial 30-70%","Media",N15="Nuevo Desarrollo <20%","Alta")} -> Alta | T15: {=+_xlfn.IFS(L15="","",L15=0,"Baja",L15<=2,"Media",L15>=3,"Alta")} -> Baja | U15: {=+IFERROR((+_xlfn.IFS(Q15="",0,Q15="Baja",1,Q15="Media",2,Q15="Alta",3)*'Scoring Complejidad'!$C$8+_xlfn.IFS(R15="Baja",1,R15="Media",2,R15="Alta",3)*'Scoring Complejidad'!$C$9+_xlfn.IFS(S15="Baja",1,S15="Media",2,S15="Alta",3)*'Scoring Complejidad'!$C$7+_xlfn.IFS(T15="",1,T15="Baja",1,T15="Media",2,T15="Alta",3)*'Scoring Complejidad'!$C$5+_xlfn.IFS(M15="Caja",1,M15="Configuración",2,M15="Desarrollo",3,M15="Desarrollo + Configuración",3,M15="No Aplica",0)*'Scoring Complejidad'!$C$6),"")} -> 2.05 | V15: {=IFERROR(_xlfn.IFS(U15="","",U15<=1.69,"Baja",U15<=2.29,"Media",U15<=3,"Alta",U15>3,"Error"),"")} -> Media | W15: 46181 | X15: 46234 | Y15: No Aplica | Z15: No Aplica | AA15: 46237 | AB15: 46265 | AC15: No aplica diseño | AD15: 46237
A16: HDU-SMART-R4-14 | B16: Smart Vista | C16: Excluir abonos bancarios del límite. | D16: TDC | E16: Control de saldo a favor | F16: Los abonos originados por el banco (aclaraciones, correcciones, reversos, abonos CAT) no están sujetos al límite de saldo a favor y se procesan libremente sin sumar al tope del cliente. | G16: Abonos del banco (aclaración/corrección/reverso/CAT) exentos del límite [RN-OP-S3-01]. No suman al saldo a favor para efectos del tope. NOTA: Confirmado por negocio que se desestima para R4 y pasa al siguiente release. | H16: Smart Vista | I16: Área de Negocio / Sistema | J16: Wont | K16: Solución | L16: 0 | M16: Desarrollo + Configuración | N16: Nuevo Desarrollo <20% | O16: 0 | P16: 0 | Q16: {=+_xlfn.IFS(O16="","",O16<=1,"Baja",O16<=3,"Media",O16>3,"Alta")} -> Baja | R16: {=+_xlfn.IFS(P16="","",P16<=0,"Baja",P16<=2,"Media",P16>2,"Alta")} -> Baja | S16: {=+_xlfn.IFS(N16="","",N16="Componentes existentes reutilizables >80%","Baja",N16="No Aplica","Baja",N16="Reutilización parcial 30-70%","Media",N16="Nuevo Desarrollo <20%","Alta")} -> Alta | T16: {=+_xlfn.IFS(L16="","",L16=0,"Baja",L16<=2,"Media",L16>=3,"Alta")} -> Baja | U16: {=+IFERROR((+_xlfn.IFS(Q16="",0,Q16="Baja",1,Q16="Media",2,Q16="Alta",3)*'Scoring Complejidad'!$C$8+_xlfn.IFS(R16="Baja",1,R16="Media",2,R16="Alta",3)*'Scoring Complejidad'!$C$9+_xlfn.IFS(S16="Baja",1,S16="Media",2,S16="Alta",3)*'Scoring Complejidad'!$C$7+_xlfn.IFS(T16="",1,T16="Baja",1,T16="Media",2,T16="Alta",3)*'Scoring Complejidad'!$C$5+_xlfn.IFS(M16="Caja",1,M16="Configuración",2,M16="Desarrollo",3,M16="Desarrollo + Configuración",3,M16="No Aplica",0)*'Scoring Complejidad'!$C$6),"")} -> 1.9 | V16: {=IFERROR(_xlfn.IFS(U16="","",U16<=1.69,"Baja",U16<=2.29,"Media",U16<=3,"Alta",U16>3,"Error"),"")} -> Media | Y16: No Aplica | Z16: No Aplica | AC16: Negocio ya ha enviado correo confirmando que puede no considerarse para release 4. No aplica diseño | AD16: 46237
A17: HDU-SMART-R4-15 | B17: Smart Vista | C17: Mostrar mensaje por límite alcanzado. | D17: TDC | E17: Control de saldo a favor | F17: Mensaje homologado exacto al rechazar pagos/depósitos por límite de saldo a favor: 'No se puede completar la transacción.' Aplica en App, SIWEB, ATM, BPI y SPEI/corresponsales. | G17: Mensaje exacto homologado en todos los canales [RN-HU-022/023/024/065-068]. Frontend deshabilita 'Otra cantidad' para evitar Defecto 748001 [RN-OP-SF-02]. SPEI/corresponsales: rechaza, regresa fondos al emisor sin notificar al cliente [RN-HU-069/070]. Sin conteo de intentos en R4 [RN-OP-S3-02]. | H17: App, SIWEB,SPEI | I17: Cliente Final / Canales | J17: Must | K17: Solución e Integración | L17: 0 | M17: Desarrollo | N17: Reutilización parcial 30-70% | O17: 1 | P17: 0 | Q17: {=+_xlfn.IFS(O17="","",O17<=1,"Baja",O17<=3,"Media",O17>3,"Alta")} -> Baja | R17: {=+_xlfn.IFS(P17="","",P17<=0,"Baja",P17<=2,"Media",P17>2,"Alta")} -> Baja | S17: {=+_xlfn.IFS(N17="","",N17="Componentes existentes reutilizables >80%","Baja",N17="No Aplica","Baja",N17="Reutilización parcial 30-70%","Media",N17="Nuevo Desarrollo <20%","Alta")} -> Media | T17: {=+_xlfn.IFS(L17="","",L17=0,"Baja",L17<=2,"Media",L17>=3,"Alta")} -> Baja | U17: {=+IFERROR((+_xlfn.IFS(Q17="",0,Q17="Baja",1,Q17="Media",2,Q17="Alta",3)*'Scoring Complejidad'!$C$8+_xlfn.IFS(R17="Baja",1,R17="Media",2,R17="Alta",3)*'Scoring Complejidad'!$C$9+_xlfn.IFS(S17="Baja",1,S17="Media",2,S17="Alta",3)*'Scoring Complejidad'!$C$7+_xlfn.IFS(T17="",1,T17="Baja",1,T17="Media",2,T17="Alta",3)*'Scoring Complejidad'!$C$5+_xlfn.IFS(M17="Caja",1,M17="Configuración",2,M17="Desarrollo",3,M17="Desarrollo + Configuración",3,M17="No Aplica",0)*'Scoring Complejidad'!$C$6),"")} -> 1.7 | V17: {=IFERROR(_xlfn.IFS(U17="","",U17<=1.69,"Baja",U17<=2.29,"Media",U17<=3,"Alta",U17>3,"Error"),"")} -> Media | W17: 46181 | X17: 46234 | Y17: No Aplica | Z17: No Aplica | AA17: 46237 | AB17: 46265 | AC17: No aplica diseño. 3 integraciones consideradas en el alcance de pruebas de regresión pero no como nuevo desarrollo porque ya vienen de releases anteriores- | AD17: 46237
A18: HDU-SMARTVISTA-R4-16 | B18: Smart Vista | C18: Configurar campañas de compras diferidas. | D18: TDC | E18: Diferemiento de compra a MCI | F18: Configuración de campañas de Compras Diferidas (MCI) en Smart Vista: atributo permanente por toda la vida de la cuenta, campañas temporales con tasa promocional dentro de vigencia y portafolio elegible. Split: MSI libera en R4 con pruebas integrales; MCI solo backend en R4, consumo App en R4.5. | G18: Atributo permanente independiente de segmentación inicial [DEF RF-4 MCI]. Campaña temporal: tasa solo dentro de vigencia/portafolio [RN-HU-048]. Fuera del portafolio: no aplica la tasa. Split confirmado S4/S5: MSI solo pruebas en R4, MCI backend R4/App R4.5 [RN-OP-S4-02/03]. | H18: Smart Vista | I18: Administrador de Producto | J18: Should | K18: Solución | L18: 0 | M18: Desarrollo + Configuración | N18: Nuevo Desarrollo <20% | O18: 3 | P18: 0 | Q18: {=+_xlfn.IFS(O18="","",O18<=1,"Baja",O18<=3,"Media",O18>3,"Alta")} -> Media | R18: {=+_xlfn.IFS(P18="","",P18<=0,"Baja",P18<=2,"Media",P18>2,"Alta")} -> Baja | S18: {=+_xlfn.IFS(N18="","",N18="Componentes existentes reutilizables >80%","Baja",N18="No Aplica","Baja",N18="Reutilización parcial 30-70%","Media",N18="Nuevo Desarrollo <20%","Alta")} -> Alta | T18: {=+_xlfn.IFS(L18="","",L18=0,"Baja",L18<=2,"Media",L18>=3,"Alta")} -> Baja | U18: {=+IFERROR((+_xlfn.IFS(Q18="",0,Q18="Baja",1,Q18="Media",2,Q18="Alta",3)*'Scoring Complejidad'!$C$8+_xlfn.IFS(R18="Baja",1,R18="Media",2,R18="Alta",3)*'Scoring Complejidad'!$C$9+_xlfn.IFS(S18="Baja",1,S18="Media",2,S18="Alta",3)*'Scoring Complejidad'!$C$7+_xlfn.IFS(T18="",1,T18="Baja",1,T18="Media",2,T18="Alta",3)*'Scoring Complejidad'!$C$5+_xlfn.IFS(M18="Caja",1,M18="Configuración",2,M18="Desarrollo",3,M18="Desarrollo + Configuración",3,M18="No Aplica",0)*'Scoring Complejidad'!$C$6),"")} -> 2.05 | V18: {=IFERROR(_xlfn.IFS(U18="","",U18<=1.69,"Baja",U18<=2.29,"Media",U18<=3,"Alta",U18>3,"Error"),"")} -> Media | W18: 46216 | X18: 46262 | Y18: No Aplica | Z18: No Aplica | AA18: 46251 | AB18: 46353 | AC18: No impacta desde la perspectiva operativa pero es muy relevante desde el punto de vista comercial Análisis extenso en fechas por impacto en contabilidad y revisiones financieras. No aplica diseño porque directamente lo implementa BPC con los requerimientos. Fecha 27 de noviembre es la más pesimista y se podría acortar Las trabaja SmartVista no requieren pruebas integrales porque hasta el siguiente R se libera conexión con canales | AD18: 46241
A19: HDU-SMART-R4-17 | B19: Smart Vista | C19: Calcular oferta de compra diferida. | D19: TDC | E19: Diferemiento de compra a MCI | F19: Cálculo de la oferta de diferimiento para compras elegibles (>$1,000, no parcializadas, del periodo actual o último): plazos 3, 6, 9, 12, 18 y 24 meses con cuota mensual, capital e intereses. Validación de línea disponible neta al confirmar. | G19: Elegibilidad: compra >$1,000, no parcializada, del periodo o último [RN-HU-049-053]. Plazos 3/6/9/12/18/24 meses con cuota mensual e intereses [DEF RF-4]. Validación de línea neta al swipe/token [RN-OP-S4-01]. Sin sobregiro salvo capitalización de intereses [RN-OP-S4-11]. Desglose capital+intereses antes de confirmar. Umbral resuelto en $1,000. | H19: Smart Vista (motor de cálculo) | I19: Cliente Final TDC | J19: Should | K19: Solución | L19: 0 | M19: Desarrollo + Configuración | N19: Reutilización parcial 30-70% | O19: 3 | P19: 0 | Q19: {=+_xlfn.IFS(O19="","",O19<=1,"Baja",O19<=3,"Media",O19>3,"Alta")} -> Media | R19: {=+_xlfn.IFS(P19="","",P19<=0,"Baja",P19<=2,"Media",P19>2,"Alta")} -> Baja | S19: {=+_xlfn.IFS(N19="","",N19="Componentes existentes reutilizables >80%","Baja",N19="No Aplica","Baja",N19="Reutilización parcial 30-70%","Media",N19="Nuevo Desarrollo <20%","Alta")} -> Media | T19: {=+_xlfn.IFS(L19="","",L19=0,"Baja",L19<=2,"Media",L19>=3,"Alta")} -> Baja | U19: {=+IFERROR((+_xlfn.IFS(Q19="",0,Q19="Baja",1,Q19="Media",2,Q19="Alta",3)*'Scoring Complejidad'!$C$8+_xlfn.IFS(R19="Baja",1,R19="Media",2,R19="Alta",3)*'Scoring Complejidad'!$C$9+_xlfn.IFS(S19="Baja",1,S19="Media",2,S19="Alta",3)*'Scoring Complejidad'!$C$7+_xlfn.IFS(T19="",1,T19="Baja",1,T19="Media",2,T19="Alta",3)*'Scoring Complejidad'!$C$5+_xlfn.IFS(M19="Caja",1,M19="Configuración",2,M19="Desarrollo",3,M19="Desarrollo + Configuración",3,M19="No Aplica",0)*'Scoring Complejidad'!$C$6),"")} -> 1.85 | V19: {=IFERROR(_xlfn.IFS(U19="","",U19<=1.69,"Baja",U19<=2.29,"Media",U19<=3,"Alta",U19>3,"Error"),"")} -> Media | W19: 46209 | X19: 46248 | Y19: No Aplica | Z19: No Aplica | AA19: 46251 | AB19: 46353 | AC19: No impacta desde la perspectiva operativa pero es muy relevante desde el punto de vista comercial Análisis extenso en fechas por impacto en contabilidad y revisiones financieras. No aplica diseño porque directamente lo implementa BPC con los requerimientos. Fecha 27 de noviembre es la más pesimista y se podría acortar Las trabaja SmartVista no requieren pruebas integrales porque hasta el siguiente R se libera conexión con canales | AD19: 46241
A20: HDU-SMART-R4-18 | B20: Smart Vista | C20: Aplicar plan MCI/MSI a compra. | D20: TDC | E20: Diferemiento de compra a MCI | F20: Aplicación del plan de compras diferidas en línea (inmediata) con impacto de saldo, cuenta y estado. Por cada movimiento diferido se crea un Pago Fijo independiente; abono inverso reclasifica al grupo contable 13; intereses cobrados solo en fecha de corte. | G20: Aplicación en línea, no esperar cierre contable [DEF RF-4]. Producto Pago Fijo independiente por movimiento; saldo retenido = suma capital+intereses. Abono inverso reclasifica a grupo 13, no recircula a 2402/Eglobal [RN-OP-S4-04/05]. Intereses solo en corte [RN-OP-S4-06]. TRNT exacta pendiente guía contable formal. | H20: Smart Vista | I20: Cliente Final TDC | J20: Should | K20: Solución | L20: 0 | M20: Desarrollo + Configuración | N20: Reutilización parcial 30-70% | O20: 3 | P20: 0 | Q20: {=+_xlfn.IFS(O20="","",O20<=1,"Baja",O20<=3,"Media",O20>3,"Alta")} -> Media | R20: {=+_xlfn.IFS(P20="","",P20<=0,"Baja",P20<=2,"Media",P20>2,"Alta")} -> Baja | S20: {=+_xlfn.IFS(N20="","",N20="Componentes existentes reutilizables >80%","Baja",N20="No Aplica","Baja",N20="Reutilización parcial 30-70%","Media",N20="Nuevo Desarrollo <20%","Alta")} -> Media | T20: {=+_xlfn.IFS(L20="","",L20=0,"Baja",L20<=2,"Media",L20>=3,"Alta")} -> Baja | U20: {=+IFERROR((+_xlfn.IFS(Q20="",0,Q20="Baja",1,Q20="Media",2,Q20="Alta",3)*'Scoring Complejidad'!$C$8+_xlfn.IFS(R20="Baja",1,R20="Media",2,R20="Alta",3)*'Scoring Complejidad'!$C$9+_xlfn.IFS(S20="Baja",1,S20="Media",2,S20="Alta",3)*'Scoring Complejidad'!$C$7+_xlfn.IFS(T20="",1,T20="Baja",1,T20="Media",2,T20="Alta",3)*'Scoring Complejidad'!$C$5+_xlfn.IFS(M20="Caja",1,M20="Configuración",2,M20="Desarrollo",3,M20="Desarrollo + Configuración",3,M20="No Aplica",0)*'Scoring Complejidad'!$C$6),"")} -> 1.85 | V20: {=IFERROR(_xlfn.IFS(U20="","",U20<=1.69,"Baja",U20<=2.29,"Media",U20<=3,"Alta",U20>3,"Error"),"")} -> Media | W20: 46209 | X20: 46248 | Y20: No Aplica | Z20: No Aplica | AA20: 46251 | AB20: 46353 | AC20: No impacta desde la perspectiva operativa pero es muy relevante desde el punto de vista comercial Análisis extenso en fechas por impacto en contabilidad y revisiones financieras. No aplica diseño porque directamente lo implementa BPC con los requerimientos. Fecha 27 de noviembre es la más pesimista y se podría acortar Las trabaja SmartVista no requieren pruebas integrales porque hasta el siguiente R se libera conexión con canales | AD20: 46241
A21: HDU-SMART-R4-19 | B21: Smart Vista | C21: Aplicar pagos anticipados a pagos fijos. | D21: TDC | E21: Pagos anticipados y Liquidaciones de compras diferidas | F21: Pago anticipado parcial aplicado directo al capital de una compra diferida, reduciendo el plazo (no la mensualidad). Selección de compra específica. No exime la siguiente mensualidad. Registro via transacción SIWEB 623. | G21: Pago a capital reduce plazo, no monto de mensualidad [RN-OP-S4-07]. Sin límite de pagos parciales por corte. No exime siguiente mensualidad. Transacción SIWEB 623 'PAGO CGO A CTA DE CREDISOLUCIONES'. Pago directo a productos MSI/MCI (6900/8900). | H21: Smart Vista, SIWEB, App | I21: Cliente Final TDC / Ejecutivo de Sucursal | J21: Should | K21: Solución e Integración | L21: 2 | M21: Desarrollo + Configuración | N21: Nuevo Desarrollo <20% | O21: 3 | P21: 0 | Q21: {=+_xlfn.IFS(O21="","",O21<=1,"Baja",O21<=3,"Media",O21>3,"Alta")} -> Media | R21: {=+_xlfn.IFS(P21="","",P21<=0,"Baja",P21<=2,"Media",P21>2,"Alta")} -> Baja | S21: {=+_xlfn.IFS(N21="","",N21="Componentes existentes reutilizables >80%","Baja",N21="No Aplica","Baja",N21="Reutilización parcial 30-70%","Media",N21="Nuevo Desarrollo <20%","Alta")} -> Alta | T21: {=+_xlfn.IFS(L21="","",L21=0,"Baja",L21<=2,"Media",L21>=3,"Alta")} -> Media | U21: {=+IFERROR((+_xlfn.IFS(Q21="",0,Q21="Baja",1,Q21="Media",2,Q21="Alta",3)*'Scoring Complejidad'!$C$8+_xlfn.IFS(R21="Baja",1,R21="Media",2,R21="Alta",3)*'Scoring Complejidad'!$C$9+_xlfn.IFS(S21="Baja",1,S21="Media",2,S21="Alta",3)*'Scoring Complejidad'!$C$7+_xlfn.IFS(T21="",1,T21="Baja",1,T21="Media",2,T21="Alta",3)*'Scoring Complejidad'!$C$5+_xlfn.IFS(M21="Caja",1,M21="Configuración",2,M21="Desarrollo",3,M21="Desarrollo + Configuración",3,M21="No Aplica",0)*'Scoring Complejidad'!$C$6),"")} -> 2.35 | V21: {=IFERROR(_xlfn.IFS(U21="","",U21<=1.69,"Baja",U21<=2.29,"Media",U21<=3,"Alta",U21>3,"Error"),"")} -> Alta | W21: 46209 | X21: 46255 | Y21: No Aplica | Z21: No Aplica | AA21: 46244 | AB21: 46283 | AC21: Dependencia de APIs con SIWEB para pruebas integrales - DTMs son dependencia de SIWEB, Smart Vista solo disponibiliza No aplica diseño porque directamente lo implementa BPC con los requerimientos. | AD21: 46241
A22: HDU-SMART-R4-20 | B22: Smart Vista | C22: Liquidar totalmente compras diferidas. | D22: TDC | E22: Pagos anticipados y Liquidaciones de compras diferidas | F22: Liquidación total de compra diferida: capital pendiente + intereses devengados sin cobrar intereses futuros. Al liquidar, el pago fijo se cancela automáticamente. App solo permite liquidación total (no parcial). | G22: Monto = capital pendiente + intereses devengados, sin intereses futuros [RN-HU-058, RN-OP-S4-06]. Cancelación automática del pago fijo al liquidar [DEF RF-6]. Transacción SIWEB 623. App SOLO permite liquidación total, sucursal permite parcial y total [RN-HU-059]. Recálculo de intereses MCI para no cobrar no devengados. | H22: Smart Vista, App, SIWEB | I22: Cliente Final TDC | J22: Should | K22: Solución e Integración | L22: 2 | M22: Desarrollo + Configuración | N22: Nuevo Desarrollo <20% | O22: 2 | P22: 0 | Q22: {=+_xlfn.IFS(O22="","",O22<=1,"Baja",O22<=3,"Media",O22>3,"Alta")} -> Media | R22: {=+_xlfn.IFS(P22="","",P22<=0,"Baja",P22<=2,"Media",P22>2,"Alta")} -> Baja | S22: {=+_xlfn.IFS(N22="","",N22="Componentes existentes reutilizables >80%","Baja",N22="No Aplica","Baja",N22="Reutilización parcial 30-70%","Media",N22="Nuevo Desarrollo <20%","Alta")} -> Alta | T22: {=+_xlfn.IFS(L22="","",L22=0,"Baja",L22<=2,"Media",L22>=3,"Alta")} -> Media | U22: {=+IFERROR((+_xlfn.IFS(Q22="",0,Q22="Baja",1,Q22="Media",2,Q22="Alta",3)*'Scoring Complejidad'!$C$8+_xlfn.IFS(R22="Baja",1,R22="Media",2,R22="Alta",3)*'Scoring Complejidad'!$C$9+_xlfn.IFS(S22="Baja",1,S22="Media",2,S22="Alta",3)*'Scoring Complejidad'!$C$7+_xlfn.IFS(T22="",1,T22="Baja",1,T22="Media",2,T22="Alta",3)*'Scoring Complejidad'!$C$5+_xlfn.IFS(M22="Caja",1,M22="Configuración",2,M22="Desarrollo",3,M22="Desarrollo + Configuración",3,M22="No Aplica",0)*'Scoring Complejidad'!$C$6),"")} -> 2.35 | V22: {=IFERROR(_xlfn.IFS(U22="","",U22<=1.69,"Baja",U22<=2.29,"Media",U22<=3,"Alta",U22>3,"Error"),"")} -> Alta | W22: 46209 | X22: 46262 | Y22: No Aplica | Z22: No Aplica | AA22: 46244 | AB22: 46283 | AC22: Reutilización de APIs de R4-19 , validar con los DTMs que se generen para entender reutilización. Dependencia de APIs con SIWEB para pruebas integrales - DTMs son dependencia de SIWEB, Smart Vista solo disponibiliza No aplica diseño porque directamente lo implementa BPC con los requerimientos. | AD22: 46241
A23: HDU-SMART-R4-21 | B23: Smart Vista | C23: Cancelar compras diferidas en línea. | D23: TDC | E23: Pagos anticipados y Liquidaciones de compras diferidas | F23: Cancelación en línea del pago fijo desde el mismo día de apertura. Cancelación centralizada por impago (2 meses consecutivos) o aclaración de cargo no reconocido sin validación de identidad. Cargo en una exhibición al revolvente. Solo aplica a digital 4900. | G23: Cancelación posible desde el día de apertura [DEF RF-7]. Centralizada por 2 impagos consecutivos o aclaración, sin validación de identidad [RF-18/DEF RF-7]. Cargo 'Cargo por cancelación de CrediSoluciones'. Solo tarjetas digitales 4900 [RN-OP-S10-05]. NOTA: Estrategia E2E difiere RF-18 a R5 — validar con negocio. | H23: Smart Vista, App, SIWEB | I23: Cliente Final / Sistema (centralizado) | J23: Should | K23: Solución e Integración | L23: 2 | M23: Desarrollo | N23: Nuevo Desarrollo <20% | O23: 3 | P23: 0 | Q23: {=+_xlfn.IFS(O23="","",O23<=1,"Baja",O23<=3,"Media",O23>3,"Alta")} -> Media | R23: {=+_xlfn.IFS(P23="","",P23<=0,"Baja",P23<=2,"Media",P23>2,"Alta")} -> Baja | S23: {=+_xlfn.IFS(N23="","",N23="Componentes existentes reutilizables >80%","Baja",N23="No Aplica","Baja",N23="Reutilización parcial 30-70%","Media",N23="Nuevo Desarrollo <20%","Alta")} -> Alta | T23: {=+_xlfn.IFS(L23="","",L23=0,"Baja",L23<=2,"Media",L23>=3,"Alta")} -> Media | U23: {=+IFERROR((+_xlfn.IFS(Q23="",0,Q23="Baja",1,Q23="Media",2,Q23="Alta",3)*'Scoring Complejidad'!$C$8+_xlfn.IFS(R23="Baja",1,R23="Media",2,R23="Alta",3)*'Scoring Complejidad'!$C$9+_xlfn.IFS(S23="Baja",1,S23="Media",2,S23="Alta",3)*'Scoring Complejidad'!$C$7+_xlfn.IFS(T23="",1,T23="Baja",1,T23="Media",2,T23="Alta",3)*'Scoring Complejidad'!$C$5+_xlfn.IFS(M23="Caja",1,M23="Configuración",2,M23="Desarrollo",3,M23="Desarrollo + Configuración",3,M23="No Aplica",0)*'Scoring Complejidad'!$C$6),"")} -> 2.35 | V23: {=IFERROR(_xlfn.IFS(U23="","",U23<=1.69,"Baja",U23<=2.29,"Media",U23<=3,"Alta",U23>3,"Error"),"")} -> Alta | W23: 46209 | X23: 46262 | Y23: No Aplica | Z23: No Aplica | AA23: 46244 | AB23: 46283 | AC23: Reutilización de APIs de R4-19 , validar con los DTMs que se generen para entender reutilización. Dependencia de APIs con SIWEB para pruebas integrales - DTMs son dependencia de SIWEB, Smart Vista solo disponibiliza No aplica diseño porque directamente lo implementa BPC con los requerimientos. | AD23: 46241
A24: HDU-CAT-R4-01 | B24: CAT | C24: Alta producto 4900 en menú IVR. | D24: TDC | E24: Autoservicio TDC en IVR | F24: Alta del producto 4900 en el menú IVR del 800 BanCoppel con opciones 1-6. IVR acepta cuenta contrato a 18 dígitos (vs 12 del legado). Canal IVR parametrizado desde cero en SmartVista. Item 4 'Enviar CLABE por SMS' deshabilitado para 4900. | G24: Opciones 1-6 en menú IVR [DEF RF-13]. Cuenta contrato a 18 dígitos (vs 12 legado) [RN-OP-CAT-06]. Canal IVR parametrizado desde cero en SV [Comentado en sesión]. Item 4 CLABE por SMS deshabilitado para 4900 [RN-OP-CAT-07]. Validación ANI: coincidencia habilita consulta automática [RN-OP-CAT-01]. | H24: CAT (IVR) | I24: Cliente Final BanCoppel | J24: Must | K24: Solución e Integración | L24: 2 | M24: Desarrollo + Configuración | N24: Reutilización parcial 30-70% | O24: 3 | P24: 3 | Q24: {=+_xlfn.IFS(O24="","",O24<=1,"Baja",O24<=3,"Media",O24>3,"Alta")} -> Media | R24: {=+_xlfn.IFS(P24="","",P24<=0,"Baja",P24<=2,"Media",P24>2,"Alta")} -> Alta | S24: {=+_xlfn.IFS(N24="","",N24="Componentes existentes reutilizables >80%","Baja",N24="No Aplica","Baja",N24="Reutilización parcial 30-70%","Media",N24="Nuevo Desarrollo <20%","Alta")} -> Media | T24: {=+_xlfn.IFS(L24="","",L24=0,"Baja",L24<=2,"Media",L24>=3,"Alta")} -> Media | U24: {=+IFERROR((+_xlfn.IFS(Q24="",0,Q24="Baja",1,Q24="Media",2,Q24="Alta",3)*'Scoring Complejidad'!$C$8+_xlfn.IFS(R24="Baja",1,R24="Media",2,R24="Alta",3)*'Scoring Complejidad'!$C$9+_xlfn.IFS(S24="Baja",1,S24="Media",2,S24="Alta",3)*'Scoring Complejidad'!$C$7+_xlfn.IFS(T24="",1,T24="Baja",1,T24="Media",2,T24="Alta",3)*'Scoring Complejidad'!$C$5+_xlfn.IFS(M24="Caja",1,M24="Configuración",2,M24="Desarrollo",3,M24="Desarrollo + Configuración",3,M24="No Aplica",0)*'Scoring Complejidad'!$C$6),"")} -> 2.35 | V24: {=IFERROR(_xlfn.IFS(U24="","",U24<=1.69,"Baja",U24<=2.29,"Media",U24<=3,"Alta",U24>3,"Error"),"")} -> Alta | W24: 46167 | X24: 46234 | Y24: Dependencia DTMs | Z24: Dependencia DTMs | AA24: Dependencia DTMs | AB24: Dependencia DTMs | AC24: Fechas de implementación dependientes de proceso de contratación del proveedor nuevo (15 de Septiembre); Onboarding y habilitación de proveedor aproximado de 4 semanas. Pendiente revisar proveedor Fecha de fin de análisis pendiente de validar por Ramses Santos; Fechas de diseño e implementación dependientes de cierre de análisis y contratación de proveedor Consulta de clientes y cuentas - integraciones Considerar en etapas de diseño - certificación de arquitectura Fechas DTMS/ DTCs Appwhere - Alfredo | AD24: 46237
A25: HDU-CAT-R4-02 | B25: CAT | C25: Rutar opciones IVR de atención TDC. | D25: TDC | E25: Autoservicio TDC en IVR | F25: Enrutamiento de opciones IVR hacia el ejecutivo o servicio correspondiente. Sin coincidencia ANI: transferencia directa al ejecutivo con batería de preguntas. Consulta de saldos/movimientos por cuenta contrato de 18 dígitos para incluir histórico completo. | G25: Sin coincidencia ANI: transfiere al ejecutivo, bloquea consultas automáticas [RN-OP-CAT-02]. Ejecutivo aplica batería de preguntas antes de consulta [RN-OP-CAT-03]. Consulta por 18 dígitos incluye comisiones/cargos de tarjetas antiguas [RN-OP-CAT-11]. Knockouts RN-HU-035..040. | H25: CAT (IVR) | I25: Cliente Final BanCoppel | J25: Must | K25: Solución e Integración | L25: 1 | M25: Desarrollo | N25: Componentes existentes reutilizables >80% | O25: 3 | P25: 3 | Q25: {=+_xlfn.IFS(O25="","",O25<=1,"Baja",O25<=3,"Media",O25>3,"Alta")} -> Media | R25: {=+_xlfn.IFS(P25="","",P25<=0,"Baja",P25<=2,"Media",P25>2,"Alta")} -> Alta | S25: {=+_xlfn.IFS(N25="","",N25="Componentes existentes reutilizables >80%","Baja",N25="No Aplica","Baja",N25="Reutilización parcial 30-70%","Media",N25="Nuevo Desarrollo <20%","Alta")} -> Baja | T25: {=+_xlfn.IFS(L25="","",L25=0,"Baja",L25<=2,"Media",L25>=3,"Alta")} -> Media | U25: {=+IFERROR((+_xlfn.IFS(Q25="",0,Q25="Baja",1,Q25="Media",2,Q25="Alta",3)*'Scoring Complejidad'!$C$8+_xlfn.IFS(R25="Baja",1,R25="Media",2,R25="Alta",3)*'Scoring Complejidad'!$C$9+_xlfn.IFS(S25="Baja",1,S25="Media",2,S25="Alta",3)*'Scoring Complejidad'!$C$7+_xlfn.IFS(T25="",1,T25="Baja",1,T25="Media",2,T25="Alta",3)*'Scoring Complejidad'!$C$5+_xlfn.IFS(M25="Caja",1,M25="Configuración",2,M25="Desarrollo",3,M25="Desarrollo + Configuración",3,M25="No Aplica",0)*'Scoring Complejidad'!$C$6),"")} -> 2.15 | V25: {=IFERROR(_xlfn.IFS(U25="","",U25<=1.69,"Baja",U25<=2.29,"Media",U25<=3,"Alta",U25>3,"Error"),"")} -> Media | W25: 46167 | X25: 46234 | Y25: Dependencia DTMs | Z25: Dependencia DTMs | AA25: Dependencia DTMs | AB25: Dependencia DTMs | AC25: Fechas DTMS/ DTCs Appwhere - Alfredo | AD25: 46237
A26: HDU-CAT-R4-03 | B26: CAT | C26: Identificar cliente Apolo en CAT. | D26: TDC | E26: Identificación y autenticación en ICCAT | F26: Identificación del cliente originado en APOLO/4900 en ICCAT mediante batería de preguntas aleatorias Factor 1. Enmascaramiento de número de tarjeta (solo últimos 4 dígitos), muestra tipo de producto y estatus. Obligatorio mostrar 18 dígitos del crédito. | G26: Batería de preguntas Factor 1 aleatoria para clientes APOLO [DEF RF-14]. Clientes no-APOLO: autenticación estándar [RF-14 Escenario 3]. Enmascaramiento de número (últimos 4 dígitos), tipo y estatus [RN-OP-S10-04]. 18 dígitos del crédito obligatorios. Actualización de contacto en sucursal sincroniza en Informix sin desfase batch [RF-14]. | H26: CAT (ICCAT) | I26: Ejecutivo CAT | J26: Must | K26: Solución | L26: 0 | M26: Configuración | N26: Componentes existentes reutilizables >80% | O26: 3 | P26: 2 | Q26: {=+_xlfn.IFS(O26="","",O26<=1,"Baja",O26<=3,"Media",O26>3,"Alta")} -> Media | R26: {=+_xlfn.IFS(P26="","",P26<=0,"Baja",P26<=2,"Media",P26>2,"Alta")} -> Media | S26: {=+_xlfn.IFS(N26="","",N26="Componentes existentes reutilizables >80%","Baja",N26="No Aplica","Baja",N26="Reutilización parcial 30-70%","Media",N26="Nuevo Desarrollo <20%","Alta")} -> Baja | T26: {=+_xlfn.IFS(L26="","",L26=0,"Baja",L26<=2,"Media",L26>=3,"Alta")} -> Baja | U26: {=+IFERROR((+_xlfn.IFS(Q26="",0,Q26="Baja",1,Q26="Media",2,Q26="Alta",3)*'Scoring Complejidad'!$C$8+_xlfn.IFS(R26="Baja",1,R26="Media",2,R26="Alta",3)*'Scoring Complejidad'!$C$9+_xlfn.IFS(S26="Baja",1,S26="Media",2,S26="Alta",3)*'Scoring Complejidad'!$C$7+_xlfn.IFS(T26="",1,T26="Baja",1,T26="Media",2,T26="Alta",3)*'Scoring Complejidad'!$C$5+_xlfn.IFS(M26="Caja",1,M26="Configuración",2,M26="Desarrollo",3,M26="Desarrollo + Configuración",3,M26="No Aplica",0)*'Scoring Complejidad'!$C$6),"")} -> 1.5 | V26: {=IFERROR(_xlfn.IFS(U26="","",U26<=1.69,"Baja",U26<=2.29,"Media",U26<=3,"Alta",U26>3,"Error"),"")} -> Baja | W26: 46167 | X26: 46234 | Y26: Dependencia DTMs | Z26: Dependencia DTMs | AA26: Dependencia DTMs | AB26: Dependencia DTMs | AC26: Fechas DTMS/ DTCs Appwhere - Alfredo | AD26: 46237
A27: HDU-CAT-R4-04 | B27: CAT | C27: Mantener autenticación en misma llamada. | D27: TDC | E27: Identificación y autenticación en ICCAT | F27: Reutilización de autenticación durante la misma llamada activa con el mismo ejecutivo. Nueva autenticación requerida al finalizar la llamada o al transferir a otro ejecutivo. Tercer intento fallido del día bloquea la atención por el resto del día. | G27: Autenticación válida solo durante la misma llamada con el mismo ejecutivo. Nueva autenticación: al iniciar nueva llamada [RN-HU-042] o al transferir a otro ejecutivo [RN-HU-043]. 3er intento fallido del día bloquea y envía a sucursal [RN-HU-044]. Respuestas enmascaradas. Cada intento se audita en SV. | H27: CAT (ICCAT) | I27: Ejecutivo CAT | J27: Should | K27: Solución | L27: 0 | M27: Configuración | N27: Componentes existentes reutilizables >80% | O27: 3 | P27: 0 | Q27: {=+_xlfn.IFS(O27="","",O27<=1,"Baja",O27<=3,"Media",O27>3,"Alta")} -> Media | R27: {=+_xlfn.IFS(P27="","",P27<=0,"Baja",P27<=2,"Media",P27>2,"Alta")} -> Baja | S27: {=+_xlfn.IFS(N27="","",N27="Componentes existentes reutilizables >80%","Baja",N27="No Aplica","Baja",N27="Reutilización parcial 30-70%","Media",N27="Nuevo Desarrollo <20%","Alta")} -> Baja | T27: {=+_xlfn.IFS(L27="","",L27=0,"Baja",L27<=2,"Media",L27>=3,"Alta")} -> Baja | U27: {=+IFERROR((+_xlfn.IFS(Q27="",0,Q27="Baja",1,Q27="Media",2,Q27="Alta",3)*'Scoring Complejidad'!$C$8+_xlfn.IFS(R27="Baja",1,R27="Media",2,R27="Alta",3)*'Scoring Complejidad'!$C$9+_xlfn.IFS(S27="Baja",1,S27="Media",2,S27="Alta",3)*'Scoring Complejidad'!$C$7+_xlfn.IFS(T27="",1,T27="Baja",1,T27="Media",2,T27="Alta",3)*'Scoring Complejidad'!$C$5+_xlfn.IFS(M27="Caja",1,M27="Configuración",2,M27="Desarrollo",3,M27="Desarrollo + Configuración",3,M27="No Aplica",0)*'Scoring Complejidad'!$C$6),"")} -> 1.4 | V27: {=IFERROR(_xlfn.IFS(U27="","",U27<=1.69,"Baja",U27<=2.29,"Media",U27<=3,"Alta",U27>3,"Error"),"")} -> Baja | W27: 46167 | X27: 46234 | Y27: Dependencia DTMs | Z27: Dependencia DTMs | AA27: Dependencia DTMs | AB27: Dependencia DTMs | AC27: Se esta validando con negocio- el tema normativo relacionado con la reutilización Fechas DTMS/ DTCs Appwhere - Alfredo | AD27: 46237
A28: HDU-CAT-R4-05 | B28: CAT | C28: Bloquear tarjeta por CAT. | D28: TDC | E28: Gestión de tarjetas desde CAT | F28: Bloqueo temporal (estatus 20) de tarjeta física o digital desde CAT a petición del cliente autenticado. Centralizado en tronco común igual que App y Sucursal. Para virtuales: solo bloqueo temporal (no cancelación por robo/extravío). Notificación por correo MAI_BDT_IC y SMS. | G28: Bloqueo estatus 20, centralizado [DEF RF-16/RN-OP-CAT-04]. Solo si cliente autenticado [RN-HU-045]. Para tarjetas virtuales: solo bloqueo temporal (20), NO cancelación 06/07 [RN-OP-CAT-08]. Estatus final 43 no modificable [RN-OP-CAT-09]. Notificación automática correo MAI_BDT_IC + SMS SMS_BDT_IC [RN-OP-CAT-10]. | H28: CAT, SmartVista | I28: Ejecutivo CAT | J28: Must | K28: Solución e Integración | L28: 1 | M28: Desarrollo + Configuración | N28: Nuevo Desarrollo <20% | O28: 3 | P28: 0 | Q28: {=+_xlfn.IFS(O28="","",O28<=1,"Baja",O28<=3,"Media",O28>3,"Alta")} -> Media | R28: {=+_xlfn.IFS(P28="","",P28<=0,"Baja",P28<=2,"Media",P28>2,"Alta")} -> Baja | S28: {=+_xlfn.IFS(N28="","",N28="Componentes existentes reutilizables >80%","Baja",N28="No Aplica","Baja",N28="Reutilización parcial 30-70%","Media",N28="Nuevo Desarrollo <20%","Alta")} -> Alta | T28: {=+_xlfn.IFS(L28="","",L28=0,"Baja",L28<=2,"Media",L28>=3,"Alta")} -> Media | U28: {=+IFERROR((+_xlfn.IFS(Q28="",0,Q28="Baja",1,Q28="Media",2,Q28="Alta",3)*'Scoring Complejidad'!$C$8+_xlfn.IFS(R28="Baja",1,R28="Media",2,R28="Alta",3)*'Scoring Complejidad'!$C$9+_xlfn.IFS(S28="Baja",1,S28="Media",2,S28="Alta",3)*'Scoring Complejidad'!$C$7+_xlfn.IFS(T28="",1,T28="Baja",1,T28="Media",2,T28="Alta",3)*'Scoring Complejidad'!$C$5+_xlfn.IFS(M28="Caja",1,M28="Configuración",2,M28="Desarrollo",3,M28="Desarrollo + Configuración",3,M28="No Aplica",0)*'Scoring Complejidad'!$C$6),"")} -> 2.35 | V28: {=IFERROR(_xlfn.IFS(U28="","",U28<=1.69,"Baja",U28<=2.29,"Media",U28<=3,"Alta",U28>3,"Error"),"")} -> Alta | W28: 46167 | X28: 46234 | Y28: Dependencia DTMs | Z28: Dependencia DTMs | AA28: Dependencia DTMs | AB28: Dependencia DTMs | AC28: Fechas DTMS/ DTCs Appwhere - Alfredo | AD28: 46237
A29: HDU-CAT-R4-06 | B29: CAT | C29: Desbloquear tarjeta por CAT. | D29: TDC | E29: Gestión de tarjetas desde CAT | F29: Desbloqueo temporal (estatus 20→00) desde CAT con validación obligatoria de código SMS OTP de 4 dígitos. Si SMS no llega: ejecutivo reenvía o cliente cancela con 1111. Código inválido/expirado rechaza el desbloqueo. Aplica para física y digital. | G29: Desbloqueo solo bloqueos reversibles (20→00). SMS OTP 4 dígitos obligatorio — revierte acuerdo S9 [RN-OP-S10-03]. Código inválido/expirado rechaza [RN-HU-046]. Reenvío disponible. 1111 cancela el trámite. Centralizado igual que App/Sucursal. Aplica a física y digital [RN-OP-CAT-04]. | H29: CAT, SmartVista | I29: Ejecutivo CAT | J29: Must | K29: Solución e Integración | L29: 1 | M29: Desarrollo + Configuración | N29: Nuevo Desarrollo <20% | O29: 3 | P29: 2 | Q29: {=+_xlfn.IFS(O29="","",O29<=1,"Baja",O29<=3,"Media",O29>3,"Alta")} -> Media | R29: {=+_xlfn.IFS(P29="","",P29<=0,"Baja",P29<=2,"Media",P29>2,"Alta")} -> Media | S29: {=+_xlfn.IFS(N29="","",N29="Componentes existentes reutilizables >80%","Baja",N29="No Aplica","Baja",N29="Reutilización parcial 30-70%","Media",N29="Nuevo Desarrollo <20%","Alta")} -> Alta | T29: {=+_xlfn.IFS(L29="","",L29=0,"Baja",L29<=2,"Media",L29>=3,"Alta")} -> Media | U29: {=+IFERROR((+_xlfn.IFS(Q29="",0,Q29="Baja",1,Q29="Media",2,Q29="Alta",3)*'Scoring Complejidad'!$C$8+_xlfn.IFS(R29="Baja",1,R29="Media",2,R29="Alta",3)*'Scoring Complejidad'!$C$9+_xlfn.IFS(S29="Baja",1,S29="Media",2,S29="Alta",3)*'Scoring Complejidad'!$C$7+_xlfn.IFS(T29="",1,T29="Baja",1,T29="Media",2,T29="Alta",3)*'Scoring Complejidad'!$C$5+_xlfn.IFS(M29="Caja",1,M29="Configuración",2,M29="Desarrollo",3,M29="Desarrollo + Configuración",3,M29="No Aplica",0)*'Scoring Complejidad'!$C$6),"")} -> 2.45 | V29: {=IFERROR(_xlfn.IFS(U29="","",U29<=1.69,"Baja",U29<=2.29,"Media",U29<=3,"Alta",U29>3,"Error"),"")} -> Alta | W29: 46167 | X29: 46234 | Y29: Dependencia DTMs | Z29: Dependencia DTMs | AA29: Dependencia DTMs | AB29: Dependencia DTMs | AC29: Fechas DTMS/ DTCs Appwhere - Alfredo | AD29: 46237
A30: HDU-CAT-R4-07 | B30: CAT | C30: Actualizar históricos CAT por cambio de estatus. | D30: TDC | E30: Gestión de tarjetas desde CAT | F30: Consulta del estatus actualizado de tarjetas en ICCAT tras bloqueos, desbloqueos, cancelaciones y reposiciones. Sin mostrar datos parciales en cambio fallido. Consulta histórica por cuenta clave de 18 dígitos con número enmascarado. | G30: Estatus actualizado de cada tarjeta tras cambios [DEF RF-16]. Cambio fallido: no mostrar datos parciales [RN-HU-012/013]. Cliente no autenticado: no mostrar información [RN-HU-047]. Consulta histórica por cuenta clave 18 dígitos. Número enmascarado últimos 4 [RN-OP-S10-02/04]. Motivos de cancelación granulares: Extraviada, Deterioro, Robada, Dañada. | H30: CAT (ICCAT) | I30: Ejecutivo CAT | J30: Should | K30: Solución | L30: 0 | M30: Desarrollo | N30: Componentes existentes reutilizables >80% | O30: 3 | P30: 2 | Q30: {=+_xlfn.IFS(O30="","",O30<=1,"Baja",O30<=3,"Media",O30>3,"Alta")} -> Media | R30: {=+_xlfn.IFS(P30="","",P30<=0,"Baja",P30<=2,"Media",P30>2,"Alta")} -> Media | S30: {=+_xlfn.IFS(N30="","",N30="Componentes existentes reutilizables >80%","Baja",N30="No Aplica","Baja",N30="Reutilización parcial 30-70%","Media",N30="Nuevo Desarrollo <20%","Alta")} -> Baja | T30: {=+_xlfn.IFS(L30="","",L30=0,"Baja",L30<=2,"Media",L30>=3,"Alta")} -> Baja | U30: {=+IFERROR((+_xlfn.IFS(Q30="",0,Q30="Baja",1,Q30="Media",2,Q30="Alta",3)*'Scoring Complejidad'!$C$8+_xlfn.IFS(R30="Baja",1,R30="Media",2,R30="Alta",3)*'Scoring Complejidad'!$C$9+_xlfn.IFS(S30="Baja",1,S30="Media",2,S30="Alta",3)*'Scoring Complejidad'!$C$7+_xlfn.IFS(T30="",1,T30="Baja",1,T30="Media",2,T30="Alta",3)*'Scoring Complejidad'!$C$5+_xlfn.IFS(M30="Caja",1,M30="Configuración",2,M30="Desarrollo",3,M30="Desarrollo + Configuración",3,M30="No Aplica",0)*'Scoring Complejidad'!$C$6),"")} -> 1.75 | V30: {=IFERROR(_xlfn.IFS(U30="","",U30<=1.69,"Baja",U30<=2.29,"Media",U30<=3,"Alta",U30>3,"Error"),"")} -> Media | W30: 46167 | X30: 46234 | Y30: Dependencia DTMs | Z30: Dependencia DTMs | AA30: Dependencia DTMs | AB30: Dependencia DTMs | AC30: Ramsés clasificó esta HU como SHOULD dado que no es bloqueante para la operación principal. Es candidata a diferirse al R4.1 si hay presión de tiempos en la implementación. | AD30: 46237
A31: HDU-CAT-R4-08 | B31: CAT | C31: Consultar saldos y movimientos del producto 4900 por IVR. | D31: TDC | E31: Autoservicio TDC en IVR | F31: Consulta de saldos y movimientos del producto 4900 vía IVR tras autenticación. Usa cuenta/contrato de 18 dígitos. Fecha de referencia: si apertura anterior a corte → fecha de corte; si posterior → fecha de apertura. Transferencia al ejecutivo ante indisponibilidad. | G31: Reconocimiento del producto 4900 en IVR. Autenticación previa obligatoria. Consulta por cuenta/contrato 18 dígitos. Fecha de consulta: anterior al corte → fecha de corte; posterior → fecha de apertura. Servicio no disponible → transferencia al ejecutivo. Datos sensibles protegidos. | H31: CAT (IVR), SmartVista | I31: Cliente Final BanCoppel | J31: Must | K31: Solución e Integración | L31: 1 | M31: Desarrollo | N31: Nuevo Desarrollo <20% | O31: 5 | P31: 3 | Q31: {=+_xlfn.IFS(O31="","",O31<=1,"Baja",O31<=3,"Media",O31>3,"Alta")} -> Alta | R31: {=+_xlfn.IFS(P31="","",P31<=0,"Baja",P31<=2,"Media",P31>2,"Alta")} -> Alta | S31: {=+_xlfn.IFS(N31="","",N31="Componentes existentes reutilizables >80%","Baja",N31="No Aplica","Baja",N31="Reutilización parcial 30-70%","Media",N31="Nuevo Desarrollo <20%","Alta")} -> Alta | T31: {=+_xlfn.IFS(L31="","",L31=0,"Baja",L31<=2,"Media",L31>=3,"Alta")} -> Media | U31: {=+IFERROR((+_xlfn.IFS(Q31="",0,Q31="Baja",1,Q31="Media",2,Q31="Alta",3)*'Scoring Complejidad'!$C$8+_xlfn.IFS(R31="Baja",1,R31="Media",2,R31="Alta",3)*'Scoring Complejidad'!$C$9+_xlfn.IFS(S31="Baja",1,S31="Media",2,S31="Alta",3)*'Scoring Complejidad'!$C$7+_xlfn.IFS(T31="",1,T31="Baja",1,T31="Media",2,T31="Alta",3)*'Scoring Complejidad'!$C$5+_xlfn.IFS(M31="Caja",1,M31="Configuración",2,M31="Desarrollo",3,M31="Desarrollo + Configuración",3,M31="No Aplica",0)*'Scoring Complejidad'!$C$6),"")} -> 2.7 | V31: {=IFERROR(_xlfn.IFS(U31="","",U31<=1.69,"Baja",U31<=2.29,"Media",U31<=3,"Alta",U31>3,"Error"),"")} -> Alta | W31: 46167 | X31: 46234 | Y31: Dependencia DTMs | Z31: Dependencia DTMs | AA31: Dependencia DTMs | AB31: Dependencia DTMs | AC31: Fechas DTMS/ DTCs Appwhere - Alfredo | AD31: 46237
A32: HDU-CAT-R4-09 | B32: CAT | C32: Controlar datos inválidos e intentos fallidos en el IVR. | D32: TDC | E32: Autoservicio TDC en IVR | F32: Validación de formato y consistencia de datos en IVR. Registro de cada intento fallido. Bloqueo del autoservicio al alcanzar el umbral (3 intentos). Conservación de evidencia de auditoría. Enrutamiento al ejecutivo al alcanzar el límite. | G32: Validación de formato de datos (tarjeta, CLABE, teléfono). Registro de intento fallido por cliente y periodo. Máx 3 intentos → bloquea autoservicio y enruta según política. Auditoría conserva fecha, canal y resultado. Mensajes de error específicos por tipo de error. | H32: CAT (IVR) | I32: Cliente Final BanCoppel | J32: Must | K32: Solución | L32: 0 | M32: Configuración | N32: Componentes existentes reutilizables >80% | O32: 3 | P32: 0 | Q32: {=+_xlfn.IFS(O32="","",O32<=1,"Baja",O32<=3,"Media",O32>3,"Alta")} -> Media | R32: {=+_xlfn.IFS(P32="","",P32<=0,"Baja",P32<=2,"Media",P32>2,"Alta")} -> Baja | S32: {=+_xlfn.IFS(N32="","",N32="Componentes existentes reutilizables >80%","Baja",N32="No Aplica","Baja",N32="Reutilización parcial 30-70%","Media",N32="Nuevo Desarrollo <20%","Alta")} -> Baja | T32: {=+_xlfn.IFS(L32="","",L32=0,"Baja",L32<=2,"Media",L32>=3,"Alta")} -> Baja | U32: {=+IFERROR((+_xlfn.IFS(Q32="",0,Q32="Baja",1,Q32="Media",2,Q32="Alta",3)*'Scoring Complejidad'!$C$8+_xlfn.IFS(R32="Baja",1,R32="Media",2,R32="Alta",3)*'Scoring Complejidad'!$C$9+_xlfn.IFS(S32="Baja",1,S32="Media",2,S32="Alta",3)*'Scoring Complejidad'!$C$7+_xlfn.IFS(T32="",1,T32="Baja",1,T32="Media",2,T32="Alta",3)*'Scoring Complejidad'!$C$5+_xlfn.IFS(M32="Caja",1,M32="Configuración",2,M32="Desarrollo",3,M32="Desarrollo + Configuración",3,M32="No Aplica",0)*'Scoring Complejidad'!$C$6),"")} -> 1.4 | V32: {=IFERROR(_xlfn.IFS(U32="","",U32<=1.69,"Baja",U32<=2.29,"Media",U32<=3,"Alta",U32>3,"Error"),"")} -> Baja | W32: 46167 | X32: 46234 | Y32: Dependencia DTMs | Z32: Dependencia DTMs | AA32: Dependencia DTMs | AB32: Dependencia DTMs | AC32: Fechas DTMS/ DTCs Appwhere - Alfredo | AD32: 46237
A33: HDU-CAT-R4-10 | B33: CAT | C33: Gestionar intentos fallidos de autenticación en ICCAT. | D33: TDC | E33: Identificación y autenticación en ICCAT | F33: Conteo de intentos fallidos de autenticación a nivel cliente en ICCAT durante el periodo diario. Bloqueo al alcanzar el umbral (3 intentos), invitando a acudir a sucursal. Reutilización del contador entre llamadas del mismo periodo. Inicio de nuevo periodo sin borrar histórico. | G33: Conteo de intentos fallidos nivel cliente, periodo diario. 3er intento fallido del día → bloqueo del flujo + invitación a sucursal. Preguntas cambian en cada reintento sin repetirse. Reutiliza contador entre llamadas del mismo periodo. Nuevo periodo respeta parametrización sin borrar histórico. | H33: CAT (ICCAT) | I33: Ejecutivo CAT | J33: Should | K33: Solución | L33: 0 | M33: Configuración | N33: Componentes existentes reutilizables >80% | O33: 3 | P33: 1 | Q33: {=+_xlfn.IFS(O33="","",O33<=1,"Baja",O33<=3,"Media",O33>3,"Alta")} -> Media | R33: {=+_xlfn.IFS(P33="","",P33<=0,"Baja",P33<=2,"Media",P33>2,"Alta")} -> Media | S33: {=+_xlfn.IFS(N33="","",N33="Componentes existentes reutilizables >80%","Baja",N33="No Aplica","Baja",N33="Reutilización parcial 30-70%","Media",N33="Nuevo Desarrollo <20%","Alta")} -> Baja | T33: {=+_xlfn.IFS(L33="","",L33=0,"Baja",L33<=2,"Media",L33>=3,"Alta")} -> Baja | U33: {=+IFERROR((+_xlfn.IFS(Q33="",0,Q33="Baja",1,Q33="Media",2,Q33="Alta",3)*'Scoring Complejidad'!$C$8+_xlfn.IFS(R33="Baja",1,R33="Media",2,R33="Alta",3)*'Scoring Complejidad'!$C$9+_xlfn.IFS(S33="Baja",1,S33="Media",2,S33="Alta",3)*'Scoring Complejidad'!$C$7+_xlfn.IFS(T33="",1,T33="Baja",1,T33="Media",2,T33="Alta",3)*'Scoring Complejidad'!$C$5+_xlfn.IFS(M33="Caja",1,M33="Configuración",2,M33="Desarrollo",3,M33="Desarrollo + Configuración",3,M33="No Aplica",0)*'Scoring Complejidad'!$C$6),"")} -> 1.5 | V33: {=IFERROR(_xlfn.IFS(U33="","",U33<=1.69,"Baja",U33<=2.29,"Media",U33<=3,"Alta",U33>3,"Error"),"")} -> Baja | W33: 46167 | X33: 46234 | Y33: Dependencia DTMs | Z33: Dependencia DTMs | AA33: Dependencia DTMs | AB33: Dependencia DTMs | AC33: Fechas DTMS/ DTCs Appwhere - Alfredo | AD33: 46237
A34: HDU-CAT-R4-11 | B34: CAT | C34: Consultar en CAT los productos y estatus de tarjetas del cliente. | D34: TDC | E34: Gestión de tarjetas desde CAT | F34: Consulta de productos TDC del cliente en CAT incluyendo el producto 4900, mostrando tarjeta física y digital como instrumentos independientes con estatus homologado, tipo de tarjeta y número enmascarado (últimos 4 dígitos). Sin datos parciales ante fallo de servicio. | G34: Muestra todos los TDC del cliente incluyendo 4900. Física y digital como instrumentos independientes con su propio estatus. Estatus homologado, tipo y últimos 4 dígitos. Refleja cambios confirmados por SV (bloqueo, desbloqueo, reposición, cancelación). Sin datos parciales ante fallo del servicio de consulta. | H34: CAT (ICCAT), SmartVista | I34: Ejecutivo CAT | J34: Must | K34: Solución e Integración | L34: 1 | M34: Desarrollo + Configuración | N34: Reutilización parcial 30-70% | O34: 3 | P34: 0 | Q34: {=+_xlfn.IFS(O34="","",O34<=1,"Baja",O34<=3,"Media",O34>3,"Alta")} -> Media | R34: {=+_xlfn.IFS(P34="","",P34<=0,"Baja",P34<=2,"Media",P34>2,"Alta")} -> Baja | S34: {=+_xlfn.IFS(N34="","",N34="Componentes existentes reutilizables >80%","Baja",N34="No Aplica","Baja",N34="Reutilización parcial 30-70%","Media",N34="Nuevo Desarrollo <20%","Alta")} -> Media | T34: {=+_xlfn.IFS(L34="","",L34=0,"Baja",L34<=2,"Media",L34>=3,"Alta")} -> Media | U34: {=+IFERROR((+_xlfn.IFS(Q34="",0,Q34="Baja",1,Q34="Media",2,Q34="Alta",3)*'Scoring Complejidad'!$C$8+_xlfn.IFS(R34="Baja",1,R34="Media",2,R34="Alta",3)*'Scoring Complejidad'!$C$9+_xlfn.IFS(S34="Baja",1,S34="Media",2,S34="Alta",3)*'Scoring Complejidad'!$C$7+_xlfn.IFS(T34="",1,T34="Baja",1,T34="Media",2,T34="Alta",3)*'Scoring Complejidad'!$C$5+_xlfn.IFS(M34="Caja",1,M34="Configuración",2,M34="Desarrollo",3,M34="Desarrollo + Configuración",3,M34="No Aplica",0)*'Scoring Complejidad'!$C$6),"")} -> 2.15 | V34: {=IFERROR(_xlfn.IFS(U34="","",U34<=1.69,"Baja",U34<=2.29,"Media",U34<=3,"Alta",U34>3,"Error"),"")} -> Media | W34: 46167 | X34: 46234 | Y34: Dependencia DTMs | Z34: Dependencia DTMs | AA34: Dependencia DTMs | AB34: Dependencia DTMs | AC34: Fechas DTMS/ DTCs Appwhere - Alfredo | AD34: 46237
A35: HDU-CAT-R4-12 | B35: CAT | C35: Reportar robo, extravío, daño o vencimiento y cancelar el plástico desde CAT. | D35: TDC | E35: Gestión de tarjetas desde CAT | F35: Registro del motivo de reporte (robo, extravío, daño, vencimiento) y cancelación del plástico afectado. Solo cancela el plástico seleccionado sin modificar el otro instrumento. Registro de folio, fecha, canal, ejecutivo y estatus resultante. Refleja cambio en SV, CAT, App y SIWEB. | G35: Selección del instrumento y motivo: robo (07), extravío (06), daño (27), vencimiento. Solo plástico seleccionado se cancela. Folio, fecha, canal, ejecutivo y estatus resultante registrados. Cambio reflejado en SV+CAT+App+SIWEB tras confirmación. Informar al ejecutivo si transición no es válida o falla. Sin cancelación parcial. | H35: CAT (ICCAT), SmartVista, App, SIWEB | I35: Ejecutivo CAT | J35: Must | K35: Solución e Integración | L35: 1 | M35: Desarrollo + Configuración | N35: Reutilización parcial 30-70% | O35: 3 | P35: 2 | Q35: {=+_xlfn.IFS(O35="","",O35<=1,"Baja",O35<=3,"Media",O35>3,"Alta")} -> Media | R35: {=+_xlfn.IFS(P35="","",P35<=0,"Baja",P35<=2,"Media",P35>2,"Alta")} -> Media | S35: {=+_xlfn.IFS(N35="","",N35="Componentes existentes reutilizables >80%","Baja",N35="No Aplica","Baja",N35="Reutilización parcial 30-70%","Media",N35="Nuevo Desarrollo <20%","Alta")} -> Media | T35: {=+_xlfn.IFS(L35="","",L35=0,"Baja",L35<=2,"Media",L35>=3,"Alta")} -> Media | U35: {=+IFERROR((+_xlfn.IFS(Q35="",0,Q35="Baja",1,Q35="Media",2,Q35="Alta",3)*'Scoring Complejidad'!$C$8+_xlfn.IFS(R35="Baja",1,R35="Media",2,R35="Alta",3)*'Scoring Complejidad'!$C$9+_xlfn.IFS(S35="Baja",1,S35="Media",2,S35="Alta",3)*'Scoring Complejidad'!$C$7+_xlfn.IFS(T35="",1,T35="Baja",1,T35="Media",2,T35="Alta",3)*'Scoring Complejidad'!$C$5+_xlfn.IFS(M35="Caja",1,M35="Configuración",2,M35="Desarrollo",3,M35="Desarrollo + Configuración",3,M35="No Aplica",0)*'Scoring Complejidad'!$C$6),"")} -> 2.25 | V35: {=IFERROR(_xlfn.IFS(U35="","",U35<=1.69,"Baja",U35<=2.29,"Media",U35<=3,"Alta",U35>3,"Error"),"")} -> Media | W35: 46167 | X35: 46234 | Y35: Dependencia DTMs | Z35: Dependencia DTMs | AA35: Dependencia DTMs | AB35: Dependencia DTMs | AC35: Considerar desarrollo E2E para que SmartVista envíe la notificación al resto de los canales | AD35: 46237
A36: HDU-SIWEB-R4-01 | B36: SIWEB | C36: Adelantar pago parcial en SIWEB. | D36: TDC | E36: Operación de compras diferidas en sucursal | F36: Adelanto de pago parcial anticipado a compras diferidas desde ventanilla, directo a capital reduciendo el plazo. No exime la siguiente mensualidad. Transacción SIWEB 623. Bloqueo estricto si cliente tiene pagos vencidos (agingPeriod>0). | G36: Aplica a capital, reduce plazo [RN-OP-S4-07]. No exime siguiente mensualidad [DEF RF-6]. Transacción SIWEB 623 'PAGO CGO A CTA DE CREDISOLUCIONES'. Pago directo a productos MSI/MCI (6900/8900). Bloqueo si agingPeriod>0 [RN-OP-S10-01]. En sucursal aplica parcial Y total (a diferencia de App, solo total). | H36: SIWEB (Sucursal) | I36: Ejecutivo de Sucursal / Cajero | J36: Should | K36: Solución e Integración | M36: Desarrollo + Configuración | N36: Nuevo Desarrollo <20% | O36: 3 | P36: 0 | Q36: {=+_xlfn.IFS(O36="","",O36<=1,"Baja",O36<=3,"Media",O36>3,"Alta")} -> Media | R36: {=+_xlfn.IFS(P36="","",P36<=0,"Baja",P36<=2,"Media",P36>2,"Alta")} -> Baja | S36: {=+_xlfn.IFS(N36="","",N36="Componentes existentes reutilizables >80%","Baja",N36="No Aplica","Baja",N36="Reutilización parcial 30-70%","Media",N36="Nuevo Desarrollo <20%","Alta")} -> Alta | T36: {=+_xlfn.IFS(L36="","",L36=0,"Baja",L36<=2,"Media",L36>=3,"Alta")} | U36: {=+IFERROR((+_xlfn.IFS(Q36="",0,Q36="Baja",1,Q36="Media",2,Q36="Alta",3)*'Scoring Complejidad'!$C$8+_xlfn.IFS(R36="Baja",1,R36="Media",2,R36="Alta",3)*'Scoring Complejidad'!$C$9+_xlfn.IFS(S36="Baja",1,S36="Media",2,S36="Alta",3)*'Scoring Complejidad'!$C$7+_xlfn.IFS(T36="",1,T36="Baja",1,T36="Media",2,T36="Alta",3)*'Scoring Complejidad'!$C$5+_xlfn.IFS(M36="Caja",1,M36="Configuración",2,M36="Desarrollo",3,M36="Desarrollo + Configuración",3,M36="No Aplica",0)*'Scoring Complejidad'!$C$6),"")} -> 2.05 | V36: {=IFERROR(_xlfn.IFS(U36="","",U36<=1.69,"Baja",U36<=2.29,"Media",U36<=3,"Alta",U36>3,"Error"),"")} -> Media | W36: 46174 | X36: 46223 | Y36: Dependencia DTMs | Z36: Dependencia DTMs | AA36: Dependencia DTMs | AB36: Dependencia DTMs | AC36: Integraciones por revisar en siguiente sesión con equipo de SMARTVISTA y APIFICACIÓN - Daniela Viridiana Ramirez Perez (Coppel), Armando Garcia y DTMs Dependencia en fechas de diseño- por confirmar si Appwhere estará elaborando DTMs Dependencia en fechas de implementación de DTMs Prompt existe para legado pero no para SMARTVISTA- lo que se tiene que hacer son las APIs para el consumo de SMARTVISTA 10 semanas de implementación de la solución a partir de la entrega de DTMs y APIs | AD36: 05/082026
A37: HDU-SIWEB-R4-02 | B37: SIWEB | C37: Liquidar compra diferida en SIWEB. | D37: TDC | E37: Operación de compras diferidas en sucursal | F37: Liquidación total de compra diferida desde ventanilla: capital pendiente + intereses devengados sin cobrar futuros. Pago fijo se cancela automáticamente. En sucursal aplica parcial y total (diferencia vs App). Transacción SIWEB 623. | G37: Monto = capital pendiente + intereses devengados, sin futuros [RN-HU-060/RN-OP-S4-06]. Cancelación automática del pago fijo. Transacción SIWEB 623. En sucursal aplica parcial y total [RN-HU-061]. Recálculo de intereses MCI para no cobrar no devengados. | H37: SIWEB (Sucursal) | I37: Ejecutivo de Sucursal | J37: Should | K37: Solución e Integración | M37: Desarrollo + Configuración | N37: Nuevo Desarrollo <20% | O37: 3 | P37: 0 | Q37: {=+_xlfn.IFS(O37="","",O37<=1,"Baja",O37<=3,"Media",O37>3,"Alta")} -> Media | R37: {=+_xlfn.IFS(P37="","",P37<=0,"Baja",P37<=2,"Media",P37>2,"Alta")} -> Baja | S37: {=+_xlfn.IFS(N37="","",N37="Componentes existentes reutilizables >80%","Baja",N37="No Aplica","Baja",N37="Reutilización parcial 30-70%","Media",N37="Nuevo Desarrollo <20%","Alta")} -> Alta | T37: {=+_xlfn.IFS(L37="","",L37=0,"Baja",L37<=2,"Media",L37>=3,"Alta")} | U37: {=+IFERROR((+_xlfn.IFS(Q37="",0,Q37="Baja",1,Q37="Media",2,Q37="Alta",3)*'Scoring Complejidad'!$C$8+_xlfn.IFS(R37="Baja",1,R37="Media",2,R37="Alta",3)*'Scoring Complejidad'!$C$9+_xlfn.IFS(S37="Baja",1,S37="Media",2,S37="Alta",3)*'Scoring Complejidad'!$C$7+_xlfn.IFS(T37="",1,T37="Baja",1,T37="Media",2,T37="Alta",3)*'Scoring Complejidad'!$C$5+_xlfn.IFS(M37="Caja",1,M37="Configuración",2,M37="Desarrollo",3,M37="Desarrollo + Configuración",3,M37="No Aplica",0)*'Scoring Complejidad'!$C$6),"")} -> 2.05 | V37: {=IFERROR(_xlfn.IFS(U37="","",U37<=1.69,"Baja",U37<=2.29,"Media",U37<=3,"Alta",U37>3,"Error"),"")} -> Media | W37: 46174 | X37: 46223 | Y37: Dependencia DTMs | Z37: Dependencia DTMs | AA37: Dependencia DTMs | AB37: Dependencia DTMs | AC37: Integraciones por revisar en siguiente sesión con equipo de SMARTVISTA y APIFICACIÓN - Daniela Viridiana Ramirez Perez (Coppel), Armando Garcia y DTMs Dependencia en fechas de diseño- por confirmar si Appwhere estará elaborando DTMs Dependencia en fechas de implementación de DTMs Prompt existe para legado pero no para SMARTVISTA- lo que se tiene que hacer son las APIs para el consumo de SMARTVISTA 10 semanas de implementación de la solución a partir de la entrega de DTMs y APIs | AD37: 05/082026
A38: HDU-SIWEB-R4-03 | B38: SIWEB | C38: Cancelar compra diferida en SIWEB. | D38: TDC | E38: Operación de compras diferidas en sucursal | F38: Cancelación de compra diferida en sucursal con validación de identidad (huella) ANTES de mostrar cualquier detalle de MCI/MSI. Cargo en una exhibición. Sin cancelar si crédito vencido. Restricción cruzada con credisolucion de saldo total vigente. | G38: Validación de huella ANTES de mostrar detalle [RN-HU-063]. Cargo en una exhibición por monto restante. Sin cancelar con crédito vencido (comentado en sesión). Restricción cruzada: con credisolucion de saldo total vigente no se permite nuevo pago fijo [RN-HU-054..057]. Crédito vigente obligatorio. | H38: SIWEB (Sucursal) | I38: Ejecutivo de Sucursal | J38: Should | K38: Solución e Integración | M38: Desarrollo + Configuración | N38: Nuevo Desarrollo <20% | O38: 3 | P38: 0 | Q38: {=+_xlfn.IFS(O38="","",O38<=1,"Baja",O38<=3,"Media",O38>3,"Alta")} -> Media | R38: {=+_xlfn.IFS(P38="","",P38<=0,"Baja",P38<=2,"Media",P38>2,"Alta")} -> Baja | S38: {=+_xlfn.IFS(N38="","",N38="Componentes existentes reutilizables >80%","Baja",N38="No Aplica","Baja",N38="Reutilización parcial 30-70%","Media",N38="Nuevo Desarrollo <20%","Alta")} -> Alta | T38: {=+_xlfn.IFS(L38="","",L38=0,"Baja",L38<=2,"Media",L38>=3,"Alta")} | U38: {=+IFERROR((+_xlfn.IFS(Q38="",0,Q38="Baja",1,Q38="Media",2,Q38="Alta",3)*'Scoring Complejidad'!$C$8+_xlfn.IFS(R38="Baja",1,R38="Media",2,R38="Alta",3)*'Scoring Complejidad'!$C$9+_xlfn.IFS(S38="Baja",1,S38="Media",2,S38="Alta",3)*'Scoring Complejidad'!$C$7+_xlfn.IFS(T38="",1,T38="Baja",1,T38="Media",2,T38="Alta",3)*'Scoring Complejidad'!$C$5+_xlfn.IFS(M38="Caja",1,M38="Configuración",2,M38="Desarrollo",3,M38="Desarrollo + Configuración",3,M38="No Aplica",0)*'Scoring Complejidad'!$C$6),"")} -> 2.05 | V38: {=IFERROR(_xlfn.IFS(U38="","",U38<=1.69,"Baja",U38<=2.29,"Media",U38<=3,"Alta",U38>3,"Error"),"")} -> Media | W38: 46174 | X38: 46223 | Y38: Dependencia DTMs | Z38: Dependencia DTMs | AA38: Dependencia DTMs | AB38: Dependencia DTMs | AC38: Integraciones por revisar en siguiente sesión con equipo de SMARTVISTA y APIFICACIÓN - Daniela Viridiana Ramirez Perez (Coppel), Armando Garcia y DTMs Dependencia en fechas de diseño- por confirmar si Appwhere estará elaborando DTMs Dependencia en fechas de implementación de DTMs Prompt existe para legado pero no para SMARTVISTA- lo que se tiene que hacer son las APIs para el consumo de SMARTVISTA 10 semanas de implementación de la solución a partir de la entrega de DTMs y APIs | AD38: 05/082026
A39: HDU-SIWEB-R4-04 | B39: SIWEB | C39: Registrar efectos contables de pagos fijos. | D39: TDC | E39: Operación de compras diferidas en sucursal | F39: Registro de los efectos contables de pagos, liquidaciones y cancelaciones de compras diferidas en SIWEB (productos 6900/8900). Al cancelar: capital al revolvente, intereses devengados+IVA al revolvente. Reverso controlado ante falla contable. | G39: Asientos contables para productos 6900/8900. Al cancelar: capital+intereses devengados+IVA→revolvente [RF-18 Escenario 2]. Concepto 'Cargo por cancelación de CrediSoluciones'. Reverso/ajuste controlado ante falla contable [RN-OP-S4-09/RN-HU-064]. TRNT exacta pendiente de guía contable formal (VAL-13). | H39: SIWEB / Contabilidad | I39: Área Operativa / Contable | J39: Should | K39: Solución e Integración | M39: Desarrollo + Configuración | N39: Nuevo Desarrollo <20% | O39: 3 | P39: 0 | Q39: {=+_xlfn.IFS(O39="","",O39<=1,"Baja",O39<=3,"Media",O39>3,"Alta")} -> Media | R39: {=+_xlfn.IFS(P39="","",P39<=0,"Baja",P39<=2,"Media",P39>2,"Alta")} -> Baja | S39: {=+_xlfn.IFS(N39="","",N39="Componentes existentes reutilizables >80%","Baja",N39="No Aplica","Baja",N39="Reutilización parcial 30-70%","Media",N39="Nuevo Desarrollo <20%","Alta")} -> Alta | T39: {=+_xlfn.IFS(L39="","",L39=0,"Baja",L39<=2,"Media",L39>=3,"Alta")} | U39: {=+IFERROR((+_xlfn.IFS(Q39="",0,Q39="Baja",1,Q39="Media",2,Q39="Alta",3)*'Scoring Complejidad'!$C$8+_xlfn.IFS(R39="Baja",1,R39="Media",2,R39="Alta",3)*'Scoring Complejidad'!$C$9+_xlfn.IFS(S39="Baja",1,S39="Media",2,S39="Alta",3)*'Scoring Complejidad'!$C$7+_xlfn.IFS(T39="",1,T39="Baja",1,T39="Media",2,T39="Alta",3)*'Scoring Complejidad'!$C$5+_xlfn.IFS(M39="Caja",1,M39="Configuración",2,M39="Desarrollo",3,M39="Desarrollo + Configuración",3,M39="No Aplica",0)*'Scoring Complejidad'!$C$6),"")} -> 2.05 | V39: {=IFERROR(_xlfn.IFS(U39="","",U39<=1.69,"Baja",U39<=2.29,"Media",U39<=3,"Alta",U39>3,"Error"),"")} -> Media | W39: 46174 | X39: 46223 | Y39: Dependencia DTMs | Z39: Dependencia DTMs | AA39: Dependencia DTMs | AB39: Dependencia DTMs | AC39: Integraciones por revisar en siguiente sesión con equipo de SMARTVISTA y APIFICACIÓN - Daniela Viridiana Ramirez Perez (Coppel), Armando Garcia y DTMs Dependencia en fechas de diseño- por confirmar si Appwhere estará elaborando DTMs Dependencia en fechas de implementación de DTMs Prompt existe para legado pero no para SMARTVISTA- lo que se tiene que hacer son las APIs para el consumo de SMARTVISTA 10 semanas de implementación de la solución a partir de la entrega de DTMs y APIs | AD39: 05/082026
A40: HDU-SIWEB-R4-05 | B40: SIWEB | C40: Validar el límite de saldo a favor en transacciones de caja. | D40: TDC | E40: Control de saldo a favor en caja | F40: Validación del pago/depósito de TDC contra el límite centralizado de saldo a favor antes de contabilizarlo. Aplica a ventanilla en efectivo y cargo a cuenta. Rechazo completo si excede el límite, sin generar póliza parcial. Abonos por aclaración bancaria: decisión diferida a R4.5/R5. | G40: Consulta en SV el parámetro vigente antes de aplicar el pago. Regla acumulada todos los canales incluida ventanilla. Rechazo completo si excede el límite; no póliza parcial. Mensaje homologado al usuario de caja. Abonos por aclaración: decisión R4 vigente, exclusión diferida a R4.5/R5. | H40: SIWEB (Sucursal / Caja) | I40: Ejecutivo de Caja / Ventanilla | J40: Should | K40: Solución e Integración | M40: Desarrollo + Configuración | N40: Nuevo Desarrollo <20% | O40: 3 | P40: 0 | Q40: {=+_xlfn.IFS(O40="","",O40<=1,"Baja",O40<=3,"Media",O40>3,"Alta")} -> Media | R40: {=+_xlfn.IFS(P40="","",P40<=0,"Baja",P40<=2,"Media",P40>2,"Alta")} -> Baja | S40: {=+_xlfn.IFS(N40="","",N40="Componentes existentes reutilizables >80%","Baja",N40="No Aplica","Baja",N40="Reutilización parcial 30-70%","Media",N40="Nuevo Desarrollo <20%","Alta")} -> Alta | T40: {=+_xlfn.IFS(L40="","",L40=0,"Baja",L40<=2,"Media",L40>=3,"Alta")} | U40: {=+IFERROR((+_xlfn.IFS(Q40="",0,Q40="Baja",1,Q40="Media",2,Q40="Alta",3)*'Scoring Complejidad'!$C$8+_xlfn.IFS(R40="Baja",1,R40="Media",2,R40="Alta",3)*'Scoring Complejidad'!$C$9+_xlfn.IFS(S40="Baja",1,S40="Media",2,S40="Alta",3)*'Scoring Complejidad'!$C$7+_xlfn.IFS(T40="",1,T40="Baja",1,T40="Media",2,T40="Alta",3)*'Scoring Complejidad'!$C$5+_xlfn.IFS(M40="Caja",1,M40="Configuración",2,M40="Desarrollo",3,M40="Desarrollo + Configuración",3,M40="No Aplica",0)*'Scoring Complejidad'!$C$6),"")} -> 2.05 | V40: {=IFERROR(_xlfn.IFS(U40="","",U40<=1.69,"Baja",U40<=2.29,"Media",U40<=3,"Alta",U40>3,"Error"),"")} -> Media | W40: 46174 | X40: 46223 | Y40: Dependencia DTMs | Z40: Dependencia DTMs | AA40: Dependencia DTMs | AB40: Dependencia DTMs | AC40: Integraciones por revisar en siguiente sesión con equipo de SMARTVISTA y APIFICACIÓN - Daniela Viridiana Ramirez Perez (Coppel), Armando Garcia y DTMs Dependencia en fechas de diseño- por confirmar si Appwhere estará elaborando DTMs Dependencia en fechas de implementación de DTMs Prompt existe para legado pero no para SMARTVISTA- lo que se tiene que hacer son las APIs para el consumo de SMARTVISTA 10 semanas de implementación de la solución a partir de la entrega de DTMs y APIs | AD40: 05/082026
A41: HDU-TDC-R4-01 | B41: Apolo | C41: Actualizar la tasa ordinaria y el CAT en la oferta de producto. | D41: TDC | E41: Oferta de Producto | F41: La oferta de producto debe mostrar la tasa ordinaria vigente (69.4%) y el CAT calculado conforme a la fórmula regulatoria. La tasa es parametrizable; aplica al solicitante precalificado al llegar a Oferta de Producto. | G41: Tasa ordinaria 69.4% parametrizable en BD. CAT refleja proporcionalmente el cambio conforme a fórmula vigente. Aplica al solicitante precalificado al concluir fase paramétrica. Vigencia de solicitud: 60 días para continuar. | H41: Apolo (Onboarding digital — Oferta de Producto) | I41: Solicitante TDC / Negocio | J41: Must | K41: Solución e Integración | L41: Pendiente | M41: Desarrollo | N41: Componentes existentes reutilizables >80% | O41: 3 | P41: 3 | Q41: {=+_xlfn.IFS(O41="","",O41<=1,"Baja",O41<=3,"Media",O41>3,"Alta")} -> Media | R41: {=+_xlfn.IFS(P41="","",P41<=0,"Baja",P41<=2,"Media",P41>2,"Alta")} -> Alta | S41: {=+_xlfn.IFS(N41="","",N41="Componentes existentes reutilizables >80%","Baja",N41="No Aplica","Baja",N41="Reutilización parcial 30-70%","Media",N41="Nuevo Desarrollo <20%","Alta")} -> Baja | T41: {=+_xlfn.IFS(L41="","",L41=0,"Baja",L41<=2,"Media",L41>=3,"Alta")} -> Alta | U41: {=+IFERROR((+_xlfn.IFS(Q41="",0,Q41="Baja",1,Q41="Media",2,Q41="Alta",3)*'Scoring Complejidad'!$C$8+_xlfn.IFS(R41="Baja",1,R41="Media",2,R41="Alta",3)*'Scoring Complejidad'!$C$9+_xlfn.IFS(S41="Baja",1,S41="Media",2,S41="Alta",3)*'Scoring Complejidad'!$C$7+_xlfn.IFS(T41="",1,T41="Baja",1,T41="Media",2,T41="Alta",3)*'Scoring Complejidad'!$C$5+_xlfn.IFS(M41="Caja",1,M41="Configuración",2,M41="Desarrollo",3,M41="Desarrollo + Configuración",3,M41="No Aplica",0)*'Scoring Complejidad'!$C$6),"")} -> 2.45 | V41: {=IFERROR(_xlfn.IFS(U41="","",U41<=1.69,"Baja",U41<=2.29,"Media",U41<=3,"Alta",U41>3,"Error"),"")} -> Alta | W41: 46179 | X41: 46237 | Y41: 46238 | Z41: 46261 | AA41: 46244 | AB41: 46310
A42: HDU-TDC-R4-03 | B42: Apolo | C42: Enviar por correo el contrato vigente al finalizar la firma. | D42: TDC | E42: Bienvenida | F42: Al completar exitosamente la firma y el onboarding TDC, el sistema envía automáticamente al correo del titular el Welcome Kit completo en PDF: contrato múltiple de crédito (RECA 1654-999-037863/09-01070-0526), tabla de comisiones, carátula, portada de tarjeta, contrato de servicios digitales y carátula de servicios digitales. | G42: Evento de confirmación de cuenta dispara el correo. Adjunta todos los documentos del Welcome Kit en PDF. Solo se dispara con onboarding exitoso; no se envía si el proceso no concluyó. Correo del titular debe estar disponible y validado previamente. | H42: Apolo (Onboarding digital — Bienvenida) | I42: Titular TDC / Sistema | J42: Must | K42: Integración | L42: Pendiente | M42: No Aplica | N42: No Aplica | O42: 3 | P42: 4 | Q42: {=+_xlfn.IFS(O42="","",O42<=1,"Baja",O42<=3,"Media",O42>3,"Alta")} -> Media | R42: {=+_xlfn.IFS(P42="","",P42<=0,"Baja",P42<=2,"Media",P42>2,"Alta")} -> Alta | S42: {=+_xlfn.IFS(N42="","",N42="Componentes existentes reutilizables >80%","Baja",N42="No Aplica","Baja",N42="Reutilización parcial 30-70%","Media",N42="Nuevo Desarrollo <20%","Alta")} -> Baja | T42: {=+_xlfn.IFS(L42="","",L42=0,"Baja",L42<=2,"Media",L42>=3,"Alta")} -> Alta | U42: {=+IFERROR((+_xlfn.IFS(Q42="",0,Q42="Baja",1,Q42="Media",2,Q42="Alta",3)*'Scoring Complejidad'!$C$8+_xlfn.IFS(R42="Baja",1,R42="Media",2,R42="Alta",3)*'Scoring Complejidad'!$C$9+_xlfn.IFS(S42="Baja",1,S42="Media",2,S42="Alta",3)*'Scoring Complejidad'!$C$7+_xlfn.IFS(T42="",1,T42="Baja",1,T42="Media",2,T42="Alta",3)*'Scoring Complejidad'!$C$5+_xlfn.IFS(M42="Caja",1,M42="Configuración",2,M42="Desarrollo",3,M42="Desarrollo + Configuración",3,M42="No Aplica",0)*'Scoring Complejidad'!$C$6),"")} -> 1.7 | V42: {=IFERROR(_xlfn.IFS(U42="","",U42<=1.69,"Baja",U42<=2.29,"Media",U42<=3,"Alta",U42>3,"Error"),"")} -> Media | W42: 46179 | X42: 46237 | Y42: 46238 | Z42: 46261 | AA42: 46244 | AB42: 46310
A43: HDU-TDC-R4-04 | B43: Apolo | C43: Aplicar Coltrane en bloques iniciales y validación temprana (BB1-BB4). | D43: TDC | E43: Preparación / TyC / Validación de Teléfono / Validación del Cliente | F43: Los BBs 1 a 4 (Preparación, TyC y Aviso de Privacidad, Validación de Teléfono, Validación del Cliente) deben adoptar tipografía, paleta, espaciados y componentes del sistema de diseño Coltrane conforme al Figma Mobile y Desktop. No modifica reglas funcionales de fondo. | G43: Aplica tipografía, paleta, espaciados y componentes Coltrane. Alinear con Figma Mobile y Desktop para BB1 (Preparación), BB2 (TyC), BB3 (Validación Teléfono), BB4 (Validación Cliente). No cambia reglas funcionales ni lógica de negocio. | H43: Apolo (Onboarding digital — BB1 al BB4) | I43: Solicitante TDC / UX | J43: Should | K43: Solución | L43: 0 | M43: Desarrollo | N43: Componentes existentes reutilizables >80% | O43: 4 | P43: 0 | Q43: {=+_xlfn.IFS(O43="","",O43<=1,"Baja",O43<=3,"Media",O43>3,"Alta")} -> Alta | R43: {=+_xlfn.IFS(P43="","",P43<=0,"Baja",P43<=2,"Media",P43>2,"Alta")} -> Baja | S43: {=+_xlfn.IFS(N43="","",N43="Componentes existentes reutilizables >80%","Baja",N43="No Aplica","Baja",N43="Reutilización parcial 30-70%","Media",N43="Nuevo Desarrollo <20%","Alta")} -> Baja | T43: {=+_xlfn.IFS(L43="","",L43=0,"Baja",L43<=2,"Media",L43>=3,"Alta")} -> Baja | U43: {=+IFERROR((+_xlfn.IFS(Q43="",0,Q43="Baja",1,Q43="Media",2,Q43="Alta",3)*'Scoring Complejidad'!$C$8+_xlfn.IFS(R43="Baja",1,R43="Media",2,R43="Alta",3)*'Scoring Complejidad'!$C$9+_xlfn.IFS(S43="Baja",1,S43="Media",2,S43="Alta",3)*'Scoring Complejidad'!$C$7+_xlfn.IFS(T43="",1,T43="Baja",1,T43="Media",2,T43="Alta",3)*'Scoring Complejidad'!$C$5+_xlfn.IFS(M43="Caja",1,M43="Configuración",2,M43="Desarrollo",3,M43="Desarrollo + Configuración",3,M43="No Aplica",0)*'Scoring Complejidad'!$C$6),"")} -> 1.8 | V43: {=IFERROR(_xlfn.IFS(U43="","",U43<=1.69,"Baja",U43<=2.29,"Media",U43<=3,"Alta",U43>3,"Error"),"")} -> Media | W43: 46174 | X43: 46174 | Y43: No Aplica | Z43: No Aplica | AA43: 46237 | AB43: 46262 | AC43: Should porque no rompen el flujo del onboarding No aplica diseño porque son cambios sencillos que no necesitan requerimientos técnicos | AD43: * Revisión de # de pantallas - Cecilia De Leon Modyo * Validar reusabilidad con Modyo
A44: HDU-TDC-R4-05 | B44: Apolo | C44: Aplicar Coltrane en bloques de perfilamiento, riesgo y decisión (BB5-BB11). | D44: TDC | E44: Perfilamiento / Validación de Domicilio / KYC-PEP / PLD / Persona Vulnerable / Validación SIC / Paramétrico | F44: Los BBs 5 a 11 (Perfilamiento, Validación de Domicilio, KYC-PEP, PLD, Persona Vulnerable, Validación SIC, Paramétrico) deben cumplir el sistema de diseño Coltrane conforme al Figma. No modifica la lógica de validación ni decisión crediticia. | G44: Aplica a Perfilamiento, Validación de Domicilio, KYC/PEP, PLD, Persona Vulnerable, Validación SIC y Paramétrico. Debe seguir Figma anexo. No se modifica lógica de validación ni decisión. Pendiente: acceso a Jira para equipos. | H44: Apolo (Onboarding digital — BB5 al BB11) | I44: Solicitante TDC / UX | J44: Should | K44: Solución | L44: 0 | M44: Desarrollo | N44: Componentes existentes reutilizables >80% | O44: 4 | P44: 0 | Q44: {=+_xlfn.IFS(O44="","",O44<=1,"Baja",O44<=3,"Media",O44>3,"Alta")} -> Alta | R44: {=+_xlfn.IFS(P44="","",P44<=0,"Baja",P44<=2,"Media",P44>2,"Alta")} -> Baja | S44: {=+_xlfn.IFS(N44="","",N44="Componentes existentes reutilizables >80%","Baja",N44="No Aplica","Baja",N44="Reutilización parcial 30-70%","Media",N44="Nuevo Desarrollo <20%","Alta")} -> Baja | T44: {=+_xlfn.IFS(L44="","",L44=0,"Baja",L44<=2,"Media",L44>=3,"Alta")} -> Baja | U44: {=+IFERROR((+_xlfn.IFS(Q44="",0,Q44="Baja",1,Q44="Media",2,Q44="Alta",3)*'Scoring Complejidad'!$C$8+_xlfn.IFS(R44="Baja",1,R44="Media",2,R44="Alta",3)*'Scoring Complejidad'!$C$9+_xlfn.IFS(S44="Baja",1,S44="Media",2,S44="Alta",3)*'Scoring Complejidad'!$C$7+_xlfn.IFS(T44="",1,T44="Baja",1,T44="Media",2,T44="Alta",3)*'Scoring Complejidad'!$C$5+_xlfn.IFS(M44="Caja",1,M44="Configuración",2,M44="Desarrollo",3,M44="Desarrollo + Configuración",3,M44="No Aplica",0)*'Scoring Complejidad'!$C$6),"")} -> 1.8 | V44: {=IFERROR(_xlfn.IFS(U44="","",U44<=1.69,"Baja",U44<=2.29,"Media",U44<=3,"Alta",U44>3,"Error"),"")} -> Media | W44: 46179 | X44: 46237 | Y44: 46238 | Z44: 46261 | AA44: 46244 | AB44: 46310 | AC44: Should porque es marcación digital * Validar pantallas con Modyo *Pendiente validar con Modyo y UX/UI
A45: HDU-TDC-R4-06 | B45: Apolo | C45: Aplicar Coltrane en oferta, autenticación, expediente y cierre (BB12-BB17). | D45: TDC | E45: Oferta de Producto / Prueba de Vida / Solicitud de Servicios Digitales / Validación de Correo / Integración de Expediente Digital / Bienvenida | F45: Los BBs 12 a 17 (Oferta de Producto, Prueba de Vida y Vídeo Selfie, Solicitud de Servicios Digitales, Validación de Correo, Integración de Expediente Digital, Bienvenida) deben usar el sistema visual Coltrane para cerrar el flujo con experiencia homogénea. | G45: Aplica a Oferta de Producto, Prueba de Vida, Solicitud Servicios Digitales, Validación Correo, Expediente Digital y Bienvenida. Cambio limitado a experiencia visual/patrones. No afecta lógica de firma ni expediente. | H45: Apolo (Onboarding digital — BB12 al BB17) | I45: Solicitante TDC / UX | J45: Should | K45: Solución | L45: 0 | M45: Desarrollo | N45: Componentes existentes reutilizables >80% | O45: 4 | P45: 0 | Q45: {=+_xlfn.IFS(O45="","",O45<=1,"Baja",O45<=3,"Media",O45>3,"Alta")} -> Alta | R45: {=+_xlfn.IFS(P45="","",P45<=0,"Baja",P45<=2,"Media",P45>2,"Alta")} -> Baja | S45: {=+_xlfn.IFS(N45="","",N45="Componentes existentes reutilizables >80%","Baja",N45="No Aplica","Baja",N45="Reutilización parcial 30-70%","Media",N45="Nuevo Desarrollo <20%","Alta")} -> Baja | T45: {=+_xlfn.IFS(L45="","",L45=0,"Baja",L45<=2,"Media",L45>=3,"Alta")} -> Baja | U45: {=+IFERROR((+_xlfn.IFS(Q45="",0,Q45="Baja",1,Q45="Media",2,Q45="Alta",3)*'Scoring Complejidad'!$C$8+_xlfn.IFS(R45="Baja",1,R45="Media",2,R45="Alta",3)*'Scoring Complejidad'!$C$9+_xlfn.IFS(S45="Baja",1,S45="Media",2,S45="Alta",3)*'Scoring Complejidad'!$C$7+_xlfn.IFS(T45="",1,T45="Baja",1,T45="Media",2,T45="Alta",3)*'Scoring Complejidad'!$C$5+_xlfn.IFS(M45="Caja",1,M45="Configuración",2,M45="Desarrollo",3,M45="Desarrollo + Configuración",3,M45="No Aplica",0)*'Scoring Complejidad'!$C$6),"")} -> 1.8 | V45: {=IFERROR(_xlfn.IFS(U45="","",U45<=1.69,"Baja",U45<=2.29,"Media",U45<=3,"Alta",U45>3,"Error"),"")} -> Media | W45: 46179 | X45: 46237 | Y45: 46238 | Z45: 46261 | AA45: 46244 | AB45: 46310 | AC45: Marcaje digital para métricas de funnel
A46: HDU-TDC-R4-07 | B46: Apolo | C46: Capturar la declaración inicial de persona vulnerable. | D46: TDC | E46: Persona Vulnerable | F46: Construcción del BB Persona Vulnerable (nuevo). El prospecto declara si pertenece a un grupo prioritario mediante pregunta obligatoria con opciones Sí / No / Prefiero no contestar, enlace informativo y despliegue condicional de listado. La respuesta se persiste en Informix/Yugabyte. | G46: BB Nuevo. Pregunta obligatoria: '¿Formas parte de algún grupo prioritario?'. Opciones: Sí, No, Prefiero no contestar (radio buttons). Enlace '¿Para qué usamos esta información?' despliega popup. Si Sí → muestra listado de selección múltiple. Respuesta bloqueante hasta seleccionar. Persistir en Informix/Yugabyte. | H46: Apolo (Onboarding digital — BB9 Persona Vulnerable) | I46: Prospecto TDC | J46: Should | K46: Solución e Integración | L46: Pendiente | M46: Desarrollo + Configuración | N46: Nuevo Desarrollo <20% | O46: 9 | P46: 1 | Q46: {=+_xlfn.IFS(O46="","",O46<=1,"Baja",O46<=3,"Media",O46>3,"Alta")} -> Alta | R46: {=+_xlfn.IFS(P46="","",P46<=0,"Baja",P46<=2,"Media",P46>2,"Alta")} -> Media | S46: {=+_xlfn.IFS(N46="","",N46="Componentes existentes reutilizables >80%","Baja",N46="No Aplica","Baja",N46="Reutilización parcial 30-70%","Media",N46="Nuevo Desarrollo <20%","Alta")} -> Alta | T46: {=+_xlfn.IFS(L46="","",L46=0,"Baja",L46<=2,"Media",L46>=3,"Alta")} -> Alta | U46: {=+IFERROR((+_xlfn.IFS(Q46="",0,Q46="Baja",1,Q46="Media",2,Q46="Alta",3)*'Scoring Complejidad'!$C$8+_xlfn.IFS(R46="Baja",1,R46="Media",2,R46="Alta",3)*'Scoring Complejidad'!$C$9+_xlfn.IFS(S46="Baja",1,S46="Media",2,S46="Alta",3)*'Scoring Complejidad'!$C$7+_xlfn.IFS(T46="",1,T46="Baja",1,T46="Media",2,T46="Alta",3)*'Scoring Complejidad'!$C$5+_xlfn.IFS(M46="Caja",1,M46="Configuración",2,M46="Desarrollo",3,M46="Desarrollo + Configuración",3,M46="No Aplica",0)*'Scoring Complejidad'!$C$6),"")} -> 2.9 | V46: {=IFERROR(_xlfn.IFS(U46="","",U46<=1.69,"Baja",U46<=2.29,"Media",U46<=3,"Alta",U46>3,"Error"),"")} -> Alta | W46: 46179 | X46: 46237 | Y46: 46238 | Z46: 46261 | AA46: 46244 | AB46: 46310 | AC46: Should- pendiente por validar si es regulatorio. Información de perfilamiento *Pediente validar # de integraciones con Oscar Melo
A47: HDU-TDC-R4-08 | B47: Apolo | C47: Desplegar y guardar opciones de grupo prioritario cuando el prospecto responde Sí. | D47: TDC | E47: Persona Vulnerable | F47: Cuando el prospecto responde 'Sí' en la declaración de persona vulnerable, el sistema despliega dinámicamente un listado de selección múltiple (discapacidad, comunidad indígena/etnia/pueblo, adulto mayor). La selección se persiste en BD asociada al perfil. | G47: Despliegue dinámico solo si respuesta = Sí. Selección múltiple habilitada. Opciones: discapacidad, comunidad indígena/etnia/pueblo, adulto mayor. No se despliega con No o Prefiero no contestar. Persistir en BD asociada al perfil del prospecto. | H47: Apolo (Onboarding digital — BB9 Persona Vulnerable) | I47: Prospecto TDC / Sistema | J47: Should | K47: Solución e Integración | L47: Pendiente | M47: Desarrollo + Configuración | N47: Nuevo Desarrollo <20% | O47: 4 | P47: 1 | Q47: {=+_xlfn.IFS(O47="","",O47<=1,"Baja",O47<=3,"Media",O47>3,"Alta")} -> Alta | R47: {=+_xlfn.IFS(P47="","",P47<=0,"Baja",P47<=2,"Media",P47>2,"Alta")} -> Media | S47: {=+_xlfn.IFS(N47="","",N47="Componentes existentes reutilizables >80%","Baja",N47="No Aplica","Baja",N47="Reutilización parcial 30-70%","Media",N47="Nuevo Desarrollo <20%","Alta")} -> Alta | T47: {=+_xlfn.IFS(L47="","",L47=0,"Baja",L47<=2,"Media",L47>=3,"Alta")} -> Alta | U47: {=+IFERROR((+_xlfn.IFS(Q47="",0,Q47="Baja",1,Q47="Media",2,Q47="Alta",3)*'Scoring Complejidad'!$C$8+_xlfn.IFS(R47="Baja",1,R47="Media",2,R47="Alta",3)*'Scoring Complejidad'!$C$9+_xlfn.IFS(S47="Baja",1,S47="Media",2,S47="Alta",3)*'Scoring Complejidad'!$C$7+_xlfn.IFS(T47="",1,T47="Baja",1,T47="Media",2,T47="Alta",3)*'Scoring Complejidad'!$C$5+_xlfn.IFS(M47="Caja",1,M47="Configuración",2,M47="Desarrollo",3,M47="Desarrollo + Configuración",3,M47="No Aplica",0)*'Scoring Complejidad'!$C$6),"")} -> 2.9 | V47: {=IFERROR(_xlfn.IFS(U47="","",U47<=1.69,"Baja",U47<=2.29,"Media",U47<=3,"Alta",U47>3,"Error"),"")} -> Alta | W47: 46179 | X47: 46237 | Y47: 46238 | Z47: 46261 | AA47: 46244 | AB47: 46310 | AC47: Should- pendiente por validar si es regulatorio. Información de perfilamiento *Pediente validar # de integraciones con Oscar Melo
A48: HDU-TDC-R4-10 | B48: Apolo | C48: Actualizar imagen de tarjeta y textos legales en pantallas clave. | D48: TDC | E48: Preparación/ Oferta de Producto / Bienvenida | F48: Reemplazar la imagen de tarjeta de débito por la imagen de tarjeta de crédito BanCoppel en pantallas de Inicio, Oferta de Producto y Bienvenida. Corregir texto 'pre-aprobada' (sin guión) e incluir 'BanCoppel' en la leyenda de aceptación. | G48: Reemplazar imagen débito → TDC BanCoppel en Inicio, Oferta y Bienvenida (según Figma). Eliminar guión en 'preaprobada'. Incluir 'BanCoppel' en leyenda de aceptación (definición por UX). Textos legales aprobados por Legal. | H48: Apolo (Onboarding digital — Preparación, Oferta, Bienvenida) | I48: Solicitante TDC | J48: Must | K48: Solución | L48: 0 | M48: Desarrollo | N48: Componentes existentes reutilizables >80% | O48: 4 | P48: 0 | Q48: {=+_xlfn.IFS(O48="","",O48<=1,"Baja",O48<=3,"Media",O48>3,"Alta")} -> Alta | R48: {=+_xlfn.IFS(P48="","",P48<=0,"Baja",P48<=2,"Media",P48>2,"Alta")} -> Baja | S48: {=+_xlfn.IFS(N48="","",N48="Componentes existentes reutilizables >80%","Baja",N48="No Aplica","Baja",N48="Reutilización parcial 30-70%","Media",N48="Nuevo Desarrollo <20%","Alta")} -> Baja | T48: {=+_xlfn.IFS(L48="","",L48=0,"Baja",L48<=2,"Media",L48>=3,"Alta")} -> Baja | U48: {=+IFERROR((+_xlfn.IFS(Q48="",0,Q48="Baja",1,Q48="Media",2,Q48="Alta",3)*'Scoring Complejidad'!$C$8+_xlfn.IFS(R48="Baja",1,R48="Media",2,R48="Alta",3)*'Scoring Complejidad'!$C$9+_xlfn.IFS(S48="Baja",1,S48="Media",2,S48="Alta",3)*'Scoring Complejidad'!$C$7+_xlfn.IFS(T48="",1,T48="Baja",1,T48="Media",2,T48="Alta",3)*'Scoring Complejidad'!$C$5+_xlfn.IFS(M48="Caja",1,M48="Configuración",2,M48="Desarrollo",3,M48="Desarrollo + Configuración",3,M48="No Aplica",0)*'Scoring Complejidad'!$C$6),"")} -> 1.8 | V48: {=IFERROR(_xlfn.IFS(U48="","",U48<=1.69,"Baja",U48<=2.29,"Media",U48<=3,"Alta",U48>3,"Error"),"")} -> Media | W48: 46174 | X48: 46174 | Y48: No Aplica | Z48: No Aplica | AA48: 46237 | AB48: 46262 | AC48: Es Must porque es un tema legal No aplica diseño porque son cambios sencillos que no necesitan requerimientos técnicos | AD48: * Revisión de # de pantallas - Cecilia De Leon Modyo * Validar reusabilidad con Modyo
A49: HDU-TDC-R4-13 | B49: Apolo | C49: Validar al solicitante contra listas negras en Perfilamiento / PLD. | D49: TDC | E49: Perfilamiento LISTAS NEGRAS PLD / Name Matching | F49: El solicitante es validado contra listas negras/bloqueantes vía servicio Name Matching (con respaldo a Informix al 100% si Name Matching no resuelve en tiempo). HIT → KO bloqueante con estatus 'Rechazo Listas Negras' (Clave RLN, Causa 66, SE:U). NO HIT → continúa flujo. | G49: Consulta Name Matching; si no resuelve → fallback Informix (100%). HIT: KO + TYP 'Gracias por tu interés. Por ahora no es posible avanzar con tu solicitud'. Clave RLN, Causa 66, SE:U en bitácora. NO HIT: continúa. Tiempo de respuesta Informix ~20 seg a considerar. | H49: Apolo (Onboarding digital — BB5 Perfilamiento / BB8 PLD) | I49: Prospecto TDC / Sistema PLD | J49: Must | K49: Integración | L49: 1 | M49: No Aplica | N49: No Aplica | O49: 4 | P49: 0 | Q49: {=+_xlfn.IFS(O49="","",O49<=1,"Baja",O49<=3,"Media",O49>3,"Alta")} -> Alta | R49: {=+_xlfn.IFS(P49="","",P49<=0,"Baja",P49<=2,"Media",P49>2,"Alta")} -> Baja | S49: {=+_xlfn.IFS(N49="","",N49="Componentes existentes reutilizables >80%","Baja",N49="No Aplica","Baja",N49="Reutilización parcial 30-70%","Media",N49="Nuevo Desarrollo <20%","Alta")} -> Baja | T49: {=+_xlfn.IFS(L49="","",L49=0,"Baja",L49<=2,"Media",L49>=3,"Alta")} -> Media | U49: {=+IFERROR((+_xlfn.IFS(Q49="",0,Q49="Baja",1,Q49="Media",2,Q49="Alta",3)*'Scoring Complejidad'!$C$8+_xlfn.IFS(R49="Baja",1,R49="Media",2,R49="Alta",3)*'Scoring Complejidad'!$C$9+_xlfn.IFS(S49="Baja",1,S49="Media",2,S49="Alta",3)*'Scoring Complejidad'!$C$7+_xlfn.IFS(T49="",1,T49="Baja",1,T49="Media",2,T49="Alta",3)*'Scoring Complejidad'!$C$5+_xlfn.IFS(M49="Caja",1,M49="Configuración",2,M49="Desarrollo",3,M49="Desarrollo + Configuración",3,M49="No Aplica",0)*'Scoring Complejidad'!$C$6),"")} -> 1.35 | V49: {=IFERROR(_xlfn.IFS(U49="","",U49<=1.69,"Baja",U49<=2.29,"Media",U49<=3,"Alta",U49>3,"Error"),"")} -> Baja | W49: 46179 | X49: 46237 | Y49: 46238 | Z49: 46261 | AA49: 46244 | AB49: 46310 | AC49: Ya existe el servicio, simplemente es agregar la integración
A50: HDU-TDC-R4-14 | B50: Apolo | C50: Validar al familiar con cargo público contra listas negras (PEP). | D50: TDC | E50: KYC / PEP / Name Matching | F50: El familiar con cargo público declarado por el prospecto es validado contra listas negras vía Name Matching (con fallback a Informix). HIT → KO con estatus 'Rechazo Listas Negras PEP' (Clave LNE, Causa 117, SE:P). NO HIT → continúa. | G50: Consulta en BB PEP(KYC). Name Matching; fallback Informix (100%). HIT: KO + TYP 'Gracias por tu interés...'. Clave LNE, Causa 117, SE:P en bitácora. NO HIT: continúa. Dependencia: datos del familiar con cargo público capturados previamente. | H50: Apolo (Onboarding digital — BB7 PEP/KYC) | I50: Familiar con Cargo Público / Sistema KYC | J50: Must | K50: Integración | L50: 1 | M50: No Aplica | N50: No Aplica | O50: 4 | P50: 6 | Q50: {=+_xlfn.IFS(O50="","",O50<=1,"Baja",O50<=3,"Media",O50>3,"Alta")} -> Alta | R50: {=+_xlfn.IFS(P50="","",P50<=0,"Baja",P50<=2,"Media",P50>2,"Alta")} -> Alta | S50: {=+_xlfn.IFS(N50="","",N50="Componentes existentes reutilizables >80%","Baja",N50="No Aplica","Baja",N50="Reutilización parcial 30-70%","Media",N50="Nuevo Desarrollo <20%","Alta")} -> Baja | T50: {=+_xlfn.IFS(L50="","",L50=0,"Baja",L50<=2,"Media",L50>=3,"Alta")} -> Media | U50: {=+IFERROR((+_xlfn.IFS(Q50="",0,Q50="Baja",1,Q50="Media",2,Q50="Alta",3)*'Scoring Complejidad'!$C$8+_xlfn.IFS(R50="Baja",1,R50="Media",2,R50="Alta",3)*'Scoring Complejidad'!$C$9+_xlfn.IFS(S50="Baja",1,S50="Media",2,S50="Alta",3)*'Scoring Complejidad'!$C$7+_xlfn.IFS(T50="",1,T50="Baja",1,T50="Media",2,T50="Alta",3)*'Scoring Complejidad'!$C$5+_xlfn.IFS(M50="Caja",1,M50="Configuración",2,M50="Desarrollo",3,M50="Desarrollo + Configuración",3,M50="No Aplica",0)*'Scoring Complejidad'!$C$6),"")} -> 1.55 | V50: {=IFERROR(_xlfn.IFS(U50="","",U50<=1.69,"Baja",U50<=2.29,"Media",U50<=3,"Alta",U50>3,"Error"),"")} -> Baja | W50: 46179 | X50: 46237 | Y50: 46238 | Z50: 46261 | AA50: 46244 | AB50: 46310 | AC50: Va al servicio de name matching- cambio de back *Detalle de integración por validar con equipo de API (Oscar Melo)
A51: HDU-TDC-R4-16 | B51: Apolo | C51: Validar la referencia contra listas negras en Paramétrico. | D51: TDC | E51: PLD / PEP/ Name Matching/parametrico | F51: La referencia capturada por el prospecto es validada contra listas negras vía Name Matching (con fallback a Informix). HIT → KO bloqueante con clave LNR (Clave LNR, Causa 119, SE:P). NO HIT → flujo continúa. | G51: Consulta en BB Paramétrico. Name Matching; fallback Informix (100%). HIT: KO + TYP. Clave LNR, Causa 119, SE:P en bitácora. NO HIT: flujo continúa. Dependencia: referencia capturada en step previo. | H51: Apolo (Onboarding digital — BB11 Paramétrico) | I51: Referencia del Prospecto / Sistema PLD | J51: Must | K51: Integración | L51: 1 | M51: No Aplica | N51: No Aplica | O51: 4 | P51: 0 | Q51: {=+_xlfn.IFS(O51="","",O51<=1,"Baja",O51<=3,"Media",O51>3,"Alta")} -> Alta | R51: {=+_xlfn.IFS(P51="","",P51<=0,"Baja",P51<=2,"Media",P51>2,"Alta")} -> Baja | S51: {=+_xlfn.IFS(N51="","",N51="Componentes existentes reutilizables >80%","Baja",N51="No Aplica","Baja",N51="Reutilización parcial 30-70%","Media",N51="Nuevo Desarrollo <20%","Alta")} -> Baja | T51: {=+_xlfn.IFS(L51="","",L51=0,"Baja",L51<=2,"Media",L51>=3,"Alta")} -> Media | U51: {=+IFERROR((+_xlfn.IFS(Q51="",0,Q51="Baja",1,Q51="Media",2,Q51="Alta",3)*'Scoring Complejidad'!$C$8+_xlfn.IFS(R51="Baja",1,R51="Media",2,R51="Alta",3)*'Scoring Complejidad'!$C$9+_xlfn.IFS(S51="Baja",1,S51="Media",2,S51="Alta",3)*'Scoring Complejidad'!$C$7+_xlfn.IFS(T51="",1,T51="Baja",1,T51="Media",2,T51="Alta",3)*'Scoring Complejidad'!$C$5+_xlfn.IFS(M51="Caja",1,M51="Configuración",2,M51="Desarrollo",3,M51="Desarrollo + Configuración",3,M51="No Aplica",0)*'Scoring Complejidad'!$C$6),"")} -> 1.35 | V51: {=IFERROR(_xlfn.IFS(U51="","",U51<=1.69,"Baja",U51<=2.29,"Media",U51<=3,"Alta",U51>3,"Error"),"")} -> Baja | W51: 46179 | X51: 46237 | Y51: 46238 | Z51: 46261 | AA51: 46244 | AB51: 46310 | AC51: Va al servicio de name matching- cambio de back *Detalle de integración por validar con equipo de API (Oscar Melo)
A52: HDU-TDC-R4-17 | B52: Apolo | C52: Presentar la pantalla de términos con Contrato Múltiple y Servicios Digitales. | D52: TDC | E52: Integración Expediente digital | F52: La pantalla previa a la firma presenta los documentos requeridos: Contrato Múltiple de Crédito (RECA 1654-999-037863/09-01070-0526, tabla de comisiones, carátula, portada de tarjeta) y Servicios Digitales (contrato y carátula). Muestra el correo del prospecto y el mensaje de envío. Guarda en OnBase al firmar. | G52: Pantalla indica 'leer y firmar T&C'. Campo Contrato Múltiple: contrato múltiple crédito persona física (RECA 1654-999-037863/09-01070-0526), tabla comisiones, carátula, portada tarjeta. Campo Servicios Digitales: contrato y carátula. Muestra correo sin opción a modificar. Guardar en OnBase al firmar. Incluye criterios de HDU-TDC-R4-11 (desestimada, ya incluidos aquí). | H52: Apolo (Onboarding digital — BB16 Integración Expediente Digital) | I52: Prospecto TDC | J52: Must | K52: Solución | L52: 0 | M52: Desarrollo | N52: Componentes existentes reutilizables >80% | O52: 6 | P52: 8 | Q52: {=+_xlfn.IFS(O52="","",O52<=1,"Baja",O52<=3,"Media",O52>3,"Alta")} -> Alta | R52: {=+_xlfn.IFS(P52="","",P52<=0,"Baja",P52<=2,"Media",P52>2,"Alta")} -> Alta | S52: {=+_xlfn.IFS(N52="","",N52="Componentes existentes reutilizables >80%","Baja",N52="No Aplica","Baja",N52="Reutilización parcial 30-70%","Media",N52="Nuevo Desarrollo <20%","Alta")} -> Baja | T52: {=+_xlfn.IFS(L52="","",L52=0,"Baja",L52<=2,"Media",L52>=3,"Alta")} -> Baja | U52: {=+IFERROR((+_xlfn.IFS(Q52="",0,Q52="Baja",1,Q52="Media",2,Q52="Alta",3)*'Scoring Complejidad'!$C$8+_xlfn.IFS(R52="Baja",1,R52="Media",2,R52="Alta",3)*'Scoring Complejidad'!$C$9+_xlfn.IFS(S52="Baja",1,S52="Media",2,S52="Alta",3)*'Scoring Complejidad'!$C$7+_xlfn.IFS(T52="",1,T52="Baja",1,T52="Media",2,T52="Alta",3)*'Scoring Complejidad'!$C$5+_xlfn.IFS(M52="Caja",1,M52="Configuración",2,M52="Desarrollo",3,M52="Desarrollo + Configuración",3,M52="No Aplica",0)*'Scoring Complejidad'!$C$6),"")} -> 2 | V52: {=IFERROR(_xlfn.IFS(U52="","",U52<=1.69,"Baja",U52<=2.29,"Media",U52<=3,"Alta",U52>3,"Error"),"")} -> Media | W52: 46179 | X52: 46237 | Y52: 46238 | Z52: 46261 | AA52: 46244 | AB52: 46310
A53: HDU-TDC-R4-18 | B53: Apolo | C53: Permitir lectura de documentos y avance a firma electrónica. | D53: TDC | E53: Integración de Expediente Digital | F53: El botón 'Leer Documentos' da acceso a los contratos como hipervínculos. El contrato de Servicios Digitales con carátula (nueva versión) debe visualizarse. Los documentos de lectura no contienen datos personalizados. Tras leer, el flujo avanza a firma electrónica. | G53: Botón 'Leer Documentos' muestra contratos como hipervínculos. Incluye contrato Servicios Digitales con nueva versión de carátula. Documentos de lectura sin datos personalizados (no interactivos). Tras lectura, avanza a firma electrónica. Dependencia: nueva carátula disponible. | H53: Apolo (Onboarding digital — BB16 Integración Expediente Digital) | I53: Prospecto TDC | J53: Must | K53: Solución | L53: 0 | M53: Desarrollo | N53: Componentes existentes reutilizables >80% | O53: 3 | P53: 8 | Q53: {=+_xlfn.IFS(O53="","",O53<=1,"Baja",O53<=3,"Media",O53>3,"Alta")} -> Media | R53: {=+_xlfn.IFS(P53="","",P53<=0,"Baja",P53<=2,"Media",P53>2,"Alta")} -> Alta | S53: {=+_xlfn.IFS(N53="","",N53="Componentes existentes reutilizables >80%","Baja",N53="No Aplica","Baja",N53="Reutilización parcial 30-70%","Media",N53="Nuevo Desarrollo <20%","Alta")} -> Baja | T53: {=+_xlfn.IFS(L53="","",L53=0,"Baja",L53<=2,"Media",L53>=3,"Alta")} -> Baja | U53: {=+IFERROR((+_xlfn.IFS(Q53="",0,Q53="Baja",1,Q53="Media",2,Q53="Alta",3)*'Scoring Complejidad'!$C$8+_xlfn.IFS(R53="Baja",1,R53="Media",2,R53="Alta",3)*'Scoring Complejidad'!$C$9+_xlfn.IFS(S53="Baja",1,S53="Media",2,S53="Alta",3)*'Scoring Complejidad'!$C$7+_xlfn.IFS(T53="",1,T53="Baja",1,T53="Media",2,T53="Alta",3)*'Scoring Complejidad'!$C$5+_xlfn.IFS(M53="Caja",1,M53="Configuración",2,M53="Desarrollo",3,M53="Desarrollo + Configuración",3,M53="No Aplica",0)*'Scoring Complejidad'!$C$6),"")} -> 1.85 | V53: {=IFERROR(_xlfn.IFS(U53="","",U53<=1.69,"Baja",U53<=2.29,"Media",U53<=3,"Alta",U53>3,"Error"),"")} -> Media | W53: 46179 | X53: 46237 | Y53: 46238 | Z53: 46261 | AA53: 46244 | AB53: 46310 | AC53: *Ya existe, solo se esta modificando sobre una integración existente
A54: HDU-TDC-R4-19 | B54: Apolo | C54: Mostrar información de activación de servicios digitales mediante popup. | D54: TDC | E54: Integración de Expediente Digital | F54: En la pantalla de Integración de Expediente Digital (versión app), un enlace '¿Cómo puedo activar los servicios digitales?' despliega un popup con contenido aprobado por Marketing, UX y Negocio. El usuario puede cerrar el popup y regresar al flujo sin perder avance. | G54: Link '¿Cómo puedo activar los servicios digitales?' en pantalla de expediente (solo versión app). Click → popup con contenido aprobado. Popup cierra sin perder progreso. Contenido aprobado por Marketing/UX/Negocio. Validar dependencia con HDU cambio de marca Fase 2. | H54: Apolo (Onboarding digital — BB16 Integración Expediente Digital) | I54: Prospecto TDC | J54: Should | K54: Solución | L54: 0 | M54: Desarrollo | N54: Nuevo Desarrollo <20% | O54: 5 | P54: 8 | Q54: {=+_xlfn.IFS(O54="","",O54<=1,"Baja",O54<=3,"Media",O54>3,"Alta")} -> Alta | R54: {=+_xlfn.IFS(P54="","",P54<=0,"Baja",P54<=2,"Media",P54>2,"Alta")} -> Alta | S54: {=+_xlfn.IFS(N54="","",N54="Componentes existentes reutilizables >80%","Baja",N54="No Aplica","Baja",N54="Reutilización parcial 30-70%","Media",N54="Nuevo Desarrollo <20%","Alta")} -> Alta | T54: {=+_xlfn.IFS(L54="","",L54=0,"Baja",L54<=2,"Media",L54>=3,"Alta")} -> Baja | U54: {=+IFERROR((+_xlfn.IFS(Q54="",0,Q54="Baja",1,Q54="Media",2,Q54="Alta",3)*'Scoring Complejidad'!$C$8+_xlfn.IFS(R54="Baja",1,R54="Media",2,R54="Alta",3)*'Scoring Complejidad'!$C$9+_xlfn.IFS(S54="Baja",1,S54="Media",2,S54="Alta",3)*'Scoring Complejidad'!$C$7+_xlfn.IFS(T54="",1,T54="Baja",1,T54="Media",2,T54="Alta",3)*'Scoring Complejidad'!$C$5+_xlfn.IFS(M54="Caja",1,M54="Configuración",2,M54="Desarrollo",3,M54="Desarrollo + Configuración",3,M54="No Aplica",0)*'Scoring Complejidad'!$C$6),"")} -> 2.4 | V54: {=IFERROR(_xlfn.IFS(U54="","",U54<=1.69,"Baja",U54<=2.29,"Media",U54<=3,"Alta",U54>3,"Error"),"")} -> Alta | W54: 46179 | X54: 46237 | Y54: 46238 | Z54: 46261 | AA54: 46244 | AB54: 46310 | AC54: Should informativo, valor de experiencia hacia el cliente como negocio
A55: HDU-TDC-R4-20 | B55: Apolo | C55: Integrar firma, alta de crédito, expediente digital y marcaje de visualización. | D55: TDC | E55: Integración Expediente Digital | F55: La firma exitosa activa el alta del crédito en SmartVista y consolida el expediente digital en OnBase. Incluye asignación del producto, anexo de datos del crédito al expediente y marcaje de visualización de cada documento para trazabilidad. | G55: Firma exitosa activa alta de crédito en SmartVista. Asignación de producto TDC. Datos del crédito se anexan al expediente digital. Expediente se almacena en OnBase. Marcaje de cada documento visualizado para trazabilidad. Integración SmartVista + OnBase disponibles. | H55: Apolo (Onboarding digital — BB16 Integración Expediente Digital) | I55: Sistema / SmartVista / OnBase | J55: Must | K55: Solución e Integración | L55: Pendiente | M55: Desarrollo + Configuración | N55: Reutilización parcial 30-70% | O55: 4 | P55: 8 | Q55: {=+_xlfn.IFS(O55="","",O55<=1,"Baja",O55<=3,"Media",O55>3,"Alta")} -> Alta | R55: {=+_xlfn.IFS(P55="","",P55<=0,"Baja",P55<=2,"Media",P55>2,"Alta")} -> Alta | S55: {=+_xlfn.IFS(N55="","",N55="Componentes existentes reutilizables >80%","Baja",N55="No Aplica","Baja",N55="Reutilización parcial 30-70%","Media",N55="Nuevo Desarrollo <20%","Alta")} -> Media | T55: {=+_xlfn.IFS(L55="","",L55=0,"Baja",L55<=2,"Media",L55>=3,"Alta")} -> Alta | U55: {=+IFERROR((+_xlfn.IFS(Q55="",0,Q55="Baja",1,Q55="Media",2,Q55="Alta",3)*'Scoring Complejidad'!$C$8+_xlfn.IFS(R55="Baja",1,R55="Media",2,R55="Alta",3)*'Scoring Complejidad'!$C$9+_xlfn.IFS(S55="Baja",1,S55="Media",2,S55="Alta",3)*'Scoring Complejidad'!$C$7+_xlfn.IFS(T55="",1,T55="Baja",1,T55="Media",2,T55="Alta",3)*'Scoring Complejidad'!$C$5+_xlfn.IFS(M55="Caja",1,M55="Configuración",2,M55="Desarrollo",3,M55="Desarrollo + Configuración",3,M55="No Aplica",0)*'Scoring Complejidad'!$C$6),"")} -> 2.8 | V55: {=IFERROR(_xlfn.IFS(U55="","",U55<=1.69,"Baja",U55<=2.29,"Media",U55<=3,"Alta",U55>3,"Error"),"")} -> Alta | W55: 46179 | X55: 46237 | Y55: 46238 | Z55: 46261 | AA55: 46244 | AB55: 46310
A56: HDU-TDC-R4-21 | B56: Apolo | C56: Aplicar KO automático cuando el prospecto usará dinero de otra persona. | D56: TDC | E56: PLD | F56: En el BB PLD, la pregunta '¿Pagarás tu tarjeta de crédito con tu dinero?' tiene dos rutas: 'Usaré mi dinero' → continúa a Validación SIC; 'Usaré dinero de otra persona' → KO automático con guardado en Yugabyte y TYP con mensaje de canalización a sucursal. | G56: Pregunta PLD: '¿Pagarás tu TDC con tu dinero?'. 'Usaré mi dinero' → continúa a SIC. 'Usaré dinero de otra persona' → KO guardado en Yugabyte, TYP con mensaje y botón de canalización. Esta HU reemplaza la HDU-TDC-R4-15 (desestimada). | H56: Apolo (Onboarding digital — BB8 PLD) | I56: Prospecto TDC / Sistema PLD | J56: Could | K56: Solución e Integración | L56: Por validar | M56: Desarrollo | N56: Reutilización parcial 30-70% | O56: 3 | P56: 4 | Q56: {=+_xlfn.IFS(O56="","",O56<=1,"Baja",O56<=3,"Media",O56>3,"Alta")} -> Media | R56: {=+_xlfn.IFS(P56="","",P56<=0,"Baja",P56<=2,"Media",P56>2,"Alta")} -> Alta | S56: {=+_xlfn.IFS(N56="","",N56="Componentes existentes reutilizables >80%","Baja",N56="No Aplica","Baja",N56="Reutilización parcial 30-70%","Media",N56="Nuevo Desarrollo <20%","Alta")} -> Media | T56: {=+_xlfn.IFS(L56="","",L56=0,"Baja",L56<=2,"Media",L56>=3,"Alta")} -> Alta | U56: {=+IFERROR((+_xlfn.IFS(Q56="",0,Q56="Baja",1,Q56="Media",2,Q56="Alta",3)*'Scoring Complejidad'!$C$8+_xlfn.IFS(R56="Baja",1,R56="Media",2,R56="Alta",3)*'Scoring Complejidad'!$C$9+_xlfn.IFS(S56="Baja",1,S56="Media",2,S56="Alta",3)*'Scoring Complejidad'!$C$7+_xlfn.IFS(T56="",1,T56="Baja",1,T56="Media",2,T56="Alta",3)*'Scoring Complejidad'!$C$5+_xlfn.IFS(M56="Caja",1,M56="Configuración",2,M56="Desarrollo",3,M56="Desarrollo + Configuración",3,M56="No Aplica",0)*'Scoring Complejidad'!$C$6),"")} -> 2.65 | V56: {=IFERROR(_xlfn.IFS(U56="","",U56<=1.69,"Baja",U56<=2.29,"Media",U56<=3,"Alta",U56>3,"Error"),"")} -> Alta | W56: 46179 | X56: 46237 | Y56: 46238 | Z56: 46261 | AA56: 46244 | AB56: 46310 | AC56: Prospecto no esta considerado en el alcance de R4 - pendiente validar
A57: HDU-TDC-R4-23 | B57: Apolo | C57: Validar formato del número celular en Preparación y Validación de Teléfono. | D57: TDC | E57: Preparación / Validación de Teléfono | F57: El campo de teléfono muestra bandera México y lada +52 bloqueada. Admite exactamente 10 dígitos. Incluye reglas de secuencias idénticas y otras restricciones por definir. Aplica en BB1 Preparación y BB3 Validación de Teléfono. | G57: Campo con bandera México y lada +52 bloqueada. Exactamente 10 dígitos. Restricciones a definir: secuencias idénticas prohibidas, longitud mínima. Aplica en Preparación y Validación del Teléfono. Reglas de formato a confirmar con equipo. | H57: Apolo (Onboarding digital — BB1 Preparación / BB3 Validación Teléfono) | I57: Prospecto TDC | J57: Should | K57: Solución | L57: 0 | M57: Desarrollo | N57: Reutilización parcial 30-70% | O57: 5 | P57: 0 | Q57: {=+_xlfn.IFS(O57="","",O57<=1,"Baja",O57<=3,"Media",O57>3,"Alta")} -> Alta | R57: {=+_xlfn.IFS(P57="","",P57<=0,"Baja",P57<=2,"Media",P57>2,"Alta")} -> Baja | S57: {=+_xlfn.IFS(N57="","",N57="Componentes existentes reutilizables >80%","Baja",N57="No Aplica","Baja",N57="Reutilización parcial 30-70%","Media",N57="Nuevo Desarrollo <20%","Alta")} -> Media | T57: {=+_xlfn.IFS(L57="","",L57=0,"Baja",L57<=2,"Media",L57>=3,"Alta")} -> Baja | U57: {=+IFERROR((+_xlfn.IFS(Q57="",0,Q57="Baja",1,Q57="Media",2,Q57="Alta",3)*'Scoring Complejidad'!$C$8+_xlfn.IFS(R57="Baja",1,R57="Media",2,R57="Alta",3)*'Scoring Complejidad'!$C$9+_xlfn.IFS(S57="Baja",1,S57="Media",2,S57="Alta",3)*'Scoring Complejidad'!$C$7+_xlfn.IFS(T57="",1,T57="Baja",1,T57="Media",2,T57="Alta",3)*'Scoring Complejidad'!$C$5+_xlfn.IFS(M57="Caja",1,M57="Configuración",2,M57="Desarrollo",3,M57="Desarrollo + Configuración",3,M57="No Aplica",0)*'Scoring Complejidad'!$C$6),"")} -> 2 | V57: {=IFERROR(_xlfn.IFS(U57="","",U57<=1.69,"Baja",U57<=2.29,"Media",U57<=3,"Alta",U57>3,"Error"),"")} -> Media | W57: 46174 | X57: 46174 | Y57: No Aplica | Z57: No Aplica | AA57: 46237 | AB57: 46262 | AC57: Should porque no rompen el flujo del onboarding No aplica diseño porque son cambios sencillos que no necesitan requerimientos técnicos | AD57: * Revisión de # de pantallas - Cecilia De Leon Modyo * Validar reusabilidad con Modyo
A58: HDU-TDC-R4-24 | B58: Apolo | C58: Validar titularidad del celular y disponibilidad por regla de 30 días. | D58: TDC | E58: Validación del teléfono | F58: Tras cumplir el formato, al dar clic en Continuar el sistema valida si el número está vinculado a un cliente ya verificado. Si no ha sido verificado por otro cliente en los últimos 30 días, continúa a OTP. Si está vinculado y en ventana de 30 días, muestra error específico. | G58: Validación tras formato correcto. Al Continuar: verifica si el número está vinculado a cliente verificado. Si vinculado y dentro de 30 días → error/bloqueo con mensaje aprobado. Si no vinculado o fuera de 30 días → continúa a OTP. Regla de 30 días parametrizable. | H58: Apolo (Onboarding digital — BB3 Validación de Teléfono) | I58: Prospecto TDC / Sistema | J58: Must | K58: Integración | L58: Pendiente | M58: No Aplica | N58: No Aplica | O58: 4 | P58: 0 | Q58: {=+_xlfn.IFS(O58="","",O58<=1,"Baja",O58<=3,"Media",O58>3,"Alta")} -> Alta | R58: {=+_xlfn.IFS(P58="","",P58<=0,"Baja",P58<=2,"Media",P58>2,"Alta")} -> Baja | S58: {=+_xlfn.IFS(N58="","",N58="Componentes existentes reutilizables >80%","Baja",N58="No Aplica","Baja",N58="Reutilización parcial 30-70%","Media",N58="Nuevo Desarrollo <20%","Alta")} -> Baja | T58: {=+_xlfn.IFS(L58="","",L58=0,"Baja",L58<=2,"Media",L58>=3,"Alta")} -> Alta | U58: {=+IFERROR((+_xlfn.IFS(Q58="",0,Q58="Baja",1,Q58="Media",2,Q58="Alta",3)*'Scoring Complejidad'!$C$8+_xlfn.IFS(R58="Baja",1,R58="Media",2,R58="Alta",3)*'Scoring Complejidad'!$C$9+_xlfn.IFS(S58="Baja",1,S58="Media",2,S58="Alta",3)*'Scoring Complejidad'!$C$7+_xlfn.IFS(T58="",1,T58="Baja",1,T58="Media",2,T58="Alta",3)*'Scoring Complejidad'!$C$5+_xlfn.IFS(M58="Caja",1,M58="Configuración",2,M58="Desarrollo",3,M58="Desarrollo + Configuración",3,M58="No Aplica",0)*'Scoring Complejidad'!$C$6),"")} -> 1.65 | V58: {=IFERROR(_xlfn.IFS(U58="","",U58<=1.69,"Baja",U58<=2.29,"Media",U58<=3,"Alta",U58>3,"Error"),"")} -> Baja | W58: 46179 | X58: 46237 | Y58: 46238 | Z58: 46261 | AA58: 46244 | AB58: 46310
A59: HDU-TDC-R4-25 | B59: Apolo | C59: Cancelar vínculo previo del número cuando la originación concluye exitosamente. | D59: TDC | E59: Integracion de Expediente digital | F59: Al completar exitosamente la originación (crédito dado de alta en SmartVista y producto TDC formalizado), el sistema cancela cualquier vinculación previa del número celular con otro cliente, asociándolo definitivamente al nuevo titular. | G59: Aplica al concluir exitosamente la originación (crédito en SV + producto TDC formalizado). Cancela vinculación previa del número con cualquier cliente anterior. Asocia el número definitivamente al nuevo titular. Regla de vinculación previa disponible. | H59: Apolo (Onboarding digital — BB16 Integración Expediente Digital) | I59: Sistema / BD Clientes | J59: Must | K59: Integración | L59: Pendiente | M59: No Aplica | N59: No Aplica | O59: 4 | P59: 8 | Q59: {=+_xlfn.IFS(O59="","",O59<=1,"Baja",O59<=3,"Media",O59>3,"Alta")} -> Alta | R59: {=+_xlfn.IFS(P59="","",P59<=0,"Baja",P59<=2,"Media",P59>2,"Alta")} -> Alta | S59: {=+_xlfn.IFS(N59="","",N59="Componentes existentes reutilizables >80%","Baja",N59="No Aplica","Baja",N59="Reutilización parcial 30-70%","Media",N59="Nuevo Desarrollo <20%","Alta")} -> Baja | T59: {=+_xlfn.IFS(L59="","",L59=0,"Baja",L59<=2,"Media",L59>=3,"Alta")} -> Alta | U59: {=+IFERROR((+_xlfn.IFS(Q59="",0,Q59="Baja",1,Q59="Media",2,Q59="Alta",3)*'Scoring Complejidad'!$C$8+_xlfn.IFS(R59="Baja",1,R59="Media",2,R59="Alta",3)*'Scoring Complejidad'!$C$9+_xlfn.IFS(S59="Baja",1,S59="Media",2,S59="Alta",3)*'Scoring Complejidad'!$C$7+_xlfn.IFS(T59="",1,T59="Baja",1,T59="Media",2,T59="Alta",3)*'Scoring Complejidad'!$C$5+_xlfn.IFS(M59="Caja",1,M59="Configuración",2,M59="Desarrollo",3,M59="Desarrollo + Configuración",3,M59="No Aplica",0)*'Scoring Complejidad'!$C$6),"")} -> 1.85 | V59: {=IFERROR(_xlfn.IFS(U59="","",U59<=1.69,"Baja",U59<=2.29,"Media",U59<=3,"Alta",U59>3,"Error"),"")} -> Media | W59: 46179 | X59: 46237 | Y59: 46238 | Z59: 46261 | AA59: 46244 | AB59: 46310
A60: HDU-TDC-R4-26 | B60: Apolo | C60: Gestionar reglas del OTP para validación telefónica. | D60: TDC | E60: Validación de telefono/ Validación SIC/Retomar solicitud | F60: El OTP de validación telefónica tiene vigencia de 10 minutos (parametrizable), hasta 3 reenvíos (4 mensajes en total), cada reenvío invalida el código anterior y reinicia el contador de espera de 1 minuto. Máximo 3 intentos de captura; al 4° se muestra TYP. | G60: OTP vigencia 10 minutos parametrizable. Hasta 3 reenvíos (4 mensajes totales). Cada reenvío invalida el código anterior y reinicia espera de 1 minuto. Máximo 3 intentos de captura. 4° intento: TYP con mensaje aprobado. Aplica en Validación Teléfono, Validación SIC y Retomar Solicitud. | H60: Apolo (Onboarding digital — BB3 Validación Teléfono / BB10 Validación SIC) | I60: Prospecto TDC / Sistema | J60: Should | K60: Solución | L60: 0 | M60: Desarrollo | N60: Reutilización parcial 30-70% | O60: 5 | P60: 0 | Q60: {=+_xlfn.IFS(O60="","",O60<=1,"Baja",O60<=3,"Media",O60>3,"Alta")} -> Alta | R60: {=+_xlfn.IFS(P60="","",P60<=0,"Baja",P60<=2,"Media",P60>2,"Alta")} -> Baja | S60: {=+_xlfn.IFS(N60="","",N60="Componentes existentes reutilizables >80%","Baja",N60="No Aplica","Baja",N60="Reutilización parcial 30-70%","Media",N60="Nuevo Desarrollo <20%","Alta")} -> Media | T60: {=+_xlfn.IFS(L60="","",L60=0,"Baja",L60<=2,"Media",L60>=3,"Alta")} -> Baja | U60: {=+IFERROR((+_xlfn.IFS(Q60="",0,Q60="Baja",1,Q60="Media",2,Q60="Alta",3)*'Scoring Complejidad'!$C$8+_xlfn.IFS(R60="Baja",1,R60="Media",2,R60="Alta",3)*'Scoring Complejidad'!$C$9+_xlfn.IFS(S60="Baja",1,S60="Media",2,S60="Alta",3)*'Scoring Complejidad'!$C$7+_xlfn.IFS(T60="",1,T60="Baja",1,T60="Media",2,T60="Alta",3)*'Scoring Complejidad'!$C$5+_xlfn.IFS(M60="Caja",1,M60="Configuración",2,M60="Desarrollo",3,M60="Desarrollo + Configuración",3,M60="No Aplica",0)*'Scoring Complejidad'!$C$6),"")} -> 2 | V60: {=IFERROR(_xlfn.IFS(U60="","",U60<=1.69,"Baja",U60<=2.29,"Media",U60<=3,"Alta",U60>3,"Error"),"")} -> Media | W60: 46174 | X60: 46174 | Y60: No Aplica | Z60: No Aplica | AA60: 46237 | AB60: 46262 | AC60: *Validar pantallas asociadas con Modyo *Son cambios en front sencillos por eso no aplica diseño *Fechas propuestas por Modyo. Pendiente validar fechas de implementación con Modyo
A61: HDU-TDC-R4-27 | B61: Apolo | C61: Asegurar máscara de SMS BanCoppel en mensajes OTP. | D61: TDC | E61: Validación de telefono/ Validación SIC/Retomar solicitud | F61: Los SMS de OTP deben enviarse con la máscara/remitente oficial BanCoppel (no un número genérico) y en español. Aplica a todos los códigos dinámicos del flujo de onboarding TDC R4. | G61: Máscara/remitente debe corresponder a BanCoppel. SMS en español (no inglés). Aplica a todos los OTPs del flujo TDC R4. Formato del mensaje bien definido. Dependencia del proveedor de SMS. Plantilla de mensaje validada por Negocio/Marketing. | H61: Apolo (Onboarding digital — BB3 Validación Teléfono / BB10 Validación SIC) | I61: Prospecto TDC | J61: Should | K61: Solución | L61: 0 | M61: Desarrollo | N61: Reutilización parcial 30-70% | O61: 4 | P61: 0 | Q61: {=+_xlfn.IFS(O61="","",O61<=1,"Baja",O61<=3,"Media",O61>3,"Alta")} -> Alta | R61: {=+_xlfn.IFS(P61="","",P61<=0,"Baja",P61<=2,"Media",P61>2,"Alta")} -> Baja | S61: {=+_xlfn.IFS(N61="","",N61="Componentes existentes reutilizables >80%","Baja",N61="No Aplica","Baja",N61="Reutilización parcial 30-70%","Media",N61="Nuevo Desarrollo <20%","Alta")} -> Media | T61: {=+_xlfn.IFS(L61="","",L61=0,"Baja",L61<=2,"Media",L61>=3,"Alta")} -> Baja | U61: {=+IFERROR((+_xlfn.IFS(Q61="",0,Q61="Baja",1,Q61="Media",2,Q61="Alta",3)*'Scoring Complejidad'!$C$8+_xlfn.IFS(R61="Baja",1,R61="Media",2,R61="Alta",3)*'Scoring Complejidad'!$C$9+_xlfn.IFS(S61="Baja",1,S61="Media",2,S61="Alta",3)*'Scoring Complejidad'!$C$7+_xlfn.IFS(T61="",1,T61="Baja",1,T61="Media",2,T61="Alta",3)*'Scoring Complejidad'!$C$5+_xlfn.IFS(M61="Caja",1,M61="Configuración",2,M61="Desarrollo",3,M61="Desarrollo + Configuración",3,M61="No Aplica",0)*'Scoring Complejidad'!$C$6),"")} -> 2 | V61: {=IFERROR(_xlfn.IFS(U61="","",U61<=1.69,"Baja",U61<=2.29,"Media",U61<=3,"Alta",U61>3,"Error"),"")} -> Media | W61: 46174 | X61: 46174 | Y61: No Aplica | Z61: No Aplica | AA61: 46237 | AB61: 46262 | AC61: *Validar pantallas asociadas con Modyo *Son cambios en front sencillos por eso no aplica diseño *Fechas propuestas por Modyo.Pendiente validar fechas de implementación con Modyo
A62: HDU-TDC-R4-34 | B62: Apolo | C62: Asignar sucursal corporativa parametrizable a la TDC BanCoppel. | D62: TDC | E62: Validación de domicilio / Intengración de expediente digital | F62: La TDC BanCoppel se asigna a la sucursal corporativa 6700 por defecto, de forma dinámica y parametrizable. Negocio podrá modificar el número sin desarrollo. Aplica en el proceso de creación del producto en SmartVista vía Apolo. | G62: Asignar sucursal corporativa 6700 por defecto. Número parametrizable; Negocio puede modificar sin desarrollo. Asignación dinámica al generar la TDC. Aplica en Validación de Domicilio e Integración de Expediente Digital. | H62: Apolo (Onboarding digital — BB6 Domicilio / BB16 Expediente) | I62: Sistema / SmartVista | J62: Should | K62: Integración | L62: Pendiente | M62: No Aplica | N62: No Aplica | O62: 2 | P62: 0 | Q62: {=+_xlfn.IFS(O62="","",O62<=1,"Baja",O62<=3,"Media",O62>3,"Alta")} -> Media | R62: {=+_xlfn.IFS(P62="","",P62<=0,"Baja",P62<=2,"Media",P62>2,"Alta")} -> Baja | S62: {=+_xlfn.IFS(N62="","",N62="Componentes existentes reutilizables >80%","Baja",N62="No Aplica","Baja",N62="Reutilización parcial 30-70%","Media",N62="Nuevo Desarrollo <20%","Alta")} -> Baja | T62: {=+_xlfn.IFS(L62="","",L62=0,"Baja",L62<=2,"Media",L62>=3,"Alta")} -> Alta | U62: {=+IFERROR((+_xlfn.IFS(Q62="",0,Q62="Baja",1,Q62="Media",2,Q62="Alta",3)*'Scoring Complejidad'!$C$8+_xlfn.IFS(R62="Baja",1,R62="Media",2,R62="Alta",3)*'Scoring Complejidad'!$C$9+_xlfn.IFS(S62="Baja",1,S62="Media",2,S62="Alta",3)*'Scoring Complejidad'!$C$7+_xlfn.IFS(T62="",1,T62="Baja",1,T62="Media",2,T62="Alta",3)*'Scoring Complejidad'!$C$5+_xlfn.IFS(M62="Caja",1,M62="Configuración",2,M62="Desarrollo",3,M62="Desarrollo + Configuración",3,M62="No Aplica",0)*'Scoring Complejidad'!$C$6),"")} -> 1.5 | V62: {=IFERROR(_xlfn.IFS(U62="","",U62<=1.69,"Baja",U62<=2.29,"Media",U62<=3,"Alta",U62>3,"Error"),"")} -> Baja | W62: 46179 | X62: 46237 | Y62: 46238 | Z62: 46261 | AA62: 46244 | AB62: 46310 | AC62: *Validar con Oscar Melo número de integraciones
A63: SMART-4219 | B63: APP | C63: Gestión de Tarjeta de Crédito Digital - Canal Apolo | D63: TDC | E63: Gestión de Tarjeta de Crédito Digital - Canal Apolo | F63: Pantalla "Tarjeta digital" accesible desde "Mis tarjetas". Permite al cliente visualizar datos de su TDC Digital (número, CLABE, vencimiento), controlar el encendido/apagado mediante switch y generar un CVV dinámico con temporizador de expiración. El botón "Eliminar tarjeta digital" está excluido en esta primera liberación por dependencia de servicio backend. | G63: 1. CVV dinámico requiere: tarjeta activa + geolocalización del dispositivo habilitada + bandera firebase show_generate_cvv = true. 2. Botón "Generar CVV" inhabilitado (gris) si la tarjeta tiene bloqueo temporal u operativo, o si ya hay un CVV visible con temporizador corriendo. 3. Al expirar el temporizador (0:00), el código se oculta y se rehabilita el botón. 4. Sin geolocalización activa: alerta diferenciada por SO (iOS: ID:000264 / Android: ID:000257). 5. Fallo en servicio CVV: alerta con ID:000031. | H63: App — canal Apolo | I63: Cliente BanCoppel con TDC Digital originada por canal Apolo | J63: Must | K63: Solución | L63: 0 | M63: Desarrollo | N63: Nuevo Desarrollo <20% | O63: 12 | P63: 1 | Q63: {=+_xlfn.IFS(O63="","",O63<=1,"Baja",O63<=3,"Media",O63>3,"Alta")} -> Alta | R63: {=+_xlfn.IFS(P63="","",P63<=0,"Baja",P63<=2,"Media",P63>2,"Alta")} -> Media | S63: {=+_xlfn.IFS(N63="","",N63="Componentes existentes reutilizables >80%","Baja",N63="No Aplica","Baja",N63="Reutilización parcial 30-70%","Media",N63="Nuevo Desarrollo <20%","Alta")} -> Alta | T63: {=+_xlfn.IFS(L63="","",L63=0,"Baja",L63<=2,"Media",L63>=3,"Alta")} -> Baja | U63: {=+IFERROR((+_xlfn.IFS(Q63="",0,Q63="Baja",1,Q63="Media",2,Q63="Alta",3)*'Scoring Complejidad'!$C$8+_xlfn.IFS(R63="Baja",1,R63="Media",2,R63="Alta",3)*'Scoring Complejidad'!$C$9+_xlfn.IFS(S63="Baja",1,S63="Media",2,S63="Alta",3)*'Scoring Complejidad'!$C$7+_xlfn.IFS(T63="",1,T63="Baja",1,T63="Media",2,T63="Alta",3)*'Scoring Complejidad'!$C$5+_xlfn.IFS(M63="Caja",1,M63="Configuración",2,M63="Desarrollo",3,M63="Desarrollo + Configuración",3,M63="No Aplica",0)*'Scoring Complejidad'!$C$6),"")} -> 2.3 | V63: {=IFERROR(_xlfn.IFS(U63="","",U63<=1.69,"Baja",U63<=2.29,"Media",U63<=3,"Alta",U63>3,"Error"),"")} -> Alta | W63: 46181 | X63: 46192 | Y63: 46195 | Z63: 29/06/206 | AA63: 46195 | AB63: 46241 | AC63: HU Prioridad 1 Diseño: Diagramas de flujo de solución. Se utilizaran integraciones actuales | AD63: 46238
A64: SMART-3964 | B64: APP | C64: Gestión de Tarjeta de Crédito Física - Canal Apolo | D64: TDC | E64: Gestión de Tarjeta de Crédito Física - Canal Apolo | F64: Pantalla "Tarjeta física" accesible desde "Mis tarjetas". Muestra datos de la TDC física originada por canal Apolo: número de tarjeta, CLABE, fecha de vencimiento, estado (activa/bloqueada), switch encendido/apagado y restricción de CVV dinámico (no aplica para plásticos físicos Apolo). | G64: 1. Switch de estado: al alternarlo activa el flujo de encendido/apagado de TDC Física y Digital (ver SMART-3965). 2. CVV dinámico NO aplica para plásticos físicos del canal Apolo — al pie de pantalla solo se muestra texto fijo, sin botón de generación. 3. Número de tarjeta: 16 dígitos, copiable al portapapeles. 4. CLABE: 18 dígitos, copiable al portapapeles. 5. Bloqueo operativo se indica con ícono de prohibición en amarillo; bloqueo temporal con ícono de apagado gris. | H64: App | I64: Cliente BanCoppel con tarjeta de crédito física del canal Apolo | J64: Must | K64: Solución | L64: 0 | M64: Desarrollo | N64: Nuevo Desarrollo <20% | O64: 4 | P64: 1 | Q64: {=+_xlfn.IFS(O64="","",O64<=1,"Baja",O64<=3,"Media",O64>3,"Alta")} -> Alta | R64: {=+_xlfn.IFS(P64="","",P64<=0,"Baja",P64<=2,"Media",P64>2,"Alta")} -> Media | S64: {=+_xlfn.IFS(N64="","",N64="Componentes existentes reutilizables >80%","Baja",N64="No Aplica","Baja",N64="Reutilización parcial 30-70%","Media",N64="Nuevo Desarrollo <20%","Alta")} -> Alta | T64: {=+_xlfn.IFS(L64="","",L64=0,"Baja",L64<=2,"Media",L64>=3,"Alta")} -> Baja | U64: {=+IFERROR((+_xlfn.IFS(Q64="",0,Q64="Baja",1,Q64="Media",2,Q64="Alta",3)*'Scoring Complejidad'!$C$8+_xlfn.IFS(R64="Baja",1,R64="Media",2,R64="Alta",3)*'Scoring Complejidad'!$C$9+_xlfn.IFS(S64="Baja",1,S64="Media",2,S64="Alta",3)*'Scoring Complejidad'!$C$7+_xlfn.IFS(T64="",1,T64="Baja",1,T64="Media",2,T64="Alta",3)*'Scoring Complejidad'!$C$5+_xlfn.IFS(M64="Caja",1,M64="Configuración",2,M64="Desarrollo",3,M64="Desarrollo + Configuración",3,M64="No Aplica",0)*'Scoring Complejidad'!$C$6),"")} -> 2.3 | V64: {=IFERROR(_xlfn.IFS(U64="","",U64<=1.69,"Baja",U64<=2.29,"Media",U64<=3,"Alta",U64>3,"Error"),"")} -> Alta | W64: 46181 | X64: 46192 | Y64: 46206 | Z64: 46210 | AA64: 46209 | AB64: 46241 | AC64: HU Prioridad 1 Diseño: Diagramas de flujo de solución. Se utilizaran integraciones actuales | AD64: 46238
A65: SMART-4226 | B65: APP | C65: Gestión de Tarjeta de Crédito Física - Modelo Legado | D65: TDC | E65: Gestión de Tarjeta de Crédito Física - Modelo Legado | F65: Pantalla "Tarjeta física" accesible desde el Dashboard para clientes con TDC Física originada en Legado. Permite visualizar datos de la tarjeta (número, CLABE, vencimiento), controlar encendido/apagado mediante switch y generar CVV dinámico con temporizador. Equivalente funcional de SMART-4219 pero para el canal Legado. | G65: 1. CVV dinámico aplica también a TDC Física Legado con las mismas condiciones: geolocalización activa + bandera show_generate_cvv = true. 2. Botón "Generar CVV" inhabilitado con bloqueo temporal u operativo. 3. Nombre de la tarjeta se toma dinámicamente de la base de datos (ej: "TARJETA DE CREDITO BANCOPPEL ORO"). 4. Switch activa flujo SMART-3965 (Encendido/Apagado) | H65: App BanCoppel — canal Legado | I65: Cliente productivo BanCoppel con TDC Física Legado | J65: Must | K65: Solución | L65: 0 | M65: Desarrollo | N65: Nuevo Desarrollo <20% | O65: 10 | P65: 1 | Q65: {=+_xlfn.IFS(O65="","",O65<=1,"Baja",O65<=3,"Media",O65>3,"Alta")} -> Alta | R65: {=+_xlfn.IFS(P65="","",P65<=0,"Baja",P65<=2,"Media",P65>2,"Alta")} -> Media | S65: {=+_xlfn.IFS(N65="","",N65="Componentes existentes reutilizables >80%","Baja",N65="No Aplica","Baja",N65="Reutilización parcial 30-70%","Media",N65="Nuevo Desarrollo <20%","Alta")} -> Alta | T65: {=+_xlfn.IFS(L65="","",L65=0,"Baja",L65<=2,"Media",L65>=3,"Alta")} -> Baja | U65: {=+IFERROR((+_xlfn.IFS(Q65="",0,Q65="Baja",1,Q65="Media",2,Q65="Alta",3)*'Scoring Complejidad'!$C$8+_xlfn.IFS(R65="Baja",1,R65="Media",2,R65="Alta",3)*'Scoring Complejidad'!$C$9+_xlfn.IFS(S65="Baja",1,S65="Media",2,S65="Alta",3)*'Scoring Complejidad'!$C$7+_xlfn.IFS(T65="",1,T65="Baja",1,T65="Media",2,T65="Alta",3)*'Scoring Complejidad'!$C$5+_xlfn.IFS(M65="Caja",1,M65="Configuración",2,M65="Desarrollo",3,M65="Desarrollo + Configuración",3,M65="No Aplica",0)*'Scoring Complejidad'!$C$6),"")} -> 2.3 | V65: {=IFERROR(_xlfn.IFS(U65="","",U65<=1.69,"Baja",U65<=2.29,"Media",U65<=3,"Alta",U65>3,"Error"),"")} -> Alta | W65: 46181 | X65: 46192 | Y65: 46209 | Z65: 46220 | AA65: 46223 | AB65: 46241 | AC65: HU Prioridad 1 Diseño: Diagramas de flujo de solución. Se utilizaran integraciones actuales | AD65: 46238
B66: APP | C66: Encendido, Apagado y Bloqueo Operativo - Tarjeta de Crédito Digital (Originación Apolo) | D66: TDC | E66: Encendido y Apagado TDC Física y Digital | F66: Flujo de encendido/apagado de TDC Física y/o Digital activado desde el switch en Gestión de TDC Digital. Presenta diálogo de confirmación con implicaciones del apagado y actualiza el ícono de estado en home de cuentas y en "Mis tarjetas" según la combinación activa del cliente. | G66: 1. El encendido/apagado refleja el estado en home de cuentas de acuerdo a la combinación de tarjetas activa al momento. 2. Al apagar: pagos automáticos (domiciliaciones) continúan procesándose. 3. Al apagar: la tarjeta no puede usarse para compras ni retiros. 4. El cliente puede reencender la tarjeta en cualquier momento. | H66: App | I66: Cliente BanCoppel con TDC Digital | J66: Must | K66: Solución | L66: 0 | M66: Desarrollo | N66: Componentes existentes reutilizables >80% | O66: 7 | P66: 2 | Q66: {=+_xlfn.IFS(O66="","",O66<=1,"Baja",O66<=3,"Media",O66>3,"Alta")} -> Alta | R66: {=+_xlfn.IFS(P66="","",P66<=0,"Baja",P66<=2,"Media",P66>2,"Alta")} -> Media | S66: {=+_xlfn.IFS(N66="","",N66="Componentes existentes reutilizables >80%","Baja",N66="No Aplica","Baja",N66="Reutilización parcial 30-70%","Media",N66="Nuevo Desarrollo <20%","Alta")} -> Baja | T66: {=+_xlfn.IFS(L66="","",L66=0,"Baja",L66<=2,"Media",L66>=3,"Alta")} -> Baja | U66: {=+IFERROR((+_xlfn.IFS(Q66="",0,Q66="Baja",1,Q66="Media",2,Q66="Alta",3)*'Scoring Complejidad'!$C$8+_xlfn.IFS(R66="Baja",1,R66="Media",2,R66="Alta",3)*'Scoring Complejidad'!$C$9+_xlfn.IFS(S66="Baja",1,S66="Media",2,S66="Alta",3)*'Scoring Complejidad'!$C$7+_xlfn.IFS(T66="",1,T66="Baja",1,T66="Media",2,T66="Alta",3)*'Scoring Complejidad'!$C$5+_xlfn.IFS(M66="Caja",1,M66="Configuración",2,M66="Desarrollo",3,M66="Desarrollo + Configuración",3,M66="No Aplica",0)*'Scoring Complejidad'!$C$6),"")} -> 1.9 | V66: {=IFERROR(_xlfn.IFS(U66="","",U66<=1.69,"Baja",U66<=2.29,"Media",U66<=3,"Alta",U66>3,"Error"),"")} -> Media | W66: 46223 | X66: 46234 | Y66: 46237 | Z66: 46239 | AA66: 46244 | AB66: 14/08/206 | AC66: ID pendiente, pendiente de creación en JIRA - ID funcionalidad en relación 3965 Fechas de implementación impactado por las dependencias de definiciones de UX, ambientes de ambiente de desarrollo, sin enrolamiento semana y media de las 3 primeras Hus (4219,3964,4226) | AD66: 46238
B67: APP | C67: Encendido, Apagado y Bloqueo Operativo - Tarjeta de Crédito Física (Originación Apolo) | D67: TDC | E67: Encendido y Apagado TDC Física y Digital | F67: Flujo de encendido/apagado de TDC Física y/o Digital activado desde el switch en Gestión de Tarjeta Física. Presenta diálogo de confirmación con implicaciones del apagado y actualiza el ícono de estado en home de cuentas y en "Mis tarjetas" según la combinación activa del cliente. | G67: 1. El encendido/apagado refleja el estado en home de cuentas de acuerdo a la combinación de tarjetas activa al momento. 2. Al apagar: pagos automáticos (domiciliaciones) continúan procesándose. 3. Al apagar: la tarjeta no puede usarse para compras ni retiros. 4. El cliente puede reencender la tarjeta en cualquier momento. | H67: App | I67: Cliente BanCoppel con TDC Física | J67: Must | K67: Solución | L67: 0 | M67: Desarrollo | N67: Componentes existentes reutilizables >80% | O67: 6 | P67: 2 | Q67: {=+_xlfn.IFS(O67="","",O67<=1,"Baja",O67<=3,"Media",O67>3,"Alta")} -> Alta | R67: {=+_xlfn.IFS(P67="","",P67<=0,"Baja",P67<=2,"Media",P67>2,"Alta")} -> Media | S67: {=+_xlfn.IFS(N67="","",N67="Componentes existentes reutilizables >80%","Baja",N67="No Aplica","Baja",N67="Reutilización parcial 30-70%","Media",N67="Nuevo Desarrollo <20%","Alta")} -> Baja | T67: {=+_xlfn.IFS(L67="","",L67=0,"Baja",L67<=2,"Media",L67>=3,"Alta")} -> Baja | U67: {=+IFERROR((+_xlfn.IFS(Q67="",0,Q67="Baja",1,Q67="Media",2,Q67="Alta",3)*'Scoring Complejidad'!$C$8+_xlfn.IFS(R67="Baja",1,R67="Media",2,R67="Alta",3)*'Scoring Complejidad'!$C$9+_xlfn.IFS(S67="Baja",1,S67="Media",2,S67="Alta",3)*'Scoring Complejidad'!$C$7+_xlfn.IFS(T67="",1,T67="Baja",1,T67="Media",2,T67="Alta",3)*'Scoring Complejidad'!$C$5+_xlfn.IFS(M67="Caja",1,M67="Configuración",2,M67="Desarrollo",3,M67="Desarrollo + Configuración",3,M67="No Aplica",0)*'Scoring Complejidad'!$C$6),"")} -> 1.9 | V67: {=IFERROR(_xlfn.IFS(U67="","",U67<=1.69,"Baja",U67<=2.29,"Media",U67<=3,"Alta",U67>3,"Error"),"")} -> Media | W67: 46223 | X67: 46234 | Y67: 46237 | Z67: 46239 | AA67: Pendiente de definición de Sprint | AB67: Pendiente de definición de Sprint | AC67: ID pendiente, pendiente de creación en JIRA / ID funcionalidad en relación 3965 Fechas de implementación impactado por las dependencias de definiciones de UX, ambientes de ambiente de desarrollo, sin enrolamiento semana y media de las 3 primeras Hus (4219,3964,4226) Pendiente de fechas de implementación - Guissel Gomez | AD67: 46238
B68: APP | C68: Encendido, Apagado y Bloqueo Operativo - Tarjeta de Crédito Física (Originación Legado) | D68: TDC | E68: Encendido y Apagado TDC Física y Digital | F68: Flujo de encendido/apagado de TDC Física y/o Digital activado desde el switch en Gestión de Tarjeta Física. Presenta diálogo de confirmación con implicaciones del apagado y actualiza el ícono de estado en home de cuentas y en "Mis tarjetas" según la combinación activa del cliente. (Legado) | G68: 1. El encendido/apagado refleja el estado en home de cuentas de acuerdo a la combinación de tarjetas activa al momento. 2. Al apagar: pagos automáticos (domiciliaciones) continúan procesándose. 3. Al apagar: la tarjeta no puede usarse para compras ni retiros. 4. El cliente puede reencender la tarjeta en cualquier momento. | H68: App | I68: Cliente BanCoppel con TDC Física | J68: Must | K68: Solución | L68: 0 | M68: Desarrollo | N68: Componentes existentes reutilizables >80% | P68: 2 | Q68: {=+_xlfn.IFS(O68="","",O68<=1,"Baja",O68<=3,"Media",O68>3,"Alta")} | R68: {=+_xlfn.IFS(P68="","",P68<=0,"Baja",P68<=2,"Media",P68>2,"Alta")} -> Media | S68: {=+_xlfn.IFS(N68="","",N68="Componentes existentes reutilizables >80%","Baja",N68="No Aplica","Baja",N68="Reutilización parcial 30-70%","Media",N68="Nuevo Desarrollo <20%","Alta")} -> Baja | T68: {=+_xlfn.IFS(L68="","",L68=0,"Baja",L68<=2,"Media",L68>=3,"Alta")} -> Baja | U68: {=+IFERROR((+_xlfn.IFS(Q68="",0,Q68="Baja",1,Q68="Media",2,Q68="Alta",3)*'Scoring Complejidad'!$C$8+_xlfn.IFS(R68="Baja",1,R68="Media",2,R68="Alta",3)*'Scoring Complejidad'!$C$9+_xlfn.IFS(S68="Baja",1,S68="Media",2,S68="Alta",3)*'Scoring Complejidad'!$C$7+_xlfn.IFS(T68="",1,T68="Baja",1,T68="Media",2,T68="Alta",3)*'Scoring Complejidad'!$C$5+_xlfn.IFS(M68="Caja",1,M68="Configuración",2,M68="Desarrollo",3,M68="Desarrollo + Configuración",3,M68="No Aplica",0)*'Scoring Complejidad'!$C$6),"")} -> 1.45 | V68: {=IFERROR(_xlfn.IFS(U68="","",U68<=1.69,"Baja",U68<=2.29,"Media",U68<=3,"Alta",U68>3,"Error"),"")} -> Baja | W68: 46223 | X68: 46234 | Y68: 46237 | Z68: 46239 | AA68: Pendiente de definición de Sprint | AB68: Pendiente de definición de Sprint | AC68: ID pendiente, pendiente de creación en JIRA / ID funcionalidad en relación 3965 Criterios de aceptacion pendientes por dependencia de UX Fechas de implementación impactado por las dependencias de definiciones de UX, ambientes de ambiente de desarrollo, sin enrolamiento semana y media de las 3 primeras Hus (4219,3964,4226) Pendiente de fechas de implementación - Guissel Gomez | AD68: 46238
A69: SMART-3963 | B69: APP | C69: Tarjetas Asociadas Física y Digital | D69: TDC | E69: Tarjetas Asociadas Física y Digital | F69: Pantalla "Mis tarjetas asociadas" accesible desde el home de cuentas o desde el detalle de TDC. Muestra en un solo módulo la TDC Física y la TDC Digital del cliente con su estatus individual, permitiendo navegar al detalle de gestión de cada una mediante chevron de acción. | G69: 1. Si el cliente solo tiene TDC Física activa, esa es la que usa para acceder al detalle. 2. Si el cliente solo tiene TDC Digital activa, esa es la que usa. 3. Cada tarjeta muestra su propio indicador de estatus (Activa / Apagada / Inactiva / Bloqueada por Fraude / Bloqueo operativo). 4. TDC Digital bloqueada por fraude redirige al mapa de sucursales. 5. TDC Digital Inactiva muestra badge "Nuevo" y botón de activación. | H69: App | I69: Cliente BanCoppel con TDC Física y/o Digital | J69: Must | K69: Solución | L69: 0 | M69: Desarrollo | N69: Nuevo Desarrollo <20% | O69: 24 | P69: 1 | Q69: {=+_xlfn.IFS(O69="","",O69<=1,"Baja",O69<=3,"Media",O69>3,"Alta")} -> Alta | R69: {=+_xlfn.IFS(P69="","",P69<=0,"Baja",P69<=2,"Media",P69>2,"Alta")} -> Media | S69: {=+_xlfn.IFS(N69="","",N69="Componentes existentes reutilizables >80%","Baja",N69="No Aplica","Baja",N69="Reutilización parcial 30-70%","Media",N69="Nuevo Desarrollo <20%","Alta")} -> Alta | T69: {=+_xlfn.IFS(L69="","",L69=0,"Baja",L69<=2,"Media",L69>=3,"Alta")} -> Baja | U69: {=+IFERROR((+_xlfn.IFS(Q69="",0,Q69="Baja",1,Q69="Media",2,Q69="Alta",3)*'Scoring Complejidad'!$C$8+_xlfn.IFS(R69="Baja",1,R69="Media",2,R69="Alta",3)*'Scoring Complejidad'!$C$9+_xlfn.IFS(S69="Baja",1,S69="Media",2,S69="Alta",3)*'Scoring Complejidad'!$C$7+_xlfn.IFS(T69="",1,T69="Baja",1,T69="Media",2,T69="Alta",3)*'Scoring Complejidad'!$C$5+_xlfn.IFS(M69="Caja",1,M69="Configuración",2,M69="Desarrollo",3,M69="Desarrollo + Configuración",3,M69="No Aplica",0)*'Scoring Complejidad'!$C$6),"")} -> 2.3 | V69: {=IFERROR(_xlfn.IFS(U69="","",U69<=1.69,"Baja",U69<=2.29,"Media",U69<=3,"Alta",U69>3,"Error"),"")} -> Alta | W69: 46240 | X69: 46245 | Y69: 46246 | Z69: 46248 | AA69: 46251 | AB69: 46276 | AC69: Criterios de aceptación con posible actualización Fecha tentativa de implementación por confirmar por impacto en retraso de HUs anteriores | AD69: 46238
A70: SMART-3966 | B70: APP | C70: Activación de TDC Digital | D70: TDC | E70: Activación de TDC Digital | F70: Flujo de activación de TDC Digital desde "Mis tarjetas asociadas". Al detectar una TDC Digital en estado "disponible para activar", muestra un toaster con CTA "Activar ahora" que invoca el flujo de Token Digital. Una vez activada exitosamente, la tarjeta se refleja como activa en "Mis tarjetas" y en el home de cuentas. | G70: 1. El card de activación solo se muestra si existe TDC Digital en estado "disponible para activar" (empty state). 2. La activación requiere validación mediante flujo de Token Digital. 3. Si el flujo de Token Digital falla (error, timeout o cancelación), la TDC Digital no se activa y el estado de la pantalla no cambia. 4. Al cancelar ("Activar en otro momento"), el toaster se oculta pero el card de activación con badge "nueva" permanece visible. 5. Activación exitosa: TDC Digital visible como activa en "Mis tarjetas" y en home de cuentas. | H70: App | I70: Cliente BanCoppel con TDC Digital disponible para activar | J70: Must | K70: Solución | L70: 0 | M70: Desarrollo | N70: Componentes existentes reutilizables >80% | O70: 4 | P70: 3 | Q70: {=+_xlfn.IFS(O70="","",O70<=1,"Baja",O70<=3,"Media",O70>3,"Alta")} -> Alta | R70: {=+_xlfn.IFS(P70="","",P70<=0,"Baja",P70<=2,"Media",P70>2,"Alta")} -> Alta | S70: {=+_xlfn.IFS(N70="","",N70="Componentes existentes reutilizables >80%","Baja",N70="No Aplica","Baja",N70="Reutilización parcial 30-70%","Media",N70="Nuevo Desarrollo <20%","Alta")} -> Baja | T70: {=+_xlfn.IFS(L70="","",L70=0,"Baja",L70<=2,"Media",L70>=3,"Alta")} -> Baja | U70: {=+IFERROR((+_xlfn.IFS(Q70="",0,Q70="Baja",1,Q70="Media",2,Q70="Alta",3)*'Scoring Complejidad'!$C$8+_xlfn.IFS(R70="Baja",1,R70="Media",2,R70="Alta",3)*'Scoring Complejidad'!$C$9+_xlfn.IFS(S70="Baja",1,S70="Media",2,S70="Alta",3)*'Scoring Complejidad'!$C$7+_xlfn.IFS(T70="",1,T70="Baja",1,T70="Media",2,T70="Alta",3)*'Scoring Complejidad'!$C$5+_xlfn.IFS(M70="Caja",1,M70="Configuración",2,M70="Desarrollo",3,M70="Desarrollo + Configuración",3,M70="No Aplica",0)*'Scoring Complejidad'!$C$6),"")} -> 2 | V70: {=IFERROR(_xlfn.IFS(U70="","",U70<=1.69,"Baja",U70<=2.29,"Media",U70<=3,"Alta",U70>3,"Error"),"")} -> Media | W70: 46251 | X70: 46255 | Y70: 46258 | Z70: 46262 | AA70: 46265 | AB70: 46276 | AC70: Fecha tentativa de implementación por confirmar por impacto en retraso de HUs anteriores | AD70: 46238
A71: SMART-4531 | B71: APP | C71: Convivencia en Home de Cuentas TDC F&D | D71: TDC | E71: Convivencia en Home de Cuentas TDC F&D | F71: Card de TDC en el Home de Cuentas de la App BanCoppel que muestra dinámicamente la convivencia entre TDC Física y Digital. El card adapta su apariencia (color, íconos, datos mostrados) según el estado y combinación de tarjetas activas del cliente en ese momento. Al hacer tap navega al detalle de la TDC (SMART-3962). | G71: 1. Aplica para TDC con BIN 42680711, número de producto 4900, o migradas a SmartVista. 2. El card muestra el estado de convivencia F&D en la esquina inferior derecha mediante íconos: círculo amarillo = activa, ícono apagado = bloqueo temporal/operativo, ícono bloqueo = inactiva. 3. Card azul cuando al menos una tarjeta está activa/encendida; card gris cuando ambas están apagadas o inactivas. 4. Solo digital encendida: muestra últimos 4 dígitos enmascarados y vigencia de la TDC Digital. 5. Solo física encendida o apagada: muestra últimos 4 dígitos enmascarados y vigencia de la TDC Física. | H71: App | I71: Cliente BanCoppel con al menos una TDC activa (Física o Digital) | J71: Must | K71: Solución | L71: 0 | M71: Desarrollo | N71: Nuevo Desarrollo <20% | O71: 2 | P71: 1 | Q71: {=+_xlfn.IFS(O71="","",O71<=1,"Baja",O71<=3,"Media",O71>3,"Alta")} -> Media | R71: {=+_xlfn.IFS(P71="","",P71<=0,"Baja",P71<=2,"Media",P71>2,"Alta")} -> Media | S71: {=+_xlfn.IFS(N71="","",N71="Componentes existentes reutilizables >80%","Baja",N71="No Aplica","Baja",N71="Reutilización parcial 30-70%","Media",N71="Nuevo Desarrollo <20%","Alta")} -> Alta | T71: {=+_xlfn.IFS(L71="","",L71=0,"Baja",L71<=2,"Media",L71>=3,"Alta")} -> Baja | U71: {=+IFERROR((+_xlfn.IFS(Q71="",0,Q71="Baja",1,Q71="Media",2,Q71="Alta",3)*'Scoring Complejidad'!$C$8+_xlfn.IFS(R71="Baja",1,R71="Media",2,R71="Alta",3)*'Scoring Complejidad'!$C$9+_xlfn.IFS(S71="Baja",1,S71="Media",2,S71="Alta",3)*'Scoring Complejidad'!$C$7+_xlfn.IFS(T71="",1,T71="Baja",1,T71="Media",2,T71="Alta",3)*'Scoring Complejidad'!$C$5+_xlfn.IFS(M71="Caja",1,M71="Configuración",2,M71="Desarrollo",3,M71="Desarrollo + Configuración",3,M71="No Aplica",0)*'Scoring Complejidad'!$C$6),"")} -> 2.15 | V71: {=IFERROR(_xlfn.IFS(U71="","",U71<=1.69,"Baja",U71<=2.29,"Media",U71<=3,"Alta",U71>3,"Error"),"")} -> Media | W71: 46265 | X71: 46269 | Y71: 46272 | Z71: 46276 | AA71: 46279 | AB71: 46304 | AC71: Criterios de aceptación con posible actualización Fecha tentativa de implementación por confirmar por impacto en retraso de HUs anteriores | AD71: 46238
A72: SMART-3962 | B72: APP | C72: Detalle de crédito convivencia TDC F&D | D72: TDC | E72: Detalle de crédito convivencia TDC F&D | F72: Pantalla "Detalle de tu tarjeta de crédito" accesible desde el home de cuentas. Muestra información de crédito utilizado, fecha de corte, crédito disponible, crédito total, botonera dinámica y movimientos de los últimos 30 días. El comportamiento visual de la sección "Crédito utilizado" cambia dinámicamente según el estado de pago del cliente. | G72: 1. Cuenta corriente: aplica cuando fecha actual es previa a fecha de corte. 2. Pago para no generar intereses: periodo posterior a corte, antes de fecha límite de pago. 3. Pago realizado: cliente pagó a tiempo y antes de fecha límite. 4. Saldo a favor: pago superior al total adeudado — saldo positivo se aplica a futuras compras. 5. Pago vencido: genera intereses moratorios al 5.5% mensual, bloquea la tarjeta y afecta historial en buró. | H72: App | I72: Cliente BanCoppel con TDC Física y/o Digital activa | J72: Must | K72: Solución e Integración | L72: 1 | M72: Desarrollo | N72: Nuevo Desarrollo <20% | O72: 7 | P72: 1 | Q72: {=+_xlfn.IFS(O72="","",O72<=1,"Baja",O72<=3,"Media",O72>3,"Alta")} -> Alta | R72: {=+_xlfn.IFS(P72="","",P72<=0,"Baja",P72<=2,"Media",P72>2,"Alta")} -> Media | S72: {=+_xlfn.IFS(N72="","",N72="Componentes existentes reutilizables >80%","Baja",N72="No Aplica","Baja",N72="Reutilización parcial 30-70%","Media",N72="Nuevo Desarrollo <20%","Alta")} -> Alta | T72: {=+_xlfn.IFS(L72="","",L72=0,"Baja",L72<=2,"Media",L72>=3,"Alta")} -> Media | U72: {=+IFERROR((+_xlfn.IFS(Q72="",0,Q72="Baja",1,Q72="Media",2,Q72="Alta",3)*'Scoring Complejidad'!$C$8+_xlfn.IFS(R72="Baja",1,R72="Media",2,R72="Alta",3)*'Scoring Complejidad'!$C$9+_xlfn.IFS(S72="Baja",1,S72="Media",2,S72="Alta",3)*'Scoring Complejidad'!$C$7+_xlfn.IFS(T72="",1,T72="Baja",1,T72="Media",2,T72="Alta",3)*'Scoring Complejidad'!$C$5+_xlfn.IFS(M72="Caja",1,M72="Configuración",2,M72="Desarrollo",3,M72="Desarrollo + Configuración",3,M72="No Aplica",0)*'Scoring Complejidad'!$C$6),"")} -> 2.6 | V72: {=IFERROR(_xlfn.IFS(U72="","",U72<=1.69,"Baja",U72<=2.29,"Media",U72<=3,"Alta",U72>3,"Error"),"")} -> Alta | W72: 46279 | X72: 46290 | Y72: 46293 | Z72: 46304 | AA72: 46307 | AB72: 46332 | AC72: Criterios de aceptación con posible actualización Fecha tentativa de implementación por confirmar por impacto en retraso de HUs anteriores | AD72: 46238
A73: PTCSF-6267 | B73: APP | C73: Actualizar operaciones TDC Digital en una misma sesión | D73: TDC | E73: Actualizar operaciones TDC Digital en una misma sesión | F73: Corrección técnica en la App Móvil para permitir realizar más de un pago de TDC dentro de la misma sesión activa.Actualmente el segundo intento de pago en la misma sesión falla con error HTTP 500. | G73: 1.El cliente debe poder realizar múltiples pagos de TDC en una misma sesión activa sin restricción de frecuencia por sesión. | H73: App | I73: Cliente BanCoppel con TDC Digital activa | J73: Must | K73: Solución | L73: 0 | M73: Desarrollo | N73: Nuevo Desarrollo <20% | O73: 1 | P73: 0 | Q73: {=+_xlfn.IFS(O73="","",O73<=1,"Baja",O73<=3,"Media",O73>3,"Alta")} -> Baja | R73: {=+_xlfn.IFS(P73="","",P73<=0,"Baja",P73<=2,"Media",P73>2,"Alta")} -> Baja | S73: {=+_xlfn.IFS(N73="","",N73="Componentes existentes reutilizables >80%","Baja",N73="No Aplica","Baja",N73="Reutilización parcial 30-70%","Media",N73="Nuevo Desarrollo <20%","Alta")} -> Alta | T73: {=+_xlfn.IFS(L73="","",L73=0,"Baja",L73<=2,"Media",L73>=3,"Alta")} -> Baja | U73: {=+IFERROR((+_xlfn.IFS(Q73="",0,Q73="Baja",1,Q73="Media",2,Q73="Alta",3)*'Scoring Complejidad'!$C$8+_xlfn.IFS(R73="Baja",1,R73="Media",2,R73="Alta",3)*'Scoring Complejidad'!$C$9+_xlfn.IFS(S73="Baja",1,S73="Media",2,S73="Alta",3)*'Scoring Complejidad'!$C$7+_xlfn.IFS(T73="",1,T73="Baja",1,T73="Media",2,T73="Alta",3)*'Scoring Complejidad'!$C$5+_xlfn.IFS(M73="Caja",1,M73="Configuración",2,M73="Desarrollo",3,M73="Desarrollo + Configuración",3,M73="No Aplica",0)*'Scoring Complejidad'!$C$6),"")} -> 1.9 | V73: {=IFERROR(_xlfn.IFS(U73="","",U73<=1.69,"Baja",U73<=2.29,"Media",U73<=3,"Alta",U73>3,"Error"),"")} -> Media | W73: Completado en R3 | X73: Completado en R3 | Y73: Completado en R3 | Z73: Completado en R3 | AA73: 46321 | AB73: 46332 | AC73: Cambio a nivel de headers. HU que se dejo como backlog en R3- Finalizo en el R3 Análisis y diseño ya completado | AD73: 46240
A74: SMART-4182 | B74: APP | C74: Visualización y aplicación de montos de pago en Línea TDC | D74: TDC | E74: Visualización y aplicación de montos de pago en Línea TDC | F74: Actualización en tiempo real de los campos de pago (pago mínimo, pago para no generar intereses y saldo a la fecha) en la pantalla "Detalle de TDC" tras realizar uno o más pagos desde la app. Los montos se recalculan y reflejan inmediatamente al completarse el pago. | G74: 1. El crédito debe haber pasado por proceso de corte para que apliquen los montos de pago. 2. Los montos (pago mínimo, pago para no generar intereses, saldo a la fecha) se actualizan en tiempo real tras cada pago. 3. Saldo a favor: se muestra con valor negativo en "Saldo a la fecha". 4. El monto a favor no debe rebasar $15,000 cuando la línea de crédito es ≤ $24,999; ni el 20% del crédito cuando la línea rebasa $25,000. | H74: App | I74: Cliente BanCoppel con TDC activa | J74: Must | K74: Integración | L74: 1 | M74: No Aplica | N74: No Aplica | O74: 0 | P74: 0 | Q74: {=+_xlfn.IFS(O74="","",O74<=1,"Baja",O74<=3,"Media",O74>3,"Alta")} -> Baja | R74: {=+_xlfn.IFS(P74="","",P74<=0,"Baja",P74<=2,"Media",P74>2,"Alta")} -> Baja | S74: {=+_xlfn.IFS(N74="","",N74="Componentes existentes reutilizables >80%","Baja",N74="No Aplica","Baja",N74="Reutilización parcial 30-70%","Media",N74="Nuevo Desarrollo <20%","Alta")} -> Baja | T74: {=+_xlfn.IFS(L74="","",L74=0,"Baja",L74<=2,"Media",L74>=3,"Alta")} -> Media | U74: {=+IFERROR((+_xlfn.IFS(Q74="",0,Q74="Baja",1,Q74="Media",2,Q74="Alta",3)*'Scoring Complejidad'!$C$8+_xlfn.IFS(R74="Baja",1,R74="Media",2,R74="Alta",3)*'Scoring Complejidad'!$C$9+_xlfn.IFS(S74="Baja",1,S74="Media",2,S74="Alta",3)*'Scoring Complejidad'!$C$7+_xlfn.IFS(T74="",1,T74="Baja",1,T74="Media",2,T74="Alta",3)*'Scoring Complejidad'!$C$5+_xlfn.IFS(M74="Caja",1,M74="Configuración",2,M74="Desarrollo",3,M74="Desarrollo + Configuración",3,M74="No Aplica",0)*'Scoring Complejidad'!$C$6),"")} -> 1.05 | V74: {=IFERROR(_xlfn.IFS(U74="","",U74<=1.69,"Baja",U74<=2.29,"Media",U74<=3,"Alta",U74>3,"Error"),"")} -> Baja | W74: 46279 | X74: 46290 | Y74: 46293 | Z74: 46304 | AA74: 46307 | AB74: 46332 | AC74: Utiliza la integración de API CAMBIOS en detalle de TDC Rec_retrieveCreditCardStatement: Misma API que SMART-3962 Fechas tentativas de implementación | AD74: 46240
A75: SMART-4280 | B75: APP | C75: Gestión del campo "Otra cantidad" basado en el límite de saldo a favor | D75: TDC | E75: Gestión del campo "Otra cantidad" basado en el límite de saldo a favor | H75: App | I75: Cliente BanCoppel con TDC activa | J75: Must | K75: Integración | L75: 1 | M75: No Aplica | N75: No Aplica | O75: 0 | P75: 0 | Q75: {=+_xlfn.IFS(O75="","",O75<=1,"Baja",O75<=3,"Media",O75>3,"Alta")} -> Baja | R75: {=+_xlfn.IFS(P75="","",P75<=0,"Baja",P75<=2,"Media",P75>2,"Alta")} -> Baja | S75: {=+_xlfn.IFS(N75="","",N75="Componentes existentes reutilizables >80%","Baja",N75="No Aplica","Baja",N75="Reutilización parcial 30-70%","Media",N75="Nuevo Desarrollo <20%","Alta")} -> Baja | T75: {=+_xlfn.IFS(L75="","",L75=0,"Baja",L75<=2,"Media",L75>=3,"Alta")} -> Media | U75: {=+IFERROR((+_xlfn.IFS(Q75="",0,Q75="Baja",1,Q75="Media",2,Q75="Alta",3)*'Scoring Complejidad'!$C$8+_xlfn.IFS(R75="Baja",1,R75="Media",2,R75="Alta",3)*'Scoring Complejidad'!$C$9+_xlfn.IFS(S75="Baja",1,S75="Media",2,S75="Alta",3)*'Scoring Complejidad'!$C$7+_xlfn.IFS(T75="",1,T75="Baja",1,T75="Media",2,T75="Alta",3)*'Scoring Complejidad'!$C$5+_xlfn.IFS(M75="Caja",1,M75="Configuración",2,M75="Desarrollo",3,M75="Desarrollo + Configuración",3,M75="No Aplica",0)*'Scoring Complejidad'!$C$6),"")} -> 1.05 | V75: {=IFERROR(_xlfn.IFS(U75="","",U75<=1.69,"Baja",U75<=2.29,"Media",U75<=3,"Alta",U75>3,"Error"),"")} -> Baja | W75: 46279 | X75: 46290 | Y75: 46293 | Z75: 46304 | AA75: 46321 | AB75: 46332 | AC75: ID Pendiente en Jira Utiliza la integración de API CAMBIOS en detalle de TDC Rec_retrieveCreditCardStatement: Misma API que SMART-3962 Fechas tentativas de implementación | AD75: 46240
A76: SMART-4183 | B76: APP | C76: Límite de saldo a favor para pago de TDC en la aplicación móvil | D76: TDC | E76: Límite de saldo a favor para pago de TDC en la aplicación móvil | F76: Validación en la App Móvil que impide realizar un pago de TDC cuando el monto resultante generaría un saldo a favor que excede los límites permitidos, mostrando una alerta al cliente y bloqueando la transacción. | G76: 1. Línea de crédito ≤ $24,999: el saldo a favor no puede rebasar $15,000. 2. Línea de crédito ≥ $25,000: el saldo a favor no puede rebasar el 20% del crédito total. 3. Si el pago excede el límite: la app bloquea la transacción y muestra alerta al cliente. | H76: App | I76: Cliente BanCoppel con TDC activa | J76: Must | K76: Integración | L76: 1 | M76: No Aplica | N76: No Aplica | O76: 0 | P76: 0 | Q76: {=+_xlfn.IFS(O76="","",O76<=1,"Baja",O76<=3,"Media",O76>3,"Alta")} -> Baja | R76: {=+_xlfn.IFS(P76="","",P76<=0,"Baja",P76<=2,"Media",P76>2,"Alta")} -> Baja | S76: {=+_xlfn.IFS(N76="","",N76="Componentes existentes reutilizables >80%","Baja",N76="No Aplica","Baja",N76="Reutilización parcial 30-70%","Media",N76="Nuevo Desarrollo <20%","Alta")} -> Baja | T76: {=+_xlfn.IFS(L76="","",L76=0,"Baja",L76<=2,"Media",L76>=3,"Alta")} -> Media | U76: {=+IFERROR((+_xlfn.IFS(Q76="",0,Q76="Baja",1,Q76="Media",2,Q76="Alta",3)*'Scoring Complejidad'!$C$8+_xlfn.IFS(R76="Baja",1,R76="Media",2,R76="Alta",3)*'Scoring Complejidad'!$C$9+_xlfn.IFS(S76="Baja",1,S76="Media",2,S76="Alta",3)*'Scoring Complejidad'!$C$7+_xlfn.IFS(T76="",1,T76="Baja",1,T76="Media",2,T76="Alta",3)*'Scoring Complejidad'!$C$5+_xlfn.IFS(M76="Caja",1,M76="Configuración",2,M76="Desarrollo",3,M76="Desarrollo + Configuración",3,M76="No Aplica",0)*'Scoring Complejidad'!$C$6),"")} -> 1.05 | V76: {=IFERROR(_xlfn.IFS(U76="","",U76<=1.69,"Baja",U76<=2.29,"Media",U76<=3,"Alta",U76>3,"Error"),"")} -> Baja | W76: 46279 | X76: 46290 | Y76: 46293 | Z76: 46304 | AA76: 46321 | AB76: 46332 | AC76: Fechas tentativas de implementación | AD76: 46240
A77: SMART-4176 | B77: APP | C77: Movimientos Convivencia TDC F&D | D77: TDC | E77: Movimientos Convivencia TDC F&D | F77: Sección "Movimientos del periodo actual" dentro de la pantalla "Detalle de tu tarjeta de crédito". Muestra el historial de movimientos de la TDC Física y/o Digital del cliente desde el día de consulta hasta 30 días posteriores, con nombre, fecha y monto de cada transacción. | G77: 1. Movimientos del periodo: desde el día de la consulta hasta 30 días posteriores. 2. Cargos se muestran con signo negativo; abonos con signo positivo. 3. Movimientos en retención muestran badge amarillo con leyenda "En proceso". 4. Si no hay movimientos en el periodo, se muestra leyenda "Sin movimientos". | H77: App | I77: Cliente BanCoppel con TDC Física y/o Digital | J77: Must | K77: Solución e Integración | L77: 1 | M77: Desarrollo | N77: Componentes existentes reutilizables >80% | O77: 2 | P77: 1 | Q77: {=+_xlfn.IFS(O77="","",O77<=1,"Baja",O77<=3,"Media",O77>3,"Alta")} -> Media | R77: {=+_xlfn.IFS(P77="","",P77<=0,"Baja",P77<=2,"Media",P77>2,"Alta")} -> Media | S77: {=+_xlfn.IFS(N77="","",N77="Componentes existentes reutilizables >80%","Baja",N77="No Aplica","Baja",N77="Reutilización parcial 30-70%","Media",N77="Nuevo Desarrollo <20%","Alta")} -> Baja | T77: {=+_xlfn.IFS(L77="","",L77=0,"Baja",L77<=2,"Media",L77>=3,"Alta")} -> Media | U77: {=+IFERROR((+_xlfn.IFS(Q77="",0,Q77="Baja",1,Q77="Media",2,Q77="Alta",3)*'Scoring Complejidad'!$C$8+_xlfn.IFS(R77="Baja",1,R77="Media",2,R77="Alta",3)*'Scoring Complejidad'!$C$9+_xlfn.IFS(S77="Baja",1,S77="Media",2,S77="Alta",3)*'Scoring Complejidad'!$C$7+_xlfn.IFS(T77="",1,T77="Baja",1,T77="Media",2,T77="Alta",3)*'Scoring Complejidad'!$C$5+_xlfn.IFS(M77="Caja",1,M77="Configuración",2,M77="Desarrollo",3,M77="Desarrollo + Configuración",3,M77="No Aplica",0)*'Scoring Complejidad'!$C$6),"")} -> 2.05 | V77: {=IFERROR(_xlfn.IFS(U77="","",U77<=1.69,"Baja",U77<=2.29,"Media",U77<=3,"Alta",U77>3,"Error"),"")} -> Media | W77: 46223 | X77: 46234 | Y77: 46230 | Z77: 46234 | AA77: 46335 | AB77: 46346 | AD77: 46240
A78: SMART-4180 | B78: APP | C78: Detalle de Movimientos Convivencia TDC F&D | D78: TDC | E78: Detalle de Movimientos Convivencia TDC F&D | F78: Pantalla "Detalle del movimiento" accesible al hacer tap sobre cualquier movimiento desde el historial de la TDC. Muestra el desglose completo de la transacción: monto, concepto, fecha, referencia, saldo y leyenda de aclaración. Incluye botón para compartir el detalle como imagen. | G78: 1. Cargos se muestran con signo negativo; abonos con signo positivo. 2. Movimiento con saldo retenido mantiene la misma estructura de pantalla que movimiento normal. 3. La leyenda de aclaración indica el número 55 9500 0002 y el plazo de 90 días para solicitarla. 4. El botón compartir exporta el detalle en formato imagen. | H78: App | I78: Cliente BanCoppel con TDC Física y/o Digital | J78: Wont | K78: Solución e Integración | L78: 1 | M78: Desarrollo | N78: Nuevo Desarrollo <20% | O78: 7 | P78: 1 | Q78: {=+_xlfn.IFS(O78="","",O78<=1,"Baja",O78<=3,"Media",O78>3,"Alta")} -> Alta | R78: {=+_xlfn.IFS(P78="","",P78<=0,"Baja",P78<=2,"Media",P78>2,"Alta")} -> Media | S78: {=+_xlfn.IFS(N78="","",N78="Componentes existentes reutilizables >80%","Baja",N78="No Aplica","Baja",N78="Reutilización parcial 30-70%","Media",N78="Nuevo Desarrollo <20%","Alta")} -> Alta | T78: {=+_xlfn.IFS(L78="","",L78=0,"Baja",L78<=2,"Media",L78>=3,"Alta")} -> Media | U78: {=+IFERROR((+_xlfn.IFS(Q78="",0,Q78="Baja",1,Q78="Media",2,Q78="Alta",3)*'Scoring Complejidad'!$C$8+_xlfn.IFS(R78="Baja",1,R78="Media",2,R78="Alta",3)*'Scoring Complejidad'!$C$9+_xlfn.IFS(S78="Baja",1,S78="Media",2,S78="Alta",3)*'Scoring Complejidad'!$C$7+_xlfn.IFS(T78="",1,T78="Baja",1,T78="Media",2,T78="Alta",3)*'Scoring Complejidad'!$C$5+_xlfn.IFS(M78="Caja",1,M78="Configuración",2,M78="Desarrollo",3,M78="Desarrollo + Configuración",3,M78="No Aplica",0)*'Scoring Complejidad'!$C$6),"")} -> 2.6 | V78: {=IFERROR(_xlfn.IFS(U78="","",U78<=1.69,"Baja",U78<=2.29,"Media",U78<=3,"Alta",U78>3,"Error"),"")} -> Alta | W78: 46223 | X78: 46234 | Y78: 46230 | Z78: 46234 | AA78: 46349 | AB78: 46360 | AC78: Criterios de aceptación con posible actualización Historia de usuario considerada en R4.5 - alineado con negocio Validar reutilización de reusabilidad- dependencia en pantallas | AD78: 46240
A79: SMART-4278 | B79: APP | C79: Eliminación de TDC Digital | D79: TDC | E79: Eliminación de TDC Digital | F79: Flujo de eliminación de TDC Digital desde la pantalla "Gestión de Tarjeta Digital". El cliente desliza un slider para confirmar la eliminación mediante Token Digital. Al completarse exitosamente, se elimina la tarjeta, se envía correo de comprobante y se habilita automáticamente una nueva TDC Digital para activar. | G79: 1. Solo aplica a TDC Digital — no es posible eliminar una TDC Física desde este módulo. 2. Límite de 2 eliminaciones de TDC Digital por mes; al alcanzarlo, la operación no procede. 3. Si la TDC Digital tiene domiciliaciones o pagos automáticos, la app debe validarlo antes de proceder. 4. La confirmación requiere completar el flujo de Token Digital (slider); si falla, la tarjeta no se elimina. 5. Tras eliminación exitosa: se disponibiliza automáticamente una nueva TDC Digital para activar. | H79: App | I79: Cliente BanCoppel con TDC Digital activa | J79: Wont | K79: Solución e Integración | L79: 1 | M79: Desarrollo | N79: Nuevo Desarrollo <20% | O79: 7 | P79: 2 | Q79: {=+_xlfn.IFS(O79="","",O79<=1,"Baja",O79<=3,"Media",O79>3,"Alta")} -> Alta | R79: {=+_xlfn.IFS(P79="","",P79<=0,"Baja",P79<=2,"Media",P79>2,"Alta")} -> Media | S79: {=+_xlfn.IFS(N79="","",N79="Componentes existentes reutilizables >80%","Baja",N79="No Aplica","Baja",N79="Reutilización parcial 30-70%","Media",N79="Nuevo Desarrollo <20%","Alta")} -> Alta | T79: {=+_xlfn.IFS(L79="","",L79=0,"Baja",L79<=2,"Media",L79>=3,"Alta")} -> Media | U79: {=+IFERROR((+_xlfn.IFS(Q79="",0,Q79="Baja",1,Q79="Media",2,Q79="Alta",3)*'Scoring Complejidad'!$C$8+_xlfn.IFS(R79="Baja",1,R79="Media",2,R79="Alta",3)*'Scoring Complejidad'!$C$9+_xlfn.IFS(S79="Baja",1,S79="Media",2,S79="Alta",3)*'Scoring Complejidad'!$C$7+_xlfn.IFS(T79="",1,T79="Baja",1,T79="Media",2,T79="Alta",3)*'Scoring Complejidad'!$C$5+_xlfn.IFS(M79="Caja",1,M79="Configuración",2,M79="Desarrollo",3,M79="Desarrollo + Configuración",3,M79="No Aplica",0)*'Scoring Complejidad'!$C$6),"")} -> 2.6 | V79: {=IFERROR(_xlfn.IFS(U79="","",U79<=1.69,"Baja",U79<=2.29,"Media",U79<=3,"Alta",U79>3,"Error"),"")} -> Alta | W79: 46272 | X79: 46283 | Y79: 46286 | Z79: 46297 | AA79: 46376 | AB79: 46387 | AC79: Historia de usuario considerada en R4.5 - alineado con negocio De momento es una integración pero podría haber modificación en 2 APIs Criterios de aceptación en revisión | AD79: 46240
A80: SMART-4105 | B80: APP | C80: Notificación de activación Tarjeta Digital BanCoppel | D80: TDC | E80: Notificación activación o elimnación de Tarjeta Digital BanCoppel | F80: Envío automático de correo electrónico de confirmación al cliente tras completar exitosamente el flujo de activación de su TDC Digital. Incluye template diferenciado por evento: "Tarjeta de crédito digital activada", con detalle de la operación. | G80: 1. El correo se dispara únicamente tras completar exitosamente el flujo de activación. 2. Asunto de activación: "Activación App BanCoppel". 3. El cuerpo del correo incluye: nombre del cliente, nombre de la tarjeta, canal (App BanCoppel), folio, fecha y hora de la operación. | H80: App | I80: Cliente BanCoppel con TDC Digital | J80: Could | K80: Integración | L80: 1 | M80: No Aplica | N80: No Aplica | O80: 0 | P80: 0 | Q80: {=+_xlfn.IFS(O80="","",O80<=1,"Baja",O80<=3,"Media",O80>3,"Alta")} -> Baja | R80: {=+_xlfn.IFS(P80="","",P80<=0,"Baja",P80<=2,"Media",P80>2,"Alta")} -> Baja | S80: {=+_xlfn.IFS(N80="","",N80="Componentes existentes reutilizables >80%","Baja",N80="No Aplica","Baja",N80="Reutilización parcial 30-70%","Media",N80="Nuevo Desarrollo <20%","Alta")} -> Baja | T80: {=+_xlfn.IFS(L80="","",L80=0,"Baja",L80<=2,"Media",L80>=3,"Alta")} -> Media | U80: {=+IFERROR((+_xlfn.IFS(Q80="",0,Q80="Baja",1,Q80="Media",2,Q80="Alta",3)*'Scoring Complejidad'!$C$8+_xlfn.IFS(R80="Baja",1,R80="Media",2,R80="Alta",3)*'Scoring Complejidad'!$C$9+_xlfn.IFS(S80="Baja",1,S80="Media",2,S80="Alta",3)*'Scoring Complejidad'!$C$7+_xlfn.IFS(T80="",1,T80="Baja",1,T80="Media",2,T80="Alta",3)*'Scoring Complejidad'!$C$5+_xlfn.IFS(M80="Caja",1,M80="Configuración",2,M80="Desarrollo",3,M80="Desarrollo + Configuración",3,M80="No Aplica",0)*'Scoring Complejidad'!$C$6),"")} -> 1.05 | V80: {=IFERROR(_xlfn.IFS(U80="","",U80<=1.69,"Baja",U80<=2.29,"Media",U80<=3,"Alta",U80>3,"Error"),"")} -> Baja | W80: 46223 | X80: 46234 | Y80: 46230 | Z80: 46234 | AA80: 46265 | AB80: 46276 | AC80: La notifiación de eliminación se va a R4.5 ID de Jira para notifiación de activivación pendiente Pendiente validación de fechas con equipo de API-SAID | AD80: 46240
A81: HDU-SMART-R4-22 | B81: Smart Vista | C81: Disposición de efectivo - APP | D81: TDC | E81: Disposición de efectivo - APP | F81: SmartVista procesa y autoriza solicitudes de disposición de efectivo desde App BanCoppel, aplica comisión e IVA según producto, y refleja el movimiento en el saldo de la TDC transfiriendo el monto a la cuenta de captación vinculada. | G81: 1. Tener la transacción en SMART VISTA | H81: Smart Vista | I81: Cliente BanCoppel con TDC activa | J81: Should | K81: Solución | L81: 0 | M81: Desarrollo + Configuración | N81: Reutilización parcial 30-70% | O81: 1 | P81: 0 | Q81: {=+_xlfn.IFS(O81="","",O81<=1,"Baja",O81<=3,"Media",O81>3,"Alta")} -> Baja | R81: {=+_xlfn.IFS(P81="","",P81<=0,"Baja",P81<=2,"Media",P81>2,"Alta")} -> Baja | S81: {=+_xlfn.IFS(N81="","",N81="Componentes existentes reutilizables >80%","Baja",N81="No Aplica","Baja",N81="Reutilización parcial 30-70%","Media",N81="Nuevo Desarrollo <20%","Alta")} -> Media | T81: {=+_xlfn.IFS(L81="","",L81=0,"Baja",L81<=2,"Media",L81>=3,"Alta")} -> Baja | U81: {=+IFERROR((+_xlfn.IFS(Q81="",0,Q81="Baja",1,Q81="Media",2,Q81="Alta",3)*'Scoring Complejidad'!$C$8+_xlfn.IFS(R81="Baja",1,R81="Media",2,R81="Alta",3)*'Scoring Complejidad'!$C$9+_xlfn.IFS(S81="Baja",1,S81="Media",2,S81="Alta",3)*'Scoring Complejidad'!$C$7+_xlfn.IFS(T81="",1,T81="Baja",1,T81="Media",2,T81="Alta",3)*'Scoring Complejidad'!$C$5+_xlfn.IFS(M81="Caja",1,M81="Configuración",2,M81="Desarrollo",3,M81="Desarrollo + Configuración",3,M81="No Aplica",0)*'Scoring Complejidad'!$C$6),"")} -> 1.7 | V81: {=IFERROR(_xlfn.IFS(U81="","",U81<=1.69,"Baja",U81<=2.29,"Media",U81<=3,"Alta",U81>3,"Error"),"")} -> Media | W81: 46214 | X81: 46269 | Y81: 46223 | Z81: 46233 | AA81: 46230 | AB81: 46295 | AC81: Las trabaja SmartVista no requieren pruebas integrales porque hasta el siguiente R se liberan Criterio de aceptación tener la transacción en SMARTVISTA | AD81: 46240
L92: =1/3 -> 0.33333333

Sheet Priorización (Claude)
A1: IDENTIFICACIÓN | F1: ALCANCE | J1: PRIORIZACIÓN | L1: COMPLEJIDAD
A2: Funcionalidad / Building Block | B2: ID HU | C2: Track / Plataforma | D2: Nombre HU | E2: Producto | F2: Descripción Funcional (qué hace) | G2: Reglas de Negocio Clave | H2: Canal(es) Afectado(s) | I2: Usuario Final / Actor Principal | J2: Criticidad Negocio | K2: Justificación Criticidad | L2: Tipo Solución | M2: Complejidad Solución | N2: Esfuerzo Estimado (días) | O2: Plataforma Principal
A3: =+VLOOKUP(B3,Diccionario!$B$2:$C$81,2,0) -> Solicitud de Maquila automatizada | B3: HDU-SMART-R4-01 | C3: Smart Vista | D3: Certificar layouts de maquila con proveedores. | E3: TDC | F3: Habilitar la certificación de layouts posicionales/planos homologados para los 4 proveedores de maquila (GID, Forza, TGS, Thomas Greg & Sons), con cifrado PGP por proveedor y HSM por tarjeta, para emitir tarjetas del producto 4900 de forma controlada y trazable. | G3: Layout único homologado para los 4 maquiladores. Campos alfanuméricos validados para rechazar caracteres no embosables. Cifrado PGP+HSM; vigencia de llaves validada antes de generar. Reproceso de archivo sin alterar números de tarjeta. Solo producto 4900 parametrizado en SV Back Office [RN-OP-MA-01/02/03/05]. | H3: Smart Vista | I3: Área de Suministros / Administración de Tarjetas | J3: Alta | K3: Prerequisito operativo para emisión de tarjetas físicas 4900. Sin layouts certificados no puede haber maquila. | L3: Parametrizable | M3: Media | N3: 20 | O3: SmartVista Back Office
A4: =+VLOOKUP(B4,Diccionario!$B$2:$C$81,2,0) -> Solicitud de Maquila automatizada | B4: HDU-SMART-R4-02 | C4: Smart Vista | D4: Consultar inventario de tarjetas por sucursal. | E4: TDC | F4: Consulta del stock de tarjetas disponibles por sucursal distinguiendo 'en existencia', 'en ruta' y 'por fabricar'; cálculo de stock semanal sobre existencias reales; filtro por tipo de sucursal. El inventario vive íntegramente en Smart Vista, sin dependencia de Macweb. | G4: Stock semanal basado SOLO en existencias físicas (no en ruta/por fabricar) [RN-HU-001]. Filtro por Tipo de Sucursal. Detalle de lotes en proceso por producto/sucursal. Datos provienen de SV, ruptura con legado Macweb [RN-OP-MA-05]. | H4: Smart Vista | I4: Área de Suministros | J4: Alta | K4: Insumo de decisión para reórdenes automáticos y manuales. Sin inventario confiable, la maquila es reactiva. | L4: Caja | M4: Baja | N4: 5 | O4: SmartVista Back Office
A5: =+VLOOKUP(B5,Diccionario!$B$2:$C$81,2,0) -> Solicitud de Maquila automatizada | B5: HDU-SMART-R4-03 | C5: Smart Vista | D5: Calcular maquila con parámetros de abasto. | E5: TDC | F5: Cálculo diario automatizado (batch 6:00 AM) de la cantidad de tarjetas a reordenar por sucursal/producto, usando piso mínimo y semanas-a-dotar parametrizables, con redondeo a múltiplos de 250 plásticos y consumo calculado sobre mes calendario completo. | G5: Corrida batch 6:00 AM. Piso mínimo default 4 semanas, parametrizable por producto/sucursal [RN-OP-MA-04]. Semanas a dotar de 1 a N (hoy topado a 3). Redondeo a múltiplos de 250 [RN-OP-MA-11]. Consumo sobre mes calendario completo, no ventana fija [RN-HU-002/078]. | H5: Smart Vista | I5: Área de Suministros | J5: Alta | K5: Motor que automatiza el reabastecimiento y evita desabasto en las 1,700+ sucursales. | L5: Parametrizable | M5: Media | N5: 15 | O5: SmartVista Back Office
A6: =+VLOOKUP(B6,Diccionario!$B$2:$C$81,2,0) -> Solicitud de Maquila automatizada | B6: HDU-SMART-R4-04 | C6: Smart Vista | D6: Ejecutar solicitud automatizada de maquila. | E6: TDC | F6: Detona el proceso de emisión masiva de tarjetas tras el cálculo de reorden. Incluye validación anti-duplicidad, pre-asignación de proveedor, notificación por correo a ~30 destinatarios usando número de lote. Dos pasos pendientes de automatizar en R4: generación OCG vía Cron y entrega Connect Direct. | G6: Solicitud se detona solo si layout tiene datos completos [RN-HU-004]. Anti-duplicidad: si existe solicitud en mismo layout se rechaza [RN-HU-003]. Pre-asignación de proveedor por matriz de capacidades o manual [RN-OP-MA-10]. Correo diario ~30 destinatarios con número de lote. | H6: Smart Vista | I6: Área de Suministros | J6: Alta | K6: Automatización del reorden que reemplaza proceso manual actual. Gap técnico: automatización de OCG y Connect Direct aún pendiente para R4. | L6: Desarrollo | M6: Alta | N6: 40 | O6: SmartVista / Connect Direct
A7: =+VLOOKUP(B7,Diccionario!$B$2:$C$81,2,0) -> Solicitud de Maquila automatizada | B7: HDU-SMART-R4-05 | C7: Smart Vista | D7: Ejecutar solicitud manual de maquila. | E7: TDC | F7: Permite al área de Suministros generar solicitudes manuales de maquila para casos específicos (ej. apertura de sucursal), usando el mismo layout que la maquila automática. Restricción: un lote por día por sucursal. | G7: Solicitud manual usa layout único compartido con la automática [RN-OP-MA-01]. Dotación inicial garantizada ante apertura de sucursal nueva. Restricción: 1 lote/día/sucursal (proceso tarda 2-3 semanas). Funcionalidad demo confirmada en S1/S2. | H7: Smart Vista | I7: Área de Suministros | J7: Alta | K7: Complemento necesario de la automática para casos operativos específicos. Flujo ya demo-ado en sesión. | L7: Caja | M7: Baja | N7: 5 | O7: SmartVista Back Office
A8: =+VLOOKUP(B8,Diccionario!$B$2:$C$81,2,0) -> Solicitud de Maquila automatizada | B8: HDU-SMART-R4-06 | C8: Smart Vista | D8: Generar archivos seguros de maquila. | E8: TDC | F8: Generación y resguardo del archivo para el maquilador tras procesar la solicitud. Incluye cifrado PGP/HSM, flujo de 4 pasos (SVBO→OCG→Cargen→PGP→Connect Direct), trazabilidad Orden→Lote→Tarjeta, y alertamiento/reproceso ante error del maquilador. | G8: Flujo técnico: SVBO→OCG→Cargen→PGP→Connect Direct [Comentado en sesión]. Archivo cifrado con PGP del proveedor destino. Trazabilidad completa Orden→Lote→Tarjeta. Alertamiento y reproceso ante error de procesamiento en maquilador [DEF RF-01 Escenario 3/4]. | H8: Smart Vista | I8: Administrador de Maquila / Suministros | J8: Alta | K8: Integración crítica de seguridad y trazabilidad. Sin archivos seguros certificados no puede completarse el proceso de emisión. | L8: Desarrollo | M8: Alta | N8: 35 | O8: SmartVista / Connect Direct
A9: =+VLOOKUP(B9,Diccionario!$B$2:$C$81,2,0) -> Solicitud de Maquila automatizada | B9: HDU-SMART-R4-07 | C9: Smart Vista | D9: Dar seguimiento a estatus de lotes. | E9: TDC | F9: Consulta del estatus de emisión y entrega de lotes por sucursal (Inventario POS), incluyendo seguimiento de paquetería desde recolección hasta entrega, reportería de existencia y detalle de lotes en proceso. | G9: Seguimiento de paquetería recolección→entrega, confirmación de recepción [DEF RF-01 Escenarios 5/6]. Consulta limitada al periodo máximo [RN-HU-006]. Sin reposición proactiva ante vencimiento: cliente acude a sucursal [RN-OP-MA-06/08]. | H9: Smart Vista | I9: Área de Suministros / Operaciones | J9: Media | K9: Visibilidad operativa del proceso de distribución. No bloquea MVP pero es necesario para operación en mercado abierto. | L9: Caja | M9: Baja | N9: 8 | O9: SmartVista Back Office
A10: =+VLOOKUP(B10,Diccionario!$B$2:$C$81,2,0) -> Solicitud de Maquila automatizada | B10: HDU-SMART-R4-08 | C10: Smart Vista | D10: Controlar recepción y cancelación de lotes. | E10: TDC | F10: Recepción de lotes en sucursal desde SIWEB con validación de lote correcto, baja de tarjetas dañadas/inexistentes, bloqueo de asignación para créditos vencidos, y validación obligatoria de huella del Gerente para cancelaciones. | G10: Recepción desde SIWEB; rechazo de lote incorrecto o de otra sucursal [RN-HU-007/008]. Mensaje corregido 'tarjeta no existe' (hoy muestra erróneamente 'ya reportada') [RN-HU-009]. Bloqueo con crédito vencido >1 mes [RN-HU-010]. Huella de Gerente obligatoria para cancelar dañadas [RN-OP-MA-12]. Gap: baja por daño solo si tarjeta asignada (candidato R4.5). | H10: Smart Vista, SIWEB | I10: Gerente de Sucursal / Ejecutivo de Sucursal | J10: Alta | K10: Gate operativo: sin recepción y cancelación controlada, el inventario en sucursal sería inconsistente. | L10: Parametrizable | M10: Media | N10: 18 | O10: SmartVista / SIWEB
A11: =+VLOOKUP(B11,Diccionario!$B$2:$C$81,2,0) -> Homologación de conceptos de comisiones | B11: HDU-SMART-R4-09 | C11: Smart Vista | D11: Homologar conceptos de comisiones TDC. | E11: TDC | F11: Definición del catálogo normativo único de comisiones para TDC 4900 (17 comisiones replicando esquema 8500), alineado a BANXICO. Solo cambia la etiqueta visible; caídas y cuentas contables permanecen idénticas. Límites de longitud: 40 caracteres en EDC, 26 en ticket SIWEB. | G11: Catálogo normativo único alineado a BANXICO [RN-HU-016]. 17 comisiones 4900=esquema 8500. Solo cambia etiqueta, NO la contabilidad [RF-03 Acuerdo S3]. Límites: 40 chars EDC / 26 chars ticket. Mapeo nombre-actual→nombre-nuevo con ID de comisión. | H11: Smart Vista, App, SIWEB | I11: Área Normativa / Negocio | J11: Alta | K11: Cumplimiento regulatorio BANXICO. Sin homologación existe riesgo de multa. | L11: Parametrizable | M11: Baja | N11: 8 | O11: SmartVista Back Office
A12: =+VLOOKUP(B12,Diccionario!$B$2:$C$81,2,0) -> Homologación de conceptos de comisiones | B12: HDU-SMART-R4-10 | C12: Smart Vista | D12: Sincronizar nombres de comisiones en canales. | E12: TDC | F12: Verificación de que los nombres homologados de comisiones se muestran de forma idéntica en todos los canales de consulta (Smart Vista, App, SIWEB, EDC), cumpliendo la regulación BANXICO y los límites de longitud por canal. | G12: Nombres idénticos en SV, App, SIWEB, EDC [RN-HU-016/017/018]. Verificación por punto de consulta. Auditoría BANXICO sin inconsistencias. Límites 40 EDC / 26 ticket. Depende de catálogo HDU-SMART-R4-09. | H12: Smart Vista, App, SIWEB, EDC | I12: Área Normativa / Todos los canales | J12: Alta | K12: Dependiente de HDU-09. Sin sincronización multicanal el riesgo BANXICO persiste. | L12: Parametrizable | M12: Baja | N12: 5 | O12: Transversal multicanal
A13: =+VLOOKUP(B13,Diccionario!$B$2:$C$81,2,0) -> Reglas del autorizador (88 reglas) | B13: HDU-SMART-R4-11 | C13: Smart Vista | D13: Incorporar reglas del autorizador BPC. | E13: TDC | F13: Motor de 88 reglas del autorizador BPC en tiempo real: Módulo 1 (estatus/ISO 8583) y Fraud Management. Incluye rechazo con códigos ISO específicos, validación MIT sin OTID contra Whitelist, y mapeo de rechazos por bloqueo temporal. | G13: 88 reglas BPC divididas entre SV Frontend y Fraud Management [RF-06a Acuerdo S3]. Módulo 1: rechazo con código ISO (BIN desconocido ISO 14, robada ISO 43, extraviada ISO 41) [RN-HU-025]. MIT sin OTID: Regla 45 vs Whitelist + umbrales Regla 88 [RN-HU-026]. Sin afectación contable hasta batch cierre de día. Alerta 000916 por bloqueo temporal [RN-OP-AU-01/02]. | H13: Smart Vista (Autorizador BPC) | I13: Administrador de Tarjetas / BPC | J13: Alta | K13: Corazón del procesamiento transaccional TDC. Sin reglas del autorizador no puede operar el procesador. | L13: Desarrollo | M13: Alta | N13: 60 | O13: SmartVista / E-global / BPC
A14: =+VLOOKUP(B14,Diccionario!$B$2:$C$81,2,0) -> Nueva regla de limitar saldo a favor | B14: HDU-SMART-R4-12 | C14: Smart Vista | D14: Parametrizar límite de saldo a favor. | E14: TDC | F14: Interfaz de administración para configurar el parámetro único de límite de saldo a favor por TDC (monto o % de la línea), con switch on/off para TDC clásica 4900 y propagación consistente a todos los canales. | G14: Parámetro único: monto o % sobre línea de crédito. Switch apagar/prender para TDC clásica (4900); extensible a legado [RF-25]. Aplica a productos 6001 y 4900. Propagación automática a todos los canales. Solo rol autorizado puede modificar [RN-HU-021]. | H14: Smart Vista (todos los canales) | I14: Área de Negocio / Administrador | J14: Alta | K14: Requisito regulatorio de CNBV/Auditoría. Parámetro base que habilita las validaciones en HDU-13 y -15. | L14: Parametrizable | M14: Baja | N14: 5 | O14: SmartVista Back Office
... A82: =+VLOOKUP(B82,Diccionario!$B$2:$C$81,2,0) -> Validación de domicilio / Intengración de expediente digital | B82: HDU-TDC-R4-34 | C82: Apolo | D82: Asignar sucursal corporativa parametrizable a la TDC BanCoppel. | E82: TDC | F82: La TDC BanCoppel se asigna a la sucursal corporativa 6700 por defecto, de forma dinámica y parametrizable. Negocio podrá modificar el número sin desarrollo. Aplica en el proceso de creación del producto en SmartVista vía Apolo. | G82: Asignar sucursal corporativa 6700 por defecto. Número parametrizable; Negocio puede modificar sin desarrollo. Asignación dinámica al generar la TDC. Aplica en Validación de Domicilio e Integración de Expediente Digital. | H82: Apolo (Onboarding digital — BB6 Domicilio / BB16 Expediente) | I82: Sistema / SmartVista | J82: Alta | K82: SmartVista requiere sucursal asignada para crear el producto. Sin esto no puede darse de alta la TDC 4900. | L82: Parametrizable | M82: Baja | N82: 4 | O82: Apolo / SmartVista / BD Parámetros

Sheet Diccionario
B1: ID HU | C1: Funcionalidad / BB
B2: HDU-SMART-R4-01 | C2: Solicitud de Maquila automatizada
B3: HDU-SMART-R4-02 | C3: Solicitud de Maquila automatizada
B4: HDU-SMART-R4-03 | C4: Solicitud de Maquila automatizada
B5: HDU-SMART-R4-04 | C5: Solicitud de Maquila automatizada
B6: HDU-SMART-R4-05 | C6: Solicitud de Maquila automatizada
B7: HDU-SMART-R4-06 | C7: Solicitud de Maquila automatizada
B8: HDU-SMART-R4-07 | C8: Solicitud de Maquila automatizada
B9: HDU-SMART-R4-08 | C9: Solicitud de Maquila automatizada
B10: HDU-SMART-R4-09 | C10: Homologación de conceptos de comisiones
B11: HDU-SMART-R4-10 | C11: Homologación de conceptos de comisiones
B12: HDU-SMART-R4-11 | C12: Reglas del autorizador (88 reglas)
... B81: HDU-TDC-R4-34 | C81: Validación de domicilio / Intengración de expediente digital

Sheet Scoring Complejidad
A1: LEYENDA DE MEDICIÓN DE COMPLEJIDAD — HUs R4
A3: 1. FACTORES DE MEDICIÓN, DESCRIPCIÓN Y PONDERACIÓN
A4: FACTOR | B4: DESCRIPCIÓN | C4: PESO | D4: BAJA → Score 1 | E4: MEDIA → Score 2 | F4: ALTA → Score 3
A5: # Integraciones | B5: Número de integraciones entre sistemas — tipo API, Batch, Evento, Archivo, MQ, SOAP o REST. | C5: 0.3 | D5: No hay integración | E5: 1 a 2 integraciones | F5: 3 ó más
A6: Impacto Solución | B6: Impacto de la solución requerido en la plataforma: Caja, Configuración = parametrización | Desarrollo = código nuevo | Des+Config = ambos. | C6: 0.25 | D6: Caja | E6: Configuración | F6: Desarrollo o Des+Config
