Workbook

Sheet Summary
A1: R4 Interoperability Capability Baseline
A2: Executive summary of required interoperability capabilities for R4 based on user stories and capability hierarchy.
A4: Assessment conclusion | B4: R4 requires a controlled interoperability layer around SmartVista and Apolo, not just direct channel-to-core APIs. Domain capabilities under 6.0-13.0 are the principal baseline; selected kernel/platform capabilities are needed for production readiness.
A5: What "available" means | B5: A capability has a governed contract, owner, runtime pattern, security controls, NFRs, traceability, failure handling and operational runbook. It does not necessarily require a new standalone platform before R4.
A6: Scope caveat | B6: Apolo and SIWEB rows in the consolidated workbook are not fully MoSCoW-scored. They are treated as R4 scope where the workbook includes them as user stories; formal release baseline should still confirm them.
A9: Capability mapping counts | E9: R4 source summary
A10: Domain capability rows | B10: =COUNTA('Domain Capability Mapping'!$A$5:$A$500) -> 121 | E10: R4 user story rows | F10: 78
A11: Supporting kernel rows | B11: =COUNTA('Supporting Kernel'!$A$5:$A$200) -> 21 | E11: Tracks in inventory | F11: Smart Vista: 21, CAT: 12, SIWEB: 5, Apolo: 22, APP: 18
A12: Domain P0 rows | B12: =COUNTIF('Domain Capability Mapping'!$D:$D,"P0*") -> 102 | E12: MoSCoW distribution | F12: Must: 30, Should: 12, Wont: 1, Not classified: 35
A13: Domain P1 rows | B13: =COUNTIF('Domain Capability Mapping'!$D:$D,"P1*") -> 18 | E13: Solution / integration distribution | F13: Solución: 26, Solución e Integración: 16, Integración: 1, Not classified: 35
A14: Domain P2 rows | B14: =COUNTIF('Domain Capability Mapping'!$D:$D,"P2*") -> 1 | E14: Integration inventory rows | F14: 15
A15: Very High confidence rows | B15: =COUNTIF('Domain Capability Mapping'!$E:$E,"Very High*") -> 40 | E15: Integration types | F15: Batch: 2, API: 12, Evento: 1
A16: High confidence rows | B16: =COUNTIF('Domain Capability Mapping'!$E:$E,"High*") -> 62 | E16: Integration status | F16: Nueva: 8, Modificar: 7
A17: Medium confidence rows | B17: =COUNTIF('Domain Capability Mapping'!$E:$E,"Medium*") -> 19 | E17: Integration frequency | F17: Diaria/EOD: 5, Tiempo real: 10
A21: Priority / confidence legend
A22: P0 | B22: P0 - Mandatory for R4 go-live / E2E certification
A23: P1 | B23: P1 - Required for controlled R4, but scope/design confirmation needed
A24: P2 | B24: P2 - Evaluate for R4.5 / not a strict R4 blocker
A25: Very High | B25: Very High - directly evidenced by R4 HUs and/or integration inventory
A26: High | B26: High - directly required by R4 behaviour, even if not always explicit as a capability
A27: Medium | B27: Medium - dependent on Should/unprioritized scope, release split or design choice
A28: Low | B28: Low - future-looking or optional relative to strict R4 baseline
A31: Track | B31: HU rows
A32: Smart Vista | B32: 21
A33: CAT | B33: 12
A34: SIWEB | B34: 5
A35: Apolo | B35: 22
A36: APP | B36: 18

Sheet Domain Capability Mapping
A1: R4 Required Interoperability Capabilities - Domain Capability Mapping
A2: Capabilities from the interoperability hierarchy that need to be available or evaluated for R4, derived from R4 user stories and the integration inventory.
A4: Interoperability capability required | B4: R4 context it is needed for | C4: Purpose and benefit from R4 perspective | D4: Priority from R4 perspective | E4: Level of confidence that this capability is required | F4: Capability ID | G4: Hierarchy level | H4: Capability family | I4: Kernel or Domain | J4: Source HU examples | K4: Integration examples / source evidence | L4: Hierarchy description | M4: BanCoppel solutions / candidates in hierarchy | N4: Key availability or design gap to verify for R4
A5: 8.1 Service Orchestrator | B5: Cross-channel R4 journeys spanning Apolo, SmartVista, APP, CAT/IVR/ICCAT, SIWEB, OnBase, payment channels, accounting and legacy systems. Primary focus: Apolo formalization, SmartVista servicing, CAT/APP/SIWEB operations. | C5: Coordinates multi-step business services so channels call stable business operations instead of coupling directly to backend steps. | D5: P0 - Mandatory for R4 go-live / E2E certification | E5: Very High - directly evidenced by R4 HUs and/or integration inventory | F5: 8.1 | G5: L1 | H5: 8.0 Service Orchestration | I5: Domain Capability | J5: Multiple HUs across Apolo, SmartVista, APP, CAT and SIWEB | K5: ISV01-07; ICAT01-07; IAPP01 plus implied Apolo/payment/accounting interfaces | L5: The engine that decomposes a complex service into an ordered or parallel set of fine-grained service invocations and manages their execution, results and exceptions. | M5: MuleSoft orchestration; Software AG WebMethods BPM/BRM; Apigee invocation management; Modyo Connect state-machine style flow orchestration; DataDog diagnostics. | N5: Confirm one approved orchestration owner and pattern per E2E journey.
A6: 8.1.1 Service Composition & Sequencing | B6: Apolo onboarding for TDC 4900: rate/CAT offer, PLD/PEP/name matching, vulnerable-person declaration, OTP/SMS, electronic signature, credit creation in SmartVista, OnBase expediente and welcome kit. Also deferred-purchase and card-status journeys. | C6: Sequences credit creation, document storage, notifications and downstream updates; reduces partial-completion risk. | D6: P0 - Mandatory for R4 go-live / E2E certification | E6: High - directly required by R4 behaviour, even if not always explicit as a capability | F6: 8.1.1 | G6: L2 | H6: 8.0 Service Orchestration | I6: Domain Capability | J6: HDU-TDC-R4-01,03-08,10,13,14,16-21,23-27,34 | K6: Apolo->SmartVista, Apolo->OnBase, signature, OTP/SMS, email and PLD/name-matching integrations implied by HUs; not fully present in integration inventory | L6: Definition and execution of composite services from fine-grained steps, with declarative or visual configuration. | M6: MuleSoft orchestration; Software AG WebMethods BPM/BRM; Apigee invocation management; Modyo Connect state-machine style flow orchestration; DataDog diagnostics. | N6: Document the sequence, compensation points and error states.
A7: 8.1.2 Parallel & Conditional Execution Control | B7: Apolo onboarding for TDC 4900: rate/CAT offer, PLD/PEP/name matching, vulnerable-person declaration, OTP/SMS, electronic signature, credit creation in SmartVista, OnBase expediente and welcome kit. CAT/IVR/ICCAT servicing for product 4900: customer lookup, authentication, balance/movement inquiry, block/unblock, cancellation and cross-channel status update. | C7: Allows conditional flows for KO decisions, PEP/name-match outcomes, authentication failures, block/unblock and cancellation outcomes. | D7: P0 - Mandatory for R4 go-live / E2E certification | E7: High - directly required by R4 behaviour, even if not always explicit as a capability | F7: 8.1.2 | G7: L2 | H7: 8.0 Service Orchestration | I7: Domain Capability | J7: HDU-TDC-R4-01,03-08,10,13,14,16-21,23-27,34; HDU-CAT-R4-01 to 12 | K7: Apolo->SmartVista, Apolo->OnBase, signature, OTP/SMS, email and PLD/name-matching integrations implied by HUs; not fully present in integration inventory; ICAT01-ICAT07 | L7: Concurrent and rule-conditioned execution of orchestration steps with aggregation of results. | M7: MuleSoft orchestration; Software AG WebMethods BPM/BRM; Apigee invocation management; Modyo Connect state-machine style flow orchestration; DataDog diagnostics. | N7: Define decision ownership and timeout/fallback rules.
A8: 8.1.3 Invocation Management | B8: CAT/IVR/ICCAT servicing for product 4900: customer lookup, authentication, balance/movement inquiry, block/unblock, cancellation and cross-channel status update. APP BanCoppel coexistence of physical/digital cards and legacy/SmartVista products: home, detail, movements, on/off, activation and consolidated credit view. MCI/MSI and deferred-purchase operations: campaigns, eligibility/calculation, plan creation, early payment, liquidation, cancellation and accounting effects. | C8: Controls backend invocations, retries and endpoint selection to SmartVista/SIWEB without exposing backend complexity to channels. | D8: P0 - Mandatory for R4 go-live / E2E certification | E8: Very High - directly evidenced by R4 HUs and/or integration inventory | F8: 8.1.3 | G8: L2 | H8: 8.0 Service Orchestration | I8: Domain Capability | J8: HDU-CAT-R4-01 to 12; SMART-4219, SMART-3964, SMART-4226, SMART-3963, SMART-3966, PTCF-6144, SMART-3962; HDU-SMART-R4-16 to 21; HDU-SIWEB-R4-01 to 04 | K8: ICAT01-ICAT07; IAPP01; ISV06, ISV07 | L8: Management of synchronous and asynchronous invocation styles, timeouts, retries and partial-failure handling. | M8: MuleSoft orchestration; Software AG WebMethods BPM/BRM; Apigee invocation management; Modyo Connect state-machine style flow orchestration; DataDog diagnostics. | N8: Confirm API owner, endpoint inventory and retry policy.
A9: 8.1.4 Orchestration Monitoring & Diagnostics | B9: R4 production control: rollout, rollback, folio/correlation, runtime administration, support, monitoring and repair of customer-impacting journeys. | C9: Provides diagnostics on orchestrated journeys so incidents can be traced from customer channel through SmartVista/OnBase/SIWEB. | D9: P0 - Mandatory for R4 go-live / E2E certification | E9: High - directly required by R4 behaviour, even if not always explicit as a capability | F9: 8.1.4 | G9: L2 | H9: 8.0 Service Orchestration | I9: Domain Capability | J9: Multiple HUs requiring traceability, rollback, runtime parameter control and operational support | K9: Operational identifiers and dashboards not present as explicit interface records | L9: Instrumentation of orchestration execution with technical and business event emission. | M9: MuleSoft orchestration; Software AG WebMethods BPM/BRM; Apigee invocation management; Modyo Connect state-machine style flow orchestration; DataDog diagnostics. | N9: Ensure monitoring is at business-journey level, not only infrastructure.
A10: 8.2 Integration & Mediation Framework | B10: Cross-channel R4 journeys spanning Apolo, SmartVista, APP, CAT/IVR/ICCAT, SIWEB, OnBase, payment channels, accounting and legacy systems. Includes batch/file, API, event and legacy mediation. | C10: Normalizes technical protocols and payloads across Apolo, SmartVista, APP, CAT, SIWEB, Informix and file-transfer components. | D10: P0 - Mandatory for R4 go-live / E2E certification | E10: Very High - directly evidenced by R4 HUs and/or integration inventory | F10: 8.2 | G10: L1 | H10: 8.0 Service Orchestration | I10: Domain Capability | J10: Multiple HUs across Apolo, SmartVista, APP, CAT and SIWEB | K10: ISV01-07; ICAT01-07; IAPP01 plus implied Apolo/payment/accounting interfaces | L10: Transformation, mapping and protocol-bridging services that reconcile differing data contracts, formats and communication mechanisms between participating platforms. | M10: MuleSoft; WebMethods; Apigee; Modyo Connect; BIAN services; Interfaces Temporales/Strangler Fig; Transact OFS/IRIS APIs. | N10: Complete interface inventory and canonical mapping before design freeze.
A11: 8.2.1 Message Transformation & Mapping | B11: Canonical customer, account, credit-line, physical/digital card, transaction, commission, lot and deferred-plan data across R4 channels and systems. APP/CAT/SIWEB need consistent card, balance, movement and status structures. | C11: Maps SmartVista, legacy and channel payloads to canonical fields; reduces channel-specific transformations. | D11: P0 - Mandatory for R4 go-live / E2E certification | E11: Very High - directly evidenced by R4 HUs and/or integration inventory | F11: 8.2.1 | G11: L2 | H11: 8.0 Service Orchestration | I11: Domain Capability | J11: SMART-4219, SMART-3964, SMART-4226, SMART-3963, SMART-3966, PTCF-6144, SMART-3962; HDU-CAT-R4-01 to 12; HDU-SIWEB-R4-01 to 05; HDU-SMART-R4-08,17,19-21 | K11: IAPP01; ICAT01-ICAT07; ISV06, ISV07 | L11: Declarative mapping between canonical and native message structures, including enrichment and defaulting. | M11: MuleSoft transformation and protocol bridging; Apigee API contracts; BIAN canonical service design; DataStage for data transformation; OpenAPI/Swagger API documentation. | N11: Define canonical fields and status/value mappings.
A12: 8.2.2 Protocol Bridging | B12: SmartVista card manufacturing and branch supply: maquila layout certification, re-order calculation, secure files, PGP/Connect:Direct transfer, lot tracking and SIWEB lot receipt/cancellation. and CAT/IVR/ICCAT/SIWEB integration. | C12: Bridges REST/API, batch, PGP file exchange, event and legacy protocols required by R4. | D12: P0 - Mandatory for R4 go-live / E2E certification | E12: Very High - directly evidenced by R4 HUs and/or integration inventory | F12: 8.2.2 | G12: L2 | H12: 8.0 Service Orchestration | I12: Domain Capability | J12: HDU-SMART-R4-01 to 08; HDU-CAT-R4-01 to 12; HDU-SIWEB-R4-01 to 05; HDU-SMART-R4-08,17,19-21 | K12: ISV01, ISV02, ISV03; ICAT01-ICAT07; ISV06, ISV07 | L12: Adaptation between communication mechanisms (REST, gRPC, messaging, file, legacy transaction protocols). | M12: MuleSoft transformation and protocol bridging; Apigee API contracts; BIAN canonical service design; DataStage for data transformation; OpenAPI/Swagger API documentation. | N12: Confirm runtime support for batch, event and real-time APIs.
A13: 8.2.3 Dynamic Data Mapping & Schema Governance | B13: Canonical customer, account, credit-line, physical/digital card, transaction, commission, lot and deferred-plan data across R4 channels and systems. Commission catalogue harmonization across SmartVista, APP, SIWEB and EDC for product 4900. | C13: Governed schemas prevent each channel from interpreting commission names, card status, transaction state or deferred-plan data differently. | D13: P0 - Mandatory for R4 go-live / E2E certification | E13: High - directly required by R4 behaviour, even if not always explicit as a capability | F13: 8.2.3 | G13: L2 | H13: 8.0 Service Orchestration | I13: Domain Capability | J13: HDU-SMART-R4-09,10; SMART-4219, SMART-3964, SMART-4226, SMART-3963, SMART-3966, PTCF-6144, SMART-3962; HDU-CAT-R4-01 to 12; HDU-SMART-R4-16 to 21; HDU-SIWEB-R4-01 to 04 | K13: ISV04, ISV05; IAPP01; ICAT01-ICAT07; ISV06, ISV07 | L13: Configurable, versioned mapping definitions and schema contracts maintained outside application code. | M13: MuleSoft transformation and protocol bridging; Apigee API contracts; BIAN canonical service design; DataStage for data transformation; OpenAPI/Swagger API documentation. | N13: Create schema ownership and compatibility rules.
A14: 8.3 Context Management | B14: APP BanCoppel coexistence of physical/digital cards and legacy/SmartVista products: home, detail, movements, on/off, activation and consolidated credit view. CAT/IVR/ICCAT servicing for product 4900: customer lookup, authentication, balance/movement inquiry, block/unblock, cancellation and cross-channel status update. Positive-balance controls across SmartVista, APP, SIWEB, SPEI/payment channels and branch cash operations. | C14: Carries product, channel, customer, card, rollout and authorization context across service calls. | D14: P0 - Mandatory for R4 go-live / E2E certification | E14: High - directly required by R4 behaviour, even if not always explicit as a capability | F14: 8.3 | G14: L1 | H14: 8.0 Service Orchestration | I14: Domain Capability | J14: SMART-4219, SMART-3964, SMART-4226, SMART-3963, SMART-3966, PTCF-6144, SMART-3962; HDU-CAT-R4-01 to 12; HDU-SMART-R4-12,13,15; HDU-SIWEB-R4-05; SMART-4183/backlog; APP other-amount story | K14: IAPP01; ICAT01-ICAT07; Payment/APP/SIWEB/SPEI interfaces identified in HUs; not fully present in integration inventory | L14: Capture, propagation and consistent availability of execution context - identity, channel, entity, locale, correlation, entitlements - across every hop of a composed service. | M14: Golden Record / Party-CIF; Transact Product Catalog and AA Framework; BRM; Apigee/MuleSoft context propagation; not a separate registry product in sources. | N14: Define required request context attributes and source of truth.
A15: 8.3.1 Request Context Propagation | B15: Cross-channel R4 journeys spanning Apolo, SmartVista, APP, CAT/IVR/ICCAT, SIWEB, OnBase, payment channels, accounting and legacy systems. | C15: Propagates customer, card, product 4900, channel, folio and correlation context so downstream systems can act consistently. | D15: P0 - Mandatory for R4 go-live / E2E certification | E15: High - directly required by R4 behaviour, even if not always explicit as a capability | F15: 8.3.1 | G15: L2 | H15: 8.0 Service Orchestration | I15: Domain Capability | J15: Multiple HUs across Apolo, SmartVista, APP, CAT and SIWEB | K15: ISV01-07; ICAT01-07; IAPP01 plus implied Apolo/payment/accounting interfaces | L15: Standardised transmission of caller, channel and correlation context through all orchestration hops. | M15: Golden Record / Party-CIF; Transact Product Catalog and AA Framework; BRM; Apigee/MuleSoft context propagation; not a separate registry product in sources. | N15: Make correlation and business context mandatory in API headers/events.
... A125: 10.6.2 Signing & Verification Services | B125: Apolo onboarding for TDC 4900: rate/CAT offer, PLD/PEP/name matching, vulnerable-person declaration, OTP/SMS, electronic signature, credit creation in SmartVista, OnBase expediente and welcome kit. electronic signature and verification. | C125: Captures/verifies signature and links the signed version to the stored version and welcome-kit delivery. | D125: P0 - Mandatory for R4 go-live / E2E certification | E125: Very High - directly evidenced by R4 HUs and/or integration inventory | F125: 10.6.2 | G125: L2 | H125: 10.0 Common Business Services (Cross-Domain Coexistence Services) | I125: Domain Capability | J125: HDU-TDC-R4-17,18,20 | K125: Apolo->SmartVista, Apolo->OnBase, signature, OTP/SMS, email and PLD/name-matching integrations implied by HUs; not fully present in integration inventory | L125: HSM-backed signing and verification of business instructions and documents as a shared service. | M125: Incode biometric verification and NOM-151 signing; Apolo onboarding approvals; Azure AD/OAuth for access verification; branch/Teller approval flows. | N125: Define signature status, retry and cancellation handling.

Sheet Supporting Kernel
A1: R4 Supporting Kernel / Platform Capabilities
A2: Kernel capabilities needed to make the domain capabilities production-ready for R4. These complement the domain capability baseline.
A4: Interoperability capability required | B4: R4 context it is needed for | C4: Purpose and benefit from R4 perspective | D4: Priority from R4 perspective | E4: Level of confidence that this capability is required | F4: Capability ID | G4: Hierarchy level | H4: Capability family | I4: Kernel or Domain | J4: Source HU examples | K4: Integration examples / source evidence | L4: Hierarchy description | M4: BanCoppel solutions / candidates in hierarchy | N4: Key availability or design gap to verify for R4
A5: 5.1 API Gateway & Runtime Mediation | B5: APP BanCoppel coexistence of physical/digital cards and legacy/SmartVista products: home, detail, movements, on/off, activation and consolidated credit view. CAT/IVR/ICCAT servicing for product 4900: customer lookup, authentication, balance/movement inquiry, block/unblock, cancellation and cross-channel status update. SIWEB branch operations for payments, deferred-purchase settlement/cancellation, lot receipt and positive-balance validation. Apolo onboarding for TDC 4900: rate/CAT offer, PLD/PEP/name matching, vulnerable-person declaration, OTP/SMS, electronic signature, credit creation in SmartVista, OnBase expediente and welcome kit. | C5: Runtime API gateway mediation protects channels and backends with one governed access pattern. | D5: P0 - Mandatory for R4 go-live / E2E certification | E5: Very High - directly evidenced by R4 HUs and/or integration inventory | F5: 5.1 | G5: L1 | H5: 5.0 API Management | I5: Kernel & Platform | J5: Multiple HUs across Apolo, SmartVista, APP, CAT and SIWEB | K5: ISV01-07; ICAT01-07; IAPP01 plus implied Apolo/payment/accounting interfaces | L5: Runtime plane that terminates, validates, mediates and routes API traffic between consumers and providers, applying policy at the point of invocation rather than inside application code. | M5: Apigee API Gateway/API Management; MuleSoft integration/orchestration; WebMethods BPM/BRM; BIAN-aligned APIs; Transact OFS/IRIS REST APIs. | N5: Expose SmartVista/domain facade instead of raw backend APIs.
A6: 5.1.1 Routing | B6: APP BanCoppel coexistence of physical/digital cards and legacy/SmartVista products: home, detail, movements, on/off, activation and consolidated credit view. CAT/IVR/ICCAT servicing for product 4900: customer lookup, authentication, balance/movement inquiry, block/unblock, cancellation and cross-channel status update. product-location routing. | C6: Routes requests to SmartVista or legacy/backing service based on product, instrument and operation. | D6: P0 - Mandatory for R4 go-live / E2E certification | E6: Very High - directly evidenced by R4 HUs and/or integration inventory | F6: 5.1.1 | G6: L2 | H6: 5.0 API Management | I6: Kernel & Platform | J6: SMART-4219, SMART-3964, SMART-4226, SMART-3963, SMART-3966, PTCF-6144, SMART-3962; HDU-CAT-R4-01 to 12 | K6: IAPP01; ICAT01-ICAT07 | L6: Resolution of a logical API contract to one or more physical service endpoints, including host, version and environment-based routing. | M6: Apigee API Gateway/API Management; MuleSoft integration/orchestration; WebMethods BPM/BRM; BIAN-aligned APIs; Transact OFS/IRIS REST APIs. | N6: Create explicit routing rules and ownership.
A7: 5.1.2 Mediation & Message Transformation | B7: Canonical customer, account, credit-line, physical/digital card, transaction, commission, lot and deferred-plan data across R4 channels and systems. | C7: Transforms messages so channels are insulated from backend-specific formats. | D7: P0 - Mandatory for R4 go-live / E2E certification | E7: Very High - directly evidenced by R4 HUs and/or integration inventory | F7: 5.1.2 | G7: L2 | H7: 5.0 API Management | I7: Kernel & Platform | J7: Multiple HUs across Apolo, APP, CAT, SmartVista and SIWEB | K7: IAPP01, ICAT01-04/07, ISV03-07 plus implied canonical data feeds | L7: Protocol and payload adaptation at the edge (REST, SOAP, gRPC, legacy protocols), including header manipulation and canonical-to-native mapping. | M7: Apigee API Gateway/API Management; MuleSoft integration/orchestration; WebMethods BPM/BRM; BIAN-aligned APIs; Transact OFS/IRIS REST APIs. | N7: Align with 6.2.1 and canonical model.
A8: 5.1.5 Error Handling & Fault Normalisation | B8: CAT/IVR/ICCAT servicing for product 4900: customer lookup, authentication, balance/movement inquiry, block/unblock, cancellation and cross-channel status update. APP BanCoppel coexistence of physical/digital cards and legacy/SmartVista products: home, detail, movements, on/off, activation and consolidated credit view. SIWEB branch operations for payments, deferred-purchase settlement/cancellation, lot receipt and positive-balance validation. | C8: Normalizes errors and business rejection messages, especially positive-balance, authentication and card status outcomes. | D8: P0 - Mandatory for R4 go-live / E2E certification | E8: Very High - directly evidenced by R4 HUs and/or integration inventory | F8: 5.1.5 | G8: L2 | H8: 5.0 API Management | I8: Kernel & Platform | J8: HDU-SMART-R4-12,13,15; HDU-SIWEB-R4-05; SMART-4183/backlog; APP other-amount story; HDU-CAT-R4-01 to 12; SMART-4219, SMART-3964, SMART-4226, SMART-3963, SMART-3966, PTCF-6144, SMART-3962 | K8: ICAT01-ICAT07; IAPP01; Payment/APP/SIWEB/SPEI interfaces identified in HUs; not fully present in integration inventory | L8: Standardised error taxonomy, fault mapping and response codes across heterogeneous backends. | M8: Apigee API Gateway/API Management; MuleSoft integration/orchestration; WebMethods BPM/BRM; BIAN-aligned APIs; Transact OFS/IRIS REST APIs. | N8: Create common error taxonomy.
A9: 5.2.1 API Design & Contract Standards | B9: Cross-channel R4 journeys spanning Apolo, SmartVista, APP, CAT/IVR/ICCAT, SIWEB, OnBase, payment channels, accounting and legacy systems. | C9: Defines API contracts before build/test, avoiding undocumented reuse or direct backend coupling. | D9: P0 - Mandatory for R4 go-live / E2E certification | E9: Very High - directly evidenced by R4 HUs and/or integration inventory | F9: 5.2.1 | G9: L2 | H9: 5.0 API Management | I9: Kernel & Platform | J9: Multiple HUs across Apolo, SmartVista, APP, CAT and SIWEB | K9: ISV01-07; ICAT01-07; IAPP01 plus implied Apolo/payment/accounting interfaces | L9: Definition and enforcement of interface standards, canonical or BIAN-aligned naming, and design review gates before publication. | M9: BIAN API standards; Apigee API lifecycle/governance; OpenAPI/Swagger-style API documentation for OfiWeb/Canales; API change controlled by architecture governance. | N9: Complete missing APIs from Apolo/payment/accounting/status flows.
A10: 5.2.2 API Versioning | B10: R4 production control: rollout, rollback, folio/correlation, runtime administration, support, monitoring and repair of customer-impacting journeys. | C10: Versioning allows R4, R4.5 and R5 channel/back-end changes to coexist safely. | D10: P0 - Mandatory for R4 go-live / E2E certification | E10: High - directly required by R4 behaviour, even if not always explicit as a capability | F10: 5.2.2 | G10: L2 | H10: 5.0 API Management | I10: Kernel & Platform | J10: Multiple HUs requiring traceability, rollback, runtime parameter control and operational support | K10: Operational identifiers and dashboards not present as explicit interface records | L10: Concurrent support of multiple contract versions with defined compatibility and deprecation rules. | M10: BIAN API standards; Apigee API lifecycle/governance; OpenAPI/Swagger-style API documentation for OfiWeb/Canales; API change controlled by architecture governance. | N10: Define compatibility and deprecation rules.
A11: 5.3.2 API Monitoring, Analytics & Monetisation | B11: R4 production control: rollout, rollback, folio/correlation, runtime administration, support, monitoring and repair of customer-impacting journeys. | C11: Monitors API usage, errors and latency by R4 journey/channel. | D11: P0 - Mandatory for R4 go-live / E2E certification | E11: High - directly required by R4 behaviour, even if not always explicit as a capability | F11: 5.3.2 | G11: L2 | H11: 5.0 API Management | I11: Kernel & Platform | J11: Multiple HUs requiring traceability, rollback, runtime parameter control and operational support | K11: ISV01-07; ICAT01-07; IAPP01 plus implied Apolo/payment/accounting interfaces | L11: Consumption metrics, latency and error analytics per API and per consumer, with the metering basis for internal chargeback or partner monetisation. | M11: Apigee platform administration and policies; DataDog/API monitoring; DevSecOps pipelines; GCP-hosted Apigee with AWS/on-prem providers. | N11: Current integration inventory lacks response times and volumes.
A12: 4.2.2 Outbound File Gateway | B12: SmartVista card manufacturing and branch supply: maquila layout certification, re-order calculation, secure files, PGP/Connect:Direct transfer, lot tracking and SIWEB lot receipt/cancellation. | C12: Provides controlled outbound file movement for PGP/Connect:Direct maquila files. | D12: P0 - Mandatory for R4 go-live / E2E certification | E12: Very High - directly evidenced by R4 HUs and/or integration inventory | F12: 4.2.2 | G12: L2 | H12: 4.0 Gateway Services | I12: Kernel & Platform | J12: HDU-SMART-R4-01 to 08 | K12: ISV01, ISV02, ISV03 | L12: Managed generation, encryption, scheduling and transmission of outbound files, superseding unmanaged SFTP arrangements. | M12: DataStage ETL; batch/COB interfaces; OnBase document flows; PISA/Informix legacy file/data interfaces. No dedicated MFT product is explicitly evidenced. | N12: Define file acknowledgements, checksums, reprocessing and key rotation.
A13: 4.4 Perimeter Zoning & Connectivity | B13: Cross-channel R4 journeys spanning Apolo, SmartVista, APP, CAT/IVR/ICCAT, SIWEB, OnBase, payment channels, accounting and legacy systems. hybrid cloud/on-premise integration. | C13: Provides zoning and connectivity controls across AWS/GCP/on-premise/legacy/provider endpoints. | D13: P0 - Mandatory for R4 go-live / E2E certification | E13: High - directly required by R4 behaviour, even if not always explicit as a capability | F13: 4.4 | G13: L1 | H13: 4.0 Gateway Services | I13: Kernel & Platform | J13: Multiple HUs across Apolo, SmartVista, APP, CAT and SIWEB | K13: ISV01-07; ICAT01-07; IAPP01 plus implied Apolo/payment/accounting interfaces | L13: Network segmentation, DMZ exposure model, transport security termination and connectivity management underpinning all gateway modalities. | M13: Imperva WAF / Cloud Armor; AWS Shield; Zscaler TLS termination; VPN/Direct Connect; Tetration rules; AWS/GCP/on-prem network zoning. | N13: Validate UAT/pre-prod/prod connectivity and firewall readiness.
A14: 1.1 Identity & Access Management | B14: Apolo onboarding for TDC 4900: rate/CAT offer, PLD/PEP/name matching, vulnerable-person declaration, OTP/SMS, electronic signature, credit creation in SmartVista, OnBase expediente and welcome kit. APP BanCoppel coexistence of physical/digital cards and legacy/SmartVista products: home, detail, movements, on/off, activation and consolidated credit view. CAT/IVR/ICCAT servicing for product 4900: customer lookup, authentication, balance/movement inquiry, block/unblock, cancellation and cross-channel status update. SIWEB branch operations for payments, deferred-purchase settlement/cancellation, lot receipt and positive-balance validation. | C14: Authenticates and authorizes customers, agents, apps and system integrations. | D14: P0 - Mandatory for R4 go-live / E2E certification | E14: Very High - directly evidenced by R4 HUs and/or integration inventory | F14: 1.1 | G14: L1 | H14: 1.0 Security | I14: Kernel & Platform | J14: Multiple HUs across Apolo, SmartVista, APP, CAT and SIWEB | K14: ISV01-07; ICAT01-07; IAPP01 plus implied Apolo/payment/accounting interfaces | L14: Authentication, authorisation, token and session services for customers, employees, partners and machine identities consuming the interoperability layer. | M14: OAuth 2.0 via Apigee; Azure AD / Microsoft Entra ID; Token Party Identity; Incode identity/KYC; HashiCorp Vault for credential support. | N14: Confirm OAuth/mTLS/RBAC patterns per channel and API.
A15: 1.2 Crypto Services | B15: SmartVista card manufacturing and branch supply: maquila layout certification, re-order calculation, secure files, PGP/Connect:Direct transfer, lot tracking and SIWEB lot receipt/cancellation. Apolo onboarding for TDC 4900: rate/CAT offer, PLD/PEP/name matching, vulnerable-person declaration, OTP/SMS, electronic signature, credit creation in SmartVista, OnBase expediente and welcome kit. card and document data. | C15: Protects sensitive data with encryption/signature operations across APIs, files and stores. | D15: P0 - Mandatory for R4 go-live / E2E certification | E15: Very High - directly evidenced by R4 HUs and/or integration inventory | F15: 1.2 | G15: L1 | H15: 1.0 Security | I15: Kernel & Platform | J15: HDU-SMART-R4-01 to 08; HDU-TDC-R4-01,03-08,10,13,14,16-21,23-27,34; SMART-4219, SMART-3964, SMART-4226, SMART-3963, SMART-3966, PTCF-6144, SMART-3962 | K15: ISV01, ISV02, ISV03; Apolo->SmartVista, Apolo->OnBase, signature, OTP/SMS, email and PLD/name-matching integrations implied by HUs; not fully present in integration inventory; IAPP01 | L15: Shared cryptographic operations - signing, encryption, end-to-end payload protection - delivered as callable services backed by hardware security modules and managed key stores. | M15: AES-256 encryption; TLS/SSL; HSM key management; Oracle TDE; Istio mTLS; Incode/NOM-151 signature for onboarding contracts. | N15: Validate HSM/PGP/PAN masking controls.
... A25: 13.5 Infrastructure Resilience | B25: R4 production control: rollout, rollback, folio/correlation, runtime administration, support, monitoring and repair of customer-impacting journeys. | C25: Provides resilience, failover and recovery capabilities for R4 production journeys. | D25: P0 - Mandatory for R4 go-live / E2E certification | E25: High - directly required by R4 behaviour, even if not always explicit as a capability | F25: 13.5 | G25: L1 | H25: 13.0 Infrastructure (Tech Stack) | I25: Kernel & Platform | J25: Multiple HUs requiring traceability, rollback, runtime parameter control and operational support | K25: ISV01-07; ICAT01-07; IAPP01 plus implied Apolo/payment/accounting interfaces | L25: Engineering and validation of the layer's ability to withstand and recover from component failure, including deliberate failure injection, high availability design and recovery services. | M25: AWS multi-AZ/DR architecture; Producción and DR Producción environments; Oracle Data Guard/R-SYNC for SmartVista; backup/restore and regional DR. | N25: Validate recovery procedures for SmartVista/API/file/payment flows.

Sheet Domain Family View
A1: Domain Family View
A2: L0 domain capability families and their R4 readiness posture.
A4: Domain family | B4: Required R4 posture | C4: Confidence | D4: Why it matters for R4 | E4: Key gap to validate | F4: Detailed capability rows | G4: P0 rows | H4: P1 rows | I4: P2 rows
A5: 6.0 Service Orchestration | B5: P0 | C5: Very High | D5: Business/API orchestration, mediation, context and legacy adapters for Apolo, SmartVista, APP, CAT, SIWEB and file flows. | E5: Confirm orchestrator/facade pattern and owner per journey. | F5: =COUNTIF('Domain Capability Mapping'!$H:$H,A5) -> 0 | G5: =COUNTIFS('Domain Capability Mapping'!$H:$H,A5,'Domain Capability Mapping'!$D:$D,"P0*") -> 0 | H5: =COUNTIFS('Domain Capability Mapping'!$H:$H,A5,'Domain Capability Mapping'!$D:$D,"P1*") -> 0 | I5: =COUNTIFS('Domain Capability Mapping'!$H:$H,A5,'Domain Capability Mapping'!$D:$D,"P2*") -> 0
A6: 7.0 Process Orchestration | B6: P0 | C6: High | D6: Long-running onboarding, maquila, branch and customer service workflows with exception handling. | E6: Consolidate process state and operational work queues. | F6: =COUNTIF('Domain Capability Mapping'!$H:$H,A6) -> 0 | G6: =COUNTIFS('Domain Capability Mapping'!$H:$H,A6,'Domain Capability Mapping'!$D:$D,"P0*") -> 0 | H6: =COUNTIFS('Domain Capability Mapping'!$H:$H,A6,'Domain Capability Mapping'!$D:$D,"P1*") -> 0 | I6: =COUNTIFS('Domain Capability Mapping'!$H:$H,A6,'Domain Capability Mapping'!$D:$D,"P2*") -> 0
A7: 8.0 Distributed Transactions | B7: P0 | C7: Very High | D7: Financial/card/document operations that must not partially complete or duplicate. | E7: Define compensation, idempotency, reversal and reconciliation design. | F7: =COUNTIF('Domain Capability Mapping'!$H:$H,A7) -> 0 | G7: =COUNTIFS('Domain Capability Mapping'!$H:$H,A7,'Domain Capability Mapping'!$D:$D,"P0*") -> 0 | H7: =COUNTIFS('Domain Capability Mapping'!$H:$H,A7,'Domain Capability Mapping'!$D:$D,"P1*") -> 0 | I7: =COUNTIFS('Domain Capability Mapping'!$H:$H,A7,'Domain Capability Mapping'!$D:$D,"P2*") -> 0
A8: 9.0 Event Processing & Reactive Components | B8: P0 scoped / P1 broader | C8: High | D8: Status, customer/card creation, notification, cache-invalidation and accounting events. | E8: Create bounded R4 event catalogue and guaranteed-delivery controls. | F8: =COUNTIF('Domain Capability Mapping'!$H:$H,A8) -> 0 | G8: =COUNTIFS('Domain Capability Mapping'!$H:$H,A8,'Domain Capability Mapping'!$D:$D,"P0*") -> 0 | H8: =COUNTIFS('Domain Capability Mapping'!$H:$H,A8,'Domain Capability Mapping'!$D:$D,"P1*") -> 0 | I8: =COUNTIFS('Domain Capability Mapping'!$H:$H,A8,'Domain Capability Mapping'!$D:$D,"P2*") -> 0
A9: 10.0 Omnichannel & Caching Components | B9: P0 scoped | C9: High | D9: Consistent APP/CAT/SIWEB view of physical/digital and legacy/SmartVista cards. | E9: Decide composed API vs ODS/cache and define consistency rules. | F9: =COUNTIF('Domain Capability Mapping'!$H:$H,A9) -> 0 | G9: =COUNTIFS('Domain Capability Mapping'!$H:$H,A9,'Domain Capability Mapping'!$D:$D,"P0*") -> 0 | H9: =COUNTIFS('Domain Capability Mapping'!$H:$H,A9,'Domain Capability Mapping'!$D:$D,"P1*") -> 0 | I9: =COUNTIFS('Domain Capability Mapping'!$H:$H,A9,'Domain Capability Mapping'!$D:$D,"P2*") -> 0
A10: 11.0 Data Delivery | B10: P0 | C10: Very High | D10: Canonical data, cross-core consolidation, batch/real-time delivery and reporting feeds. | E10: Close source-of-truth, lineage and data-quality decisions. | F10: =COUNTIF('Domain Capability Mapping'!$H:$H,A10) -> 18 | G10: =COUNTIFS('Domain Capability Mapping'!$H:$H,A10,'Domain Capability Mapping'!$D:$D,"P0*") -> 17 | H10: =COUNTIFS('Domain Capability Mapping'!$H:$H,A10,'Domain Capability Mapping'!$D:$D,"P1*") -> 1 | I10: =COUNTIFS('Domain Capability Mapping'!$H:$H,A10,'Domain Capability Mapping'!$D:$D,"P2*") -> 0
A11: 12.0 Operations | B11: P0 | C11: High | D11: Business folios, feature flags, correlation, runtime admin and operational support. | E11: Hierarchy shows gaps in dedicated folio/feature/correlation tooling; define standards. | F11: =COUNTIF('Domain Capability Mapping'!$H:$H,A11) -> 0 | G11: =COUNTIFS('Domain Capability Mapping'!$H:$H,A11,'Domain Capability Mapping'!$D:$D,"P0*") -> 0 | H11: =COUNTIFS('Domain Capability Mapping'!$H:$H,A11,'Domain Capability Mapping'!$D:$D,"P1*") -> 0 | I11: =COUNTIFS('Domain Capability Mapping'!$H:$H,A11,'Domain Capability Mapping'!$D:$D,"P2*") -> 0
A12: 13.0 Common Business Services (Cross-Domain Coexistence Services) | B12: P0 | C12: Very High | D12: Reusable customer, product, limit/risk, accounting, payment, document and trust services. | E12: Expose as stable contracts; avoid channel-specific rule duplication. | F12: =COUNTIF('Domain Capability Mapping'!$H:$H,A12) -> 0 | G12: =COUNTIFS('Domain Capability Mapping'!$H:$H,A12,'Domain Capability Mapping'!$D:$D,"P0*") -> 0 | H12: =COUNTIFS('Domain Capability Mapping'!$H:$H,A12,'Domain Capability Mapping'!$D:$D,"P1*") -> 0 | I12: =COUNTIFS('Domain Capability Mapping'!$H:$H,A12,'Domain Capability Mapping'!$D:$D,"P2*") -> 0

Sheet R4 Context Drivers
A1: R4 Context Drivers
A2: R4 functional areas used to infer required interoperability capabilities.
A4: R4 context / journey | B4: Source HU examples | C4: Primary systems / interfaces | D4: Why it drives interoperability | E4: Primary domain capability families
A5: Apolo onboarding / compliance / contracting | B5: HDU-TDC-R4-01,03-08,10,13,14,16-21,23-27,34 | C5: Apolo, SmartVista, OnBase, signature, SMS/OTP, email, PLD/name matching | D5: Multi-step journey with legal evidence, third-party validations and credit creation. | E5: 6, 7, 8, 9, 11, 12, 13
A6: SmartVista card manufacturing and supply | B6: HDU-SMART-R4-01 to 08 | C6: SmartVista, AWS, OLTP-Informix, Connect:Direct, SIWEB, maquiladores | D6: Batch/file and branch-supply process with secure files, lots and duplicate/retry risk. | E6: 6, 7, 8, 11, 12
A7: Commission catalogue consistency | B7: HDU-SMART-R4-09,10 | C7: SmartVista -> APP/SIWEB/EDC | D7: Regulatory names and pricing need one source and channel consistency. | E7: 6, 7, 11, 12, 13
A8: Authorization and fraud rules | B8: HDU-SMART-R4-11 | C8: SmartVista/BPC authorizer | D8: Authorization/fraud decisions must be consistent, auditable and channel-safe. | E8: 7, 8, 11, 13
A9: Positive-balance controls | B9: HDU-SMART-R4-12,13,15; HDU-SIWEB-R4-05; SMART-4183/backlog; APP other-amount story | C9: SmartVista, APP, SIWEB, SPEI/payment channels | D9: Cross-channel payments must be validated/rejected consistently and reconciled. | E9: 6, 8, 10, 11, 12, 13
A10: MCI/MSI deferred purchases and fixed payments | B10: HDU-SMART-R4-16 to 21; HDU-SIWEB-R4-01 to 04 | C10: SmartVista, SIWEB, APP, accounting/ledger | D10: Financial lifecycle requires pricing, plan creation, early payment, liquidation, cancellation and accounting. | E10: 6, 7, 8, 9, 11, 12, 13
A11: CAT/IVR/ICCAT servicing | B11: HDU-CAT-R4-01 to 12 | C11: IVR, ICCAT, SmartVista, Call Center, APP/SIWEB status consumers | D11: Real-time lookup, authentication, block/unblock/cancel and status propagation. | E11: 6, 7, 8, 9, 10, 11, 12, 13
A12: APP physical/digital coexistence | B12: SMART-4219, SMART-3964, SMART-4226, SMART-3963, SMART-3966, PTCF-6144, SMART-3962 | C12: APP, SmartVista, legacy card/product sources | D12: Home/detail/movements/on-off need consistent product-location and instrument model. | E12: 6, 9, 10, 11, 12, 13
A13: SIWEB branch operations | B13: HDU-SIWEB-R4-01 to 05; HDU-SMART-R4-08,17,19-21 | C13: SIWEB, SmartVista, accounting, branch/cash operations | D13: Branch operations must use same limits, deferred-plan rules and accounting outcomes. | E13: 6, 7, 8, 11, 12, 13

Sheet Sources & Method
A1: Sources & Method
A2: Files and methodology used to build the R4 capability baseline.
A4: Section | B4: Detail
A5: Source file | B5: /mnt/data/Interoperability_Capability_Hierarchy_BanCoppel_Solutions.xlsx
A6: Source file | B6: /mnt/data/Consolidacion y priorizacion_HUs_R4_v2.xlsx
A7: Source file | B7: /mnt/data/Inventario de Integraciones_HUs_ R4_v1.0.xlsx
A8: Source hierarchy | B8: Capabilities were selected from PH Vertical Expansion in Interoperability_Capability_Hierarchy_BanCoppel_Solutions.xlsx.
A9: R4 basis | B9: R4 user stories and integration records were used to infer capability need. Direct story/integration evidence drives Very High or High confidence.
A10: Prioritization approach | B10: P0 = mandatory for R4 go-live / E2E certification; P1 = needed for controlled R4 or design confirmation; P2 = evaluate/defer, not a strict R4 blocker.
A11: Important caveat | B11: Apolo and SIWEB rows are included where present in the R4 workbook, even if MoSCoW was blank. Formal R4 baseline should confirm their commitment.
A12: Excluded / not a current blocker | B12: Capabilities such as currency conversion, knowledge graph, full event mesh, complex event processing and developer marketplace are not treated as R4 blockers unless a specific design later requires them.
